Workbook

Sheet SEED
AD1: SEQUENCE | AM1: PARENT
B2: LEVEL 1 | D2: LEVEL 2 | F2: LEVEL 3 | H2: LEVEL 4 | J2: LEVEL 5 (Currency) | L2: LEVEL 6 (Data Linkage) | V2: ALL LEVEL | W2: L1 | X2: L2 | Y2: L3 | Z2: L4 | AA2: L5 | AB2: L6 | AD2: L1 | AE2: L2 | AF2: L3 | AG2: L4 | AH2: L5 | AI2: L6 | AK2: PERUBAHAN | AM2: L1 | AN2: L2 | AO2: L3 | AP2: L4 | AQ2: L5 | AS2: Conclution
B3: a-bcdd.ee.ff | D3: a-bcdd.ee.ff | F3: a-bcdd.ee.ff | H3: a-bcdd.ee.ff | J3: a-bcdd.ee.ff | L3: a-bcdd.ee.ff | O3: L1 | P3: L2 | Q3: L3 | R3: L4 | S3: L5 | T3: L6 | BA3: SYS_PID Prediction | BB3: SQL Syntax | BC3: =IF(EXACT(LEFT($B5, 1), "1"), "TRUE", "FALSE") -> TRUE
B4: COA | C4: Name | D4: COA | E4: Name | F4: COA | G4: Name | H4: COA | I4: Name | J4: COA | K4: Name | L4: COA | M4: Name | V4: 65000000000000 | W4: =$V4 -> 65000000000000 | X4: =$V4 -> 65000000000000 | Y4: =$V4 -> 65000000000000 | Z4: =$V4 -> 65000000000000 | AA4: =$V4 -> 65000000000000 | AB4: =$V4 -> 65000000000000 | AM4: null | AV4: SYS_PID | AW4: PARENT ID | BA4: 65000000000000
B5: 1-0000 | C5: Aset | O5: =IF(EXACT($B5, ""), $O4, $B5) -> 1-0000 | P5: =IF(EXACT($D5, ""), $P4, $D5) | Q5: =IF(EXACT($F5, ""), $Q4, $F5) | R5: =IF(EXACT($H5, ""), $R4, $H5) | S5: =IF(EXACT($J5, ""), $S4, $J5) | T5: =IF(EXACT($L5, ""), $T4, $L5) | V5: =V4+IF(AND(EXACT(B5, ""), EXACT(D5, ""), EXACT(F5, ""), EXACT(H5, ""), EXACT(J5, ""), EXACT(L5, "")), 0, 1) -> 65000000000001 | W5: =IF(EXACT($B5, ""), $W4, $V5) -> 65000000000001 | X5: =IF(EXACT($D5, ""), $X4, $V5) -> 65000000000000 | Y5: =IF(EXACT($F5, ""), $Y4, $V5) -> 65000000000000 | Z5: =IF(EXACT($H5, ""), $Z4, $V5) -> 65000000000000 | AA5: =IF(EXACT($J5, ""), $AA4, $V5) -> 65000000000000 | AB5: =IF(EXACT($L5, ""), $AB4, $V5) -> 65000000000000 | AD5: =AD4 + IF(W5<>W4, 1, 0) -> 1 | AE5: =IF(AD4<>AD5, 1, AE4) + IF(X5<>X4, 1, 0) -> 1 | AF5: =IF(AE4<>AE5, 1, AF4) + IF(Y5<>Y4, 1, 0) -> 1 | AG5: =IF(AF4<>AF5, 1, AG4) + IF(Z5<>Z4, 1, 0) -> 1 | AH5: =IF(AG4<>AG5, 1, AH4) + IF(AA5<>AA4, 1, 0) -> 1 | AI5: =IF(AH4<>AH5, 1, AI4) + IF(AB5<>AB4, 1, 0) -> 1 | AK5: =IF(AA5<>AA4, "L5", IF(Z5<>Z4, "L4", IF(Y5<>Y4, "L3", IF(X5<>X4, "L2", IF(W5<>W4, "L1", "L1" ) ) ) ) ) -> L1 | AM5: null | AN5: =IF(EXACT($AK4, "L1"), $W4, AN4) -> 0 | AO5: =IF(EXACT($AK4, "L1"), $W4, IF(EXACT($AK4, "L2"), $X4, AO4)) -> 0 | AP5: =IF(EXACT($AK4, "L1"), $W4, IF(EXACT($AK4, "L2"), $X4, IF(EXACT($AK4, "L3"), $Y4, AP4))) -> 0 | AQ5: =IF(EXACT($AK4, "L1"), $W4, IF(EXACT($AK4, "L2"), $X4, IF(EXACT($AK4, "L3"), $Y4, IF(EXACT($AK4, "L4"), $Z4, AQ4)))) -> 0 | AS5: =IF(EXACT($AK5, "L1"), AM5, IF(EXACT($AK5, "L2"), AN5, IF(EXACT($AK5, "L3"), AO5, IF(EXACT($AK5, "L4"), AP5, IF(EXACT($AK5, "L5"), AQ5, ""))))) -> null | AU5: =IF(AND(EXACT(B5, ""), EXACT(D5, ""), EXACT(F5, ""), EXACT(H5, ""), EXACT(J5, ""), EXACT(L5, "")), "", CONCATENATE( "PERFORM * FROM ""SchData-OLTP-Accounting"".""Func_TblChartOfAccount_SET""(varSystemLoginSession, null, null, null, varInstitutionBranchID, 62000000000001::bigint,'", IF(EXACT(B5, ""), IF(EXACT(D5, ""), IF(EXACT(F5, ""), IF(EXACT(H5, ""), IF(EXACT(J5, ""), IF(EXACT(L5, ""), "", L5), J5), H5), F5), D5), B5), "', '", IF(EXACT(B5, ""), IF(EXACT(D5, ""), IF(EXACT(F5, ""), IF(EXACT(H5, ""), IF(EXACT(J5, ""), IF(EXACT(L5, ""), "", M5), K5), I5), G5), E5), C5), "', ", IF(EXACT(J5, ""), "62000000000001::bigint", IF((RIGHT(J5, 2)*1 = 1), "62000000000001::bigint", IF((RIGHT(J5, 2)*1 = 2), "62000000000002::bigint", "null"))), ", '2016-01-01 00:00:00'::timestamp, null::timestamp, ", AW5, "::bigint, 66000000000001::bigint);")) -> PERFORM * FROM "SchData-OLTP-Accounting"."Func_TblChartOfAccount_SET"(varSystemLoginSession, null, null, null, varInstitutionBranchID, 62000000000001::bigint,'1-0000', 'Aset', 62000000000001::bigint, '2016-01-01 00:00:00'::timestamp, null::timestamp, null::bigint, 66000000000001::bigint); | AV5: =IF(AND(EXACT($B5, ""), EXACT($D5, ""), EXACT($F5, ""), EXACT($H5, ""), EXACT($J5, ""), EXACT($L5, "")), "", V5) -> 65000000000001 | AW5: =AS5 -> null | AY5: =IF(AND(EXACT($B5, ""), EXACT($D5, ""), EXACT($F5, ""), EXACT($H5, ""), EXACT($J5, ""), EXACT($L5, "")), "", IF(NOT(EXACT($B5, "")), "null", IF(NOT(EXACT($D5, "")), IF($W4<>$W3, $W4, $W5), IF(NOT(EXACT($F5, "")), IF($X4<>$X3, $X4, IF($W4<>$W3, $W4, $X5)), IF(NOT(EXACT($H5, "")), IF($Y4<>$Y3, $Y4, IF($X4<>$X3, $X4, IF($W4<>$W3, $W4, $Y5))), IF(NOT(EXACT($J5, "")), IF($Z4<>$Z3, $Z4, IF($Y4<>$Y3, $Y4, IF($X4<>$X3, $X4, IF($W4<>$W3, $W4, $Z5)))), IF(NOT(EXACT($L5, "")), IF($AA4<>$AA3, $AA4, IF($Z4<>$Z3, $Z4, IF($Y4<>$Y3, $Y4, IF($X4<>$X3, $X4, IF($W4<>$W3, $W4, $AA5))))), "others"))))))) -> null | BA5: =BA4 + IF(EXACT(BB5, ""), 0, 1) -> 65000000000001 | BB5: =IF(AND(EXACT($B5, ""), EXACT($D5, ""), EXACT($F5, ""), EXACT($H5, ""), EXACT($J5, ""), EXACT($L5, "")), "", CONCATENATE( "PERFORM * FROM ""SchData-OLTP-Accounting"".""Func_TblChartOfAccount_SET""(varSystemLoginSession, null, null, null, null, null, varInstitutionBranchID, 62000000000001::bigint,'", IF(EXACT($B5, ""), IF(EXACT($D5, ""), IF(EXACT($F5, ""), IF(EXACT($H5, ""), IF(EXACT($J5, ""), IF(EXACT($L5, ""), "", $L5), $J5), $H5), $F5), $D5), $B5), "', '", IF(EXACT($B5, ""), IF(EXACT($D5, ""), IF(EXACT($F5, ""), IF(EXACT($H5, ""), IF(EXACT($J5, ""), IF(EXACT($L5, ""), "", $M5), $K5), $I5), $G5), $E5), $C5), "', ", IF(EXACT($J5, ""), "62000000000001::bigint", IF((RIGHT($J5, 2)*1 = 1), "62000000000001::bigint", IF((RIGHT($J5, 2)*1 = 2), "62000000000002::bigint", "null"))), ", '2016-01-01 00:00:00'::timestamp, null::timestamp, ", $AW5, "::bigint, 66000000000001::bigint, ", IF(EXACT(LEFT(IF(EXACT($B5, ""), IF(EXACT($D5, ""), IF(EXACT($F5, ""), IF(EXACT($H5, ""), IF(EXACT($J5, ""), IF(EXACT($L5, ""), "", $L5), $J5), $H5), $F5), $D5), $B5), 1), "1"), "TRUE", "FALSE"), "::boolean);")) -> PERFORM * FROM "SchData-OLTP-Accounting"."Func_TblChartOfAccount_SET"(varSystemLoginSession, null, null, null, null, null, varInstitutionBranchID, 62000000000001::bigint,'1-0000', 'Aset', 62000000000001::bigint, '2016-01-01 00:00:00'::timestamp, null::timestamp, null::bigint, 66000000000001::bigint, TRUE::boolean);
D6: 1-1000 | E6: Aset Lancar | O6: =IF(EXACT($B6, ""), $O5, $B6) -> 1-0000 | P6: =IF(EXACT($D6, ""), $P5, $D6) -> 1-1000 | Q6: =IF(EXACT($F6, ""), $Q5, $F6) | R6: =IF(EXACT($H6, ""), $R5, $H6) | S6: =IF(EXACT($J6, ""), $S5, $J6) | T6: =IF(EXACT($L6, ""), $T5, $L6) | V6: =V5+IF(AND(EXACT(B6, ""), EXACT(D6, ""), EXACT(F6, ""), EXACT(H6, ""), EXACT(J6, ""), EXACT(L6, "")), 0, 1) -> 65000000000002 | W6: =IF(EXACT($B6, ""), $W5, $V6) -> 65000000000001 | X6: =IF(EXACT($D6, ""), $X5, $V6) -> 65000000000002 | Y6: =IF(EXACT($F6, ""), $Y5, $V6) -> 65000000000000 | Z6: =IF(EXACT($H6, ""), $Z5, $V6) -> 65000000000000 | AA6: =IF(EXACT($J6, ""), $AA5, $V6) -> 65000000000000 | AB6: =IF(EXACT($L6, ""), $AB5, $V6) -> 65000000000000 | AD6: =AD5 + IF(W6<>W5, 1, 0) -> 1 | AE6: =IF(AD5<>AD6, 1, AE5) + IF(X6<>X5, 1, 0) -> 2 | AF6: =IF(AE5<>AE6, 1, AF5) + IF(Y6<>Y5, 1, 0) -> 1 | AG6: =IF(AF5<>AF6, 1, AG5) + IF(Z6<>Z5, 1, 0) -> 1 | AH6: =IF(AG5<>AG6, 1, AH5) + IF(AA6<>AA5, 1, 0) -> 1 | AI6: =IF(AH5<>AH6, 1, AI5) + IF(AB6<>AB5, 1, 0) -> 1 | AK6: =IF(AA6<>AA5, "L5", IF(Z6<>Z5, "L4", IF(Y6<>Y5, "L3", IF(X6<>X5, "L2", IF(W6<>W5, "L1", "L1" ) ) ) ) ) -> L2 | AM6: null | AN6: =IF(EXACT($AK5, "L1"), $W5, AN5) -> 65000000000001 | AO6: =IF(EXACT($AK5, "L1"), $W5, IF(EXACT($AK5, "L2"), $X5, AO5)) -> 65000000000001 | AP6: =IF(EXACT($AK5, "L1"), $W5, IF(EXACT($AK5, "L2"), $X5, IF(EXACT($AK5, "L3"), $Y5, AP5))) -> 65000000000001 | AQ6: =IF(EXACT($AK5, "L1"), $W5, IF(EXACT($AK5, "L2"), $X5, IF(EXACT($AK5, "L3"), $Y5, IF(EXACT($AK5, "L4"), $Z5, AQ5)))) -> 65000000000001 | AS6: =IF(EXACT($AK6, "L1"), AM6, IF(EXACT($AK6, "L2"), AN6, IF(EXACT($AK6, "L3"), AO6, IF(EXACT($AK6, "L4"), AP6, IF(EXACT($AK6, "L5"), AQ6, ""))))) -> 65000000000001 | AU6: =IF(AND(EXACT(B6, ""), EXACT(D6, ""), EXACT(F6, ""), EXACT(H6, ""), EXACT(J6, ""), EXACT(L6, "")), "", CONCATENATE( "PERFORM * FROM ""SchData-OLTP-Accounting"".""Func_TblChartOfAccount_SET""(varSystemLoginSession, null, null, null, varInstitutionBranchID, 62000000000001::bigint,'", IF(EXACT(B6, ""), IF(EXACT(D6, ""), IF(EXACT(F6, ""), IF(EXACT(H6, ""), IF(EXACT(J6, ""), IF(EXACT(L6, ""), "", L6), J6), H6), F6), D6), B6), "', '", IF(EXACT(B6, ""), IF(EXACT(D6, ""), IF(EXACT(F6, ""), IF(EXACT(H6, ""), IF(EXACT(J6, ""), IF(EXACT(L6, ""), "", M6), K6), I6), G6), E6), C6), "', ", IF(EXACT(J6, ""), "62000000000001::bigint", IF((RIGHT(J6, 2)*1 = 1), "62000000000001::bigint", IF((RIGHT(J6, 2)*1 = 2), "62000000000002::bigint", "null"))), ", '2016-01-01 00:00:00'::timestamp, null::timestamp, ", AW6, "::bigint, 66000000000001::bigint);")) -> PERFORM * FROM "SchData-OLTP-Accounting"."Func_TblChartOfAccount_SET"(varSystemLoginSession, null, null, null, varInstitutionBranchID, 62000000000001::bigint,'1-1000', 'Aset Lancar', 62000000000001::bigint, '2016-01-01 00:00:00'::timestamp, null::timestamp, 65000000000001::bigint, 66000000000001::bigint); | AV6: =IF(AND(EXACT($B6, ""), EXACT($D6, ""), EXACT($F6, ""), EXACT($H6, ""), EXACT($J6, ""), EXACT($L6, "")), "", V6) -> 65000000000002 | AW6: =AS6 -> 65000000000001 | AY6: =IF(AND(EXACT($B6, ""), EXACT($D6, ""), EXACT($F6, ""), EXACT($H6, ""), EXACT($J6, ""), EXACT($L6, "")), "", IF(NOT(EXACT($B6, "")), "null", IF(NOT(EXACT($D6, "")), IF($W5<>$W4, $W5, $W6), IF(NOT(EXACT($F6, "")), IF($X5<>$X4, $X5, IF($W5<>$W4, $W5, $X6)), IF(NOT(EXACT($H6, "")), IF($Y5<>$Y4, $Y5, IF($X5<>$X4, $X5, IF($W5<>$W4, $W5, $Y6))), IF(NOT(EXACT($J6, "")), IF($Z5<>$Z4, $Z5, IF($Y5<>$Y4, $Y5, IF($X5<>$X4, $X5, IF($W5<>$W4, $W5, $Z6)))), IF(NOT(EXACT($L6, "")), IF($AA5<>$AA4, $AA5, IF($Z5<>$Z4, $Z5, IF($Y5<>$Y4, $Y5, IF($X5<>$X4, $X5, IF($W5<>$W4, $W5, $AA6))))), "others"))))))) -> 65000000000001 | BA6: =BA5 + IF(EXACT(BB6, ""), 0, 1) -> 65000000000002 | BB6: =IF(AND(EXACT($B6, ""), EXACT($D6, ""), EXACT($F6, ""), EXACT($H6, ""), EXACT($J6, ""), EXACT($L6, "")), "", CONCATENATE( "PERFORM * FROM ""SchData-OLTP-Accounting"".""Func_TblChartOfAccount_SET""(varSystemLoginSession, null, null, null, null, null, varInstitutionBranchID, 62000000000001::bigint,'", IF(EXACT($B6, ""), IF(EXACT($D6, ""), IF(EXACT($F6, ""), IF(EXACT($H6, ""), IF(EXACT($J6, ""), IF(EXACT($L6, ""), "", $L6), $J6), $H6), $F6), $D6), $B6), "', '", IF(EXACT($B6, ""), IF(EXACT($D6, ""), IF(EXACT($F6, ""), IF(EXACT($H6, ""), IF(EXACT($J6, ""), IF(EXACT($L6, ""), "", $M6), $K6), $I6), $G6), $E6), $C6), "', ", IF(EXACT($J6, ""), "62000000000001::bigint", IF((RIGHT($J6, 2)*1 = 1), "62000000000001::bigint", IF((RIGHT($J6, 2)*1 = 2), "62000000000002::bigint", "null"))), ", '2016-01-01 00:00:00'::timestamp, null::timestamp, ", $AW6, "::bigint, 66000000000001::bigint, ", IF(EXACT(LEFT(IF(EXACT($B6, ""), IF(EXACT($D6, ""), IF(EXACT($F6, ""), IF(EXACT($H6, ""), IF(EXACT($J6, ""), IF(EXACT($L6, ""), "", $L6), $J6), $H6), $F6), $D6), $B6), 1), "1"), "TRUE", "FALSE"), "::boolean);")) -> PERFORM * FROM "SchData-OLTP-Accounting"."Func_TblChartOfAccount_SET"(varSystemLoginSession, null, null, null, null, null, varInstitutionBranchID, 62000000000001::bigint,'1-1000', 'Aset Lancar', 62000000000001::bigint, '2016-01-01 00:00:00'::timestamp, null::timestamp, 65000000000001::bigint, 66000000000001::bigint, TRUE::boolean);
F7: 1-1100 | G7: Cash & Bank | O7: =IF(EXACT($B7, ""), $O6, $B7) -> 1-0000 | P7: =IF(EXACT($D7, ""), $P6, $D7) -> 1-1000 | Q7: =IF(EXACT($F7, ""), $Q6, $F7) -> 1-1100 | R7: =IF(EXACT($H7, ""), $R6, $H7) | S7: =IF(EXACT($J7, ""), $S6, $J7) | T7: =IF(EXACT($L7, ""), $T6, $L7) | V7: =V6+IF(AND(EXACT(B7, ""), EXACT(D7, ""), EXACT(F7, ""), EXACT(H7, ""), EXACT(J7, ""), EXACT(L7, "")), 0, 1) -> 65000000000003 | W7: =IF(EXACT($B7, ""), $W6, $V7) -> 65000000000001 | X7: =IF(EXACT($D7, ""), $X6, $V7) -> 65000000000002 | Y7: =IF(EXACT($F7, ""), $Y6, $V7) -> 65000000000003 | Z7: =IF(EXACT($H7, ""), $Z6, $V7) -> 65000000000000 | AA7: =IF(EXACT($J7, ""), $AA6, $V7) -> 65000000000000 | AB7: =IF(EXACT($L7, ""), $AB6, $V7) -> 65000000000000 | AD7: =AD6 + IF(W7<>W6, 1, 0) -> 1 | AE7: =IF(AD6<>AD7, 1, AE6) + IF(X7<>X6, 1, 0) -> 2 | AF7: =IF(AE6<>AE7, 1, AF6) + IF(Y7<>Y6, 1, 0) -> 2 | AG7: =IF(AF6<>AF7, 1, AG6) + IF(Z7<>Z6, 1, 0) -> 1 | AH7: =IF(AG6<>AG7, 1, AH6) + IF(AA7<>AA6, 1, 0) -> 1 | AI7: =IF(AH6<>AH7, 1, AI6) + IF(AB7<>AB6, 1, 0) -> 1 | AK7: =IF(AA7<>AA6, "L5", IF(Z7<>Z6, "L4", IF(Y7<>Y6, "L3", IF(X7<>X6, "L2", IF(W7<>W6, "L1", "L1" ) ) ) ) ) -> L3 | AM7: null | AN7: =IF(EXACT($AK6, "L1"), $W6, AN6) -> 65000000000001 | AO7: =IF(EXACT($AK6, "L1"), $W6, IF(EXACT($AK6, "L2"), $X6, AO6)) -> 65000000000002 | AP7: =IF(EXACT($AK6, "L1"), $W6, IF(EXACT($AK6, "L2"), $X6, IF(EXACT($AK6, "L3"), $Y6, AP6))) -> 65000000000002 | AQ7: =IF(EXACT($AK6, "L1"), $W6, IF(EXACT($AK6, "L2"), $X6, IF(EXACT($AK6, "L3"), $Y6, IF(EXACT($AK6, "L4"), $Z6, AQ6)))) -> 65000000000002 | AS7: =IF(EXACT($AK7, "L1"), AM7, IF(EXACT($AK7, "L2"), AN7, IF(EXACT($AK7, "L3"), AO7, IF(EXACT($AK7, "L4"), AP7, IF(EXACT($AK7, "L5"), AQ7, ""))))) -> 65000000000002 | AU7: =IF(AND(EXACT(B7, ""), EXACT(D7, ""), EXACT(F7, ""), EXACT(H7, ""), EXACT(J7, ""), EXACT(L7, "")), "", CONCATENATE( "PERFORM * FROM ""SchData-OLTP-Accounting"".""Func_TblChartOfAccount_SET""(varSystemLoginSession, null, null, null, varInstitutionBranchID, 62000000000001::bigint,'", IF(EXACT(B7, ""), IF(EXACT(D7, ""), IF(EXACT(F7, ""), IF(EXACT(H7, ""), IF(EXACT(J7, ""), IF(EXACT(L7, ""), "", L7), J7), H7), F7), D7), B7), "', '", IF(EXACT(B7, ""), IF(EXACT(D7, ""), IF(EXACT(F7, ""), IF(EXACT(H7, ""), IF(EXACT(J7, ""), IF(EXACT(L7, ""), "", M7), K7), I7), G7), E7), C7), "', ", IF(EXACT(J7, ""), "62000000000001::bigint", IF((RIGHT(J7, 2)*1 = 1), "62000000000001::bigint", IF((RIGHT(J7, 2)*1 = 2), "62000000000002::bigint", "null"))), ", '2016-01-01 00:00:00'::timestamp, null::timestamp, ", AW7, "::bigint, 66000000000001::bigint);")) -> PERFORM * FROM "SchData-OLTP-Accounting"."Func_TblChartOfAccount_SET"(varSystemLoginSession, null, null, null, varInstitutionBranchID, 62000000000001::bigint,'1-1100', 'Cash & Bank', 62000000000001::bigint, '2016-01-01 00:00:00'::timestamp, null::timestamp, 65000000000002::bigint, 66000000000001::bigint); | AV7: =IF(AND(EXACT($B7, ""), EXACT($D7, ""), EXACT($F7, ""), EXACT($H7, ""), EXACT($J7, ""), EXACT($L7, "")), "", V7) -> 65000000000003 | AW7: =AS7 -> 65000000000002 | AY7: =IF(AND(EXACT($B7, ""), EXACT($D7, ""), EXACT($F7, ""), EXACT($H7, ""), EXACT($J7, ""), EXACT($L7, "")), "", IF(NOT(EXACT($B7, "")), "null", IF(NOT(EXACT($D7, "")), IF($W6<>$W5, $W6, $W7), IF(NOT(EXACT($F7, "")), IF($X6<>$X5, $X6, IF($W6<>$W5, $W6, $X7)), IF(NOT(EXACT($H7, "")), IF($Y6<>$Y5, $Y6, IF($X6<>$X5, $X6, IF($W6<>$W5, $W6, $Y7))), IF(NOT(EXACT($J7, "")), IF($Z6<>$Z5, $Z6, IF($Y6<>$Y5, $Y6, IF($X6<>$X5, $X6, IF($W6<>$W5, $W6, $Z7)))), IF(NOT(EXACT($L7, "")), IF($AA6<>$AA5, $AA6, IF($Z6<>$Z5, $Z6, IF($Y6<>$Y5, $Y6, IF($X6<>$X5, $X6, IF($W6<>$W5, $W6, $AA7))))), "others"))))))) -> 65000000000002 | BA7: =BA6 + IF(EXACT(BB7, ""), 0, 1) -> 65000000000003 | BB7: =IF(AND(EXACT($B7, ""), EXACT($D7, ""), EXACT($F7, ""), EXACT($H7, ""), EXACT($J7, ""), EXACT($L7, "")), "", CONCATENATE( "PERFORM * FROM ""SchData-OLTP-Accounting"".""Func_TblChartOfAccount_SET""(varSystemLoginSession, null, null, null, null, null, varInstitutionBranchID, 62000000000001::bigint,'", IF(EXACT($B7, ""), IF(EXACT($D7, ""), IF(EXACT($F7, ""), IF(EXACT($H7, ""), IF(EXACT($J7, ""), IF(EXACT($L7, ""), "", $L7), $J7), $H7), $F7), $D7), $B7), "', '", IF(EXACT($B7, ""), IF(EXACT($D7, ""), IF(EXACT($F7, ""), IF(EXACT($H7, ""), IF(EXACT($J7, ""), IF(EXACT($L7, ""), "", $M7), $K7), $I7), $G7), $E7), $C7), "', ", IF(EXACT($J7, ""), "62000000000001::bigint", IF((RIGHT($J7, 2)*1 = 1), "62000000000001::bigint", IF((RIGHT($J7, 2)*1 = 2), "62000000000002::bigint", "null"))), ", '2016-01-01 00:00:00'::timestamp, null::timestamp, ", $AW7, "::bigint, 66000000000001::bigint, ", IF(EXACT(LEFT(IF(EXACT($B7, ""), IF(EXACT($D7, ""), IF(EXACT($F7, ""), IF(EXACT($H7, ""), IF(EXACT($J7, ""), IF(EXACT($L7, ""), "", $L7), $J7), $H7), $F7), $D7), $B7), 1), "1"), "TRUE", "FALSE"), "::boolean);")) -> PERFORM * FROM "SchData-OLTP-Accounting"."Func_TblChartOfAccount_SET"(varSystemLoginSession, null, null, null, null, null, varInstitutionBranchID, 62000000000001::bigint,'1-1100', 'Cash & Bank', 62000000000001::bigint, '2016-01-01 00:00:00'::timestamp, null::timestamp, 65000000000002::bigint, 66000000000001::bigint, TRUE::boolean);
H8: 1-1101 | I8: Petty Cash | O8: =IF(EXACT($B8, ""), $O7, $B8) -> 1-0000 | P8: =IF(EXACT($D8, ""), $P7, $D8) -> 1-1000 | Q8: =IF(EXACT($F8, ""), $Q7, $F8) -> 1-1100 | R8: =IF(EXACT($H8, ""), $R7, $H8) -> 1-1101 | S8: =IF(EXACT($J8, ""), $S7, $J8) | T8: =IF(EXACT($L8, ""), $T7, $L8) | V8: =V7+IF(AND(EXACT(B8, ""), EXACT(D8, ""), EXACT(F8, ""), EXACT(H8, ""), EXACT(J8, ""), EXACT(L8, "")), 0, 1) -> 65000000000004 | W8: =IF(EXACT($B8, ""), $W7, $V8) -> 65000000000001 | X8: =IF(EXACT($D8, ""), $X7, $V8) -> 65000000000002 | Y8: =IF(EXACT($F8, ""), $Y7, $V8) -> 65000000000003 | Z8: =IF(EXACT($H8, ""), $Z7, $V8) -> 65000000000004 | AA8: =IF(EXACT($J8, ""), $AA7, $V8) -> 65000000000000 | AB8: =IF(EXACT($L8, ""), $AB7, $V8) -> 65000000000000 | AD8: =AD7 + IF(W8<>W7, 1, 0) -> 1 | AE8: =IF(AD7<>AD8, 1, AE7) + IF(X8<>X7, 1, 0) -> 2 | AF8: =IF(AE7<>AE8, 1, AF7) + IF(Y8<>Y7, 1, 0) -> 2 | AG8: =IF(AF7<>AF8, 1, AG7) + IF(Z8<>Z7, 1, 0) -> 2 | AH8: =IF(AG7<>AG8, 1, AH7) + IF(AA8<>AA7, 1, 0) -> 1 | AI8: =IF(AH7<>AH8, 1, AI7) + IF(AB8<>AB7, 1, 0) -> 1 | AK8: =IF(AA8<>AA7, "L5", IF(Z8<>Z7, "L4", IF(Y8<>Y7, "L3", IF(X8<>X7, "L2", IF(W8<>W7, "L1", "L1" ) ) ) ) ) -> L4 | AM8: null | AN8: =IF(EXACT($AK7, "L1"), $W7, AN7) -> 65000000000001 | AO8: =IF(EXACT($AK7, "L1"), $W7, IF(EXACT($AK7, "L2"), $X7, AO7)) -> 65000000000002 | AP8: =IF(EXACT($AK7, "L1"), $W7, IF(EXACT($AK7, "L2"), $X7, IF(EXACT($AK7, "L3"), $Y7, AP7))) -> 65000000000003 | AQ8: =IF(EXACT($AK7, "L1"), $W7, IF(EXACT($AK7, "L2"), $X7, IF(EXACT($AK7, "L3"), $Y7, IF(EXACT($AK7, "L4"), $Z7, AQ7)))) -> 65000000000003 | AS8: =IF(EXACT($AK8, "L1"), AM8, IF(EXACT($AK8, "L2"), AN8, IF(EXACT($AK8, "L3"), AO8, IF(EXACT($AK8, "L4"), AP8, IF(EXACT($AK8, "L5"), AQ8, ""))))) -> 65000000000003 | AU8: =IF(AND(EXACT(B8, ""), EXACT(D8, ""), EXACT(F8, ""), EXACT(H8, ""), EXACT(J8, ""), EXACT(L8, "")), "", CONCATENATE( "PERFORM * FROM ""SchData-OLTP-Accounting"".""Func_TblChartOfAccount_SET""(varSystemLoginSession, null, null, null, varInstitutionBranchID, 62000000000001::bigint,'", IF(EXACT(B8, ""), IF(EXACT(D8, ""), IF(EXACT(F8, ""), IF(EXACT(H8, ""), IF(EXACT(J8, ""), IF(EXACT(L8, ""), "", L8), J8), H8), F8), D8), B8), "', '", IF(EXACT(B8, ""), IF(EXACT(D8, ""), IF(EXACT(F8, ""), IF(EXACT(H8, ""), IF(EXACT(J8, ""), IF(EXACT(L8, ""), "", M8), K8), I8), G8), E8), C8), "', ", IF(EXACT(J8, ""), "62000000000001::bigint", IF((RIGHT(J8, 2)*1 = 1), "62000000000001::bigint", IF((RIGHT(J8, 2)*1 = 2), "62000000000002::bigint", "null"))), ", '2016-01-01 00:00:00'::timestamp, null::timestamp, ", AW8, "::bigint, 66000000000001::bigint);")) -> PERFORM * FROM "SchData-OLTP-Accounting"."Func_TblChartOfAccount_SET"(varSystemLoginSession, null, null, null, varInstitutionBranchID, 62000000000001::bigint,'1-1101', 'Petty Cash', 62000000000001::bigint, '2016-01-01 00:00:00'::timestamp, null::timestamp, 65000000000003::bigint, 66000000000001::bigint); | AV8: =IF(AND(EXACT($B8, ""), EXACT($D8, ""), EXACT($F8, ""), EXACT($H8, ""), EXACT($J8, ""), EXACT($L8, "")), "", V8) -> 65000000000004 | AW8: =AS8 -> 65000000000003 | AY8: =IF(AND(EXACT($B8, ""), EXACT($D8, ""), EXACT($F8, ""), EXACT($H8, ""), EXACT($J8, ""), EXACT($L8, "")), "", IF(NOT(EXACT($B8, "")), "null", IF(NOT(EXACT($D8, "")), IF($W7<>$W6, $W7, $W8), IF(NOT(EXACT($F8, "")), IF($X7<>$X6, $X7, IF($W7<>$W6, $W7, $X8)), IF(NOT(EXACT($H8, "")), IF($Y7<>$Y6, $Y7, IF($X7<>$X6, $X7, IF($W7<>$W6, $W7, $Y8))), IF(NOT(EXACT($J8, "")), IF($Z7<>$Z6, $Z7, IF($Y7<>$Y6, $Y7, IF($X7<>$X6, $X7, IF($W7<>$W6, $W7, $Z8)))), IF(NOT(EXACT($L8, "")), IF($AA7<>$AA6, $AA7, IF($Z7<>$Z6, $Z7, IF($Y7<>$Y6, $Y7, IF($X7<>$X6, $X7, IF($W7<>$W6, $W7, $AA8))))), "others"))))))) -> 65000000000003 | BA8: =BA7 + IF(EXACT(BB8, ""), 0, 1) -> 65000000000004 | BB8: =IF(AND(EXACT($B8, ""), EXACT($D8, ""), EXACT($F8, ""), EXACT($H8, ""), EXACT($J8, ""), EXACT($L8, "")), "", CONCATENATE( "PERFORM * FROM ""SchData-OLTP-Accounting"".""Func_TblChartOfAccount_SET""(varSystemLoginSession, null, null, null, null, null, varInstitutionBranchID, 62000000000001::bigint,'", IF(EXACT($B8, ""), IF(EXACT($D8, ""), IF(EXACT($F8, ""), IF(EXACT($H8, ""), IF(EXACT($J8, ""), IF(EXACT($L8, ""), "", $L8), $J8), $H8), $F8), $D8), $B8), "', '", IF(EXACT($B8, ""), IF(EXACT($D8, ""), IF(EXACT($F8, ""), IF(EXACT($H8, ""), IF(EXACT($J8, ""), IF(EXACT($L8, ""), "", $M8), $K8), $I8), $G8), $E8), $C8), "', ", IF(EXACT($J8, ""), "62000000000001::bigint", IF((RIGHT($J8, 2)*1 = 1), "62000000000001::bigint", IF((RIGHT($J8, 2)*1 = 2), "62000000000002::bigint", "null"))), ", '2016-01-01 00:00:00'::timestamp, null::timestamp, ", $AW8, "::bigint, 66000000000001::bigint, ", IF(EXACT(LEFT(IF(EXACT($B8, ""), IF(EXACT($D8, ""), IF(EXACT($F8, ""), IF(EXACT($H8, ""), IF(EXACT($J8, ""), IF(EXACT($L8, ""), "", $L8), $J8), $H8), $F8), $D8), $B8), 1), "1"), "TRUE", "FALSE"), "::boolean);")) -> PERFORM * FROM "SchData-OLTP-Accounting"."Func_TblChartOfAccount_SET"(varSystemLoginSession, null, null, null, null, null, varInstitutionBranchID, 62000000000001::bigint,'1-1101', 'Petty Cash', 62000000000001::bigint, '2016-01-01 00:00:00'::timestamp, null::timestamp, 65000000000003::bigint, 66000000000001::bigint, TRUE::boolean);
J9: 1-1101.01 | K9: Petty Cash (IDR) | O9: =IF(EXACT($B9, ""), $O8, $B9) -> 1-0000 | P9: =IF(EXACT($D9, ""), $P8, $D9) -> 1-1000 | Q9: =IF(EXACT($F9, ""), $Q8, $F9) -> 1-1100 | R9: =IF(EXACT($H9, ""), $R8, $H9) -> 1-1101 | S9: =IF(EXACT($J9, ""), $S8, $J9) -> 1-1101.01 | T9: =IF(EXACT($L9, ""), $T8, $L9) | V9: =V8+IF(AND(EXACT(B9, ""), EXACT(D9, ""), EXACT(F9, ""), EXACT(H9, ""), EXACT(J9, ""), EXACT(L9, "")), 0, 1) -> 65000000000005 | W9: =IF(EXACT($B9, ""), $W8, $V9) -> 65000000000001 | X9: =IF(EXACT($D9, ""), $X8, $V9) -> 65000000000002 | Y9: =IF(EXACT($F9, ""), $Y8, $V9) -> 65000000000003 | Z9: =IF(EXACT($H9, ""), $Z8, $V9) -> 65000000000004 | AA9: =IF(EXACT($J9, ""), $AA8, $V9) -> 65000000000005 | AB9: =IF(EXACT($L9, ""), $AB8, $V9) -> 65000000000000 | AD9: =AD8 + IF(W9<>W8, 1, 0) -> 1 | AE9: =IF(AD8<>AD9, 1, AE8) + IF(X9<>X8, 1, 0) -> 2 | AF9: =IF(AE8<>AE9, 1, AF8) + IF(Y9<>Y8, 1, 0) -> 2 | AG9: =IF(AF8<>AF9, 1, AG8) + IF(Z9<>Z8, 1, 0) -> 2 | AH9: =IF(AG8<>AG9, 1, AH8) + IF(AA9<>AA8, 1, 0) -> 2 | AI9: =IF(AH8<>AH9, 1, AI8) + IF(AB9<>AB8, 1, 0) -> 1 | AK9: =IF(AA9<>AA8, "L5", IF(Z9<>Z8, "L4", IF(Y9<>Y8, "L3", IF(X9<>X8, "L2", IF(W9<>W8, "L1", "L1" ) ) ) ) ) -> L5 | AM9: null | AN9: =IF(EXACT($AK8, "L1"), $W8, AN8) -> 65000000000001 | AO9: =IF(EXACT($AK8, "L1"), $W8, IF(EXACT($AK8, "L2"), $X8, AO8)) -> 65000000000002 | AP9: =IF(EXACT($AK8, "L1"), $W8, IF(EXACT($AK8, "L2"), $X8, IF(EXACT($AK8, "L3"), $Y8, AP8))) -> 65000000000003 | AQ9: =IF(EXACT($AK8, "L1"), $W8, IF(EXACT($AK8, "L2"), $X8, IF(EXACT($AK8, "L3"), $Y8, IF(EXACT($AK8, "L4"), $Z8, AQ8)))) -> 65000000000004 | AS9: =IF(EXACT($AK9, "L1"), AM9, IF(EXACT($AK9, "L2"), AN9, IF(EXACT($AK9, "L3"), AO9, IF(EXACT($AK9, "L4"), AP9, IF(EXACT($AK9, "L5"), AQ9, ""))))) -> 65000000000004 | AU9: =IF(AND(EXACT(B9, ""), EXACT(D9, ""), EXACT(F9, ""), EXACT(H9, ""), EXACT(J9, ""), EXACT(L9, "")), "", CONCATENATE( "PERFORM * FROM ""SchData-OLTP-Accounting"".""Func_TblChartOfAccount_SET""(varSystemLoginSession, null, null, null, varInstitutionBranchID, 62000000000001::bigint,'", IF(EXACT(B9, ""), IF(EXACT(D9, ""), IF(EXACT(F9, ""), IF(EXACT(H9, ""), IF(EXACT(J9, ""), IF(EXACT(L9, ""), "", L9), J9), H9), F9), D9), B9), "', '", IF(EXACT(B9, ""), IF(EXACT(D9, ""), IF(EXACT(F9, ""), IF(EXACT(H9, ""), IF(EXACT(J9, ""), IF(EXACT(L9, ""), "", M9), K9), I9), G9), E9), C9), "', ", IF(EXACT(J9, ""), "62000000000001::bigint", IF((RIGHT(J9, 2)*1 = 1), "62000000000001::bigint", IF((RIGHT(J9, 2)*1 = 2), "62000000000002::bigint", "null"))), ", '2016-01-01 00:00:00'::timestamp, null::timestamp, ", AW9, "::bigint, 66000000000001::bigint);")) -> PERFORM * FROM "SchData-OLTP-Accounting"."Func_TblChartOfAccount_SET"(varSystemLoginSession, null, null, null, varInstitutionBranchID, 62000000000001::bigint,'1-1101.01', 'Petty Cash (IDR)', 62000000000001::bigint, '2016-01-01 00:00:00'::timestamp, null::timestamp, 65000000000004::bigint, 66000000000001::bigint); | AV9: =IF(AND(EXACT($B9, ""), EXACT($D9, ""), EXACT($F9, ""), EXACT($H9, ""), EXACT($J9, ""), EXACT($L9, "")), "", V9) -> 65000000000005 | AW9: =AS9 -> 65000000000004 | AY9: =IF(AND(EXACT($B9, ""), EXACT($D9, ""), EXACT($F9, ""), EXACT($H9, ""), EXACT($J9, ""), EXACT($L9, "")), "", IF(NOT(EXACT($B9, "")), "null", IF(NOT(EXACT($D9, "")), IF($W8<>$W7, $W8, $W9), IF(NOT(EXACT($F9, "")), IF($X8<>$X7, $X8, IF($W8<>$W7, $W8, $X9)), IF(NOT(EXACT($H9, "")), IF($Y8<>$Y7, $Y8, IF($X8<>$X7, $X8, IF($W8<>$W7, $W8, $Y9))), IF(NOT(EXACT($J9, "")), IF($Z8<>$Z7, $Z8, IF($Y8<>$Y7, $Y8, IF($X8<>$X7, $X8, IF($W8<>$W7, $W8, $Z9)))), IF(NOT(EXACT($L9, "")), IF($AA8<>$AA7, $AA8, IF($Z8<>$Z7, $Z8, IF($Y8<>$Y7, $Y8, IF($X8<>$X7, $X8, IF($W8<>$W7, $W8, $AA9))))), "others"))))))) -> 65000000000004 | BA9: =BA8 + IF(EXACT(BB9, ""), 0, 1) -> 65000000000005 | BB9: =IF(AND(EXACT($B9, ""), EXACT($D9, ""), EXACT($F9, ""), EXACT($H9, ""), EXACT($J9, ""), EXACT($L9, "")), "", CONCATENATE( "PERFORM * FROM ""SchData-OLTP-Accounting"".""Func_TblChartOfAccount_SET""(varSystemLoginSession, null, null, null, null, null, varInstitutionBranchID, 62000000000001::bigint,'", IF(EXACT($B9, ""), IF(EXACT($D9, ""), IF(EXACT($F9, ""), IF(EXACT($H9, ""), IF(EXACT($J9, ""), IF(EXACT($L9, ""), "", $L9), $J9), $H9), $F9), $D9), $B9), "', '", IF(EXACT($B9, ""), IF(EXACT($D9, ""), IF(EXACT($F9, ""), IF(EXACT($H9, ""), IF(EXACT($J9, ""), IF(EXACT($L9, ""), "", $M9), $K9), $I9), $G9), $E9), $C9), "', ", IF(EXACT($J9, ""), "62000000000001::bigint", IF((RIGHT($J9, 2)*1 = 1), "62000000000001::bigint", IF((RIGHT($J9, 2)*1 = 2), "62000000000002::bigint", "null"))), ", '2016-01-01 00:00:00'::timestamp, null::timestamp, ", $AW9, "::bigint, 66000000000001::bigint, ", IF(EXACT(LEFT(IF(EXACT($B9, ""), IF(EXACT($D9, ""), IF(EXACT($F9, ""), IF(EXACT($H9, ""), IF(EXACT($J9, ""), IF(EXACT($L9, ""), "", $L9), $J9), $H9), $F9), $D9), $B9), 1), "1"), "TRUE", "FALSE"), "::boolean);")) -> PERFORM * FROM "SchData-OLTP-Accounting"."Func_TblChartOfAccount_SET"(varSystemLoginSession, null, null, null, null, null, varInstitutionBranchID, 62000000000001::bigint,'1-1101.01', 'Petty Cash (IDR)', 62000000000001::bigint, '2016-01-01 00:00:00'::timestamp, null::timestamp, 65000000000004::bigint, 66000000000001::bigint, TRUE::boolean);
H10: 1-1102 | I10: Bank | O10: =IF(EXACT($B10, ""), $O9, $B10) -> 1-0000 | P10: =IF(EXACT($D10, ""), $P9, $D10) -> 1-1000 | Q10: =IF(EXACT($F10, ""), $Q9, $F10) -> 1-1100 | R10: =IF(EXACT($H10, ""), $R9, $H10) -> 1-1102 | S10: =IF(EXACT($J10, ""), $S9, $J10) -> 1-1101.01 | T10: =IF(EXACT($L10, ""), $T9, $L10) | V10: =V9+IF(AND(EXACT(B10, ""), EXACT(D10, ""), EXACT(F10, ""), EXACT(H10, ""), EXACT(J10, ""), EXACT(L10, "")), 0, 1) -> 65000000000006 | W10: =IF(EXACT($B10, ""), $W9, $V10) -> 65000000000001 | X10: =IF(EXACT($D10, ""), $X9, $V10) -> 65000000000002 | Y10: =IF(EXACT($F10, ""), $Y9, $V10) -> 65000000000003 | Z10: =IF(EXACT($H10, ""), $Z9, $V10) -> 65000000000006 | AA10: =IF(EXACT($J10, ""), $AA9, $V10) -> 65000000000005 | AB10: =IF(EXACT($L10, ""), $AB9, $V10) -> 65000000000000 | AD10: =AD9 + IF(W10<>W9, 1, 0) -> 1 | AE10: =IF(AD9<>AD10, 1, AE9) + IF(X10<>X9, 1, 0) -> 2 | AF10: =IF(AE9<>AE10, 1, AF9) + IF(Y10<>Y9, 1, 0) -> 2 | AG10: =IF(AF9<>AF10, 1, AG9) + IF(Z10<>Z9, 1, 0) -> 3 | AH10: =IF(AG9<>AG10, 1, AH9) + IF(AA10<>AA9, 1, 0) -> 1 | AI10: =IF(AH9<>AH10, 1, AI9) + IF(AB10<>AB9, 1, 0) -> 1 | AK10: =IF(AA10<>AA9, "L5", IF(Z10<>Z9, "L4", IF(Y10<>Y9, "L3", IF(X10<>X9, "L2", IF(W10<>W9, "L1", "L1" ) ) ) ) ) -> L4 | AM10: null | AN10: =IF(EXACT($AK9, "L1"), $W9, AN9) -> 65000000000001 | AO10: =IF(EXACT($AK9, "L1"), $W9, IF(EXACT($AK9, "L2"), $X9, AO9)) -> 65000000000002 | AP10: =IF(EXACT($AK9, "L1"), $W9, IF(EXACT($AK9, "L2"), $X9, IF(EXACT($AK9, "L3"), $Y9, AP9))) -> 65000000000003 | AQ10: =IF(EXACT($AK9, "L1"), $W9, IF(EXACT($AK9, "L2"), $X9, IF(EXACT($AK9, "L3"), $Y9, IF(EXACT($AK9, "L4"), $Z9, AQ9)))) -> 65000000000004 | AS10: =IF(EXACT($AK10, "L1"), AM10, IF(EXACT($AK10, "L2"), AN10, IF(EXACT($AK10, "L3"), AO10, IF(EXACT($AK10, "L4"), AP10, IF(EXACT($AK10, "L5"), AQ10, ""))))) -> 65000000000003 | AU10: =IF(AND(EXACT(B10, ""), EXACT(D10, ""), EXACT(F10, ""), EXACT(H10, ""), EXACT(J10, ""), EXACT(L10, "")), "", CONCATENATE( "PERFORM * FROM ""SchData-OLTP-Accounting"".""Func_TblChartOfAccount_SET""(varSystemLoginSession, null, null, null, varInstitutionBranchID, 62000000000001::bigint,'", IF(EXACT(B10, ""), IF(EXACT(D10, ""), IF(EXACT(F10, ""), IF(EXACT(H10, ""), IF(EXACT(J10, ""), IF(EXACT(L10, ""), "", L10), J10), H10), F10), D10), B10), "', '", IF(EXACT(B10, ""), IF(EXACT(D10, ""), IF(EXACT(F10, ""), IF(EXACT(H10, ""), IF(EXACT(J10, ""), IF(EXACT(L10, ""), "", M10), K10), I10), G10), E10), C10), "', ", IF(EXACT(J10, ""), "62000000000001::bigint", IF((RIGHT(J10, 2)*1 = 1), "62000000000001::bigint", IF((RIGHT(J10, 2)*1 = 2), "62000000000002::bigint", "null"))), ", '2016-01-01 00:00:00'::timestamp, null::timestamp, ", AW10, "::bigint, 66000000000001::bigint);")) -> PERFORM * FROM "SchData-OLTP-Accounting"."Func_TblChartOfAccount_SET"(varSystemLoginSession, null, null, null, varInstitutionBranchID, 62000000000001::bigint,'1-1102', 'Bank', 62000000000001::bigint, '2016-01-01 00:00:00'::timestamp, null::timestamp, 65000000000003::bigint, 66000000000001::bigint); | AV10: =IF(AND(EXACT($B10, ""), EXACT($D10, ""), EXACT($F10, ""), EXACT($H10, ""), EXACT($J10, ""), EXACT($L10, "")), "", V10) -> 65000000000006 | AW10: =AS10 -> 65000000000003 | AY10: =IF(AND(EXACT($B10, ""), EXACT($D10, ""), EXACT($F10, ""), EXACT($H10, ""), EXACT($J10, ""), EXACT($L10, "")), "", IF(NOT(EXACT($B10, "")), "null", IF(NOT(EXACT($D10, "")), IF($W9<>$W8, $W9, $W10), IF(NOT(EXACT($F10, "")), IF($X9<>$X8, $X9, IF($W9<>$W8, $W9, $X10)), IF(NOT(EXACT($H10, "")), IF($Y9<>$Y8, $Y9, IF($X9<>$X8, $X9, IF($W9<>$W8, $W9, $Y10))), IF(NOT(EXACT($J10, "")), IF($Z9<>$Z8, $Z9, IF($Y9<>$Y8, $Y9, IF($X9<>$X8, $X9, IF($W9<>$W8, $W9, $Z10)))), IF(NOT(EXACT($L10, "")), IF($AA9<>$AA8, $AA9, IF($Z9<>$Z8, $Z9, IF($Y9<>$Y8, $Y9, IF($X9<>$X8, $X9, IF($W9<>$W8, $W9, $AA10))))), "others"))))))) -> 65000000000003 | BA10: =BA9 + IF(EXACT(BB10, ""), 0, 1) -> 65000000000006 | BB10: =IF(AND(EXACT($B10, ""), EXACT($D10, ""), EXACT($F10, ""), EXACT($H10, ""), EXACT($J10, ""), EXACT($L10, "")), "", CONCATENATE( "PERFORM * FROM ""SchData-OLTP-Accounting"".""Func_TblChartOfAccount_SET""(varSystemLoginSession, null, null, null, null, null, varInstitutionBranchID, 62000000000001::bigint,'", IF(EXACT($B10, ""), IF(EXACT($D10, ""), IF(EXACT($F10, ""), IF(EXACT($H10, ""), IF(EXACT($J10, ""), IF(EXACT($L10, ""), "", $L10), $J10), $H10), $F10), $D10), $B10), "', '", IF(EXACT($B10, ""), IF(EXACT($D10, ""), IF(EXACT($F10, ""), IF(EXACT($H10, ""), IF(EXACT($J10, ""), IF(EXACT($L10, ""), "", $M10), $K10), $I10), $G10), $E10), $C10), "', ", IF(EXACT($J10, ""), "62000000000001::bigint", IF((RIGHT($J10, 2)*1 = 1), "62000000000001::bigint", IF((RIGHT($J10, 2)*1 = 2), "62000000000002::bigint", "null"))), ", '2016-01-01 00:00:00'::timestamp, null::timestamp, ", $AW10, "::bigint, 66000000000001::bigint, ", IF(EXACT(LEFT(IF(EXACT($B10, ""), IF(EXACT($D10, ""), IF(EXACT($F10, ""), IF(EXACT($H10, ""), IF(EXACT($J10, ""), IF(EXACT($L10, ""), "", $L10), $J10), $H10), $F10), $D10), $B10), 1), "1"), "TRUE", "FALSE"), "::boolean);")) -> PERFORM * FROM "SchData-OLTP-Accounting"."Func_TblChartOfAccount_SET"(varSystemLoginSession, null, null, null, null, null, varInstitutionBranchID, 62000000000001::bigint,'1-1102', 'Bank', 62000000000001::bigint, '2016-01-01 00:00:00'::timestamp, null::timestamp, 65000000000003::bigint, 66000000000001::bigint, TRUE::boolean);
J11: 1-1102.01 | K11: Bank (IDR) | M11: Tag : Bank-IDR | O11: =IF(EXACT($B11, ""), $O10, $B11) -> 1-0000 | P11: =IF(EXACT($D11, ""), $P10, $D11) -> 1-1000 | Q11: =IF(EXACT($F11, ""), $Q10, $F11) -> 1-1100 | R11: =IF(EXACT($H11, ""), $R10, $H11) -> 1-1102 | S11: =IF(EXACT($J11, ""), $S10, $J11) -> 1-1102.01 | T11: =IF(EXACT($L11, ""), $T10, $L11) | V11: =V10+IF(AND(EXACT(B11, ""), EXACT(D11, ""), EXACT(F11, ""), EXACT(H11, ""), EXACT(J11, ""), EXACT(L11, "")), 0, 1) -> 65000000000007 | W11: =IF(EXACT($B11, ""), $W10, $V11) -> 65000000000001 | X11: =IF(EXACT($D11, ""), $X10, $V11) -> 65000000000002 | Y11: =IF(EXACT($F11, ""), $Y10, $V11) -> 65000000000003 | Z11: =IF(EXACT($H11, ""), $Z10, $V11) -> 65000000000006 | AA11: =IF(EXACT($J11, ""), $AA10, $V11) -> 65000000000007 | AB11: =IF(EXACT($L11, ""), $AB10, $V11) -> 65000000000000 | AD11: =AD10 + IF(W11<>W10, 1, 0) -> 1 | AE11: =IF(AD10<>AD11, 1, AE10) + IF(X11<>X10, 1, 0) -> 2 | AF11: =IF(AE10<>AE11, 1, AF10) + IF(Y11<>Y10, 1, 0) -> 2 | AG11: =IF(AF10<>AF11, 1, AG10) + IF(Z11<>Z10, 1, 0) -> 3 | AH11: =IF(AG10<>AG11, 1, AH10) + IF(AA11<>AA10, 1, 0) -> 2 | AI11: =IF(AH10<>AH11, 1, AI10) + IF(AB11<>AB10, 1, 0) -> 1 | AK11: =IF(AA11<>AA10, "L5", IF(Z11<>Z10, "L4", IF(Y11<>Y10, "L3", IF(X11<>X10, "L2", IF(W11<>W10, "L1", "L1" ) ) ) ) ) -> L5 | AM11: null | AN11: =IF(EXACT($AK10, "L1"), $W10, AN10) -> 65000000000001 | AO11: =IF(EXACT($AK10, "L1"), $W10, IF(EXACT($AK10, "L2"), $X10, AO10)) -> 65000000000002 | AP11: =IF(EXACT($AK10, "L1"), $W10, IF(EXACT($AK10, "L2"), $X10, IF(EXACT($AK10, "L3"), $Y10, AP10))) -> 65000000000003 | AQ11: =IF(EXACT($AK10, "L1"), $W10, IF(EXACT($AK10, "L2"), $X10, IF(EXACT($AK10, "L3"), $Y10, IF(EXACT($AK10, "L4"), $Z10, AQ10)))) -> 65000000000006 | AS11: =IF(EXACT($AK11, "L1"), AM11, IF(EXACT($AK11, "L2"), AN11, IF(EXACT($AK11, "L3"), AO11, IF(EXACT($AK11, "L4"), AP11, IF(EXACT($AK11, "L5"), AQ11, ""))))) -> 65000000000006 | AU11: =IF(AND(EXACT(B11, ""), EXACT(D11, ""), EXACT(F11, ""), EXACT(H11, ""), EXACT(J11, ""), EXACT(L11, "")), "", CONCATENATE( "PERFORM * FROM ""SchData-OLTP-Accounting"".""Func_TblChartOfAccount_SET""(varSystemLoginSession, null, null, null, varInstitutionBranchID, 62000000000001::bigint,'", IF(EXACT(B11, ""), IF(EXACT(D11, ""), IF(EXACT(F11, ""), IF(EXACT(H11, ""), IF(EXACT(J11, ""), IF(EXACT(L11, ""), "", L11), J11), H11), F11), D11), B11), "', '", IF(EXACT(B11, ""), IF(EXACT(D11, ""), IF(EXACT(F11, ""), IF(EXACT(H11, ""), IF(EXACT(J11, ""), IF(EXACT(L11, ""), "", M11), K11), I11), G11), E11), C11), "', ", IF(EXACT(J11, ""), "62000000000001::bigint", IF((RIGHT(J11, 2)*1 = 1), "62000000000001::bigint", IF((RIGHT(J11, 2)*1 = 2), "62000000000002::bigint", "null"))), ", '2016-01-01 00:00:00'::timestamp, null::timestamp, ", AW11, "::bigint, 66000000000001::bigint);")) -> PERFORM * FROM "SchData-OLTP-Accounting"."Func_TblChartOfAccount_SET"(varSystemLoginSession, null, null, null, varInstitutionBranchID, 62000000000001::bigint,'1-1102.01', 'Bank (IDR)', 62000000000001::bigint, '2016-01-01 00:00:00'::timestamp, null::timestamp, 65000000000006::bigint, 66000000000001::bigint); | AV11: =IF(AND(EXACT($B11, ""), EXACT($D11, ""), EXACT($F11, ""), EXACT($H11, ""), EXACT($J11, ""), EXACT($L11, "")), "", V11) -> 65000000000007 | AW11: =AS11 -> 65000000000006 | AY11: =IF(AND(EXACT($B11, ""), EXACT($D11, ""), EXACT($F11, ""), EXACT($H11, ""), EXACT($J11, ""), EXACT($L11, "")), "", IF(NOT(EXACT($B11, "")), "null", IF(NOT(EXACT($D11, "")), IF($W10<>$W9, $W10, $W11), IF(NOT(EXACT($F11, "")), IF($X10<>$X9, $X10, IF($W10<>$W9, $W10, $X11)), IF(NOT(EXACT($H11, "")), IF($Y10<>$Y9, $Y10, IF($X10<>$X9, $X10, IF($W10<>$W9, $W10, $Y11))), IF(NOT(EXACT($J11, "")), IF($Z10<>$Z9, $Z10, IF($Y10<>$Y9, $Y10, IF($X10<>$X9, $X10, IF($W10<>$W9, $W10, $Z11)))), IF(NOT(EXACT($L11, "")), IF($AA10<>$AA9, $AA10, IF($Z10<>$Z9, $Z10, IF($Y10<>$Y9, $Y10, IF($X10<>$X9, $X10, IF($W10<>$W9, $W10, $AA11))))), "others"))))))) -> 65000000000006 | BA11: =BA10 + IF(EXACT(BB11, ""), 0, 1) -> 65000000000007 | BB11: =IF(AND(EXACT($B11, ""), EXACT($D11, ""), EXACT($F11, ""), EXACT($H11, ""), EXACT($J11, ""), EXACT($L11, "")), "", CONCATENATE( "PERFORM * FROM ""SchData-OLTP-Accounting"".""Func_TblChartOfAccount_SET""(varSystemLoginSession, null, null, null, null, null, varInstitutionBranchID, 62000000000001::bigint,'", IF(EXACT($B11, ""), IF(EXACT($D11, ""), IF(EXACT($F11, ""), IF(EXACT($H11, ""), IF(EXACT($J11, ""), IF(EXACT($L11, ""), "", $L11), $J11), $H11), $F11), $D11), $B11), "', '", IF(EXACT($B11, ""), IF(EXACT($D11, ""), IF(EXACT($F11, ""), IF(EXACT($H11, ""), IF(EXACT($J11, ""), IF(EXACT($L11, ""), "", $M11), $K11), $I11), $G11), $E11), $C11), "', ", IF(EXACT($J11, ""), "62000000000001::bigint", IF((RIGHT($J11, 2)*1 = 1), "62000000000001::bigint", IF((RIGHT($J11, 2)*1 = 2), "62000000000002::bigint", "null"))), ", '2016-01-01 00:00:00'::timestamp, null::timestamp, ", $AW11, "::bigint, 66000000000001::bigint, ", IF(EXACT(LEFT(IF(EXACT($B11, ""), IF(EXACT($D11, ""), IF(EXACT($F11, ""), IF(EXACT($H11, ""), IF(EXACT($J11, ""), IF(EXACT($L11, ""), "", $L11), $J11), $H11), $F11), $D11), $B11), 1), "1"), "TRUE", "FALSE"), "::boolean);")) -> PERFORM * FROM "SchData-OLTP-Accounting"."Func_TblChartOfAccount_SET"(varSystemLoginSession, null, null, null, null, null, varInstitutionBranchID, 62000000000001::bigint,'1-1102.01', 'Bank (IDR)', 62000000000001::bigint, '2016-01-01 00:00:00'::timestamp, null::timestamp, 65000000000006::bigint, 66000000000001::bigint, TRUE::boolean);
J12: 1-1102.02 | K12: Bank (USD) | M12: Tag : Bank-USD | O12: =IF(EXACT($B12, ""), $O11, $B12) -> 1-0000 | P12: =IF(EXACT($D12, ""), $P11, $D12) -> 1-1000 | Q12: =IF(EXACT($F12, ""), $Q11, $F12) -> 1-1100 | R12: =IF(EXACT($H12, ""), $R11, $H12) -> 1-1102 | S12: =IF(EXACT($J12, ""), $S11, $J12) -> 1-1102.02 | T12: =IF(EXACT($L12, ""), $T11, $L12) | V12: =V11+IF(AND(EXACT(B12, ""), EXACT(D12, ""), EXACT(F12, ""), EXACT(H12, ""), EXACT(J12, ""), EXACT(L12, "")), 0, 1) -> 65000000000008 | W12: =IF(EXACT($B12, ""), $W11, $V12) -> 65000000000001 | X12: =IF(EXACT($D12, ""), $X11, $V12) -> 65000000000002 | Y12: =IF(EXACT($F12, ""), $Y11, $V12) -> 65000000000003 | Z12: =IF(EXACT($H12, ""), $Z11, $V12) -> 65000000000006 | AA12: =IF(EXACT($J12, ""), $AA11, $V12) -> 65000000000008 | AB12: =IF(EXACT($L12, ""), $AB11, $V12) -> 65000000000000 | AD12: =AD11 + IF(W12<>W11, 1, 0) -> 1 | AE12: =IF(AD11<>AD12, 1, AE11) + IF(X12<>X11, 1, 0) -> 2 | AF12: =IF(AE11<>AE12, 1, AF11) + IF(Y12<>Y11, 1, 0) -> 2 | AG12: =IF(AF11<>AF12, 1, AG11) + IF(Z12<>Z11, 1, 0) -> 3 | AH12: =IF(AG11<>AG12, 1, AH11) + IF(AA12<>AA11, 1, 0) -> 3 | AI12: =IF(AH11<>AH12, 1, AI11) + IF(AB12<>AB11, 1, 0) -> 1 | AK12: =IF(AA12<>AA11, "L5", IF(Z12<>Z11, "L4", IF(Y12<>Y11, "L3", IF(X12<>X11, "L2", IF(W12<>W11, "L1", "L1" ) ) ) ) ) -> L5 | AM12: null | AN12: =IF(EXACT($AK11, "L1"), $W11, AN11) -> 65000000000001 | AO12: =IF(EXACT($AK11, "L1"), $W11, IF(EXACT($AK11, "L2"), $X11, AO11)) -> 65000000000002 | AP12: =IF(EXACT($AK11, "L1"), $W11, IF(EXACT($AK11, "L2"), $X11, IF(EXACT($AK11, "L3"), $Y11, AP11))) -> 65000000000003 | AQ12: =IF(EXACT($AK11, "L1"), $W11, IF(EXACT($AK11, "L2"), $X11, IF(EXACT($AK11, "L3"), $Y11, IF(EXACT($AK11, "L4"), $Z11, AQ11)))) -> 65000000000006 | AS12: =IF(EXACT($AK12, "L1"), AM12, IF(EXACT($AK12, "L2"), AN12, IF(EXACT($AK12, "L3"), AO12, IF(EXACT($AK12, "L4"), AP12, IF(EXACT($AK12, "L5"), AQ12, ""))))) -> 65000000000006 | AU12: =IF(AND(EXACT(B12, ""), EXACT(D12, ""), EXACT(F12, ""), EXACT(H12, ""), EXACT(J12, ""), EXACT(L12, "")), "", CONCATENATE( "PERFORM * FROM ""SchData-OLTP-Accounting"".""Func_TblChartOfAccount_SET""(varSystemLoginSession, null, null, null, varInstitutionBranchID, 62000000000001::bigint,'", IF(EXACT(B12, ""), IF(EXACT(D12, ""), IF(EXACT(F12, ""), IF(EXACT(H12, ""), IF(EXACT(J12, ""), IF(EXACT(L12, ""), "", L12), J12), H12), F12), D12), B12), "', '", IF(EXACT(B12, ""), IF(EXACT(D12, ""), IF(EXACT(F12, ""), IF(EXACT(H12, ""), IF(EXACT(J12, ""), IF(EXACT(L12, ""), "", M12), K12), I12), G12), E12), C12), "', ", IF(EXACT(J12, ""), "62000000000001::bigint", IF((RIGHT(J12, 2)*1 = 1), "62000000000001::bigint", IF((RIGHT(J12, 2)*1 = 2), "62000000000002::bigint", "null"))), ", '2016-01-01 00:00:00'::timestamp, null::timestamp, ", AW12, "::bigint, 66000000000001::bigint);")) -> PERFORM * FROM "SchData-OLTP-Accounting"."Func_TblChartOfAccount_SET"(varSystemLoginSession, null, null, null, varInstitutionBranchID, 62000000000001::bigint,'1-1102.02', 'Bank (USD)', 62000000000002::bigint, '2016-01-01 00:00:00'::timestamp, null::timestamp, 65000000000006::bigint, 66000000000001::bigint); | AV12: =IF(AND(EXACT($B12, ""), EXACT($D12, ""), EXACT($F12, ""), EXACT($H12, ""), EXACT($J12, ""), EXACT($L12, "")), "", V12) -> 65000000000008 | AW12: =AS12 -> 65000000000006 | AY12: =IF(AND(EXACT($B12, ""), EXACT($D12, ""), EXACT($F12, ""), EXACT($H12, ""), EXACT($J12, ""), EXACT($L12, "")), "", IF(NOT(EXACT($B12, "")), "null", IF(NOT(EXACT($D12, "")), IF($W11<>$W10, $W11, $W12), IF(NOT(EXACT($F12, "")), IF($X11<>$X10, $X11, IF($W11<>$W10, $W11, $X12)), IF(NOT(EXACT($H12, "")), IF($Y11<>$Y10, $Y11, IF($X11<>$X10, $X11, IF($W11<>$W10, $W11, $Y12))), IF(NOT(EXACT($J12, "")), IF($Z11<>$Z10, $Z11, IF($Y11<>$Y10, $Y11, IF($X11<>$X10, $X11, IF($W11<>$W10, $W11, $Z12)))), IF(NOT(EXACT($L12, "")), IF($AA11<>$AA10, $AA11, IF($Z11<>$Z10, $Z11, IF($Y11<>$Y10, $Y11, IF($X11<>$X10, $X11, IF($W11<>$W10, $W11, $AA12))))), "others"))))))) -> 65000000000006 | BA12: =BA11 + IF(EXACT(BB12, ""), 0, 1) -> 65000000000008 | BB12: =IF(AND(EXACT($B12, ""), EXACT($D12, ""), EXACT($F12, ""), EXACT($H12, ""), EXACT($J12, ""), EXACT($L12, "")), "", CONCATENATE( "PERFORM * FROM ""SchData-OLTP-Accounting"".""Func_TblChartOfAccount_SET""(varSystemLoginSession, null, null, null, null, null, varInstitutionBranchID, 62000000000001::bigint,'", IF(EXACT($B12, ""), IF(EXACT($D12, ""), IF(EXACT($F12, ""), IF(EXACT($H12, ""), IF(EXACT($J12, ""), IF(EXACT($L12, ""), "", $L12), $J12), $H12), $F12), $D12), $B12), "', '", IF(EXACT($B12, ""), IF(EXACT($D12, ""), IF(EXACT($F12, ""), IF(EXACT($H12, ""), IF(EXACT($J12, ""), IF(EXACT($L12, ""), "", $M12), $K12), $I12), $G12), $E12), $C12), "', ", IF(EXACT($J12, ""), "62000000000001::bigint", IF((RIGHT($J12, 2)*1 = 1), "62000000000001::bigint", IF((RIGHT($J12, 2)*1 = 2), "62000000000002::bigint", "null"))), ", '2016-01-01 00:00:00'::timestamp, null::timestamp, ", $AW12, "::bigint, 66000000000001::bigint, ", IF(EXACT(LEFT(IF(EXACT($B12, ""), IF(EXACT($D12, ""), IF(EXACT($F12, ""), IF(EXACT($H12, ""), IF(EXACT($J12, ""), IF(EXACT($L12, ""), "", $L12), $J12), $H12), $F12), $D12), $B12), 1), "1"), "TRUE", "FALSE"), "::boolean);")) -> PERFORM * FROM "SchData-OLTP-Accounting"."Func_TblChartOfAccount_SET"(varSystemLoginSession, null, null, null, null, null, varInstitutionBranchID, 62000000000001::bigint,'1-1102.02', 'Bank (USD)', 62000000000002::bigint, '2016-01-01 00:00:00'::timestamp, null::timestamp, 65000000000006::bigint, 66000000000001::bigint, TRUE::boolean);
F13: 1-1200 | G13: Account Receivable | O13: =IF(EXACT($B13, ""), $O12, $B13) -> 1-0000 | P13: =IF(EXACT($D13, ""), $P12, $D13) -> 1-1000 | Q13: =IF(EXACT($F13, ""), $Q12, $F13) -> 1-1200 | R13: =IF(EXACT($H13, ""), $R12, $H13) -> 1-1102 | S13: =IF(EXACT($J13, ""), $S12, $J13) -> 1-1102.02 | T13: =IF(EXACT($L13, ""), $T12, $L13) | V13: =V12+IF(AND(EXACT(B13, ""), EXACT(D13, ""), EXACT(F13, ""), EXACT(H13, ""), EXACT(J13, ""), EXACT(L13, "")), 0, 1) -> 65000000000009 | W13: =IF(EXACT($B13, ""), $W12, $V13) -> 65000000000001 | X13: =IF(EXACT($D13, ""), $X12, $V13) -> 65000000000002 | Y13: =IF(EXACT($F13, ""), $Y12, $V13) -> 65000000000009 | Z13: =IF(EXACT($H13, ""), $Z12, $V13) -> 65000000000006 | AA13: =IF(EXACT($J13, ""), $AA12, $V13) -> 65000000000008 | AB13: =IF(EXACT($L13, ""), $AB12, $V13) -> 65000000000000 | AD13: =AD12 + IF(W13<>W12, 1, 0) -> 1 | AE13: =IF(AD12<>AD13, 1, AE12) + IF(X13<>X12, 1, 0) -> 2 | AF13: =IF(AE12<>AE13, 1, AF12) + IF(Y13<>Y12, 1, 0) -> 3 | AG13: =IF(AF12<>AF13, 1, AG12) + IF(Z13<>Z12, 1, 0) -> 1 | AH13: =IF(AG12<>AG13, 1, AH12) + IF(AA13<>AA12, 1, 0) -> 1 | AI13: =IF(AH12<>AH13, 1, AI12) + IF(AB13<>AB12, 1, 0) -> 1 | AK13: =IF(AA13<>AA12, "L5", IF(Z13<>Z12, "L4", IF(Y13<>Y12, "L3", IF(X13<>X12, "L2", IF(W13<>W12, "L1", "L1" ) ) ) ) ) -> L3 | AM13: null | AN13: =IF(EXACT($AK12, "L1"), $W12, AN12) -> 65000000000001 | AO13: =IF(EXACT($AK12, "L1"), $W12, IF(EXACT($AK12, "L2"), $X12, AO12)) -> 65000000000002 | AP13: =IF(EXACT($AK12, "L1"), $W12, IF(EXACT($AK12, "L2"), $X12, IF(EXACT($AK12, "L3"), $Y12, AP12))) -> 65000000000003 | AQ13: =IF(EXACT($AK12, "L1"), $W12, IF(EXACT($AK12, "L2"), $X12, IF(EXACT($AK12, "L3"), $Y12, IF(EXACT($AK12, "L4"), $Z12, AQ12)))) -> 65000000000006 | AS13: =IF(EXACT($AK13, "L1"), AM13, IF(EXACT($AK13, "L2"), AN13, IF(EXACT($AK13, "L3"), AO13, IF(EXACT($AK13, "L4"), AP13, IF(EXACT($AK13, "L5"), AQ13, ""))))) -> 65000000000002 | AU13: =IF(AND(EXACT(B13, ""), EXACT(D13, ""), EXACT(F13, ""), EXACT(H13, ""), EXACT(J13, ""), EXACT(L13, "")), "", CONCATENATE( "PERFORM * FROM ""SchData-OLTP-Accounting"".""Func_TblChartOfAccount_SET""(varSystemLoginSession, null, null, null, varInstitutionBranchID, 62000000000001::bigint,'", IF(EXACT(B13, ""), IF(EXACT(D13, ""), IF(EXACT(F13, ""), IF(EXACT(H13, ""), IF(EXACT(J13, ""), IF(EXACT(L13, ""), "", L13), J13), H13), F13), D13), B13), "', '", IF(EXACT(B13, ""), IF(EXACT(D13, ""), IF(EXACT(F13, ""), IF(EXACT(H13, ""), IF(EXACT(J13, ""), IF(EXACT(L13, ""), "", M13), K13), I13), G13), E13), C13), "', ", IF(EXACT(J13, ""), "62000000000001::bigint", IF((RIGHT(J13, 2)*1 = 1), "62000000000001::bigint", IF((RIGHT(J13, 2)*1 = 2), "62000000000002::bigint", "null"))), ", '2016-01-01 00:00:00'::timestamp, null::timestamp, ", AW13, "::bigint, 66000000000001::bigint);")) -> PERFORM * FROM "SchData-OLTP-Accounting"."Func_TblChartOfAccount_SET"(varSystemLoginSession, null, null, null, varInstitutionBranchID, 62000000000001::bigint,'1-1200', 'Account Receivable', 62000000000001::bigint, '2016-01-01 00:00:00'::timestamp, null::timestamp, 65000000000002::bigint, 66000000000001::bigint); | AV13: =IF(AND(EXACT($B13, ""), EXACT($D13, ""), EXACT($F13, ""), EXACT($H13, ""), EXACT($J13, ""), EXACT($L13, "")), "", V13) -> 65000000000009 | AW13: =AS13 -> 65000000000002 | AY13: =IF(AND(EXACT($B13, ""), EXACT($D13, ""), EXACT($F13, ""), EXACT($H13, ""), EXACT($J13, ""), EXACT($L13, "")), "", IF(NOT(EXACT($B13, "")), "null", IF(NOT(EXACT($D13, "")), IF($W12<>$W11, $W12, $W13), IF(NOT(EXACT($F13, "")), IF($X12<>$X11, $X12, IF($W12<>$W11, $W12, $X13)), IF(NOT(EXACT($H13, "")), IF($Y12<>$Y11, $Y12, IF($X12<>$X11, $X12, IF($W12<>$W11, $W12, $Y13))), IF(NOT(EXACT($J13, "")), IF($Z12<>$Z11, $Z12, IF($Y12<>$Y11, $Y12, IF($X12<>$X11, $X12, IF($W12<>$W11, $W12, $Z13)))), IF(NOT(EXACT($L13, "")), IF($AA12<>$AA11, $AA12, IF($Z12<>$Z11, $Z12, IF($Y12<>$Y11, $Y12, IF($X12<>$X11, $X12, IF($W12<>$W11, $W12, $AA13))))), "others"))))))) -> 65000000000002 | BA13: =BA12 + IF(EXACT(BB13, ""), 0, 1) -> 65000000000009 | BB13: =IF(AND(EXACT($B13, ""), EXACT($D13, ""), EXACT($F13, ""), EXACT($H13, ""), EXACT($J13, ""), EXACT($L13, "")), "", CONCATENATE( "PERFORM * FROM ""SchData-OLTP-Accounting"".""Func_TblChartOfAccount_SET""(varSystemLoginSession, null, null, null, null, null, varInstitutionBranchID, 62000000000001::bigint,'", IF(EXACT($B13, ""), IF(EXACT($D13, ""), IF(EXACT($F13, ""), IF(EXACT($H13, ""), IF(EXACT($J13, ""), IF(EXACT($L13, ""), "", $L13), $J13), $H13), $F13), $D13), $B13), "', '", IF(EXACT($B13, ""), IF(EXACT($D13, ""), IF(EXACT($F13, ""), IF(EXACT($H13, ""), IF(EXACT($J13, ""), IF(EXACT($L13, ""), "", $M13), $K13), $I13), $G13), $E13), $C13), "', ", IF(EXACT($J13, ""), "62000000000001::bigint", IF((RIGHT($J13, 2)*1 = 1), "62000000000001::bigint", IF((RIGHT($J13, 2)*1 = 2), "62000000000002::bigint", "null"))), ", '2016-01-01 00:00:00'::timestamp, null::timestamp, ", $AW13, "::bigint, 66000000000001::bigint, ", IF(EXACT(LEFT(IF(EXACT($B13, ""), IF(EXACT($D13, ""), IF(EXACT($F13, ""), IF(EXACT($H13, ""), IF(EXACT($J13, ""), IF(EXACT($L13, ""), "", $L13), $J13), $H13), $F13), $D13), $B13), 1), "1"), "TRUE", "FALSE"), "::boolean);")) -> PERFORM * FROM "SchData-OLTP-Accounting"."Func_TblChartOfAccount_SET"(varSystemLoginSession, null, null, null, null, null, varInstitutionBranchID, 62000000000001::bigint,'1-1200', 'Account Receivable', 62000000000001::bigint, '2016-01-01 00:00:00'::timestamp, null::timestamp, 65000000000002::bigint, 66000000000001::bigint, TRUE::boolean);
H14: 1-1201 | I14: Piutang Usaha | O14: =IF(EXACT($B14, ""), $O13, $B14) -> 1-0000 | P14: =IF(EXACT($D14, ""), $P13, $D14) -> 1-1000 | Q14: =IF(EXACT($F14, ""), $Q13, $F14) -> 1-1200 | R14: =IF(EXACT($H14, ""), $R13, $H14) -> 1-1201 | S14: =IF(EXACT($J14, ""), $S13, $J14) -> 1-1102.02 | T14: =IF(EXACT($L14, ""), $T13, $L14) | V14: =V13+IF(AND(EXACT(B14, ""), EXACT(D14, ""), EXACT(F14, ""), EXACT(H14, ""), EXACT(J14, ""), EXACT(L14, "")), 0, 1) -> 65000000000010 | W14: =IF(EXACT($B14, ""), $W13, $V14) -> 65000000000001 | X14: =IF(EXACT($D14, ""), $X13, $V14) -> 65000000000002 | Y14: =IF(EXACT($F14, ""), $Y13, $V14) -> 65000000000009 | Z14: =IF(EXACT($H14, ""), $Z13, $V14) -> 65000000000010 | AA14: =IF(EXACT($J14, ""), $AA13, $V14) -> 65000000000008 | AB14: =IF(EXACT($L14, ""), $AB13, $V14) -> 65000000000000 | AD14: =AD13 + IF(W14<>W13, 1, 0) -> 1 | AE14: =IF(AD13<>AD14, 1, AE13) + IF(X14<>X13, 1, 0) -> 2 | AF14: =IF(AE13<>AE14, 1, AF13) + IF(Y14<>Y13, 1, 0) -> 3 | AG14: =IF(AF13<>AF14, 1, AG13) + IF(Z14<>Z13, 1, 0) -> 2 | AH14: =IF(AG13<>AG14, 1, AH13) + IF(AA14<>AA13, 1, 0) -> 1 | AI14: =IF(AH13<>AH14, 1, AI13) + IF(AB14<>AB13, 1, 0) -> 1 | AK14: =IF(AA14<>AA13, "L5", IF(Z14<>Z13, "L4", IF(Y14<>Y13, "L3", IF(X14<>X13, "L2", IF(W14<>W13, "L1", "L1" ) ) ) ) ) -> L4 | AM14: null | AN14: =IF(EXACT($AK13, "L1"), $W13, AN13) -> 65000000000001 | AO14: =IF(EXACT($AK13, "L1"), $W13, IF(EXACT($AK13, "L2"), $X13, AO13)) -> 65000000000002 | AP14: =IF(EXACT($AK13, "L1"), $W13, IF(EXACT($AK13, "L2"), $X13, IF(EXACT($AK13, "L3"), $Y13, AP13))) -> 65000000000009 | AQ14: =IF(EXACT($AK13, "L1"), $W13, IF(EXACT($AK13, "L2"), $X13, IF(EXACT($AK13, "L3"), $Y13, IF(EXACT($AK13, "L4"), $Z13, AQ13)))) -> 65000000000009 | AS14: =IF(EXACT($AK14, "L1"), AM14, IF(EXACT($AK14, "L2"), AN14, IF(EXACT($AK14, "L3"), AO14, IF(EXACT($AK14, "L4"), AP14, IF(EXACT($AK14, "L5"), AQ14, ""))))) -> 65000000000009 | AU14: =IF(AND(EXACT(B14, ""), EXACT(D14, ""), EXACT(F14, ""), EXACT(H14, ""), EXACT(J14, ""), EXACT(L14, "")), "", CONCATENATE( "PERFORM * FROM ""SchData-OLTP-Accounting"".""Func_TblChartOfAccount_SET""(varSystemLoginSession, null, null, null, varInstitutionBranchID, 62000000000001::bigint,'", IF(EXACT(B14, ""), IF(EXACT(D14, ""), IF(EXACT(F14, ""), IF(EXACT(H14, ""), IF(EXACT(J14, ""), IF(EXACT(L14, ""), "", L14), J14), H14), F14), D14), B14), "', '", IF(EXACT(B14, ""), IF(EXACT(D14, ""), IF(EXACT(F14, ""), IF(EXACT(H14, ""), IF(EXACT(J14, ""), IF(EXACT(L14, ""), "", M14), K14), I14), G14), E14), C14), "', ", IF(EXACT(J14, ""), "62000000000001::bigint", IF((RIGHT(J14, 2)*1 = 1), "62000000000001::bigint", IF((RIGHT(J14, 2)*1 = 2), "62000000000002::bigint", "null"))), ", '2016-01-01 00:00:00'::timestamp, null::timestamp, ", AW14, "::bigint, 66000000000001::bigint);")) -> PERFORM * FROM "SchData-OLTP-Accounting"."Func_TblChartOfAccount_SET"(varSystemLoginSession, null, null, null, varInstitutionBranchID, 62000000000001::bigint,'1-1201', 'Piutang Usaha', 62000000000001::bigint, '2016-01-01 00:00:00'::timestamp, null::timestamp, 65000000000009::bigint, 66000000000001::bigint); | AV14: =IF(AND(EXACT($B14, ""), EXACT($D14, ""), EXACT($F14, ""), EXACT($H14, ""), EXACT($J14, ""), EXACT($L14, "")), "", V14) -> 65000000000010 | AW14: =AS14 -> 65000000000009 | AY14: =IF(AND(EXACT($B14, ""), EXACT($D14, ""), EXACT($F14, ""), EXACT($H14, ""), EXACT($J14, ""), EXACT($L14, "")), "", IF(NOT(EXACT($B14, "")), "null", IF(NOT(EXACT($D14, "")), IF($W13<>$W12, $W13, $W14), IF(NOT(EXACT($F14, "")), IF($X13<>$X12, $X13, IF($W13<>$W12, $W13, $X14)), IF(NOT(EXACT($H14, "")), IF($Y13<>$Y12, $Y13, IF($X13<>$X12, $X13, IF($W13<>$W12, $W13, $Y14))), IF(NOT(EXACT($J14, "")), IF($Z13<>$Z12, $Z13, IF($Y13<>$Y12, $Y13, IF($X13<>$X12, $X13, IF($W13<>$W12, $W13, $Z14)))), IF(NOT(EXACT($L14, "")), IF($AA13<>$AA12, $AA13, IF($Z13<>$Z12, $Z13, IF($Y13<>$Y12, $Y13, IF($X13<>$X12, $X13, IF($W13<>$W12, $W13, $AA14))))), "others"))))))) -> 65000000000009 | BA14: =BA13 + IF(EXACT(BB14, ""), 0, 1) -> 65000000000010 | BB14: =IF(AND(EXACT($B14, ""), EXACT($D14, ""), EXACT($F14, ""), EXACT($H14, ""), EXACT($J14, ""), EXACT($L14, "")), "", CONCATENATE( "PERFORM * FROM ""SchData-OLTP-Accounting"".""Func_TblChartOfAccount_SET""(varSystemLoginSession, null, null, null, null, null, varInstitutionBranchID, 62000000000001::bigint,'", IF(EXACT($B14, ""), IF(EXACT($D14, ""), IF(EXACT($F14, ""), IF(EXACT($H14, ""), IF(EXACT($J14, ""), IF(EXACT($L14, ""), "", $L14), $J14), $H14), $F14), $D14), $B14), "', '", IF(EXACT($B14, ""), IF(EXACT($D14, ""), IF(EXACT($F14, ""), IF(EXACT($H14, ""), IF(EXACT($J14, ""), IF(EXACT($L14, ""), "", $M14), $K14), $I14), $G14), $E14), $C14), "', ", IF(EXACT($J14, ""), "62000000000001::bigint", IF((RIGHT($J14, 2)*1 = 1), "62000000000001::bigint", IF((RIGHT($J14, 2)*1 = 2), "62000000000002::bigint", "null"))), ", '2016-01-01 00:00:00'::timestamp, null::timestamp, ", $AW14, "::bigint, 66000000000001::bigint, ", IF(EXACT(LEFT(IF(EXACT($B14, ""), IF(EXACT($D14, ""), IF(EXACT($F14, ""), IF(EXACT($H14, ""), IF(EXACT($J14, ""), IF(EXACT($L14, ""), "", $L14), $J14), $H14), $F14), $D14), $B14), 1), "1"), "TRUE", "FALSE"), "::boolean);")) -> PERFORM * FROM "SchData-OLTP-Accounting"."Func_TblChartOfAccount_SET"(varSystemLoginSession, null, null, null, null, null, varInstitutionBranchID, 62000000000001::bigint,'1-1201', 'Piutang Usaha', 62000000000001::bigint, '2016-01-01 00:00:00'::timestamp, null::timestamp, 65000000000009::bigint, 66000000000001::bigint, TRUE::boolean);
J15: 1-1201.01 | K15: AR (IDR) | M15: Tag : Customer-IDR | O15: =IF(EXACT($B15, ""), $O14, $B15) -> 1-0000 | P15: =IF(EXACT($D15, ""), $P14, $D15) -> 1-1000 | Q15: =IF(EXACT($F15, ""), $Q14, $F15) -> 1-1200 | R15: =IF(EXACT($H15, ""), $R14, $H15) -> 1-1201 | S15: =IF(EXACT($J15, ""), $S14, $J15) -> 1-1201.01 | T15: =IF(EXACT($L15, ""), $T14, $L15) | V15: =V14+IF(AND(EXACT(B15, ""), EXACT(D15, ""), EXACT(F15, ""), EXACT(H15, ""), EXACT(J15, ""), EXACT(L15, "")), 0, 1) -> 65000000000011 | W15: =IF(EXACT($B15, ""), $W14, $V15) -> 65000000000001 | X15: =IF(EXACT($D15, ""), $X14, $V15) -> 65000000000002 | Y15: =IF(EXACT($F15, ""), $Y14, $V15) -> 65000000000009 | Z15: =IF(EXACT($H15, ""), $Z14, $V15) -> 65000000000010 | AA15: =IF(EXACT($J15, ""), $AA14, $V15) -> 65000000000011 | AB15: =IF(EXACT($L15, ""), $AB14, $V15) -> 65000000000000 | AD15: =AD14 + IF(W15<>W14, 1, 0) -> 1 | AE15: =IF(AD14<>AD15, 1, AE14) + IF(X15<>X14, 1, 0) -> 2 | AF15: =IF(AE14<>AE15, 1, AF14) + IF(Y15<>Y14, 1, 0) -> 3 | AG15: =IF(AF14<>AF15, 1, AG14) + IF(Z15<>Z14, 1, 0) -> 2 | AH15: =IF(AG14<>AG15, 1, AH14) + IF(AA15<>AA14, 1, 0) -> 2 | AI15: =IF(AH14<>AH15, 1, AI14) + IF(AB15<>AB14, 1, 0) -> 1 | AK15: =IF(AA15<>AA14, "L5", IF(Z15<>Z14, "L4", IF(Y15<>Y14, "L3", IF(X15<>X14, "L2", IF(W15<>W14, "L1", "L1" ) ) ) ) ) -> L5 | AM15: null | AN15: =IF(EXACT($AK14, "L1"), $W14, AN14) -> 65000000000001 | AO15: =IF(EXACT($AK14, "L1"), $W14, IF(EXACT($AK14, "L2"), $X14, AO14)) -> 65000000000002 | AP15: =IF(EXACT($AK14, "L1"), $W14, IF(EXACT($AK14, "L2"), $X14, IF(EXACT($AK14, "L3"), $Y14, AP14))) -> 65000000000009 | AQ15: =IF(EXACT($AK14, "L1"), $W14, IF(EXACT($AK14, "L2"), $X14, IF(EXACT($AK14, "L3"), $Y14, IF(EXACT($AK14, "L4"), $Z14, AQ14)))) -> 65000000000010 | AS15: =IF(EXACT($AK15, "L1"), AM15, IF(EXACT($AK15, "L2"), AN15, IF(EXACT($AK15, "L3"), AO15, IF(EXACT($AK15, "L4"), AP15, IF(EXACT($AK15, "L5"), AQ15, ""))))) -> 65000000000010 | AU15: =IF(AND(EXACT(B15, ""), EXACT(D15, ""), EXACT(F15, ""), EXACT(H15, ""), EXACT(J15, ""), EXACT(L15, "")), "", CONCATENATE( "PERFORM * FROM ""SchData-OLTP-Accounting"".""Func_TblChartOfAccount_SET""(varSystemLoginSession, null, null, null, varInstitutionBranchID, 62000000000001::bigint,'", IF(EXACT(B15, ""), IF(EXACT(D15, ""), IF(EXACT(F15, ""), IF(EXACT(H15, ""), IF(EXACT(J15, ""), IF(EXACT(L15, ""), "", L15), J15), H15), F15), D15), B15), "', '", IF(EXACT(B15, ""), IF(EXACT(D15, ""), IF(EXACT(F15, ""), IF(EXACT(H15, ""), IF(EXACT(J15, ""), IF(EXACT(L15, ""), "", M15), K15), I15), G15), E15), C15), "', ", IF(EXACT(J15, ""), "62000000000001::bigint", IF((RIGHT(J15, 2)*1 = 1), "62000000000001::bigint", IF((RIGHT(J15, 2)*1 = 2), "62000000000002::bigint", "null"))), ", '2016-01-01 00:00:00'::timestamp, null::timestamp, ", AW15, "::bigint, 66000000000001::bigint);")) -> PERFORM * FROM "SchData-OLTP-Accounting"."Func_TblChartOfAccount_SET"(varSystemLoginSession, null, null, null, varInstitutionBranchID, 62000000000001::bigint,'1-1201.01', 'AR (IDR)', 62000000000001::bigint, '2016-01-01 00:00:00'::timestamp, null::timestamp, 65000000000010::bigint, 66000000000001::bigint); | AV15: =IF(AND(EXACT($B15, ""), EXACT($D15, ""), EXACT($F15, ""), EXACT($H15, ""), EXACT($J15, ""), EXACT($L15, "")), "", V15) -> 65000000000011 | AW15: =AS15 -> 65000000000010 | AY15: =IF(AND(EXACT($B15, ""), EXACT($D15, ""), EXACT($F15, ""), EXACT($H15, ""), EXACT($J15, ""), EXACT($L15, "")), "", IF(NOT(EXACT($B15, "")), "null", IF(NOT(EXACT($D15, "")), IF($W14<>$W13, $W14, $W15), IF(NOT(EXACT($F15, "")), IF($X14<>$X13, $X14, IF($W14<>$W13, $W14, $X15)), IF(NOT(EXACT($H15, "")), IF($Y14<>$Y13, $Y14, IF($X14<>$X13, $X14, IF($W14<>$W13, $W14, $Y15))), IF(NOT(EXACT($J15, "")), IF($Z14<>$Z13, $Z14, IF($Y14<>$Y13, $Y14, IF($X14<>$X13, $X14, IF($W14<>$W13, $W14, $Z15)))), IF(NOT(EXACT($L15, "")), IF($AA14<>$AA13, $AA14, IF($Z14<>$Z13, $Z14, IF($Y14<>$Y13, $Y14, IF($X14<>$X13, $X14, IF($W14<>$W13, $W14, $AA15))))), "others"))))))) -> 65000000000010 | BA15: =BA14 + IF(EXACT(BB15, ""), 0, 1) -> 65000000000011 | BB15: =IF(AND(EXACT($B15, ""), EXACT($D15, ""), EXACT($F15, ""), EXACT($H15, ""), EXACT($J15, ""), EXACT($L15, "")), "", CONCATENATE( "PERFORM * FROM ""SchData-OLTP-Accounting"".""Func_TblChartOfAccount_SET""(varSystemLoginSession, null, null, null, null, null, varInstitutionBranchID, 62000000000001::bigint,'", IF(EXACT($B15, ""), IF(EXACT($D15, ""), IF(EXACT($F15, ""), IF(EXACT($H15, ""), IF(EXACT($J15, ""), IF(EXACT($L15, ""), "", $L15), $J15), $H15), $F15), $D15), $B15), "', '", IF(EXACT($B15, ""), IF(EXACT($D15, ""), IF(EXACT($F15, ""), IF(EXACT($H15, ""), IF(EXACT($J15, ""), IF(EXACT($L15, ""), "", $M15), $K15), $I15), $G15), $E15), $C15), "', ", IF(EXACT($J15, ""), "62000000000001::bigint", IF((RIGHT($J15, 2)*1 = 1), "62000000000001::bigint", IF((RIGHT($J15, 2)*1 = 2), "62000000000002::bigint", "null"))), ", '2016-01-01 00:00:00'::timestamp, null::timestamp, ", $AW15, "::bigint, 66000000000001::bigint, ", IF(EXACT(LEFT(IF(EXACT($B15, ""), IF(EXACT($D15, ""), IF(EXACT($F15, ""), IF(EXACT($H15, ""), IF(EXACT($J15, ""), IF(EXACT($L15, ""), "", $L15), $J15), $H15), $F15), $D15), $B15), 1), "1"), "TRUE", "FALSE"), "::boolean);")) -> PERFORM * FROM "SchData-OLTP-Accounting"."Func_TblChartOfAccount_SET"(varSystemLoginSession, null, null, null, null, null, varInstitutionBranchID, 62000000000001::bigint,'1-1201.01', 'AR (IDR)', 62000000000001::bigint, '2016-01-01 00:00:00'::timestamp, null::timestamp, 65000000000010::bigint, 66000000000001::bigint, TRUE::boolean);
J16: 1-1201.02 | K16: AR (USD) | O16: =IF(EXACT($B16, ""), $O15, $B16) -> 1-0000 | P16: =IF(EXACT($D16, ""), $P15, $D16) -> 1-1000 | Q16: =IF(EXACT($F16, ""), $Q15, $F16) -> 1-1200 | R16: =IF(EXACT($H16, ""), $R15, $H16) -> 1-1201 | S16: =IF(EXACT($J16, ""), $S15, $J16) -> 1-1201.02 | T16: =IF(EXACT($L16, ""), $T15, $L16) | V16: =V15+IF(AND(EXACT(B16, ""), EXACT(D16, ""), EXACT(F16, ""), EXACT(H16, ""), EXACT(J16, ""), EXACT(L16, "")), 0, 1) -> 65000000000012 | W16: =IF(EXACT($B16, ""), $W15, $V16) -> 65000000000001 | X16: =IF(EXACT($D16, ""), $X15, $V16) -> 65000000000002 | Y16: =IF(EXACT($F16, ""), $Y15, $V16) -> 65000000000009 | Z16: =IF(EXACT($H16, ""), $Z15, $V16) -> 65000000000010 | AA16: =IF(EXACT($J16, ""), $AA15, $V16) -> 65000000000012 | AB16: =IF(EXACT($L16, ""), $AB15, $V16) -> 65000000000000 | AD16: =AD15 + IF(W16<>W15, 1, 0) -> 1 | AE16: =IF(AD15<>AD16, 1, AE15) + IF(X16<>X15, 1, 0) -> 2 | AF16: =IF(AE15<>AE16, 1, AF15) + IF(Y16<>Y15, 1, 0) -> 3 | AG16: =IF(AF15<>AF16, 1, AG15) + IF(Z16<>Z15, 1, 0) -> 2 | AH16: =IF(AG15<>AG16, 1, AH15) + IF(AA16<>AA15, 1, 0) -> 3 | AI16: =IF(AH15<>AH16, 1, AI15) + IF(AB16<>AB15, 1, 0) -> 1 | AK16: =IF(AA16<>AA15, "L5", IF(Z16<>Z15, "L4", IF(Y16<>Y15, "L3", IF(X16<>X15, "L2", IF(W16<>W15, "L1", "L1" ) ) ) ) ) -> L5 | AM16: null | AN16: =IF(EXACT($AK15, "L1"), $W15, AN15) -> 65000000000001 | AO16: =IF(EXACT($AK15, "L1"), $W15, IF(EXACT($AK15, "L2"), $X15, AO15)) -> 65000000000002 | AP16: =IF(EXACT($AK15, "L1"), $W15, IF(EXACT($AK15, "L2"), $X15, IF(EXACT($AK15, "L3"), $Y15, AP15))) -> 65000000000009 | AQ16: =IF(EXACT($AK15, "L1"), $W15, IF(EXACT($AK15, "L2"), $X15, IF(EXACT($AK15, "L3"), $Y15, IF(EXACT($AK15, "L4"), $Z15, AQ15)))) -> 65000000000010 | AS16: =IF(EXACT($AK16, "L1"), AM16, IF(EXACT($AK16, "L2"), AN16, IF(EXACT($AK16, "L3"), AO16, IF(EXACT($AK16, "L4"), AP16, IF(EXACT($AK16, "L5"), AQ16, ""))))) -> 65000000000010 | AU16: =IF(AND(EXACT(B16, ""), EXACT(D16, ""), EXACT(F16, ""), EXACT(H16, ""), EXACT(J16, ""), EXACT(L16, "")), "", CONCATENATE( "PERFORM * FROM ""SchData-OLTP-Accounting"".""Func_TblChartOfAccount_SET""(varSystemLoginSession, null, null, null, varInstitutionBranchID, 62000000000001::bigint,'", IF(EXACT(B16, ""), IF(EXACT(D16, ""), IF(EXACT(F16, ""), IF(EXACT(H16, ""), IF(EXACT(J16, ""), IF(EXACT(L16, ""), "", L16), J16), H16), F16), D16), B16), "', '", IF(EXACT(B16, ""), IF(EXACT(D16, ""), IF(EXACT(F16, ""), IF(EXACT(H16, ""), IF(EXACT(J16, ""), IF(EXACT(L16, ""), "", M16), K16), I16), G16), E16), C16), "', ", IF(EXACT(J16, ""), "62000000000001::bigint", IF((RIGHT(J16, 2)*1 = 1), "62000000000001::bigint", IF((RIGHT(J16, 2)*1 = 2), "62000000000002::bigint", "null"))), ", '2016-01-01 00:00:00'::timestamp, null::timestamp, ", AW16, "::bigint, 66000000000001::bigint);")) -> PERFORM * FROM "SchData-OLTP-Accounting"."Func_TblChartOfAccount_SET"(varSystemLoginSession, null, null, null, varInstitutionBranchID, 62000000000001::bigint,'1-1201.02', 'AR (USD)', 62000000000002::bigint, '2016-01-01 00:00:00'::timestamp, null::timestamp, 65000000000010::bigint, 66000000000001::bigint); | AV16: =IF(AND(EXACT($B16, ""), EXACT($D16, ""), EXACT($F16, ""), EXACT($H16, ""), EXACT($J16, ""), EXACT($L16, "")), "", V16) -> 65000000000012 | AW16: =AS16 -> 65000000000010 | AY16: =IF(AND(EXACT($B16, ""), EXACT($D16, ""), EXACT($F16, ""), EXACT($H16, ""), EXACT($J16, ""), EXACT($L16, "")), "", IF(NOT(EXACT($B16, "")), "null", IF(NOT(EXACT($D16, "")), IF($W15<>$W14, $W15, $W16), IF(NOT(EXACT($F16, "")), IF($X15<>$X14, $X15, IF($W15<>$W14, $W15, $X16)), IF(NOT(EXACT($H16, "")), IF($Y15<>$Y14, $Y15, IF($X15<>$X14, $X15, IF($W15<>$W14, $W15, $Y16))), IF(NOT(EXACT($J16, "")), IF($Z15<>$Z14, $Z15, IF($Y15<>$Y14, $Y15, IF($X15<>$X14, $X15, IF($W15<>$W14, $W15, $Z16)))), IF(NOT(EXACT($L16, "")), IF($AA15<>$AA14, $AA15, IF($Z15<>$Z14, $Z15, IF($Y15<>$Y14, $Y15, IF($X15<>$X14, $X15, IF($W15<>$W14, $W15, $AA16))))), "others"))))))) -> 65000000000010 | BA16: =BA15 + IF(EXACT(BB16, ""), 0, 1) -> 65000000000012 | BB16: =IF(AND(EXACT($B16, ""), EXACT($D16, ""), EXACT($F16, ""), EXACT($H16, ""), EXACT($J16, ""), EXACT($L16, "")), "", CONCATENATE( "PERFORM * FROM ""SchData-OLTP-Accounting"".""Func_TblChartOfAccount_SET""(varSystemLoginSession, null, null, null, null, null, varInstitutionBranchID, 62000000000001::bigint,'", IF(EXACT($B16, ""), IF(EXACT($D16, ""), IF(EXACT($F16, ""), IF(EXACT($H16, ""), IF(EXACT($J16, ""), IF(EXACT($L16, ""), "", $L16), $J16), $H16), $F16), $D16), $B16), "', '", IF(EXACT($B16, ""), IF(EXACT($D16, ""), IF(EXACT($F16, ""), IF(EXACT($H16, ""), IF(EXACT($J16, ""), IF(EXACT($L16, ""), "", $M16), $K16), $I16), $G16), $E16), $C16), "', ", IF(EXACT($J16, ""), "62000000000001::bigint", IF((RIGHT($J16, 2)*1 = 1), "62000000000001::bigint", IF((RIGHT($J16, 2)*1 = 2), "62000000000002::bigint", "null"))), ", '2016-01-01 00:00:00'::timestamp, null::timestamp, ", $AW16, "::bigint, 66000000000001::bigint, ", IF(EXACT(LEFT(IF(EXACT($B16, ""), IF(EXACT($D16, ""), IF(EXACT($F16, ""), IF(EXACT($H16, ""), IF(EXACT($J16, ""), IF(EXACT($L16, ""), "", $L16), $J16), $H16), $F16), $D16), $B16), 1), "1"), "TRUE", "FALSE"), "::boolean);")) -> PERFORM * FROM "SchData-OLTP-Accounting"."Func_TblChartOfAccount_SET"(varSystemLoginSession, null, null, null, null, null, varInstitutionBranchID, 62000000000001::bigint,'1-1201.02', 'AR (USD)', 62000000000002::bigint, '2016-01-01 00:00:00'::timestamp, null::timestamp, 65000000000010::bigint, 66000000000001::bigint, TRUE::boolean);
H17: 1-1202 | I17: Cadangan Kerugian Piutang | O17: =IF(EXACT($B17, ""), $O16, $B17) -> 1-0000 | P17: =IF(EXACT($D17, ""), $P16, $D17) -> 1-1000 | Q17: =IF(EXACT($F17, ""), $Q16, $F17) -> 1-1200 | R17: =IF(EXACT($H17, ""), $R16, $H17) -> 1-1202 | S17: =IF(EXACT($J17, ""), $S16, $J17) -> 1-1201.02 | T17: =IF(EXACT($L17, ""), $T16, $L17) | V17: =V16+IF(AND(EXACT(B17, ""), EXACT(D17, ""), EXACT(F17, ""), EXACT(H17, ""), EXACT(J17, ""), EXACT(L17, "")), 0, 1) -> 65000000000013 | W17: =IF(EXACT($B17, ""), $W16, $V17) -> 65000000000001 | X17: =IF(EXACT($D17, ""), $X16, $V17) -> 65000000000002 | Y17: =IF(EXACT($F17, ""), $Y16, $V17) -> 65000000000009 | Z17: =IF(EXACT($H17, ""), $Z16, $V17) -> 65000000000013 | AA17: =IF(EXACT($J17, ""), $AA16, $V17) -> 65000000000012 | AB17: =IF(EXACT($L17, ""), $AB16, $V17) -> 65000000000000 | AD17: =AD16 + IF(W17<>W16, 1, 0) -> 1 | AE17: =IF(AD16<>AD17, 1, AE16) + IF(X17<>X16, 1, 0) -> 2 | AF17: =IF(AE16<>AE17, 1, AF16) + IF(Y17<>Y16, 1, 0) -> 3 | AG17: =IF(AF16<>AF17, 1, AG16) + IF(Z17<>Z16, 1, 0) -> 3 | AH17: =IF(AG16<>AG17, 1, AH16) + IF(AA17<>AA16, 1, 0) -> 1 | AI17: =IF(AH16<>AH17, 1, AI16) + IF(AB17<>AB16, 1, 0) -> 1 | AK17: =IF(AA17<>AA16, "L5", IF(Z17<>Z16, "L4", IF(Y17<>Y16, "L3", IF(X17<>X16, "L2", IF(W17<>W16, "L1", "L1" ) ) ) ) ) -> L4 | AM17: null | AN17: =IF(EXACT($AK16, "L1"), $W16, AN16) -> 65000000000001 | AO17: =IF(EXACT($AK16, "L1"), $W16, IF(EXACT($AK16, "L2"), $X16, AO16)) -> 65000000000002 | AP17: =IF(EXACT($AK16, "L1"), $W16, IF(EXACT($AK16, "L2"), $X16, IF(EXACT($AK16, "L3"), $Y16, AP16))) -> 65000000000009 | AQ17: =IF(EXACT($AK16, "L1"), $W16, IF(EXACT($AK16, "L2"), $X16, IF(EXACT($AK16, "L3"), $Y16, IF(EXACT($AK16, "L4"), $Z16, AQ16)))) -> 65000000000010 | AS17: =IF(EXACT($AK17, "L1"), AM17, IF(EXACT($AK17, "L2"), AN17, IF(EXACT($AK17, "L3"), AO17, IF(EXACT($AK17, "L4"), AP17, IF(EXACT($AK17, "L5"), AQ17, ""))))) -> 65000000000009 | AU17: =IF(AND(EXACT(B17, ""), EXACT(D17, ""), EXACT(F17, ""), EXACT(H17, ""), EXACT(J17, ""), EXACT(L17, "")), "", CONCATENATE( "PERFORM * FROM ""SchData-OLTP-Accounting"".""Func_TblChartOfAccount_SET""(varSystemLoginSession, null, null, null, varInstitutionBranchID, 62000000000001::bigint,'", IF(EXACT(B17, ""), IF(EXACT(D17, ""), IF(EXACT(F17, ""), IF(EXACT(H17, ""), IF(EXACT(J17, ""), IF(EXACT(L17, ""), "", L17), J17), H17), F17), D17), B17), "', '", IF(EXACT(B17, ""), IF(EXACT(D17, ""), IF(EXACT(F17, ""), IF(EXACT(H17, ""), IF(EXACT(J17, ""), IF(EXACT(L17, ""), "", M17), K17), I17), G17), E17), C17), "', ", IF(EXACT(J17, ""), "62000000000001::bigint", IF((RIGHT(J17, 2)*1 = 1), "62000000000001::bigint", IF((RIGHT(J17, 2)*1 = 2), "62000000000002::bigint", "null"))), ", '2016-01-01 00:00:00'::timestamp, null::timestamp, ", AW17, "::bigint, 66000000000001::bigint);")) -> PERFORM * FROM "SchData-OLTP-Accounting"."Func_TblChartOfAccount_SET"(varSystemLoginSession, null, null, null, varInstitutionBranchID, 62000000000001::bigint,'1-1202', 'Cadangan Kerugian Piutang', 62000000000001::bigint, '2016-01-01 00:00:00'::timestamp, null::timestamp, 65000000000009::bigint, 66000000000001::bigint); | AV17: =IF(AND(EXACT($B17, ""), EXACT($D17, ""), EXACT($F17, ""), EXACT($H17, ""), EXACT($J17, ""), EXACT($L17, "")), "", V17) -> 65000000000013 | AW17: =AS17 -> 65000000000009 | AY17: =IF(AND(EXACT($B17, ""), EXACT($D17, ""), EXACT($F17, ""), EXACT($H17, ""), EXACT($J17, ""), EXACT($L17, "")), "", IF(NOT(EXACT($B17, "")), "null", IF(NOT(EXACT($D17, "")), IF($W16<>$W15, $W16, $W17), IF(NOT(EXACT($F17, "")), IF($X16<>$X15, $X16, IF($W16<>$W15, $W16, $X17)), IF(NOT(EXACT($H17, "")), IF($Y16<>$Y15, $Y16, IF($X16<>$X15, $X16, IF($W16<>$W15, $W16, $Y17))), IF(NOT(EXACT($J17, "")), IF($Z16<>$Z15, $Z16, IF($Y16<>$Y15, $Y16, IF($X16<>$X15, $X16, IF($W16<>$W15, $W16, $Z17)))), IF(NOT(EXACT($L17, "")), IF($AA16<>$AA15, $AA16, IF($Z16<>$Z15, $Z16, IF($Y16<>$Y15, $Y16, IF($X16<>$X15, $X16, IF($W16<>$W15, $W16, $AA17))))), "others"))))))) -> 65000000000009 | BA17: =BA16 + IF(EXACT(BB17, ""), 0, 1) -> 65000000000013 | BB17: =IF(AND(EXACT($B17, ""), EXACT($D17, ""), EXACT($F17, ""), EXACT($H17, ""), EXACT($J17, ""), EXACT($L17, "")), "", CONCATENATE( "PERFORM * FROM ""SchData-OLTP-Accounting"".""Func_TblChartOfAccount_SET""(varSystemLoginSession, null, null, null, null, null, varInstitutionBranchID, 62000000000001::bigint,'", IF(EXACT($B17, ""), IF(EXACT($D17, ""), IF(EXACT($F17, ""), IF(EXACT($H17, ""), IF(EXACT($J17, ""), IF(EXACT($L17, ""), "", $L17), $J17), $H17), $F17), $D17), $B17), "', '", IF(EXACT($B17, ""), IF(EXACT($D17, ""), IF(EXACT($F17, ""), IF(EXACT($H17, ""), IF(EXACT($J17, ""), IF(EXACT($L17, ""), "", $M17), $K17), $I17), $G17), $E17), $C17), "', ", IF(EXACT($J17, ""), "62000000000001::bigint", IF((RIGHT($J17, 2)*1 = 1), "62000000000001::bigint", IF((RIGHT($J17, 2)*1 = 2), "62000000000002::bigint", "null"))), ", '2016-01-01 00:00:00'::timestamp, null::timestamp, ", $AW17, "::bigint, 66000000000001::bigint, ", IF(EXACT(LEFT(IF(EXACT($B17, ""), IF(EXACT($D17, ""), IF(EXACT($F17, ""), IF(EXACT($H17, ""), IF(EXACT($J17, ""), IF(EXACT($L17, ""), "", $L17), $J17), $H17), $F17), $D17), $B17), 1), "1"), "TRUE", "FALSE"), "::boolean);")) -> PERFORM * FROM "SchData-OLTP-Accounting"."Func_TblChartOfAccount_SET"(varSystemLoginSession, null, null, null, null, null, varInstitutionBranchID, 62000000000001::bigint,'1-1202', 'Cadangan Kerugian Piutang', 62000000000001::bigint, '2016-01-01 00:00:00'::timestamp, null::timestamp, 65000000000009::bigint, 66000000000001::bigint, TRUE::boolean);
J18: 1-1202.01 | K18: Cadangan Kerugian Piutang (IDR) | M18: Tag : Customer-IDR | O18: =IF(EXACT($B18, ""), $O17, $B18) -> 1-0000 | P18: =IF(EXACT($D18, ""), $P17, $D18) -> 1-1000 | Q18: =IF(EXACT($F18, ""), $Q17, $F18) -> 1-1200 | R18: =IF(EXACT($H18, ""), $R17, $H18) -> 1-1202 | S18: =IF(EXACT($J18, ""), $S17, $J18) -> 1-1202.01 | T18: =IF(EXACT($L18, ""), $T17, $L18) | V18: =V17+IF(AND(EXACT(B18, ""), EXACT(D18, ""), EXACT(F18, ""), EXACT(H18, ""), EXACT(J18, ""), EXACT(L18, "")), 0, 1) -> 65000000000014 | W18: =IF(EXACT($B18, ""), $W17, $V18) -> 65000000000001 | X18: =IF(EXACT($D18, ""), $X17, $V18) -> 65000000000002 | Y18: =IF(EXACT($F18, ""), $Y17, $V18) -> 65000000000009 | Z18: =IF(EXACT($H18, ""), $Z17, $V18) -> 65000000000013 | AA18: =IF(EXACT($J18, ""), $AA17, $V18) -> 65000000000014 | AB18: =IF(EXACT($L18, ""), $AB17, $V18) -> 65000000000000 | AD18: =AD17 + IF(W18<>W17, 1, 0) -> 1 | AE18: =IF(AD17<>AD18, 1, AE17) + IF(X18<>X17, 1, 0) -> 2 | AF18: =IF(AE17<>AE18, 1, AF17) + IF(Y18<>Y17, 1, 0) -> 3 | AG18: =IF(AF17<>AF18, 1, AG17) + IF(Z18<>Z17, 1, 0) -> 3 | AH18: =IF(AG17<>AG18, 1, AH17) + IF(AA18<>AA17, 1, 0) -> 2 | AI18: =IF(AH17<>AH18, 1, AI17) + IF(AB18<>AB17, 1, 0) -> 1 | AK18: =IF(AA18<>AA17, "L5", IF(Z18<>Z17, "L4", IF(Y18<>Y17, "L3", IF(X18<>X17, "L2", IF(W18<>W17, "L1", "L1" ) ) ) ) ) -> L5 | AM18: null | AN18: =IF(EXACT($AK17, "L1"), $W17, AN17) -> 65000000000001 | AO18: =IF(EXACT($AK17, "L1"), $W17, IF(EXACT($AK17, "L2"), $X17, AO17)) -> 65000000000002 | AP18: =IF(EXACT($AK17, "L1"), $W17, IF(EXACT($AK17, "L2"), $X17, IF(EXACT($AK17, "L3"), $Y17, AP17))) -> 65000000000009 | AQ18: =IF(EXACT($AK17, "L1"), $W17, IF(EXACT($AK17, "L2"), $X17, IF(EXACT($AK17, "L3"), $Y17, IF(EXACT($AK17, "L4"), $Z17, AQ17)))) -> 65000000000013 | AS18: =IF(EXACT($AK18, "L1"), AM18, IF(EXACT($AK18, "L2"), AN18, IF(EXACT($AK18, "L3"), AO18, IF(EXACT($AK18, "L4"), AP18, IF(EXACT($AK18, "L5"), AQ18, ""))))) -> 65000000000013 | AU18: =IF(AND(EXACT(B18, ""), EXACT(D18, ""), EXACT(F18, ""), EXACT(H18, ""), EXACT(J18, ""), EXACT(L18, "")), "", CONCATENATE( "PERFORM * FROM ""SchData-OLTP-Accounting"".""Func_TblChartOfAccount_SET""(varSystemLoginSession, null, null, null, varInstitutionBranchID, 62000000000001::bigint,'", IF(EXACT(B18, ""), IF(EXACT(D18, ""), IF(EXACT(F18, ""), IF(EXACT(H18, ""), IF(EXACT(J18, ""), IF(EXACT(L18, ""), "", L18), J18), H18), F18), D18), B18), "', '", IF(EXACT(B18, ""), IF(EXACT(D18, ""), IF(EXACT(F18, ""), IF(EXACT(H18, ""), IF(EXACT(J18, ""), IF(EXACT(L18, ""), "", M18), K18), I18), G18), E18), C18), "', ", IF(EXACT(J18, ""), "62000000000001::bigint", IF((RIGHT(J18, 2)*1 = 1), "62000000000001::bigint", IF((RIGHT(J18, 2)*1 = 2), "62000000000002::bigint", "null"))), ", '2016-01-01 00:00:00'::timestamp, null::timestamp, ", AW18, "::bigint, 66000000000001::bigint);")) -> PERFORM * FROM "SchData-OLTP-Accounting"."Func_TblChartOfAccount_SET"(varSystemLoginSession, null, null, null, varInstitutionBranchID, 62000000000001::bigint,'1-1202.01', 'Cadangan Kerugian Piutang (IDR)', 62000000000001::bigint, '2016-01-01 00:00:00'::timestamp, null::timestamp, 65000000000013::bigint, 66000000000001::bigint); | AV18: =IF(AND(EXACT($B18, ""), EXACT($D18, ""), EXACT($F18, ""), EXACT($H18, ""), EXACT($J18, ""), EXACT($L18, "")), "", V18) -> 65000000000014 | AW18: =AS18 -> 65000000000013 | AY18: =IF(AND(EXACT($B18, ""), EXACT($D18, ""), EXACT($F18, ""), EXACT($H18, ""), EXACT($J18, ""), EXACT($L18, "")), "", IF(NOT(EXACT($B18, "")), "null", IF(NOT(EXACT($D18, "")), IF($W17<>$W16, $W17, $W18), IF(NOT(EXACT($F18, "")), IF($X17<>$X16, $X17, IF($W17<>$W16, $W17, $X18)), IF(NOT(EXACT($H18, "")), IF($Y17<>$Y16, $Y17, IF($X17<>$X16, $X17, IF($W17<>$W16, $W17, $Y18))), IF(NOT(EXACT($J18, "")), IF($Z17<>$Z16, $Z17, IF($Y17<>$Y16, $Y17, IF($X17<>$X16, $X17, IF($W17<>$W16, $W17, $Z18)))), IF(NOT(EXACT($L18, "")), IF($AA17<>$AA16, $AA17, IF($Z17<>$Z16, $Z17, IF($Y17<>$Y16, $Y17, IF($X17<>$X16, $X17, IF($W17<>$W16, $W17, $AA18))))), "others"))))))) -> 65000000000013 | BA18: =BA17 + IF(EXACT(BB18, ""), 0, 1) -> 65000000000014 | BB18: =IF(AND(EXACT($B18, ""), EXACT($D18, ""), EXACT($F18, ""), EXACT($H18, ""), EXACT($J18, ""), EXACT($L18, "")), "", CONCATENATE( "PERFORM * FROM ""SchData-OLTP-Accounting"".""Func_TblChartOfAccount_SET""(varSystemLoginSession, null, null, null, null, null, varInstitutionBranchID, 62000000000001::bigint,'", IF(EXACT($B18, ""), IF(EXACT($D18, ""), IF(EXACT($F18, ""), IF(EXACT($H18, ""), IF(EXACT($J18, ""), IF(EXACT($L18, ""), "", $L18), $J18), $H18), $F18), $D18), $B18), "', '", IF(EXACT($B18, ""), IF(EXACT($D18, ""), IF(EXACT($F18, ""), IF(EXACT($H18, ""), IF(EXACT($J18, ""), IF(EXACT($L18, ""), "", $M18), $K18), $I18), $G18), $E18), $C18), "', ", IF(EXACT($J18, ""), "62000000000001::bigint", IF((RIGHT($J18, 2)*1 = 1), "62000000000001::bigint", IF((RIGHT($J18, 2)*1 = 2), "62000000000002::bigint", "null"))), ", '2016-01-01 00:00:00'::timestamp, null::timestamp, ", $AW18, "::bigint, 66000000000001::bigint, ", IF(EXACT(LEFT(IF(EXACT($B18, ""), IF(EXACT($D18, ""), IF(EXACT($F18, ""), IF(EXACT($H18, ""), IF(EXACT($J18, ""), IF(EXACT($L18, ""), "", $L18), $J18), $H18), $F18), $D18), $B18), 1), "1"), "TRUE", "FALSE"), "::boolean);")) -> PERFORM * FROM "SchData-OLTP-Accounting"."Func_TblChartOfAccount_SET"(varSystemLoginSession, null, null, null, null, null, varInstitutionBranchID, 62000000000001::bigint,'1-1202.01', 'Cadangan Kerugian Piutang (IDR)', 62000000000001::bigint, '2016-01-01 00:00:00'::timestamp, null::timestamp, 65000000000013::bigint, 66000000000001::bigint, TRUE::boolean);
J19: 1-1202.02 | K19: Cadangan Kerugian Piutang (USD) | O19: =IF(EXACT($B19, ""), $O18, $B19) -> 1-0000 | P19: =IF(EXACT($D19, ""), $P18, $D19) -> 1-1000 | Q19: =IF(EXACT($F19, ""), $Q18, $F19) -> 1-1200 | R19: =IF(EXACT($H19, ""), $R18, $H19) -> 1-1202 | S19: =IF(EXACT($J19, ""), $S18, $J19) -> 1-1202.02 | T19: =IF(EXACT($L19, ""), $T18, $L19) | V19: =V18+IF(AND(EXACT(B19, ""), EXACT(D19, ""), EXACT(F19, ""), EXACT(H19, ""), EXACT(J19, ""), EXACT(L19, "")), 0, 1) -> 65000000000015 | W19: =IF(EXACT($B19, ""), $W18, $V19) -> 65000000000001 | X19: =IF(EXACT($D19, ""), $X18, $V19) -> 65000000000002 | Y19: =IF(EXACT($F19, ""), $Y18, $V19) -> 65000000000009 | Z19: =IF(EXACT($H19, ""), $Z18, $V19) -> 65000000000013 | AA19: =IF(EXACT($J19, ""), $AA18, $V19) -> 65000000000015 | AB19: =IF(EXACT($L19, ""), $AB18, $V19) -> 65000000000000 | AD19: =AD18 + IF(W19<>W18, 1, 0) -> 1 | AE19: =IF(AD18<>AD19, 1, AE18) + IF(X19<>X18, 1, 0) -> 2 | AF19: =IF(AE18<>AE19, 1, AF18) + IF(Y19<>Y18, 1, 0) -> 3 | AG19: =IF(AF18<>AF19, 1, AG18) + IF(Z19<>Z18, 1, 0) -> 3 | AH19: =IF(AG18<>AG19, 1, AH18) + IF(AA19<>AA18, 1, 0) -> 3 | AI19: =IF(AH18<>AH19, 1, AI18) + IF(AB19<>AB18, 1, 0) -> 1 | AK19: =IF(AA19<>AA18, "L5", IF(Z19<>Z18, "L4", IF(Y19<>Y18, "L3", IF(X19<>X18, "L2", IF(W19<>W18, "L1", "L1" ) ) ) ) ) -> L5 | AM19: null | AN19: =IF(EXACT($AK18, "L1"), $W18, AN18) -> 65000000000001 | AO19: =IF(EXACT($AK18, "L1"), $W18, IF(EXACT($AK18, "L2"), $X18, AO18)) -> 65000000000002 | AP19: =IF(EXACT($AK18, "L1"), $W18, IF(EXACT($AK18, "L2"), $X18, IF(EXACT($AK18, "L3"), $Y18, AP18))) -> 65000000000009 | AQ19: =IF(EXACT($AK18, "L1"), $W18, IF(EXACT($AK18, "L2"), $X18, IF(EXACT($AK18, "L3"), $Y18, IF(EXACT($AK18, "L4"), $Z18, AQ18)))) -> 65000000000013 | AS19: =IF(EXACT($AK19, "L1"), AM19, IF(EXACT($AK19, "L2"), AN19, IF(EXACT($AK19, "L3"), AO19, IF(EXACT($AK19, "L4"), AP19, IF(EXACT($AK19, "L5"), AQ19, ""))))) -> 65000000000013 | AU19: =IF(AND(EXACT(B19, ""), EXACT(D19, ""), EXACT(F19, ""), EXACT(H19, ""), EXACT(J19, ""), EXACT(L19, "")), "", CONCATENATE( "PERFORM * FROM ""SchData-OLTP-Accounting"".""Func_TblChartOfAccount_SET""(varSystemLoginSession, null, null, null, varInstitutionBranchID, 62000000000001::bigint,'", IF(EXACT(B19, ""), IF(EXACT(D19, ""), IF(EXACT(F19, ""), IF(EXACT(H19, ""), IF(EXACT(J19, ""), IF(EXACT(L19, ""), "", L19), J19), H19), F19), D19), B19), "', '", IF(EXACT(B19, ""), IF(EXACT(D19, ""), IF(EXACT(F19, ""), IF(EXACT(H19, ""), IF(EXACT(J19, ""), IF(EXACT(L19, ""), "", M19), K19), I19), G19), E19), C19), "', ", IF(EXACT(J19, ""), "62000000000001::bigint", IF((RIGHT(J19, 2)*1 = 1), "62000000000001::bigint", IF((RIGHT(J19, 2)*1 = 2), "62000000000002::bigint", "null"))), ", '2016-01-01 00:00:00'::timestamp, null::timestamp, ", AW19, "::bigint, 66000000000001::bigint);")) -> PERFORM * FROM "SchData-OLTP-Accounting"."Func_TblChartOfAccount_SET"(varSystemLoginSession, null, null, null, varInstitutionBranchID, 62000000000001::bigint,'1-1202.02', 'Cadangan Kerugian Piutang (USD)', 62000000000002::bigint, '2016-01-01 00:00:00'::timestamp, null::timestamp, 65000000000013::bigint, 66000000000001::bigint); | AV19: =IF(AND(EXACT($B19, ""), EXACT($D19, ""), EXACT($F19, ""), EXACT($H19, ""), EXACT($J19, ""), EXACT($L19, "")), "", V19) -> 65000000000015 | AW19: =AS19 -> 65000000000013 | AY19: =IF(AND(EXACT($B19, ""), EXACT($D19, ""), EXACT($F19, ""), EXACT($H19, ""), EXACT($J19, ""), EXACT($L19, "")), "", IF(NOT(EXACT($B19, "")), "null", IF(NOT(EXACT($D19, "")), IF($W18<>$W17, $W18, $W19), IF(NOT(EXACT($F19, "")), IF($X18<>$X17, $X18, IF($W18<>$W17, $W18, $X19)), IF(NOT(EXACT($H19, "")), IF($Y18<>$Y17, $Y18, IF($X18<>$X17, $X18, IF($W18<>$W17, $W18, $Y19))), IF(NOT(EXACT($J19, "")), IF($Z18<>$Z17, $Z18, IF($Y18<>$Y17, $Y18, IF($X18<>$X17, $X18, IF($W18<>$W17, $W18, $Z19)))), IF(NOT(EXACT($L19, "")), IF($AA18<>$AA17, $AA18, IF($Z18<>$Z17, $Z18, IF($Y18<>$Y17, $Y18, IF($X18<>$X17, $X18, IF($W18<>$W17, $W18, $AA19))))), "others"))))))) -> 65000000000013 | BA19: =BA18 + IF(EXACT(BB19, ""), 0, 1) -> 65000000000015 | BB19: =IF(AND(EXACT($B19, ""), EXACT($D19, ""), EXACT($F19, ""), EXACT($H19, ""), EXACT($J19, ""), EXACT($L19, "")), "", CONCATENATE( "PERFORM * FROM ""SchData-OLTP-Accounting"".""Func_TblChartOfAccount_SET""(varSystemLoginSession, null, null, null, null, null, varInstitutionBranchID, 62000000000001::bigint,'", IF(EXACT($B19, ""), IF(EXACT($D19, ""), IF(EXACT($F19, ""), IF(EXACT($H19, ""), IF(EXACT($J19, ""), IF(EXACT($L19, ""), "", $L19), $J19), $H19), $F19), $D19), $B19), "', '", IF(EXACT($B19, ""), IF(EXACT($D19, ""), IF(EXACT($F19, ""), IF(EXACT($H19, ""), IF(EXACT($J19, ""), IF(EXACT($L19, ""), "", $M19), $K19), $I19), $G19), $E19), $C19), "', ", IF(EXACT($J19, ""), "62000000000001::bigint", IF((RIGHT($J19, 2)*1 = 1), "62000000000001::bigint", IF((RIGHT($J19, 2)*1 = 2), "62000000000002::bigint", "null"))), ", '2016-01-01 00:00:00'::timestamp, null::timestamp, ", $AW19, "::bigint, 66000000000001::bigint, ", IF(EXACT(LEFT(IF(EXACT($B19, ""), IF(EXACT($D19, ""), IF(EXACT($F19, ""), IF(EXACT($H19, ""), IF(EXACT($J19, ""), IF(EXACT($L19, ""), "", $L19), $J19), $H19), $F19), $D19), $B19), 1), "1"), "TRUE", "FALSE"), "::boolean);")) -> PERFORM * FROM "SchData-OLTP-Accounting"."Func_TblChartOfAccount_SET"(varSystemLoginSession, null, null, null, null, null, varInstitutionBranchID, 62000000000001::bigint,'1-1202.02', 'Cadangan Kerugian Piutang (USD)', 62000000000002::bigint, '2016-01-01 00:00:00'::timestamp, null::timestamp, 65000000000013::bigint, 66000000000001::bigint, TRUE::boolean);
H20: 1-1203 | I20: Piutang Non Usaha | O20: =IF(EXACT($B20, ""), $O19, $B20) -> 1-0000 | P20: =IF(EXACT($D20, ""), $P19, $D20) -> 1-1000 | Q20: =IF(EXACT($F20, ""), $Q19, $F20) -> 1-1200 | R20: =IF(EXACT($H20, ""), $R19, $H20) -> 1-1203 | S20: =IF(EXACT($J20, ""), $S19, $J20) -> 1-1202.02 | T20: =IF(EXACT($L20, ""), $T19, $L20) | V20: =V19+IF(AND(EXACT(B20, ""), EXACT(D20, ""), EXACT(F20, ""), EXACT(H20, ""), EXACT(J20, ""), EXACT(L20, "")), 0, 1) -> 65000000000016 | W20: =IF(EXACT($B20, ""), $W19, $V20) -> 65000000000001 | X20: =IF(EXACT($D20, ""), $X19, $V20) -> 65000000000002 | Y20: =IF(EXACT($F20, ""), $Y19, $V20) -> 65000000000009 | Z20: =IF(EXACT($H20, ""), $Z19, $V20) -> 65000000000016 | AA20: =IF(EXACT($J20, ""), $AA19, $V20) -> 65000000000015 | AB20: =IF(EXACT($L20, ""), $AB19, $V20) -> 65000000000000 | AD20: =AD19 + IF(W20<>W19, 1, 0) -> 1 | AE20: =IF(AD19<>AD20, 1, AE19) + IF(X20<>X19, 1, 0) -> 2 | AF20: =IF(AE19<>AE20, 1, AF19) + IF(Y20<>Y19, 1, 0) -> 3 | AG20: =IF(AF19<>AF20, 1, AG19) + IF(Z20<>Z19, 1, 0) -> 4 | AH20: =IF(AG19<>AG20, 1, AH19) + IF(AA20<>AA19, 1, 0) -> 1 | AI20: =IF(AH19<>AH20, 1, AI19) + IF(AB20<>AB19, 1, 0) -> 1 | AK20: =IF(AA20<>AA19, "L5", IF(Z20<>Z19, "L4", IF(Y20<>Y19, "L3", IF(X20<>X19, "L2", IF(W20<>W19, "L1", "L1" ) ) ) ) ) -> L4 | AM20: null | AN20: =IF(EXACT($AK19, "L1"), $W19, AN19) -> 65000000000001 | AO20: =IF(EXACT($AK19, "L1"), $W19, IF(EXACT($AK19, "L2"), $X19, AO19)) -> 65000000000002 | AP20: =IF(EXACT($AK19, "L1"), $W19, IF(EXACT($AK19, "L2"), $X19, IF(EXACT($AK19, "L3"), $Y19, AP19))) -> 65000000000009 | AQ20: =IF(EXACT($AK19, "L1"), $W19, IF(EXACT($AK19, "L2"), $X19, IF(EXACT($AK19, "L3"), $Y19, IF(EXACT($AK19, "L4"), $Z19, AQ19)))) -> 65000000000013 | AS20: =IF(EXACT($AK20, "L1"), AM20, IF(EXACT($AK20, "L2"), AN20, IF(EXACT($AK20, "L3"), AO20, IF(EXACT($AK20, "L4"), AP20, IF(EXACT($AK20, "L5"), AQ20, ""))))) -> 65000000000009 | AU20: =IF(AND(EXACT(B20, ""), EXACT(D20, ""), EXACT(F20, ""), EXACT(H20, ""), EXACT(J20, ""), EXACT(L20, "")), "", CONCATENATE( "PERFORM * FROM ""SchData-OLTP-Accounting"".""Func_TblChartOfAccount_SET""(varSystemLoginSession, null, null, null, varInstitutionBranchID, 62000000000001::bigint,'", IF(EXACT(B20, ""), IF(EXACT(D20, ""), IF(EXACT(F20, ""), IF(EXACT(H20, ""), IF(EXACT(J20, ""), IF(EXACT(L20, ""), "", L20), J20), H20), F20), D20), B20), "', '", IF(EXACT(B20, ""), IF(EXACT(D20, ""), IF(EXACT(F20, ""), IF(EXACT(H20, ""), IF(EXACT(J20, ""), IF(EXACT(L20, ""), "", M20), K20), I20), G20), E20), C20), "', ", IF(EXACT(J20, ""), "62000000000001::bigint", IF((RIGHT(J20, 2)*1 = 1), "62000000000001::bigint", IF((RIGHT(J20, 2)*1 = 2), "62000000000002::bigint", "null"))), ", '2016-01-01 00:00:00'::timestamp, null::timestamp, ", AW20, "::bigint, 66000000000001::bigint);")) -> PERFORM * FROM "SchData-OLTP-Accounting"."Func_TblChartOfAccount_SET"(varSystemLoginSession, null, null, null, varInstitutionBranchID, 62000000000001::bigint,'1-1203', 'Piutang Non Usaha', 62000000000001::bigint, '2016-01-01 00:00:00'::timestamp, null::timestamp, 65000000000009::bigint, 66000000000001::bigint); | AV20: =IF(AND(EXACT($B20, ""), EXACT($D20, ""), EXACT($F20, ""), EXACT($H20, ""), EXACT($J20, ""), EXACT($L20, "")), "", V20) -> 65000000000016 | AW20: =AS20 -> 65000000000009 | AY20: =IF(AND(EXACT($B20, ""), EXACT($D20, ""), EXACT($F20, ""), EXACT($H20, ""), EXACT($J20, ""), EXACT($L20, "")), "", IF(NOT(EXACT($B20, "")), "null", IF(NOT(EXACT($D20, "")), IF($W19<>$W18, $W19, $W20), IF(NOT(EXACT($F20, "")), IF($X19<>$X18, $X19, IF($W19<>$W18, $W19, $X20)), IF(NOT(EXACT($H20, "")), IF($Y19<>$Y18, $Y19, IF($X19<>$X18, $X19, IF($W19<>$W18, $W19, $Y20))), IF(NOT(EXACT($J20, "")), IF($Z19<>$Z18, $Z19, IF($Y19<>$Y18, $Y19, IF($X19<>$X18, $X19, IF($W19<>$W18, $W19, $Z20)))), IF(NOT(EXACT($L20, "")), IF($AA19<>$AA18, $AA19, IF($Z19<>$Z18, $Z19, IF($Y19<>$Y18, $Y19, IF($X19<>$X18, $X19, IF($W19<>$W18, $W19, $AA20))))), "others"))))))) -> 65000000000009 | BA20: =BA19 + IF(EXACT(BB20, ""), 0, 1) -> 65000000000016 | BB20: =IF(AND(EXACT($B20, ""), EXACT($D20, ""), EXACT($F20, ""), EXACT($H20, ""), EXACT($J20, ""), EXACT($L20, "")), "", CONCATENATE( "PERFORM * FROM ""SchData-OLTP-Accounting"".""Func_TblChartOfAccount_SET""(varSystemLoginSession, null, null, null, null, null, varInstitutionBranchID, 62000000000001::bigint,'", IF(EXACT($B20, ""), IF(EXACT($D20, ""), IF(EXACT($F20, ""), IF(EXACT($H20, ""), IF(EXACT($J20, ""), IF(EXACT($L20, ""), "", $L20), $J20), $H20), $F20), $D20), $B20), "', '", IF(EXACT($B20, ""), IF(EXACT($D20, ""), IF(EXACT($F20, ""), IF(EXACT($H20, ""), IF(EXACT($J20, ""), IF(EXACT($L20, ""), "", $M20), $K20), $I20), $G20), $E20), $C20), "', ", IF(EXACT($J20, ""), "62000000000001::bigint", IF((RIGHT($J20, 2)*1 = 1), "62000000000001::bigint", IF((RIGHT($J20, 2)*1 = 2), "62000000000002::bigint", "null"))), ", '2016-01-01 00:00:00'::timestamp, null::timestamp, ", $AW20, "::bigint, 66000000000001::bigint, ", IF(EXACT(LEFT(IF(EXACT($B20, ""), IF(EXACT($D20, ""), IF(EXACT($F20, ""), IF(EXACT($H20, ""), IF(EXACT($J20, ""), IF(EXACT($L20, ""), "", $L20), $J20), $H20), $F20), $D20), $B20), 1), "1"), "TRUE", "FALSE"), "::boolean);")) -> PERFORM * FROM "SchData-OLTP-Accounting"."Func_TblChartOfAccount_SET"(varSystemLoginSession, null, null, null, null, null, varInstitutionBranchID, 62000000000001::bigint,'1-1203', 'Piutang Non Usaha', 62000000000001::bigint, '2016-01-01 00:00:00'::timestamp, null::timestamp, 65000000000009::bigint, 66000000000001::bigint, TRUE::boolean);
J21: 1-1203.01 | K21: Piutang Non Usaha (IDR) | O21: =IF(EXACT($B21, ""), $O20, $B21) -> 1-0000 | P21: =IF(EXACT($D21, ""), $P20, $D21) -> 1-1000 | Q21: =IF(EXACT($F21, ""), $Q20, $F21) -> 1-1200 | R21: =IF(EXACT($H21, ""), $R20, $H21) -> 1-1203 | S21: =IF(EXACT($J21, ""), $S20, $J21) -> 1-1203.01 | T21: =IF(EXACT($L21, ""), $T20, $L21) | V21: =V20+IF(AND(EXACT(B21, ""), EXACT(D21, ""), EXACT(F21, ""), EXACT(H21, ""), EXACT(J21, ""), EXACT(L21, "")), 0, 1) -> 65000000000017 | W21: =IF(EXACT($B21, ""), $W20, $V21) -> 65000000000001 | X21: =IF(EXACT($D21, ""), $X20, $V21) -> 65000000000002 | Y21: =IF(EXACT($F21, ""), $Y20, $V21) -> 65000000000009 | Z21: =IF(EXACT($H21, ""), $Z20, $V21) -> 65000000000016 | AA21: =IF(EXACT($J21, ""), $AA20, $V21) -> 65000000000017 | AB21: =IF(EXACT($L21, ""), $AB20, $V21) -> 65000000000000 | AD21: =AD20 + IF(W21<>W20, 1, 0) -> 1 | AE21: =IF(AD20<>AD21, 1, AE20) + IF(X21<>X20, 1, 0) -> 2 | AF21: =IF(AE20<>AE21, 1, AF20) + IF(Y21<>Y20, 1, 0) -> 3 | AG21: =IF(AF20<>AF21, 1, AG20) + IF(Z21<>Z20, 1, 0) -> 4 | AH21: =IF(AG20<>AG21, 1, AH20) + IF(AA21<>AA20, 1, 0) -> 2 | AI21: =IF(AH20<>AH21, 1, AI20) + IF(AB21<>AB20, 1, 0) -> 1 | AK21: =IF(AA21<>AA20, "L5", IF(Z21<>Z20, "L4", IF(Y21<>Y20, "L3", IF(X21<>X20, "L2", IF(W21<>W20, "L1", "L1" ) ) ) ) ) -> L5 | AM21: null | AN21: =IF(EXACT($AK20, "L1"), $W20, AN20) -> 65000000000001 | AO21: =IF(EXACT($AK20, "L1"), $W20, IF(EXACT($AK20, "L2"), $X20, AO20)) -> 65000000000002 | AP21: =IF(EXACT($AK20, "L1"), $W20, IF(EXACT($AK20, "L2"), $X20, IF(EXACT($AK20, "L3"), $Y20, AP20))) -> 65000000000009 | AQ21: =IF(EXACT($AK20, "L1"), $W20, IF(EXACT($AK20, "L2"), $X20, IF(EXACT($AK20, "L3"), $Y20, IF(EXACT($AK20, "L4"), $Z20, AQ20)))) -> 65000000000016 | AS21: =IF(EXACT($AK21, "L1"), AM21, IF(EXACT($AK21, "L2"), AN21, IF(EXACT($AK21, "L3"), AO21, IF(EXACT($AK21, "L4"), AP21, IF(EXACT($AK21, "L5"), AQ21, ""))))) -> 65000000000016 | AU21: =IF(AND(EXACT(B21, ""), EXACT(D21, ""), EXACT(F21, ""), EXACT(H21, ""), EXACT(J21, ""), EXACT(L21, "")), "", CONCATENATE( "PERFORM * FROM ""SchData-OLTP-Accounting"".""Func_TblChartOfAccount_SET""(varSystemLoginSession, null, null, null, varInstitutionBranchID, 62000000000001::bigint,'", IF(EXACT(B21, ""), IF(EXACT(D21, ""), IF(EXACT(F21, ""), IF(EXACT(H21, ""), IF(EXACT(J21, ""), IF(EXACT(L21, ""), "", L21), J21), H21), F21), D21), B21), "', '", IF(EXACT(B21, ""), IF(EXACT(D21, ""), IF(EXACT(F21, ""), IF(EXACT(H21, ""), IF(EXACT(J21, ""), IF(EXACT(L21, ""), "", M21), K21), I21), G21), E21), C21), "', ", IF(EXACT(J21, ""), "62000000000001::bigint", IF((RIGHT(J21, 2)*1 = 1), "62000000000001::bigint", IF((RIGHT(J21, 2)*1 = 2), "62000000000002::bigint", "null"))), ", '2016-01-01 00:00:00'::timestamp, null::timestamp, ", AW21, "::bigint, 66000000000001::bigint);")) -> PERFORM * FROM "SchData-OLTP-Accounting"."Func_TblChartOfAccount_SET"(varSystemLoginSession, null, null, null, varInstitutionBranchID, 62000000000001::bigint,'1-1203.01', 'Piutang Non Usaha (IDR)', 62000000000001::bigint, '2016-01-01 00:00:00'::timestamp, null::timestamp, 65000000000016::bigint, 66000000000001::bigint); | AV21: =IF(AND(EXACT($B21, ""), EXACT($D21, ""), EXACT($F21, ""), EXACT($H21, ""), EXACT($J21, ""), EXACT($L21, "")), "", V21) -> 65000000000017 | AW21: =AS21 -> 65000000000016 | AY21: =IF(AND(EXACT($B21, ""), EXACT($D21, ""), EXACT($F21, ""), EXACT($H21, ""), EXACT($J21, ""), EXACT($L21, "")), "", IF(NOT(EXACT($B21, "")), "null", IF(NOT(EXACT($D21, "")), IF($W20<>$W19, $W20, $W21), IF(NOT(EXACT($F21, "")), IF($X20<>$X19, $X20, IF($W20<>$W19, $W20, $X21)), IF(NOT(EXACT($H21, "")), IF($Y20<>$Y19, $Y20, IF($X20<>$X19, $X20, IF($W20<>$W19, $W20, $Y21))), IF(NOT(EXACT($J21, "")), IF($Z20<>$Z19, $Z20, IF($Y20<>$Y19, $Y20, IF($X20<>$X19, $X20, IF($W20<>$W19, $W20, $Z21)))), IF(NOT(EXACT($L21, "")), IF($AA20<>$AA19, $AA20, IF($Z20<>$Z19, $Z20, IF($Y20<>$Y19, $Y20, IF($X20<>$X19, $X20, IF($W20<>$W19, $W20, $AA21))))), "others"))))))) -> 65000000000016 | BA21: =BA20 + IF(EXACT(BB21, ""), 0, 1) -> 65000000000017 | BB21: =IF(AND(EXACT($B21, ""), EXACT($D21, ""), EXACT($F21, ""), EXACT($H21, ""), EXACT($J21, ""), EXACT($L21, "")), "", CONCATENATE( "PERFORM * FROM ""SchData-OLTP-Accounting"".""Func_TblChartOfAccount_SET""(varSystemLoginSession, null, null, null, null, null, varInstitutionBranchID, 62000000000001::bigint,'", IF(EXACT($B21, ""), IF(EXACT($D21, ""), IF(EXACT($F21, ""), IF(EXACT($H21, ""), IF(EXACT($J21, ""), IF(EXACT($L21, ""), "", $L21), $J21), $H21), $F21), $D21), $B21), "', '", IF(EXACT($B21, ""), IF(EXACT($D21, ""), IF(EXACT($F21, ""), IF(EXACT($H21, ""), IF(EXACT($J21, ""), IF(EXACT($L21, ""), "", $M21), $K21), $I21), $G21), $E21), $C21), "', ", IF(EXACT($J21, ""), "62000000000001::bigint", IF((RIGHT($J21, 2)*1 = 1), "62000000000001::bigint", IF((RIGHT($J21, 2)*1 = 2), "62000000000002::bigint", "null"))), ", '2016-01-01 00:00:00'::timestamp, null::timestamp, ", $AW21, "::bigint, 66000000000001::bigint, ", IF(EXACT(LEFT(IF(EXACT($B21, ""), IF(EXACT($D21, ""), IF(EXACT($F21, ""), IF(EXACT($H21, ""), IF(EXACT($J21, ""), IF(EXACT($L21, ""), "", $L21), $J21), $H21), $F21), $D21), $B21), 1), "1"), "TRUE", "FALSE"), "::boolean);")) -> PERFORM * FROM "SchData-OLTP-Accounting"."Func_TblChartOfAccount_SET"(varSystemLoginSession, null, null, null, null, null, varInstitutionBranchID, 62000000000001::bigint,'1-1203.01', 'Piutang Non Usaha (IDR)', 62000000000001::bigint, '2016-01-01 00:00:00'::timestamp, null::timestamp, 65000000000016::bigint, 66000000000001::bigint, TRUE::boolean);
J22: 1-1203.02 | K22: Piutang Non Usaha (USD) | O22: =IF(EXACT($B22, ""), $O21, $B22) -> 1-0000 | P22: =IF(EXACT($D22, ""), $P21, $D22) -> 1-1000 | Q22: =IF(EXACT($F22, ""), $Q21, $F22) -> 1-1200 | R22: =IF(EXACT($H22, ""), $R21, $H22) -> 1-1203 | S22: =IF(EXACT($J22, ""), $S21, $J22) -> 1-1203.02 | T22: =IF(EXACT($L22, ""), $T21, $L22) | V22: =V21+IF(AND(EXACT(B22, ""), EXACT(D22, ""), EXACT(F22, ""), EXACT(H22, ""), EXACT(J22, ""), EXACT(L22, "")), 0, 1) -> 65000000000018 | W22: =IF(EXACT($B22, ""), $W21, $V22) -> 65000000000001 | X22: =IF(EXACT($D22, ""), $X21, $V22) -> 65000000000002 | Y22: =IF(EXACT($F22, ""), $Y21, $V22) -> 65000000000009 | Z22: =IF(EXACT($H22, ""), $Z21, $V22) -> 65000000000016 | AA22: =IF(EXACT($J22, ""), $AA21, $V22) -> 65000000000018 | AB22: =IF(EXACT($L22, ""), $AB21, $V22) -> 65000000000000 | AD22: =AD21 + IF(W22<>W21, 1, 0) -> 1 | AE22: =IF(AD21<>AD22, 1, AE21) + IF(X22<>X21, 1, 0) -> 2 | AF22: =IF(AE21<>AE22, 1, AF21) + IF(Y22<>Y21, 1, 0) -> 3 | AG22: =IF(AF21<>AF22, 1, AG21) + IF(Z22<>Z21, 1, 0) -> 4 | AH22: =IF(AG21<>AG22, 1, AH21) + IF(AA22<>AA21, 1, 0) -> 3 | AI22: =IF(AH21<>AH22, 1, AI21) + IF(AB22<>AB21, 1, 0) -> 1 | AK22: =IF(AA22<>AA21, "L5", IF(Z22<>Z21, "L4", IF(Y22<>Y21, "L3", IF(X22<>X21, "L2", IF(W22<>W21, "L1", "L1" ) ) ) ) ) -> L5 | AM22: null | AN22: =IF(EXACT($AK21, "L1"), $W21, AN21) -> 65000000000001 | AO22: =IF(EXACT($AK21, "L1"), $W21, IF(EXACT($AK21, "L2"), $X21, AO21)) -> 65000000000002 | AP22: =IF(EXACT($AK21, "L1"), $W21, IF(EXACT($AK21, "L2"), $X21, IF(EXACT($AK21, "L3"), $Y21, AP21))) -> 65000000000009 | AQ22: =IF(EXACT($AK21, "L1"), $W21, IF(EXACT($AK21, "L2"), $X21, IF(EXACT($AK21, "L3"), $Y21, IF(EXACT($AK21, "L4"), $Z21, AQ21)))) -> 65000000000016 | AS22: =IF(EXACT($AK22, "L1"), AM22, IF(EXACT($AK22, "L2"), AN22, IF(EXACT($AK22, "L3"), AO22, IF(EXACT($AK22, "L4"), AP22, IF(EXACT($AK22, "L5"), AQ22, ""))))) -> 65000000000016 | AU22: =IF(AND(EXACT(B22, ""), EXACT(D22, ""), EXACT(F22, ""), EXACT(H22, ""), EXACT(J22, ""), EXACT(L22, "")), "", CONCATENATE( "PERFORM * FROM ""SchData-OLTP-Accounting"".""Func_TblChartOfAccount_SET""(varSystemLoginSession, null, null, null, varInstitutionBranchID, 62000000000001::bigint,'", IF(EXACT(B22, ""), IF(EXACT(D22, ""), IF(EXACT(F22, ""), IF(EXACT(H22, ""), IF(EXACT(J22, ""), IF(EXACT(L22, ""), "", L22), J22), H22), F22), D22), B22), "', '", IF(EXACT(B22, ""), IF(EXACT(D22, ""), IF(EXACT(F22, ""), IF(EXACT(H22, ""), IF(EXACT(J22, ""), IF(EXACT(L22, ""), "", M22), K22), I22), G22), E22), C22), "', ", IF(EXACT(J22, ""), "62000000000001::bigint", IF((RIGHT(J22, 2)*1 = 1), "62000000000001::bigint", IF((RIGHT(J22, 2)*1 = 2), "62000000000002::bigint", "null"))), ", '2016-01-01 00:00:00'::timestamp, null::timestamp, ", AW22, "::bigint, 66000000000001::bigint);")) -> PERFORM * FROM "SchData-OLTP-Accounting"."Func_TblChartOfAccount_SET"(varSystemLoginSession, null, null, null, varInstitutionBranchID, 62000000000001::bigint,'1-1203.02', 'Piutang Non Usaha (USD)', 62000000000002::bigint, '2016-01-01 00:00:00'::timestamp, null::timestamp, 65000000000016::bigint, 66000000000001::bigint); | AV22: =IF(AND(EXACT($B22, ""), EXACT($D22, ""), EXACT($F22, ""), EXACT($H22, ""), EXACT($J22, ""), EXACT($L22, "")), "", V22) -> 65000000000018 | AW22: =AS22 -> 65000000000016 | AY22: =IF(AND(EXACT($B22, ""), EXACT($D22, ""), EXACT($F22, ""), EXACT($H22, ""), EXACT($J22, ""), EXACT($L22, "")), "", IF(NOT(EXACT($B22, "")), "null", IF(NOT(EXACT($D22, "")), IF($W21<>$W20, $W21, $W22), IF(NOT(EXACT($F22, "")), IF($X21<>$X20, $X21, IF($W21<>$W20, $W21, $X22)), IF(NOT(EXACT($H22, "")), IF($Y21<>$Y20, $Y21, IF($X21<>$X20, $X21, IF($W21<>$W20, $W21, $Y22))), IF(NOT(EXACT($J22, "")), IF($Z21<>$Z20, $Z21, IF($Y21<>$Y20, $Y21, IF($X21<>$X20, $X21, IF($W21<>$W20, $W21, $Z22)))), IF(NOT(EXACT($L22, "")), IF($AA21<>$AA20, $AA21, IF($Z21<>$Z20, $Z21, IF($Y21<>$Y20, $Y21, IF($X21<>$X20, $X21, IF($W21<>$W20, $W21, $AA22))))), "others"))))))) -> 65000000000016 | BA22: =BA21 + IF(EXACT(BB22, ""), 0, 1) -> 65000000000018 | BB22: =IF(AND(EXACT($B22, ""), EXACT($D22, ""), EXACT($F22, ""), EXACT($H22, ""), EXACT($J22, ""), EXACT($L22, "")), "", CONCATENATE( "PERFORM * FROM ""SchData-OLTP-Accounting"".""Func_TblChartOfAccount_SET""(varSystemLoginSession, null, null, null, null, null, varInstitutionBranchID, 62000000000001::bigint,'", IF(EXACT($B22, ""), IF(EXACT($D22, ""), IF(EXACT($F22, ""), IF(EXACT($H22, ""), IF(EXACT($J22, ""), IF(EXACT($L22, ""), "", $L22), $J22), $H22), $F22), $D22), $B22), "', '", IF(EXACT($B22, ""), IF(EXACT($D22, ""), IF(EXACT($F22, ""), IF(EXACT($H22, ""), IF(EXACT($J22, ""), IF(EXACT($L22, ""), "", $M22), $K22), $I22), $G22), $E22), $C22), "', ", IF(EXACT($J22, ""), "62000000000001::bigint", IF((RIGHT($J22, 2)*1 = 1), "62000000000001::bigint", IF((RIGHT($J22, 2)*1 = 2), "62000000000002::bigint", "null"))), ", '2016-01-01 00:00:00'::timestamp, null::timestamp, ", $AW22, "::bigint, 66000000000001::bigint, ", IF(EXACT(LEFT(IF(EXACT($B22, ""), IF(EXACT($D22, ""), IF(EXACT($F22, ""), IF(EXACT($H22, ""), IF(EXACT($J22, ""), IF(EXACT($L22, ""), "", $L22), $J22), $H22), $F22), $D22), $B22), 1), "1"), "TRUE", "FALSE"), "::boolean);")) -> PERFORM * FROM "SchData-OLTP-Accounting"."Func_TblChartOfAccount_SET"(varSystemLoginSession, null, null, null, null, null, varInstitutionBranchID, 62000000000001::bigint,'1-1203.02', 'Piutang Non Usaha (USD)', 62000000000002::bigint, '2016-01-01 00:00:00'::timestamp, null::timestamp, 65000000000016::bigint, 66000000000001::bigint, TRUE::boolean);
H23: 1-1204 | I23: Piutang Antar Perusahaan | O23: =IF(EXACT($B23, ""), $O22, $B23) -> 1-0000 | P23: =IF(EXACT($D23, ""), $P22, $D23) -> 1-1000 | Q23: =IF(EXACT($F23, ""), $Q22, $F23) -> 1-1200 | R23: =IF(EXACT($H23, ""), $R22, $H23) -> 1-1204 | S23: =IF(EXACT($J23, ""), $S22, $J23) -> 1-1203.02 | T23: =IF(EXACT($L23, ""), $T22, $L23) | V23: =V22+IF(AND(EXACT(B23, ""), EXACT(D23, ""), EXACT(F23, ""), EXACT(H23, ""), EXACT(J23, ""), EXACT(L23, "")), 0, 1) -> 65000000000019 | W23: =IF(EXACT($B23, ""), $W22, $V23) -> 65000000000001 | X23: =IF(EXACT($D23, ""), $X22, $V23) -> 65000000000002 | Y23: =IF(EXACT($F23, ""), $Y22, $V23) -> 65000000000009 | Z23: =IF(EXACT($H23, ""), $Z22, $V23) -> 65000000000019 | AA23: =IF(EXACT($J23, ""), $AA22, $V23) -> 65000000000018 | AB23: =IF(EXACT($L23, ""), $AB22, $V23) -> 65000000000000 | AD23: =AD22 + IF(W23<>W22, 1, 0) -> 1 | AE23: =IF(AD22<>AD23, 1, AE22) + IF(X23<>X22, 1, 0) -> 2 | AF23: =IF(AE22<>AE23, 1, AF22) + IF(Y23<>Y22, 1, 0) -> 3 | AG23: =IF(AF22<>AF23, 1, AG22) + IF(Z23<>Z22, 1, 0) -> 5 | AH23: =IF(AG22<>AG23, 1, AH22) + IF(AA23<>AA22, 1, 0) -> 1 | AI23: =IF(AH22<>AH23, 1, AI22) + IF(AB23<>AB22, 1, 0) -> 1 | AK23: =IF(AA23<>AA22, "L5", IF(Z23<>Z22, "L4", IF(Y23<>Y22, "L3", IF(X23<>X22, "L2", IF(W23<>W22, "L1", "L1" ) ) ) ) ) -> L4 | AM23: null | AN23: =IF(EXACT($AK22, "L1"), $W22, AN22) -> 65000000000001 | AO23: =IF(EXACT($AK22, "L1"), $W22, IF(EXACT($AK22, "L2"), $X22, AO22)) -> 65000000000002 | AP23: =IF(EXACT($AK22, "L1"), $W22, IF(EXACT($AK22, "L2"), $X22, IF(EXACT($AK22, "L3"), $Y22, AP22))) -> 65000000000009 | AQ23: =IF(EXACT($AK22, "L1"), $W22, IF(EXACT($AK22, "L2"), $X22, IF(EXACT($AK22, "L3"), $Y22, IF(EXACT($AK22, "L4"), $Z22, AQ22)))) -> 65000000000016 | AS23: =IF(EXACT($AK23, "L1"), AM23, IF(EXACT($AK23, "L2"), AN23, IF(EXACT($AK23, "L3"), AO23, IF(EXACT($AK23, "L4"), AP23, IF(EXACT($AK23, "L5"), AQ23, ""))))) -> 65000000000009 | AU23: =IF(AND(EXACT(B23, ""), EXACT(D23, ""), EXACT(F23, ""), EXACT(H23, ""), EXACT(J23, ""), EXACT(L23, "")), "", CONCATENATE( "PERFORM * FROM ""SchData-OLTP-Accounting"".""Func_TblChartOfAccount_SET""(varSystemLoginSession, null, null, null, varInstitutionBranchID, 62000000000001::bigint,'", IF(EXACT(B23, ""), IF(EXACT(D23, ""), IF(EXACT(F23, ""), IF(EXACT(H23, ""), IF(EXACT(J23, ""), IF(EXACT(L23, ""), "", L23), J23), H23), F23), D23), B23), "', '", IF(EXACT(B23, ""), IF(EXACT(D23, ""), IF(EXACT(F23, ""), IF(EXACT(H23, ""), IF(EXACT(J23, ""), IF(EXACT(L23, ""), "", M23), K23), I23), G23), E23), C23), "', ", IF(EXACT(J23, ""), "62000000000001::bigint", IF((RIGHT(J23, 2)*1 = 1), "62000000000001::bigint", IF((RIGHT(J23, 2)*1 = 2), "62000000000002::bigint", "null"))), ", '2016-01-01 00:00:00'::timestamp, null::timestamp, ", AW23, "::bigint, 66000000000001::bigint);")) -> PERFORM * FROM "SchData-OLTP-Accounting"."Func_TblChartOfAccount_SET"(varSystemLoginSession, null, null, null, varInstitutionBranchID, 62000000000001::bigint,'1-1204', 'Piutang Antar Perusahaan', 62000000000001::bigint, '2016-01-01 00:00:00'::timestamp, null::timestamp, 65000000000009::bigint, 66000000000001::bigint); | AV23: =IF(AND(EXACT($B23, ""), EXACT($D23, ""), EXACT($F23, ""), EXACT($H23, ""), EXACT($J23, ""), EXACT($L23, "")), "", V23) -> 65000000000019 | AW23: =AS23 -> 65000000000009 | AY23: =IF(AND(EXACT($B23, ""), EXACT($D23, ""), EXACT($F23, ""), EXACT($H23, ""), EXACT($J23, ""), EXACT($L23, "")), "", IF(NOT(EXACT($B23, "")), "null", IF(NOT(EXACT($D23, "")), IF($W22<>$W21, $W22, $W23), IF(NOT(EXACT($F23, "")), IF($X22<>$X21, $X22, IF($W22<>$W21, $W22, $X23)), IF(NOT(EXACT($H23, "")), IF($Y22<>$Y21, $Y22, IF($X22<>$X21, $X22, IF($W22<>$W21, $W22, $Y23))), IF(NOT(EXACT($J23, "")), IF($Z22<>$Z21, $Z22, IF($Y22<>$Y21, $Y22, IF($X22<>$X21, $X22, IF($W22<>$W21, $W22, $Z23)))), IF(NOT(EXACT($L23, "")), IF($AA22<>$AA21, $AA22, IF($Z22<>$Z21, $Z22, IF($Y22<>$Y21, $Y22, IF($X22<>$X21, $X22, IF($W22<>$W21, $W22, $AA23))))), "others"))))))) -> 65000000000009 | BA23: =BA22 + IF(EXACT(BB23, ""), 0, 1) -> 65000000000019 | BB23: =IF(AND(EXACT($B23, ""), EXACT($D23, ""), EXACT($F23, ""), EXACT($H23, ""), EXACT($J23, ""), EXACT($L23, "")), "", CONCATENATE( "PERFORM * FROM ""SchData-OLTP-Accounting"".""Func_TblChartOfAccount_SET""(varSystemLoginSession, null, null, null, null, null, varInstitutionBranchID, 62000000000001::bigint,'", IF(EXACT($B23, ""), IF(EXACT($D23, ""), IF(EXACT($F23, ""), IF(EXACT($H23, ""), IF(EXACT($J23, ""), IF(EXACT($L23, ""), "", $L23), $J23), $H23), $F23), $D23), $B23), "', '", IF(EXACT($B23, ""), IF(EXACT($D23, ""), IF(EXACT($F23, ""), IF(EXACT($H23, ""), IF(EXACT($J23, ""), IF(EXACT($L23, ""), "", $M23), $K23), $I23), $G23), $E23), $C23), "', ", IF(EXACT($J23, ""), "62000000000001::bigint", IF((RIGHT($J23, 2)*1 = 1), "62000000000001::bigint", IF((RIGHT($J23, 2)*1 = 2), "62000000000002::bigint", "null"))), ", '2016-01-01 00:00:00'::timestamp, null::timestamp, ", $AW23, "::bigint, 66000000000001::bigint, ", IF(EXACT(LEFT(IF(EXACT($B23, ""), IF(EXACT($D23, ""), IF(EXACT($F23, ""), IF(EXACT($H23, ""), IF(EXACT($J23, ""), IF(EXACT($L23, ""), "", $L23), $J23), $H23), $F23), $D23), $B23), 1), "1"), "TRUE", "FALSE"), "::boolean);")) -> PERFORM * FROM "SchData-OLTP-Accounting"."Func_TblChartOfAccount_SET"(varSystemLoginSession, null, null, null, null, null, varInstitutionBranchID, 62000000000001::bigint,'1-1204', 'Piutang Antar Perusahaan', 62000000000001::bigint, '2016-01-01 00:00:00'::timestamp, null::timestamp, 65000000000009::bigint, 66000000000001::bigint, TRUE::boolean);
J24: 1-1204.01 | K24: Piutang Antar Perusahaan (IDR) | M24: Tag : SisterCompany-IDR | O24: =IF(EXACT($B24, ""), $O23, $B24) -> 1-0000 | P24: =IF(EXACT($D24, ""), $P23, $D24) -> 1-1000 | Q24: =IF(EXACT($F24, ""), $Q23, $F24) -> 1-1200 | R24: =IF(EXACT($H24, ""), $R23, $H24) -> 1-1204 | S24: =IF(EXACT($J24, ""), $S23, $J24) -> 1-1204.01 | T24: =IF(EXACT($L24, ""), $T23, $L24) | V24: =V23+IF(AND(EXACT(B24, ""), EXACT(D24, ""), EXACT(F24, ""), EXACT(H24, ""), EXACT(J24, ""), EXACT(L24, "")), 0, 1) -> 65000000000020 | W24: =IF(EXACT($B24, ""), $W23, $V24) -> 65000000000001 | X24: =IF(EXACT($D24, ""), $X23, $V24) -> 65000000000002 | Y24: =IF(EXACT($F24, ""), $Y23, $V24) -> 65000000000009 | Z24: =IF(EXACT($H24, ""), $Z23, $V24) -> 65000000000019 | AA24: =IF(EXACT($J24, ""), $AA23, $V24) -> 65000000000020 | AB24: =IF(EXACT($L24, ""), $AB23, $V24) -> 65000000000000 | AD24: =AD23 + IF(W24<>W23, 1, 0) -> 1 | AE24: =IF(AD23<>AD24, 1, AE23) + IF(X24<>X23, 1, 0) -> 2 | AF24: =IF(AE23<>AE24, 1, AF23) + IF(Y24<>Y23, 1, 0) -> 3 | AG24: =IF(AF23<>AF24, 1, AG23) + IF(Z24<>Z23, 1, 0) -> 5 | AH24: =IF(AG23<>AG24, 1, AH23) + IF(AA24<>AA23, 1, 0) -> 2 | AI24: =IF(AH23<>AH24, 1, AI23) + IF(AB24<>AB23, 1, 0) -> 1 | AK24: =IF(AA24<>AA23, "L5", IF(Z24<>Z23, "L4", IF(Y24<>Y23, "L3", IF(X24<>X23, "L2", IF(W24<>W23, "L1", "L1" ) ) ) ) ) -> L5 | AM24: null | AN24: =IF(EXACT($AK23, "L1"), $W23, AN23) -> 65000000000001 | AO24: =IF(EXACT($AK23, "L1"), $W23, IF(EXACT($AK23, "L2"), $X23, AO23)) -> 65000000000002 | AP24: =IF(EXACT($AK23, "L1"), $W23, IF(EXACT($AK23, "L2"), $X23, IF(EXACT($AK23, "L3"), $Y23, AP23))) -> 65000000000009 | AQ24: =IF(EXACT($AK23, "L1"), $W23, IF(EXACT($AK23, "L2"), $X23, IF(EXACT($AK23, "L3"), $Y23, IF(EXACT($AK23, "L4"), $Z23, AQ23)))) -> 65000000000019 | AS24: =IF(EXACT($AK24, "L1"), AM24, IF(EXACT($AK24, "L2"), AN24, IF(EXACT($AK24, "L3"), AO24, IF(EXACT($AK24, "L4"), AP24, IF(EXACT($AK24, "L5"), AQ24, ""))))) -> 65000000000019 | AU24: =IF(AND(EXACT(B24, ""), EXACT(D24, ""), EXACT(F24, ""), EXACT(H24, ""), EXACT(J24, ""), EXACT(L24, "")), "", CONCATENATE( "PERFORM * FROM ""SchData-OLTP-Accounting"".""Func_TblChartOfAccount_SET""(varSystemLoginSession, null, null, null, varInstitutionBranchID, 62000000000001::bigint,'", IF(EXACT(B24, ""), IF(EXACT(D24, ""), IF(EXACT(F24, ""), IF(EXACT(H24, ""), IF(EXACT(J24, ""), IF(EXACT(L24, ""), "", L24), J24), H24), F24), D24), B24), "', '", IF(EXACT(B24, ""), IF(EXACT(D24, ""), IF(EXACT(F24, ""), IF(EXACT(H24, ""), IF(EXACT(J24, ""), IF(EXACT(L24, ""), "", M24), K24), I24), G24), E24), C24), "', ", IF(EXACT(J24, ""), "62000000000001::bigint", IF((RIGHT(J24, 2)*1 = 1), "62000000000001::bigint", IF((RIGHT(J24, 2)*1 = 2), "62000000000002::bigint", "null"))), ", '2016-01-01 00:00:00'::timestamp, null::timestamp, ", AW24, "::bigint, 66000000000001::bigint);")) -> PERFORM * FROM "SchData-OLTP-Accounting"."Func_TblChartOfAccount_SET"(varSystemLoginSession, null, null, null, varInstitutionBranchID, 62000000000001::bigint,'1-1204.01', 'Piutang Antar Perusahaan (IDR)', 62000000000001::bigint, '2016-01-01 00:00:00'::timestamp, null::timestamp, 65000000000019::bigint, 66000000000001::bigint); | AV24: =IF(AND(EXACT($B24, ""), EXACT($D24, ""), EXACT($F24, ""), EXACT($H24, ""), EXACT($J24, ""), EXACT($L24, "")), "", V24) -> 65000000000020 | AW24: =AS24 -> 65000000000019 | AY24: =IF(AND(EXACT($B24, ""), EXACT($D24, ""), EXACT($F24, ""), EXACT($H24, ""), EXACT($J24, ""), EXACT($L24, "")), "", IF(NOT(EXACT($B24, "")), "null", IF(NOT(EXACT($D24, "")), IF($W23<>$W22, $W23, $W24), IF(NOT(EXACT($F24, "")), IF($X23<>$X22, $X23, IF($W23<>$W22, $W23, $X24)), IF(NOT(EXACT($H24, "")), IF($Y23<>$Y22, $Y23, IF($X23<>$X22, $X23, IF($W23<>$W22, $W23, $Y24))), IF(NOT(EXACT($J24, "")), IF($Z23<>$Z22, $Z23, IF($Y23<>$Y22, $Y23, IF($X23<>$X22, $X23, IF($W23<>$W22, $W23, $Z24)))), IF(NOT(EXACT($L24, "")), IF($AA23<>$AA22, $AA23, IF($Z23<>$Z22, $Z23, IF($Y23<>$Y22, $Y23, IF($X23<>$X22, $X23, IF($W23<>$W22, $W23, $AA24))))), "others"))))))) -> 65000000000019 | BA24: =BA23 + IF(EXACT(BB24, ""), 0, 1) -> 65000000000020 | BB24: =IF(AND(EXACT($B24, ""), EXACT($D24, ""), EXACT($F24, ""), EXACT($H24, ""), EXACT($J24, ""), EXACT($L24, "")), "", CONCATENATE( "PERFORM * FROM ""SchData-OLTP-Accounting"".""Func_TblChartOfAccount_SET""(varSystemLoginSession, null, null, null, null, null, varInstitutionBranchID, 62000000000001::bigint,'", IF(EXACT($B24, ""), IF(EXACT($D24, ""), IF(EXACT($F24, ""), IF(EXACT($H24, ""), IF(EXACT($J24, ""), IF(EXACT($L24, ""), "", $L24), $J24), $H24), $F24), $D24), $B24), "', '", IF(EXACT($B24, ""), IF(EXACT($D24, ""), IF(EXACT($F24, ""), IF(EXACT($H24, ""), IF(EXACT($J24, ""), IF(EXACT($L24, ""), "", $M24), $K24), $I24), $G24), $E24), $C24), "', ", IF(EXACT($J24, ""), "62000000000001::bigint", IF((RIGHT($J24, 2)*1 = 1), "62000000000001::bigint", IF((RIGHT($J24, 2)*1 = 2), "62000000000002::bigint", "null"))), ", '2016-01-01 00:00:00'::timestamp, null::timestamp, ", $AW24, "::bigint, 66000000000001::bigint, ", IF(EXACT(LEFT(IF(EXACT($B24, ""), IF(EXACT($D24, ""), IF(EXACT($F24, ""), IF(EXACT($H24, ""), IF(EXACT($J24, ""), IF(EXACT($L24, ""), "", $L24), $J24), $H24), $F24), $D24), $B24), 1), "1"), "TRUE", "FALSE"), "::boolean);")) -> PERFORM * FROM "SchData-OLTP-Accounting"."Func_TblChartOfAccount_SET"(varSystemLoginSession, null, null, null, null, null, varInstitutionBranchID, 62000000000001::bigint,'1-1204.01', 'Piutang Antar Perusahaan (IDR)', 62000000000001::bigint, '2016-01-01 00:00:00'::timestamp, null::timestamp, 65000000000019::bigint, 66000000000001::bigint, TRUE::boolean);
J25: 1-1204.02 | K25: Piutang Antar Perusahaan (USD) | O25: =IF(EXACT($B25, ""), $O24, $B25) -> 1-0000 | P25: =IF(EXACT($D25, ""), $P24, $D25) -> 1-1000 | Q25: =IF(EXACT($F25, ""), $Q24, $F25) -> 1-1200 | R25: =IF(EXACT($H25, ""), $R24, $H25) -> 1-1204 | S25: =IF(EXACT($J25, ""), $S24, $J25) -> 1-1204.02 | T25: =IF(EXACT($L25, ""), $T24, $L25) | V25: =V24+IF(AND(EXACT(B25, ""), EXACT(D25, ""), EXACT(F25, ""), EXACT(H25, ""), EXACT(J25, ""), EXACT(L25, "")), 0, 1) -> 65000000000021 | W25: =IF(EXACT($B25, ""), $W24, $V25) -> 65000000000001 | X25: =IF(EXACT($D25, ""), $X24, $V25) -> 65000000000002 | Y25: =IF(EXACT($F25, ""), $Y24, $V25) -> 65000000000009 | Z25: =IF(EXACT($H25, ""), $Z24, $V25) -> 65000000000019 | AA25: =IF(EXACT($J25, ""), $AA24, $V25) -> 65000000000021 | AB25: =IF(EXACT($L25, ""), $AB24, $V25) -> 65000000000000 | AD25: =AD24 + IF(W25<>W24, 1, 0) -> 1 | AE25: =IF(AD24<>AD25, 1, AE24) + IF(X25<>X24, 1, 0) -> 2 | AF25: =IF(AE24<>AE25, 1, AF24) + IF(Y25<>Y24, 1, 0) -> 3 | AG25: =IF(AF24<>AF25, 1, AG24) + IF(Z25<>Z24, 1, 0) -> 5 | AH25: =IF(AG24<>AG25, 1, AH24) + IF(AA25<>AA24, 1, 0) -> 3 | AI25: =IF(AH24<>AH25, 1, AI24) + IF(AB25<>AB24, 1, 0) -> 1 | AK25: =IF(AA25<>AA24, "L5", IF(Z25<>Z24, "L4", IF(Y25<>Y24, "L3", IF(X25<>X24, "L2", IF(W25<>W24, "L1", "L1" ) ) ) ) ) -> L5 | AM25: null | AN25: =IF(EXACT($AK24, "L1"), $W24, AN24) -> 65000000000001 | AO25: =IF(EXACT($AK24, "L1"), $W24, IF(EXACT($AK24, "L2"), $X24, AO24)) -> 65000000000002 | AP25: =IF(EXACT($AK24, "L1"), $W24, IF(EXACT($AK24, "L2"), $X24, IF(EXACT($AK24, "L3"), $Y24, AP24))) -> 65000000000009 | AQ25: =IF(EXACT($AK24, "L1"), $W24, IF(EXACT($AK24, "L2"), $X24, IF(EXACT($AK24, "L3"), $Y24, IF(EXACT($AK24, "L4"), $Z24, AQ24)))) -> 65000000000019 | AS25: =IF(EXACT($AK25, "L1"), AM25, IF(EXACT($AK25, "L2"), AN25, IF(EXACT($AK25, "L3"), AO25, IF(EXACT($AK25, "L4"), AP25, IF(EXACT($AK25, "L5"), AQ25, ""))))) -> 65000000000019 | AU25: =IF(AND(EXACT(B25, ""), EXACT(D25, ""), EXACT(F25, ""), EXACT(H25, ""), EXACT(J25, ""), EXACT(L25, "")), "", CONCATENATE( "PERFORM * FROM ""SchData-OLTP-Accounting"".""Func_TblChartOfAccount_SET""(varSystemLoginSession, null, null, null, varInstitutionBranchID, 62000000000001::bigint,'", IF(EXACT(B25, ""), IF(EXACT(D25, ""), IF(EXACT(F25, ""), IF(EXACT(H25, ""), IF(EXACT(J25, ""), IF(EXACT(L25, ""), "", L25), J25), H25), F25), D25), B25), "', '", IF(EXACT(B25, ""), IF(EXACT(D25, ""), IF(EXACT(F25, ""), IF(EXACT(H25, ""), IF(EXACT(J25, ""), IF(EXACT(L25, ""), "", M25), K25), I25), G25), E25), C25), "', ", IF(EXACT(J25, ""), "62000000000001::bigint", IF((RIGHT(J25, 2)*1 = 1), "62000000000001::bigint", IF((RIGHT(J25, 2)*1 = 2), "62000000000002::bigint", "null"))), ", '2016-01-01 00:00:00'::timestamp, null::timestamp, ", AW25, "::bigint, 66000000000001::bigint);")) -> PERFORM * FROM "SchData-OLTP-Accounting"."Func_TblChartOfAccount_SET"(varSystemLoginSession, null, null, null, varInstitutionBranchID, 62000000000001::bigint,'1-1204.02', 'Piutang Antar Perusahaan (USD)', 62000000000002::bigint, '2016-01-01 00:00:00'::timestamp, null::timestamp, 65000000000019::bigint, 66000000000001::bigint); | AV25: =IF(AND(EXACT($B25, ""), EXACT($D25, ""), EXACT($F25, ""), EXACT($H25, ""), EXACT($J25, ""), EXACT($L25, "")), "", V25) -> 65000000000021 | AW25: =AS25 -> 65000000000019 | AY25: =IF(AND(EXACT($B25, ""), EXACT($D25, ""), EXACT($F25, ""), EXACT($H25, ""), EXACT($J25, ""), EXACT($L25, "")), "", IF(NOT(EXACT($B25, "")), "null", IF(NOT(EXACT($D25, "")), IF($W24<>$W23, $W24, $W25), IF(NOT(EXACT($F25, "")), IF($X24<>$X23, $X24, IF($W24<>$W23, $W24, $X25)), IF(NOT(EXACT($H25, "")), IF($Y24<>$Y23, $Y24, IF($X24<>$X23, $X24, IF($W24<>$W23, $W24, $Y25))), IF(NOT(EXACT($J25, "")), IF($Z24<>$Z23, $Z24, IF($Y24<>$Y23, $Y24, IF($X24<>$X23, $X24, IF($W24<>$W23, $W24, $Z25)))), IF(NOT(EXACT($L25, "")), IF($AA24<>$AA23, $AA24, IF($Z24<>$Z23, $Z24, IF($Y24<>$Y23, $Y24, IF($X24<>$X23, $X24, IF($W24<>$W23, $W24, $AA25))))), "others"))))))) -> 65000000000019 | BA25: =BA24 + IF(EXACT(BB25, ""), 0, 1) -> 65000000000021 | BB25: =IF(AND(EXACT($B25, ""), EXACT($D25, ""), EXACT($F25, ""), EXACT($H25, ""), EXACT($J25, ""), EXACT($L25, "")), "", CONCATENATE( "PERFORM * FROM ""SchData-OLTP-Accounting"".""Func_TblChartOfAccount_SET""(varSystemLoginSession, null, null, null, null, null, varInstitutionBranchID, 62000000000001::bigint,'", IF(EXACT($B25, ""), IF(EXACT($D25, ""), IF(EXACT($F25, ""), IF(EXACT($H25, ""), IF(EXACT($J25, ""), IF(EXACT($L25, ""), "", $L25), $J25), $H25), $F25), $D25), $B25), "', '", IF(EXACT($B25, ""), IF(EXACT($D25, ""), IF(EXACT($F25, ""), IF(EXACT($H25, ""), IF(EXACT($J25, ""), IF(EXACT($L25, ""), "", $M25), $K25), $I25), $G25), $E25), $C25), "', ", IF(EXACT($J25, ""), "62000000000001::bigint", IF((RIGHT($J25, 2)*1 = 1), "62000000000001::bigint", IF((RIGHT($J25, 2)*1 = 2), "62000000000002::bigint", "null"))), ", '2016-01-01 00:00:00'::timestamp, null::timestamp, ", $AW25, "::bigint, 66000000000001::bigint, ", IF(EXACT(LEFT(IF(EXACT($B25, ""), IF(EXACT($D25, ""), IF(EXACT($F25, ""), IF(EXACT($H25, ""), IF(EXACT($J25, ""), IF(EXACT($L25, ""), "", $L25), $J25), $H25), $F25), $D25), $B25), 1), "1"), "TRUE", "FALSE"), "::boolean);")) -> PERFORM * FROM "SchData-OLTP-Accounting"."Func_TblChartOfAccount_SET"(varSystemLoginSession, null, null, null, null, null, varInstitutionBranchID, 62000000000001::bigint,'1-1204.02', 'Piutang Antar Perusahaan (USD)', 62000000000002::bigint, '2016-01-01 00:00:00'::timestamp, null::timestamp, 65000000000019::bigint, 66000000000001::bigint, TRUE::boolean);
F26: 1-1300 | G26: Inventory | O26: =IF(EXACT($B26, ""), $O25, $B26) -> 1-0000 | P26: =IF(EXACT($D26, ""), $P25, $D26) -> 1-1000 | Q26: =IF(EXACT($F26, ""), $Q25, $F26) -> 1-1300 | R26: =IF(EXACT($H26, ""), $R25, $H26) -> 1-1204 | S26: =IF(EXACT($J26, ""), $S25, $J26) -> 1-1204.02 | T26: =IF(EXACT($L26, ""), $T25, $L26) | V26: =V25+IF(AND(EXACT(B26, ""), EXACT(D26, ""), EXACT(F26, ""), EXACT(H26, ""), EXACT(J26, ""), EXACT(L26, "")), 0, 1) -> 65000000000022 | W26: =IF(EXACT($B26, ""), $W25, $V26) -> 65000000000001 | X26: =IF(EXACT($D26, ""), $X25, $V26) -> 65000000000002 | Y26: =IF(EXACT($F26, ""), $Y25, $V26) -> 65000000000022 | Z26: =IF(EXACT($H26, ""), $Z25, $V26) -> 65000000000019 | AA26: =IF(EXACT($J26, ""), $AA25, $V26) -> 65000000000021 | AB26: =IF(EXACT($L26, ""), $AB25, $V26) -> 65000000000000 | AD26: =AD25 + IF(W26<>W25, 1, 0) -> 1 | AE26: =IF(AD25<>AD26, 1, AE25) + IF(X26<>X25, 1, 0) -> 2 | AF26: =IF(AE25<>AE26, 1, AF25) + IF(Y26<>Y25, 1, 0) -> 4 | AG26: =IF(AF25<>AF26, 1, AG25) + IF(Z26<>Z25, 1, 0) -> 1 | AH26: =IF(AG25<>AG26, 1, AH25) + IF(AA26<>AA25, 1, 0) -> 1 | AI26: =IF(AH25<>AH26, 1, AI25) + IF(AB26<>AB25, 1, 0) -> 1 | AK26: =IF(AA26<>AA25, "L5", IF(Z26<>Z25, "L4", IF(Y26<>Y25, "L3", IF(X26<>X25, "L2", IF(W26<>W25, "L1", "L1" ) ) ) ) ) -> L3 | AM26: null | AN26: =IF(EXACT($AK25, "L1"), $W25, AN25) -> 65000000000001 | AO26: =IF(EXACT($AK25, "L1"), $W25, IF(EXACT($AK25, "L2"), $X25, AO25)) -> 65000000000002 | AP26: =IF(EXACT($AK25, "L1"), $W25, IF(EXACT($AK25, "L2"), $X25, IF(EXACT($AK25, "L3"), $Y25, AP25))) -> 65000000000009 | AQ26: =IF(EXACT($AK25, "L1"), $W25, IF(EXACT($AK25, "L2"), $X25, IF(EXACT($AK25, "L3"), $Y25, IF(EXACT($AK25, "L4"), $Z25, AQ25)))) -> 65000000000019 | AS26: =IF(EXACT($AK26, "L1"), AM26, IF(EXACT($AK26, "L2"), AN26, IF(EXACT($AK26, "L3"), AO26, IF(EXACT($AK26, "L4"), AP26, IF(EXACT($AK26, "L5"), AQ26, ""))))) -> 65000000000002 | AU26: =IF(AND(EXACT(B26, ""), EXACT(D26, ""), EXACT(F26, ""), EXACT(H26, ""), EXACT(J26, ""), EXACT(L26, "")), "", CONCATENATE( "PERFORM * FROM ""SchData-OLTP-Accounting"".""Func_TblChartOfAccount_SET""(varSystemLoginSession, null, null, null, varInstitutionBranchID, 62000000000001::bigint,'", IF(EXACT(B26, ""), IF(EXACT(D26, ""), IF(EXACT(F26, ""), IF(EXACT(H26, ""), IF(EXACT(J26, ""), IF(EXACT(L26, ""), "", L26), J26), H26), F26), D26), B26), "', '", IF(EXACT(B26, ""), IF(EXACT(D26, ""), IF(EXACT(F26, ""), IF(EXACT(H26, ""), IF(EXACT(J26, ""), IF(EXACT(L26, ""), "", M26), K26), I26), G26), E26), C26), "', ", IF(EXACT(J26, ""), "62000000000001::bigint", IF((RIGHT(J26, 2)*1 = 1), "62000000000001::bigint", IF((RIGHT(J26, 2)*1 = 2), "62000000000002::bigint", "null"))), ", '2016-01-01 00:00:00'::timestamp, null::timestamp, ", AW26, "::bigint, 66000000000001::bigint);")) -> PERFORM * FROM "SchData-OLTP-Accounting"."Func_TblChartOfAccount_SET"(varSystemLoginSession, null, null, null, varInstitutionBranchID, 62000000000001::bigint,'1-1300', 'Inventory', 62000000000001::bigint, '2016-01-01 00:00:00'::timestamp, null::timestamp, 65000000000002::bigint, 66000000000001::bigint); | AV26: =IF(AND(EXACT($B26, ""), EXACT($D26, ""), EXACT($F26, ""), EXACT($H26, ""), EXACT($J26, ""), EXACT($L26, "")), "", V26) -> 65000000000022 | AW26: =AS26 -> 65000000000002 | AY26: =IF(AND(EXACT($B26, ""), EXACT($D26, ""), EXACT($F26, ""), EXACT($H26, ""), EXACT($J26, ""), EXACT($L26, "")), "", IF(NOT(EXACT($B26, "")), "null", IF(NOT(EXACT($D26, "")), IF($W25<>$W24, $W25, $W26), IF(NOT(EXACT($F26, "")), IF($X25<>$X24, $X25, IF($W25<>$W24, $W25, $X26)), IF(NOT(EXACT($H26, "")), IF($Y25<>$Y24, $Y25, IF($X25<>$X24, $X25, IF($W25<>$W24, $W25, $Y26))), IF(NOT(EXACT($J26, "")), IF($Z25<>$Z24, $Z25, IF($Y25<>$Y24, $Y25, IF($X25<>$X24, $X25, IF($W25<>$W24, $W25, $Z26)))), IF(NOT(EXACT($L26, "")), IF($AA25<>$AA24, $AA25, IF($Z25<>$Z24, $Z25, IF($Y25<>$Y24, $Y25, IF($X25<>$X24, $X25, IF($W25<>$W24, $W25, $AA26))))), "others"))))))) -> 65000000000002 | BA26: =BA25 + IF(EXACT(BB26, ""), 0, 1) -> 65000000000022 | BB26: =IF(AND(EXACT($B26, ""), EXACT($D26, ""), EXACT($F26, ""), EXACT($H26, ""), EXACT($J26, ""), EXACT($L26, "")), "", CONCATENATE( "PERFORM * FROM ""SchData-OLTP-Accounting"".""Func_TblChartOfAccount_SET""(varSystemLoginSession, null, null, null, null, null, varInstitutionBranchID, 62000000000001::bigint,'", IF(EXACT($B26, ""), IF(EXACT($D26, ""), IF(EXACT($F26, ""), IF(EXACT($H26, ""), IF(EXACT($J26, ""), IF(EXACT($L26, ""), "", $L26), $J26), $H26), $F26), $D26), $B26), "', '", IF(EXACT($B26, ""), IF(EXACT($D26, ""), IF(EXACT($F26, ""), IF(EXACT($H26, ""), IF(EXACT($J26, ""), IF(EXACT($L26, ""), "", $M26), $K26), $I26), $G26), $E26), $C26), "', ", IF(EXACT($J26, ""), "62000000000001::bigint", IF((RIGHT($J26, 2)*1 = 1), "62000000000001::bigint", IF((RIGHT($J26, 2)*1 = 2), "62000000000002::bigint", "null"))), ", '2016-01-01 00:00:00'::timestamp, null::timestamp, ", $AW26, "::bigint, 66000000000001::bigint, ", IF(EXACT(LEFT(IF(EXACT($B26, ""), IF(EXACT($D26, ""), IF(EXACT($F26, ""), IF(EXACT($H26, ""), IF(EXACT($J26, ""), IF(EXACT($L26, ""), "", $L26), $J26), $H26), $F26), $D26), $B26), 1), "1"), "TRUE", "FALSE"), "::boolean);")) -> PERFORM * FROM "SchData-OLTP-Accounting"."Func_TblChartOfAccount_SET"(varSystemLoginSession, null, null, null, null, null, varInstitutionBranchID, 62000000000001::bigint,'1-1300', 'Inventory', 62000000000001::bigint, '2016-01-01 00:00:00'::timestamp, null::timestamp, 65000000000002::bigint, 66000000000001::bigint, TRUE::boolean);
H27: 1-1301 | I27: Inventory | O27: =IF(EXACT($B27, ""), $O26, $B27) -> 1-0000 | P27: =IF(EXACT($D27, ""), $P26, $D27) -> 1-1000 | Q27: =IF(EXACT($F27, ""), $Q26, $F27) -> 1-1300 | R27: =IF(EXACT($H27, ""), $R26, $H27) -> 1-1301 | S27: =IF(EXACT($J27, ""), $S26, $J27) -> 1-1204.02 | T27: =IF(EXACT($L27, ""), $T26, $L27) | V27: =V26+IF(AND(EXACT(B27, ""), EXACT(D27, ""), EXACT(F27, ""), EXACT(H27, ""), EXACT(J27, ""), EXACT(L27, "")), 0, 1) -> 65000000000023 | W27: =IF(EXACT($B27, ""), $W26, $V27) -> 65000000000001 | X27: =IF(EXACT($D27, ""), $X26, $V27) -> 65000000000002 | Y27: =IF(EXACT($F27, ""), $Y26, $V27) -> 65000000000022 | Z27: =IF(EXACT($H27, ""), $Z26, $V27) -> 65000000000023 | AA27: =IF(EXACT($J27, ""), $AA26, $V27) -> 65000000000021 | AB27: =IF(EXACT($L27, ""), $AB26, $V27) -> 65000000000000 | AD27: =AD26 + IF(W27<>W26, 1, 0) -> 1 | AE27: =IF(AD26<>AD27, 1, AE26) + IF(X27<>X26, 1, 0) -> 2 | AF27: =IF(AE26<>AE27, 1, AF26) + IF(Y27<>Y26, 1, 0) -> 4 | AG27: =IF(AF26<>AF27, 1, AG26) + IF(Z27<>Z26, 1, 0) -> 2 | AH27: =IF(AG26<>AG27, 1, AH26) + IF(AA27<>AA26, 1, 0) -> 1 | AI27: =IF(AH26<>AH27, 1, AI26) + IF(AB27<>AB26, 1, 0) -> 1 | AK27: =IF(AA27<>AA26, "L5", IF(Z27<>Z26, "L4", IF(Y27<>Y26, "L3", IF(X27<>X26, "L2", IF(W27<>W26, "L1", "L1" ) ) ) ) ) -> L4 | AM27: null | AN27: =IF(EXACT($AK26, "L1"), $W26, AN26) -> 65000000000001 | AO27: =IF(EXACT($AK26, "L1"), $W26, IF(EXACT($AK26, "L2"), $X26, AO26)) -> 65000000000002 | AP27: =IF(EXACT($AK26, "L1"), $W26, IF(EXACT($AK26, "L2"), $X26, IF(EXACT($AK26, "L3"), $Y26, AP26))) -> 65000000000022 | AQ27: =IF(EXACT($AK26, "L1"), $W26, IF(EXACT($AK26, "L2"), $X26, IF(EXACT($AK26, "L3"), $Y26, IF(EXACT($AK26, "L4"), $Z26, AQ26)))) -> 65000000000022 | AS27: =IF(EXACT($AK27, "L1"), AM27, IF(EXACT($AK27, "L2"), AN27, IF(EXACT($AK27, "L3"), AO27, IF(EXACT($AK27, "L4"), AP27, IF(EXACT($AK27, "L5"), AQ27, ""))))) -> 65000000000022 | AU27: =IF(AND(EXACT(B27, ""), EXACT(D27, ""), EXACT(F27, ""), EXACT(H27, ""), EXACT(J27, ""), EXACT(L27, "")), "", CONCATENATE( "PERFORM * FROM ""SchData-OLTP-Accounting"".""Func_TblChartOfAccount_SET""(varSystemLoginSession, null, null, null, varInstitutionBranchID, 62000000000001::bigint,'", IF(EXACT(B27, ""), IF(EXACT(D27, ""), IF(EXACT(F27, ""), IF(EXACT(H27, ""), IF(EXACT(J27, ""), IF(EXACT(L27, ""), "", L27), J27), H27), F27), D27), B27), "', '", IF(EXACT(B27, ""), IF(EXACT(D27, ""), IF(EXACT(F27, ""), IF(EXACT(H27, ""), IF(EXACT(J27, ""), IF(EXACT(L27, ""), "", M27), K27), I27), G27), E27), C27), "', ", IF(EXACT(J27, ""), "62000000000001::bigint", IF((RIGHT(J27, 2)*1 = 1), "62000000000001::bigint", IF((RIGHT(J27, 2)*1 = 2), "62000000000002::bigint", "null"))), ", '2016-01-01 00:00:00'::timestamp, null::timestamp, ", AW27, "::bigint, 66000000000001::bigint);")) -> PERFORM * FROM "SchData-OLTP-Accounting"."Func_TblChartOfAccount_SET"(varSystemLoginSession, null, null, null, varInstitutionBranchID, 62000000000001::bigint,'1-1301', 'Inventory', 62000000000001::bigint, '2016-01-01 00:00:00'::timestamp, null::timestamp, 65000000000022::bigint, 66000000000001::bigint); | AV27: =IF(AND(EXACT($B27, ""), EXACT($D27, ""), EXACT($F27, ""), EXACT($H27, ""), EXACT($J27, ""), EXACT($L27, "")), "", V27) -> 65000000000023 | AW27: =AS27 -> 65000000000022 | AY27: =IF(AND(EXACT($B27, ""), EXACT($D27, ""), EXACT($F27, ""), EXACT($H27, ""), EXACT($J27, ""), EXACT($L27, "")), "", IF(NOT(EXACT($B27, "")), "null", IF(NOT(EXACT($D27, "")), IF($W26<>$W25, $W26, $W27), IF(NOT(EXACT($F27, "")), IF($X26<>$X25, $X26, IF($W26<>$W25, $W26, $X27)), IF(NOT(EXACT($H27, "")), IF($Y26<>$Y25, $Y26, IF($X26<>$X25, $X26, IF($W26<>$W25, $W26, $Y27))), IF(NOT(EXACT($J27, "")), IF($Z26<>$Z25, $Z26, IF($Y26<>$Y25, $Y26, IF($X26<>$X25, $X26, IF($W26<>$W25, $W26, $Z27)))), IF(NOT(EXACT($L27, "")), IF($AA26<>$AA25, $AA26, IF($Z26<>$Z25, $Z26, IF($Y26<>$Y25, $Y26, IF($X26<>$X25, $X26, IF($W26<>$W25, $W26, $AA27))))), "others"))))))) -> 65000000000022 | BA27: =BA26 + IF(EXACT(BB27, ""), 0, 1) -> 65000000000023 | BB27: =IF(AND(EXACT($B27, ""), EXACT($D27, ""), EXACT($F27, ""), EXACT($H27, ""), EXACT($J27, ""), EXACT($L27, "")), "", CONCATENATE( "PERFORM * FROM ""SchData-OLTP-Accounting"".""Func_TblChartOfAccount_SET""(varSystemLoginSession, null, null, null, null, null, varInstitutionBranchID, 62000000000001::bigint,'", IF(EXACT($B27, ""), IF(EXACT($D27, ""), IF(EXACT($F27, ""), IF(EXACT($H27, ""), IF(EXACT($J27, ""), IF(EXACT($L27, ""), "", $L27), $J27), $H27), $F27), $D27), $B27), "', '", IF(EXACT($B27, ""), IF(EXACT($D27, ""), IF(EXACT($F27, ""), IF(EXACT($H27, ""), IF(EXACT($J27, ""), IF(EXACT($L27, ""), "", $M27), $K27), $I27), $G27), $E27), $C27), "', ", IF(EXACT($J27, ""), "62000000000001::bigint", IF((RIGHT($J27, 2)*1 = 1), "62000000000001::bigint", IF((RIGHT($J27, 2)*1 = 2), "62000000000002::bigint", "null"))), ", '2016-01-01 00:00:00'::timestamp, null::timestamp, ", $AW27, "::bigint, 66000000000001::bigint, ", IF(EXACT(LEFT(IF(EXACT($B27, ""), IF(EXACT($D27, ""), IF(EXACT($F27, ""), IF(EXACT($H27, ""), IF(EXACT($J27, ""), IF(EXACT($L27, ""), "", $L27), $J27), $H27), $F27), $D27), $B27), 1), "1"), "TRUE", "FALSE"), "::boolean);")) -> PERFORM * FROM "SchData-OLTP-Accounting"."Func_TblChartOfAccount_SET"(varSystemLoginSession, null, null, null, null, null, varInstitutionBranchID, 62000000000001::bigint,'1-1301', 'Inventory', 62000000000001::bigint, '2016-01-01 00:00:00'::timestamp, null::timestamp, 65000000000022::bigint, 66000000000001::bigint, TRUE::boolean);
J28: 1-1301.01 | K28: Inventory (IDR) | O28: =IF(EXACT($B28, ""), $O27, $B28) -> 1-0000 | P28: =IF(EXACT($D28, ""), $P27, $D28) -> 1-1000 | Q28: =IF(EXACT($F28, ""), $Q27, $F28) -> 1-1300 | R28: =IF(EXACT($H28, ""), $R27, $H28) -> 1-1301 | S28: =IF(EXACT($J28, ""), $S27, $J28) -> 1-1301.01 | T28: =IF(EXACT($L28, ""), $T27, $L28) | V28: =V27+IF(AND(EXACT(B28, ""), EXACT(D28, ""), EXACT(F28, ""), EXACT(H28, ""), EXACT(J28, ""), EXACT(L28, "")), 0, 1) -> 65000000000024 | W28: =IF(EXACT($B28, ""), $W27, $V28) -> 65000000000001 | X28: =IF(EXACT($D28, ""), $X27, $V28) -> 65000000000002 | Y28: =IF(EXACT($F28, ""), $Y27, $V28) -> 65000000000022 | Z28: =IF(EXACT($H28, ""), $Z27, $V28) -> 65000000000023 | AA28: =IF(EXACT($J28, ""), $AA27, $V28) -> 65000000000024 | AB28: =IF(EXACT($L28, ""), $AB27, $V28) -> 65000000000000 | AD28: =AD27 + IF(W28<>W27, 1, 0) -> 1 | AE28: =IF(AD27<>AD28, 1, AE27) + IF(X28<>X27, 1, 0) -> 2 | AF28: =IF(AE27<>AE28, 1, AF27) + IF(Y28<>Y27, 1, 0) -> 4 | AG28: =IF(AF27<>AF28, 1, AG27) + IF(Z28<>Z27, 1, 0) -> 2 | AH28: =IF(AG27<>AG28, 1, AH27) + IF(AA28<>AA27, 1, 0) -> 2 | AI28: =IF(AH27<>AH28, 1, AI27) + IF(AB28<>AB27, 1, 0) -> 1 | AK28: =IF(AA28<>AA27, "L5", IF(Z28<>Z27, "L4", IF(Y28<>Y27, "L3", IF(X28<>X27, "L2", IF(W28<>W27, "L1", "L1" ) ) ) ) ) -> L5 | AM28: null | AN28: =IF(EXACT($AK27, "L1"), $W27, AN27) -> 65000000000001 | AO28: =IF(EXACT($AK27, "L1"), $W27, IF(EXACT($AK27, "L2"), $X27, AO27)) -> 65000000000002 | AP28: =IF(EXACT($AK27, "L1"), $W27, IF(EXACT($AK27, "L2"), $X27, IF(EXACT($AK27, "L3"), $Y27, AP27))) -> 65000000000022 | AQ28: =IF(EXACT($AK27, "L1"), $W27, IF(EXACT($AK27, "L2"), $X27, IF(EXACT($AK27, "L3"), $Y27, IF(EXACT($AK27, "L4"), $Z27, AQ27)))) -> 65000000000023 | AS28: =IF(EXACT($AK28, "L1"), AM28, IF(EXACT($AK28, "L2"), AN28, IF(EXACT($AK28, "L3"), AO28, IF(EXACT($AK28, "L4"), AP28, IF(EXACT($AK28, "L5"), AQ28, ""))))) -> 65000000000023 | AU28: =IF(AND(EXACT(B28, ""), EXACT(D28, ""), EXACT(F28, ""), EXACT(H28, ""), EXACT(J28, ""), EXACT(L28, "")), "", CONCATENATE( "PERFORM * FROM ""SchData-OLTP-Accounting"".""Func_TblChartOfAccount_SET""(varSystemLoginSession, null, null, null, varInstitutionBranchID, 62000000000001::bigint,'", IF(EXACT(B28, ""), IF(EXACT(D28, ""), IF(EXACT(F28, ""), IF(EXACT(H28, ""), IF(EXACT(J28, ""), IF(EXACT(L28, ""), "", L28), J28), H28), F28), D28), B28), "', '", IF(EXACT(B28, ""), IF(EXACT(D28, ""), IF(EXACT(F28, ""), IF(EXACT(H28, ""), IF(EXACT(J28, ""), IF(EXACT(L28, ""), "", M28), K28), I28), G28), E28), C28), "', ", IF(EXACT(J28, ""), "62000000000001::bigint", IF((RIGHT(J28, 2)*1 = 1), "62000000000001::bigint", IF((RIGHT(J28, 2)*1 = 2), "62000000000002::bigint", "null"))), ", '2016-01-01 00:00:00'::timestamp, null::timestamp, ", AW28, "::bigint, 66000000000001::bigint);")) -> PERFORM * FROM "SchData-OLTP-Accounting"."Func_TblChartOfAccount_SET"(varSystemLoginSession, null, null, null, varInstitutionBranchID, 62000000000001::bigint,'1-1301.01', 'Inventory (IDR)', 62000000000001::bigint, '2016-01-01 00:00:00'::timestamp, null::timestamp, 65000000000023::bigint, 66000000000001::bigint); | AV28: =IF(AND(EXACT($B28, ""), EXACT($D28, ""), EXACT($F28, ""), EXACT($H28, ""), EXACT($J28, ""), EXACT($L28, "")), "", V28) -> 65000000000024 | AW28: =AS28 -> 65000000000023 | AY28: =IF(AND(EXACT($B28, ""), EXACT($D28, ""), EXACT($F28, ""), EXACT($H28, ""), EXACT($J28, ""), EXACT($L28, "")), "", IF(NOT(EXACT($B28, "")), "null", IF(NOT(EXACT($D28, "")), IF($W27<>$W26, $W27, $W28), IF(NOT(EXACT($F28, "")), IF($X27<>$X26, $X27, IF($W27<>$W26, $W27, $X28)), IF(NOT(EXACT($H28, "")), IF($Y27<>$Y26, $Y27, IF($X27<>$X26, $X27, IF($W27<>$W26, $W27, $Y28))), IF(NOT(EXACT($J28, "")), IF($Z27<>$Z26, $Z27, IF($Y27<>$Y26, $Y27, IF($X27<>$X26, $X27, IF($W27<>$W26, $W27, $Z28)))), IF(NOT(EXACT($L28, "")), IF($AA27<>$AA26, $AA27, IF($Z27<>$Z26, $Z27, IF($Y27<>$Y26, $Y27, IF($X27<>$X26, $X27, IF($W27<>$W26, $W27, $AA28))))), "others"))))))) -> 65000000000023 | BA28: =BA27 + IF(EXACT(BB28, ""), 0, 1) -> 65000000000024 | BB28: =IF(AND(EXACT($B28, ""), EXACT($D28, ""), EXACT($F28, ""), EXACT($H28, ""), EXACT($J28, ""), EXACT($L28, "")), "", CONCATENATE( "PERFORM * FROM ""SchData-OLTP-Accounting"".""Func_TblChartOfAccount_SET""(varSystemLoginSession, null, null, null, null, null, varInstitutionBranchID, 62000000000001::bigint,'", IF(EXACT($B28, ""), IF(EXACT($D28, ""), IF(EXACT($F28, ""), IF(EXACT($H28, ""), IF(EXACT($J28, ""), IF(EXACT($L28, ""), "", $L28), $J28), $H28), $F28), $D28), $B28), "', '", IF(EXACT($B28, ""), IF(EXACT($D28, ""), IF(EXACT($F28, ""), IF(EXACT($H28, ""), IF(EXACT($J28, ""), IF(EXACT($L28, ""), "", $M28), $K28), $I28), $G28), $E28), $C28), "', ", IF(EXACT($J28, ""), "62000000000001::bigint", IF((RIGHT($J28, 2)*1 = 1), "62000000000001::bigint", IF((RIGHT($J28, 2)*1 = 2), "62000000000002::bigint", "null"))), ", '2016-01-01 00:00:00'::timestamp, null::timestamp, ", $AW28, "::bigint, 66000000000001::bigint, ", IF(EXACT(LEFT(IF(EXACT($B28, ""), IF(EXACT($D28, ""), IF(EXACT($F28, ""), IF(EXACT($H28, ""), IF(EXACT($J28, ""), IF(EXACT($L28, ""), "", $L28), $J28), $H28), $F28), $D28), $B28), 1), "1"), "TRUE", "FALSE"), "::boolean);")) -> PERFORM * FROM "SchData-OLTP-Accounting"."Func_TblChartOfAccount_SET"(varSystemLoginSession, null, null, null, null, null, varInstitutionBranchID, 62000000000001::bigint,'1-1301.01', 'Inventory (IDR)', 62000000000001::bigint, '2016-01-01 00:00:00'::timestamp, null::timestamp, 65000000000023::bigint, 66000000000001::bigint, TRUE::boolean);
F29: 1-1400 | G29: Biaya Dibayar Dimuka | O29: =IF(EXACT($B29, ""), $O28, $B29) -> 1-0000 | P29: =IF(EXACT($D29, ""), $P28, $D29) -> 1-1000 | Q29: =IF(EXACT($F29, ""), $Q28, $F29) -> 1-1400 | R29: =IF(EXACT($H29, ""), $R28, $H29) -> 1-1301 | S29: =IF(EXACT($J29, ""), $S28, $J29) -> 1-1301.01 | T29: =IF(EXACT($L29, ""), $T28, $L29) | V29: =V28+IF(AND(EXACT(B29, ""), EXACT(D29, ""), EXACT(F29, ""), EXACT(H29, ""), EXACT(J29, ""), EXACT(L29, "")), 0, 1) -> 65000000000025 | W29: =IF(EXACT($B29, ""), $W28, $V29) -> 65000000000001 | X29: =IF(EXACT($D29, ""), $X28, $V29) -> 65000000000002 | Y29: =IF(EXACT($F29, ""), $Y28, $V29) -> 65000000000025 | Z29: =IF(EXACT($H29, ""), $Z28, $V29) -> 65000000000023 | AA29: =IF(EXACT($J29, ""), $AA28, $V29) -> 65000000000024 | AB29: =IF(EXACT($L29, ""), $AB28, $V29) -> 65000000000000 | AD29: =AD28 + IF(W29<>W28, 1, 0) -> 1 | AE29: =IF(AD28<>AD29, 1, AE28) + IF(X29<>X28, 1, 0) -> 2 | AF29: =IF(AE28<>AE29, 1, AF28) + IF(Y29<>Y28, 1, 0) -> 5 | AG29: =IF(AF28<>AF29, 1, AG28) + IF(Z29<>Z28, 1, 0) -> 1 | AH29: =IF(AG28<>AG29, 1, AH28) + IF(AA29<>AA28, 1, 0) -> 1 | AI29: =IF(AH28<>AH29, 1, AI28) + IF(AB29<>AB28, 1, 0) -> 1 | AK29: =IF(AA29<>AA28, "L5", IF(Z29<>Z28, "L4", IF(Y29<>Y28, "L3", IF(X29<>X28, "L2", IF(W29<>W28, "L1", "L1" ) ) ) ) ) -> L3 | AM29: null | AN29: =IF(EXACT($AK28, "L1"), $W28, AN28) -> 65000000000001 | AO29: =IF(EXACT($AK28, "L1"), $W28, IF(EXACT($AK28, "L2"), $X28, AO28)) -> 65000000000002 | AP29: =IF(EXACT($AK28, "L1"), $W28, IF(EXACT($AK28, "L2"), $X28, IF(EXACT($AK28, "L3"), $Y28, AP28))) -> 65000000000022 | AQ29: =IF(EXACT($AK28, "L1"), $W28, IF(EXACT($AK28, "L2"), $X28, IF(EXACT($AK28, "L3"), $Y28, IF(EXACT($AK28, "L4"), $Z28, AQ28)))) -> 65000000000023 | AS29: =IF(EXACT($AK29, "L1"), AM29, IF(EXACT($AK29, "L2"), AN29, IF(EXACT($AK29, "L3"), AO29, IF(EXACT($AK29, "L4"), AP29, IF(EXACT($AK29, "L5"), AQ29, ""))))) -> 65000000000002 | AU29: =IF(AND(EXACT(B29, ""), EXACT(D29, ""), EXACT(F29, ""), EXACT(H29, ""), EXACT(J29, ""), EXACT(L29, "")), "", CONCATENATE( "PERFORM * FROM ""SchData-OLTP-Accounting"".""Func_TblChartOfAccount_SET""(varSystemLoginSession, null, null, null, varInstitutionBranchID, 62000000000001::bigint,'", IF(EXACT(B29, ""), IF(EXACT(D29, ""), IF(EXACT(F29, ""), IF(EXACT(H29, ""), IF(EXACT(J29, ""), IF(EXACT(L29, ""), "", L29), J29), H29), F29), D29), B29), "', '", IF(EXACT(B29, ""), IF(EXACT(D29, ""), IF(EXACT(F29, ""), IF(EXACT(H29, ""), IF(EXACT(J29, ""), IF(EXACT(L29, ""), "", M29), K29), I29), G29), E29), C29), "', ", IF(EXACT(J29, ""), "62000000000001::bigint", IF((RIGHT(J29, 2)*1 = 1), "62000000000001::bigint", IF((RIGHT(J29, 2)*1 = 2), "62000000000002::bigint", "null"))), ", '2016-01-01 00:00:00'::timestamp, null::timestamp, ", AW29, "::bigint, 66000000000001::bigint);")) -> PERFORM * FROM "SchData-OLTP-Accounting"."Func_TblChartOfAccount_SET"(varSystemLoginSession, null, null, null, varInstitutionBranchID, 62000000000001::bigint,'1-1400', 'Biaya Dibayar Dimuka', 62000000000001::bigint, '2016-01-01 00:00:00'::timestamp, null::timestamp, 65000000000002::bigint, 66000000000001::bigint); | AV29: =IF(AND(EXACT($B29, ""), EXACT($D29, ""), EXACT($F29, ""), EXACT($H29, ""), EXACT($J29, ""), EXACT($L29, "")), "", V29) -> 65000000000025 | AW29: =AS29 -> 65000000000002 | AY29: =IF(AND(EXACT($B29, ""), EXACT($D29, ""), EXACT($F29, ""), EXACT($H29, ""), EXACT($J29, ""), EXACT($L29, "")), "", IF(NOT(EXACT($B29, "")), "null", IF(NOT(EXACT($D29, "")), IF($W28<>$W27, $W28, $W29), IF(NOT(EXACT($F29, "")), IF($X28<>$X27, $X28, IF($W28<>$W27, $W28, $X29)), IF(NOT(EXACT($H29, "")), IF($Y28<>$Y27, $Y28, IF($X28<>$X27, $X28, IF($W28<>$W27, $W28, $Y29))), IF(NOT(EXACT($J29, "")), IF($Z28<>$Z27, $Z28, IF($Y28<>$Y27, $Y28, IF($X28<>$X27, $X28, IF($W28<>$W27, $W28, $Z29)))), IF(NOT(EXACT($L29, "")), IF($AA28<>$AA27, $AA28, IF($Z28<>$Z27, $Z28, IF($Y28<>$Y27, $Y28, IF($X28<>$X27, $X28, IF($W28<>$W27, $W28, $AA29))))), "others"))))))) -> 65000000000002 | BA29: =BA28 + IF(EXACT(BB29, ""), 0, 1) -> 65000000000025 | BB29: =IF(AND(EXACT($B29, ""), EXACT($D29, ""), EXACT($F29, ""), EXACT($H29, ""), EXACT($J29, ""), EXACT($L29, "")), "", CONCATENATE( "PERFORM * FROM ""SchData-OLTP-Accounting"".""Func_TblChartOfAccount_SET""(varSystemLoginSession, null, null, null, null, null, varInstitutionBranchID, 62000000000001::bigint,'", IF(EXACT($B29, ""), IF(EXACT($D29, ""), IF(EXACT($F29, ""), IF(EXACT($H29, ""), IF(EXACT($J29, ""), IF(EXACT($L29, ""), "", $L29), $J29), $H29), $F29), $D29), $B29), "', '", IF(EXACT($B29, ""), IF(EXACT($D29, ""), IF(EXACT($F29, ""), IF(EXACT($H29, ""), IF(EXACT($J29, ""), IF(EXACT($L29, ""), "", $M29), $K29), $I29), $G29), $E29), $C29), "', ", IF(EXACT($J29, ""), "62000000000001::bigint", IF((RIGHT($J29, 2)*1 = 1), "62000000000001::bigint", IF((RIGHT($J29, 2)*1 = 2), "62000000000002::bigint", "null"))), ", '2016-01-01 00:00:00'::timestamp, null::timestamp, ", $AW29, "::bigint, 66000000000001::bigint, ", IF(EXACT(LEFT(IF(EXACT($B29, ""), IF(EXACT($D29, ""), IF(EXACT($F29, ""), IF(EXACT($H29, ""), IF(EXACT($J29, ""), IF(EXACT($L29, ""), "", $L29), $J29), $H29), $F29), $D29), $B29), 1), "1"), "TRUE", "FALSE"), "::boolean);")) -> PERFORM * FROM "SchData-OLTP-Accounting"."Func_TblChartOfAccount_SET"(varSystemLoginSession, null, null, null, null, null, varInstitutionBranchID, 62000000000001::bigint,'1-1400', 'Biaya Dibayar Dimuka', 62000000000001::bigint, '2016-01-01 00:00:00'::timestamp, null::timestamp, 65000000000002::bigint, 66000000000001::bigint, TRUE::boolean);
J30: 1-1400.01 | K30: Biaya Dibayar Dimuka (IDR) | M30: Tag : Supplier-IDR | O30: =IF(EXACT($B30, ""), $O29, $B30) -> 1-0000 | P30: =IF(EXACT($D30, ""), $P29, $D30) -> 1-1000 | Q30: =IF(EXACT($F30, ""), $Q29, $F30) -> 1-1400 | R30: =IF(EXACT($H30, ""), $R29, $H30) -> 1-1301 | S30: =IF(EXACT($J30, ""), $S29, $J30) -> 1-1400.01 | T30: =IF(EXACT($L30, ""), $T29, $L30) | V30: =V29+IF(AND(EXACT(B30, ""), EXACT(D30, ""), EXACT(F30, ""), EXACT(H30, ""), EXACT(J30, ""), EXACT(L30, "")), 0, 1) -> 65000000000026 | W30: =IF(EXACT($B30, ""), $W29, $V30) -> 65000000000001 | X30: =IF(EXACT($D30, ""), $X29, $V30) -> 65000000000002 | Y30: =IF(EXACT($F30, ""), $Y29, $V30) -> 65000000000025 | Z30: =IF(EXACT($H30, ""), $Z29, $V30) -> 65000000000023 | AA30: =IF(EXACT($J30, ""), $AA29, $V30) -> 65000000000026 | AB30: =IF(EXACT($L30, ""), $AB29, $V30) -> 65000000000000 | AD30: =AD29 + IF(W30<>W29, 1, 0) -> 1 | AE30: =IF(AD29<>AD30, 1, AE29) + IF(X30<>X29, 1, 0) -> 2 | AF30: =IF(AE29<>AE30, 1, AF29) + IF(Y30<>Y29, 1, 0) -> 5 | AG30: =IF(AF29<>AF30, 1, AG29) + IF(Z30<>Z29, 1, 0) -> 1 | AH30: =IF(AG29<>AG30, 1, AH29) + IF(AA30<>AA29, 1, 0) -> 2 | AI30: =IF(AH29<>AH30, 1, AI29) + IF(AB30<>AB29, 1, 0) -> 1 | AK30: =IF(AA30<>AA29, "L5", IF(Z30<>Z29, "L4", IF(Y30<>Y29, "L3", IF(X30<>X29, "L2", IF(W30<>W29, "L1", "L1" ) ) ) ) ) -> L5 | AM30: null | AN30: =IF(EXACT($AK29, "L1"), $W29, AN29) -> 65000000000001 | AO30: =IF(EXACT($AK29, "L1"), $W29, IF(EXACT($AK29, "L2"), $X29, AO29)) -> 65000000000002 | AP30: =IF(EXACT($AK29, "L1"), $W29, IF(EXACT($AK29, "L2"), $X29, IF(EXACT($AK29, "L3"), $Y29, AP29))) -> 65000000000025 | AQ30: =IF(EXACT($AK29, "L1"), $W29, IF(EXACT($AK29, "L2"), $X29, IF(EXACT($AK29, "L3"), $Y29, IF(EXACT($AK29, "L4"), $Z29, AQ29)))) -> 65000000000025 | AS30: =IF(EXACT($AK30, "L1"), AM30, IF(EXACT($AK30, "L2"), AN30, IF(EXACT($AK30, "L3"), AO30, IF(EXACT($AK30, "L4"), AP30, IF(EXACT($AK30, "L5"), AQ30, ""))))) -> 65000000000025 | AU30: =IF(AND(EXACT(B30, ""), EXACT(D30, ""), EXACT(F30, ""), EXACT(H30, ""), EXACT(J30, ""), EXACT(L30, "")), "", CONCATENATE( "PERFORM * FROM ""SchData-OLTP-Accounting"".""Func_TblChartOfAccount_SET""(varSystemLoginSession, null, null, null, varInstitutionBranchID, 62000000000001::bigint,'", IF(EXACT(B30, ""), IF(EXACT(D30, ""), IF(EXACT(F30, ""), IF(EXACT(H30, ""), IF(EXACT(J30, ""), IF(EXACT(L30, ""), "", L30), J30), H30), F30), D30), B30), "', '", IF(EXACT(B30, ""), IF(EXACT(D30, ""), IF(EXACT(F30, ""), IF(EXACT(H30, ""), IF(EXACT(J30, ""), IF(EXACT(L30, ""), "", M30), K30), I30), G30), E30), C30), "', ", IF(EXACT(J30, ""), "62000000000001::bigint", IF((RIGHT(J30, 2)*1 = 1), "62000000000001::bigint", IF((RIGHT(J30, 2)*1 = 2), "62000000000002::bigint", "null"))), ", '2016-01-01 00:00:00'::timestamp, null::timestamp, ", AW30, "::bigint, 66000000000001::bigint);")) -> PERFORM * FROM "SchData-OLTP-Accounting"."Func_TblChartOfAccount_SET"(varSystemLoginSession, null, null, null, varInstitutionBranchID, 62000000000001::bigint,'1-1400.01', 'Biaya Dibayar Dimuka (IDR)', 62000000000001::bigint, '2016-01-01 00:00:00'::timestamp, null::timestamp, 65000000000025::bigint, 66000000000001::bigint); | AV30: =IF(AND(EXACT($B30, ""), EXACT($D30, ""), EXACT($F30, ""), EXACT($H30, ""), EXACT($J30, ""), EXACT($L30, "")), "", V30) -> 65000000000026 | AW30: =AS30 -> 65000000000025 | AY30: =IF(AND(EXACT($B30, ""), EXACT($D30, ""), EXACT($F30, ""), EXACT($H30, ""), EXACT($J30, ""), EXACT($L30, "")), "", IF(NOT(EXACT($B30, "")), "null", IF(NOT(EXACT($D30, "")), IF($W29<>$W28, $W29, $W30), IF(NOT(EXACT($F30, "")), IF($X29<>$X28, $X29, IF($W29<>$W28, $W29, $X30)), IF(NOT(EXACT($H30, "")), IF($Y29<>$Y28, $Y29, IF($X29<>$X28, $X29, IF($W29<>$W28, $W29, $Y30))), IF(NOT(EXACT($J30, "")), IF($Z29<>$Z28, $Z29, IF($Y29<>$Y28, $Y29, IF($X29<>$X28, $X29, IF($W29<>$W28, $W29, $Z30)))), IF(NOT(EXACT($L30, "")), IF($AA29<>$AA28, $AA29, IF($Z29<>$Z28, $Z29, IF($Y29<>$Y28, $Y29, IF($X29<>$X28, $X29, IF($W29<>$W28, $W29, $AA30))))), "others"))))))) -> 65000000000025 | BA30: =BA29 + IF(EXACT(BB30, ""), 0, 1) -> 65000000000026 | BB30: =IF(AND(EXACT($B30, ""), EXACT($D30, ""), EXACT($F30, ""), EXACT($H30, ""), EXACT($J30, ""), EXACT($L30, "")), "", CONCATENATE( "PERFORM * FROM ""SchData-OLTP-Accounting"".""Func_TblChartOfAccount_SET""(varSystemLoginSession, null, null, null, null, null, varInstitutionBranchID, 62000000000001::bigint,'", IF(EXACT($B30, ""), IF(EXACT($D30, ""), IF(EXACT($F30, ""), IF(EXACT($H30, ""), IF(EXACT($J30, ""), IF(EXACT($L30, ""), "", $L30), $J30), $H30), $F30), $D30), $B30), "', '", IF(EXACT($B30, ""), IF(EXACT($D30, ""), IF(EXACT($F30, ""), IF(EXACT($H30, ""), IF(EXACT($J30, ""), IF(EXACT($L30, ""), "", $M30), $K30), $I30), $G30), $E30), $C30), "', ", IF(EXACT($J30, ""), "62000000000001::bigint", IF((RIGHT($J30, 2)*1 = 1), "62000000000001::bigint", IF((RIGHT($J30, 2)*1 = 2), "62000000000002::bigint", "null"))), ", '2016-01-01 00:00:00'::timestamp, null::timestamp, ", $AW30, "::bigint, 66000000000001::bigint, ", IF(EXACT(LEFT(IF(EXACT($B30, ""), IF(EXACT($D30, ""), IF(EXACT($F30, ""), IF(EXACT($H30, ""), IF(EXACT($J30, ""), IF(EXACT($L30, ""), "", $L30), $J30), $H30), $F30), $D30), $B30), 1), "1"), "TRUE", "FALSE"), "::boolean);")) -> PERFORM * FROM "SchData-OLTP-Accounting"."Func_TblChartOfAccount_SET"(varSystemLoginSession, null, null, null, null, null, varInstitutionBranchID, 62000000000001::bigint,'1-1400.01', 'Biaya Dibayar Dimuka (IDR)', 62000000000001::bigint, '2016-01-01 00:00:00'::timestamp, null::timestamp, 65000000000025::bigint, 66000000000001::bigint, TRUE::boolean);
F31: 1-1500 | G31: Pajak Dibayar Dimuka | O31: =IF(EXACT($B31, ""), $O30, $B31) -> 1-0000 | P31: =IF(EXACT($D31, ""), $P30, $D31) -> 1-1000 | Q31: =IF(EXACT($F31, ""), $Q30, $F31) -> 1-1500 | R31: =IF(EXACT($H31, ""), $R30, $H31) -> 1-1301 | S31: =IF(EXACT($J31, ""), $S30, $J31) -> 1-1400.01 | T31: =IF(EXACT($L31, ""), $T30, $L31) | V31: =V30+IF(AND(EXACT(B31, ""), EXACT(D31, ""), EXACT(F31, ""), EXACT(H31, ""), EXACT(J31, ""), EXACT(L31, "")), 0, 1) -> 65000000000027 | W31: =IF(EXACT($B31, ""), $W30, $V31) -> 65000000000001 | X31: =IF(EXACT($D31, ""), $X30, $V31) -> 65000000000002 | Y31: =IF(EXACT($F31, ""), $Y30, $V31) -> 65000000000027 | Z31: =IF(EXACT($H31, ""), $Z30, $V31) -> 65000000000023 | AA31: =IF(EXACT($J31, ""), $AA30, $V31) -> 65000000000026 | AB31: =IF(EXACT($L31, ""), $AB30, $V31) -> 65000000000000 | AD31: =AD30 + IF(W31<>W30, 1, 0) -> 1 | AE31: =IF(AD30<>AD31, 1, AE30) + IF(X31<>X30, 1, 0) -> 2 | AF31: =IF(AE30<>AE31, 1, AF30) + IF(Y31<>Y30, 1, 0) -> 6 | AG31: =IF(AF30<>AF31, 1, AG30) + IF(Z31<>Z30, 1, 0) -> 1 | AH31: =IF(AG30<>AG31, 1, AH30) + IF(AA31<>AA30, 1, 0) -> 2 | AI31: =IF(AH30<>AH31, 1, AI30) + IF(AB31<>AB30, 1, 0) -> 1 | AK31: =IF(AA31<>AA30, "L5", IF(Z31<>Z30, "L4", IF(Y31<>Y30, "L3", IF(X31<>X30, "L2", IF(W31<>W30, "L1", "L1" ) ) ) ) ) -> L3 | AM31: null | AN31: =IF(EXACT($AK30, "L1"), $W30, AN30) -> 65000000000001 | AO31: =IF(EXACT($AK30, "L1"), $W30, IF(EXACT($AK30, "L2"), $X30, AO30)) -> 65000000000002 | AP31: =IF(EXACT($AK30, "L1"), $W30, IF(EXACT($AK30, "L2"), $X30, IF(EXACT($AK30, "L3"), $Y30, AP30))) -> 65000000000025 | AQ31: =IF(EXACT($AK30, "L1"), $W30, IF(EXACT($AK30, "L2"), $X30, IF(EXACT($AK30, "L3"), $Y30, IF(EXACT($AK30, "L4"), $Z30, AQ30)))) -> 65000000000025 | AS31: =IF(EXACT($AK31, "L1"), AM31, IF(EXACT($AK31, "L2"), AN31, IF(EXACT($AK31, "L3"), AO31, IF(EXACT($AK31, "L4"), AP31, IF(EXACT($AK31, "L5"), AQ31, ""))))) -> 65000000000002 | AU31: =IF(AND(EXACT(B31, ""), EXACT(D31, ""), EXACT(F31, ""), EXACT(H31, ""), EXACT(J31, ""), EXACT(L31, "")), "", CONCATENATE( "PERFORM * FROM ""SchData-OLTP-Accounting"".""Func_TblChartOfAccount_SET""(varSystemLoginSession, null, null, null, varInstitutionBranchID, 62000000000001::bigint,'", IF(EXACT(B31, ""), IF(EXACT(D31, ""), IF(EXACT(F31, ""), IF(EXACT(H31, ""), IF(EXACT(J31, ""), IF(EXACT(L31, ""), "", L31), J31), H31), F31), D31), B31), "', '", IF(EXACT(B31, ""), IF(EXACT(D31, ""), IF(EXACT(F31, ""), IF(EXACT(H31, ""), IF(EXACT(J31, ""), IF(EXACT(L31, ""), "", M31), K31), I31), G31), E31), C31), "', ", IF(EXACT(J31, ""), "62000000000001::bigint", IF((RIGHT(J31, 2)*1 = 1), "62000000000001::bigint", IF((RIGHT(J31, 2)*1 = 2), "62000000000002::bigint", "null"))), ", '2016-01-01 00:00:00'::timestamp, null::timestamp, ", AW31, "::bigint, 66000000000001::bigint);")) -> PERFORM * FROM "SchData-OLTP-Accounting"."Func_TblChartOfAccount_SET"(varSystemLoginSession, null, null, null, varInstitutionBranchID, 62000000000001::bigint,'1-1500', 'Pajak Dibayar Dimuka', 62000000000001::bigint, '2016-01-01 00:00:00'::timestamp, null::timestamp, 65000000000002::bigint, 66000000000001::bigint); | AV31: =IF(AND(EXACT($B31, ""), EXACT($D31, ""), EXACT($F31, ""), EXACT($H31, ""), EXACT($J31, ""), EXACT($L31, "")), "", V31) -> 65000000000027 | AW31: =AS31 -> 65000000000002 | AY31: =IF(AND(EXACT($B31, ""), EXACT($D31, ""), EXACT($F31, ""), EXACT($H31, ""), EXACT($J31, ""), EXACT($L31, "")), "", IF(NOT(EXACT($B31, "")), "null", IF(NOT(EXACT($D31, "")), IF($W30<>$W29, $W30, $W31), IF(NOT(EXACT($F31, "")), IF($X30<>$X29, $X30, IF($W30<>$W29, $W30, $X31)), IF(NOT(EXACT($H31, "")), IF($Y30<>$Y29, $Y30, IF($X30<>$X29, $X30, IF($W30<>$W29, $W30, $Y31))), IF(NOT(EXACT($J31, "")), IF($Z30<>$Z29, $Z30, IF($Y30<>$Y29, $Y30, IF($X30<>$X29, $X30, IF($W30<>$W29, $W30, $Z31)))), IF(NOT(EXACT($L31, "")), IF($AA30<>$AA29, $AA30, IF($Z30<>$Z29, $Z30, IF($Y30<>$Y29, $Y30, IF($X30<>$X29, $X30, IF($W30<>$W29, $W30, $AA31))))), "others"))))))) -> 65000000000002 | BA31: =BA30 + IF(EXACT(BB31, ""), 0, 1) -> 65000000000027 | BB31: =IF(AND(EXACT($B31, ""), EXACT($D31, ""), EXACT($F31, ""), EXACT($H31, ""), EXACT($J31, ""), EXACT($L31, "")), "", CONCATENATE( "PERFORM * FROM ""SchData-OLTP-Accounting"".""Func_TblChartOfAccount_SET""(varSystemLoginSession, null, null, null, null, null, varInstitutionBranchID, 62000000000001::bigint,'", IF(EXACT($B31, ""), IF(EXACT($D31, ""), IF(EXACT($F31, ""), IF(EXACT($H31, ""), IF(EXACT($J31, ""), IF(EXACT($L31, ""), "", $L31), $J31), $H31), $F31), $D31), $B31), "', '", IF(EXACT($B31, ""), IF(EXACT($D31, ""), IF(EXACT($F31, ""), IF(EXACT($H31, ""), IF(EXACT($J31, ""), IF(EXACT($L31, ""), "", $M31), $K31), $I31), $G31), $E31), $C31), "', ", IF(EXACT($J31, ""), "62000000000001::bigint", IF((RIGHT($J31, 2)*1 = 1), "62000000000001::bigint", IF((RIGHT($J31, 2)*1 = 2), "62000000000002::bigint", "null"))), ", '2016-01-01 00:00:00'::timestamp, null::timestamp, ", $AW31, "::bigint, 66000000000001::bigint, ", IF(EXACT(LEFT(IF(EXACT($B31, ""), IF(EXACT($D31, ""), IF(EXACT($F31, ""), IF(EXACT($H31, ""), IF(EXACT($J31, ""), IF(EXACT($L31, ""), "", $L31), $J31), $H31), $F31), $D31), $B31), 1), "1"), "TRUE", "FALSE"), "::boolean);")) -> PERFORM * FROM "SchData-OLTP-Accounting"."Func_TblChartOfAccount_SET"(varSystemLoginSession, null, null, null, null, null, varInstitutionBranchID, 62000000000001::bigint,'1-1500', 'Pajak Dibayar Dimuka', 62000000000001::bigint, '2016-01-01 00:00:00'::timestamp, null::timestamp, 65000000000002::bigint, 66000000000001::bigint, TRUE::boolean);
H32: 1-1501 | I32: VAT IN | O32: =IF(EXACT($B32, ""), $O31, $B32) -> 1-0000 | P32: =IF(EXACT($D32, ""), $P31, $D32) -> 1-1000 | Q32: =IF(EXACT($F32, ""), $Q31, $F32) -> 1-1500 | R32: =IF(EXACT($H32, ""), $R31, $H32) -> 1-1501 | S32: =IF(EXACT($J32, ""), $S31, $J32) -> 1-1400.01 | T32: =IF(EXACT($L32, ""), $T31, $L32) | V32: =V31+IF(AND(EXACT(B32, ""), EXACT(D32, ""), EXACT(F32, ""), EXACT(H32, ""), EXACT(J32, ""), EXACT(L32, "")), 0, 1) -> 65000000000028 | W32: =IF(EXACT($B32, ""), $W31, $V32) -> 65000000000001 | X32: =IF(EXACT($D32, ""), $X31, $V32) -> 65000000000002 | Y32: =IF(EXACT($F32, ""), $Y31, $V32) -> 65000000000027 | Z32: =IF(EXACT($H32, ""), $Z31, $V32) -> 65000000000028 | AA32: =IF(EXACT($J32, ""), $AA31, $V32) -> 65000000000026 | AB32: =IF(EXACT($L32, ""), $AB31, $V32) -> 65000000000000 | AD32: =AD31 + IF(W32<>W31, 1, 0) -> 1 | AE32: =IF(AD31<>AD32, 1, AE31) + IF(X32<>X31, 1, 0) -> 2 | AF32: =IF(AE31<>AE32, 1, AF31) + IF(Y32<>Y31, 1, 0) -> 6 | AG32: =IF(AF31<>AF32, 1, AG31) + IF(Z32<>Z31, 1, 0) -> 2 | AH32: =IF(AG31<>AG32, 1, AH31) + IF(AA32<>AA31, 1, 0) -> 1 | AI32: =IF(AH31<>AH32, 1, AI31) + IF(AB32<>AB31, 1, 0) -> 1 | AK32: =IF(AA32<>AA31, "L5", IF(Z32<>Z31, "L4", IF(Y32<>Y31, "L3", IF(X32<>X31, "L2", IF(W32<>W31, "L1", "L1" ) ) ) ) ) -> L4 | AM32: null | AN32: =IF(EXACT($AK31, "L1"), $W31, AN31) -> 65000000000001 | AO32: =IF(EXACT($AK31, "L1"), $W31, IF(EXACT($AK31, "L2"), $X31, AO31)) -> 65000000000002 | AP32: =IF(EXACT($AK31, "L1"), $W31, IF(EXACT($AK31, "L2"), $X31, IF(EXACT($AK31, "L3"), $Y31, AP31))) -> 65000000000027 | AQ32: =IF(EXACT($AK31, "L1"), $W31, IF(EXACT($AK31, "L2"), $X31, IF(EXACT($AK31, "L3"), $Y31, IF(EXACT($AK31, "L4"), $Z31, AQ31)))) -> 65000000000027 | AS32: =IF(EXACT($AK32, "L1"), AM32, IF(EXACT($AK32, "L2"), AN32, IF(EXACT($AK32, "L3"), AO32, IF(EXACT($AK32, "L4"), AP32, IF(EXACT($AK32, "L5"), AQ32, ""))))) -> 65000000000027 | AU32: =IF(AND(EXACT(B32, ""), EXACT(D32, ""), EXACT(F32, ""), EXACT(H32, ""), EXACT(J32, ""), EXACT(L32, "")), "", CONCATENATE( "PERFORM * FROM ""SchData-OLTP-Accounting"".""Func_TblChartOfAccount_SET""(varSystemLoginSession, null, null, null, varInstitutionBranchID, 62000000000001::bigint,'", IF(EXACT(B32, ""), IF(EXACT(D32, ""), IF(EXACT(F32, ""), IF(EXACT(H32, ""), IF(EXACT(J32, ""), IF(EXACT(L32, ""), "", L32), J32), H32), F32), D32), B32), "', '", IF(EXACT(B32, ""), IF(EXACT(D32, ""), IF(EXACT(F32, ""), IF(EXACT(H32, ""), IF(EXACT(J32, ""), IF(EXACT(L32, ""), "", M32), K32), I32), G32), E32), C32), "', ", IF(EXACT(J32, ""), "62000000000001::bigint", IF((RIGHT(J32, 2)*1 = 1), "62000000000001::bigint", IF((RIGHT(J32, 2)*1 = 2), "62000000000002::bigint", "null"))), ", '2016-01-01 00:00:00'::timestamp, null::timestamp, ", AW32, "::bigint, 66000000000001::bigint);")) -> PERFORM * FROM "SchData-OLTP-Accounting"."Func_TblChartOfAccount_SET"(varSystemLoginSession, null, null, null, varInstitutionBranchID, 62000000000001::bigint,'1-1501', 'VAT IN', 62000000000001::bigint, '2016-01-01 00:00:00'::timestamp, null::timestamp, 65000000000027::bigint, 66000000000001::bigint); | AV32: =IF(AND(EXACT($B32, ""), EXACT($D32, ""), EXACT($F32, ""), EXACT($H32, ""), EXACT($J32, ""), EXACT($L32, "")), "", V32) -> 65000000000028 | AW32: =AS32 -> 65000000000027 | AY32: =IF(AND(EXACT($B32, ""), EXACT($D32, ""), EXACT($F32, ""), EXACT($H32, ""), EXACT($J32, ""), EXACT($L32, "")), "", IF(NOT(EXACT($B32, "")), "null", IF(NOT(EXACT($D32, "")), IF($W31<>$W30, $W31, $W32), IF(NOT(EXACT($F32, "")), IF($X31<>$X30, $X31, IF($W31<>$W30, $W31, $X32)), IF(NOT(EXACT($H32, "")), IF($Y31<>$Y30, $Y31, IF($X31<>$X30, $X31, IF($W31<>$W30, $W31, $Y32))), IF(NOT(EXACT($J32, "")), IF($Z31<>$Z30, $Z31, IF($Y31<>$Y30, $Y31, IF($X31<>$X30, $X31, IF($W31<>$W30, $W31, $Z32)))), IF(NOT(EXACT($L32, "")), IF($AA31<>$AA30, $AA31, IF($Z31<>$Z30, $Z31, IF($Y31<>$Y30, $Y31, IF($X31<>$X30, $X31, IF($W31<>$W30, $W31, $AA32))))), "others"))))))) -> 65000000000027 | BA32: =BA31 + IF(EXACT(BB32, ""), 0, 1) -> 65000000000028 | BB32: =IF(AND(EXACT($B32, ""), EXACT($D32, ""), EXACT($F32, ""), EXACT($H32, ""), EXACT($J32, ""), EXACT($L32, "")), "", CONCATENATE( "PERFORM * FROM ""SchData-OLTP-Accounting"".""Func_TblChartOfAccount_SET""(varSystemLoginSession, null, null, null, null, null, varInstitutionBranchID, 62000000000001::bigint,'", IF(EXACT($B32, ""), IF(EXACT($D32, ""), IF(EXACT($F32, ""), IF(EXACT($H32, ""), IF(EXACT($J32, ""), IF(EXACT($L32, ""), "", $L32), $J32), $H32), $F32), $D32), $B32), "', '", IF(EXACT($B32, ""), IF(EXACT($D32, ""), IF(EXACT($F32, ""), IF(EXACT($H32, ""), IF(EXACT($J32, ""), IF(EXACT($L32, ""), "", $M32), $K32), $I32), $G32), $E32), $C32), "', ", IF(EXACT($J32, ""), "62000000000001::bigint", IF((RIGHT($J32, 2)*1 = 1), "62000000000001::bigint", IF((RIGHT($J32, 2)*1 = 2), "62000000000002::bigint", "null"))), ", '2016-01-01 00:00:00'::timestamp, null::timestamp, ", $AW32, "::bigint, 66000000000001::bigint, ", IF(EXACT(LEFT(IF(EXACT($B32, ""), IF(EXACT($D32, ""), IF(EXACT($F32, ""), IF(EXACT($H32, ""), IF(EXACT($J32, ""), IF(EXACT($L32, ""), "", $L32), $J32), $H32), $F32), $D32), $B32), 1), "1"), "TRUE", "FALSE"), "::boolean);")) -> PERFORM * FROM "SchData-OLTP-Accounting"."Func_TblChartOfAccount_SET"(varSystemLoginSession, null, null, null, null, null, varInstitutionBranchID, 62000000000001::bigint,'1-1501', 'VAT IN', 62000000000001::bigint, '2016-01-01 00:00:00'::timestamp, null::timestamp, 65000000000027::bigint, 66000000000001::bigint, TRUE::boolean);
J33: 1-1501.01 | K33: VAT IN (IDR) | O33: =IF(EXACT($B33, ""), $O32, $B33) -> 1-0000 | P33: =IF(EXACT($D33, ""), $P32, $D33) -> 1-1000 | Q33: =IF(EXACT($F33, ""), $Q32, $F33) -> 1-1500 | R33: =IF(EXACT($H33, ""), $R32, $H33) -> 1-1501 | S33: =IF(EXACT($J33, ""), $S32, $J33) -> 1-1501.01 | T33: =IF(EXACT($L33, ""), $T32, $L33) | V33: =V32+IF(AND(EXACT(B33, ""), EXACT(D33, ""), EXACT(F33, ""), EXACT(H33, ""), EXACT(J33, ""), EXACT(L33, "")), 0, 1) -> 65000000000029 | W33: =IF(EXACT($B33, ""), $W32, $V33) -> 65000000000001 | X33: =IF(EXACT($D33, ""), $X32, $V33) -> 65000000000002 | Y33: =IF(EXACT($F33, ""), $Y32, $V33) -> 65000000000027 | Z33: =IF(EXACT($H33, ""), $Z32, $V33) -> 65000000000028 | AA33: =IF(EXACT($J33, ""), $AA32, $V33) -> 65000000000029 | AB33: =IF(EXACT($L33, ""), $AB32, $V33) -> 65000000000000 | AD33: =AD32 + IF(W33<>W32, 1, 0) -> 1 | AE33: =IF(AD32<>AD33, 1, AE32) + IF(X33<>X32, 1, 0) -> 2 | AF33: =IF(AE32<>AE33, 1, AF32) + IF(Y33<>Y32, 1, 0) -> 6 | AG33: =IF(AF32<>AF33, 1, AG32) + IF(Z33<>Z32, 1, 0) -> 2 | AH33: =IF(AG32<>AG33, 1, AH32) + IF(AA33<>AA32, 1, 0) -> 2 | AI33: =IF(AH32<>AH33, 1, AI32) + IF(AB33<>AB32, 1, 0) -> 1 | AK33: =IF(AA33<>AA32, "L5", IF(Z33<>Z32, "L4", IF(Y33<>Y32, "L3", IF(X33<>X32, "L2", IF(W33<>W32, "L1", "L1" ) ) ) ) ) -> L5 | AM33: null | AN33: =IF(EXACT($AK32, "L1"), $W32, AN32) -> 65000000000001 | AO33: =IF(EXACT($AK32, "L1"), $W32, IF(EXACT($AK32, "L2"), $X32, AO32)) -> 65000000000002 | AP33: =IF(EXACT($AK32, "L1"), $W32, IF(EXACT($AK32, "L2"), $X32, IF(EXACT($AK32, "L3"), $Y32, AP32))) -> 65000000000027 | AQ33: =IF(EXACT($AK32, "L1"), $W32, IF(EXACT($AK32, "L2"), $X32, IF(EXACT($AK32, "L3"), $Y32, IF(EXACT($AK32, "L4"), $Z32, AQ32)))) -> 65000000000028 | AS33: =IF(EXACT($AK33, "L1"), AM33, IF(EXACT($AK33, "L2"), AN33, IF(EXACT($AK33, "L3"), AO33, IF(EXACT($AK33, "L4"), AP33, IF(EXACT($AK33, "L5"), AQ33, ""))))) -> 65000000000028 | AU33: =IF(AND(EXACT(B33, ""), EXACT(D33, ""), EXACT(F33, ""), EXACT(H33, ""), EXACT(J33, ""), EXACT(L33, "")), "", CONCATENATE( "PERFORM * FROM ""SchData-OLTP-Accounting"".""Func_TblChartOfAccount_SET""(varSystemLoginSession, null, null, null, varInstitutionBranchID, 62000000000001::bigint,'", IF(EXACT(B33, ""), IF(EXACT(D33, ""), IF(EXACT(F33, ""), IF(EXACT(H33, ""), IF(EXACT(J33, ""), IF(EXACT(L33, ""), "", L33), J33), H33), F33), D33), B33), "', '", IF(EXACT(B33, ""), IF(EXACT(D33, ""), IF(EXACT(F33, ""), IF(EXACT(H33, ""), IF(EXACT(J33, ""), IF(EXACT(L33, ""), "", M33), K33), I33), G33), E33), C33), "', ", IF(EXACT(J33, ""), "62000000000001::bigint", IF((RIGHT(J33, 2)*1 = 1), "62000000000001::bigint", IF((RIGHT(J33, 2)*1 = 2), "62000000000002::bigint", "null"))), ", '2016-01-01 00:00:00'::timestamp, null::timestamp, ", AW33, "::bigint, 66000000000001::bigint);")) -> PERFORM * FROM "SchData-OLTP-Accounting"."Func_TblChartOfAccount_SET"(varSystemLoginSession, null, null, null, varInstitutionBranchID, 62000000000001::bigint,'1-1501.01', 'VAT IN (IDR)', 62000000000001::bigint, '2016-01-01 00:00:00'::timestamp, null::timestamp, 65000000000028::bigint, 66000000000001::bigint); | AV33: =IF(AND(EXACT($B33, ""), EXACT($D33, ""), EXACT($F33, ""), EXACT($H33, ""), EXACT($J33, ""), EXACT($L33, "")), "", V33) -> 65000000000029 | AW33: =AS33 -> 65000000000028 | AY33: =IF(AND(EXACT($B33, ""), EXACT($D33, ""), EXACT($F33, ""), EXACT($H33, ""), EXACT($J33, ""), EXACT($L33, "")), "", IF(NOT(EXACT($B33, "")), "null", IF(NOT(EXACT($D33, "")), IF($W32<>$W31, $W32, $W33), IF(NOT(EXACT($F33, "")), IF($X32<>$X31, $X32, IF($W32<>$W31, $W32, $X33)), IF(NOT(EXACT($H33, "")), IF($Y32<>$Y31, $Y32, IF($X32<>$X31, $X32, IF($W32<>$W31, $W32, $Y33))), IF(NOT(EXACT($J33, "")), IF($Z32<>$Z31, $Z32, IF($Y32<>$Y31, $Y32, IF($X32<>$X31, $X32, IF($W32<>$W31, $W32, $Z33)))), IF(NOT(EXACT($L33, "")), IF($AA32<>$AA31, $AA32, IF($Z32<>$Z31, $Z32, IF($Y32<>$Y31, $Y32, IF($X32<>$X31, $X32, IF($W32<>$W31, $W32, $AA33))))), "others"))))))) -> 65000000000028 | BA33: =BA32 + IF(EXACT(BB33, ""), 0, 1) -> 65000000000029 | BB33: =IF(AND(EXACT($B33, ""), EXACT($D33, ""), EXACT($F33, ""), EXACT($H33, ""), EXACT($J33, ""), EXACT($L33, "")), "", CONCATENATE( "PERFORM * FROM ""SchData-OLTP-Accounting"".""Func_TblChartOfAccount_SET""(varSystemLoginSession, null, null, null, null, null, varInstitutionBranchID, 62000000000001::bigint,'", IF(EXACT($B33, ""), IF(EXACT($D33, ""), IF(EXACT($F33, ""), IF(EXACT($H33, ""), IF(EXACT($J33, ""), IF(EXACT($L33, ""), "", $L33), $J33), $H33), $F33), $D33), $B33), "', '", IF(EXACT($B33, ""), IF(EXACT($D33, ""), IF(EXACT($F33, ""), IF(EXACT($H33, ""), IF(EXACT($J33, ""), IF(EXACT($L33, ""), "", $M33), $K33), $I33), $G33), $E33), $C33), "', ", IF(EXACT($J33, ""), "62000000000001::bigint", IF((RIGHT($J33, 2)*1 = 1), "62000000000001::bigint", IF((RIGHT($J33, 2)*1 = 2), "62000000000002::bigint", "null"))), ", '2016-01-01 00:00:00'::timestamp, null::timestamp, ", $AW33, "::bigint, 66000000000001::bigint, ", IF(EXACT(LEFT(IF(EXACT($B33, ""), IF(EXACT($D33, ""), IF(EXACT($F33, ""), IF(EXACT($H33, ""), IF(EXACT($J33, ""), IF(EXACT($L33, ""), "", $L33), $J33), $H33), $F33), $D33), $B33), 1), "1"), "TRUE", "FALSE"), "::boolean);")) -> PERFORM * FROM "SchData-OLTP-Accounting"."Func_TblChartOfAccount_SET"(varSystemLoginSession, null, null, null, null, null, varInstitutionBranchID, 62000000000001::bigint,'1-1501.01', 'VAT IN (IDR)', 62000000000001::bigint, '2016-01-01 00:00:00'::timestamp, null::timestamp, 65000000000028::bigint, 66000000000001::bigint, TRUE::boolean);
H34: 1-1502 | I34: Prepaid Tax 22 | O34: =IF(EXACT($B34, ""), $O33, $B34) -> 1-0000 | P34: =IF(EXACT($D34, ""), $P33, $D34) -> 1-1000 | Q34: =IF(EXACT($F34, ""), $Q33, $F34) -> 1-1500 | R34: =IF(EXACT($H34, ""), $R33, $H34) -> 1-1502 | S34: =IF(EXACT($J34, ""), $S33, $J34) -> 1-1501.01 | T34: =IF(EXACT($L34, ""), $T33, $L34) | V34: =V33+IF(AND(EXACT(B34, ""), EXACT(D34, ""), EXACT(F34, ""), EXACT(H34, ""), EXACT(J34, ""), EXACT(L34, "")), 0, 1) -> 65000000000030 | W34: =IF(EXACT($B34, ""), $W33, $V34) -> 65000000000001 | X34: =IF(EXACT($D34, ""), $X33, $V34) -> 65000000000002 | Y34: =IF(EXACT($F34, ""), $Y33, $V34) -> 65000000000027 | Z34: =IF(EXACT($H34, ""), $Z33, $V34) -> 65000000000030 | AA34: =IF(EXACT($J34, ""), $AA33, $V34) -> 65000000000029 | AB34: =IF(EXACT($L34, ""), $AB33, $V34) -> 65000000000000 | AD34: =AD33 + IF(W34<>W33, 1, 0) -> 1 | AE34: =IF(AD33<>AD34, 1, AE33) + IF(X34<>X33, 1, 0) -> 2 | AF34: =IF(AE33<>AE34, 1, AF33) + IF(Y34<>Y33, 1, 0) -> 6 | AG34: =IF(AF33<>AF34, 1, AG33) + IF(Z34<>Z33, 1, 0) -> 3 | AH34: =IF(AG33<>AG34, 1, AH33) + IF(AA34<>AA33, 1, 0) -> 1 | AI34: =IF(AH33<>AH34, 1, AI33) + IF(AB34<>AB33, 1, 0) -> 1 | AK34: =IF(AA34<>AA33, "L5", IF(Z34<>Z33, "L4", IF(Y34<>Y33, "L3", IF(X34<>X33, "L2", IF(W34<>W33, "L1", "L1" ) ) ) ) ) -> L4 | AM34: null | AN34: =IF(EXACT($AK33, "L1"), $W33, AN33) -> 65000000000001 | AO34: =IF(EXACT($AK33, "L1"), $W33, IF(EXACT($AK33, "L2"), $X33, AO33)) -> 65000000000002 | AP34: =IF(EXACT($AK33, "L1"), $W33, IF(EXACT($AK33, "L2"), $X33, IF(EXACT($AK33, "L3"), $Y33, AP33))) -> 65000000000027 | AQ34: =IF(EXACT($AK33, "L1"), $W33, IF(EXACT($AK33, "L2"), $X33, IF(EXACT($AK33, "L3"), $Y33, IF(EXACT($AK33, "L4"), $Z33, AQ33)))) -> 65000000000028 | AS34: =IF(EXACT($AK34, "L1"), AM34, IF(EXACT($AK34, "L2"), AN34, IF(EXACT($AK34, "L3"), AO34, IF(EXACT($AK34, "L4"), AP34, IF(EXACT($AK34, "L5"), AQ34, ""))))) -> 65000000000027 | AU34: =IF(AND(EXACT(B34, ""), EXACT(D34, ""), EXACT(F34, ""), EXACT(H34, ""), EXACT(J34, ""), EXACT(L34, "")), "", CONCATENATE( "PERFORM * FROM ""SchData-OLTP-Accounting"".""Func_TblChartOfAccount_SET""(varSystemLoginSession, null, null, null, varInstitutionBranchID, 62000000000001::bigint,'", IF(EXACT(B34, ""), IF(EXACT(D34, ""), IF(EXACT(F34, ""), IF(EXACT(H34, ""), IF(EXACT(J34, ""), IF(EXACT(L34, ""), "", L34), J34), H34), F34), D34), B34), "', '", IF(EXACT(B34, ""), IF(EXACT(D34, ""), IF(EXACT(F34, ""), IF(EXACT(H34, ""), IF(EXACT(J34, ""), IF(EXACT(L34, ""), "", M34), K34), I34), G34), E34), C34), "', ", IF(EXACT(J34, ""), "62000000000001::bigint", IF((RIGHT(J34, 2)*1 = 1), "62000000000001::bigint", IF((RIGHT(J34, 2)*1 = 2), "62000000000002::bigint", "null"))), ", '2016-01-01 00:00:00'::timestamp, null::timestamp, ", AW34, "::bigint, 66000000000001::bigint);")) -> PERFORM * FROM "SchData-OLTP-Accounting"."Func_TblChartOfAccount_SET"(varSystemLoginSession, null, null, null, varInstitutionBranchID, 62000000000001::bigint,'1-1502', 'Prepaid Tax 22', 62000000000001::bigint, '2016-01-01 00:00:00'::timestamp, null::timestamp, 65000000000027::bigint, 66000000000001::bigint); | AV34: =IF(AND(EXACT($B34, ""), EXACT($D34, ""), EXACT($F34, ""), EXACT($H34, ""), EXACT($J34, ""), EXACT($L34, "")), "", V34) -> 65000000000030 | AW34: =AS34 -> 65000000000027 | AY34: =IF(AND(EXACT($B34, ""), EXACT($D34, ""), EXACT($F34, ""), EXACT($H34, ""), EXACT($J34, ""), EXACT($L34, "")), "", IF(NOT(EXACT($B34, "")), "null", IF(NOT(EXACT($D34, "")), IF($W33<>$W32, $W33, $W34), IF(NOT(EXACT($F34, "")), IF($X33<>$X32, $X33, IF($W33<>$W32, $W33, $X34)), IF(NOT(EXACT($H34, "")), IF($Y33<>$Y32, $Y33, IF($X33<>$X32, $X33, IF($W33<>$W32, $W33, $Y34))), IF(NOT(EXACT($J34, "")), IF($Z33<>$Z32, $Z33, IF($Y33<>$Y32, $Y33, IF($X33<>$X32, $X33, IF($W33<>$W32, $W33, $Z34)))), IF(NOT(EXACT($L34, "")), IF($AA33<>$AA32, $AA33, IF($Z33<>$Z32, $Z33, IF($Y33<>$Y32, $Y33, IF($X33<>$X32, $X33, IF($W33<>$W32, $W33, $AA34))))), "others"))))))) -> 65000000000027 | BA34: =BA33 + IF(EXACT(BB34, ""), 0, 1) -> 65000000000030 | BB34: =IF(AND(EXACT($B34, ""), EXACT($D34, ""), EXACT($F34, ""), EXACT($H34, ""), EXACT($J34, ""), EXACT($L34, "")), "", CONCATENATE( "PERFORM * FROM ""SchData-OLTP-Accounting"".""Func_TblChartOfAccount_SET""(varSystemLoginSession, null, null, null, null, null, varInstitutionBranchID, 62000000000001::bigint,'", IF(EXACT($B34, ""), IF(EXACT($D34, ""), IF(EXACT($F34, ""), IF(EXACT($H34, ""), IF(EXACT($J34, ""), IF(EXACT($L34, ""), "", $L34), $J34), $H34), $F34), $D34), $B34), "', '", IF(EXACT($B34, ""), IF(EXACT($D34, ""), IF(EXACT($F34, ""), IF(EXACT($H34, ""), IF(EXACT($J34, ""), IF(EXACT($L34, ""), "", $M34), $K34), $I34), $G34), $E34), $C34), "', ", IF(EXACT($J34, ""), "62000000000001::bigint", IF((RIGHT($J34, 2)*1 = 1), "62000000000001::bigint", IF((RIGHT($J34, 2)*1 = 2), "62000000000002::bigint", "null"))), ", '2016-01-01 00:00:00'::timestamp, null::timestamp, ", $AW34, "::bigint, 66000000000001::bigint, ", IF(EXACT(LEFT(IF(EXACT($B34, ""), IF(EXACT($D34, ""), IF(EXACT($F34, ""), IF(EXACT($H34, ""), IF(EXACT($J34, ""), IF(EXACT($L34, ""), "", $L34), $J34), $H34), $F34), $D34), $B34), 1), "1"), "TRUE", "FALSE"), "::boolean);")) -> PERFORM * FROM "SchData-OLTP-Accounting"."Func_TblChartOfAccount_SET"(varSystemLoginSession, null, null, null, null, null, varInstitutionBranchID, 62000000000001::bigint,'1-1502', 'Prepaid Tax 22', 62000000000001::bigint, '2016-01-01 00:00:00'::timestamp, null::timestamp, 65000000000027::bigint, 66000000000001::bigint, TRUE::boolean);
J35: 1-1502.01 | K35: Prepaid Tax 22 (IDR) | O35: =IF(EXACT($B35, ""), $O34, $B35) -> 1-0000 | P35: =IF(EXACT($D35, ""), $P34, $D35) -> 1-1000 | Q35: =IF(EXACT($F35, ""), $Q34, $F35) -> 1-1500 | R35: =IF(EXACT($H35, ""), $R34, $H35) -> 1-1502 | S35: =IF(EXACT($J35, ""), $S34, $J35) -> 1-1502.01 | T35: =IF(EXACT($L35, ""), $T34, $L35) | V35: =V34+IF(AND(EXACT(B35, ""), EXACT(D35, ""), EXACT(F35, ""), EXACT(H35, ""), EXACT(J35, ""), EXACT(L35, "")), 0, 1) -> 65000000000031 | W35: =IF(EXACT($B35, ""), $W34, $V35) -> 65000000000001 | X35: =IF(EXACT($D35, ""), $X34, $V35) -> 65000000000002 | Y35: =IF(EXACT($F35, ""), $Y34, $V35) -> 65000000000027 | Z35: =IF(EXACT($H35, ""), $Z34, $V35) -> 65000000000030 | AA35: =IF(EXACT($J35, ""), $AA34, $V35) -> 65000000000031 | AB35: =IF(EXACT($L35, ""), $AB34, $V35) -> 65000000000000 | AD35: =AD34 + IF(W35<>W34, 1, 0) -> 1 | AE35: =IF(AD34<>AD35, 1, AE34) + IF(X35<>X34, 1, 0) -> 2 | AF35: =IF(AE34<>AE35, 1, AF34) + IF(Y35<>Y34, 1, 0) -> 6 | AG35: =IF(AF34<>AF35, 1, AG34) + IF(Z35<>Z34, 1, 0) -> 3 | AH35: =IF(AG34<>AG35, 1, AH34) + IF(AA35<>AA34, 1, 0) -> 2 | AI35: =IF(AH34<>AH35, 1, AI34) + IF(AB35<>AB34, 1, 0) -> 1 | AK35: =IF(AA35<>AA34, "L5", IF(Z35<>Z34, "L4", IF(Y35<>Y34, "L3", IF(X35<>X34, "L2", IF(W35<>W34, "L1", "L1" ) ) ) ) ) -> L5 | AM35: null | AN35: =IF(EXACT($AK34, "L1"), $W34, AN34) -> 65000000000001 | AO35: =IF(EXACT($AK34, "L1"), $W34, IF(EXACT($AK34, "L2"), $X34, AO34)) -> 65000000000002 | AP35: =IF(EXACT($AK34, "L1"), $W34, IF(EXACT($AK34, "L2"), $X34, IF(EXACT($AK34, "L3"), $Y34, AP34))) -> 65000000000027 | AQ35: =IF(EXACT($AK34, "L1"), $W34, IF(EXACT($AK34, "L2"), $X34, IF(EXACT($AK34, "L3"), $Y34, IF(EXACT($AK34, "L4"), $Z34, AQ34)))) -> 65000000000030 | AS35: =IF(EXACT($AK35, "L1"), AM35, IF(EXACT($AK35, "L2"), AN35, IF(EXACT($AK35, "L3"), AO35, IF(EXACT($AK35, "L4"), AP35, IF(EXACT($AK35, "L5"), AQ35, ""))))) -> 65000000000030 | AU35: =IF(AND(EXACT(B35, ""), EXACT(D35, ""), EXACT(F35, ""), EXACT(H35, ""), EXACT(J35, ""), EXACT(L35, "")), "", CONCATENATE( "PERFORM * FROM ""SchData-OLTP-Accounting"".""Func_TblChartOfAccount_SET""(varSystemLoginSession, null, null, null, varInstitutionBranchID, 62000000000001::bigint,'", IF(EXACT(B35, ""), IF(EXACT(D35, ""), IF(EXACT(F35, ""), IF(EXACT(H35, ""), IF(EXACT(J35, ""), IF(EXACT(L35, ""), "", L35), J35), H35), F35), D35), B35), "', '", IF(EXACT(B35, ""), IF(EXACT(D35, ""), IF(EXACT(F35, ""), IF(EXACT(H35, ""), IF(EXACT(J35, ""), IF(EXACT(L35, ""), "", M35), K35), I35), G35), E35), C35), "', ", IF(EXACT(J35, ""), "62000000000001::bigint", IF((RIGHT(J35, 2)*1 = 1), "62000000000001::bigint", IF((RIGHT(J35, 2)*1 = 2), "62000000000002::bigint", "null"))), ", '2016-01-01 00:00:00'::timestamp, null::timestamp, ", AW35, "::bigint, 66000000000001::bigint);")) -> PERFORM * FROM "SchData-OLTP-Accounting"."Func_TblChartOfAccount_SET"(varSystemLoginSession, null, null, null, varInstitutionBranchID, 62000000000001::bigint,'1-1502.01', 'Prepaid Tax 22 (IDR)', 62000000000001::bigint, '2016-01-01 00:00:00'::timestamp, null::timestamp, 65000000000030::bigint, 66000000000001::bigint); | AV35: =IF(AND(EXACT($B35, ""), EXACT($D35, ""), EXACT($F35, ""), EXACT($H35, ""), EXACT($J35, ""), EXACT($L35, "")), "", V35) -> 65000000000031 | AW35: =AS35 -> 65000000000030 | AY35: =IF(AND(EXACT($B35, ""), EXACT($D35, ""), EXACT($F35, ""), EXACT($H35, ""), EXACT($J35, ""), EXACT($L35, "")), "", IF(NOT(EXACT($B35, "")), "null", IF(NOT(EXACT($D35, "")), IF($W34<>$W33, $W34, $W35), IF(NOT(EXACT($F35, "")), IF($X34<>$X33, $X34, IF($W34<>$W33, $W34, $X35)), IF(NOT(EXACT($H35, "")), IF($Y34<>$Y33, $Y34, IF($X34<>$X33, $X34, IF($W34<>$W33, $W34, $Y35))), IF(NOT(EXACT($J35, "")), IF($Z34<>$Z33, $Z34, IF($Y34<>$Y33, $Y34, IF($X34<>$X33, $X34, IF($W34<>$W33, $W34, $Z35)))), IF(NOT(EXACT($L35, "")), IF($AA34<>$AA33, $AA34, IF($Z34<>$Z33, $Z34, IF($Y34<>$Y33, $Y34, IF($X34<>$X33, $X34, IF($W34<>$W33, $W34, $AA35))))), "others"))))))) -> 65000000000030 | BA35: =BA34 + IF(EXACT(BB35, ""), 0, 1) -> 65000000000031 | BB35: =IF(AND(EXACT($B35, ""), EXACT($D35, ""), EXACT($F35, ""), EXACT($H35, ""), EXACT($J35, ""), EXACT($L35, "")), "", CONCATENATE( "PERFORM * FROM ""SchData-OLTP-Accounting"".""Func_TblChartOfAccount_SET""(varSystemLoginSession, null, null, null, null, null, varInstitutionBranchID, 62000000000001::bigint,'", IF(EXACT($B35, ""), IF(EXACT($D35, ""), IF(EXACT($F35, ""), IF(EXACT($H35, ""), IF(EXACT($J35, ""), IF(EXACT($L35, ""), "", $L35), $J35), $H35), $F35), $D35), $B35), "', '", IF(EXACT($B35, ""), IF(EXACT($D35, ""), IF(EXACT($F35, ""), IF(EXACT($H35, ""), IF(EXACT($J35, ""), IF(EXACT($L35, ""), "", $M35), $K35), $I35), $G35), $E35), $C35), "', ", IF(EXACT($J35, ""), "62000000000001::bigint", IF((RIGHT($J35, 2)*1 = 1), "62000000000001::bigint", IF((RIGHT($J35, 2)*1 = 2), "62000000000002::bigint", "null"))), ", '2016-01-01 00:00:00'::timestamp, null::timestamp, ", $AW35, "::bigint, 66000000000001::bigint, ", IF(EXACT(LEFT(IF(EXACT($B35, ""), IF(EXACT($D35, ""), IF(EXACT($F35, ""), IF(EXACT($H35, ""), IF(EXACT($J35, ""), IF(EXACT($L35, ""), "", $L35), $J35), $H35), $F35), $D35), $B35), 1), "1"), "TRUE", "FALSE"), "::boolean);")) -> PERFORM * FROM "SchData-OLTP-Accounting"."Func_TblChartOfAccount_SET"(varSystemLoginSession, null, null, null, null, null, varInstitutionBranchID, 62000000000001::bigint,'1-1502.01', 'Prepaid Tax 22 (IDR)', 62000000000001::bigint, '2016-01-01 00:00:00'::timestamp, null::timestamp, 65000000000030::bigint, 66000000000001::bigint, TRUE::boolean);
H36: 1-1503 | I36: Prepaid Tax 23 | O36: =IF(EXACT($B36, ""), $O35, $B36) -> 1-0000 | P36: =IF(EXACT($D36, ""), $P35, $D36) -> 1-1000 | Q36: =IF(EXACT($F36, ""), $Q35, $F36) -> 1-1500 | R36: =IF(EXACT($H36, ""), $R35, $H36) -> 1-1503 | S36: =IF(EXACT($J36, ""), $S35, $J36) -> 1-1502.01 | T36: =IF(EXACT($L36, ""), $T35, $L36) | V36: =V35+IF(AND(EXACT(B36, ""), EXACT(D36, ""), EXACT(F36, ""), EXACT(H36, ""), EXACT(J36, ""), EXACT(L36, "")), 0, 1) -> 65000000000032 | W36: =IF(EXACT($B36, ""), $W35, $V36) -> 65000000000001 | X36: =IF(EXACT($D36, ""), $X35, $V36) -> 65000000000002 | Y36: =IF(EXACT($F36, ""), $Y35, $V36) -> 65000000000027 | Z36: =IF(EXACT($H36, ""), $Z35, $V36) -> 65000000000032 | AA36: =IF(EXACT($J36, ""), $AA35, $V36) -> 65000000000031 | AB36: =IF(EXACT($L36, ""), $AB35, $V36) -> 65000000000000 | AD36: =AD35 + IF(W36<>W35, 1, 0) -> 1 | AE36: =IF(AD35<>AD36, 1, AE35) + IF(X36<>X35, 1, 0) -> 2 | AF36: =IF(AE35<>AE36, 1, AF35) + IF(Y36<>Y35, 1, 0) -> 6 | AG36: =IF(AF35<>AF36, 1, AG35) + IF(Z36<>Z35, 1, 0) -> 4 | AH36: =IF(AG35<>AG36, 1, AH35) + IF(AA36<>AA35, 1, 0) -> 1 | AI36: =IF(AH35<>AH36, 1, AI35) + IF(AB36<>AB35, 1, 0) -> 1 | AK36: =IF(AA36<>AA35, "L5", IF(Z36<>Z35, "L4", IF(Y36<>Y35, "L3", IF(X36<>X35, "L2", IF(W36<>W35, "L1", "L1" ) ) ) ) ) -> L4 | AM36: null | AN36: =IF(EXACT($AK35, "L1"), $W35, AN35) -> 65000000000001 | AO36: =IF(EXACT($AK35, "L1"), $W35, IF(EXACT($AK35, "L2"), $X35, AO35)) -> 65000000000002 | AP36: =IF(EXACT($AK35, "L1"), $W35, IF(EXACT($AK35, "L2"), $X35, IF(EXACT($AK35, "L3"), $Y35, AP35))) -> 65000000000027 | AQ36: =IF(EXACT($AK35, "L1"), $W35, IF(EXACT($AK35, "L2"), $X35, IF(EXACT($AK35, "L3"), $Y35, IF(EXACT($AK35, "L4"), $Z35, AQ35)))) -> 65000000000030 | AS36: =IF(EXACT($AK36, "L1"), AM36, IF(EXACT($AK36, "L2"), AN36, IF(EXACT($AK36, "L3"), AO36, IF(EXACT($AK36, "L4"), AP36, IF(EXACT($AK36, "L5"), AQ36, ""))))) -> 65000000000027 | AU36: =IF(AND(EXACT(B36, ""), EXACT(D36, ""), EXACT(F36, ""), EXACT(H36, ""), EXACT(J36, ""), EXACT(L36, "")), "", CONCATENATE( "PERFORM * FROM ""SchData-OLTP-Accounting"".""Func_TblChartOfAccount_SET""(varSystemLoginSession, null, null, null, varInstitutionBranchID, 62000000000001::bigint,'", IF(EXACT(B36, ""), IF(EXACT(D36, ""), IF(EXACT(F36, ""), IF(EXACT(H36, ""), IF(EXACT(J36, ""), IF(EXACT(L36, ""), "", L36), J36), H36), F36), D36), B36), "', '", IF(EXACT(B36, ""), IF(EXACT(D36, ""), IF(EXACT(F36, ""), IF(EXACT(H36, ""), IF(EXACT(J36, ""), IF(EXACT(L36, ""), "", M36), K36), I36), G36), E36), C36), "', ", IF(EXACT(J36, ""), "62000000000001::bigint", IF((RIGHT(J36, 2)*1 = 1), "62000000000001::bigint", IF((RIGHT(J36, 2)*1 = 2), "62000000000002::bigint", "null"))), ", '2016-01-01 00:00:00'::timestamp, null::timestamp, ", AW36, "::bigint, 66000000000001::bigint);")) -> PERFORM * FROM "SchData-OLTP-Accounting"."Func_TblChartOfAccount_SET"(varSystemLoginSession, null, null, null, varInstitutionBranchID, 62000000000001::bigint,'1-1503', 'Prepaid Tax 23', 62000000000001::bigint, '2016-01-01 00:00:00'::timestamp, null::timestamp, 65000000000027::bigint, 66000000000001::bigint); | AV36: =IF(AND(EXACT($B36, ""), EXACT($D36, ""), EXACT($F36, ""), EXACT($H36, ""), EXACT($J36, ""), EXACT($L36, "")), "", V36) -> 65000000000032 | AW36: =AS36 -> 65000000000027 | AY36: =IF(AND(EXACT($B36, ""), EXACT($D36, ""), EXACT($F36, ""), EXACT($H36, ""), EXACT($J36, ""), EXACT($L36, "")), "", IF(NOT(EXACT($B36, "")), "null", IF(NOT(EXACT($D36, "")), IF($W35<>$W34, $W35, $W36), IF(NOT(EXACT($F36, "")), IF($X35<>$X34, $X35, IF($W35<>$W34, $W35, $X36)), IF(NOT(EXACT($H36, "")), IF($Y35<>$Y34, $Y35, IF($X35<>$X34, $X35, IF($W35<>$W34, $W35, $Y36))), IF(NOT(EXACT($J36, "")), IF($Z35<>$Z34, $Z35, IF($Y35<>$Y34, $Y35, IF($X35<>$X34, $X35, IF($W35<>$W34, $W35, $Z36)))), IF(NOT(EXACT($L36, "")), IF($AA35<>$AA34, $AA35, IF($Z35<>$Z34, $Z35, IF($Y35<>$Y34, $Y35, IF($X35<>$X34, $X35, IF($W35<>$W34, $W35, $AA36))))), "others"))))))) -> 65000000000027 | BA36: =BA35 + IF(EXACT(BB36, ""), 0, 1) -> 65000000000032 | BB36: =IF(AND(EXACT($B36, ""), EXACT($D36, ""), EXACT($F36, ""), EXACT($H36, ""), EXACT($J36, ""), EXACT($L36, "")), "", CONCATENATE( "PERFORM * FROM ""SchData-OLTP-Accounting"".""Func_TblChartOfAccount_SET""(varSystemLoginSession, null, null, null, null, null, varInstitutionBranchID, 62000000000001::bigint,'", IF(EXACT($B36, ""), IF(EXACT($D36, ""), IF(EXACT($F36, ""), IF(EXACT($H36, ""), IF(EXACT($J36, ""), IF(EXACT($L36, ""), "", $L36), $J36), $H36), $F36), $D36), $B36), "', '", IF(EXACT($B36, ""), IF(EXACT($D36, ""), IF(EXACT($F36, ""), IF(EXACT($H36, ""), IF(EXACT($J36, ""), IF(EXACT($L36, ""), "", $M36), $K36), $I36), $G36), $E36), $C36), "', ", IF(EXACT($J36, ""), "62000000000001::bigint", IF((RIGHT($J36, 2)*1 = 1), "62000000000001::bigint", IF((RIGHT($J36, 2)*1 = 2), "62000000000002::bigint", "null"))), ", '2016-01-01 00:00:00'::timestamp, null::timestamp, ", $AW36, "::bigint, 66000000000001::bigint, ", IF(EXACT(LEFT(IF(EXACT($B36, ""), IF(EXACT($D36, ""), IF(EXACT($F36, ""), IF(EXACT($H36, ""), IF(EXACT($J36, ""), IF(EXACT($L36, ""), "", $L36), $J36), $H36), $F36), $D36), $B36), 1), "1"), "TRUE", "FALSE"), "::boolean);")) -> PERFORM * FROM "SchData-OLTP-Accounting"."Func_TblChartOfAccount_SET"(varSystemLoginSession, null, null, null, null, null, varInstitutionBranchID, 62000000000001::bigint,'1-1503', 'Prepaid Tax 23', 62000000000001::bigint, '2016-01-01 00:00:00'::timestamp, null::timestamp, 65000000000027::bigint, 66000000000001::bigint, TRUE::boolean);
J37: 1-1503.01 | K37: Prepaid Tax 23 (IDR) | O37: =IF(EXACT($B37, ""), $O36, $B37) -> 1-0000 | P37: =IF(EXACT($D37, ""), $P36, $D37) -> 1-1000 | Q37: =IF(EXACT($F37, ""), $Q36, $F37) -> 1-1500 | R37: =IF(EXACT($H37, ""), $R36, $H37) -> 1-1503 | S37: =IF(EXACT($J37, ""), $S36, $J37) -> 1-1503.01 | T37: =IF(EXACT($L37, ""), $T36, $L37) | V37: =V36+IF(AND(EXACT(B37, ""), EXACT(D37, ""), EXACT(F37, ""), EXACT(H37, ""), EXACT(J37, ""), EXACT(L37, "")), 0, 1) -> 65000000000033 | W37: =IF(EXACT($B37, ""), $W36, $V37) -> 65000000000001 | X37: =IF(EXACT($D37, ""), $X36, $V37) -> 65000000000002 | Y37: =IF(EXACT($F37, ""), $Y36, $V37) -> 65000000000027 | Z37: =IF(EXACT($H37, ""), $Z36, $V37) -> 65000000000032 | AA37: =IF(EXACT($J37, ""), $AA36, $V37) -> 65000000000033 | AB37: =IF(EXACT($L37, ""), $AB36, $V37) -> 65000000000000 | AD37: =AD36 + IF(W37<>W36, 1, 0) -> 1 | AE37: =IF(AD36<>AD37, 1, AE36) + IF(X37<>X36, 1, 0) -> 2 | AF37: =IF(AE36<>AE37, 1, AF36) + IF(Y37<>Y36, 1, 0) -> 6 | AG37: =IF(AF36<>AF37, 1, AG36) + IF(Z37<>Z36, 1, 0) -> 4 | AH37: =IF(AG36<>AG37, 1, AH36) + IF(AA37<>AA36, 1, 0) -> 2 | AI37: =IF(AH36<>AH37, 1, AI36) + IF(AB37<>AB36, 1, 0) -> 1 | AK37: =IF(AA37<>AA36, "L5", IF(Z37<>Z36, "L4", IF(Y37<>Y36, "L3", IF(X37<>X36, "L2", IF(W37<>W36, "L1", "L1" ) ) ) ) ) -> L5 | AM37: null | AN37: =IF(EXACT($AK36, "L1"), $W36, AN36) -> 65000000000001 | AO37: =IF(EXACT($AK36, "L1"), $W36, IF(EXACT($AK36, "L2"), $X36, AO36)) -> 65000000000002 | AP37: =IF(EXACT($AK36, "L1"), $W36, IF(EXACT($AK36, "L2"), $X36, IF(EXACT($AK36, "L3"), $Y36, AP36))) -> 65000000000027 | AQ37: =IF(EXACT($AK36, "L1"), $W36, IF(EXACT($AK36, "L2"), $X36, IF(EXACT($AK36, "L3"), $Y36, IF(EXACT($AK36, "L4"), $Z36, AQ36)))) -> 65000000000032 | AS37: =IF(EXACT($AK37, "L1"), AM37, IF(EXACT($AK37, "L2"), AN37, IF(EXACT($AK37, "L3"), AO37, IF(EXACT($AK37, "L4"), AP37, IF(EXACT($AK37, "L5"), AQ37, ""))))) -> 65000000000032 | AU37: =IF(AND(EXACT(B37, ""), EXACT(D37, ""), EXACT(F37, ""), EXACT(H37, ""), EXACT(J37, ""), EXACT(L37, "")), "", CONCATENATE( "PERFORM * FROM ""SchData-OLTP-Accounting"".""Func_TblChartOfAccount_SET""(varSystemLoginSession, null, null, null, varInstitutionBranchID, 62000000000001::bigint,'", IF(EXACT(B37, ""), IF(EXACT(D37, ""), IF(EXACT(F37, ""), IF(EXACT(H37, ""), IF(EXACT(J37, ""), IF(EXACT(L37, ""), "", L37), J37), H37), F37), D37), B37), "', '", IF(EXACT(B37, ""), IF(EXACT(D37, ""), IF(EXACT(F37, ""), IF(EXACT(H37, ""), IF(EXACT(J37, ""), IF(EXACT(L37, ""), "", M37), K37), I37), G37), E37), C37), "', ", IF(EXACT(J37, ""), "62000000000001::bigint", IF((RIGHT(J37, 2)*1 = 1), "62000000000001::bigint", IF((RIGHT(J37, 2)*1 = 2), "62000000000002::bigint", "null"))), ", '2016-01-01 00:00:00'::timestamp, null::timestamp, ", AW37, "::bigint, 66000000000001::bigint);")) -> PERFORM * FROM "SchData-OLTP-Accounting"."Func_TblChartOfAccount_SET"(varSystemLoginSession, null, null, null, varInstitutionBranchID, 62000000000001::bigint,'1-1503.01', 'Prepaid Tax 23 (IDR)', 62000000000001::bigint, '2016-01-01 00:00:00'::timestamp, null::timestamp, 65000000000032::bigint, 66000000000001::bigint); | AV37: =IF(AND(EXACT($B37, ""), EXACT($D37, ""), EXACT($F37, ""), EXACT($H37, ""), EXACT($J37, ""), EXACT($L37, "")), "", V37) -> 65000000000033 | AW37: =AS37 -> 65000000000032 | AY37: =IF(AND(EXACT($B37, ""), EXACT($D37, ""), EXACT($F37, ""), EXACT($H37, ""), EXACT($J37, ""), EXACT($L37, "")), "", IF(NOT(EXACT($B37, "")), "null", IF(NOT(EXACT($D37, "")), IF($W36<>$W35, $W36, $W37), IF(NOT(EXACT($F37, "")), IF($X36<>$X35, $X36, IF($W36<>$W35, $W36, $X37)), IF(NOT(EXACT($H37, "")), IF($Y36<>$Y35, $Y36, IF($X36<>$X35, $X36, IF($W36<>$W35, $W36, $Y37))), IF(NOT(EXACT($J37, "")), IF($Z36<>$Z35, $Z36, IF($Y36<>$Y35, $Y36, IF($X36<>$X35, $X36, IF($W36<>$W35, $W36, $Z37)))), IF(NOT(EXACT($L37, "")), IF($AA36<>$AA35, $AA36, IF($Z36<>$Z35, $Z36, IF($Y36<>$Y35, $Y36, IF($X36<>$X35, $X36, IF($W36<>$W35, $W36, $AA37))))), "others"))))))) -> 65000000000032 | BA37: =BA36 + IF(EXACT(BB37, ""), 0, 1) -> 65000000000033 | BB37: =IF(AND(EXACT($B37, ""), EXACT($D37, ""), EXACT($F37, ""), EXACT($H37, ""), EXACT($J37, ""), EXACT($L37, "")), "", CONCATENATE( "PERFORM * FROM ""SchData-OLTP-Accounting"".""Func_TblChartOfAccount_SET""(varSystemLoginSession, null, null, null, null, null, varInstitutionBranchID, 62000000000001::bigint,'", IF(EXACT($B37, ""), IF(EXACT($D37, ""), IF(EXACT($F37, ""), IF(EXACT($H37, ""), IF(EXACT($J37, ""), IF(EXACT($L37, ""), "", $L37), $J37), $H37), $F37), $D37), $B37), "', '", IF(EXACT($B37, ""), IF(EXACT($D37, ""), IF(EXACT($F37, ""), IF(EXACT($H37, ""), IF(EXACT($J37, ""), IF(EXACT($L37, ""), "", $M37), $K37), $I37), $G37), $E37), $C37), "', ", IF(EXACT($J37, ""), "62000000000001::bigint", IF((RIGHT($J37, 2)*1 = 1), "62000000000001::bigint", IF((RIGHT($J37, 2)*1 = 2), "62000000000002::bigint", "null"))), ", '2016-01-01 00:00:00'::timestamp, null::timestamp, ", $AW37, "::bigint, 66000000000001::bigint, ", IF(EXACT(LEFT(IF(EXACT($B37, ""), IF(EXACT($D37, ""), IF(EXACT($F37, ""), IF(EXACT($H37, ""), IF(EXACT($J37, ""), IF(EXACT($L37, ""), "", $L37), $J37), $H37), $F37), $D37), $B37), 1), "1"), "TRUE", "FALSE"), "::boolean);")) -> PERFORM * FROM "SchData-OLTP-Accounting"."Func_TblChartOfAccount_SET"(varSystemLoginSession, null, null, null, null, null, varInstitutionBranchID, 62000000000001::bigint,'1-1503.01', 'Prepaid Tax 23 (IDR)', 62000000000001::bigint, '2016-01-01 00:00:00'::timestamp, null::timestamp, 65000000000032::bigint, 66000000000001::bigint, TRUE::boolean);
H38: 1-1504 | I38: Prepaid Tax 25 | O38: =IF(EXACT($B38, ""), $O37, $B38) -> 1-0000 | P38: =IF(EXACT($D38, ""), $P37, $D38) -> 1-1000 | Q38: =IF(EXACT($F38, ""), $Q37, $F38) -> 1-1500 | R38: =IF(EXACT($H38, ""), $R37, $H38) -> 1-1504 | S38: =IF(EXACT($J38, ""), $S37, $J38) -> 1-1503.01 | T38: =IF(EXACT($L38, ""), $T37, $L38) | V38: =V37+IF(AND(EXACT(B38, ""), EXACT(D38, ""), EXACT(F38, ""), EXACT(H38, ""), EXACT(J38, ""), EXACT(L38, "")), 0, 1) -> 65000000000034 | W38: =IF(EXACT($B38, ""), $W37, $V38) -> 65000000000001 | X38: =IF(EXACT($D38, ""), $X37, $V38) -> 65000000000002 | Y38: =IF(EXACT($F38, ""), $Y37, $V38) -> 65000000000027 | Z38: =IF(EXACT($H38, ""), $Z37, $V38) -> 65000000000034 | AA38: =IF(EXACT($J38, ""), $AA37, $V38) -> 65000000000033 | AB38: =IF(EXACT($L38, ""), $AB37, $V38) -> 65000000000000 | AD38: =AD37 + IF(W38<>W37, 1, 0) -> 1 | AE38: =IF(AD37<>AD38, 1, AE37) + IF(X38<>X37, 1, 0) -> 2 | AF38: =IF(AE37<>AE38, 1, AF37) + IF(Y38<>Y37, 1, 0) -> 6 | AG38: =IF(AF37<>AF38, 1, AG37) + IF(Z38<>Z37, 1, 0) -> 5 | AH38: =IF(AG37<>AG38, 1, AH37) + IF(AA38<>AA37, 1, 0) -> 1 | AI38: =IF(AH37<>AH38, 1, AI37) + IF(AB38<>AB37, 1, 0) -> 1 | AK38: =IF(AA38<>AA37, "L5", IF(Z38<>Z37, "L4", IF(Y38<>Y37, "L3", IF(X38<>X37, "L2", IF(W38<>W37, "L1", "L1" ) ) ) ) ) -> L4 | AM38: null | AN38: =IF(EXACT($AK37, "L1"), $W37, AN37) -> 65000000000001 | AO38: =IF(EXACT($AK37, "L1"), $W37, IF(EXACT($AK37, "L2"), $X37, AO37)) -> 65000000000002 | AP38: =IF(EXACT($AK37, "L1"), $W37, IF(EXACT($AK37, "L2"), $X37, IF(EXACT($AK37, "L3"), $Y37, AP37))) -> 65000000000027 | AQ38: =IF(EXACT($AK37, "L1"), $W37, IF(EXACT($AK37, "L2"), $X37, IF(EXACT($AK37, "L3"), $Y37, IF(EXACT($AK37, "L4"), $Z37, AQ37)))) -> 65000000000032 | AS38: =IF(EXACT($AK38, "L1"), AM38, IF(EXACT($AK38, "L2"), AN38, IF(EXACT($AK38, "L3"), AO38, IF(EXACT($AK38, "L4"), AP38, IF(EXACT($AK38, "L5"), AQ38, ""))))) -> 65000000000027 | AU38: =IF(AND(EXACT(B38, ""), EXACT(D38, ""), EXACT(F38, ""), EXACT(H38, ""), EXACT(J38, ""), EXACT(L38, "")), "", CONCATENATE( "PERFORM * FROM ""SchData-OLTP-Accounting"".""Func_TblChartOfAccount_SET""(varSystemLoginSession, null, null, null, varInstitutionBranchID, 62000000000001::bigint,'", IF(EXACT(B38, ""), IF(EXACT(D38, ""), IF(EXACT(F38, ""), IF(EXACT(H38, ""), IF(EXACT(J38, ""), IF(EXACT(L38, ""), "", L38), J38), H38), F38), D38), B38), "', '", IF(EXACT(B38, ""), IF(EXACT(D38, ""), IF(EXACT(F38, ""), IF(EXACT(H38, ""), IF(EXACT(J38, ""), IF(EXACT(L38, ""), "", M38), K38), I38), G38), E38), C38), "', ", IF(EXACT(J38, ""), "62000000000001::bigint", IF((RIGHT(J38, 2)*1 = 1), "62000000000001::bigint", IF((RIGHT(J38, 2)*1 = 2), "62000000000002::bigint", "null"))), ", '2016-01-01 00:00:00'::timestamp, null::timestamp, ", AW38, "::bigint, 66000000000001::bigint);")) -> PERFORM * FROM "SchData-OLTP-Accounting"."Func_TblChartOfAccount_SET"(varSystemLoginSession, null, null, null, varInstitutionBranchID, 62000000000001::bigint,'1-1504', 'Prepaid Tax 25', 62000000000001::bigint, '2016-01-01 00:00:00'::timestamp, null::timestamp, 65000000000027::bigint, 66000000000001::bigint); | AV38: =IF(AND(EXACT($B38, ""), EXACT($D38, ""), EXACT($F38, ""), EXACT($H38, ""), EXACT($J38, ""), EXACT($L38, "")), "", V38) -> 65000000000034 | AW38: =AS38 -> 65000000000027 | AY38: =IF(AND(EXACT($B38, ""), EXACT($D38, ""), EXACT($F38, ""), EXACT($H38, ""), EXACT($J38, ""), EXACT($L38, "")), "", IF(NOT(EXACT($B38, "")), "null", IF(NOT(EXACT($D38, "")), IF($W37<>$W36, $W37, $W38), IF(NOT(EXACT($F38, "")), IF($X37<>$X36, $X37, IF($W37<>$W36, $W37, $X38)), IF(NOT(EXACT($H38, "")), IF($Y37<>$Y36, $Y37, IF($X37<>$X36, $X37, IF($W37<>$W36, $W37, $Y38))), IF(NOT(EXACT($J38, "")), IF($Z37<>$Z36, $Z37, IF($Y37<>$Y36, $Y37, IF($X37<>$X36, $X37, IF($W37<>$W36, $W37, $Z38)))), IF(NOT(EXACT($L38, "")), IF($AA37<>$AA36, $AA37, IF($Z37<>$Z36, $Z37, IF($Y37<>$Y36, $Y37, IF($X37<>$X36, $X37, IF($W37<>$W36, $W37, $AA38))))), "others"))))))) -> 65000000000027 | BA38: =BA37 + IF(EXACT(BB38, ""), 0, 1) -> 65000000000034 | BB38: =IF(AND(EXACT($B38, ""), EXACT($D38, ""), EXACT($F38, ""), EXACT($H38, ""), EXACT($J38, ""), EXACT($L38, "")), "", CONCATENATE( "PERFORM * FROM ""SchData-OLTP-Accounting"".""Func_TblChartOfAccount_SET""(varSystemLoginSession, null, null, null, null, null, varInstitutionBranchID, 62000000000001::bigint,'", IF(EXACT($B38, ""), IF(EXACT($D38, ""), IF(EXACT($F38, ""), IF(EXACT($H38, ""), IF(EXACT($J38, ""), IF(EXACT($L38, ""), "", $L38), $J38), $H38), $F38), $D38), $B38), "', '", IF(EXACT($B38, ""), IF(EXACT($D38, ""), IF(EXACT($F38, ""), IF(EXACT($H38, ""), IF(EXACT($J38, ""), IF(EXACT($L38, ""), "", $M38), $K38), $I38), $G38), $E38), $C38), "', ", IF(EXACT($J38, ""), "62000000000001::bigint", IF((RIGHT($J38, 2)*1 = 1), "62000000000001::bigint", IF((RIGHT($J38, 2)*1 = 2), "62000000000002::bigint", "null"))), ", '2016-01-01 00:00:00'::timestamp, null::timestamp, ", $AW38, "::bigint, 66000000000001::bigint, ", IF(EXACT(LEFT(IF(EXACT($B38, ""), IF(EXACT($D38, ""), IF(EXACT($F38, ""), IF(EXACT($H38, ""), IF(EXACT($J38, ""), IF(EXACT($L38, ""), "", $L38), $J38), $H38), $F38), $D38), $B38), 1), "1"), "TRUE", "FALSE"), "::boolean);")) -> PERFORM * FROM "SchData-OLTP-Accounting"."Func_TblChartOfAccount_SET"(varSystemLoginSession, null, null, null, null, null, varInstitutionBranchID, 62000000000001::bigint,'1-1504', 'Prepaid Tax 25', 62000000000001::bigint, '2016-01-01 00:00:00'::timestamp, null::timestamp, 65000000000027::bigint, 66000000000001::bigint, TRUE::boolean);
J39: 1-1504.01 | K39: Prepaid Tax 25 (IDR) | O39: =IF(EXACT($B39, ""), $O38, $B39) -> 1-0000 | P39: =IF(EXACT($D39, ""), $P38, $D39) -> 1-1000 | Q39: =IF(EXACT($F39, ""), $Q38, $F39) -> 1-1500 | R39: =IF(EXACT($H39, ""), $R38, $H39) -> 1-1504 | S39: =IF(EXACT($J39, ""), $S38, $J39) -> 1-1504.01 | T39: =IF(EXACT($L39, ""), $T38, $L39) | V39: =V38+IF(AND(EXACT(B39, ""), EXACT(D39, ""), EXACT(F39, ""), EXACT(H39, ""), EXACT(J39, ""), EXACT(L39, "")), 0, 1) -> 65000000000035 | W39: =IF(EXACT($B39, ""), $W38, $V39) -> 65000000000001 | X39: =IF(EXACT($D39, ""), $X38, $V39) -> 65000000000002 | Y39: =IF(EXACT($F39, ""), $Y38, $V39) -> 65000000000027 | Z39: =IF(EXACT($H39, ""), $Z38, $V39) -> 65000000000034 | AA39: =IF(EXACT($J39, ""), $AA38, $V39) -> 65000000000035 | AB39: =IF(EXACT($L39, ""), $AB38, $V39) -> 65000000000000 | AD39: =AD38 + IF(W39<>W38, 1, 0) -> 1 | AE39: =IF(AD38<>AD39, 1, AE38) + IF(X39<>X38, 1, 0) -> 2 | AF39: =IF(AE38<>AE39, 1, AF38) + IF(Y39<>Y38, 1, 0) -> 6 | AG39: =IF(AF38<>AF39, 1, AG38) + IF(Z39<>Z38, 1, 0) -> 5 | AH39: =IF(AG38<>AG39, 1, AH38) + IF(AA39<>AA38, 1, 0) -> 2 | AI39: =IF(AH38<>AH39, 1, AI38) + IF(AB39<>AB38, 1, 0) -> 1 | AK39: =IF(AA39<>AA38, "L5", IF(Z39<>Z38, "L4", IF(Y39<>Y38, "L3", IF(X39<>X38, "L2", IF(W39<>W38, "L1", "L1" ) ) ) ) ) -> L5 | AM39: null | AN39: =IF(EXACT($AK38, "L1"), $W38, AN38) -> 65000000000001 | AO39: =IF(EXACT($AK38, "L1"), $W38, IF(EXACT($AK38, "L2"), $X38, AO38)) -> 65000000000002 | AP39: =IF(EXACT($AK38, "L1"), $W38, IF(EXACT($AK38, "L2"), $X38, IF(EXACT($AK38, "L3"), $Y38, AP38))) -> 65000000000027 | AQ39: =IF(EXACT($AK38, "L1"), $W38, IF(EXACT($AK38, "L2"), $X38, IF(EXACT($AK38, "L3"), $Y38, IF(EXACT($AK38, "L4"), $Z38, AQ38)))) -> 65000000000034 | AS39: =IF(EXACT($AK39, "L1"), AM39, IF(EXACT($AK39, "L2"), AN39, IF(EXACT($AK39, "L3"), AO39, IF(EXACT($AK39, "L4"), AP39, IF(EXACT($AK39, "L5"), AQ39, ""))))) -> 65000000000034 | AU39: =IF(AND(EXACT(B39, ""), EXACT(D39, ""), EXACT(F39, ""), EXACT(H39, ""), EXACT(J39, ""), EXACT(L39, "")), "", CONCATENATE( "PERFORM * FROM ""SchData-OLTP-Accounting"".""Func_TblChartOfAccount_SET""(varSystemLoginSession, null, null, null, varInstitutionBranchID, 62000000000001::bigint,'", IF(EXACT(B39, ""), IF(EXACT(D39, ""), IF(EXACT(F39, ""), IF(EXACT(H39, ""), IF(EXACT(J39, ""), IF(EXACT(L39, ""), "", L39), J39), H39), F39), D39), B39), "', '", IF(EXACT(B39, ""), IF(EXACT(D39, ""), IF(EXACT(F39, ""), IF(EXACT(H39, ""), IF(EXACT(J39, ""), IF(EXACT(L39, ""), "", M39), K39), I39), G39), E39), C39), "', ", IF(EXACT(J39, ""), "62000000000001::bigint", IF((RIGHT(J39, 2)*1 = 1), "62000000000001::bigint", IF((RIGHT(J39, 2)*1 = 2), "62000000000002::bigint", "null"))), ", '2016-01-01 00:00:00'::timestamp, null::timestamp, ", AW39, "::bigint, 66000000000001::bigint);")) -> PERFORM * FROM "SchData-OLTP-Accounting"."Func_TblChartOfAccount_SET"(varSystemLoginSession, null, null, null, varInstitutionBranchID, 62000000000001::bigint,'1-1504.01', 'Prepaid Tax 25 (IDR)', 62000000000001::bigint, '2016-01-01 00:00:00'::timestamp, null::timestamp, 65000000000034::bigint, 66000000000001::bigint); | AV39: =IF(AND(EXACT($B39, ""), EXACT($D39, ""), EXACT($F39, ""), EXACT($H39, ""), EXACT($J39, ""), EXACT($L39, "")), "", V39) -> 65000000000035 | AW39: =AS39 -> 65000000000034 | AY39: =IF(AND(EXACT($B39, ""), EXACT($D39, ""), EXACT($F39, ""), EXACT($H39, ""), EXACT($J39, ""), EXACT($L39, "")), "", IF(NOT(EXACT($B39, "")), "null", IF(NOT(EXACT($D39, "")), IF($W38<>$W37, $W38, $W39), IF(NOT(EXACT($F39, "")), IF($X38<>$X37, $X38, IF($W38<>$W37, $W38, $X39)), IF(NOT(EXACT($H39, "")), IF($Y38<>$Y37, $Y38, IF($X38<>$X37, $X38, IF($W38<>$W37, $W38, $Y39))), IF(NOT(EXACT($J39, "")), IF($Z38<>$Z37, $Z38, IF($Y38<>$Y37, $Y38, IF($X38<>$X37, $X38, IF($W38<>$W37, $W38, $Z39)))), IF(NOT(EXACT($L39, "")), IF($AA38<>$AA37, $AA38, IF($Z38<>$Z37, $Z38, IF($Y38<>$Y37, $Y38, IF($X38<>$X37, $X38, IF($W38<>$W37, $W38, $AA39))))), "others"))))))) -> 65000000000034 | BA39: =BA38 + IF(EXACT(BB39, ""), 0, 1) -> 65000000000035 | BB39: =IF(AND(EXACT($B39, ""), EXACT($D39, ""), EXACT($F39, ""), EXACT($H39, ""), EXACT($J39, ""), EXACT($L39, "")), "", CONCATENATE( "PERFORM * FROM ""SchData-OLTP-Accounting"".""Func_TblChartOfAccount_SET""(varSystemLoginSession, null, null, null, null, null, varInstitutionBranchID, 62000000000001::bigint,'", IF(EXACT($B39, ""), IF(EXACT($D39, ""), IF(EXACT($F39, ""), IF(EXACT($H39, ""), IF(EXACT($J39, ""), IF(EXACT($L39, ""), "", $L39), $J39), $H39), $F39), $D39), $B39), "', '", IF(EXACT($B39, ""), IF(EXACT($D39, ""), IF(EXACT($F39, ""), IF(EXACT($H39, ""), IF(EXACT($J39, ""), IF(EXACT($L39, ""), "", $M39), $K39), $I39), $G39), $E39), $C39), "', ", IF(EXACT($J39, ""), "62000000000001::bigint", IF((RIGHT($J39, 2)*1 = 1), "62000000000001::bigint", IF((RIGHT($J39, 2)*1 = 2), "62000000000002::bigint", "null"))), ", '2016-01-01 00:00:00'::timestamp, null::timestamp, ", $AW39, "::bigint, 66000000000001::bigint, ", IF(EXACT(LEFT(IF(EXACT($B39, ""), IF(EXACT($D39, ""), IF(EXACT($F39, ""), IF(EXACT($H39, ""), IF(EXACT($J39, ""), IF(EXACT($L39, ""), "", $L39), $J39), $H39), $F39), $D39), $B39), 1), "1"), "TRUE", "FALSE"), "::boolean);")) -> PERFORM * FROM "SchData-OLTP-Accounting"."Func_TblChartOfAccount_SET"(varSystemLoginSession, null, null, null, null, null, varInstitutionBranchID, 62000000000001::bigint,'1-1504.01', 'Prepaid Tax 25 (IDR)', 62000000000001::bigint, '2016-01-01 00:00:00'::timestamp, null::timestamp, 65000000000034::bigint, 66000000000001::bigint, TRUE::boolean);
F40: 1-1600 | G40: Perlengkapan Kantor | O40: =IF(EXACT($B40, ""), $O39, $B40) -> 1-0000 | P40: =IF(EXACT($D40, ""), $P39, $D40) -> 1-1000 | Q40: =IF(EXACT($F40, ""), $Q39, $F40) -> 1-1600 | R40: =IF(EXACT($H40, ""), $R39, $H40) -> 1-1504 | S40: =IF(EXACT($J40, ""), $S39, $J40) -> 1-1504.01 | T40: =IF(EXACT($L40, ""), $T39, $L40) | V40: =V39+IF(AND(EXACT(B40, ""), EXACT(D40, ""), EXACT(F40, ""), EXACT(H40, ""), EXACT(J40, ""), EXACT(L40, "")), 0, 1) -> 65000000000036 | W40: =IF(EXACT($B40, ""), $W39, $V40) -> 65000000000001 | X40: =IF(EXACT($D40, ""), $X39, $V40) -> 65000000000002 | Y40: =IF(EXACT($F40, ""), $Y39, $V40) -> 65000000000036 | Z40: =IF(EXACT($H40, ""), $Z39, $V40) -> 65000000000034 | AA40: =IF(EXACT($J40, ""), $AA39, $V40) -> 65000000000035 | AB40: =IF(EXACT($L40, ""), $AB39, $V40) -> 65000000000000 | AD40: =AD39 + IF(W40<>W39, 1, 0) -> 1 | AE40: =IF(AD39<>AD40, 1, AE39) + IF(X40<>X39, 1, 0) -> 2 | AF40: =IF(AE39<>AE40, 1, AF39) + IF(Y40<>Y39, 1, 0) -> 7 | AG40: =IF(AF39<>AF40, 1, AG39) + IF(Z40<>Z39, 1, 0) -> 1 | AH40: =IF(AG39<>AG40, 1, AH39) + IF(AA40<>AA39, 1, 0) -> 1 | AI40: =IF(AH39<>AH40, 1, AI39) + IF(AB40<>AB39, 1, 0) -> 1 | AK40: =IF(AA40<>AA39, "L5", IF(Z40<>Z39, "L4", IF(Y40<>Y39, "L3", IF(X40<>X39, "L2", IF(W40<>W39, "L1", "L1" ) ) ) ) ) -> L3 | AM40: null | AN40: =IF(EXACT($AK39, "L1"), $W39, AN39) -> 65000000000001 | AO40: =IF(EXACT($AK39, "L1"), $W39, IF(EXACT($AK39, "L2"), $X39, AO39)) -> 65000000000002 | AP40: =IF(EXACT($AK39, "L1"), $W39, IF(EXACT($AK39, "L2"), $X39, IF(EXACT($AK39, "L3"), $Y39, AP39))) -> 65000000000027 | AQ40: =IF(EXACT($AK39, "L1"), $W39, IF(EXACT($AK39, "L2"), $X39, IF(EXACT($AK39, "L3"), $Y39, IF(EXACT($AK39, "L4"), $Z39, AQ39)))) -> 65000000000034 | AS40: =IF(EXACT($AK40, "L1"), AM40, IF(EXACT($AK40, "L2"), AN40, IF(EXACT($AK40, "L3"), AO40, IF(EXACT($AK40, "L4"), AP40, IF(EXACT($AK40, "L5"), AQ40, ""))))) -> 65000000000002 | AU40: =IF(AND(EXACT(B40, ""), EXACT(D40, ""), EXACT(F40, ""), EXACT(H40, ""), EXACT(J40, ""), EXACT(L40, "")), "", CONCATENATE( "PERFORM * FROM ""SchData-OLTP-Accounting"".""Func_TblChartOfAccount_SET""(varSystemLoginSession, null, null, null, varInstitutionBranchID, 62000000000001::bigint,'", IF(EXACT(B40, ""), IF(EXACT(D40, ""), IF(EXACT(F40, ""), IF(EXACT(H40, ""), IF(EXACT(J40, ""), IF(EXACT(L40, ""), "", L40), J40), H40), F40), D40), B40), "', '", IF(EXACT(B40, ""), IF(EXACT(D40, ""), IF(EXACT(F40, ""), IF(EXACT(H40, ""), IF(EXACT(J40, ""), IF(EXACT(L40, ""), "", M40), K40), I40), G40), E40), C40), "', ", IF(EXACT(J40, ""), "62000000000001::bigint", IF((RIGHT(J40, 2)*1 = 1), "62000000000001::bigint", IF((RIGHT(J40, 2)*1 = 2), "62000000000002::bigint", "null"))), ", '2016-01-01 00:00:00'::timestamp, null::timestamp, ", AW40, "::bigint, 66000000000001::bigint);")) -> PERFORM * FROM "SchData-OLTP-Accounting"."Func_TblChartOfAccount_SET"(varSystemLoginSession, null, null, null, varInstitutionBranchID, 62000000000001::bigint,'1-1600', 'Perlengkapan Kantor', 62000000000001::bigint, '2016-01-01 00:00:00'::timestamp, null::timestamp, 65000000000002::bigint, 66000000000001::bigint); | AV40: =IF(AND(EXACT($B40, ""), EXACT($D40, ""), EXACT($F40, ""), EXACT($H40, ""), EXACT($J40, ""), EXACT($L40, "")), "", V40) -> 65000000000036 | AW40: =AS40 -> 65000000000002 | AY40: =IF(AND(EXACT($B40, ""), EXACT($D40, ""), EXACT($F40, ""), EXACT($H40, ""), EXACT($J40, ""), EXACT($L40, "")), "", IF(NOT(EXACT($B40, "")), "null", IF(NOT(EXACT($D40, "")), IF($W39<>$W38, $W39, $W40), IF(NOT(EXACT($F40, "")), IF($X39<>$X38, $X39, IF($W39<>$W38, $W39, $X40)), IF(NOT(EXACT($H40, "")), IF($Y39<>$Y38, $Y39, IF($X39<>$X38, $X39, IF($W39<>$W38, $W39, $Y40))), IF(NOT(EXACT($J40, "")), IF($Z39<>$Z38, $Z39, IF($Y39<>$Y38, $Y39, IF($X39<>$X38, $X39, IF($W39<>$W38, $W39, $Z40)))), IF(NOT(EXACT($L40, "")), IF($AA39<>$AA38, $AA39, IF($Z39<>$Z38, $Z39, IF($Y39<>$Y38, $Y39, IF($X39<>$X38, $X39, IF($W39<>$W38, $W39, $AA40))))), "others"))))))) -> 65000000000002 | BA40: =BA39 + IF(EXACT(BB40, ""), 0, 1) -> 65000000000036 | BB40: =IF(AND(EXACT($B40, ""), EXACT($D40, ""), EXACT($F40, ""), EXACT($H40, ""), EXACT($J40, ""), EXACT($L40, "")), "", CONCATENATE( "PERFORM * FROM ""SchData-OLTP-Accounting"".""Func_TblChartOfAccount_SET""(varSystemLoginSession, null, null, null, null, null, varInstitutionBranchID, 62000000000001::bigint,'", IF(EXACT($B40, ""), IF(EXACT($D40, ""), IF(EXACT($F40, ""), IF(EXACT($H40, ""), IF(EXACT($J40, ""), IF(EXACT($L40, ""), "", $L40), $J40), $H40), $F40), $D40), $B40), "', '", IF(EXACT($B40, ""), IF(EXACT($D40, ""), IF(EXACT($F40, ""), IF(EXACT($H40, ""), IF(EXACT($J40, ""), IF(EXACT($L40, ""), "", $M40), $K40), $I40), $G40), $E40), $C40), "', ", IF(EXACT($J40, ""), "62000000000001::bigint", IF((RIGHT($J40, 2)*1 = 1), "62000000000001::bigint", IF((RIGHT($J40, 2)*1 = 2), "62000000000002::bigint", "null"))), ", '2016-01-01 00:00:00'::timestamp, null::timestamp, ", $AW40, "::bigint, 66000000000001::bigint, ", IF(EXACT(LEFT(IF(EXACT($B40, ""), IF(EXACT($D40, ""), IF(EXACT($F40, ""), IF(EXACT($H40, ""), IF(EXACT($J40, ""), IF(EXACT($L40, ""), "", $L40), $J40), $H40), $F40), $D40), $B40), 1), "1"), "TRUE", "FALSE"), "::boolean);")) -> PERFORM * FROM "SchData-OLTP-Accounting"."Func_TblChartOfAccount_SET"(varSystemLoginSession, null, null, null, null, null, varInstitutionBranchID, 62000000000001::bigint,'1-1600', 'Perlengkapan Kantor', 62000000000001::bigint, '2016-01-01 00:00:00'::timestamp, null::timestamp, 65000000000002::bigint, 66000000000001::bigint, TRUE::boolean);
