Workbook

Sheet MAIN
B2: Ref ID Person | C2: Person Name | D2: Nomor Induk Pekerja | E2: Default Entity | G2: SYS_PID Prediction | H2: SQL Syntax
G3: 32000000000000
B4: =IF(EXACT([1]DataLookUp!$B4, ""), "", [1]DataLookUp!$B4) -> 25000000000001 | C4: =IF(EXACT(B4, ""), "", VLOOKUP(B4, [1]DataLookUp!$B$4:$C$1000, 2,FALSE )) -> Abdollah Syani Siregar | G4: =G3 + IF(EXACT(H4, ""), 0, 1) -> 32000000000001 | H4: =CONCATENATE("PERFORM ""SchData-OLTP-HumanResource"".""Func_TblWorker_SET""(varSystemLoginSession, null::bigint, null::varchar, null::timestamptz, null::timestamptz, null::varchar, varInstitutionBranchID, varBaseCurrencyID, ", B4, "::bigint, ", IF(EXACT(D4, ""), "null", CONCATENATE("'", D4, "'")), "::varchar);") -> PERFORM "SchData-OLTP-HumanResource"."Func_TblWorker_SET"(varSystemLoginSession, null::bigint, null::varchar, null::timestamptz, null::timestamptz, null::varchar, varInstitutionBranchID, varBaseCurrencyID, 25000000000001::bigint, null::varchar);
B5: =IF(EXACT([1]DataLookUp!$B5, ""), "", [1]DataLookUp!$B5) -> 25000000000002 | C5: =IF(EXACT(B5, ""), "", VLOOKUP(B5, [1]DataLookUp!$B$4:$C$1000, 2,FALSE )) -> Abdul Karim | G5: =G4 + IF(EXACT(H5, ""), 0, 1) -> 32000000000002 | H5: =CONCATENATE("PERFORM ""SchData-OLTP-HumanResource"".""Func_TblWorker_SET""(varSystemLoginSession, null::bigint, null::varchar, null::timestamptz, null::timestamptz, null::varchar, varInstitutionBranchID, varBaseCurrencyID, ", B5, "::bigint, ", IF(EXACT(D5, ""), "null", CONCATENATE("'", D5, "'")), "::varchar);") -> PERFORM "SchData-OLTP-HumanResource"."Func_TblWorker_SET"(varSystemLoginSession, null::bigint, null::varchar, null::timestamptz, null::timestamptz, null::varchar, varInstitutionBranchID, varBaseCurrencyID, 25000000000002::bigint, null::varchar);
B6: =IF(EXACT([1]DataLookUp!$B6, ""), "", [1]DataLookUp!$B6) -> 25000000000003 | C6: =IF(EXACT(B6, ""), "", VLOOKUP(B6, [1]DataLookUp!$B$4:$C$1000, 2,FALSE )) -> Abdul Rahman Sitompul | G6: =G5 + IF(EXACT(H6, ""), 0, 1) -> 32000000000003 | H6: =CONCATENATE("PERFORM ""SchData-OLTP-HumanResource"".""Func_TblWorker_SET""(varSystemLoginSession, null::bigint, null::varchar, null::timestamptz, null::timestamptz, null::varchar, varInstitutionBranchID, varBaseCurrencyID, ", B6, "::bigint, ", IF(EXACT(D6, ""), "null", CONCATENATE("'", D6, "'")), "::varchar);") -> PERFORM "SchData-OLTP-HumanResource"."Func_TblWorker_SET"(varSystemLoginSession, null::bigint, null::varchar, null::timestamptz, null::timestamptz, null::varchar, varInstitutionBranchID, varBaseCurrencyID, 25000000000003::bigint, null::varchar);
B7: =IF(EXACT([1]DataLookUp!$B7, ""), "", [1]DataLookUp!$B7) -> 25000000000004 | C7: =IF(EXACT(B7, ""), "", VLOOKUP(B7, [1]DataLookUp!$B$4:$C$1000, 2,FALSE )) -> Abdul Risan | G7: =G6 + IF(EXACT(H7, ""), 0, 1) -> 32000000000004 | H7: =CONCATENATE("PERFORM ""SchData-OLTP-HumanResource"".""Func_TblWorker_SET""(varSystemLoginSession, null::bigint, null::varchar, null::timestamptz, null::timestamptz, null::varchar, varInstitutionBranchID, varBaseCurrencyID, ", B7, "::bigint, ", IF(EXACT(D7, ""), "null", CONCATENATE("'", D7, "'")), "::varchar);") -> PERFORM "SchData-OLTP-HumanResource"."Func_TblWorker_SET"(varSystemLoginSession, null::bigint, null::varchar, null::timestamptz, null::timestamptz, null::varchar, varInstitutionBranchID, varBaseCurrencyID, 25000000000004::bigint, null::varchar);
B8: =IF(EXACT([1]DataLookUp!$B8, ""), "", [1]DataLookUp!$B8) -> 25000000000005 | C8: =IF(EXACT(B8, ""), "", VLOOKUP(B8, [1]DataLookUp!$B$4:$C$1000, 2,FALSE )) -> Abdullah Nabil | G8: =G7 + IF(EXACT(H8, ""), 0, 1) -> 32000000000005 | H8: =CONCATENATE("PERFORM ""SchData-OLTP-HumanResource"".""Func_TblWorker_SET""(varSystemLoginSession, null::bigint, null::varchar, null::timestamptz, null::timestamptz, null::varchar, varInstitutionBranchID, varBaseCurrencyID, ", B8, "::bigint, ", IF(EXACT(D8, ""), "null", CONCATENATE("'", D8, "'")), "::varchar);") -> PERFORM "SchData-OLTP-HumanResource"."Func_TblWorker_SET"(varSystemLoginSession, null::bigint, null::varchar, null::timestamptz, null::timestamptz, null::varchar, varInstitutionBranchID, varBaseCurrencyID, 25000000000005::bigint, null::varchar);
B9: =IF(EXACT([1]DataLookUp!$B9, ""), "", [1]DataLookUp!$B9) -> 25000000000006 | C9: =IF(EXACT(B9, ""), "", VLOOKUP(B9, [1]DataLookUp!$B$4:$C$1000, 2,FALSE )) -> Adhitya Danar | G9: =G8 + IF(EXACT(H9, ""), 0, 1) -> 32000000000006 | H9: =CONCATENATE("PERFORM ""SchData-OLTP-HumanResource"".""Func_TblWorker_SET""(varSystemLoginSession, null::bigint, null::varchar, null::timestamptz, null::timestamptz, null::varchar, varInstitutionBranchID, varBaseCurrencyID, ", B9, "::bigint, ", IF(EXACT(D9, ""), "null", CONCATENATE("'", D9, "'")), "::varchar);") -> PERFORM "SchData-OLTP-HumanResource"."Func_TblWorker_SET"(varSystemLoginSession, null::bigint, null::varchar, null::timestamptz, null::timestamptz, null::varchar, varInstitutionBranchID, varBaseCurrencyID, 25000000000006::bigint, null::varchar);
B10: =IF(EXACT([1]DataLookUp!$B10, ""), "", [1]DataLookUp!$B10) -> 25000000000007 | C10: =IF(EXACT(B10, ""), "", VLOOKUP(B10, [1]DataLookUp!$B$4:$C$1000, 2,FALSE )) -> Adi Ruswandi | D10: 0209251009 | E10: QDC | G10: =G9 + IF(EXACT(H10, ""), 0, 1) -> 32000000000007 | H10: =CONCATENATE("PERFORM ""SchData-OLTP-HumanResource"".""Func_TblWorker_SET""(varSystemLoginSession, null::bigint, null::varchar, null::timestamptz, null::timestamptz, null::varchar, varInstitutionBranchID, varBaseCurrencyID, ", B10, "::bigint, ", IF(EXACT(D10, ""), "null", CONCATENATE("'", D10, "'")), "::varchar);") -> PERFORM "SchData-OLTP-HumanResource"."Func_TblWorker_SET"(varSystemLoginSession, null::bigint, null::varchar, null::timestamptz, null::timestamptz, null::varchar, varInstitutionBranchID, varBaseCurrencyID, 25000000000007::bigint, '0209251009'::varchar);
B11: =IF(EXACT([1]DataLookUp!$B11, ""), "", [1]DataLookUp!$B11) -> 25000000000008 | C11: =IF(EXACT(B11, ""), "", VLOOKUP(B11, [1]DataLookUp!$B$4:$C$1000, 2,FALSE )) -> Adietya Dharmawan | D11: 050321947 | E11: QDC | G11: =G10 + IF(EXACT(H11, ""), 0, 1) -> 32000000000008 | H11: =CONCATENATE("PERFORM ""SchData-OLTP-HumanResource"".""Func_TblWorker_SET""(varSystemLoginSession, null::bigint, null::varchar, null::timestamptz, null::timestamptz, null::varchar, varInstitutionBranchID, varBaseCurrencyID, ", B11, "::bigint, ", IF(EXACT(D11, ""), "null", CONCATENATE("'", D11, "'")), "::varchar);") -> PERFORM "SchData-OLTP-HumanResource"."Func_TblWorker_SET"(varSystemLoginSession, null::bigint, null::varchar, null::timestamptz, null::timestamptz, null::varchar, varInstitutionBranchID, varBaseCurrencyID, 25000000000008::bigint, '050321947'::varchar);
B12: =IF(EXACT([1]DataLookUp!$B12, ""), "", [1]DataLookUp!$B12) -> 25000000000009 | C12: =IF(EXACT(B12, ""), "", VLOOKUP(B12, [1]DataLookUp!$B$4:$C$1000, 2,FALSE )) -> Aditya Yudha Prawira | G12: =G11 + IF(EXACT(H12, ""), 0, 1) -> 32000000000009 | H12: =CONCATENATE("PERFORM ""SchData-OLTP-HumanResource"".""Func_TblWorker_SET""(varSystemLoginSession, null::bigint, null::varchar, null::timestamptz, null::timestamptz, null::varchar, varInstitutionBranchID, varBaseCurrencyID, ", B12, "::bigint, ", IF(EXACT(D12, ""), "null", CONCATENATE("'", D12, "'")), "::varchar);") -> PERFORM "SchData-OLTP-HumanResource"."Func_TblWorker_SET"(varSystemLoginSession, null::bigint, null::varchar, null::timestamptz, null::timestamptz, null::varchar, varInstitutionBranchID, varBaseCurrencyID, 25000000000009::bigint, null::varchar);
B13: =IF(EXACT([1]DataLookUp!$B13, ""), "", [1]DataLookUp!$B13) -> 25000000000010 | C13: =IF(EXACT(B13, ""), "", VLOOKUP(B13, [1]DataLookUp!$B$4:$C$1000, 2,FALSE )) -> Adli Margie | G13: =G12 + IF(EXACT(H13, ""), 0, 1) -> 32000000000010 | H13: =CONCATENATE("PERFORM ""SchData-OLTP-HumanResource"".""Func_TblWorker_SET""(varSystemLoginSession, null::bigint, null::varchar, null::timestamptz, null::timestamptz, null::varchar, varInstitutionBranchID, varBaseCurrencyID, ", B13, "::bigint, ", IF(EXACT(D13, ""), "null", CONCATENATE("'", D13, "'")), "::varchar);") -> PERFORM "SchData-OLTP-HumanResource"."Func_TblWorker_SET"(varSystemLoginSession, null::bigint, null::varchar, null::timestamptz, null::timestamptz, null::varchar, varInstitutionBranchID, varBaseCurrencyID, 25000000000010::bigint, null::varchar);
B14: =IF(EXACT([1]DataLookUp!$B14, ""), "", [1]DataLookUp!$B14) -> 25000000000011 | C14: =IF(EXACT(B14, ""), "", VLOOKUP(B14, [1]DataLookUp!$B$4:$C$1000, 2,FALSE )) -> Afrida Eka Putri | G14: =G13 + IF(EXACT(H14, ""), 0, 1) -> 32000000000011 | H14: =CONCATENATE("PERFORM ""SchData-OLTP-HumanResource"".""Func_TblWorker_SET""(varSystemLoginSession, null::bigint, null::varchar, null::timestamptz, null::timestamptz, null::varchar, varInstitutionBranchID, varBaseCurrencyID, ", B14, "::bigint, ", IF(EXACT(D14, ""), "null", CONCATENATE("'", D14, "'")), "::varchar);") -> PERFORM "SchData-OLTP-HumanResource"."Func_TblWorker_SET"(varSystemLoginSession, null::bigint, null::varchar, null::timestamptz, null::timestamptz, null::varchar, varInstitutionBranchID, varBaseCurrencyID, 25000000000011::bigint, null::varchar);
B15: =IF(EXACT([1]DataLookUp!$B15, ""), "", [1]DataLookUp!$B15) -> 25000000000012 | C15: =IF(EXACT(B15, ""), "", VLOOKUP(B15, [1]DataLookUp!$B$4:$C$1000, 2,FALSE )) -> Agnes Sutedja | D15: 010703020 | E15: QDC | G15: =G14 + IF(EXACT(H15, ""), 0, 1) -> 32000000000012 | H15: =CONCATENATE("PERFORM ""SchData-OLTP-HumanResource"".""Func_TblWorker_SET""(varSystemLoginSession, null::bigint, null::varchar, null::timestamptz, null::timestamptz, null::varchar, varInstitutionBranchID, varBaseCurrencyID, ", B15, "::bigint, ", IF(EXACT(D15, ""), "null", CONCATENATE("'", D15, "'")), "::varchar);") -> PERFORM "SchData-OLTP-HumanResource"."Func_TblWorker_SET"(varSystemLoginSession, null::bigint, null::varchar, null::timestamptz, null::timestamptz, null::varchar, varInstitutionBranchID, varBaseCurrencyID, 25000000000012::bigint, '010703020'::varchar);
B16: =IF(EXACT([1]DataLookUp!$B16, ""), "", [1]DataLookUp!$B16) -> 25000000000013 | C16: =IF(EXACT(B16, ""), "", VLOOKUP(B16, [1]DataLookUp!$B$4:$C$1000, 2,FALSE )) -> Agung Hendarto | G16: =G15 + IF(EXACT(H16, ""), 0, 1) -> 32000000000013 | H16: =CONCATENATE("PERFORM ""SchData-OLTP-HumanResource"".""Func_TblWorker_SET""(varSystemLoginSession, null::bigint, null::varchar, null::timestamptz, null::timestamptz, null::varchar, varInstitutionBranchID, varBaseCurrencyID, ", B16, "::bigint, ", IF(EXACT(D16, ""), "null", CONCATENATE("'", D16, "'")), "::varchar);") -> PERFORM "SchData-OLTP-HumanResource"."Func_TblWorker_SET"(varSystemLoginSession, null::bigint, null::varchar, null::timestamptz, null::timestamptz, null::varchar, varInstitutionBranchID, varBaseCurrencyID, 25000000000013::bigint, null::varchar);
B17: =IF(EXACT([1]DataLookUp!$B17, ""), "", [1]DataLookUp!$B17) -> 25000000000014 | C17: =IF(EXACT(B17, ""), "", VLOOKUP(B17, [1]DataLookUp!$B$4:$C$1000, 2,FALSE )) -> Agus Priyatno Mahmudo | G17: =G16 + IF(EXACT(H17, ""), 0, 1) -> 32000000000014 | H17: =CONCATENATE("PERFORM ""SchData-OLTP-HumanResource"".""Func_TblWorker_SET""(varSystemLoginSession, null::bigint, null::varchar, null::timestamptz, null::timestamptz, null::varchar, varInstitutionBranchID, varBaseCurrencyID, ", B17, "::bigint, ", IF(EXACT(D17, ""), "null", CONCATENATE("'", D17, "'")), "::varchar);") -> PERFORM "SchData-OLTP-HumanResource"."Func_TblWorker_SET"(varSystemLoginSession, null::bigint, null::varchar, null::timestamptz, null::timestamptz, null::varchar, varInstitutionBranchID, varBaseCurrencyID, 25000000000014::bigint, null::varchar);
B18: =IF(EXACT([1]DataLookUp!$B18, ""), "", [1]DataLookUp!$B18) -> 25000000000015 | C18: =IF(EXACT(B18, ""), "", VLOOKUP(B18, [1]DataLookUp!$B$4:$C$1000, 2,FALSE )) -> Agus Salim | D18: 130223978 | E18: QDC | G18: =G17 + IF(EXACT(H18, ""), 0, 1) -> 32000000000015 | H18: =CONCATENATE("PERFORM ""SchData-OLTP-HumanResource"".""Func_TblWorker_SET""(varSystemLoginSession, null::bigint, null::varchar, null::timestamptz, null::timestamptz, null::varchar, varInstitutionBranchID, varBaseCurrencyID, ", B18, "::bigint, ", IF(EXACT(D18, ""), "null", CONCATENATE("'", D18, "'")), "::varchar);") -> PERFORM "SchData-OLTP-HumanResource"."Func_TblWorker_SET"(varSystemLoginSession, null::bigint, null::varchar, null::timestamptz, null::timestamptz, null::varchar, varInstitutionBranchID, varBaseCurrencyID, 25000000000015::bigint, '130223978'::varchar);
B19: =IF(EXACT([1]DataLookUp!$B19, ""), "", [1]DataLookUp!$B19) -> 25000000000016 | C19: =IF(EXACT(B19, ""), "", VLOOKUP(B19, [1]DataLookUp!$B$4:$C$1000, 2,FALSE )) -> Agus Tanto | G19: =G18 + IF(EXACT(H19, ""), 0, 1) -> 32000000000016 | H19: =CONCATENATE("PERFORM ""SchData-OLTP-HumanResource"".""Func_TblWorker_SET""(varSystemLoginSession, null::bigint, null::varchar, null::timestamptz, null::timestamptz, null::varchar, varInstitutionBranchID, varBaseCurrencyID, ", B19, "::bigint, ", IF(EXACT(D19, ""), "null", CONCATENATE("'", D19, "'")), "::varchar);") -> PERFORM "SchData-OLTP-HumanResource"."Func_TblWorker_SET"(varSystemLoginSession, null::bigint, null::varchar, null::timestamptz, null::timestamptz, null::varchar, varInstitutionBranchID, varBaseCurrencyID, 25000000000016::bigint, null::varchar);
B20: =IF(EXACT([1]DataLookUp!$B20, ""), "", [1]DataLookUp!$B20) -> 25000000000017 | C20: =IF(EXACT(B20, ""), "", VLOOKUP(B20, [1]DataLookUp!$B$4:$C$1000, 2,FALSE )) -> Ahmad Faiz Haems Muda | D20: 280314716 | E20: QDC | G20: =G19 + IF(EXACT(H20, ""), 0, 1) -> 32000000000017 | H20: =CONCATENATE("PERFORM ""SchData-OLTP-HumanResource"".""Func_TblWorker_SET""(varSystemLoginSession, null::bigint, null::varchar, null::timestamptz, null::timestamptz, null::varchar, varInstitutionBranchID, varBaseCurrencyID, ", B20, "::bigint, ", IF(EXACT(D20, ""), "null", CONCATENATE("'", D20, "'")), "::varchar);") -> PERFORM "SchData-OLTP-HumanResource"."Func_TblWorker_SET"(varSystemLoginSession, null::bigint, null::varchar, null::timestamptz, null::timestamptz, null::varchar, varInstitutionBranchID, varBaseCurrencyID, 25000000000017::bigint, '280314716'::varchar);
B21: =IF(EXACT([1]DataLookUp!$B21, ""), "", [1]DataLookUp!$B21) -> 25000000000018 | C21: =IF(EXACT(B21, ""), "", VLOOKUP(B21, [1]DataLookUp!$B$4:$C$1000, 2,FALSE )) -> Ahmad Faza | G21: =G20 + IF(EXACT(H21, ""), 0, 1) -> 32000000000018 | H21: =CONCATENATE("PERFORM ""SchData-OLTP-HumanResource"".""Func_TblWorker_SET""(varSystemLoginSession, null::bigint, null::varchar, null::timestamptz, null::timestamptz, null::varchar, varInstitutionBranchID, varBaseCurrencyID, ", B21, "::bigint, ", IF(EXACT(D21, ""), "null", CONCATENATE("'", D21, "'")), "::varchar);") -> PERFORM "SchData-OLTP-HumanResource"."Func_TblWorker_SET"(varSystemLoginSession, null::bigint, null::varchar, null::timestamptz, null::timestamptz, null::varchar, varInstitutionBranchID, varBaseCurrencyID, 25000000000018::bigint, null::varchar);
B22: =IF(EXACT([1]DataLookUp!$B22, ""), "", [1]DataLookUp!$B22) -> 25000000000019 | C22: =IF(EXACT(B22, ""), "", VLOOKUP(B22, [1]DataLookUp!$B$4:$C$1000, 2,FALSE )) -> Ahmad Syaifulloh | D22: 150506222 | E22: QDC | G22: =G21 + IF(EXACT(H22, ""), 0, 1) -> 32000000000019 | H22: =CONCATENATE("PERFORM ""SchData-OLTP-HumanResource"".""Func_TblWorker_SET""(varSystemLoginSession, null::bigint, null::varchar, null::timestamptz, null::timestamptz, null::varchar, varInstitutionBranchID, varBaseCurrencyID, ", B22, "::bigint, ", IF(EXACT(D22, ""), "null", CONCATENATE("'", D22, "'")), "::varchar);") -> PERFORM "SchData-OLTP-HumanResource"."Func_TblWorker_SET"(varSystemLoginSession, null::bigint, null::varchar, null::timestamptz, null::timestamptz, null::varchar, varInstitutionBranchID, varBaseCurrencyID, 25000000000019::bigint, '150506222'::varchar);
B23: =IF(EXACT([1]DataLookUp!$B23, ""), "", [1]DataLookUp!$B23) -> 25000000000020 | C23: =IF(EXACT(B23, ""), "", VLOOKUP(B23, [1]DataLookUp!$B$4:$C$1000, 2,FALSE )) -> Ahmad Zulkarnaen | G23: =G22 + IF(EXACT(H23, ""), 0, 1) -> 32000000000020 | H23: =CONCATENATE("PERFORM ""SchData-OLTP-HumanResource"".""Func_TblWorker_SET""(varSystemLoginSession, null::bigint, null::varchar, null::timestamptz, null::timestamptz, null::varchar, varInstitutionBranchID, varBaseCurrencyID, ", B23, "::bigint, ", IF(EXACT(D23, ""), "null", CONCATENATE("'", D23, "'")), "::varchar);") -> PERFORM "SchData-OLTP-HumanResource"."Func_TblWorker_SET"(varSystemLoginSession, null::bigint, null::varchar, null::timestamptz, null::timestamptz, null::varchar, varInstitutionBranchID, varBaseCurrencyID, 25000000000020::bigint, null::varchar);
B24: =IF(EXACT([1]DataLookUp!$B24, ""), "", [1]DataLookUp!$B24) -> 25000000000021 | C24: =IF(EXACT(B24, ""), "", VLOOKUP(B24, [1]DataLookUp!$B$4:$C$1000, 2,FALSE )) -> Ajan | G24: =G23 + IF(EXACT(H24, ""), 0, 1) -> 32000000000021 | H24: =CONCATENATE("PERFORM ""SchData-OLTP-HumanResource"".""Func_TblWorker_SET""(varSystemLoginSession, null::bigint, null::varchar, null::timestamptz, null::timestamptz, null::varchar, varInstitutionBranchID, varBaseCurrencyID, ", B24, "::bigint, ", IF(EXACT(D24, ""), "null", CONCATENATE("'", D24, "'")), "::varchar);") -> PERFORM "SchData-OLTP-HumanResource"."Func_TblWorker_SET"(varSystemLoginSession, null::bigint, null::varchar, null::timestamptz, null::timestamptz, null::varchar, varInstitutionBranchID, varBaseCurrencyID, 25000000000021::bigint, null::varchar);
B25: =IF(EXACT([1]DataLookUp!$B25, ""), "", [1]DataLookUp!$B25) -> 25000000000022 | C25: =IF(EXACT(B25, ""), "", VLOOKUP(B25, [1]DataLookUp!$B$4:$C$1000, 2,FALSE )) -> Al Amin | G25: =G24 + IF(EXACT(H25, ""), 0, 1) -> 32000000000022 | H25: =CONCATENATE("PERFORM ""SchData-OLTP-HumanResource"".""Func_TblWorker_SET""(varSystemLoginSession, null::bigint, null::varchar, null::timestamptz, null::timestamptz, null::varchar, varInstitutionBranchID, varBaseCurrencyID, ", B25, "::bigint, ", IF(EXACT(D25, ""), "null", CONCATENATE("'", D25, "'")), "::varchar);") -> PERFORM "SchData-OLTP-HumanResource"."Func_TblWorker_SET"(varSystemLoginSession, null::bigint, null::varchar, null::timestamptz, null::timestamptz, null::varchar, varInstitutionBranchID, varBaseCurrencyID, 25000000000022::bigint, null::varchar);
B26: =IF(EXACT([1]DataLookUp!$B26, ""), "", [1]DataLookUp!$B26) -> 25000000000023 | C26: =IF(EXACT(B26, ""), "", VLOOKUP(B26, [1]DataLookUp!$B$4:$C$1000, 2,FALSE )) -> Aldi Mulyadi | D26: 141020935 | E26: QDC | G26: =G25 + IF(EXACT(H26, ""), 0, 1) -> 32000000000023 | H26: =CONCATENATE("PERFORM ""SchData-OLTP-HumanResource"".""Func_TblWorker_SET""(varSystemLoginSession, null::bigint, null::varchar, null::timestamptz, null::timestamptz, null::varchar, varInstitutionBranchID, varBaseCurrencyID, ", B26, "::bigint, ", IF(EXACT(D26, ""), "null", CONCATENATE("'", D26, "'")), "::varchar);") -> PERFORM "SchData-OLTP-HumanResource"."Func_TblWorker_SET"(varSystemLoginSession, null::bigint, null::varchar, null::timestamptz, null::timestamptz, null::varchar, varInstitutionBranchID, varBaseCurrencyID, 25000000000023::bigint, '141020935'::varchar);
B27: =IF(EXACT([1]DataLookUp!$B27, ""), "", [1]DataLookUp!$B27) -> 25000000000024 | C27: =IF(EXACT(B27, ""), "", VLOOKUP(B27, [1]DataLookUp!$B$4:$C$1000, 2,FALSE )) -> Alexandri | G27: =G26 + IF(EXACT(H27, ""), 0, 1) -> 32000000000024 | H27: =CONCATENATE("PERFORM ""SchData-OLTP-HumanResource"".""Func_TblWorker_SET""(varSystemLoginSession, null::bigint, null::varchar, null::timestamptz, null::timestamptz, null::varchar, varInstitutionBranchID, varBaseCurrencyID, ", B27, "::bigint, ", IF(EXACT(D27, ""), "null", CONCATENATE("'", D27, "'")), "::varchar);") -> PERFORM "SchData-OLTP-HumanResource"."Func_TblWorker_SET"(varSystemLoginSession, null::bigint, null::varchar, null::timestamptz, null::timestamptz, null::varchar, varInstitutionBranchID, varBaseCurrencyID, 25000000000024::bigint, null::varchar);
B28: =IF(EXACT([1]DataLookUp!$B28, ""), "", [1]DataLookUp!$B28) -> 25000000000025 | C28: =IF(EXACT(B28, ""), "", VLOOKUP(B28, [1]DataLookUp!$B$4:$C$1000, 2,FALSE )) -> Alfaedi | G28: =G27 + IF(EXACT(H28, ""), 0, 1) -> 32000000000025 | H28: =CONCATENATE("PERFORM ""SchData-OLTP-HumanResource"".""Func_TblWorker_SET""(varSystemLoginSession, null::bigint, null::varchar, null::timestamptz, null::timestamptz, null::varchar, varInstitutionBranchID, varBaseCurrencyID, ", B28, "::bigint, ", IF(EXACT(D28, ""), "null", CONCATENATE("'", D28, "'")), "::varchar);") -> PERFORM "SchData-OLTP-HumanResource"."Func_TblWorker_SET"(varSystemLoginSession, null::bigint, null::varchar, null::timestamptz, null::timestamptz, null::varchar, varInstitutionBranchID, varBaseCurrencyID, 25000000000025::bigint, null::varchar);
B29: =IF(EXACT([1]DataLookUp!$B29, ""), "", [1]DataLookUp!$B29) -> 25000000000026 | C29: =IF(EXACT(B29, ""), "", VLOOKUP(B29, [1]DataLookUp!$B$4:$C$1000, 2,FALSE )) -> Ali Wahono | G29: =G28 + IF(EXACT(H29, ""), 0, 1) -> 32000000000026 | H29: =CONCATENATE("PERFORM ""SchData-OLTP-HumanResource"".""Func_TblWorker_SET""(varSystemLoginSession, null::bigint, null::varchar, null::timestamptz, null::timestamptz, null::varchar, varInstitutionBranchID, varBaseCurrencyID, ", B29, "::bigint, ", IF(EXACT(D29, ""), "null", CONCATENATE("'", D29, "'")), "::varchar);") -> PERFORM "SchData-OLTP-HumanResource"."Func_TblWorker_SET"(varSystemLoginSession, null::bigint, null::varchar, null::timestamptz, null::timestamptz, null::varchar, varInstitutionBranchID, varBaseCurrencyID, 25000000000026::bigint, null::varchar);
B30: =IF(EXACT([1]DataLookUp!$B30, ""), "", [1]DataLookUp!$B30) -> 25000000000027 | C30: =IF(EXACT(B30, ""), "", VLOOKUP(B30, [1]DataLookUp!$B$4:$C$1000, 2,FALSE )) -> Alphaliyanri Lasria | G30: =G29 + IF(EXACT(H30, ""), 0, 1) -> 32000000000027 | H30: =CONCATENATE("PERFORM ""SchData-OLTP-HumanResource"".""Func_TblWorker_SET""(varSystemLoginSession, null::bigint, null::varchar, null::timestamptz, null::timestamptz, null::varchar, varInstitutionBranchID, varBaseCurrencyID, ", B30, "::bigint, ", IF(EXACT(D30, ""), "null", CONCATENATE("'", D30, "'")), "::varchar);") -> PERFORM "SchData-OLTP-HumanResource"."Func_TblWorker_SET"(varSystemLoginSession, null::bigint, null::varchar, null::timestamptz, null::timestamptz, null::varchar, varInstitutionBranchID, varBaseCurrencyID, 25000000000027::bigint, null::varchar);
B31: =IF(EXACT([1]DataLookUp!$B31, ""), "", [1]DataLookUp!$B31) -> 25000000000028 | C31: =IF(EXACT(B31, ""), "", VLOOKUP(B31, [1]DataLookUp!$B$4:$C$1000, 2,FALSE )) -> Ambon Rumalean | G31: =G30 + IF(EXACT(H31, ""), 0, 1) -> 32000000000028 | H31: =CONCATENATE("PERFORM ""SchData-OLTP-HumanResource"".""Func_TblWorker_SET""(varSystemLoginSession, null::bigint, null::varchar, null::timestamptz, null::timestamptz, null::varchar, varInstitutionBranchID, varBaseCurrencyID, ", B31, "::bigint, ", IF(EXACT(D31, ""), "null", CONCATENATE("'", D31, "'")), "::varchar);") -> PERFORM "SchData-OLTP-HumanResource"."Func_TblWorker_SET"(varSystemLoginSession, null::bigint, null::varchar, null::timestamptz, null::timestamptz, null::varchar, varInstitutionBranchID, varBaseCurrencyID, 25000000000028::bigint, null::varchar);
B32: =IF(EXACT([1]DataLookUp!$B32, ""), "", [1]DataLookUp!$B32) -> 25000000000029 | C32: =IF(EXACT(B32, ""), "", VLOOKUP(B32, [1]DataLookUp!$B$4:$C$1000, 2,FALSE )) -> Amir Sofyan Hadi | G32: =G31 + IF(EXACT(H32, ""), 0, 1) -> 32000000000029 | H32: =CONCATENATE("PERFORM ""SchData-OLTP-HumanResource"".""Func_TblWorker_SET""(varSystemLoginSession, null::bigint, null::varchar, null::timestamptz, null::timestamptz, null::varchar, varInstitutionBranchID, varBaseCurrencyID, ", B32, "::bigint, ", IF(EXACT(D32, ""), "null", CONCATENATE("'", D32, "'")), "::varchar);") -> PERFORM "SchData-OLTP-HumanResource"."Func_TblWorker_SET"(varSystemLoginSession, null::bigint, null::varchar, null::timestamptz, null::timestamptz, null::varchar, varInstitutionBranchID, varBaseCurrencyID, 25000000000029::bigint, null::varchar);
B33: =IF(EXACT([1]DataLookUp!$B33, ""), "", [1]DataLookUp!$B33) -> 25000000000030 | C33: =IF(EXACT(B33, ""), "", VLOOKUP(B33, [1]DataLookUp!$B$4:$C$1000, 2,FALSE )) -> Anak Agung Netti Ariani | G33: =G32 + IF(EXACT(H33, ""), 0, 1) -> 32000000000030 | H33: =CONCATENATE("PERFORM ""SchData-OLTP-HumanResource"".""Func_TblWorker_SET""(varSystemLoginSession, null::bigint, null::varchar, null::timestamptz, null::timestamptz, null::varchar, varInstitutionBranchID, varBaseCurrencyID, ", B33, "::bigint, ", IF(EXACT(D33, ""), "null", CONCATENATE("'", D33, "'")), "::varchar);") -> PERFORM "SchData-OLTP-HumanResource"."Func_TblWorker_SET"(varSystemLoginSession, null::bigint, null::varchar, null::timestamptz, null::timestamptz, null::varchar, varInstitutionBranchID, varBaseCurrencyID, 25000000000030::bigint, null::varchar);
B34: =IF(EXACT([1]DataLookUp!$B34, ""), "", [1]DataLookUp!$B34) -> 25000000000031 | C34: =IF(EXACT(B34, ""), "", VLOOKUP(B34, [1]DataLookUp!$B$4:$C$1000, 2,FALSE )) -> Andri Gunawan | G34: =G33 + IF(EXACT(H34, ""), 0, 1) -> 32000000000031 | H34: =CONCATENATE("PERFORM ""SchData-OLTP-HumanResource"".""Func_TblWorker_SET""(varSystemLoginSession, null::bigint, null::varchar, null::timestamptz, null::timestamptz, null::varchar, varInstitutionBranchID, varBaseCurrencyID, ", B34, "::bigint, ", IF(EXACT(D34, ""), "null", CONCATENATE("'", D34, "'")), "::varchar);") -> PERFORM "SchData-OLTP-HumanResource"."Func_TblWorker_SET"(varSystemLoginSession, null::bigint, null::varchar, null::timestamptz, null::timestamptz, null::varchar, varInstitutionBranchID, varBaseCurrencyID, 25000000000031::bigint, null::varchar);
B35: =IF(EXACT([1]DataLookUp!$B35, ""), "", [1]DataLookUp!$B35) -> 25000000000032 | C35: =IF(EXACT(B35, ""), "", VLOOKUP(B35, [1]DataLookUp!$B$4:$C$1000, 2,FALSE )) -> Andri Herdiansyah | G35: =G34 + IF(EXACT(H35, ""), 0, 1) -> 32000000000032 | H35: =CONCATENATE("PERFORM ""SchData-OLTP-HumanResource"".""Func_TblWorker_SET""(varSystemLoginSession, null::bigint, null::varchar, null::timestamptz, null::timestamptz, null::varchar, varInstitutionBranchID, varBaseCurrencyID, ", B35, "::bigint, ", IF(EXACT(D35, ""), "null", CONCATENATE("'", D35, "'")), "::varchar);") -> PERFORM "SchData-OLTP-HumanResource"."Func_TblWorker_SET"(varSystemLoginSession, null::bigint, null::varchar, null::timestamptz, null::timestamptz, null::varchar, varInstitutionBranchID, varBaseCurrencyID, 25000000000032::bigint, null::varchar);
B36: =IF(EXACT([1]DataLookUp!$B36, ""), "", [1]DataLookUp!$B36) -> 25000000000033 | C36: =IF(EXACT(B36, ""), "", VLOOKUP(B36, [1]DataLookUp!$B$4:$C$1000, 2,FALSE )) -> Andrie | G36: =G35 + IF(EXACT(H36, ""), 0, 1) -> 32000000000033 | H36: =CONCATENATE("PERFORM ""SchData-OLTP-HumanResource"".""Func_TblWorker_SET""(varSystemLoginSession, null::bigint, null::varchar, null::timestamptz, null::timestamptz, null::varchar, varInstitutionBranchID, varBaseCurrencyID, ", B36, "::bigint, ", IF(EXACT(D36, ""), "null", CONCATENATE("'", D36, "'")), "::varchar);") -> PERFORM "SchData-OLTP-HumanResource"."Func_TblWorker_SET"(varSystemLoginSession, null::bigint, null::varchar, null::timestamptz, null::timestamptz, null::varchar, varInstitutionBranchID, varBaseCurrencyID, 25000000000033::bigint, null::varchar);
B37: =IF(EXACT([1]DataLookUp!$B37, ""), "", [1]DataLookUp!$B37) -> 25000000000034 | C37: =IF(EXACT(B37, ""), "", VLOOKUP(B37, [1]DataLookUp!$B$4:$C$1000, 2,FALSE )) -> Anggina Tri Yudandi | G37: =G36 + IF(EXACT(H37, ""), 0, 1) -> 32000000000034 | H37: =CONCATENATE("PERFORM ""SchData-OLTP-HumanResource"".""Func_TblWorker_SET""(varSystemLoginSession, null::bigint, null::varchar, null::timestamptz, null::timestamptz, null::varchar, varInstitutionBranchID, varBaseCurrencyID, ", B37, "::bigint, ", IF(EXACT(D37, ""), "null", CONCATENATE("'", D37, "'")), "::varchar);") -> PERFORM "SchData-OLTP-HumanResource"."Func_TblWorker_SET"(varSystemLoginSession, null::bigint, null::varchar, null::timestamptz, null::timestamptz, null::varchar, varInstitutionBranchID, varBaseCurrencyID, 25000000000034::bigint, null::varchar);
B38: =IF(EXACT([1]DataLookUp!$B38, ""), "", [1]DataLookUp!$B38) -> 25000000000035 | C38: =IF(EXACT(B38, ""), "", VLOOKUP(B38, [1]DataLookUp!$B$4:$C$1000, 2,FALSE )) -> Anggit Ismiyanto | G38: =G37 + IF(EXACT(H38, ""), 0, 1) -> 32000000000035 | H38: =CONCATENATE("PERFORM ""SchData-OLTP-HumanResource"".""Func_TblWorker_SET""(varSystemLoginSession, null::bigint, null::varchar, null::timestamptz, null::timestamptz, null::varchar, varInstitutionBranchID, varBaseCurrencyID, ", B38, "::bigint, ", IF(EXACT(D38, ""), "null", CONCATENATE("'", D38, "'")), "::varchar);") -> PERFORM "SchData-OLTP-HumanResource"."Func_TblWorker_SET"(varSystemLoginSession, null::bigint, null::varchar, null::timestamptz, null::timestamptz, null::varchar, varInstitutionBranchID, varBaseCurrencyID, 25000000000035::bigint, null::varchar);
... B41: =IF(EXACT([1]DataLookUp!$B41, ""), "", [1]DataLookUp!$B41) -> 25000000000038 | C41: =IF(EXACT(B41, ""), "", VLOOKUP(B41, [1]DataLookUp!$B$4:$C$1000, 2,FALSE )) -> Anna Savitrie | G41: =G40 + IF(EXACT(H41, ""), 0, 1) -> 32000000000038 | H41: =CONCATENATE("PERFORM ""SchData-OLTP-HumanResource"".""Func_TblWorker_SET""(varSystemLoginSession, null::bigint, null::varchar, null::timestamptz, null::timestamptz, null::varchar, varInstitutionBranchID, varBaseCurrencyID, ", B41, "::bigint, ", IF(EXACT(D41, ""), "null", CONCATENATE("'", D41, "'")), "::varchar);") -> PERFORM "SchData-OLTP-HumanResource"."Func_TblWorker_SET"(varSystemLoginSession, null::bigint, null::varchar, null::timestamptz, null::timestamptz, null::varchar, varInstitutionBranchID, varBaseCurrencyID, 25000000000038::bigint, null::varchar);
B42: =IF(EXACT([1]DataLookUp!$B42, ""), "", [1]DataLookUp!$B42) -> 25000000000039 | C42: =IF(EXACT(B42, ""), "", VLOOKUP(B42, [1]DataLookUp!$B$4:$C$1000, 2,FALSE )) -> Annisa Dewi Arumsari | D42: 100419903 | E42: QDC | G42: =G41 + IF(EXACT(H42, ""), 0, 1) -> 32000000000039 | H42: =CONCATENATE("PERFORM ""SchData-OLTP-HumanResource"".""Func_TblWorker_SET""(varSystemLoginSession, null::bigint, null::varchar, null::timestamptz, null::timestamptz, null::varchar, varInstitutionBranchID, varBaseCurrencyID, ", B42, "::bigint, ", IF(EXACT(D42, ""), "null", CONCATENATE("'", D42, "'")), "::varchar);") -> PERFORM "SchData-OLTP-HumanResource"."Func_TblWorker_SET"(varSystemLoginSession, null::bigint, null::varchar, null::timestamptz, null::timestamptz, null::varchar, varInstitutionBranchID, varBaseCurrencyID, 25000000000039::bigint, '100419903'::varchar);
B43: =IF(EXACT([1]DataLookUp!$B43, ""), "", [1]DataLookUp!$B43) -> 25000000000040 | C43: =IF(EXACT(B43, ""), "", VLOOKUP(B43, [1]DataLookUp!$B$4:$C$1000, 2,FALSE )) -> Annyes Sri Maristi | G43: =G42 + IF(EXACT(H43, ""), 0, 1) -> 32000000000040 | H43: =CONCATENATE("PERFORM ""SchData-OLTP-HumanResource"".""Func_TblWorker_SET""(varSystemLoginSession, null::bigint, null::varchar, null::timestamptz, null::timestamptz, null::varchar, varInstitutionBranchID, varBaseCurrencyID, ", B43, "::bigint, ", IF(EXACT(D43, ""), "null", CONCATENATE("'", D43, "'")), "::varchar);") -> PERFORM "SchData-OLTP-HumanResource"."Func_TblWorker_SET"(varSystemLoginSession, null::bigint, null::varchar, null::timestamptz, null::timestamptz, null::varchar, varInstitutionBranchID, varBaseCurrencyID, 25000000000040::bigint, null::varchar);
B44: =IF(EXACT([1]DataLookUp!$B44, ""), "", [1]DataLookUp!$B44) -> 25000000000041 | C44: =IF(EXACT(B44, ""), "", VLOOKUP(B44, [1]DataLookUp!$B$4:$C$1000, 2,FALSE )) -> Antok | G44: =G43 + IF(EXACT(H44, ""), 0, 1) -> 32000000000041 | H44: =CONCATENATE("PERFORM ""SchData-OLTP-HumanResource"".""Func_TblWorker_SET""(varSystemLoginSession, null::bigint, null::varchar, null::timestamptz, null::timestamptz, null::varchar, varInstitutionBranchID, varBaseCurrencyID, ", B44, "::bigint, ", IF(EXACT(D44, ""), "null", CONCATENATE("'", D44, "'")), "::varchar);") -> PERFORM "SchData-OLTP-HumanResource"."Func_TblWorker_SET"(varSystemLoginSession, null::bigint, null::varchar, null::timestamptz, null::timestamptz, null::varchar, varInstitutionBranchID, varBaseCurrencyID, 25000000000041::bigint, null::varchar);
B45: =IF(EXACT([1]DataLookUp!$B45, ""), "", [1]DataLookUp!$B45) -> 25000000000042 | C45: =IF(EXACT(B45, ""), "", VLOOKUP(B45, [1]DataLookUp!$B$4:$C$1000, 2,FALSE )) -> Anton Iryanto | G45: =G44 + IF(EXACT(H45, ""), 0, 1) -> 32000000000042 | H45: =CONCATENATE("PERFORM ""SchData-OLTP-HumanResource"".""Func_TblWorker_SET""(varSystemLoginSession, null::bigint, null::varchar, null::timestamptz, null::timestamptz, null::varchar, varInstitutionBranchID, varBaseCurrencyID, ", B45, "::bigint, ", IF(EXACT(D45, ""), "null", CONCATENATE("'", D45, "'")), "::varchar);") -> PERFORM "SchData-OLTP-HumanResource"."Func_TblWorker_SET"(varSystemLoginSession, null::bigint, null::varchar, null::timestamptz, null::timestamptz, null::varchar, varInstitutionBranchID, varBaseCurrencyID, 25000000000042::bigint, null::varchar);
B46: =IF(EXACT([1]DataLookUp!$B46, ""), "", [1]DataLookUp!$B46) -> 25000000000043 | C46: =IF(EXACT(B46, ""), "", VLOOKUP(B46, [1]DataLookUp!$B$4:$C$1000, 2,FALSE )) -> Antony Pakpahan | G46: =G45 + IF(EXACT(H46, ""), 0, 1) -> 32000000000043 | H46: =CONCATENATE("PERFORM ""SchData-OLTP-HumanResource"".""Func_TblWorker_SET""(varSystemLoginSession, null::bigint, null::varchar, null::timestamptz, null::timestamptz, null::varchar, varInstitutionBranchID, varBaseCurrencyID, ", B46, "::bigint, ", IF(EXACT(D46, ""), "null", CONCATENATE("'", D46, "'")), "::varchar);") -> PERFORM "SchData-OLTP-HumanResource"."Func_TblWorker_SET"(varSystemLoginSession, null::bigint, null::varchar, null::timestamptz, null::timestamptz, null::varchar, varInstitutionBranchID, varBaseCurrencyID, 25000000000043::bigint, null::varchar);
B47: =IF(EXACT([1]DataLookUp!$B47, ""), "", [1]DataLookUp!$B47) -> 25000000000044 | C47: =IF(EXACT(B47, ""), "", VLOOKUP(B47, [1]DataLookUp!$B$4:$C$1000, 2,FALSE )) -> Anugerah Januariansyah | D47: 310821007 | E47: QDC | G47: =G46 + IF(EXACT(H47, ""), 0, 1) -> 32000000000044 | H47: =CONCATENATE("PERFORM ""SchData-OLTP-HumanResource"".""Func_TblWorker_SET""(varSystemLoginSession, null::bigint, null::varchar, null::timestamptz, null::timestamptz, null::varchar, varInstitutionBranchID, varBaseCurrencyID, ", B47, "::bigint, ", IF(EXACT(D47, ""), "null", CONCATENATE("'", D47, "'")), "::varchar);") -> PERFORM "SchData-OLTP-HumanResource"."Func_TblWorker_SET"(varSystemLoginSession, null::bigint, null::varchar, null::timestamptz, null::timestamptz, null::varchar, varInstitutionBranchID, varBaseCurrencyID, 25000000000044::bigint, '310821007'::varchar);
B48: =IF(EXACT([1]DataLookUp!$B48, ""), "", [1]DataLookUp!$B48) -> 25000000000045 | C48: =IF(EXACT(B48, ""), "", VLOOKUP(B48, [1]DataLookUp!$B$4:$C$1000, 2,FALSE )) -> Anwar Purnomo | G48: =G47 + IF(EXACT(H48, ""), 0, 1) -> 32000000000045 | H48: =CONCATENATE("PERFORM ""SchData-OLTP-HumanResource"".""Func_TblWorker_SET""(varSystemLoginSession, null::bigint, null::varchar, null::timestamptz, null::timestamptz, null::varchar, varInstitutionBranchID, varBaseCurrencyID, ", B48, "::bigint, ", IF(EXACT(D48, ""), "null", CONCATENATE("'", D48, "'")), "::varchar);") -> PERFORM "SchData-OLTP-HumanResource"."Func_TblWorker_SET"(varSystemLoginSession, null::bigint, null::varchar, null::timestamptz, null::timestamptz, null::varchar, varInstitutionBranchID, varBaseCurrencyID, 25000000000045::bigint, null::varchar);
B49: =IF(EXACT([1]DataLookUp!$B49, ""), "", [1]DataLookUp!$B49) -> 25000000000046 | C49: =IF(EXACT(B49, ""), "", VLOOKUP(B49, [1]DataLookUp!$B$4:$C$1000, 2,FALSE )) -> Ardhi Swasono | G49: =G48 + IF(EXACT(H49, ""), 0, 1) -> 32000000000046 | H49: =CONCATENATE("PERFORM ""SchData-OLTP-HumanResource"".""Func_TblWorker_SET""(varSystemLoginSession, null::bigint, null::varchar, null::timestamptz, null::timestamptz, null::varchar, varInstitutionBranchID, varBaseCurrencyID, ", B49, "::bigint, ", IF(EXACT(D49, ""), "null", CONCATENATE("'", D49, "'")), "::varchar);") -> PERFORM "SchData-OLTP-HumanResource"."Func_TblWorker_SET"(varSystemLoginSession, null::bigint, null::varchar, null::timestamptz, null::timestamptz, null::varchar, varInstitutionBranchID, varBaseCurrencyID, 25000000000046::bigint, null::varchar);
B50: =IF(EXACT([1]DataLookUp!$B50, ""), "", [1]DataLookUp!$B50) -> 25000000000047 | C50: =IF(EXACT(B50, ""), "", VLOOKUP(B50, [1]DataLookUp!$B$4:$C$1000, 2,FALSE )) -> Ardi | G50: =G49 + IF(EXACT(H50, ""), 0, 1) -> 32000000000047 | H50: =CONCATENATE("PERFORM ""SchData-OLTP-HumanResource"".""Func_TblWorker_SET""(varSystemLoginSession, null::bigint, null::varchar, null::timestamptz, null::timestamptz, null::varchar, varInstitutionBranchID, varBaseCurrencyID, ", B50, "::bigint, ", IF(EXACT(D50, ""), "null", CONCATENATE("'", D50, "'")), "::varchar);") -> PERFORM "SchData-OLTP-HumanResource"."Func_TblWorker_SET"(varSystemLoginSession, null::bigint, null::varchar, null::timestamptz, null::timestamptz, null::varchar, varInstitutionBranchID, varBaseCurrencyID, 25000000000047::bigint, null::varchar);
B51: =IF(EXACT([1]DataLookUp!$B51, ""), "", [1]DataLookUp!$B51) -> 25000000000048 | C51: =IF(EXACT(B51, ""), "", VLOOKUP(B51, [1]DataLookUp!$B$4:$C$1000, 2,FALSE )) -> Ardiansyah | G51: =G50 + IF(EXACT(H51, ""), 0, 1) -> 32000000000048 | H51: =CONCATENATE("PERFORM ""SchData-OLTP-HumanResource"".""Func_TblWorker_SET""(varSystemLoginSession, null::bigint, null::varchar, null::timestamptz, null::timestamptz, null::varchar, varInstitutionBranchID, varBaseCurrencyID, ", B51, "::bigint, ", IF(EXACT(D51, ""), "null", CONCATENATE("'", D51, "'")), "::varchar);") -> PERFORM "SchData-OLTP-HumanResource"."Func_TblWorker_SET"(varSystemLoginSession, null::bigint, null::varchar, null::timestamptz, null::timestamptz, null::varchar, varInstitutionBranchID, varBaseCurrencyID, 25000000000048::bigint, null::varchar);
B52: =IF(EXACT([1]DataLookUp!$B52, ""), "", [1]DataLookUp!$B52) -> 25000000000049 | C52: =IF(EXACT(B52, ""), "", VLOOKUP(B52, [1]DataLookUp!$B$4:$C$1000, 2,FALSE )) -> Ardisam | G52: =G51 + IF(EXACT(H52, ""), 0, 1) -> 32000000000049 | H52: =CONCATENATE("PERFORM ""SchData-OLTP-HumanResource"".""Func_TblWorker_SET""(varSystemLoginSession, null::bigint, null::varchar, null::timestamptz, null::timestamptz, null::varchar, varInstitutionBranchID, varBaseCurrencyID, ", B52, "::bigint, ", IF(EXACT(D52, ""), "null", CONCATENATE("'", D52, "'")), "::varchar);") -> PERFORM "SchData-OLTP-HumanResource"."Func_TblWorker_SET"(varSystemLoginSession, null::bigint, null::varchar, null::timestamptz, null::timestamptz, null::varchar, varInstitutionBranchID, varBaseCurrencyID, 25000000000049::bigint, null::varchar);
B53: =IF(EXACT([1]DataLookUp!$B53, ""), "", [1]DataLookUp!$B53) -> 25000000000050 | C53: =IF(EXACT(B53, ""), "", VLOOKUP(B53, [1]DataLookUp!$B$4:$C$1000, 2,FALSE )) -> Ardita | G53: =G52 + IF(EXACT(H53, ""), 0, 1) -> 32000000000050 | H53: =CONCATENATE("PERFORM ""SchData-OLTP-HumanResource"".""Func_TblWorker_SET""(varSystemLoginSession, null::bigint, null::varchar, null::timestamptz, null::timestamptz, null::varchar, varInstitutionBranchID, varBaseCurrencyID, ", B53, "::bigint, ", IF(EXACT(D53, ""), "null", CONCATENATE("'", D53, "'")), "::varchar);") -> PERFORM "SchData-OLTP-HumanResource"."Func_TblWorker_SET"(varSystemLoginSession, null::bigint, null::varchar, null::timestamptz, null::timestamptz, null::varchar, varInstitutionBranchID, varBaseCurrencyID, 25000000000050::bigint, null::varchar);
B54: =IF(EXACT([1]DataLookUp!$B54, ""), "", [1]DataLookUp!$B54) -> 25000000000051 | C54: =IF(EXACT(B54, ""), "", VLOOKUP(B54, [1]DataLookUp!$B$4:$C$1000, 2,FALSE )) -> Ares S. Mauboi | D54: 160313008 | E54: IMD | G54: =G53 + IF(EXACT(H54, ""), 0, 1) -> 32000000000051 | H54: =CONCATENATE("PERFORM ""SchData-OLTP-HumanResource"".""Func_TblWorker_SET""(varSystemLoginSession, null::bigint, null::varchar, null::timestamptz, null::timestamptz, null::varchar, varInstitutionBranchID, varBaseCurrencyID, ", B54, "::bigint, ", IF(EXACT(D54, ""), "null", CONCATENATE("'", D54, "'")), "::varchar);") -> PERFORM "SchData-OLTP-HumanResource"."Func_TblWorker_SET"(varSystemLoginSession, null::bigint, null::varchar, null::timestamptz, null::timestamptz, null::varchar, varInstitutionBranchID, varBaseCurrencyID, 25000000000051::bigint, '160313008'::varchar);
B55: =IF(EXACT([1]DataLookUp!$B55, ""), "", [1]DataLookUp!$B55) -> 25000000000052 | C55: =IF(EXACT(B55, ""), "", VLOOKUP(B55, [1]DataLookUp!$B$4:$C$1000, 2,FALSE )) -> Arfah Hanum | G55: =G54 + IF(EXACT(H55, ""), 0, 1) -> 32000000000052 | H55: =CONCATENATE("PERFORM ""SchData-OLTP-HumanResource"".""Func_TblWorker_SET""(varSystemLoginSession, null::bigint, null::varchar, null::timestamptz, null::timestamptz, null::varchar, varInstitutionBranchID, varBaseCurrencyID, ", B55, "::bigint, ", IF(EXACT(D55, ""), "null", CONCATENATE("'", D55, "'")), "::varchar);") -> PERFORM "SchData-OLTP-HumanResource"."Func_TblWorker_SET"(varSystemLoginSession, null::bigint, null::varchar, null::timestamptz, null::timestamptz, null::varchar, varInstitutionBranchID, varBaseCurrencyID, 25000000000052::bigint, null::varchar);
B56: =IF(EXACT([1]DataLookUp!$B56, ""), "", [1]DataLookUp!$B56) -> 25000000000053 | C56: =IF(EXACT(B56, ""), "", VLOOKUP(B56, [1]DataLookUp!$B$4:$C$1000, 2,FALSE )) -> Arfianti Haryani | G56: =G55 + IF(EXACT(H56, ""), 0, 1) -> 32000000000053 | H56: =CONCATENATE("PERFORM ""SchData-OLTP-HumanResource"".""Func_TblWorker_SET""(varSystemLoginSession, null::bigint, null::varchar, null::timestamptz, null::timestamptz, null::varchar, varInstitutionBranchID, varBaseCurrencyID, ", B56, "::bigint, ", IF(EXACT(D56, ""), "null", CONCATENATE("'", D56, "'")), "::varchar);") -> PERFORM "SchData-OLTP-HumanResource"."Func_TblWorker_SET"(varSystemLoginSession, null::bigint, null::varchar, null::timestamptz, null::timestamptz, null::varchar, varInstitutionBranchID, varBaseCurrencyID, 25000000000053::bigint, null::varchar);
B57: =IF(EXACT([1]DataLookUp!$B57, ""), "", [1]DataLookUp!$B57) -> 25000000000054 | C57: =IF(EXACT(B57, ""), "", VLOOKUP(B57, [1]DataLookUp!$B$4:$C$1000, 2,FALSE )) -> Ari Priwarsono | G57: =G56 + IF(EXACT(H57, ""), 0, 1) -> 32000000000054 | H57: =CONCATENATE("PERFORM ""SchData-OLTP-HumanResource"".""Func_TblWorker_SET""(varSystemLoginSession, null::bigint, null::varchar, null::timestamptz, null::timestamptz, null::varchar, varInstitutionBranchID, varBaseCurrencyID, ", B57, "::bigint, ", IF(EXACT(D57, ""), "null", CONCATENATE("'", D57, "'")), "::varchar);") -> PERFORM "SchData-OLTP-HumanResource"."Func_TblWorker_SET"(varSystemLoginSession, null::bigint, null::varchar, null::timestamptz, null::timestamptz, null::varchar, varInstitutionBranchID, varBaseCurrencyID, 25000000000054::bigint, null::varchar);
B58: =IF(EXACT([1]DataLookUp!$B58, ""), "", [1]DataLookUp!$B58) -> 25000000000055 | C58: =IF(EXACT(B58, ""), "", VLOOKUP(B58, [1]DataLookUp!$B$4:$C$1000, 2,FALSE )) -> Ari Yuniasmono | G58: =G57 + IF(EXACT(H58, ""), 0, 1) -> 32000000000055 | H58: =CONCATENATE("PERFORM ""SchData-OLTP-HumanResource"".""Func_TblWorker_SET""(varSystemLoginSession, null::bigint, null::varchar, null::timestamptz, null::timestamptz, null::varchar, varInstitutionBranchID, varBaseCurrencyID, ", B58, "::bigint, ", IF(EXACT(D58, ""), "null", CONCATENATE("'", D58, "'")), "::varchar);") -> PERFORM "SchData-OLTP-HumanResource"."Func_TblWorker_SET"(varSystemLoginSession, null::bigint, null::varchar, null::timestamptz, null::timestamptz, null::varchar, varInstitutionBranchID, varBaseCurrencyID, 25000000000055::bigint, null::varchar);
B59: =IF(EXACT([1]DataLookUp!$B59, ""), "", [1]DataLookUp!$B59) -> 25000000000056 | C59: =IF(EXACT(B59, ""), "", VLOOKUP(B59, [1]DataLookUp!$B$4:$C$1000, 2,FALSE )) -> Arif Gunawan | G59: =G58 + IF(EXACT(H59, ""), 0, 1) -> 32000000000056 | H59: =CONCATENATE("PERFORM ""SchData-OLTP-HumanResource"".""Func_TblWorker_SET""(varSystemLoginSession, null::bigint, null::varchar, null::timestamptz, null::timestamptz, null::varchar, varInstitutionBranchID, varBaseCurrencyID, ", B59, "::bigint, ", IF(EXACT(D59, ""), "null", CONCATENATE("'", D59, "'")), "::varchar);") -> PERFORM "SchData-OLTP-HumanResource"."Func_TblWorker_SET"(varSystemLoginSession, null::bigint, null::varchar, null::timestamptz, null::timestamptz, null::varchar, varInstitutionBranchID, varBaseCurrencyID, 25000000000056::bigint, null::varchar);
B60: =IF(EXACT([1]DataLookUp!$B60, ""), "", [1]DataLookUp!$B60) -> 25000000000057 | C60: =IF(EXACT(B60, ""), "", VLOOKUP(B60, [1]DataLookUp!$B$4:$C$1000, 2,FALSE )) -> Arif Prasetyo | G60: =G59 + IF(EXACT(H60, ""), 0, 1) -> 32000000000057 | H60: =CONCATENATE("PERFORM ""SchData-OLTP-HumanResource"".""Func_TblWorker_SET""(varSystemLoginSession, null::bigint, null::varchar, null::timestamptz, null::timestamptz, null::varchar, varInstitutionBranchID, varBaseCurrencyID, ", B60, "::bigint, ", IF(EXACT(D60, ""), "null", CONCATENATE("'", D60, "'")), "::varchar);") -> PERFORM "SchData-OLTP-HumanResource"."Func_TblWorker_SET"(varSystemLoginSession, null::bigint, null::varchar, null::timestamptz, null::timestamptz, null::varchar, varInstitutionBranchID, varBaseCurrencyID, 25000000000057::bigint, null::varchar);
B61: =IF(EXACT([1]DataLookUp!$B61, ""), "", [1]DataLookUp!$B61) -> 25000000000058 | C61: =IF(EXACT(B61, ""), "", VLOOKUP(B61, [1]DataLookUp!$B$4:$C$1000, 2,FALSE )) -> Arini | G61: =G60 + IF(EXACT(H61, ""), 0, 1) -> 32000000000058 | H61: =CONCATENATE("PERFORM ""SchData-OLTP-HumanResource"".""Func_TblWorker_SET""(varSystemLoginSession, null::bigint, null::varchar, null::timestamptz, null::timestamptz, null::varchar, varInstitutionBranchID, varBaseCurrencyID, ", B61, "::bigint, ", IF(EXACT(D61, ""), "null", CONCATENATE("'", D61, "'")), "::varchar);") -> PERFORM "SchData-OLTP-HumanResource"."Func_TblWorker_SET"(varSystemLoginSession, null::bigint, null::varchar, null::timestamptz, null::timestamptz, null::varchar, varInstitutionBranchID, varBaseCurrencyID, 25000000000058::bigint, null::varchar);
B62: =IF(EXACT([1]DataLookUp!$B62, ""), "", [1]DataLookUp!$B62) -> 25000000000059 | C62: =IF(EXACT(B62, ""), "", VLOOKUP(B62, [1]DataLookUp!$B$4:$C$1000, 2,FALSE )) -> Ario Setyo Gunawan | G62: =G61 + IF(EXACT(H62, ""), 0, 1) -> 32000000000059 | H62: =CONCATENATE("PERFORM ""SchData-OLTP-HumanResource"".""Func_TblWorker_SET""(varSystemLoginSession, null::bigint, null::varchar, null::timestamptz, null::timestamptz, null::varchar, varInstitutionBranchID, varBaseCurrencyID, ", B62, "::bigint, ", IF(EXACT(D62, ""), "null", CONCATENATE("'", D62, "'")), "::varchar);") -> PERFORM "SchData-OLTP-HumanResource"."Func_TblWorker_SET"(varSystemLoginSession, null::bigint, null::varchar, null::timestamptz, null::timestamptz, null::varchar, varInstitutionBranchID, varBaseCurrencyID, 25000000000059::bigint, null::varchar);
B63: =IF(EXACT([1]DataLookUp!$B63, ""), "", [1]DataLookUp!$B63) -> 25000000000060 | C63: =IF(EXACT(B63, ""), "", VLOOKUP(B63, [1]DataLookUp!$B$4:$C$1000, 2,FALSE )) -> Ario Yulianto Wibowo | G63: =G62 + IF(EXACT(H63, ""), 0, 1) -> 32000000000060 | H63: =CONCATENATE("PERFORM ""SchData-OLTP-HumanResource"".""Func_TblWorker_SET""(varSystemLoginSession, null::bigint, null::varchar, null::timestamptz, null::timestamptz, null::varchar, varInstitutionBranchID, varBaseCurrencyID, ", B63, "::bigint, ", IF(EXACT(D63, ""), "null", CONCATENATE("'", D63, "'")), "::varchar);") -> PERFORM "SchData-OLTP-HumanResource"."Func_TblWorker_SET"(varSystemLoginSession, null::bigint, null::varchar, null::timestamptz, null::timestamptz, null::varchar, varInstitutionBranchID, varBaseCurrencyID, 25000000000060::bigint, null::varchar);
B64: =IF(EXACT([1]DataLookUp!$B64, ""), "", [1]DataLookUp!$B64) -> 25000000000061 | C64: =IF(EXACT(B64, ""), "", VLOOKUP(B64, [1]DataLookUp!$B$4:$C$1000, 2,FALSE )) -> Aris Widodo Pamungkas | G64: =G63 + IF(EXACT(H64, ""), 0, 1) -> 32000000000061 | H64: =CONCATENATE("PERFORM ""SchData-OLTP-HumanResource"".""Func_TblWorker_SET""(varSystemLoginSession, null::bigint, null::varchar, null::timestamptz, null::timestamptz, null::varchar, varInstitutionBranchID, varBaseCurrencyID, ", B64, "::bigint, ", IF(EXACT(D64, ""), "null", CONCATENATE("'", D64, "'")), "::varchar);") -> PERFORM "SchData-OLTP-HumanResource"."Func_TblWorker_SET"(varSystemLoginSession, null::bigint, null::varchar, null::timestamptz, null::timestamptz, null::varchar, varInstitutionBranchID, varBaseCurrencyID, 25000000000061::bigint, null::varchar);
B65: =IF(EXACT([1]DataLookUp!$B65, ""), "", [1]DataLookUp!$B65) -> 25000000000062 | C65: =IF(EXACT(B65, ""), "", VLOOKUP(B65, [1]DataLookUp!$B$4:$C$1000, 2,FALSE )) -> Arjiyanto | G65: =G64 + IF(EXACT(H65, ""), 0, 1) -> 32000000000062 | H65: =CONCATENATE("PERFORM ""SchData-OLTP-HumanResource"".""Func_TblWorker_SET""(varSystemLoginSession, null::bigint, null::varchar, null::timestamptz, null::timestamptz, null::varchar, varInstitutionBranchID, varBaseCurrencyID, ", B65, "::bigint, ", IF(EXACT(D65, ""), "null", CONCATENATE("'", D65, "'")), "::varchar);") -> PERFORM "SchData-OLTP-HumanResource"."Func_TblWorker_SET"(varSystemLoginSession, null::bigint, null::varchar, null::timestamptz, null::timestamptz, null::varchar, varInstitutionBranchID, varBaseCurrencyID, 25000000000062::bigint, null::varchar);
B66: =IF(EXACT([1]DataLookUp!$B66, ""), "", [1]DataLookUp!$B66) -> 25000000000063 | C66: =IF(EXACT(B66, ""), "", VLOOKUP(B66, [1]DataLookUp!$B$4:$C$1000, 2,FALSE )) -> Arman | G66: =G65 + IF(EXACT(H66, ""), 0, 1) -> 32000000000063 | H66: =CONCATENATE("PERFORM ""SchData-OLTP-HumanResource"".""Func_TblWorker_SET""(varSystemLoginSession, null::bigint, null::varchar, null::timestamptz, null::timestamptz, null::varchar, varInstitutionBranchID, varBaseCurrencyID, ", B66, "::bigint, ", IF(EXACT(D66, ""), "null", CONCATENATE("'", D66, "'")), "::varchar);") -> PERFORM "SchData-OLTP-HumanResource"."Func_TblWorker_SET"(varSystemLoginSession, null::bigint, null::varchar, null::timestamptz, null::timestamptz, null::varchar, varInstitutionBranchID, varBaseCurrencyID, 25000000000063::bigint, null::varchar);
... B77: =IF(EXACT([1]DataLookUp!$B77, ""), "", [1]DataLookUp!$B77) -> 25000000000074 | C77: =IF(EXACT(B77, ""), "", VLOOKUP(B77, [1]DataLookUp!$B$4:$C$1000, 2,FALSE )) -> Bela Retmalantika | G77: =G76 + IF(EXACT(H77, ""), 0, 1) -> 32000000000074 | H77: =CONCATENATE("PERFORM ""SchData-OLTP-HumanResource"".""Func_TblWorker_SET""(varSystemLoginSession, null::bigint, null::varchar, null::timestamptz, null::timestamptz, null::varchar, varInstitutionBranchID, varBaseCurrencyID, ", B77, "::bigint, ", IF(EXACT(D77, ""), "null", CONCATENATE("'", D77, "'")), "::varchar);") -> PERFORM "SchData-OLTP-HumanResource"."Func_TblWorker_SET"(varSystemLoginSession, null::bigint, null::varchar, null::timestamptz, null::timestamptz, null::varchar, varInstitutionBranchID, varBaseCurrencyID, 25000000000074::bigint, null::varchar);
B78: =IF(EXACT([1]DataLookUp!$B78, ""), "", [1]DataLookUp!$B78) -> 25000000000075 | C78: =IF(EXACT(B78, ""), "", VLOOKUP(B78, [1]DataLookUp!$B$4:$C$1000, 2,FALSE )) -> Belina Lindarwani | D78: 100920934 | E78: QDC | G78: =G77 + IF(EXACT(H78, ""), 0, 1) -> 32000000000075 | H78: =CONCATENATE("PERFORM ""SchData-OLTP-HumanResource"".""Func_TblWorker_SET""(varSystemLoginSession, null::bigint, null::varchar, null::timestamptz, null::timestamptz, null::varchar, varInstitutionBranchID, varBaseCurrencyID, ", B78, "::bigint, ", IF(EXACT(D78, ""), "null", CONCATENATE("'", D78, "'")), "::varchar);") -> PERFORM "SchData-OLTP-HumanResource"."Func_TblWorker_SET"(varSystemLoginSession, null::bigint, null::varchar, null::timestamptz, null::timestamptz, null::varchar, varInstitutionBranchID, varBaseCurrencyID, 25000000000075::bigint, '100920934'::varchar);
B79: =IF(EXACT([1]DataLookUp!$B79, ""), "", [1]DataLookUp!$B79) -> 25000000000076 | C79: =IF(EXACT(B79, ""), "", VLOOKUP(B79, [1]DataLookUp!$B$4:$C$1000, 2,FALSE )) -> Benita Sofia | G79: =G78 + IF(EXACT(H79, ""), 0, 1) -> 32000000000076 | H79: =CONCATENATE("PERFORM ""SchData-OLTP-HumanResource"".""Func_TblWorker_SET""(varSystemLoginSession, null::bigint, null::varchar, null::timestamptz, null::timestamptz, null::varchar, varInstitutionBranchID, varBaseCurrencyID, ", B79, "::bigint, ", IF(EXACT(D79, ""), "null", CONCATENATE("'", D79, "'")), "::varchar);") -> PERFORM "SchData-OLTP-HumanResource"."Func_TblWorker_SET"(varSystemLoginSession, null::bigint, null::varchar, null::timestamptz, null::timestamptz, null::varchar, varInstitutionBranchID, varBaseCurrencyID, 25000000000076::bigint, null::varchar);
B80: =IF(EXACT([1]DataLookUp!$B80, ""), "", [1]DataLookUp!$B80) -> 25000000000077 | C80: =IF(EXACT(B80, ""), "", VLOOKUP(B80, [1]DataLookUp!$B$4:$C$1000, 2,FALSE )) -> Bherly Novrandy | G80: =G79 + IF(EXACT(H80, ""), 0, 1) -> 32000000000077 | H80: =CONCATENATE("PERFORM ""SchData-OLTP-HumanResource"".""Func_TblWorker_SET""(varSystemLoginSession, null::bigint, null::varchar, null::timestamptz, null::timestamptz, null::varchar, varInstitutionBranchID, varBaseCurrencyID, ", B80, "::bigint, ", IF(EXACT(D80, ""), "null", CONCATENATE("'", D80, "'")), "::varchar);") -> PERFORM "SchData-OLTP-HumanResource"."Func_TblWorker_SET"(varSystemLoginSession, null::bigint, null::varchar, null::timestamptz, null::timestamptz, null::varchar, varInstitutionBranchID, varBaseCurrencyID, 25000000000077::bigint, null::varchar);
B81: =IF(EXACT([1]DataLookUp!$B81, ""), "", [1]DataLookUp!$B81) -> 25000000000078 | C81: =IF(EXACT(B81, ""), "", VLOOKUP(B81, [1]DataLookUp!$B$4:$C$1000, 2,FALSE )) -> Binsar | G81: =G80 + IF(EXACT(H81, ""), 0, 1) -> 32000000000078 | H81: =CONCATENATE("PERFORM ""SchData-OLTP-HumanResource"".""Func_TblWorker_SET""(varSystemLoginSession, null::bigint, null::varchar, null::timestamptz, null::timestamptz, null::varchar, varInstitutionBranchID, varBaseCurrencyID, ", B81, "::bigint, ", IF(EXACT(D81, ""), "null", CONCATENATE("'", D81, "'")), "::varchar);") -> PERFORM "SchData-OLTP-HumanResource"."Func_TblWorker_SET"(varSystemLoginSession, null::bigint, null::varchar, null::timestamptz, null::timestamptz, null::varchar, varInstitutionBranchID, varBaseCurrencyID, 25000000000078::bigint, null::varchar);
B82: =IF(EXACT([1]DataLookUp!$B82, ""), "", [1]DataLookUp!$B82) -> 25000000000079 | C82: =IF(EXACT(B82, ""), "", VLOOKUP(B82, [1]DataLookUp!$B$4:$C$1000, 2,FALSE )) -> Bondhan Sosiarta | G82: =G81 + IF(EXACT(H82, ""), 0, 1) -> 32000000000079 | H82: =CONCATENATE("PERFORM ""SchData-OLTP-HumanResource"".""Func_TblWorker_SET""(varSystemLoginSession, null::bigint, null::varchar, null::timestamptz, null::timestamptz, null::varchar, varInstitutionBranchID, varBaseCurrencyID, ", B82, "::bigint, ", IF(EXACT(D82, ""), "null", CONCATENATE("'", D82, "'")), "::varchar);") -> PERFORM "SchData-OLTP-HumanResource"."Func_TblWorker_SET"(varSystemLoginSession, null::bigint, null::varchar, null::timestamptz, null::timestamptz, null::varchar, varInstitutionBranchID, varBaseCurrencyID, 25000000000079::bigint, null::varchar);
B83: =IF(EXACT([1]DataLookUp!$B83, ""), "", [1]DataLookUp!$B83) -> 25000000000080 | C83: =IF(EXACT(B83, ""), "", VLOOKUP(B83, [1]DataLookUp!$B$4:$C$1000, 2,FALSE )) -> Budi Pranata Sinaga | G83: =G82 + IF(EXACT(H83, ""), 0, 1) -> 32000000000080 | H83: =CONCATENATE("PERFORM ""SchData-OLTP-HumanResource"".""Func_TblWorker_SET""(varSystemLoginSession, null::bigint, null::varchar, null::timestamptz, null::timestamptz, null::varchar, varInstitutionBranchID, varBaseCurrencyID, ", B83, "::bigint, ", IF(EXACT(D83, ""), "null", CONCATENATE("'", D83, "'")), "::varchar);") -> PERFORM "SchData-OLTP-HumanResource"."Func_TblWorker_SET"(varSystemLoginSession, null::bigint, null::varchar, null::timestamptz, null::timestamptz, null::varchar, varInstitutionBranchID, varBaseCurrencyID, 25000000000080::bigint, null::varchar);
B84: =IF(EXACT([1]DataLookUp!$B84, ""), "", [1]DataLookUp!$B84) -> 25000000000081 | C84: =IF(EXACT(B84, ""), "", VLOOKUP(B84, [1]DataLookUp!$B$4:$C$1000, 2,FALSE )) -> Budi Satrio | G84: =G83 + IF(EXACT(H84, ""), 0, 1) -> 32000000000081 | H84: =CONCATENATE("PERFORM ""SchData-OLTP-HumanResource"".""Func_TblWorker_SET""(varSystemLoginSession, null::bigint, null::varchar, null::timestamptz, null::timestamptz, null::varchar, varInstitutionBranchID, varBaseCurrencyID, ", B84, "::bigint, ", IF(EXACT(D84, ""), "null", CONCATENATE("'", D84, "'")), "::varchar);") -> PERFORM "SchData-OLTP-HumanResource"."Func_TblWorker_SET"(varSystemLoginSession, null::bigint, null::varchar, null::timestamptz, null::timestamptz, null::varchar, varInstitutionBranchID, varBaseCurrencyID, 25000000000081::bigint, null::varchar);
B85: =IF(EXACT([1]DataLookUp!$B85, ""), "", [1]DataLookUp!$B85) -> 25000000000082 | C85: =IF(EXACT(B85, ""), "", VLOOKUP(B85, [1]DataLookUp!$B$4:$C$1000, 2,FALSE )) -> Budianto | D85: 060515769 | E85: QDC | G85: =G84 + IF(EXACT(H85, ""), 0, 1) -> 32000000000082 | H85: =CONCATENATE("PERFORM ""SchData-OLTP-HumanResource"".""Func_TblWorker_SET""(varSystemLoginSession, null::bigint, null::varchar, null::timestamptz, null::timestamptz, null::varchar, varInstitutionBranchID, varBaseCurrencyID, ", B85, "::bigint, ", IF(EXACT(D85, ""), "null", CONCATENATE("'", D85, "'")), "::varchar);") -> PERFORM "SchData-OLTP-HumanResource"."Func_TblWorker_SET"(varSystemLoginSession, null::bigint, null::varchar, null::timestamptz, null::timestamptz, null::varchar, varInstitutionBranchID, varBaseCurrencyID, 25000000000082::bigint, '060515769'::varchar);
B86: =IF(EXACT([1]DataLookUp!$B86, ""), "", [1]DataLookUp!$B86) -> 25000000000083 | C86: =IF(EXACT(B86, ""), "", VLOOKUP(B86, [1]DataLookUp!$B$4:$C$1000, 2,FALSE )) -> Budiman | G86: =G85 + IF(EXACT(H86, ""), 0, 1) -> 32000000000083 | H86: =CONCATENATE("PERFORM ""SchData-OLTP-HumanResource"".""Func_TblWorker_SET""(varSystemLoginSession, null::bigint, null::varchar, null::timestamptz, null::timestamptz, null::varchar, varInstitutionBranchID, varBaseCurrencyID, ", B86, "::bigint, ", IF(EXACT(D86, ""), "null", CONCATENATE("'", D86, "'")), "::varchar);") -> PERFORM "SchData-OLTP-HumanResource"."Func_TblWorker_SET"(varSystemLoginSession, null::bigint, null::varchar, null::timestamptz, null::timestamptz, null::varchar, varInstitutionBranchID, varBaseCurrencyID, 25000000000083::bigint, null::varchar);
B87: =IF(EXACT([1]DataLookUp!$B87, ""), "", [1]DataLookUp!$B87) -> 25000000000084 | C87: =IF(EXACT(B87, ""), "", VLOOKUP(B87, [1]DataLookUp!$B$4:$C$1000, 2,FALSE )) -> Cahyaning Annisa | G87: =G86 + IF(EXACT(H87, ""), 0, 1) -> 32000000000084 | H87: =CONCATENATE("PERFORM ""SchData-OLTP-HumanResource"".""Func_TblWorker_SET""(varSystemLoginSession, null::bigint, null::varchar, null::timestamptz, null::timestamptz, null::varchar, varInstitutionBranchID, varBaseCurrencyID, ", B87, "::bigint, ", IF(EXACT(D87, ""), "null", CONCATENATE("'", D87, "'")), "::varchar);") -> PERFORM "SchData-OLTP-HumanResource"."Func_TblWorker_SET"(varSystemLoginSession, null::bigint, null::varchar, null::timestamptz, null::timestamptz, null::varchar, varInstitutionBranchID, varBaseCurrencyID, 25000000000084::bigint, null::varchar);
B88: =IF(EXACT([1]DataLookUp!$B88, ""), "", [1]DataLookUp!$B88) -> 25000000000085 | C88: =IF(EXACT(B88, ""), "", VLOOKUP(B88, [1]DataLookUp!$B$4:$C$1000, 2,FALSE )) -> Cahyaningrum Widiastuti | G88: =G87 + IF(EXACT(H88, ""), 0, 1) -> 32000000000085 | H88: =CONCATENATE("PERFORM ""SchData-OLTP-HumanResource"".""Func_TblWorker_SET""(varSystemLoginSession, null::bigint, null::varchar, null::timestamptz, null::timestamptz, null::varchar, varInstitutionBranchID, varBaseCurrencyID, ", B88, "::bigint, ", IF(EXACT(D88, ""), "null", CONCATENATE("'", D88, "'")), "::varchar);") -> PERFORM "SchData-OLTP-HumanResource"."Func_TblWorker_SET"(varSystemLoginSession, null::bigint, null::varchar, null::timestamptz, null::timestamptz, null::varchar, varInstitutionBranchID, varBaseCurrencyID, 25000000000085::bigint, null::varchar);
B89: =IF(EXACT([1]DataLookUp!$B89, ""), "", [1]DataLookUp!$B89) -> 25000000000086 | C89: =IF(EXACT(B89, ""), "", VLOOKUP(B89, [1]DataLookUp!$B$4:$C$1000, 2,FALSE )) -> Cecep Maulana | G89: =G88 + IF(EXACT(H89, ""), 0, 1) -> 32000000000086 | H89: =CONCATENATE("PERFORM ""SchData-OLTP-HumanResource"".""Func_TblWorker_SET""(varSystemLoginSession, null::bigint, null::varchar, null::timestamptz, null::timestamptz, null::varchar, varInstitutionBranchID, varBaseCurrencyID, ", B89, "::bigint, ", IF(EXACT(D89, ""), "null", CONCATENATE("'", D89, "'")), "::varchar);") -> PERFORM "SchData-OLTP-HumanResource"."Func_TblWorker_SET"(varSystemLoginSession, null::bigint, null::varchar, null::timestamptz, null::timestamptz, null::varchar, varInstitutionBranchID, varBaseCurrencyID, 25000000000086::bigint, null::varchar);
B90: =IF(EXACT([1]DataLookUp!$B90, ""), "", [1]DataLookUp!$B90) -> 25000000000087 | C90: =IF(EXACT(B90, ""), "", VLOOKUP(B90, [1]DataLookUp!$B$4:$C$1000, 2,FALSE )) -> Chairul Musaddat | G90: =G89 + IF(EXACT(H90, ""), 0, 1) -> 32000000000087 | H90: =CONCATENATE("PERFORM ""SchData-OLTP-HumanResource"".""Func_TblWorker_SET""(varSystemLoginSession, null::bigint, null::varchar, null::timestamptz, null::timestamptz, null::varchar, varInstitutionBranchID, varBaseCurrencyID, ", B90, "::bigint, ", IF(EXACT(D90, ""), "null", CONCATENATE("'", D90, "'")), "::varchar);") -> PERFORM "SchData-OLTP-HumanResource"."Func_TblWorker_SET"(varSystemLoginSession, null::bigint, null::varchar, null::timestamptz, null::timestamptz, null::varchar, varInstitutionBranchID, varBaseCurrencyID, 25000000000087::bigint, null::varchar);
B91: =IF(EXACT([1]DataLookUp!$B91, ""), "", [1]DataLookUp!$B91) -> 25000000000088 | C91: =IF(EXACT(B91, ""), "", VLOOKUP(B91, [1]DataLookUp!$B$4:$C$1000, 2,FALSE )) -> Christianto | G91: =G90 + IF(EXACT(H91, ""), 0, 1) -> 32000000000088 | H91: =CONCATENATE("PERFORM ""SchData-OLTP-HumanResource"".""Func_TblWorker_SET""(varSystemLoginSession, null::bigint, null::varchar, null::timestamptz, null::timestamptz, null::varchar, varInstitutionBranchID, varBaseCurrencyID, ", B91, "::bigint, ", IF(EXACT(D91, ""), "null", CONCATENATE("'", D91, "'")), "::varchar);") -> PERFORM "SchData-OLTP-HumanResource"."Func_TblWorker_SET"(varSystemLoginSession, null::bigint, null::varchar, null::timestamptz, null::timestamptz, null::varchar, varInstitutionBranchID, varBaseCurrencyID, 25000000000088::bigint, null::varchar);
B92: =IF(EXACT([1]DataLookUp!$B92, ""), "", [1]DataLookUp!$B92) -> 25000000000089 | C92: =IF(EXACT(B92, ""), "", VLOOKUP(B92, [1]DataLookUp!$B$4:$C$1000, 2,FALSE )) -> Dadan Hermawan | G92: =G91 + IF(EXACT(H92, ""), 0, 1) -> 32000000000089 | H92: =CONCATENATE("PERFORM ""SchData-OLTP-HumanResource"".""Func_TblWorker_SET""(varSystemLoginSession, null::bigint, null::varchar, null::timestamptz, null::timestamptz, null::varchar, varInstitutionBranchID, varBaseCurrencyID, ", B92, "::bigint, ", IF(EXACT(D92, ""), "null", CONCATENATE("'", D92, "'")), "::varchar);") -> PERFORM "SchData-OLTP-HumanResource"."Func_TblWorker_SET"(varSystemLoginSession, null::bigint, null::varchar, null::timestamptz, null::timestamptz, null::varchar, varInstitutionBranchID, varBaseCurrencyID, 25000000000089::bigint, null::varchar);
B93: =IF(EXACT([1]DataLookUp!$B93, ""), "", [1]DataLookUp!$B93) -> 25000000000090 | C93: =IF(EXACT(B93, ""), "", VLOOKUP(B93, [1]DataLookUp!$B$4:$C$1000, 2,FALSE )) -> Dadan Suhendar | G93: =G92 + IF(EXACT(H93, ""), 0, 1) -> 32000000000090 | H93: =CONCATENATE("PERFORM ""SchData-OLTP-HumanResource"".""Func_TblWorker_SET""(varSystemLoginSession, null::bigint, null::varchar, null::timestamptz, null::timestamptz, null::varchar, varInstitutionBranchID, varBaseCurrencyID, ", B93, "::bigint, ", IF(EXACT(D93, ""), "null", CONCATENATE("'", D93, "'")), "::varchar);") -> PERFORM "SchData-OLTP-HumanResource"."Func_TblWorker_SET"(varSystemLoginSession, null::bigint, null::varchar, null::timestamptz, null::timestamptz, null::varchar, varInstitutionBranchID, varBaseCurrencyID, 25000000000090::bigint, null::varchar);
B94: =IF(EXACT([1]DataLookUp!$B94, ""), "", [1]DataLookUp!$B94) -> 25000000000091 | C94: =IF(EXACT(B94, ""), "", VLOOKUP(B94, [1]DataLookUp!$B$4:$C$1000, 2,FALSE )) -> Dadi Anda Zuchradi | G94: =G93 + IF(EXACT(H94, ""), 0, 1) -> 32000000000091 | H94: =CONCATENATE("PERFORM ""SchData-OLTP-HumanResource"".""Func_TblWorker_SET""(varSystemLoginSession, null::bigint, null::varchar, null::timestamptz, null::timestamptz, null::varchar, varInstitutionBranchID, varBaseCurrencyID, ", B94, "::bigint, ", IF(EXACT(D94, ""), "null", CONCATENATE("'", D94, "'")), "::varchar);") -> PERFORM "SchData-OLTP-HumanResource"."Func_TblWorker_SET"(varSystemLoginSession, null::bigint, null::varchar, null::timestamptz, null::timestamptz, null::varchar, varInstitutionBranchID, varBaseCurrencyID, 25000000000091::bigint, null::varchar);
B95: =IF(EXACT([1]DataLookUp!$B95, ""), "", [1]DataLookUp!$B95) -> 25000000000092 | C95: =IF(EXACT(B95, ""), "", VLOOKUP(B95, [1]DataLookUp!$B$4:$C$1000, 2,FALSE )) -> Darsito | D95: 031212631 | E95: QDC | G95: =G94 + IF(EXACT(H95, ""), 0, 1) -> 32000000000092 | H95: =CONCATENATE("PERFORM ""SchData-OLTP-HumanResource"".""Func_TblWorker_SET""(varSystemLoginSession, null::bigint, null::varchar, null::timestamptz, null::timestamptz, null::varchar, varInstitutionBranchID, varBaseCurrencyID, ", B95, "::bigint, ", IF(EXACT(D95, ""), "null", CONCATENATE("'", D95, "'")), "::varchar);") -> PERFORM "SchData-OLTP-HumanResource"."Func_TblWorker_SET"(varSystemLoginSession, null::bigint, null::varchar, null::timestamptz, null::timestamptz, null::varchar, varInstitutionBranchID, varBaseCurrencyID, 25000000000092::bigint, '031212631'::varchar);
B96: =IF(EXACT([1]DataLookUp!$B96, ""), "", [1]DataLookUp!$B96) -> 25000000000093 | C96: =IF(EXACT(B96, ""), "", VLOOKUP(B96, [1]DataLookUp!$B$4:$C$1000, 2,FALSE )) -> Davit Lumban Gaol | D96: 170417832 | E96: QDC | G96: =G95 + IF(EXACT(H96, ""), 0, 1) -> 32000000000093 | H96: =CONCATENATE("PERFORM ""SchData-OLTP-HumanResource"".""Func_TblWorker_SET""(varSystemLoginSession, null::bigint, null::varchar, null::timestamptz, null::timestamptz, null::varchar, varInstitutionBranchID, varBaseCurrencyID, ", B96, "::bigint, ", IF(EXACT(D96, ""), "null", CONCATENATE("'", D96, "'")), "::varchar);") -> PERFORM "SchData-OLTP-HumanResource"."Func_TblWorker_SET"(varSystemLoginSession, null::bigint, null::varchar, null::timestamptz, null::timestamptz, null::varchar, varInstitutionBranchID, varBaseCurrencyID, 25000000000093::bigint, '170417832'::varchar);
B97: =IF(EXACT([1]DataLookUp!$B97, ""), "", [1]DataLookUp!$B97) -> 25000000000094 | C97: =IF(EXACT(B97, ""), "", VLOOKUP(B97, [1]DataLookUp!$B$4:$C$1000, 2,FALSE )) -> Deddy Rochman | D97: 171215791 | E97: QDC | G97: =G96 + IF(EXACT(H97, ""), 0, 1) -> 32000000000094 | H97: =CONCATENATE("PERFORM ""SchData-OLTP-HumanResource"".""Func_TblWorker_SET""(varSystemLoginSession, null::bigint, null::varchar, null::timestamptz, null::timestamptz, null::varchar, varInstitutionBranchID, varBaseCurrencyID, ", B97, "::bigint, ", IF(EXACT(D97, ""), "null", CONCATENATE("'", D97, "'")), "::varchar);") -> PERFORM "SchData-OLTP-HumanResource"."Func_TblWorker_SET"(varSystemLoginSession, null::bigint, null::varchar, null::timestamptz, null::timestamptz, null::varchar, varInstitutionBranchID, varBaseCurrencyID, 25000000000094::bigint, '171215791'::varchar);
B98: =IF(EXACT([1]DataLookUp!$B98, ""), "", [1]DataLookUp!$B98) -> 25000000000095 | C98: =IF(EXACT(B98, ""), "", VLOOKUP(B98, [1]DataLookUp!$B$4:$C$1000, 2,FALSE )) -> Dedi Kusnadi | G98: =G97 + IF(EXACT(H98, ""), 0, 1) -> 32000000000095 | H98: =CONCATENATE("PERFORM ""SchData-OLTP-HumanResource"".""Func_TblWorker_SET""(varSystemLoginSession, null::bigint, null::varchar, null::timestamptz, null::timestamptz, null::varchar, varInstitutionBranchID, varBaseCurrencyID, ", B98, "::bigint, ", IF(EXACT(D98, ""), "null", CONCATENATE("'", D98, "'")), "::varchar);") -> PERFORM "SchData-OLTP-HumanResource"."Func_TblWorker_SET"(varSystemLoginSession, null::bigint, null::varchar, null::timestamptz, null::timestamptz, null::varchar, varInstitutionBranchID, varBaseCurrencyID, 25000000000095::bigint, null::varchar);
B99: =IF(EXACT([1]DataLookUp!$B99, ""), "", [1]DataLookUp!$B99) -> 25000000000096 | C99: =IF(EXACT(B99, ""), "", VLOOKUP(B99, [1]DataLookUp!$B$4:$C$1000, 2,FALSE )) -> Dedi Marciano Rizanur | G99: =G98 + IF(EXACT(H99, ""), 0, 1) -> 32000000000096 | H99: =CONCATENATE("PERFORM ""SchData-OLTP-HumanResource"".""Func_TblWorker_SET""(varSystemLoginSession, null::bigint, null::varchar, null::timestamptz, null::timestamptz, null::varchar, varInstitutionBranchID, varBaseCurrencyID, ", B99, "::bigint, ", IF(EXACT(D99, ""), "null", CONCATENATE("'", D99, "'")), "::varchar);") -> PERFORM "SchData-OLTP-HumanResource"."Func_TblWorker_SET"(varSystemLoginSession, null::bigint, null::varchar, null::timestamptz, null::timestamptz, null::varchar, varInstitutionBranchID, varBaseCurrencyID, 25000000000096::bigint, null::varchar);
B100: =IF(EXACT([1]DataLookUp!$B100, ""), "", [1]DataLookUp!$B100) -> 25000000000097 | C100: =IF(EXACT(B100, ""), "", VLOOKUP(B100, [1]DataLookUp!$B$4:$C$1000, 2,FALSE )) -> Dedi Rianto | G100: =G99 + IF(EXACT(H100, ""), 0, 1) -> 32000000000097 | H100: =CONCATENATE("PERFORM ""SchData-OLTP-HumanResource"".""Func_TblWorker_SET""(varSystemLoginSession, null::bigint, null::varchar, null::timestamptz, null::timestamptz, null::varchar, varInstitutionBranchID, varBaseCurrencyID, ", B100, "::bigint, ", IF(EXACT(D100, ""), "null", CONCATENATE("'", D100, "'")), "::varchar);") -> PERFORM "SchData-OLTP-HumanResource"."Func_TblWorker_SET"(varSystemLoginSession, null::bigint, null::varchar, null::timestamptz, null::timestamptz, null::varchar, varInstitutionBranchID, varBaseCurrencyID, 25000000000097::bigint, null::varchar);
B101: =IF(EXACT([1]DataLookUp!$B101, ""), "", [1]DataLookUp!$B101) -> 25000000000098 | C101: =IF(EXACT(B101, ""), "", VLOOKUP(B101, [1]DataLookUp!$B$4:$C$1000, 2,FALSE )) -> Dedi Syahputra | G101: =G100 + IF(EXACT(H101, ""), 0, 1) -> 32000000000098 | H101: =CONCATENATE("PERFORM ""SchData-OLTP-HumanResource"".""Func_TblWorker_SET""(varSystemLoginSession, null::bigint, null::varchar, null::timestamptz, null::timestamptz, null::varchar, varInstitutionBranchID, varBaseCurrencyID, ", B101, "::bigint, ", IF(EXACT(D101, ""), "null", CONCATENATE("'", D101, "'")), "::varchar);") -> PERFORM "SchData-OLTP-HumanResource"."Func_TblWorker_SET"(varSystemLoginSession, null::bigint, null::varchar, null::timestamptz, null::timestamptz, null::varchar, varInstitutionBranchID, varBaseCurrencyID, 25000000000098::bigint, null::varchar);
B102: =IF(EXACT([1]DataLookUp!$B102, ""), "", [1]DataLookUp!$B102) -> 25000000000099 | C102: =IF(EXACT(B102, ""), "", VLOOKUP(B102, [1]DataLookUp!$B$4:$C$1000, 2,FALSE )) -> Deni Setiawan | G102: =G101 + IF(EXACT(H102, ""), 0, 1) -> 32000000000099 | H102: =CONCATENATE("PERFORM ""SchData-OLTP-HumanResource"".""Func_TblWorker_SET""(varSystemLoginSession, null::bigint, null::varchar, null::timestamptz, null::timestamptz, null::varchar, varInstitutionBranchID, varBaseCurrencyID, ", B102, "::bigint, ", IF(EXACT(D102, ""), "null", CONCATENATE("'", D102, "'")), "::varchar);") -> PERFORM "SchData-OLTP-HumanResource"."Func_TblWorker_SET"(varSystemLoginSession, null::bigint, null::varchar, null::timestamptz, null::timestamptz, null::varchar, varInstitutionBranchID, varBaseCurrencyID, 25000000000099::bigint, null::varchar);
B103: =IF(EXACT([1]DataLookUp!$B103, ""), "", [1]DataLookUp!$B103) -> 25000000000100 | C103: =IF(EXACT(B103, ""), "", VLOOKUP(B103, [1]DataLookUp!$B$4:$C$1000, 2,FALSE )) -> Deny Adi Purnama | D103: 050123975 | E103: QDC | G103: =G102 + IF(EXACT(H103, ""), 0, 1) -> 32000000000100 | H103: =CONCATENATE("PERFORM ""SchData-OLTP-HumanResource"".""Func_TblWorker_SET""(varSystemLoginSession, null::bigint, null::varchar, null::timestamptz, null::timestamptz, null::varchar, varInstitutionBranchID, varBaseCurrencyID, ", B103, "::bigint, ", IF(EXACT(D103, ""), "null", CONCATENATE("'", D103, "'")), "::varchar);") -> PERFORM "SchData-OLTP-HumanResource"."Func_TblWorker_SET"(varSystemLoginSession, null::bigint, null::varchar, null::timestamptz, null::timestamptz, null::varchar, varInstitutionBranchID, varBaseCurrencyID, 25000000000100::bigint, '050123975'::varchar);
B104: =IF(EXACT([1]DataLookUp!$B104, ""), "", [1]DataLookUp!$B104) -> 25000000000101 | C104: =IF(EXACT(B104, ""), "", VLOOKUP(B104, [1]DataLookUp!$B$4:$C$1000, 2,FALSE )) -> Desi Herawati | G104: =G103 + IF(EXACT(H104, ""), 0, 1) -> 32000000000101 | H104: =CONCATENATE("PERFORM ""SchData-OLTP-HumanResource"".""Func_TblWorker_SET""(varSystemLoginSession, null::bigint, null::varchar, null::timestamptz, null::timestamptz, null::varchar, varInstitutionBranchID, varBaseCurrencyID, ", B104, "::bigint, ", IF(EXACT(D104, ""), "null", CONCATENATE("'", D104, "'")), "::varchar);") -> PERFORM "SchData-OLTP-HumanResource"."Func_TblWorker_SET"(varSystemLoginSession, null::bigint, null::varchar, null::timestamptz, null::timestamptz, null::varchar, varInstitutionBranchID, varBaseCurrencyID, 25000000000101::bigint, null::varchar);
B105: =IF(EXACT([1]DataLookUp!$B105, ""), "", [1]DataLookUp!$B105) -> 25000000000102 | C105: =IF(EXACT(B105, ""), "", VLOOKUP(B105, [1]DataLookUp!$B$4:$C$1000, 2,FALSE )) -> Desi Setiowati | G105: =G104 + IF(EXACT(H105, ""), 0, 1) -> 32000000000102 | H105: =CONCATENATE("PERFORM ""SchData-OLTP-HumanResource"".""Func_TblWorker_SET""(varSystemLoginSession, null::bigint, null::varchar, null::timestamptz, null::timestamptz, null::varchar, varInstitutionBranchID, varBaseCurrencyID, ", B105, "::bigint, ", IF(EXACT(D105, ""), "null", CONCATENATE("'", D105, "'")), "::varchar);") -> PERFORM "SchData-OLTP-HumanResource"."Func_TblWorker_SET"(varSystemLoginSession, null::bigint, null::varchar, null::timestamptz, null::timestamptz, null::varchar, varInstitutionBranchID, varBaseCurrencyID, 25000000000102::bigint, null::varchar);
B106: =IF(EXACT([1]DataLookUp!$B106, ""), "", [1]DataLookUp!$B106) -> 25000000000103 | C106: =IF(EXACT(B106, ""), "", VLOOKUP(B106, [1]DataLookUp!$B$4:$C$1000, 2,FALSE )) -> Dian Firdaus | G106: =G105 + IF(EXACT(H106, ""), 0, 1) -> 32000000000103 | H106: =CONCATENATE("PERFORM ""SchData-OLTP-HumanResource"".""Func_TblWorker_SET""(varSystemLoginSession, null::bigint, null::varchar, null::timestamptz, null::timestamptz, null::varchar, varInstitutionBranchID, varBaseCurrencyID, ", B106, "::bigint, ", IF(EXACT(D106, ""), "null", CONCATENATE("'", D106, "'")), "::varchar);") -> PERFORM "SchData-OLTP-HumanResource"."Func_TblWorker_SET"(varSystemLoginSession, null::bigint, null::varchar, null::timestamptz, null::timestamptz, null::varchar, varInstitutionBranchID, varBaseCurrencyID, 25000000000103::bigint, null::varchar);
B107: =IF(EXACT([1]DataLookUp!$B107, ""), "", [1]DataLookUp!$B107) -> 25000000000104 | C107: =IF(EXACT(B107, ""), "", VLOOKUP(B107, [1]DataLookUp!$B$4:$C$1000, 2,FALSE )) -> Dian Hariyana | G107: =G106 + IF(EXACT(H107, ""), 0, 1) -> 32000000000104 | H107: =CONCATENATE("PERFORM ""SchData-OLTP-HumanResource"".""Func_TblWorker_SET""(varSystemLoginSession, null::bigint, null::varchar, null::timestamptz, null::timestamptz, null::varchar, varInstitutionBranchID, varBaseCurrencyID, ", B107, "::bigint, ", IF(EXACT(D107, ""), "null", CONCATENATE("'", D107, "'")), "::varchar);") -> PERFORM "SchData-OLTP-HumanResource"."Func_TblWorker_SET"(varSystemLoginSession, null::bigint, null::varchar, null::timestamptz, null::timestamptz, null::varchar, varInstitutionBranchID, varBaseCurrencyID, 25000000000104::bigint, null::varchar);
B108: =IF(EXACT([1]DataLookUp!$B108, ""), "", [1]DataLookUp!$B108) -> 25000000000105 | C108: =IF(EXACT(B108, ""), "", VLOOKUP(B108, [1]DataLookUp!$B$4:$C$1000, 2,FALSE )) -> Dinnar Budiarti | G108: =G107 + IF(EXACT(H108, ""), 0, 1) -> 32000000000105 | H108: =CONCATENATE("PERFORM ""SchData-OLTP-HumanResource"".""Func_TblWorker_SET""(varSystemLoginSession, null::bigint, null::varchar, null::timestamptz, null::timestamptz, null::varchar, varInstitutionBranchID, varBaseCurrencyID, ", B108, "::bigint, ", IF(EXACT(D108, ""), "null", CONCATENATE("'", D108, "'")), "::varchar);") -> PERFORM "SchData-OLTP-HumanResource"."Func_TblWorker_SET"(varSystemLoginSession, null::bigint, null::varchar, null::timestamptz, null::timestamptz, null::varchar, varInstitutionBranchID, varBaseCurrencyID, 25000000000105::bigint, null::varchar);
B109: =IF(EXACT([1]DataLookUp!$B109, ""), "", [1]DataLookUp!$B109) -> 25000000000106 | C109: =IF(EXACT(B109, ""), "", VLOOKUP(B109, [1]DataLookUp!$B$4:$C$1000, 2,FALSE )) -> Dionesius Sostenist Duka | D109: 010605133 | E109: QDC | G109: =G108 + IF(EXACT(H109, ""), 0, 1) -> 32000000000106 | H109: =CONCATENATE("PERFORM ""SchData-OLTP-HumanResource"".""Func_TblWorker_SET""(varSystemLoginSession, null::bigint, null::varchar, null::timestamptz, null::timestamptz, null::varchar, varInstitutionBranchID, varBaseCurrencyID, ", B109, "::bigint, ", IF(EXACT(D109, ""), "null", CONCATENATE("'", D109, "'")), "::varchar);") -> PERFORM "SchData-OLTP-HumanResource"."Func_TblWorker_SET"(varSystemLoginSession, null::bigint, null::varchar, null::timestamptz, null::timestamptz, null::varchar, varInstitutionBranchID, varBaseCurrencyID, 25000000000106::bigint, '010605133'::varchar);
B110: =IF(EXACT([1]DataLookUp!$B110, ""), "", [1]DataLookUp!$B110) -> 25000000000107 | C110: =IF(EXACT(B110, ""), "", VLOOKUP(B110, [1]DataLookUp!$B$4:$C$1000, 2,FALSE )) -> Diyah Martina | G110: =G109 + IF(EXACT(H110, ""), 0, 1) -> 32000000000107 | H110: =CONCATENATE("PERFORM ""SchData-OLTP-HumanResource"".""Func_TblWorker_SET""(varSystemLoginSession, null::bigint, null::varchar, null::timestamptz, null::timestamptz, null::varchar, varInstitutionBranchID, varBaseCurrencyID, ", B110, "::bigint, ", IF(EXACT(D110, ""), "null", CONCATENATE("'", D110, "'")), "::varchar);") -> PERFORM "SchData-OLTP-HumanResource"."Func_TblWorker_SET"(varSystemLoginSession, null::bigint, null::varchar, null::timestamptz, null::timestamptz, null::varchar, varInstitutionBranchID, varBaseCurrencyID, 25000000000107::bigint, null::varchar);
B111: =IF(EXACT([1]DataLookUp!$B111, ""), "", [1]DataLookUp!$B111) -> 25000000000108 | C111: =IF(EXACT(B111, ""), "", VLOOKUP(B111, [1]DataLookUp!$B$4:$C$1000, 2,FALSE )) -> Djuang Tampubolon | G111: =G110 + IF(EXACT(H111, ""), 0, 1) -> 32000000000108 | H111: =CONCATENATE("PERFORM ""SchData-OLTP-HumanResource"".""Func_TblWorker_SET""(varSystemLoginSession, null::bigint, null::varchar, null::timestamptz, null::timestamptz, null::varchar, varInstitutionBranchID, varBaseCurrencyID, ", B111, "::bigint, ", IF(EXACT(D111, ""), "null", CONCATENATE("'", D111, "'")), "::varchar);") -> PERFORM "SchData-OLTP-HumanResource"."Func_TblWorker_SET"(varSystemLoginSession, null::bigint, null::varchar, null::timestamptz, null::timestamptz, null::varchar, varInstitutionBranchID, varBaseCurrencyID, 25000000000108::bigint, null::varchar);
B112: =IF(EXACT([1]DataLookUp!$B112, ""), "", [1]DataLookUp!$B112) -> 25000000000109 | C112: =IF(EXACT(B112, ""), "", VLOOKUP(B112, [1]DataLookUp!$B$4:$C$1000, 2,FALSE )) -> Dodit Widiarto | G112: =G111 + IF(EXACT(H112, ""), 0, 1) -> 32000000000109 | H112: =CONCATENATE("PERFORM ""SchData-OLTP-HumanResource"".""Func_TblWorker_SET""(varSystemLoginSession, null::bigint, null::varchar, null::timestamptz, null::timestamptz, null::varchar, varInstitutionBranchID, varBaseCurrencyID, ", B112, "::bigint, ", IF(EXACT(D112, ""), "null", CONCATENATE("'", D112, "'")), "::varchar);") -> PERFORM "SchData-OLTP-HumanResource"."Func_TblWorker_SET"(varSystemLoginSession, null::bigint, null::varchar, null::timestamptz, null::timestamptz, null::varchar, varInstitutionBranchID, varBaseCurrencyID, 25000000000109::bigint, null::varchar);
B113: =IF(EXACT([1]DataLookUp!$B113, ""), "", [1]DataLookUp!$B113) -> 25000000000110 | C113: =IF(EXACT(B113, ""), "", VLOOKUP(B113, [1]DataLookUp!$B$4:$C$1000, 2,FALSE )) -> Dony Darmawan | G113: =G112 + IF(EXACT(H113, ""), 0, 1) -> 32000000000110 | H113: =CONCATENATE("PERFORM ""SchData-OLTP-HumanResource"".""Func_TblWorker_SET""(varSystemLoginSession, null::bigint, null::varchar, null::timestamptz, null::timestamptz, null::varchar, varInstitutionBranchID, varBaseCurrencyID, ", B113, "::bigint, ", IF(EXACT(D113, ""), "null", CONCATENATE("'", D113, "'")), "::varchar);") -> PERFORM "SchData-OLTP-HumanResource"."Func_TblWorker_SET"(varSystemLoginSession, null::bigint, null::varchar, null::timestamptz, null::timestamptz, null::varchar, varInstitutionBranchID, varBaseCurrencyID, 25000000000110::bigint, null::varchar);
...

Sheet DataLookUp
B2: SYS_PID | C2: =MAIN!B2 -> Ref ID Person | D2: =MAIN!C2 -> Person Name | E2: =MAIN!D2 -> Nomor Induk Pekerja
B4: =IF(EXACT(MAIN!$H4, ""), "", MAIN!$G4) -> 32000000000001 | C4: =IF(EXACT(MAIN!$H4, ""), "", MAIN!$B4) -> 25000000000001 | D4: =IF(EXACT(MAIN!$H4, ""), "", MAIN!$C4) -> Abdollah Syani Siregar | E4: =IF(EXACT(MAIN!$B4, ""), "", ""&MAIN!$D4) | G4: =C4 -> 25000000000001
B5: =IF(EXACT(MAIN!$H5, ""), "", MAIN!$G5) -> 32000000000002 | C5: =IF(EXACT(MAIN!$H5, ""), "", MAIN!$B5) -> 25000000000002 | D5: =IF(EXACT(MAIN!$H5, ""), "", MAIN!$C5) -> Abdul Karim | E5: =IF(EXACT(MAIN!$B5, ""), "", ""&MAIN!$D5) | G5: =C5 -> 25000000000002
B6: =IF(EXACT(MAIN!$H6, ""), "", MAIN!$G6) -> 32000000000003 | C6: =IF(EXACT(MAIN!$H6, ""), "", MAIN!$B6) -> 25000000000003 | D6: =IF(EXACT(MAIN!$H6, ""), "", MAIN!$C6) -> Abdul Rahman Sitompul | E6: =IF(EXACT(MAIN!$B6, ""), "", ""&MAIN!$D6) | G6: =C6 -> 25000000000003
B7: =IF(EXACT(MAIN!$H7, ""), "", MAIN!$G7) -> 32000000000004 | C7: =IF(EXACT(MAIN!$H7, ""), "", MAIN!$B7) -> 25000000000004 | D7: =IF(EXACT(MAIN!$H7, ""), "", MAIN!$C7) -> Abdul Risan | E7: =IF(EXACT(MAIN!$B7, ""), "", ""&MAIN!$D7) | G7: =C7 -> 25000000000004
B8: =IF(EXACT(MAIN!$H8, ""), "", MAIN!$G8) -> 32000000000005 | C8: =IF(EXACT(MAIN!$H8, ""), "", MAIN!$B8) -> 25000000000005 | D8: =IF(EXACT(MAIN!$H8, ""), "", MAIN!$C8) -> Abdullah Nabil | E8: =IF(EXACT(MAIN!$B8, ""), "", ""&MAIN!$D8) | G8: =C8 -> 25000000000005
B9: =IF(EXACT(MAIN!$H9, ""), "", MAIN!$G9) -> 32000000000006 | C9: =IF(EXACT(MAIN!$H9, ""), "", MAIN!$B9) -> 25000000000006 | D9: =IF(EXACT(MAIN!$H9, ""), "", MAIN!$C9) -> Adhitya Danar | E9: =IF(EXACT(MAIN!$B9, ""), "", ""&MAIN!$D9) | G9: =C9 -> 25000000000006
B10: =IF(EXACT(MAIN!$H10, ""), "", MAIN!$G10) -> 32000000000007 | C10: =IF(EXACT(MAIN!$H10, ""), "", MAIN!$B10) -> 25000000000007 | D10: =IF(EXACT(MAIN!$H10, ""), "", MAIN!$C10) -> Adi Ruswandi | E10: =IF(EXACT(MAIN!$B10, ""), "", ""&MAIN!$D10) -> 0209251009 | G10: =C10 -> 25000000000007
B11: =IF(EXACT(MAIN!$H11, ""), "", MAIN!$G11) -> 32000000000008 | C11: =IF(EXACT(MAIN!$H11, ""), "", MAIN!$B11) -> 25000000000008 | D11: =IF(EXACT(MAIN!$H11, ""), "", MAIN!$C11) -> Adietya Dharmawan | E11: =IF(EXACT(MAIN!$B11, ""), "", ""&MAIN!$D11) -> 050321947 | G11: =C11 -> 25000000000008
B12: =IF(EXACT(MAIN!$H12, ""), "", MAIN!$G12) -> 32000000000009 | C12: =IF(EXACT(MAIN!$H12, ""), "", MAIN!$B12) -> 25000000000009 | D12: =IF(EXACT(MAIN!$H12, ""), "", MAIN!$C12) -> Aditya Yudha Prawira | E12: =IF(EXACT(MAIN!$B12, ""), "", ""&MAIN!$D12) | G12: =C12 -> 25000000000009
B13: =IF(EXACT(MAIN!$H13, ""), "", MAIN!$G13) -> 32000000000010 | C13: =IF(EXACT(MAIN!$H13, ""), "", MAIN!$B13) -> 25000000000010 | D13: =IF(EXACT(MAIN!$H13, ""), "", MAIN!$C13) -> Adli Margie | E13: =IF(EXACT(MAIN!$B13, ""), "", ""&MAIN!$D13) | G13: =C13 -> 25000000000010
B14: =IF(EXACT(MAIN!$H14, ""), "", MAIN!$G14) -> 32000000000011 | C14: =IF(EXACT(MAIN!$H14, ""), "", MAIN!$B14) -> 25000000000011 | D14: =IF(EXACT(MAIN!$H14, ""), "", MAIN!$C14) -> Afrida Eka Putri | E14: =IF(EXACT(MAIN!$B14, ""), "", ""&MAIN!$D14) | G14: =C14 -> 25000000000011
B15: =IF(EXACT(MAIN!$H15, ""), "", MAIN!$G15) -> 32000000000012 | C15: =IF(EXACT(MAIN!$H15, ""), "", MAIN!$B15) -> 25000000000012 | D15: =IF(EXACT(MAIN!$H15, ""), "", MAIN!$C15) -> Agnes Sutedja | E15: =IF(EXACT(MAIN!$B15, ""), "", ""&MAIN!$D15) -> 010703020 | G15: =C15 -> 25000000000012
... B617: =IF(EXACT(MAIN!$H617, ""), "", MAIN!$G617) -> 32000000000614 | C617: =IF(EXACT(MAIN!$H617, ""), "", MAIN!$B617) -> 25000000000614 | D617: =IF(EXACT(MAIN!$H617, ""), "", MAIN!$C617) -> Timotius Tabun | E617: =IF(EXACT(MAIN!$B617, ""), "", ""&MAIN!$D617) -> 300913696 | G617: =C617 -> 25000000000614
B618: =IF(EXACT(MAIN!$H618, ""), "", MAIN!$G618) -> 32000000000615 | C618: =IF(EXACT(MAIN!$H618, ""), "", MAIN!$B618) -> 25000000000615 | D618: =IF(EXACT(MAIN!$H618, ""), "", MAIN!$C618) -> Adi | E618: =IF(EXACT(MAIN!$B618, ""), "", ""&MAIN!$D618) -> 0209251009
B619: =IF(EXACT(MAIN!$H619, ""), "", MAIN!$G619) -> 32000000000616 | C619: =IF(EXACT(MAIN!$H619, ""), "", MAIN!$B619) -> 25000000000616 | D619: =IF(EXACT(MAIN!$H619, ""), "", MAIN!$C619) -> Andrean Fahrizi | E619: =IF(EXACT(MAIN!$B619, ""), "", ""&MAIN!$D619)
B620: =IF(EXACT(MAIN!$H620, ""), "", MAIN!$G620) -> 32000000000617 | C620: =IF(EXACT(MAIN!$H620, ""), "", MAIN!$B620) -> 25000000000617 | D620: =IF(EXACT(MAIN!$H620, ""), "", MAIN!$C620) -> Amar Abdilah | E620: =IF(EXACT(MAIN!$B620, ""), "", ""&MAIN!$D620)
B621: =IF(EXACT(MAIN!$H621, ""), "", MAIN!$G621) -> 32000000000618 | C621: =IF(EXACT(MAIN!$H621, ""), "", MAIN!$B621) -> 25000000000618 | D621: =IF(EXACT(MAIN!$H621, ""), "", MAIN!$C621) -> Heru Indra Permana | E621: =IF(EXACT(MAIN!$B621, ""), "", ""&MAIN!$D621)
B622: =IF(EXACT(MAIN!$H622, ""), "", MAIN!$G622) -> 32000000000619 | C622: =IF(EXACT(MAIN!$H622, ""), "", MAIN!$B622) -> 25000000000619 | D622: =IF(EXACT(MAIN!$H622, ""), "", MAIN!$C622) -> Budi Santosa (KSO) | E622: =IF(EXACT(MAIN!$B622, ""), "", ""&MAIN!$D622)
B623: =IF(EXACT(MAIN!$H623, ""), "", MAIN!$G623) -> 32000000000620 | C623: =IF(EXACT(MAIN!$H623, ""), "", MAIN!$B623) -> 25000000000620 | D623: =IF(EXACT(MAIN!$H623, ""), "", MAIN!$C623) -> Haryono | E623: =IF(EXACT(MAIN!$B623, ""), "", ""&MAIN!$D623)
B624: =IF(EXACT(MAIN!$H624, ""), "", MAIN!$G624) -> 32000000000621 | C624: =IF(EXACT(MAIN!$H624, ""), "", MAIN!$B624) -> 25000000000621 | D624: =IF(EXACT(MAIN!$H624, ""), "", MAIN!$C624) -> Indah Sri Rejeki | E624: =IF(EXACT(MAIN!$B624, ""), "", ""&MAIN!$D624)
B625: =IF(EXACT(MAIN!$H626, ""), "", MAIN!$G626) | C625: =IF(EXACT(MAIN!$H626, ""), "", MAIN!$B626) | D625: =IF(EXACT(MAIN!$H626, ""), "", MAIN!$C626) | E625: =IF(EXACT(MAIN!$B626, ""), "", ""&MAIN!$D626)

Sheet MAIN - OrgJobsPos
B2: 160000000000001 | C2: Clerical | D2: 9
B3: 160000000000002 | C3: Senior Clerical | D3: 8
B4: 160000000000003 | C4: Staff | D4: 7
B5: 160000000000004 | C5: Supervisor | D5: 6
B6: 160000000000005 | C6: Senior Supervisor | D6: 5
B7: 160000000000006 | C7: Manager | D7: 4
B8: 160000000000007 | C8: Senior Manager | D8: 3
B9: 160000000000008 | C9: General Manager | D9: 2
B10: 160000000000009 | C10: Director | D10: 1

Sheet MAIN - OrgDepartment
A3: QDC | B3: 11000000000004 | C3: 111000000000001 | D3: Non Department
B4: 11000000000004 | C4: 111000000000002 | D4: Business Development
B5: 11000000000004 | C5: 111000000000003 | D5: Information Technology
B6: 11000000000004 | C6: 111000000000004 | D6: Sales & Marketing
B7: 11000000000004 | C7: 111000000000005 | D7: Finance & Accounting
B8: 11000000000004 | C8: 111000000000006 | D8: Human Resource Development
B9: 11000000000004 | C9: 111000000000007 | D9: Health Safety Environment
B10: 11000000000004 | C10: 111000000000008 | D10: Logistics & Warehouse
B11: 11000000000004 | C11: 111000000000009 | D11: Legal
B12: 11000000000004 | C12: 111000000000010 | D12: Tools & Asset Management
B13: 11000000000004 | C13: 111000000000011 | D13: Project
B14: 11000000000004 | C14: 111000000000012 | D14: Procurement
B15: 11000000000004 | C15: 111000000000013 | D15: Civil And Mechanical Engineering
... B19: 11000000000004 | C19: 111000000000017 | D19: Estimator
A20: IMD | B20: 11000000000007 | C20: 111000000000018 | D20: Non Department
B21: 11000000000007 | C21: 111000000000019 | D21: Operation & Business Development
B22: 11000000000007 | C22: 111000000000020 | D22: Business Development
B23: 11000000000007 | C23: 111000000000021 | D23: Finance & Accounting
B24: 11000000000007 | C24: 111000000000022 | D24: Sales
B25: 11000000000007 | C25: 111000000000023 | D25: Operation & Maintenance
B26: 11000000000007 | C26: 111000000000024 | D26: Warehouse & TAM
G28: Maintenance Building & Technician
G29: Security
G30: Driver
G31: Driver Operational & Ops Truck Crane
G32: Office Boy
G33: Warehouse & Stringing Machine Operator
G34: Mechanic & Maintenance
G35: Warehouse

Sheet Internal Career (Last Position)
B2: Ref ID Worker | C2: =DataLookUp!D2 -> Person Name | D2: Ref ID Worker Type | E2: Worker Type Name | F2: Ref ID Organizational Department | G2: Organizational Department Name | H2: Ref ID Organizational Job Position | I2: Organizational Job Position Name | J2: Job Title | K2: Valid Start DateTimeTZ | L2: Valid Finish DateTimeTZ | M2: Ref ID Document Employment Relationship | O2: SYS_PID Prediction | P2: SQL Syntax
O3: 164000000000000
B4: =IF(EXACT(DataLookUp!$B4, ""), "", DataLookUp!$B4) -> 32000000000001 | C4: =IF(EXACT(DataLookUp!$B4, ""), "", DataLookUp!$D4) -> Abdollah Syani Siregar | D4: 163000000000003 | E4: =IF(EXACT($D4, ""), "", VLOOKUP($D4, [2]DataLookUp!$B$4:$D$15, 2, FALSE )) -> Karyawan Tidak Tetap (Kontrak) | G4: =IF(EXACT($F4, ""), "", VLOOKUP($F4, 'MAIN - OrgDepartment'!$C$3:$D$104, 2, FALSE)) | I4: =IF(EXACT($H4, ""), "", VLOOKUP($H4, 'MAIN - OrgJobsPos'!$B$2:$C$101, 2, FALSE)) | L4: 1900-12-31 23:59:59+07 | O4: =O3 + IF(EXACT(P4, ""), 0, 1) -> 164000000000001 | P4: =CONCATENATE("PERFORM ""SchData-OLTP-HumanResource"".""Func_TblWorkerCareerInternal_SET""(varSystemLoginSession, null::bigint, null::varchar", CONCATENATE(IF(EXACT($K4, ""), ", null", CONCATENATE(", '", $K4, "'")), "::timestamptz"), CONCATENATE(IF(EXACT($L4, ""), ", null", CONCATENATE(", '", $L4, "'")), "::timestamptz"), ", null::varchar, varInstitutionBranchID, varBaseCurrencyID", CONCATENATE(IF(EXACT($B4, ""), ", null", CONCATENATE(", ", $B4, "")), "::bigint"), CONCATENATE(IF(EXACT($D4, ""), ", null", CONCATENATE(", ", $D4, "")), "::bigint"), CONCATENATE(IF(EXACT($F4, ""), ", null", CONCATENATE(", ", $F4, "")), "::bigint"), CONCATENATE(IF(EXACT($H4, ""), ", null", CONCATENATE(", ", $H4, "")), "::bigint"), CONCATENATE(IF(EXACT($J4, ""), ", null", CONCATENATE(", '", $J4, "'")), "::varchar"), CONCATENATE(IF(EXACT($K4, ""), ", null", CONCATENATE(", '", $K4, "'")), "::timestamptz"), CONCATENATE(IF(EXACT($L4, ""), ", null", CONCATENATE(", '", $L4, "'")), "::timestamptz"), CONCATENATE(IF(EXACT($M4, ""), ", null", CONCATENATE(", ", $M4, "")), "::bigint"), ");") -> PERFORM "SchData-OLTP-HumanResource"."Func_TblWorkerCareerInternal_SET"(varSystemLoginSession, null::bigint, null::varchar, null::timestamptz, '1900-12-31 23:59:59+07'::timestamptz, null::varchar, varInstitutionBranchID, varBaseCurrencyID, 32000000000001::bigint, 163000000000003::bigint, null::bigint, null::bigint, null::varchar, null::timestamptz, '1900-12-31 23:59:59+07'::timestamptz, null::bigint);
B5: =IF(EXACT(DataLookUp!$B5, ""), "", DataLookUp!$B5) -> 32000000000002 | C5: =MAIN!C5 -> Abdul Karim | D5: 163000000000003 | E5: =IF(EXACT($D5, ""), "", VLOOKUP($D5, [2]DataLookUp!$B$4:$D$15, 2, FALSE )) -> Karyawan Tidak Tetap (Kontrak) | G5: =IF(EXACT($F5, ""), "", VLOOKUP($F5, 'MAIN - OrgDepartment'!$C$3:$D$104, 2, FALSE)) | I5: =IF(EXACT($H5, ""), "", VLOOKUP($H5, 'MAIN - OrgJobsPos'!$B$2:$C$101, 2, FALSE)) | L5: 1900-12-31 23:59:59+07 | O5: =O4 + IF(EXACT(P5, ""), 0, 1) -> 164000000000002 | P5: =CONCATENATE("PERFORM ""SchData-OLTP-HumanResource"".""Func_TblWorkerCareerInternal_SET""(varSystemLoginSession, null::bigint, null::varchar", CONCATENATE(IF(EXACT($K5, ""), ", null", CONCATENATE(", '", $K5, "'")), "::timestamptz"), CONCATENATE(IF(EXACT($L5, ""), ", null", CONCATENATE(", '", $L5, "'")), "::timestamptz"), ", null::varchar, varInstitutionBranchID, varBaseCurrencyID", CONCATENATE(IF(EXACT($B5, ""), ", null", CONCATENATE(", ", $B5, "")), "::bigint"), CONCATENATE(IF(EXACT($D5, ""), ", null", CONCATENATE(", ", $D5, "")), "::bigint"), CONCATENATE(IF(EXACT($F5, ""), ", null", CONCATENATE(", ", $F5, "")), "::bigint"), CONCATENATE(IF(EXACT($H5, ""), ", null", CONCATENATE(", ", $H5, "")), "::bigint"), CONCATENATE(IF(EXACT($J5, ""), ", null", CONCATENATE(", '", $J5, "'")), "::varchar"), CONCATENATE(IF(EXACT($K5, ""), ", null", CONCATENATE(", '", $K5, "'")), "::timestamptz"), CONCATENATE(IF(EXACT($L5, ""), ", null", CONCATENATE(", '", $L5, "'")), "::timestamptz"), CONCATENATE(IF(EXACT($M5, ""), ", null", CONCATENATE(", ", $M5, "")), "::bigint"), ");") -> PERFORM "SchData-OLTP-HumanResource"."Func_TblWorkerCareerInternal_SET"(varSystemLoginSession, null::bigint, null::varchar, null::timestamptz, '1900-12-31 23:59:59+07'::timestamptz, null::varchar, varInstitutionBranchID, varBaseCurrencyID, 32000000000002::bigint, 163000000000003::bigint, null::bigint, null::bigint, null::varchar, null::timestamptz, '1900-12-31 23:59:59+07'::timestamptz, null::bigint);
B6: =IF(EXACT(DataLookUp!$B6, ""), "", DataLookUp!$B6) -> 32000000000003 | C6: =MAIN!C6 -> Abdul Rahman Sitompul | D6: 163000000000003 | E6: =IF(EXACT($D6, ""), "", VLOOKUP($D6, [2]DataLookUp!$B$4:$D$15, 2, FALSE )) -> Karyawan Tidak Tetap (Kontrak) | G6: =IF(EXACT($F6, ""), "", VLOOKUP($F6, 'MAIN - OrgDepartment'!$C$3:$D$104, 2, FALSE)) | I6: =IF(EXACT($H6, ""), "", VLOOKUP($H6, 'MAIN - OrgJobsPos'!$B$2:$C$101, 2, FALSE)) | L6: 1900-12-31 23:59:59+07 | O6: =O5 + IF(EXACT(P6, ""), 0, 1) -> 164000000000003 | P6: =CONCATENATE("PERFORM ""SchData-OLTP-HumanResource"".""Func_TblWorkerCareerInternal_SET""(varSystemLoginSession, null::bigint, null::varchar", CONCATENATE(IF(EXACT($K6, ""), ", null", CONCATENATE(", '", $K6, "'")), "::timestamptz"), CONCATENATE(IF(EXACT($L6, ""), ", null", CONCATENATE(", '", $L6, "'")), "::timestamptz"), ", null::varchar, varInstitutionBranchID, varBaseCurrencyID", CONCATENATE(IF(EXACT($B6, ""), ", null", CONCATENATE(", ", $B6, "")), "::bigint"), CONCATENATE(IF(EXACT($D6, ""), ", null", CONCATENATE(", ", $D6, "")), "::bigint"), CONCATENATE(IF(EXACT($F6, ""), ", null", CONCATENATE(", ", $F6, "")), "::bigint"), CONCATENATE(IF(EXACT($H6, ""), ", null", CONCATENATE(", ", $H6, "")), "::bigint"), CONCATENATE(IF(EXACT($J6, ""), ", null", CONCATENATE(", '", $J6, "'")), "::varchar"), CONCATENATE(IF(EXACT($K6, ""), ", null", CONCATENATE(", '", $K6, "'")), "::timestamptz"), CONCATENATE(IF(EXACT($L6, ""), ", null", CONCATENATE(", '", $L6, "'")), "::timestamptz"), CONCATENATE(IF(EXACT($M6, ""), ", null", CONCATENATE(", ", $M6, "")), "::bigint"), ");") -> PERFORM "SchData-OLTP-HumanResource"."Func_TblWorkerCareerInternal_SET"(varSystemLoginSession, null::bigint, null::varchar, null::timestamptz, '1900-12-31 23:59:59+07'::timestamptz, null::varchar, varInstitutionBranchID, varBaseCurrencyID, 32000000000003::bigint, 163000000000003::bigint, null::bigint, null::bigint, null::varchar, null::timestamptz, '1900-12-31 23:59:59+07'::timestamptz, null::bigint);
B7: =IF(EXACT(DataLookUp!$B7, ""), "", DataLookUp!$B7) -> 32000000000004 | C7: =MAIN!C7 -> Abdul Risan | D7: 163000000000003 | E7: =IF(EXACT($D7, ""), "", VLOOKUP($D7, [2]DataLookUp!$B$4:$D$15, 2, FALSE )) -> Karyawan Tidak Tetap (Kontrak) | G7: =IF(EXACT($F7, ""), "", VLOOKUP($F7, 'MAIN - OrgDepartment'!$C$3:$D$104, 2, FALSE)) | I7: =IF(EXACT($H7, ""), "", VLOOKUP($H7, 'MAIN - OrgJobsPos'!$B$2:$C$101, 2, FALSE)) | L7: 1900-12-31 23:59:59+07 | O7: =O6 + IF(EXACT(P7, ""), 0, 1) -> 164000000000004 | P7: =CONCATENATE("PERFORM ""SchData-OLTP-HumanResource"".""Func_TblWorkerCareerInternal_SET""(varSystemLoginSession, null::bigint, null::varchar", CONCATENATE(IF(EXACT($K7, ""), ", null", CONCATENATE(", '", $K7, "'")), "::timestamptz"), CONCATENATE(IF(EXACT($L7, ""), ", null", CONCATENATE(", '", $L7, "'")), "::timestamptz"), ", null::varchar, varInstitutionBranchID, varBaseCurrencyID", CONCATENATE(IF(EXACT($B7, ""), ", null", CONCATENATE(", ", $B7, "")), "::bigint"), CONCATENATE(IF(EXACT($D7, ""), ", null", CONCATENATE(", ", $D7, "")), "::bigint"), CONCATENATE(IF(EXACT($F7, ""), ", null", CONCATENATE(", ", $F7, "")), "::bigint"), CONCATENATE(IF(EXACT($H7, ""), ", null", CONCATENATE(", ", $H7, "")), "::bigint"), CONCATENATE(IF(EXACT($J7, ""), ", null", CONCATENATE(", '", $J7, "'")), "::varchar"), CONCATENATE(IF(EXACT($K7, ""), ", null", CONCATENATE(", '", $K7, "'")), "::timestamptz"), CONCATENATE(IF(EXACT($L7, ""), ", null", CONCATENATE(", '", $L7, "'")), "::timestamptz"), CONCATENATE(IF(EXACT($M7, ""), ", null", CONCATENATE(", ", $M7, "")), "::bigint"), ");") -> PERFORM "SchData-OLTP-HumanResource"."Func_TblWorkerCareerInternal_SET"(varSystemLoginSession, null::bigint, null::varchar, null::timestamptz, '1900-12-31 23:59:59+07'::timestamptz, null::varchar, varInstitutionBranchID, varBaseCurrencyID, 32000000000004::bigint, 163000000000003::bigint, null::bigint, null::bigint, null::varchar, null::timestamptz, '1900-12-31 23:59:59+07'::timestamptz, null::bigint);
B8: =IF(EXACT(DataLookUp!$B8, ""), "", DataLookUp!$B8) -> 32000000000005 | C8: =MAIN!C8 -> Abdullah Nabil | D8: 163000000000003 | E8: =IF(EXACT($D8, ""), "", VLOOKUP($D8, [2]DataLookUp!$B$4:$D$15, 2, FALSE )) -> Karyawan Tidak Tetap (Kontrak) | G8: =IF(EXACT($F8, ""), "", VLOOKUP($F8, 'MAIN - OrgDepartment'!$C$3:$D$104, 2, FALSE)) | I8: =IF(EXACT($H8, ""), "", VLOOKUP($H8, 'MAIN - OrgJobsPos'!$B$2:$C$101, 2, FALSE)) | L8: 1900-12-31 23:59:59+07 | O8: =O7 + IF(EXACT(P8, ""), 0, 1) -> 164000000000005 | P8: =CONCATENATE("PERFORM ""SchData-OLTP-HumanResource"".""Func_TblWorkerCareerInternal_SET""(varSystemLoginSession, null::bigint, null::varchar", CONCATENATE(IF(EXACT($K8, ""), ", null", CONCATENATE(", '", $K8, "'")), "::timestamptz"), CONCATENATE(IF(EXACT($L8, ""), ", null", CONCATENATE(", '", $L8, "'")), "::timestamptz"), ", null::varchar, varInstitutionBranchID, varBaseCurrencyID", CONCATENATE(IF(EXACT($B8, ""), ", null", CONCATENATE(", ", $B8, "")), "::bigint"), CONCATENATE(IF(EXACT($D8, ""), ", null", CONCATENATE(", ", $D8, "")), "::bigint"), CONCATENATE(IF(EXACT($F8, ""), ", null", CONCATENATE(", ", $F8, "")), "::bigint"), CONCATENATE(IF(EXACT($H8, ""), ", null", CONCATENATE(", ", $H8, "")), "::bigint"), CONCATENATE(IF(EXACT($J8, ""), ", null", CONCATENATE(", '", $J8, "'")), "::varchar"), CONCATENATE(IF(EXACT($K8, ""), ", null", CONCATENATE(", '", $K8, "'")), "::timestamptz"), CONCATENATE(IF(EXACT($L8, ""), ", null", CONCATENATE(", '", $L8, "'")), "::timestamptz"), CONCATENATE(IF(EXACT($M8, ""), ", null", CONCATENATE(", ", $M8, "")), "::bigint"), ");") -> PERFORM "SchData-OLTP-HumanResource"."Func_TblWorkerCareerInternal_SET"(varSystemLoginSession, null::bigint, null::varchar, null::timestamptz, '1900-12-31 23:59:59+07'::timestamptz, null::varchar, varInstitutionBranchID, varBaseCurrencyID, 32000000000005::bigint, 163000000000003::bigint, null::bigint, null::bigint, null::varchar, null::timestamptz, '1900-12-31 23:59:59+07'::timestamptz, null::bigint);
B9: =IF(EXACT(DataLookUp!$B9, ""), "", DataLookUp!$B9) -> 32000000000006 | C9: =MAIN!C9 -> Adhitya Danar | D9: 163000000000003 | E9: =IF(EXACT($D9, ""), "", VLOOKUP($D9, [2]DataLookUp!$B$4:$D$15, 2, FALSE )) -> Karyawan Tidak Tetap (Kontrak) | G9: =IF(EXACT($F9, ""), "", VLOOKUP($F9, 'MAIN - OrgDepartment'!$C$3:$D$104, 2, FALSE)) | I9: =IF(EXACT($H9, ""), "", VLOOKUP($H9, 'MAIN - OrgJobsPos'!$B$2:$C$101, 2, FALSE)) | L9: 1900-12-31 23:59:59+07 | O9: =O8 + IF(EXACT(P9, ""), 0, 1) -> 164000000000006 | P9: =CONCATENATE("PERFORM ""SchData-OLTP-HumanResource"".""Func_TblWorkerCareerInternal_SET""(varSystemLoginSession, null::bigint, null::varchar", CONCATENATE(IF(EXACT($K9, ""), ", null", CONCATENATE(", '", $K9, "'")), "::timestamptz"), CONCATENATE(IF(EXACT($L9, ""), ", null", CONCATENATE(", '", $L9, "'")), "::timestamptz"), ", null::varchar, varInstitutionBranchID, varBaseCurrencyID", CONCATENATE(IF(EXACT($B9, ""), ", null", CONCATENATE(", ", $B9, "")), "::bigint"), CONCATENATE(IF(EXACT($D9, ""), ", null", CONCATENATE(", ", $D9, "")), "::bigint"), CONCATENATE(IF(EXACT($F9, ""), ", null", CONCATENATE(", ", $F9, "")), "::bigint"), CONCATENATE(IF(EXACT($H9, ""), ", null", CONCATENATE(", ", $H9, "")), "::bigint"), CONCATENATE(IF(EXACT($J9, ""), ", null", CONCATENATE(", '", $J9, "'")), "::varchar"), CONCATENATE(IF(EXACT($K9, ""), ", null", CONCATENATE(", '", $K9, "'")), "::timestamptz"), CONCATENATE(IF(EXACT($L9, ""), ", null", CONCATENATE(", '", $L9, "'")), "::timestamptz"), CONCATENATE(IF(EXACT($M9, ""), ", null", CONCATENATE(", ", $M9, "")), "::bigint"), ");") -> PERFORM "SchData-OLTP-HumanResource"."Func_TblWorkerCareerInternal_SET"(varSystemLoginSession, null::bigint, null::varchar, null::timestamptz, '1900-12-31 23:59:59+07'::timestamptz, null::varchar, varInstitutionBranchID, varBaseCurrencyID, 32000000000006::bigint, 163000000000003::bigint, null::bigint, null::bigint, null::varchar, null::timestamptz, '1900-12-31 23:59:59+07'::timestamptz, null::bigint);
B10: =IF(EXACT(DataLookUp!$B10, ""), "", DataLookUp!$B10) -> 32000000000007 | C10: =MAIN!C10 -> Adi Ruswandi | D10: 163000000000003 | E10: =IF(EXACT($D10, ""), "", VLOOKUP($D10, [2]DataLookUp!$B$4:$D$15, 2, FALSE )) -> Karyawan Tidak Tetap (Kontrak) | G10: =IF(EXACT($F10, ""), "", VLOOKUP($F10, 'MAIN - OrgDepartment'!$C$3:$D$104, 2, FALSE)) | I10: =IF(EXACT($H10, ""), "", VLOOKUP($H10, 'MAIN - OrgJobsPos'!$B$2:$C$101, 2, FALSE)) | L10: 1900-12-31 23:59:59+07 | O10: =O9 + IF(EXACT(P10, ""), 0, 1) -> 164000000000007 | P10: =CONCATENATE("PERFORM ""SchData-OLTP-HumanResource"".""Func_TblWorkerCareerInternal_SET""(varSystemLoginSession, null::bigint, null::varchar", CONCATENATE(IF(EXACT($K10, ""), ", null", CONCATENATE(", '", $K10, "'")), "::timestamptz"), CONCATENATE(IF(EXACT($L10, ""), ", null", CONCATENATE(", '", $L10, "'")), "::timestamptz"), ", null::varchar, varInstitutionBranchID, varBaseCurrencyID", CONCATENATE(IF(EXACT($B10, ""), ", null", CONCATENATE(", ", $B10, "")), "::bigint"), CONCATENATE(IF(EXACT($D10, ""), ", null", CONCATENATE(", ", $D10, "")), "::bigint"), CONCATENATE(IF(EXACT($F10, ""), ", null", CONCATENATE(", ", $F10, "")), "::bigint"), CONCATENATE(IF(EXACT($H10, ""), ", null", CONCATENATE(", ", $H10, "")), "::bigint"), CONCATENATE(IF(EXACT($J10, ""), ", null", CONCATENATE(", '", $J10, "'")), "::varchar"), CONCATENATE(IF(EXACT($K10, ""), ", null", CONCATENATE(", '", $K10, "'")), "::timestamptz"), CONCATENATE(IF(EXACT($L10, ""), ", null", CONCATENATE(", '", $L10, "'")), "::timestamptz"), CONCATENATE(IF(EXACT($M10, ""), ", null", CONCATENATE(", ", $M10, "")), "::bigint"), ");") -> PERFORM "SchData-OLTP-HumanResource"."Func_TblWorkerCareerInternal_SET"(varSystemLoginSession, null::bigint, null::varchar, null::timestamptz, '1900-12-31 23:59:59+07'::timestamptz, null::varchar, varInstitutionBranchID, varBaseCurrencyID, 32000000000007::bigint, 163000000000003::bigint, null::bigint, null::bigint, null::varchar, null::timestamptz, '1900-12-31 23:59:59+07'::timestamptz, null::bigint);
B11: =IF(EXACT(DataLookUp!$B11, ""), "", DataLookUp!$B11) -> 32000000000008 | C11: =MAIN!C11 -> Adietya Dharmawan | D11: 163000000000003 | E11: =IF(EXACT($D11, ""), "", VLOOKUP($D11, [2]DataLookUp!$B$4:$D$15, 2, FALSE )) -> Karyawan Tidak Tetap (Kontrak) | G11: =IF(EXACT($F11, ""), "", VLOOKUP($F11, 'MAIN - OrgDepartment'!$C$3:$D$104, 2, FALSE)) | I11: =IF(EXACT($H11, ""), "", VLOOKUP($H11, 'MAIN - OrgJobsPos'!$B$2:$C$101, 2, FALSE)) | L11: 1900-12-31 23:59:59+07 | O11: =O10 + IF(EXACT(P11, ""), 0, 1) -> 164000000000008 | P11: =CONCATENATE("PERFORM ""SchData-OLTP-HumanResource"".""Func_TblWorkerCareerInternal_SET""(varSystemLoginSession, null::bigint, null::varchar", CONCATENATE(IF(EXACT($K11, ""), ", null", CONCATENATE(", '", $K11, "'")), "::timestamptz"), CONCATENATE(IF(EXACT($L11, ""), ", null", CONCATENATE(", '", $L11, "'")), "::timestamptz"), ", null::varchar, varInstitutionBranchID, varBaseCurrencyID", CONCATENATE(IF(EXACT($B11, ""), ", null", CONCATENATE(", ", $B11, "")), "::bigint"), CONCATENATE(IF(EXACT($D11, ""), ", null", CONCATENATE(", ", $D11, "")), "::bigint"), CONCATENATE(IF(EXACT($F11, ""), ", null", CONCATENATE(", ", $F11, "")), "::bigint"), CONCATENATE(IF(EXACT($H11, ""), ", null", CONCATENATE(", ", $H11, "")), "::bigint"), CONCATENATE(IF(EXACT($J11, ""), ", null", CONCATENATE(", '", $J11, "'")), "::varchar"), CONCATENATE(IF(EXACT($K11, ""), ", null", CONCATENATE(", '", $K11, "'")), "::timestamptz"), CONCATENATE(IF(EXACT($L11, ""), ", null", CONCATENATE(", '", $L11, "'")), "::timestamptz"), CONCATENATE(IF(EXACT($M11, ""), ", null", CONCATENATE(", ", $M11, "")), "::bigint"), ");") -> PERFORM "SchData-OLTP-HumanResource"."Func_TblWorkerCareerInternal_SET"(varSystemLoginSession, null::bigint, null::varchar, null::timestamptz, '1900-12-31 23:59:59+07'::timestamptz, null::varchar, varInstitutionBranchID, varBaseCurrencyID, 32000000000008::bigint, 163000000000003::bigint, null::bigint, null::bigint, null::varchar, null::timestamptz, '1900-12-31 23:59:59+07'::timestamptz, null::bigint);
B12: =IF(EXACT(DataLookUp!$B12, ""), "", DataLookUp!$B12) -> 32000000000009 | C12: =MAIN!C12 -> Aditya Yudha Prawira | D12: 163000000000003 | E12: =IF(EXACT($D12, ""), "", VLOOKUP($D12, [2]DataLookUp!$B$4:$D$15, 2, FALSE )) -> Karyawan Tidak Tetap (Kontrak) | G12: =IF(EXACT($F12, ""), "", VLOOKUP($F12, 'MAIN - OrgDepartment'!$C$3:$D$104, 2, FALSE)) | I12: =IF(EXACT($H12, ""), "", VLOOKUP($H12, 'MAIN - OrgJobsPos'!$B$2:$C$101, 2, FALSE)) | L12: 1900-12-31 23:59:59+07 | O12: =O11 + IF(EXACT(P12, ""), 0, 1) -> 164000000000009 | P12: =CONCATENATE("PERFORM ""SchData-OLTP-HumanResource"".""Func_TblWorkerCareerInternal_SET""(varSystemLoginSession, null::bigint, null::varchar", CONCATENATE(IF(EXACT($K12, ""), ", null", CONCATENATE(", '", $K12, "'")), "::timestamptz"), CONCATENATE(IF(EXACT($L12, ""), ", null", CONCATENATE(", '", $L12, "'")), "::timestamptz"), ", null::varchar, varInstitutionBranchID, varBaseCurrencyID", CONCATENATE(IF(EXACT($B12, ""), ", null", CONCATENATE(", ", $B12, "")), "::bigint"), CONCATENATE(IF(EXACT($D12, ""), ", null", CONCATENATE(", ", $D12, "")), "::bigint"), CONCATENATE(IF(EXACT($F12, ""), ", null", CONCATENATE(", ", $F12, "")), "::bigint"), CONCATENATE(IF(EXACT($H12, ""), ", null", CONCATENATE(", ", $H12, "")), "::bigint"), CONCATENATE(IF(EXACT($J12, ""), ", null", CONCATENATE(", '", $J12, "'")), "::varchar"), CONCATENATE(IF(EXACT($K12, ""), ", null", CONCATENATE(", '", $K12, "'")), "::timestamptz"), CONCATENATE(IF(EXACT($L12, ""), ", null", CONCATENATE(", '", $L12, "'")), "::timestamptz"), CONCATENATE(IF(EXACT($M12, ""), ", null", CONCATENATE(", ", $M12, "")), "::bigint"), ");") -> PERFORM "SchData-OLTP-HumanResource"."Func_TblWorkerCareerInternal_SET"(varSystemLoginSession, null::bigint, null::varchar, null::timestamptz, '1900-12-31 23:59:59+07'::timestamptz, null::varchar, varInstitutionBranchID, varBaseCurrencyID, 32000000000009::bigint, 163000000000003::bigint, null::bigint, null::bigint, null::varchar, null::timestamptz, '1900-12-31 23:59:59+07'::timestamptz, null::bigint);
B13: =IF(EXACT(DataLookUp!$B13, ""), "", DataLookUp!$B13) -> 32000000000010 | C13: =MAIN!C13 -> Adli Margie | D13: 163000000000002 | E13: =IF(EXACT($D13, ""), "", VLOOKUP($D13, [2]DataLookUp!$B$4:$D$15, 2, FALSE )) -> Karyawan Tetap (Purna Waktu) | G13: =IF(EXACT($F13, ""), "", VLOOKUP($F13, 'MAIN - OrgDepartment'!$C$3:$D$104, 2, FALSE)) | I13: =IF(EXACT($H13, ""), "", VLOOKUP($H13, 'MAIN - OrgJobsPos'!$B$2:$C$101, 2, FALSE)) | L13: 1900-12-31 23:59:59+07 | O13: =O12 + IF(EXACT(P13, ""), 0, 1) -> 164000000000010 | P13: =CONCATENATE("PERFORM ""SchData-OLTP-HumanResource"".""Func_TblWorkerCareerInternal_SET""(varSystemLoginSession, null::bigint, null::varchar", CONCATENATE(IF(EXACT($K13, ""), ", null", CONCATENATE(", '", $K13, "'")), "::timestamptz"), CONCATENATE(IF(EXACT($L13, ""), ", null", CONCATENATE(", '", $L13, "'")), "::timestamptz"), ", null::varchar, varInstitutionBranchID, varBaseCurrencyID", CONCATENATE(IF(EXACT($B13, ""), ", null", CONCATENATE(", ", $B13, "")), "::bigint"), CONCATENATE(IF(EXACT($D13, ""), ", null", CONCATENATE(", ", $D13, "")), "::bigint"), CONCATENATE(IF(EXACT($F13, ""), ", null", CONCATENATE(", ", $F13, "")), "::bigint"), CONCATENATE(IF(EXACT($H13, ""), ", null", CONCATENATE(", ", $H13, "")), "::bigint"), CONCATENATE(IF(EXACT($J13, ""), ", null", CONCATENATE(", '", $J13, "'")), "::varchar"), CONCATENATE(IF(EXACT($K13, ""), ", null", CONCATENATE(", '", $K13, "'")), "::timestamptz"), CONCATENATE(IF(EXACT($L13, ""), ", null", CONCATENATE(", '", $L13, "'")), "::timestamptz"), CONCATENATE(IF(EXACT($M13, ""), ", null", CONCATENATE(", ", $M13, "")), "::bigint"), ");") -> PERFORM "SchData-OLTP-HumanResource"."Func_TblWorkerCareerInternal_SET"(varSystemLoginSession, null::bigint, null::varchar, null::timestamptz, '1900-12-31 23:59:59+07'::timestamptz, null::varchar, varInstitutionBranchID, varBaseCurrencyID, 32000000000010::bigint, 163000000000002::bigint, null::bigint, null::bigint, null::varchar, null::timestamptz, '1900-12-31 23:59:59+07'::timestamptz, null::bigint);
B14: =IF(EXACT(DataLookUp!$B14, ""), "", DataLookUp!$B14) -> 32000000000011 | C14: =MAIN!C14 -> Afrida Eka Putri | D14: 163000000000003 | E14: =IF(EXACT($D14, ""), "", VLOOKUP($D14, [2]DataLookUp!$B$4:$D$15, 2, FALSE )) -> Karyawan Tidak Tetap (Kontrak) | G14: =IF(EXACT($F14, ""), "", VLOOKUP($F14, 'MAIN - OrgDepartment'!$C$3:$D$104, 2, FALSE)) | I14: =IF(EXACT($H14, ""), "", VLOOKUP($H14, 'MAIN - OrgJobsPos'!$B$2:$C$101, 2, FALSE)) | L14: 1900-12-31 23:59:59+07 | O14: =O13 + IF(EXACT(P14, ""), 0, 1) -> 164000000000011 | P14: =CONCATENATE("PERFORM ""SchData-OLTP-HumanResource"".""Func_TblWorkerCareerInternal_SET""(varSystemLoginSession, null::bigint, null::varchar", CONCATENATE(IF(EXACT($K14, ""), ", null", CONCATENATE(", '", $K14, "'")), "::timestamptz"), CONCATENATE(IF(EXACT($L14, ""), ", null", CONCATENATE(", '", $L14, "'")), "::timestamptz"), ", null::varchar, varInstitutionBranchID, varBaseCurrencyID", CONCATENATE(IF(EXACT($B14, ""), ", null", CONCATENATE(", ", $B14, "")), "::bigint"), CONCATENATE(IF(EXACT($D14, ""), ", null", CONCATENATE(", ", $D14, "")), "::bigint"), CONCATENATE(IF(EXACT($F14, ""), ", null", CONCATENATE(", ", $F14, "")), "::bigint"), CONCATENATE(IF(EXACT($H14, ""), ", null", CONCATENATE(", ", $H14, "")), "::bigint"), CONCATENATE(IF(EXACT($J14, ""), ", null", CONCATENATE(", '", $J14, "'")), "::varchar"), CONCATENATE(IF(EXACT($K14, ""), ", null", CONCATENATE(", '", $K14, "'")), "::timestamptz"), CONCATENATE(IF(EXACT($L14, ""), ", null", CONCATENATE(", '", $L14, "'")), "::timestamptz"), CONCATENATE(IF(EXACT($M14, ""), ", null", CONCATENATE(", ", $M14, "")), "::bigint"), ");") -> PERFORM "SchData-OLTP-HumanResource"."Func_TblWorkerCareerInternal_SET"(varSystemLoginSession, null::bigint, null::varchar, null::timestamptz, '1900-12-31 23:59:59+07'::timestamptz, null::varchar, varInstitutionBranchID, varBaseCurrencyID, 32000000000011::bigint, 163000000000003::bigint, null::bigint, null::bigint, null::varchar, null::timestamptz, '1900-12-31 23:59:59+07'::timestamptz, null::bigint);
B15: =IF(EXACT(DataLookUp!$B15, ""), "", DataLookUp!$B15) -> 32000000000012 | C15: =MAIN!C15 -> Agnes Sutedja | D15: 163000000000002 | E15: =IF(EXACT($D15, ""), "", VLOOKUP($D15, [2]DataLookUp!$B$4:$D$15, 2, FALSE )) -> Karyawan Tetap (Purna Waktu) | F15: 111000000000007 | G15: =IF(EXACT($F15, ""), "", VLOOKUP($F15, 'MAIN - OrgDepartment'!$C$3:$D$104, 2, FALSE)) -> Health Safety Environment | H15: 160000000000006 | I15: =IF(EXACT($H15, ""), "", VLOOKUP($H15, 'MAIN - OrgJobsPos'!$B$2:$C$101, 2, FALSE)) -> Manager | J15: QHSE Manager | K15: 2003-07-01 00:00:00+07 | L15: 9999-12-31 23:59:59+07 | O15: =O14 + IF(EXACT(P15, ""), 0, 1) -> 164000000000012 | P15: =CONCATENATE("PERFORM ""SchData-OLTP-HumanResource"".""Func_TblWorkerCareerInternal_SET""(varSystemLoginSession, null::bigint, null::varchar", CONCATENATE(IF(EXACT($K15, ""), ", null", CONCATENATE(", '", $K15, "'")), "::timestamptz"), CONCATENATE(IF(EXACT($L15, ""), ", null", CONCATENATE(", '", $L15, "'")), "::timestamptz"), ", null::varchar, varInstitutionBranchID, varBaseCurrencyID", CONCATENATE(IF(EXACT($B15, ""), ", null", CONCATENATE(", ", $B15, "")), "::bigint"), CONCATENATE(IF(EXACT($D15, ""), ", null", CONCATENATE(", ", $D15, "")), "::bigint"), CONCATENATE(IF(EXACT($F15, ""), ", null", CONCATENATE(", ", $F15, "")), "::bigint"), CONCATENATE(IF(EXACT($H15, ""), ", null", CONCATENATE(", ", $H15, "")), "::bigint"), CONCATENATE(IF(EXACT($J15, ""), ", null", CONCATENATE(", '", $J15, "'")), "::varchar"), CONCATENATE(IF(EXACT($K15, ""), ", null", CONCATENATE(", '", $K15, "'")), "::timestamptz"), CONCATENATE(IF(EXACT($L15, ""), ", null", CONCATENATE(", '", $L15, "'")), "::timestamptz"), CONCATENATE(IF(EXACT($M15, ""), ", null", CONCATENATE(", ", $M15, "")), "::bigint"), ");") -> PERFORM "SchData-OLTP-HumanResource"."Func_TblWorkerCareerInternal_SET"(varSystemLoginSession, null::bigint, null::varchar, '2003-07-01 00:00:00+07'::timestamptz, '9999-12-31 23:59:59+07'::timestamptz, null::varchar, varInstitutionBranchID, varBaseCurrencyID, 32000000000012::bigint, 163000000000002::bigint, 111000000000007::bigint, 160000000000006::bigint, 'QHSE Manager'::varchar, '2003-07-01 00:00:00+07'::timestamptz, '9999-12-31 23:59:59+07'::timestamptz, null::bigint);
B16: =IF(EXACT(DataLookUp!$B16, ""), "", DataLookUp!$B16) -> 32000000000013 | C16: =MAIN!C16 -> Agung Hendarto | D16: 163000000000003 | E16: =IF(EXACT($D16, ""), "", VLOOKUP($D16, [2]DataLookUp!$B$4:$D$15, 2, FALSE )) -> Karyawan Tidak Tetap (Kontrak) | G16: =IF(EXACT($F16, ""), "", VLOOKUP($F16, 'MAIN - OrgDepartment'!$C$3:$D$104, 2, FALSE)) | I16: =IF(EXACT($H16, ""), "", VLOOKUP($H16, 'MAIN - OrgJobsPos'!$B$2:$C$101, 2, FALSE)) | L16: 1900-12-31 23:59:59+07 | O16: =O15 + IF(EXACT(P16, ""), 0, 1) -> 164000000000013 | P16: =CONCATENATE("PERFORM ""SchData-OLTP-HumanResource"".""Func_TblWorkerCareerInternal_SET""(varSystemLoginSession, null::bigint, null::varchar", CONCATENATE(IF(EXACT($K16, ""), ", null", CONCATENATE(", '", $K16, "'")), "::timestamptz"), CONCATENATE(IF(EXACT($L16, ""), ", null", CONCATENATE(", '", $L16, "'")), "::timestamptz"), ", null::varchar, varInstitutionBranchID, varBaseCurrencyID", CONCATENATE(IF(EXACT($B16, ""), ", null", CONCATENATE(", ", $B16, "")), "::bigint"), CONCATENATE(IF(EXACT($D16, ""), ", null", CONCATENATE(", ", $D16, "")), "::bigint"), CONCATENATE(IF(EXACT($F16, ""), ", null", CONCATENATE(", ", $F16, "")), "::bigint"), CONCATENATE(IF(EXACT($H16, ""), ", null", CONCATENATE(", ", $H16, "")), "::bigint"), CONCATENATE(IF(EXACT($J16, ""), ", null", CONCATENATE(", '", $J16, "'")), "::varchar"), CONCATENATE(IF(EXACT($K16, ""), ", null", CONCATENATE(", '", $K16, "'")), "::timestamptz"), CONCATENATE(IF(EXACT($L16, ""), ", null", CONCATENATE(", '", $L16, "'")), "::timestamptz"), CONCATENATE(IF(EXACT($M16, ""), ", null", CONCATENATE(", ", $M16, "")), "::bigint"), ");") -> PERFORM "SchData-OLTP-HumanResource"."Func_TblWorkerCareerInternal_SET"(varSystemLoginSession, null::bigint, null::varchar, null::timestamptz, '1900-12-31 23:59:59+07'::timestamptz, null::varchar, varInstitutionBranchID, varBaseCurrencyID, 32000000000013::bigint, 163000000000003::bigint, null::bigint, null::bigint, null::varchar, null::timestamptz, '1900-12-31 23:59:59+07'::timestamptz, null::bigint);
B17: =IF(EXACT(DataLookUp!$B17, ""), "", DataLookUp!$B17) -> 32000000000014 | C17: =MAIN!C17 -> Agus Priyatno Mahmudo | D17: 163000000000003 | E17: =IF(EXACT($D17, ""), "", VLOOKUP($D17, [2]DataLookUp!$B$4:$D$15, 2, FALSE )) -> Karyawan Tidak Tetap (Kontrak) | G17: =IF(EXACT($F17, ""), "", VLOOKUP($F17, 'MAIN - OrgDepartment'!$C$3:$D$104, 2, FALSE)) | I17: =IF(EXACT($H17, ""), "", VLOOKUP($H17, 'MAIN - OrgJobsPos'!$B$2:$C$101, 2, FALSE)) | L17: 1900-12-31 23:59:59+07 | O17: =O16 + IF(EXACT(P17, ""), 0, 1) -> 164000000000014 | P17: =CONCATENATE("PERFORM ""SchData-OLTP-HumanResource"".""Func_TblWorkerCareerInternal_SET""(varSystemLoginSession, null::bigint, null::varchar", CONCATENATE(IF(EXACT($K17, ""), ", null", CONCATENATE(", '", $K17, "'")), "::timestamptz"), CONCATENATE(IF(EXACT($L17, ""), ", null", CONCATENATE(", '", $L17, "'")), "::timestamptz"), ", null::varchar, varInstitutionBranchID, varBaseCurrencyID", CONCATENATE(IF(EXACT($B17, ""), ", null", CONCATENATE(", ", $B17, "")), "::bigint"), CONCATENATE(IF(EXACT($D17, ""), ", null", CONCATENATE(", ", $D17, "")), "::bigint"), CONCATENATE(IF(EXACT($F17, ""), ", null", CONCATENATE(", ", $F17, "")), "::bigint"), CONCATENATE(IF(EXACT($H17, ""), ", null", CONCATENATE(", ", $H17, "")), "::bigint"), CONCATENATE(IF(EXACT($J17, ""), ", null", CONCATENATE(", '", $J17, "'")), "::varchar"), CONCATENATE(IF(EXACT($K17, ""), ", null", CONCATENATE(", '", $K17, "'")), "::timestamptz"), CONCATENATE(IF(EXACT($L17, ""), ", null", CONCATENATE(", '", $L17, "'")), "::timestamptz"), CONCATENATE(IF(EXACT($M17, ""), ", null", CONCATENATE(", ", $M17, "")), "::bigint"), ");") -> PERFORM "SchData-OLTP-HumanResource"."Func_TblWorkerCareerInternal_SET"(varSystemLoginSession, null::bigint, null::varchar, null::timestamptz, '1900-12-31 23:59:59+07'::timestamptz, null::varchar, varInstitutionBranchID, varBaseCurrencyID, 32000000000014::bigint, 163000000000003::bigint, null::bigint, null::bigint, null::varchar, null::timestamptz, '1900-12-31 23:59:59+07'::timestamptz, null::bigint);
B18: =IF(EXACT(DataLookUp!$B18, ""), "", DataLookUp!$B18) -> 32000000000015 | C18: =MAIN!C18 -> Agus Salim | D18: 163000000000002 | E18: =IF(EXACT($D18, ""), "", VLOOKUP($D18, [2]DataLookUp!$B$4:$D$15, 2, FALSE )) -> Karyawan Tetap (Purna Waktu) | G18: =IF(EXACT($F18, ""), "", VLOOKUP($F18, 'MAIN - OrgDepartment'!$C$3:$D$104, 2, FALSE)) | I18: =IF(EXACT($H18, ""), "", VLOOKUP($H18, 'MAIN - OrgJobsPos'!$B$2:$C$101, 2, FALSE)) | L18: 9999-12-31 23:59:59+07 | O18: =O17 + IF(EXACT(P18, ""), 0, 1) -> 164000000000015 | P18: =CONCATENATE("PERFORM ""SchData-OLTP-HumanResource"".""Func_TblWorkerCareerInternal_SET""(varSystemLoginSession, null::bigint, null::varchar", CONCATENATE(IF(EXACT($K18, ""), ", null", CONCATENATE(", '", $K18, "'")), "::timestamptz"), CONCATENATE(IF(EXACT($L18, ""), ", null", CONCATENATE(", '", $L18, "'")), "::timestamptz"), ", null::varchar, varInstitutionBranchID, varBaseCurrencyID", CONCATENATE(IF(EXACT($B18, ""), ", null", CONCATENATE(", ", $B18, "")), "::bigint"), CONCATENATE(IF(EXACT($D18, ""), ", null", CONCATENATE(", ", $D18, "")), "::bigint"), CONCATENATE(IF(EXACT($F18, ""), ", null", CONCATENATE(", ", $F18, "")), "::bigint"), CONCATENATE(IF(EXACT($H18, ""), ", null", CONCATENATE(", ", $H18, "")), "::bigint"), CONCATENATE(IF(EXACT($J18, ""), ", null", CONCATENATE(", '", $J18, "'")), "::varchar"), CONCATENATE(IF(EXACT($K18, ""), ", null", CONCATENATE(", '", $K18, "'")), "::timestamptz"), CONCATENATE(IF(EXACT($L18, ""), ", null", CONCATENATE(", '", $L18, "'")), "::timestamptz"), CONCATENATE(IF(EXACT($M18, ""), ", null", CONCATENATE(", ", $M18, "")), "::bigint"), ");") -> PERFORM "SchData-OLTP-HumanResource"."Func_TblWorkerCareerInternal_SET"(varSystemLoginSession, null::bigint, null::varchar, null::timestamptz, '9999-12-31 23:59:59+07'::timestamptz, null::varchar, varInstitutionBranchID, varBaseCurrencyID, 32000000000015::bigint, 163000000000002::bigint, null::bigint, null::bigint, null::varchar, null::timestamptz, '9999-12-31 23:59:59+07'::timestamptz, null::bigint);
B19: =IF(EXACT(DataLookUp!$B19, ""), "", DataLookUp!$B19) -> 32000000000016 | C19: =MAIN!C19 -> Agus Tanto | D19: 163000000000003 | E19: =IF(EXACT($D19, ""), "", VLOOKUP($D19, [2]DataLookUp!$B$4:$D$15, 2, FALSE )) -> Karyawan Tidak Tetap (Kontrak) | G19: =IF(EXACT($F19, ""), "", VLOOKUP($F19, 'MAIN - OrgDepartment'!$C$3:$D$104, 2, FALSE)) | I19: =IF(EXACT($H19, ""), "", VLOOKUP($H19, 'MAIN - OrgJobsPos'!$B$2:$C$101, 2, FALSE)) | L19: 1900-12-31 23:59:59+07 | O19: =O18 + IF(EXACT(P19, ""), 0, 1) -> 164000000000016 | P19: =CONCATENATE("PERFORM ""SchData-OLTP-HumanResource"".""Func_TblWorkerCareerInternal_SET""(varSystemLoginSession, null::bigint, null::varchar", CONCATENATE(IF(EXACT($K19, ""), ", null", CONCATENATE(", '", $K19, "'")), "::timestamptz"), CONCATENATE(IF(EXACT($L19, ""), ", null", CONCATENATE(", '", $L19, "'")), "::timestamptz"), ", null::varchar, varInstitutionBranchID, varBaseCurrencyID", CONCATENATE(IF(EXACT($B19, ""), ", null", CONCATENATE(", ", $B19, "")), "::bigint"), CONCATENATE(IF(EXACT($D19, ""), ", null", CONCATENATE(", ", $D19, "")), "::bigint"), CONCATENATE(IF(EXACT($F19, ""), ", null", CONCATENATE(", ", $F19, "")), "::bigint"), CONCATENATE(IF(EXACT($H19, ""), ", null", CONCATENATE(", ", $H19, "")), "::bigint"), CONCATENATE(IF(EXACT($J19, ""), ", null", CONCATENATE(", '", $J19, "'")), "::varchar"), CONCATENATE(IF(EXACT($K19, ""), ", null", CONCATENATE(", '", $K19, "'")), "::timestamptz"), CONCATENATE(IF(EXACT($L19, ""), ", null", CONCATENATE(", '", $L19, "'")), "::timestamptz"), CONCATENATE(IF(EXACT($M19, ""), ", null", CONCATENATE(", ", $M19, "")), "::bigint"), ");") -> PERFORM "SchData-OLTP-HumanResource"."Func_TblWorkerCareerInternal_SET"(varSystemLoginSession, null::bigint, null::varchar, null::timestamptz, '1900-12-31 23:59:59+07'::timestamptz, null::varchar, varInstitutionBranchID, varBaseCurrencyID, 32000000000016::bigint, 163000000000003::bigint, null::bigint, null::bigint, null::varchar, null::timestamptz, '1900-12-31 23:59:59+07'::timestamptz, null::bigint);
B20: =IF(EXACT(DataLookUp!$B20, ""), "", DataLookUp!$B20) -> 32000000000017 | C20: =MAIN!C20 -> Ahmad Faiz Haems Muda | D20: 163000000000002 | E20: =IF(EXACT($D20, ""), "", VLOOKUP($D20, [2]DataLookUp!$B$4:$D$15, 2, FALSE )) -> Karyawan Tetap (Purna Waktu) | F20: 111000000000006 | G20: =IF(EXACT($F20, ""), "", VLOOKUP($F20, 'MAIN - OrgDepartment'!$C$3:$D$104, 2, FALSE)) -> Human Resource Development | H20: 160000000000006 | I20: =IF(EXACT($H20, ""), "", VLOOKUP($H20, 'MAIN - OrgJobsPos'!$B$2:$C$101, 2, FALSE)) -> Manager | J20: HRD Manager | L20: 9999-12-31 23:59:59+07 | O20: =O19 + IF(EXACT(P20, ""), 0, 1) -> 164000000000017 | P20: =CONCATENATE("PERFORM ""SchData-OLTP-HumanResource"".""Func_TblWorkerCareerInternal_SET""(varSystemLoginSession, null::bigint, null::varchar", CONCATENATE(IF(EXACT($K20, ""), ", null", CONCATENATE(", '", $K20, "'")), "::timestamptz"), CONCATENATE(IF(EXACT($L20, ""), ", null", CONCATENATE(", '", $L20, "'")), "::timestamptz"), ", null::varchar, varInstitutionBranchID, varBaseCurrencyID", CONCATENATE(IF(EXACT($B20, ""), ", null", CONCATENATE(", ", $B20, "")), "::bigint"), CONCATENATE(IF(EXACT($D20, ""), ", null", CONCATENATE(", ", $D20, "")), "::bigint"), CONCATENATE(IF(EXACT($F20, ""), ", null", CONCATENATE(", ", $F20, "")), "::bigint"), CONCATENATE(IF(EXACT($H20, ""), ", null", CONCATENATE(", ", $H20, "")), "::bigint"), CONCATENATE(IF(EXACT($J20, ""), ", null", CONCATENATE(", '", $J20, "'")), "::varchar"), CONCATENATE(IF(EXACT($K20, ""), ", null", CONCATENATE(", '", $K20, "'")), "::timestamptz"), CONCATENATE(IF(EXACT($L20, ""), ", null", CONCATENATE(", '", $L20, "'")), "::timestamptz"), CONCATENATE(IF(EXACT($M20, ""), ", null", CONCATENATE(", ", $M20, "")), "::bigint"), ");") -> PERFORM "SchData-OLTP-HumanResource"."Func_TblWorkerCareerInternal_SET"(varSystemLoginSession, null::bigint, null::varchar, null::timestamptz, '9999-12-31 23:59:59+07'::timestamptz, null::varchar, varInstitutionBranchID, varBaseCurrencyID, 32000000000017::bigint, 163000000000002::bigint, 111000000000006::bigint, 160000000000006::bigint, 'HRD Manager'::varchar, null::timestamptz, '9999-12-31 23:59:59+07'::timestamptz, null::bigint);
B21: =IF(EXACT(DataLookUp!$B21, ""), "", DataLookUp!$B21) -> 32000000000018 | C21: =MAIN!C21 -> Ahmad Faza | D21: 163000000000003 | E21: =IF(EXACT($D21, ""), "", VLOOKUP($D21, [2]DataLookUp!$B$4:$D$15, 2, FALSE )) -> Karyawan Tidak Tetap (Kontrak) | G21: =IF(EXACT($F21, ""), "", VLOOKUP($F21, 'MAIN - OrgDepartment'!$C$3:$D$104, 2, FALSE)) | I21: =IF(EXACT($H21, ""), "", VLOOKUP($H21, 'MAIN - OrgJobsPos'!$B$2:$C$101, 2, FALSE)) | L21: 1900-12-31 23:59:59+07 | O21: =O20 + IF(EXACT(P21, ""), 0, 1) -> 164000000000018 | P21: =CONCATENATE("PERFORM ""SchData-OLTP-HumanResource"".""Func_TblWorkerCareerInternal_SET""(varSystemLoginSession, null::bigint, null::varchar", CONCATENATE(IF(EXACT($K21, ""), ", null", CONCATENATE(", '", $K21, "'")), "::timestamptz"), CONCATENATE(IF(EXACT($L21, ""), ", null", CONCATENATE(", '", $L21, "'")), "::timestamptz"), ", null::varchar, varInstitutionBranchID, varBaseCurrencyID", CONCATENATE(IF(EXACT($B21, ""), ", null", CONCATENATE(", ", $B21, "")), "::bigint"), CONCATENATE(IF(EXACT($D21, ""), ", null", CONCATENATE(", ", $D21, "")), "::bigint"), CONCATENATE(IF(EXACT($F21, ""), ", null", CONCATENATE(", ", $F21, "")), "::bigint"), CONCATENATE(IF(EXACT($H21, ""), ", null", CONCATENATE(", ", $H21, "")), "::bigint"), CONCATENATE(IF(EXACT($J21, ""), ", null", CONCATENATE(", '", $J21, "'")), "::varchar"), CONCATENATE(IF(EXACT($K21, ""), ", null", CONCATENATE(", '", $K21, "'")), "::timestamptz"), CONCATENATE(IF(EXACT($L21, ""), ", null", CONCATENATE(", '", $L21, "'")), "::timestamptz"), CONCATENATE(IF(EXACT($M21, ""), ", null", CONCATENATE(", ", $M21, "")), "::bigint"), ");") -> PERFORM "SchData-OLTP-HumanResource"."Func_TblWorkerCareerInternal_SET"(varSystemLoginSession, null::bigint, null::varchar, null::timestamptz, '1900-12-31 23:59:59+07'::timestamptz, null::varchar, varInstitutionBranchID, varBaseCurrencyID, 32000000000018::bigint, 163000000000003::bigint, null::bigint, null::bigint, null::varchar, null::timestamptz, '1900-12-31 23:59:59+07'::timestamptz, null::bigint);
B22: =IF(EXACT(DataLookUp!$B22, ""), "", DataLookUp!$B22) -> 32000000000019 | C22: =MAIN!C22 -> Ahmad Syaifulloh | D22: 163000000000003 | E22: =IF(EXACT($D22, ""), "", VLOOKUP($D22, [2]DataLookUp!$B$4:$D$15, 2, FALSE )) -> Karyawan Tidak Tetap (Kontrak) | G22: =IF(EXACT($F22, ""), "", VLOOKUP($F22, 'MAIN - OrgDepartment'!$C$3:$D$104, 2, FALSE)) | I22: =IF(EXACT($H22, ""), "", VLOOKUP($H22, 'MAIN - OrgJobsPos'!$B$2:$C$101, 2, FALSE)) | L22: 1900-12-31 23:59:59+07 | O22: =O21 + IF(EXACT(P22, ""), 0, 1) -> 164000000000019 | P22: =CONCATENATE("PERFORM ""SchData-OLTP-HumanResource"".""Func_TblWorkerCareerInternal_SET""(varSystemLoginSession, null::bigint, null::varchar", CONCATENATE(IF(EXACT($K22, ""), ", null", CONCATENATE(", '", $K22, "'")), "::timestamptz"), CONCATENATE(IF(EXACT($L22, ""), ", null", CONCATENATE(", '", $L22, "'")), "::timestamptz"), ", null::varchar, varInstitutionBranchID, varBaseCurrencyID", CONCATENATE(IF(EXACT($B22, ""), ", null", CONCATENATE(", ", $B22, "")), "::bigint"), CONCATENATE(IF(EXACT($D22, ""), ", null", CONCATENATE(", ", $D22, "")), "::bigint"), CONCATENATE(IF(EXACT($F22, ""), ", null", CONCATENATE(", ", $F22, "")), "::bigint"), CONCATENATE(IF(EXACT($H22, ""), ", null", CONCATENATE(", ", $H22, "")), "::bigint"), CONCATENATE(IF(EXACT($J22, ""), ", null", CONCATENATE(", '", $J22, "'")), "::varchar"), CONCATENATE(IF(EXACT($K22, ""), ", null", CONCATENATE(", '", $K22, "'")), "::timestamptz"), CONCATENATE(IF(EXACT($L22, ""), ", null", CONCATENATE(", '", $L22, "'")), "::timestamptz"), CONCATENATE(IF(EXACT($M22, ""), ", null", CONCATENATE(", ", $M22, "")), "::bigint"), ");") -> PERFORM "SchData-OLTP-HumanResource"."Func_TblWorkerCareerInternal_SET"(varSystemLoginSession, null::bigint, null::varchar, null::timestamptz, '1900-12-31 23:59:59+07'::timestamptz, null::varchar, varInstitutionBranchID, varBaseCurrencyID, 32000000000019::bigint, 163000000000003::bigint, null::bigint, null::bigint, null::varchar, null::timestamptz, '1900-12-31 23:59:59+07'::timestamptz, null::bigint);
B23: =IF(EXACT(DataLookUp!$B23, ""), "", DataLookUp!$B23) -> 32000000000020 | C23: =MAIN!C23 -> Ahmad Zulkarnaen | D23: 163000000000003 | E23: =IF(EXACT($D23, ""), "", VLOOKUP($D23, [2]DataLookUp!$B$4:$D$15, 2, FALSE )) -> Karyawan Tidak Tetap (Kontrak) | G23: =IF(EXACT($F23, ""), "", VLOOKUP($F23, 'MAIN - OrgDepartment'!$C$3:$D$104, 2, FALSE)) | I23: =IF(EXACT($H23, ""), "", VLOOKUP($H23, 'MAIN - OrgJobsPos'!$B$2:$C$101, 2, FALSE)) | L23: 1900-12-31 23:59:59+07 | O23: =O22 + IF(EXACT(P23, ""), 0, 1) -> 164000000000020 | P23: =CONCATENATE("PERFORM ""SchData-OLTP-HumanResource"".""Func_TblWorkerCareerInternal_SET""(varSystemLoginSession, null::bigint, null::varchar", CONCATENATE(IF(EXACT($K23, ""), ", null", CONCATENATE(", '", $K23, "'")), "::timestamptz"), CONCATENATE(IF(EXACT($L23, ""), ", null", CONCATENATE(", '", $L23, "'")), "::timestamptz"), ", null::varchar, varInstitutionBranchID, varBaseCurrencyID", CONCATENATE(IF(EXACT($B23, ""), ", null", CONCATENATE(", ", $B23, "")), "::bigint"), CONCATENATE(IF(EXACT($D23, ""), ", null", CONCATENATE(", ", $D23, "")), "::bigint"), CONCATENATE(IF(EXACT($F23, ""), ", null", CONCATENATE(", ", $F23, "")), "::bigint"), CONCATENATE(IF(EXACT($H23, ""), ", null", CONCATENATE(", ", $H23, "")), "::bigint"), CONCATENATE(IF(EXACT($J23, ""), ", null", CONCATENATE(", '", $J23, "'")), "::varchar"), CONCATENATE(IF(EXACT($K23, ""), ", null", CONCATENATE(", '", $K23, "'")), "::timestamptz"), CONCATENATE(IF(EXACT($L23, ""), ", null", CONCATENATE(", '", $L23, "'")), "::timestamptz"), CONCATENATE(IF(EXACT($M23, ""), ", null", CONCATENATE(", ", $M23, "")), "::bigint"), ");") -> PERFORM "SchData-OLTP-HumanResource"."Func_TblWorkerCareerInternal_SET"(varSystemLoginSession, null::bigint, null::varchar, null::timestamptz, '1900-12-31 23:59:59+07'::timestamptz, null::varchar, varInstitutionBranchID, varBaseCurrencyID, 32000000000020::bigint, 163000000000003::bigint, null::bigint, null::bigint, null::varchar, null::timestamptz, '1900-12-31 23:59:59+07'::timestamptz, null::bigint);
B24: =IF(EXACT(DataLookUp!$B24, ""), "", DataLookUp!$B24) -> 32000000000021 | C24: =MAIN!C24 -> Ajan | D24: 163000000000003 | E24: =IF(EXACT($D24, ""), "", VLOOKUP($D24, [2]DataLookUp!$B$4:$D$15, 2, FALSE )) -> Karyawan Tidak Tetap (Kontrak) | G24: =IF(EXACT($F24, ""), "", VLOOKUP($F24, 'MAIN - OrgDepartment'!$C$3:$D$104, 2, FALSE)) | I24: =IF(EXACT($H24, ""), "", VLOOKUP($H24, 'MAIN - OrgJobsPos'!$B$2:$C$101, 2, FALSE)) | L24: 1900-12-31 23:59:59+07 | O24: =O23 + IF(EXACT(P24, ""), 0, 1) -> 164000000000021 | P24: =CONCATENATE("PERFORM ""SchData-OLTP-HumanResource"".""Func_TblWorkerCareerInternal_SET""(varSystemLoginSession, null::bigint, null::varchar", CONCATENATE(IF(EXACT($K24, ""), ", null", CONCATENATE(", '", $K24, "'")), "::timestamptz"), CONCATENATE(IF(EXACT($L24, ""), ", null", CONCATENATE(", '", $L24, "'")), "::timestamptz"), ", null::varchar, varInstitutionBranchID, varBaseCurrencyID", CONCATENATE(IF(EXACT($B24, ""), ", null", CONCATENATE(", ", $B24, "")), "::bigint"), CONCATENATE(IF(EXACT($D24, ""), ", null", CONCATENATE(", ", $D24, "")), "::bigint"), CONCATENATE(IF(EXACT($F24, ""), ", null", CONCATENATE(", ", $F24, "")), "::bigint"), CONCATENATE(IF(EXACT($H24, ""), ", null", CONCATENATE(", ", $H24, "")), "::bigint"), CONCATENATE(IF(EXACT($J24, ""), ", null", CONCATENATE(", '", $J24, "'")), "::varchar"), CONCATENATE(IF(EXACT($K24, ""), ", null", CONCATENATE(", '", $K24, "'")), "::timestamptz"), CONCATENATE(IF(EXACT($L24, ""), ", null", CONCATENATE(", '", $L24, "'")), "::timestamptz"), CONCATENATE(IF(EXACT($M24, ""), ", null", CONCATENATE(", ", $M24, "")), "::bigint"), ");") -> PERFORM "SchData-OLTP-HumanResource"."Func_TblWorkerCareerInternal_SET"(varSystemLoginSession, null::bigint, null::varchar, null::timestamptz, '1900-12-31 23:59:59+07'::timestamptz, null::varchar, varInstitutionBranchID, varBaseCurrencyID, 32000000000021::bigint, 163000000000003::bigint, null::bigint, null::bigint, null::varchar, null::timestamptz, '1900-12-31 23:59:59+07'::timestamptz, null::bigint);
B25: =IF(EXACT(DataLookUp!$B25, ""), "", DataLookUp!$B25) -> 32000000000022 | C25: =MAIN!C25 -> Al Amin | D25: 163000000000003 | E25: =IF(EXACT($D25, ""), "", VLOOKUP($D25, [2]DataLookUp!$B$4:$D$15, 2, FALSE )) -> Karyawan Tidak Tetap (Kontrak) | G25: =IF(EXACT($F25, ""), "", VLOOKUP($F25, 'MAIN - OrgDepartment'!$C$3:$D$104, 2, FALSE)) | I25: =IF(EXACT($H25, ""), "", VLOOKUP($H25, 'MAIN - OrgJobsPos'!$B$2:$C$101, 2, FALSE)) | L25: 1900-12-31 23:59:59+07 | O25: =O24 + IF(EXACT(P25, ""), 0, 1) -> 164000000000022 | P25: =CONCATENATE("PERFORM ""SchData-OLTP-HumanResource"".""Func_TblWorkerCareerInternal_SET""(varSystemLoginSession, null::bigint, null::varchar", CONCATENATE(IF(EXACT($K25, ""), ", null", CONCATENATE(", '", $K25, "'")), "::timestamptz"), CONCATENATE(IF(EXACT($L25, ""), ", null", CONCATENATE(", '", $L25, "'")), "::timestamptz"), ", null::varchar, varInstitutionBranchID, varBaseCurrencyID", CONCATENATE(IF(EXACT($B25, ""), ", null", CONCATENATE(", ", $B25, "")), "::bigint"), CONCATENATE(IF(EXACT($D25, ""), ", null", CONCATENATE(", ", $D25, "")), "::bigint"), CONCATENATE(IF(EXACT($F25, ""), ", null", CONCATENATE(", ", $F25, "")), "::bigint"), CONCATENATE(IF(EXACT($H25, ""), ", null", CONCATENATE(", ", $H25, "")), "::bigint"), CONCATENATE(IF(EXACT($J25, ""), ", null", CONCATENATE(", '", $J25, "'")), "::varchar"), CONCATENATE(IF(EXACT($K25, ""), ", null", CONCATENATE(", '", $K25, "'")), "::timestamptz"), CONCATENATE(IF(EXACT($L25, ""), ", null", CONCATENATE(", '", $L25, "'")), "::timestamptz"), CONCATENATE(IF(EXACT($M25, ""), ", null", CONCATENATE(", ", $M25, "")), "::bigint"), ");") -> PERFORM "SchData-OLTP-HumanResource"."Func_TblWorkerCareerInternal_SET"(varSystemLoginSession, null::bigint, null::varchar, null::timestamptz, '1900-12-31 23:59:59+07'::timestamptz, null::varchar, varInstitutionBranchID, varBaseCurrencyID, 32000000000022::bigint, 163000000000003::bigint, null::bigint, null::bigint, null::varchar, null::timestamptz, '1900-12-31 23:59:59+07'::timestamptz, null::bigint);
B26: =IF(EXACT(DataLookUp!$B26, ""), "", DataLookUp!$B26) -> 32000000000023 | C26: =MAIN!C26 -> Aldi Mulyadi | D26: 163000000000003 | E26: =IF(EXACT($D26, ""), "", VLOOKUP($D26, [2]DataLookUp!$B$4:$D$15, 2, FALSE )) -> Karyawan Tidak Tetap (Kontrak) | F26: 111000000000003 | G26: =IF(EXACT($F26, ""), "", VLOOKUP($F26, 'MAIN - OrgDepartment'!$C$3:$D$104, 2, FALSE)) -> Information Technology | H26: 160000000000003 | I26: =IF(EXACT($H26, ""), "", VLOOKUP($H26, 'MAIN - OrgJobsPos'!$B$2:$C$101, 2, FALSE)) -> Staff | L26: 2024-06-14 23:59:59+07 | O26: =O25 + IF(EXACT(P26, ""), 0, 1) -> 164000000000023 | P26: =CONCATENATE("PERFORM ""SchData-OLTP-HumanResource"".""Func_TblWorkerCareerInternal_SET""(varSystemLoginSession, null::bigint, null::varchar", CONCATENATE(IF(EXACT($K26, ""), ", null", CONCATENATE(", '", $K26, "'")), "::timestamptz"), CONCATENATE(IF(EXACT($L26, ""), ", null", CONCATENATE(", '", $L26, "'")), "::timestamptz"), ", null::varchar, varInstitutionBranchID, varBaseCurrencyID", CONCATENATE(IF(EXACT($B26, ""), ", null", CONCATENATE(", ", $B26, "")), "::bigint"), CONCATENATE(IF(EXACT($D26, ""), ", null", CONCATENATE(", ", $D26, "")), "::bigint"), CONCATENATE(IF(EXACT($F26, ""), ", null", CONCATENATE(", ", $F26, "")), "::bigint"), CONCATENATE(IF(EXACT($H26, ""), ", null", CONCATENATE(", ", $H26, "")), "::bigint"), CONCATENATE(IF(EXACT($J26, ""), ", null", CONCATENATE(", '", $J26, "'")), "::varchar"), CONCATENATE(IF(EXACT($K26, ""), ", null", CONCATENATE(", '", $K26, "'")), "::timestamptz"), CONCATENATE(IF(EXACT($L26, ""), ", null", CONCATENATE(", '", $L26, "'")), "::timestamptz"), CONCATENATE(IF(EXACT($M26, ""), ", null", CONCATENATE(", ", $M26, "")), "::bigint"), ");") -> PERFORM "SchData-OLTP-HumanResource"."Func_TblWorkerCareerInternal_SET"(varSystemLoginSession, null::bigint, null::varchar, null::timestamptz, '2024-06-14 23:59:59+07'::timestamptz, null::varchar, varInstitutionBranchID, varBaseCurrencyID, 32000000000023::bigint, 163000000000003::bigint, 111000000000003::bigint, 160000000000003::bigint, null::varchar, null::timestamptz, '2024-06-14 23:59:59+07'::timestamptz, null::bigint);
B27: =IF(EXACT(DataLookUp!$B27, ""), "", DataLookUp!$B27) -> 32000000000024 | C27: =MAIN!C27 -> Alexandri | D27: 163000000000003 | E27: =IF(EXACT($D27, ""), "", VLOOKUP($D27, [2]DataLookUp!$B$4:$D$15, 2, FALSE )) -> Karyawan Tidak Tetap (Kontrak) | G27: =IF(EXACT($F27, ""), "", VLOOKUP($F27, 'MAIN - OrgDepartment'!$C$3:$D$104, 2, FALSE)) | I27: =IF(EXACT($H27, ""), "", VLOOKUP($H27, 'MAIN - OrgJobsPos'!$B$2:$C$101, 2, FALSE)) | L27: 1900-12-31 23:59:59+07 | O27: =O26 + IF(EXACT(P27, ""), 0, 1) -> 164000000000024 | P27: =CONCATENATE("PERFORM ""SchData-OLTP-HumanResource"".""Func_TblWorkerCareerInternal_SET""(varSystemLoginSession, null::bigint, null::varchar", CONCATENATE(IF(EXACT($K27, ""), ", null", CONCATENATE(", '", $K27, "'")), "::timestamptz"), CONCATENATE(IF(EXACT($L27, ""), ", null", CONCATENATE(", '", $L27, "'")), "::timestamptz"), ", null::varchar, varInstitutionBranchID, varBaseCurrencyID", CONCATENATE(IF(EXACT($B27, ""), ", null", CONCATENATE(", ", $B27, "")), "::bigint"), CONCATENATE(IF(EXACT($D27, ""), ", null", CONCATENATE(", ", $D27, "")), "::bigint"), CONCATENATE(IF(EXACT($F27, ""), ", null", CONCATENATE(", ", $F27, "")), "::bigint"), CONCATENATE(IF(EXACT($H27, ""), ", null", CONCATENATE(", ", $H27, "")), "::bigint"), CONCATENATE(IF(EXACT($J27, ""), ", null", CONCATENATE(", '", $J27, "'")), "::varchar"), CONCATENATE(IF(EXACT($K27, ""), ", null", CONCATENATE(", '", $K27, "'")), "::timestamptz"), CONCATENATE(IF(EXACT($L27, ""), ", null", CONCATENATE(", '", $L27, "'")), "::timestamptz"), CONCATENATE(IF(EXACT($M27, ""), ", null", CONCATENATE(", ", $M27, "")), "::bigint"), ");") -> PERFORM "SchData-OLTP-HumanResource"."Func_TblWorkerCareerInternal_SET"(varSystemLoginSession, null::bigint, null::varchar, null::timestamptz, '1900-12-31 23:59:59+07'::timestamptz, null::varchar, varInstitutionBranchID, varBaseCurrencyID, 32000000000024::bigint, 163000000000003::bigint, null::bigint, null::bigint, null::varchar, null::timestamptz, '1900-12-31 23:59:59+07'::timestamptz, null::bigint);
B28: =IF(EXACT(DataLookUp!$B28, ""), "", DataLookUp!$B28) -> 32000000000025 | C28: =MAIN!C28 -> Alfaedi | D28: 163000000000003 | E28: =IF(EXACT($D28, ""), "", VLOOKUP($D28, [2]DataLookUp!$B$4:$D$15, 2, FALSE )) -> Karyawan Tidak Tetap (Kontrak) | G28: =IF(EXACT($F28, ""), "", VLOOKUP($F28, 'MAIN - OrgDepartment'!$C$3:$D$104, 2, FALSE)) | I28: =IF(EXACT($H28, ""), "", VLOOKUP($H28, 'MAIN - OrgJobsPos'!$B$2:$C$101, 2, FALSE)) | L28: 1900-12-31 23:59:59+07 | O28: =O27 + IF(EXACT(P28, ""), 0, 1) -> 164000000000025 | P28: =CONCATENATE("PERFORM ""SchData-OLTP-HumanResource"".""Func_TblWorkerCareerInternal_SET""(varSystemLoginSession, null::bigint, null::varchar", CONCATENATE(IF(EXACT($K28, ""), ", null", CONCATENATE(", '", $K28, "'")), "::timestamptz"), CONCATENATE(IF(EXACT($L28, ""), ", null", CONCATENATE(", '", $L28, "'")), "::timestamptz"), ", null::varchar, varInstitutionBranchID, varBaseCurrencyID", CONCATENATE(IF(EXACT($B28, ""), ", null", CONCATENATE(", ", $B28, "")), "::bigint"), CONCATENATE(IF(EXACT($D28, ""), ", null", CONCATENATE(", ", $D28, "")), "::bigint"), CONCATENATE(IF(EXACT($F28, ""), ", null", CONCATENATE(", ", $F28, "")), "::bigint"), CONCATENATE(IF(EXACT($H28, ""), ", null", CONCATENATE(", ", $H28, "")), "::bigint"), CONCATENATE(IF(EXACT($J28, ""), ", null", CONCATENATE(", '", $J28, "'")), "::varchar"), CONCATENATE(IF(EXACT($K28, ""), ", null", CONCATENATE(", '", $K28, "'")), "::timestamptz"), CONCATENATE(IF(EXACT($L28, ""), ", null", CONCATENATE(", '", $L28, "'")), "::timestamptz"), CONCATENATE(IF(EXACT($M28, ""), ", null", CONCATENATE(", ", $M28, "")), "::bigint"), ");") -> PERFORM "SchData-OLTP-HumanResource"."Func_TblWorkerCareerInternal_SET"(varSystemLoginSession, null::bigint, null::varchar, null::timestamptz, '1900-12-31 23:59:59+07'::timestamptz, null::varchar, varInstitutionBranchID, varBaseCurrencyID, 32000000000025::bigint, 163000000000003::bigint, null::bigint, null::bigint, null::varchar, null::timestamptz, '1900-12-31 23:59:59+07'::timestamptz, null::bigint);
B29: =IF(EXACT(DataLookUp!$B29, ""), "", DataLookUp!$B29) -> 32000000000026 | C29: =MAIN!C29 -> Ali Wahono | D29: 163000000000003 | E29: =IF(EXACT($D29, ""), "", VLOOKUP($D29, [2]DataLookUp!$B$4:$D$15, 2, FALSE )) -> Karyawan Tidak Tetap (Kontrak) | G29: =IF(EXACT($F29, ""), "", VLOOKUP($F29, 'MAIN - OrgDepartment'!$C$3:$D$104, 2, FALSE)) | I29: =IF(EXACT($H29, ""), "", VLOOKUP($H29, 'MAIN - OrgJobsPos'!$B$2:$C$101, 2, FALSE)) | L29: 1900-12-31 23:59:59+07 | O29: =O28 + IF(EXACT(P29, ""), 0, 1) -> 164000000000026 | P29: =CONCATENATE("PERFORM ""SchData-OLTP-HumanResource"".""Func_TblWorkerCareerInternal_SET""(varSystemLoginSession, null::bigint, null::varchar", CONCATENATE(IF(EXACT($K29, ""), ", null", CONCATENATE(", '", $K29, "'")), "::timestamptz"), CONCATENATE(IF(EXACT($L29, ""), ", null", CONCATENATE(", '", $L29, "'")), "::timestamptz"), ", null::varchar, varInstitutionBranchID, varBaseCurrencyID", CONCATENATE(IF(EXACT($B29, ""), ", null", CONCATENATE(", ", $B29, "")), "::bigint"), CONCATENATE(IF(EXACT($D29, ""), ", null", CONCATENATE(", ", $D29, "")), "::bigint"), CONCATENATE(IF(EXACT($F29, ""), ", null", CONCATENATE(", ", $F29, "")), "::bigint"), CONCATENATE(IF(EXACT($H29, ""), ", null", CONCATENATE(", ", $H29, "")), "::bigint"), CONCATENATE(IF(EXACT($J29, ""), ", null", CONCATENATE(", '", $J29, "'")), "::varchar"), CONCATENATE(IF(EXACT($K29, ""), ", null", CONCATENATE(", '", $K29, "'")), "::timestamptz"), CONCATENATE(IF(EXACT($L29, ""), ", null", CONCATENATE(", '", $L29, "'")), "::timestamptz"), CONCATENATE(IF(EXACT($M29, ""), ", null", CONCATENATE(", ", $M29, "")), "::bigint"), ");") -> PERFORM "SchData-OLTP-HumanResource"."Func_TblWorkerCareerInternal_SET"(varSystemLoginSession, null::bigint, null::varchar, null::timestamptz, '1900-12-31 23:59:59+07'::timestamptz, null::varchar, varInstitutionBranchID, varBaseCurrencyID, 32000000000026::bigint, 163000000000003::bigint, null::bigint, null::bigint, null::varchar, null::timestamptz, '1900-12-31 23:59:59+07'::timestamptz, null::bigint);
B30: =IF(EXACT(DataLookUp!$B30, ""), "", DataLookUp!$B30) -> 32000000000027 | C30: =MAIN!C30 -> Alphaliyanri Lasria | D30: 163000000000003 | E30: =IF(EXACT($D30, ""), "", VLOOKUP($D30, [2]DataLookUp!$B$4:$D$15, 2, FALSE )) -> Karyawan Tidak Tetap (Kontrak) | G30: =IF(EXACT($F30, ""), "", VLOOKUP($F30, 'MAIN - OrgDepartment'!$C$3:$D$104, 2, FALSE)) | I30: =IF(EXACT($H30, ""), "", VLOOKUP($H30, 'MAIN - OrgJobsPos'!$B$2:$C$101, 2, FALSE)) | L30: 1900-12-31 23:59:59+07 | O30: =O29 + IF(EXACT(P30, ""), 0, 1) -> 164000000000027 | P30: =CONCATENATE("PERFORM ""SchData-OLTP-HumanResource"".""Func_TblWorkerCareerInternal_SET""(varSystemLoginSession, null::bigint, null::varchar", CONCATENATE(IF(EXACT($K30, ""), ", null", CONCATENATE(", '", $K30, "'")), "::timestamptz"), CONCATENATE(IF(EXACT($L30, ""), ", null", CONCATENATE(", '", $L30, "'")), "::timestamptz"), ", null::varchar, varInstitutionBranchID, varBaseCurrencyID", CONCATENATE(IF(EXACT($B30, ""), ", null", CONCATENATE(", ", $B30, "")), "::bigint"), CONCATENATE(IF(EXACT($D30, ""), ", null", CONCATENATE(", ", $D30, "")), "::bigint"), CONCATENATE(IF(EXACT($F30, ""), ", null", CONCATENATE(", ", $F30, "")), "::bigint"), CONCATENATE(IF(EXACT($H30, ""), ", null", CONCATENATE(", ", $H30, "")), "::bigint"), CONCATENATE(IF(EXACT($J30, ""), ", null", CONCATENATE(", '", $J30, "'")), "::varchar"), CONCATENATE(IF(EXACT($K30, ""), ", null", CONCATENATE(", '", $K30, "'")), "::timestamptz"), CONCATENATE(IF(EXACT($L30, ""), ", null", CONCATENATE(", '", $L30, "'")), "::timestamptz"), CONCATENATE(IF(EXACT($M30, ""), ", null", CONCATENATE(", ", $M30, "")), "::bigint"), ");") -> PERFORM "SchData-OLTP-HumanResource"."Func_TblWorkerCareerInternal_SET"(varSystemLoginSession, null::bigint, null::varchar, null::timestamptz, '1900-12-31 23:59:59+07'::timestamptz, null::varchar, varInstitutionBranchID, varBaseCurrencyID, 32000000000027::bigint, 163000000000003::bigint, null::bigint, null::bigint, null::varchar, null::timestamptz, '1900-12-31 23:59:59+07'::timestamptz, null::bigint);
B31: =IF(EXACT(DataLookUp!$B31, ""), "", DataLookUp!$B31) -> 32000000000028 | C31: =MAIN!C31 -> Ambon Rumalean | D31: 163000000000003 | E31: =IF(EXACT($D31, ""), "", VLOOKUP($D31, [2]DataLookUp!$B$4:$D$15, 2, FALSE )) -> Karyawan Tidak Tetap (Kontrak) | G31: =IF(EXACT($F31, ""), "", VLOOKUP($F31, 'MAIN - OrgDepartment'!$C$3:$D$104, 2, FALSE)) | I31: =IF(EXACT($H31, ""), "", VLOOKUP($H31, 'MAIN - OrgJobsPos'!$B$2:$C$101, 2, FALSE)) | L31: 1900-12-31 23:59:59+07 | O31: =O30 + IF(EXACT(P31, ""), 0, 1) -> 164000000000028 | P31: =CONCATENATE("PERFORM ""SchData-OLTP-HumanResource"".""Func_TblWorkerCareerInternal_SET""(varSystemLoginSession, null::bigint, null::varchar", CONCATENATE(IF(EXACT($K31, ""), ", null", CONCATENATE(", '", $K31, "'")), "::timestamptz"), CONCATENATE(IF(EXACT($L31, ""), ", null", CONCATENATE(", '", $L31, "'")), "::timestamptz"), ", null::varchar, varInstitutionBranchID, varBaseCurrencyID", CONCATENATE(IF(EXACT($B31, ""), ", null", CONCATENATE(", ", $B31, "")), "::bigint"), CONCATENATE(IF(EXACT($D31, ""), ", null", CONCATENATE(", ", $D31, "")), "::bigint"), CONCATENATE(IF(EXACT($F31, ""), ", null", CONCATENATE(", ", $F31, "")), "::bigint"), CONCATENATE(IF(EXACT($H31, ""), ", null", CONCATENATE(", ", $H31, "")), "::bigint"), CONCATENATE(IF(EXACT($J31, ""), ", null", CONCATENATE(", '", $J31, "'")), "::varchar"), CONCATENATE(IF(EXACT($K31, ""), ", null", CONCATENATE(", '", $K31, "'")), "::timestamptz"), CONCATENATE(IF(EXACT($L31, ""), ", null", CONCATENATE(", '", $L31, "'")), "::timestamptz"), CONCATENATE(IF(EXACT($M31, ""), ", null", CONCATENATE(", ", $M31, "")), "::bigint"), ");") -> PERFORM "SchData-OLTP-HumanResource"."Func_TblWorkerCareerInternal_SET"(varSystemLoginSession, null::bigint, null::varchar, null::timestamptz, '1900-12-31 23:59:59+07'::timestamptz, null::varchar, varInstitutionBranchID, varBaseCurrencyID, 32000000000028::bigint, 163000000000003::bigint, null::bigint, null::bigint, null::varchar, null::timestamptz, '1900-12-31 23:59:59+07'::timestamptz, null::bigint);
B32: =IF(EXACT(DataLookUp!$B32, ""), "", DataLookUp!$B32) -> 32000000000029 | C32: =MAIN!C32 -> Amir Sofyan Hadi | D32: 163000000000003 | E32: =IF(EXACT($D32, ""), "", VLOOKUP($D32, [2]DataLookUp!$B$4:$D$15, 2, FALSE )) -> Karyawan Tidak Tetap (Kontrak) | G32: =IF(EXACT($F32, ""), "", VLOOKUP($F32, 'MAIN - OrgDepartment'!$C$3:$D$104, 2, FALSE)) | I32: =IF(EXACT($H32, ""), "", VLOOKUP($H32, 'MAIN - OrgJobsPos'!$B$2:$C$101, 2, FALSE)) | L32: 1900-12-31 23:59:59+07 | O32: =O31 + IF(EXACT(P32, ""), 0, 1) -> 164000000000029 | P32: =CONCATENATE("PERFORM ""SchData-OLTP-HumanResource"".""Func_TblWorkerCareerInternal_SET""(varSystemLoginSession, null::bigint, null::varchar", CONCATENATE(IF(EXACT($K32, ""), ", null", CONCATENATE(", '", $K32, "'")), "::timestamptz"), CONCATENATE(IF(EXACT($L32, ""), ", null", CONCATENATE(", '", $L32, "'")), "::timestamptz"), ", null::varchar, varInstitutionBranchID, varBaseCurrencyID", CONCATENATE(IF(EXACT($B32, ""), ", null", CONCATENATE(", ", $B32, "")), "::bigint"), CONCATENATE(IF(EXACT($D32, ""), ", null", CONCATENATE(", ", $D32, "")), "::bigint"), CONCATENATE(IF(EXACT($F32, ""), ", null", CONCATENATE(", ", $F32, "")), "::bigint"), CONCATENATE(IF(EXACT($H32, ""), ", null", CONCATENATE(", ", $H32, "")), "::bigint"), CONCATENATE(IF(EXACT($J32, ""), ", null", CONCATENATE(", '", $J32, "'")), "::varchar"), CONCATENATE(IF(EXACT($K32, ""), ", null", CONCATENATE(", '", $K32, "'")), "::timestamptz"), CONCATENATE(IF(EXACT($L32, ""), ", null", CONCATENATE(", '", $L32, "'")), "::timestamptz"), CONCATENATE(IF(EXACT($M32, ""), ", null", CONCATENATE(", ", $M32, "")), "::bigint"), ");") -> PERFORM "SchData-OLTP-HumanResource"."Func_TblWorkerCareerInternal_SET"(varSystemLoginSession, null::bigint, null::varchar, null::timestamptz, '1900-12-31 23:59:59+07'::timestamptz, null::varchar, varInstitutionBranchID, varBaseCurrencyID, 32000000000029::bigint, 163000000000003::bigint, null::bigint, null::bigint, null::varchar, null::timestamptz, '1900-12-31 23:59:59+07'::timestamptz, null::bigint);
B33: =IF(EXACT(DataLookUp!$B33, ""), "", DataLookUp!$B33) -> 32000000000030 | C33: =MAIN!C33 -> Anak Agung Netti Ariani | D33: 163000000000003 | E33: =IF(EXACT($D33, ""), "", VLOOKUP($D33, [2]DataLookUp!$B$4:$D$15, 2, FALSE )) -> Karyawan Tidak Tetap (Kontrak) | G33: =IF(EXACT($F33, ""), "", VLOOKUP($F33, 'MAIN - OrgDepartment'!$C$3:$D$104, 2, FALSE)) | I33: =IF(EXACT($H33, ""), "", VLOOKUP($H33, 'MAIN - OrgJobsPos'!$B$2:$C$101, 2, FALSE)) | L33: 1900-12-31 23:59:59+07 | O33: =O32 + IF(EXACT(P33, ""), 0, 1) -> 164000000000030 | P33: =CONCATENATE("PERFORM ""SchData-OLTP-HumanResource"".""Func_TblWorkerCareerInternal_SET""(varSystemLoginSession, null::bigint, null::varchar", CONCATENATE(IF(EXACT($K33, ""), ", null", CONCATENATE(", '", $K33, "'")), "::timestamptz"), CONCATENATE(IF(EXACT($L33, ""), ", null", CONCATENATE(", '", $L33, "'")), "::timestamptz"), ", null::varchar, varInstitutionBranchID, varBaseCurrencyID", CONCATENATE(IF(EXACT($B33, ""), ", null", CONCATENATE(", ", $B33, "")), "::bigint"), CONCATENATE(IF(EXACT($D33, ""), ", null", CONCATENATE(", ", $D33, "")), "::bigint"), CONCATENATE(IF(EXACT($F33, ""), ", null", CONCATENATE(", ", $F33, "")), "::bigint"), CONCATENATE(IF(EXACT($H33, ""), ", null", CONCATENATE(", ", $H33, "")), "::bigint"), CONCATENATE(IF(EXACT($J33, ""), ", null", CONCATENATE(", '", $J33, "'")), "::varchar"), CONCATENATE(IF(EXACT($K33, ""), ", null", CONCATENATE(", '", $K33, "'")), "::timestamptz"), CONCATENATE(IF(EXACT($L33, ""), ", null", CONCATENATE(", '", $L33, "'")), "::timestamptz"), CONCATENATE(IF(EXACT($M33, ""), ", null", CONCATENATE(", ", $M33, "")), "::bigint"), ");") -> PERFORM "SchData-OLTP-HumanResource"."Func_TblWorkerCareerInternal_SET"(varSystemLoginSession, null::bigint, null::varchar, null::timestamptz, '1900-12-31 23:59:59+07'::timestamptz, null::varchar, varInstitutionBranchID, varBaseCurrencyID, 32000000000030::bigint, 163000000000003::bigint, null::bigint, null::bigint, null::varchar, null::timestamptz, '1900-12-31 23:59:59+07'::timestamptz, null::bigint);
B34: =IF(EXACT(DataLookUp!$B34, ""), "", DataLookUp!$B34) -> 32000000000031 | C34: =MAIN!C34 -> Andri Gunawan | D34: 163000000000003 | E34: =IF(EXACT($D34, ""), "", VLOOKUP($D34, [2]DataLookUp!$B$4:$D$15, 2, FALSE )) -> Karyawan Tidak Tetap (Kontrak) | G34: =IF(EXACT($F34, ""), "", VLOOKUP($F34, 'MAIN - OrgDepartment'!$C$3:$D$104, 2, FALSE)) | I34: =IF(EXACT($H34, ""), "", VLOOKUP($H34, 'MAIN - OrgJobsPos'!$B$2:$C$101, 2, FALSE)) | L34: 1900-12-31 23:59:59+07 | O34: =O33 + IF(EXACT(P34, ""), 0, 1) -> 164000000000031 | P34: =CONCATENATE("PERFORM ""SchData-OLTP-HumanResource"".""Func_TblWorkerCareerInternal_SET""(varSystemLoginSession, null::bigint, null::varchar", CONCATENATE(IF(EXACT($K34, ""), ", null", CONCATENATE(", '", $K34, "'")), "::timestamptz"), CONCATENATE(IF(EXACT($L34, ""), ", null", CONCATENATE(", '", $L34, "'")), "::timestamptz"), ", null::varchar, varInstitutionBranchID, varBaseCurrencyID", CONCATENATE(IF(EXACT($B34, ""), ", null", CONCATENATE(", ", $B34, "")), "::bigint"), CONCATENATE(IF(EXACT($D34, ""), ", null", CONCATENATE(", ", $D34, "")), "::bigint"), CONCATENATE(IF(EXACT($F34, ""), ", null", CONCATENATE(", ", $F34, "")), "::bigint"), CONCATENATE(IF(EXACT($H34, ""), ", null", CONCATENATE(", ", $H34, "")), "::bigint"), CONCATENATE(IF(EXACT($J34, ""), ", null", CONCATENATE(", '", $J34, "'")), "::varchar"), CONCATENATE(IF(EXACT($K34, ""), ", null", CONCATENATE(", '", $K34, "'")), "::timestamptz"), CONCATENATE(IF(EXACT($L34, ""), ", null", CONCATENATE(", '", $L34, "'")), "::timestamptz"), CONCATENATE(IF(EXACT($M34, ""), ", null", CONCATENATE(", ", $M34, "")), "::bigint"), ");") -> PERFORM "SchData-OLTP-HumanResource"."Func_TblWorkerCareerInternal_SET"(varSystemLoginSession, null::bigint, null::varchar, null::timestamptz, '1900-12-31 23:59:59+07'::timestamptz, null::varchar, varInstitutionBranchID, varBaseCurrencyID, 32000000000031::bigint, 163000000000003::bigint, null::bigint, null::bigint, null::varchar, null::timestamptz, '1900-12-31 23:59:59+07'::timestamptz, null::bigint);
B35: =IF(EXACT(DataLookUp!$B35, ""), "", DataLookUp!$B35) -> 32000000000032 | C35: =MAIN!C35 -> Andri Herdiansyah | D35: 163000000000003 | E35: =IF(EXACT($D35, ""), "", VLOOKUP($D35, [2]DataLookUp!$B$4:$D$15, 2, FALSE )) -> Karyawan Tidak Tetap (Kontrak) | G35: =IF(EXACT($F35, ""), "", VLOOKUP($F35, 'MAIN - OrgDepartment'!$C$3:$D$104, 2, FALSE)) | I35: =IF(EXACT($H35, ""), "", VLOOKUP($H35, 'MAIN - OrgJobsPos'!$B$2:$C$101, 2, FALSE)) | L35: 1900-12-31 23:59:59+07 | O35: =O34 + IF(EXACT(P35, ""), 0, 1) -> 164000000000032 | P35: =CONCATENATE("PERFORM ""SchData-OLTP-HumanResource"".""Func_TblWorkerCareerInternal_SET""(varSystemLoginSession, null::bigint, null::varchar", CONCATENATE(IF(EXACT($K35, ""), ", null", CONCATENATE(", '", $K35, "'")), "::timestamptz"), CONCATENATE(IF(EXACT($L35, ""), ", null", CONCATENATE(", '", $L35, "'")), "::timestamptz"), ", null::varchar, varInstitutionBranchID, varBaseCurrencyID", CONCATENATE(IF(EXACT($B35, ""), ", null", CONCATENATE(", ", $B35, "")), "::bigint"), CONCATENATE(IF(EXACT($D35, ""), ", null", CONCATENATE(", ", $D35, "")), "::bigint"), CONCATENATE(IF(EXACT($F35, ""), ", null", CONCATENATE(", ", $F35, "")), "::bigint"), CONCATENATE(IF(EXACT($H35, ""), ", null", CONCATENATE(", ", $H35, "")), "::bigint"), CONCATENATE(IF(EXACT($J35, ""), ", null", CONCATENATE(", '", $J35, "'")), "::varchar"), CONCATENATE(IF(EXACT($K35, ""), ", null", CONCATENATE(", '", $K35, "'")), "::timestamptz"), CONCATENATE(IF(EXACT($L35, ""), ", null", CONCATENATE(", '", $L35, "'")), "::timestamptz"), CONCATENATE(IF(EXACT($M35, ""), ", null", CONCATENATE(", ", $M35, "")), "::bigint"), ");") -> PERFORM "SchData-OLTP-HumanResource"."Func_TblWorkerCareerInternal_SET"(varSystemLoginSession, null::bigint, null::varchar, null::timestamptz, '1900-12-31 23:59:59+07'::timestamptz, null::varchar, varInstitutionBranchID, varBaseCurrencyID, 32000000000032::bigint, 163000000000003::bigint, null::bigint, null::bigint, null::varchar, null::timestamptz, '1900-12-31 23:59:59+07'::timestamptz, null::bigint);
B36: =IF(EXACT(DataLookUp!$B36, ""), "", DataLookUp!$B36) -> 32000000000033 | C36: =MAIN!C36 -> Andrie | D36: 163000000000003 | E36: =IF(EXACT($D36, ""), "", VLOOKUP($D36, [2]DataLookUp!$B$4:$D$15, 2, FALSE )) -> Karyawan Tidak Tetap (Kontrak) | G36: =IF(EXACT($F36, ""), "", VLOOKUP($F36, 'MAIN - OrgDepartment'!$C$3:$D$104, 2, FALSE)) | I36: =IF(EXACT($H36, ""), "", VLOOKUP($H36, 'MAIN - OrgJobsPos'!$B$2:$C$101, 2, FALSE)) | L36: 1900-12-31 23:59:59+07 | O36: =O35 + IF(EXACT(P36, ""), 0, 1) -> 164000000000033 | P36: =CONCATENATE("PERFORM ""SchData-OLTP-HumanResource"".""Func_TblWorkerCareerInternal_SET""(varSystemLoginSession, null::bigint, null::varchar", CONCATENATE(IF(EXACT($K36, ""), ", null", CONCATENATE(", '", $K36, "'")), "::timestamptz"), CONCATENATE(IF(EXACT($L36, ""), ", null", CONCATENATE(", '", $L36, "'")), "::timestamptz"), ", null::varchar, varInstitutionBranchID, varBaseCurrencyID", CONCATENATE(IF(EXACT($B36, ""), ", null", CONCATENATE(", ", $B36, "")), "::bigint"), CONCATENATE(IF(EXACT($D36, ""), ", null", CONCATENATE(", ", $D36, "")), "::bigint"), CONCATENATE(IF(EXACT($F36, ""), ", null", CONCATENATE(", ", $F36, "")), "::bigint"), CONCATENATE(IF(EXACT($H36, ""), ", null", CONCATENATE(", ", $H36, "")), "::bigint"), CONCATENATE(IF(EXACT($J36, ""), ", null", CONCATENATE(", '", $J36, "'")), "::varchar"), CONCATENATE(IF(EXACT($K36, ""), ", null", CONCATENATE(", '", $K36, "'")), "::timestamptz"), CONCATENATE(IF(EXACT($L36, ""), ", null", CONCATENATE(", '", $L36, "'")), "::timestamptz"), CONCATENATE(IF(EXACT($M36, ""), ", null", CONCATENATE(", ", $M36, "")), "::bigint"), ");") -> PERFORM "SchData-OLTP-HumanResource"."Func_TblWorkerCareerInternal_SET"(varSystemLoginSession, null::bigint, null::varchar, null::timestamptz, '1900-12-31 23:59:59+07'::timestamptz, null::varchar, varInstitutionBranchID, varBaseCurrencyID, 32000000000033::bigint, 163000000000003::bigint, null::bigint, null::bigint, null::varchar, null::timestamptz, '1900-12-31 23:59:59+07'::timestamptz, null::bigint);
B37: =IF(EXACT(DataLookUp!$B37, ""), "", DataLookUp!$B37) -> 32000000000034 | C37: =MAIN!C37 -> Anggina Tri Yudandi | D37: 163000000000003 | E37: =IF(EXACT($D37, ""), "", VLOOKUP($D37, [2]DataLookUp!$B$4:$D$15, 2, FALSE )) -> Karyawan Tidak Tetap (Kontrak) | G37: =IF(EXACT($F37, ""), "", VLOOKUP($F37, 'MAIN - OrgDepartment'!$C$3:$D$104, 2, FALSE)) | I37: =IF(EXACT($H37, ""), "", VLOOKUP($H37, 'MAIN - OrgJobsPos'!$B$2:$C$101, 2, FALSE)) | L37: 1900-12-31 23:59:59+07 | O37: =O36 + IF(EXACT(P37, ""), 0, 1) -> 164000000000034 | P37: =CONCATENATE("PERFORM ""SchData-OLTP-HumanResource"".""Func_TblWorkerCareerInternal_SET""(varSystemLoginSession, null::bigint, null::varchar", CONCATENATE(IF(EXACT($K37, ""), ", null", CONCATENATE(", '", $K37, "'")), "::timestamptz"), CONCATENATE(IF(EXACT($L37, ""), ", null", CONCATENATE(", '", $L37, "'")), "::timestamptz"), ", null::varchar, varInstitutionBranchID, varBaseCurrencyID", CONCATENATE(IF(EXACT($B37, ""), ", null", CONCATENATE(", ", $B37, "")), "::bigint"), CONCATENATE(IF(EXACT($D37, ""), ", null", CONCATENATE(", ", $D37, "")), "::bigint"), CONCATENATE(IF(EXACT($F37, ""), ", null", CONCATENATE(", ", $F37, "")), "::bigint"), CONCATENATE(IF(EXACT($H37, ""), ", null", CONCATENATE(", ", $H37, "")), "::bigint"), CONCATENATE(IF(EXACT($J37, ""), ", null", CONCATENATE(", '", $J37, "'")), "::varchar"), CONCATENATE(IF(EXACT($K37, ""), ", null", CONCATENATE(", '", $K37, "'")), "::timestamptz"), CONCATENATE(IF(EXACT($L37, ""), ", null", CONCATENATE(", '", $L37, "'")), "::timestamptz"), CONCATENATE(IF(EXACT($M37, ""), ", null", CONCATENATE(", ", $M37, "")), "::bigint"), ");") -> PERFORM "SchData-OLTP-HumanResource"."Func_TblWorkerCareerInternal_SET"(varSystemLoginSession, null::bigint, null::varchar, null::timestamptz, '1900-12-31 23:59:59+07'::timestamptz, null::varchar, varInstitutionBranchID, varBaseCurrencyID, 32000000000034::bigint, 163000000000003::bigint, null::bigint, null::bigint, null::varchar, null::timestamptz, '1900-12-31 23:59:59+07'::timestamptz, null::bigint);
B38: =IF(EXACT(DataLookUp!$B38, ""), "", DataLookUp!$B38) -> 32000000000035 | C38: =MAIN!C38 -> Anggit Ismiyanto | D38: 163000000000003 | E38: =IF(EXACT($D38, ""), "", VLOOKUP($D38, [2]DataLookUp!$B$4:$D$15, 2, FALSE )) -> Karyawan Tidak Tetap (Kontrak) | G38: =IF(EXACT($F38, ""), "", VLOOKUP($F38, 'MAIN - OrgDepartment'!$C$3:$D$104, 2, FALSE)) | I38: =IF(EXACT($H38, ""), "", VLOOKUP($H38, 'MAIN - OrgJobsPos'!$B$2:$C$101, 2, FALSE)) | L38: 1900-12-31 23:59:59+07 | O38: =O37 + IF(EXACT(P38, ""), 0, 1) -> 164000000000035 | P38: =CONCATENATE("PERFORM ""SchData-OLTP-HumanResource"".""Func_TblWorkerCareerInternal_SET""(varSystemLoginSession, null::bigint, null::varchar", CONCATENATE(IF(EXACT($K38, ""), ", null", CONCATENATE(", '", $K38, "'")), "::timestamptz"), CONCATENATE(IF(EXACT($L38, ""), ", null", CONCATENATE(", '", $L38, "'")), "::timestamptz"), ", null::varchar, varInstitutionBranchID, varBaseCurrencyID", CONCATENATE(IF(EXACT($B38, ""), ", null", CONCATENATE(", ", $B38, "")), "::bigint"), CONCATENATE(IF(EXACT($D38, ""), ", null", CONCATENATE(", ", $D38, "")), "::bigint"), CONCATENATE(IF(EXACT($F38, ""), ", null", CONCATENATE(", ", $F38, "")), "::bigint"), CONCATENATE(IF(EXACT($H38, ""), ", null", CONCATENATE(", ", $H38, "")), "::bigint"), CONCATENATE(IF(EXACT($J38, ""), ", null", CONCATENATE(", '", $J38, "'")), "::varchar"), CONCATENATE(IF(EXACT($K38, ""), ", null", CONCATENATE(", '", $K38, "'")), "::timestamptz"), CONCATENATE(IF(EXACT($L38, ""), ", null", CONCATENATE(", '", $L38, "'")), "::timestamptz"), CONCATENATE(IF(EXACT($M38, ""), ", null", CONCATENATE(", ", $M38, "")), "::bigint"), ");") -> PERFORM "SchData-OLTP-HumanResource"."Func_TblWorkerCareerInternal_SET"(varSystemLoginSession, null::bigint, null::varchar, null::timestamptz, '1900-12-31 23:59:59+07'::timestamptz, null::varchar, varInstitutionBranchID, varBaseCurrencyID, 32000000000035::bigint, 163000000000003::bigint, null::bigint, null::bigint, null::varchar, null::timestamptz, '1900-12-31 23:59:59+07'::timestamptz, null::bigint);
... B53: =IF(EXACT(DataLookUp!$B53, ""), "", DataLookUp!$B53) -> 32000000000050 | C53: =MAIN!C53 -> Ardita | D53: 163000000000003 | E53: =IF(EXACT($D53, ""), "", VLOOKUP($D53, [2]DataLookUp!$B$4:$D$15, 2, FALSE )) -> Karyawan Tidak Tetap (Kontrak) | G53: =IF(EXACT($F53, ""), "", VLOOKUP($F53, 'MAIN - OrgDepartment'!$C$3:$D$104, 2, FALSE)) | I53: =IF(EXACT($H53, ""), "", VLOOKUP($H53, 'MAIN - OrgJobsPos'!$B$2:$C$101, 2, FALSE)) | L53: 1900-12-31 23:59:59+07 | O53: =O52 + IF(EXACT(P53, ""), 0, 1) -> 164000000000050 | P53: =CONCATENATE("PERFORM ""SchData-OLTP-HumanResource"".""Func_TblWorkerCareerInternal_SET""(varSystemLoginSession, null::bigint, null::varchar", CONCATENATE(IF(EXACT($K53, ""), ", null", CONCATENATE(", '", $K53, "'")), "::timestamptz"), CONCATENATE(IF(EXACT($L53, ""), ", null", CONCATENATE(", '", $L53, "'")), "::timestamptz"), ", null::varchar, varInstitutionBranchID, varBaseCurrencyID", CONCATENATE(IF(EXACT($B53, ""), ", null", CONCATENATE(", ", $B53, "")), "::bigint"), CONCATENATE(IF(EXACT($D53, ""), ", null", CONCATENATE(", ", $D53, "")), "::bigint"), CONCATENATE(IF(EXACT($F53, ""), ", null", CONCATENATE(", ", $F53, "")), "::bigint"), CONCATENATE(IF(EXACT($H53, ""), ", null", CONCATENATE(", ", $H53, "")), "::bigint"), CONCATENATE(IF(EXACT($J53, ""), ", null", CONCATENATE(", '", $J53, "'")), "::varchar"), CONCATENATE(IF(EXACT($K53, ""), ", null", CONCATENATE(", '", $K53, "'")), "::timestamptz"), CONCATENATE(IF(EXACT($L53, ""), ", null", CONCATENATE(", '", $L53, "'")), "::timestamptz"), CONCATENATE(IF(EXACT($M53, ""), ", null", CONCATENATE(", ", $M53, "")), "::bigint"), ");") -> PERFORM "SchData-OLTP-HumanResource"."Func_TblWorkerCareerInternal_SET"(varSystemLoginSession, null::bigint, null::varchar, null::timestamptz, '1900-12-31 23:59:59+07'::timestamptz, null::varchar, varInstitutionBranchID, varBaseCurrencyID, 32000000000050::bigint, 163000000000003::bigint, null::bigint, null::bigint, null::varchar, null::timestamptz, '1900-12-31 23:59:59+07'::timestamptz, null::bigint);
B54: =IF(EXACT(DataLookUp!$B54, ""), "", DataLookUp!$B54) -> 32000000000051 | C54: =MAIN!C54 -> Ares S. Mauboi | D54: 163000000000003 | E54: =IF(EXACT($D54, ""), "", VLOOKUP($D54, [2]DataLookUp!$B$4:$D$15, 2, FALSE )) -> Karyawan Tidak Tetap (Kontrak) | F54: 111000000000023 | G54: =IF(EXACT($F54, ""), "", VLOOKUP($F54, 'MAIN - OrgDepartment'!$C$3:$D$104, 2, FALSE)) -> Operation & Maintenance | H54: 160000000000002 | I54: =IF(EXACT($H54, ""), "", VLOOKUP($H54, 'MAIN - OrgJobsPos'!$B$2:$C$101, 2, FALSE)) -> Senior Clerical | J54: Driver | L54: 9999-12-31 23:59:59+07 | O54: =O53 + IF(EXACT(P54, ""), 0, 1) -> 164000000000051 | P54: =CONCATENATE("PERFORM ""SchData-OLTP-HumanResource"".""Func_TblWorkerCareerInternal_SET""(varSystemLoginSession, null::bigint, null::varchar", CONCATENATE(IF(EXACT($K54, ""), ", null", CONCATENATE(", '", $K54, "'")), "::timestamptz"), CONCATENATE(IF(EXACT($L54, ""), ", null", CONCATENATE(", '", $L54, "'")), "::timestamptz"), ", null::varchar, varInstitutionBranchID, varBaseCurrencyID", CONCATENATE(IF(EXACT($B54, ""), ", null", CONCATENATE(", ", $B54, "")), "::bigint"), CONCATENATE(IF(EXACT($D54, ""), ", null", CONCATENATE(", ", $D54, "")), "::bigint"), CONCATENATE(IF(EXACT($F54, ""), ", null", CONCATENATE(", ", $F54, "")), "::bigint"), CONCATENATE(IF(EXACT($H54, ""), ", null", CONCATENATE(", ", $H54, "")), "::bigint"), CONCATENATE(IF(EXACT($J54, ""), ", null", CONCATENATE(", '", $J54, "'")), "::varchar"), CONCATENATE(IF(EXACT($K54, ""), ", null", CONCATENATE(", '", $K54, "'")), "::timestamptz"), CONCATENATE(IF(EXACT($L54, ""), ", null", CONCATENATE(", '", $L54, "'")), "::timestamptz"), CONCATENATE(IF(EXACT($M54, ""), ", null", CONCATENATE(", ", $M54, "")), "::bigint"), ");") -> PERFORM "SchData-OLTP-HumanResource"."Func_TblWorkerCareerInternal_SET"(varSystemLoginSession, null::bigint, null::varchar, null::timestamptz, '9999-12-31 23:59:59+07'::timestamptz, null::varchar, varInstitutionBranchID, varBaseCurrencyID, 32000000000051::bigint, 163000000000003::bigint, 111000000000023::bigint, 160000000000002::bigint, 'Driver'::varchar, null::timestamptz, '9999-12-31 23:59:59+07'::timestamptz, null::bigint);
B55: =IF(EXACT(DataLookUp!$B55, ""), "", DataLookUp!$B55) -> 32000000000052 | C55: =MAIN!C55 -> Arfah Hanum | D55: 163000000000003 | E55: =IF(EXACT($D55, ""), "", VLOOKUP($D55, [2]DataLookUp!$B$4:$D$15, 2, FALSE )) -> Karyawan Tidak Tetap (Kontrak) | G55: =IF(EXACT($F55, ""), "", VLOOKUP($F55, 'MAIN - OrgDepartment'!$C$3:$D$104, 2, FALSE)) | I55: =IF(EXACT($H55, ""), "", VLOOKUP($H55, 'MAIN - OrgJobsPos'!$B$2:$C$101, 2, FALSE)) | L55: 1900-12-31 23:59:59+07 | O55: =O54 + IF(EXACT(P55, ""), 0, 1) -> 164000000000052 | P55: =CONCATENATE("PERFORM ""SchData-OLTP-HumanResource"".""Func_TblWorkerCareerInternal_SET""(varSystemLoginSession, null::bigint, null::varchar", CONCATENATE(IF(EXACT($K55, ""), ", null", CONCATENATE(", '", $K55, "'")), "::timestamptz"), CONCATENATE(IF(EXACT($L55, ""), ", null", CONCATENATE(", '", $L55, "'")), "::timestamptz"), ", null::varchar, varInstitutionBranchID, varBaseCurrencyID", CONCATENATE(IF(EXACT($B55, ""), ", null", CONCATENATE(", ", $B55, "")), "::bigint"), CONCATENATE(IF(EXACT($D55, ""), ", null", CONCATENATE(", ", $D55, "")), "::bigint"), CONCATENATE(IF(EXACT($F55, ""), ", null", CONCATENATE(", ", $F55, "")), "::bigint"), CONCATENATE(IF(EXACT($H55, ""), ", null", CONCATENATE(", ", $H55, "")), "::bigint"), CONCATENATE(IF(EXACT($J55, ""), ", null", CONCATENATE(", '", $J55, "'")), "::varchar"), CONCATENATE(IF(EXACT($K55, ""), ", null", CONCATENATE(", '", $K55, "'")), "::timestamptz"), CONCATENATE(IF(EXACT($L55, ""), ", null", CONCATENATE(", '", $L55, "'")), "::timestamptz"), CONCATENATE(IF(EXACT($M55, ""), ", null", CONCATENATE(", ", $M55, "")), "::bigint"), ");") -> PERFORM "SchData-OLTP-HumanResource"."Func_TblWorkerCareerInternal_SET"(varSystemLoginSession, null::bigint, null::varchar, null::timestamptz, '1900-12-31 23:59:59+07'::timestamptz, null::varchar, varInstitutionBranchID, varBaseCurrencyID, 32000000000052::bigint, 163000000000003::bigint, null::bigint, null::bigint, null::varchar, null::timestamptz, '1900-12-31 23:59:59+07'::timestamptz, null::bigint);
B56: =IF(EXACT(DataLookUp!$B56, ""), "", DataLookUp!$B56) -> 32000000000053 | C56: =MAIN!C56 -> Arfianti Haryani | D56: 163000000000003 | E56: =IF(EXACT($D56, ""), "", VLOOKUP($D56, [2]DataLookUp!$B$4:$D$15, 2, FALSE )) -> Karyawan Tidak Tetap (Kontrak) | G56: =IF(EXACT($F56, ""), "", VLOOKUP($F56, 'MAIN - OrgDepartment'!$C$3:$D$104, 2, FALSE)) | I56: =IF(EXACT($H56, ""), "", VLOOKUP($H56, 'MAIN - OrgJobsPos'!$B$2:$C$101, 2, FALSE)) | L56: 1900-12-31 23:59:59+07 | O56: =O55 + IF(EXACT(P56, ""), 0, 1) -> 164000000000053 | P56: =CONCATENATE("PERFORM ""SchData-OLTP-HumanResource"".""Func_TblWorkerCareerInternal_SET""(varSystemLoginSession, null::bigint, null::varchar", CONCATENATE(IF(EXACT($K56, ""), ", null", CONCATENATE(", '", $K56, "'")), "::timestamptz"), CONCATENATE(IF(EXACT($L56, ""), ", null", CONCATENATE(", '", $L56, "'")), "::timestamptz"), ", null::varchar, varInstitutionBranchID, varBaseCurrencyID", CONCATENATE(IF(EXACT($B56, ""), ", null", CONCATENATE(", ", $B56, "")), "::bigint"), CONCATENATE(IF(EXACT($D56, ""), ", null", CONCATENATE(", ", $D56, "")), "::bigint"), CONCATENATE(IF(EXACT($F56, ""), ", null", CONCATENATE(", ", $F56, "")), "::bigint"), CONCATENATE(IF(EXACT($H56, ""), ", null", CONCATENATE(", ", $H56, "")), "::bigint"), CONCATENATE(IF(EXACT($J56, ""), ", null", CONCATENATE(", '", $J56, "'")), "::varchar"), CONCATENATE(IF(EXACT($K56, ""), ", null", CONCATENATE(", '", $K56, "'")), "::timestamptz"), CONCATENATE(IF(EXACT($L56, ""), ", null", CONCATENATE(", '", $L56, "'")), "::timestamptz"), CONCATENATE(IF(EXACT($M56, ""), ", null", CONCATENATE(", ", $M56, "")), "::bigint"), ");") -> PERFORM "SchData-OLTP-HumanResource"."Func_TblWorkerCareerInternal_SET"(varSystemLoginSession, null::bigint, null::varchar, null::timestamptz, '1900-12-31 23:59:59+07'::timestamptz, null::varchar, varInstitutionBranchID, varBaseCurrencyID, 32000000000053::bigint, 163000000000003::bigint, null::bigint, null::bigint, null::varchar, null::timestamptz, '1900-12-31 23:59:59+07'::timestamptz, null::bigint);
B57: =IF(EXACT(DataLookUp!$B57, ""), "", DataLookUp!$B57) -> 32000000000054 | C57: =MAIN!C57 -> Ari Priwarsono | D57: 163000000000003 | E57: =IF(EXACT($D57, ""), "", VLOOKUP($D57, [2]DataLookUp!$B$4:$D$15, 2, FALSE )) -> Karyawan Tidak Tetap (Kontrak) | G57: =IF(EXACT($F57, ""), "", VLOOKUP($F57, 'MAIN - OrgDepartment'!$C$3:$D$104, 2, FALSE)) | I57: =IF(EXACT($H57, ""), "", VLOOKUP($H57, 'MAIN - OrgJobsPos'!$B$2:$C$101, 2, FALSE)) | L57: 1900-12-31 23:59:59+07 | O57: =O56 + IF(EXACT(P57, ""), 0, 1) -> 164000000000054 | P57: =CONCATENATE("PERFORM ""SchData-OLTP-HumanResource"".""Func_TblWorkerCareerInternal_SET""(varSystemLoginSession, null::bigint, null::varchar", CONCATENATE(IF(EXACT($K57, ""), ", null", CONCATENATE(", '", $K57, "'")), "::timestamptz"), CONCATENATE(IF(EXACT($L57, ""), ", null", CONCATENATE(", '", $L57, "'")), "::timestamptz"), ", null::varchar, varInstitutionBranchID, varBaseCurrencyID", CONCATENATE(IF(EXACT($B57, ""), ", null", CONCATENATE(", ", $B57, "")), "::bigint"), CONCATENATE(IF(EXACT($D57, ""), ", null", CONCATENATE(", ", $D57, "")), "::bigint"), CONCATENATE(IF(EXACT($F57, ""), ", null", CONCATENATE(", ", $F57, "")), "::bigint"), CONCATENATE(IF(EXACT($H57, ""), ", null", CONCATENATE(", ", $H57, "")), "::bigint"), CONCATENATE(IF(EXACT($J57, ""), ", null", CONCATENATE(", '", $J57, "'")), "::varchar"), CONCATENATE(IF(EXACT($K57, ""), ", null", CONCATENATE(", '", $K57, "'")), "::timestamptz"), CONCATENATE(IF(EXACT($L57, ""), ", null", CONCATENATE(", '", $L57, "'")), "::timestamptz"), CONCATENATE(IF(EXACT($M57, ""), ", null", CONCATENATE(", ", $M57, "")), "::bigint"), ");") -> PERFORM "SchData-OLTP-HumanResource"."Func_TblWorkerCareerInternal_SET"(varSystemLoginSession, null::bigint, null::varchar, null::timestamptz, '1900-12-31 23:59:59+07'::timestamptz, null::varchar, varInstitutionBranchID, varBaseCurrencyID, 32000000000054::bigint, 163000000000003::bigint, null::bigint, null::bigint, null::varchar, null::timestamptz, '1900-12-31 23:59:59+07'::timestamptz, null::bigint);
B58: =IF(EXACT(DataLookUp!$B58, ""), "", DataLookUp!$B58) -> 32000000000055 | C58: =MAIN!C58 -> Ari Yuniasmono | D58: 163000000000003 | E58: =IF(EXACT($D58, ""), "", VLOOKUP($D58, [2]DataLookUp!$B$4:$D$15, 2, FALSE )) -> Karyawan Tidak Tetap (Kontrak) | G58: =IF(EXACT($F58, ""), "", VLOOKUP($F58, 'MAIN - OrgDepartment'!$C$3:$D$104, 2, FALSE)) | I58: =IF(EXACT($H58, ""), "", VLOOKUP($H58, 'MAIN - OrgJobsPos'!$B$2:$C$101, 2, FALSE)) | L58: 1900-12-31 23:59:59+07 | O58: =O57 + IF(EXACT(P58, ""), 0, 1) -> 164000000000055 | P58: =CONCATENATE("PERFORM ""SchData-OLTP-HumanResource"".""Func_TblWorkerCareerInternal_SET""(varSystemLoginSession, null::bigint, null::varchar", CONCATENATE(IF(EXACT($K58, ""), ", null", CONCATENATE(", '", $K58, "'")), "::timestamptz"), CONCATENATE(IF(EXACT($L58, ""), ", null", CONCATENATE(", '", $L58, "'")), "::timestamptz"), ", null::varchar, varInstitutionBranchID, varBaseCurrencyID", CONCATENATE(IF(EXACT($B58, ""), ", null", CONCATENATE(", ", $B58, "")), "::bigint"), CONCATENATE(IF(EXACT($D58, ""), ", null", CONCATENATE(", ", $D58, "")), "::bigint"), CONCATENATE(IF(EXACT($F58, ""), ", null", CONCATENATE(", ", $F58, "")), "::bigint"), CONCATENATE(IF(EXACT($H58, ""), ", null", CONCATENATE(", ", $H58, "")), "::bigint"), CONCATENATE(IF(EXACT($J58, ""), ", null", CONCATENATE(", '", $J58, "'")), "::varchar"), CONCATENATE(IF(EXACT($K58, ""), ", null", CONCATENATE(", '", $K58, "'")), "::timestamptz"), CONCATENATE(IF(EXACT($L58, ""), ", null", CONCATENATE(", '", $L58, "'")), "::timestamptz"), CONCATENATE(IF(EXACT($M58, ""), ", null", CONCATENATE(", ", $M58, "")), "::bigint"), ");") -> PERFORM "SchData-OLTP-HumanResource"."Func_TblWorkerCareerInternal_SET"(varSystemLoginSession, null::bigint, null::varchar, null::timestamptz, '1900-12-31 23:59:59+07'::timestamptz, null::varchar, varInstitutionBranchID, varBaseCurrencyID, 32000000000055::bigint, 163000000000003::bigint, null::bigint, null::bigint, null::varchar, null::timestamptz, '1900-12-31 23:59:59+07'::timestamptz, null::bigint);
B59: =IF(EXACT(DataLookUp!$B59, ""), "", DataLookUp!$B59) -> 32000000000056 | C59: =MAIN!C59 -> Arif Gunawan | D59: 163000000000003 | E59: =IF(EXACT($D59, ""), "", VLOOKUP($D59, [2]DataLookUp!$B$4:$D$15, 2, FALSE )) -> Karyawan Tidak Tetap (Kontrak) | G59: =IF(EXACT($F59, ""), "", VLOOKUP($F59, 'MAIN - OrgDepartment'!$C$3:$D$104, 2, FALSE)) | I59: =IF(EXACT($H59, ""), "", VLOOKUP($H59, 'MAIN - OrgJobsPos'!$B$2:$C$101, 2, FALSE)) | L59: 1900-12-31 23:59:59+07 | O59: =O58 + IF(EXACT(P59, ""), 0, 1) -> 164000000000056 | P59: =CONCATENATE("PERFORM ""SchData-OLTP-HumanResource"".""Func_TblWorkerCareerInternal_SET""(varSystemLoginSession, null::bigint, null::varchar", CONCATENATE(IF(EXACT($K59, ""), ", null", CONCATENATE(", '", $K59, "'")), "::timestamptz"), CONCATENATE(IF(EXACT($L59, ""), ", null", CONCATENATE(", '", $L59, "'")), "::timestamptz"), ", null::varchar, varInstitutionBranchID, varBaseCurrencyID", CONCATENATE(IF(EXACT($B59, ""), ", null", CONCATENATE(", ", $B59, "")), "::bigint"), CONCATENATE(IF(EXACT($D59, ""), ", null", CONCATENATE(", ", $D59, "")), "::bigint"), CONCATENATE(IF(EXACT($F59, ""), ", null", CONCATENATE(", ", $F59, "")), "::bigint"), CONCATENATE(IF(EXACT($H59, ""), ", null", CONCATENATE(", ", $H59, "")), "::bigint"), CONCATENATE(IF(EXACT($J59, ""), ", null", CONCATENATE(", '", $J59, "'")), "::varchar"), CONCATENATE(IF(EXACT($K59, ""), ", null", CONCATENATE(", '", $K59, "'")), "::timestamptz"), CONCATENATE(IF(EXACT($L59, ""), ", null", CONCATENATE(", '", $L59, "'")), "::timestamptz"), CONCATENATE(IF(EXACT($M59, ""), ", null", CONCATENATE(", ", $M59, "")), "::bigint"), ");") -> PERFORM "SchData-OLTP-HumanResource"."Func_TblWorkerCareerInternal_SET"(varSystemLoginSession, null::bigint, null::varchar, null::timestamptz, '1900-12-31 23:59:59+07'::timestamptz, null::varchar, varInstitutionBranchID, varBaseCurrencyID, 32000000000056::bigint, 163000000000003::bigint, null::bigint, null::bigint, null::varchar, null::timestamptz, '1900-12-31 23:59:59+07'::timestamptz, null::bigint);
B60: =IF(EXACT(DataLookUp!$B60, ""), "", DataLookUp!$B60) -> 32000000000057 | C60: =MAIN!C60 -> Arif Prasetyo | D60: 163000000000003 | E60: =IF(EXACT($D60, ""), "", VLOOKUP($D60, [2]DataLookUp!$B$4:$D$15, 2, FALSE )) -> Karyawan Tidak Tetap (Kontrak) | G60: =IF(EXACT($F60, ""), "", VLOOKUP($F60, 'MAIN - OrgDepartment'!$C$3:$D$104, 2, FALSE)) | I60: =IF(EXACT($H60, ""), "", VLOOKUP($H60, 'MAIN - OrgJobsPos'!$B$2:$C$101, 2, FALSE)) | L60: 1900-12-31 23:59:59+07 | O60: =O59 + IF(EXACT(P60, ""), 0, 1) -> 164000000000057 | P60: =CONCATENATE("PERFORM ""SchData-OLTP-HumanResource"".""Func_TblWorkerCareerInternal_SET""(varSystemLoginSession, null::bigint, null::varchar", CONCATENATE(IF(EXACT($K60, ""), ", null", CONCATENATE(", '", $K60, "'")), "::timestamptz"), CONCATENATE(IF(EXACT($L60, ""), ", null", CONCATENATE(", '", $L60, "'")), "::timestamptz"), ", null::varchar, varInstitutionBranchID, varBaseCurrencyID", CONCATENATE(IF(EXACT($B60, ""), ", null", CONCATENATE(", ", $B60, "")), "::bigint"), CONCATENATE(IF(EXACT($D60, ""), ", null", CONCATENATE(", ", $D60, "")), "::bigint"), CONCATENATE(IF(EXACT($F60, ""), ", null", CONCATENATE(", ", $F60, "")), "::bigint"), CONCATENATE(IF(EXACT($H60, ""), ", null", CONCATENATE(", ", $H60, "")), "::bigint"), CONCATENATE(IF(EXACT($J60, ""), ", null", CONCATENATE(", '", $J60, "'")), "::varchar"), CONCATENATE(IF(EXACT($K60, ""), ", null", CONCATENATE(", '", $K60, "'")), "::timestamptz"), CONCATENATE(IF(EXACT($L60, ""), ", null", CONCATENATE(", '", $L60, "'")), "::timestamptz"), CONCATENATE(IF(EXACT($M60, ""), ", null", CONCATENATE(", ", $M60, "")), "::bigint"), ");") -> PERFORM "SchData-OLTP-HumanResource"."Func_TblWorkerCareerInternal_SET"(varSystemLoginSession, null::bigint, null::varchar, null::timestamptz, '1900-12-31 23:59:59+07'::timestamptz, null::varchar, varInstitutionBranchID, varBaseCurrencyID, 32000000000057::bigint, 163000000000003::bigint, null::bigint, null::bigint, null::varchar, null::timestamptz, '1900-12-31 23:59:59+07'::timestamptz, null::bigint);
B61: =IF(EXACT(DataLookUp!$B61, ""), "", DataLookUp!$B61) -> 32000000000058 | C61: =MAIN!C61 -> Arini | D61: 163000000000003 | E61: =IF(EXACT($D61, ""), "", VLOOKUP($D61, [2]DataLookUp!$B$4:$D$15, 2, FALSE )) -> Karyawan Tidak Tetap (Kontrak) | G61: =IF(EXACT($F61, ""), "", VLOOKUP($F61, 'MAIN - OrgDepartment'!$C$3:$D$104, 2, FALSE)) | I61: =IF(EXACT($H61, ""), "", VLOOKUP($H61, 'MAIN - OrgJobsPos'!$B$2:$C$101, 2, FALSE)) | L61: 1900-12-31 23:59:59+07 | O61: =O60 + IF(EXACT(P61, ""), 0, 1) -> 164000000000058 | P61: =CONCATENATE("PERFORM ""SchData-OLTP-HumanResource"".""Func_TblWorkerCareerInternal_SET""(varSystemLoginSession, null::bigint, null::varchar", CONCATENATE(IF(EXACT($K61, ""), ", null", CONCATENATE(", '", $K61, "'")), "::timestamptz"), CONCATENATE(IF(EXACT($L61, ""), ", null", CONCATENATE(", '", $L61, "'")), "::timestamptz"), ", null::varchar, varInstitutionBranchID, varBaseCurrencyID", CONCATENATE(IF(EXACT($B61, ""), ", null", CONCATENATE(", ", $B61, "")), "::bigint"), CONCATENATE(IF(EXACT($D61, ""), ", null", CONCATENATE(", ", $D61, "")), "::bigint"), CONCATENATE(IF(EXACT($F61, ""), ", null", CONCATENATE(", ", $F61, "")), "::bigint"), CONCATENATE(IF(EXACT($H61, ""), ", null", CONCATENATE(", ", $H61, "")), "::bigint"), CONCATENATE(IF(EXACT($J61, ""), ", null", CONCATENATE(", '", $J61, "'")), "::varchar"), CONCATENATE(IF(EXACT($K61, ""), ", null", CONCATENATE(", '", $K61, "'")), "::timestamptz"), CONCATENATE(IF(EXACT($L61, ""), ", null", CONCATENATE(", '", $L61, "'")), "::timestamptz"), CONCATENATE(IF(EXACT($M61, ""), ", null", CONCATENATE(", ", $M61, "")), "::bigint"), ");") -> PERFORM "SchData-OLTP-HumanResource"."Func_TblWorkerCareerInternal_SET"(varSystemLoginSession, null::bigint, null::varchar, null::timestamptz, '1900-12-31 23:59:59+07'::timestamptz, null::varchar, varInstitutionBranchID, varBaseCurrencyID, 32000000000058::bigint, 163000000000003::bigint, null::bigint, null::bigint, null::varchar, null::timestamptz, '1900-12-31 23:59:59+07'::timestamptz, null::bigint);
B62: =IF(EXACT(DataLookUp!$B62, ""), "", DataLookUp!$B62) -> 32000000000059 | C62: =MAIN!C62 -> Ario Setyo Gunawan | D62: 163000000000003 | E62: =IF(EXACT($D62, ""), "", VLOOKUP($D62, [2]DataLookUp!$B$4:$D$15, 2, FALSE )) -> Karyawan Tidak Tetap (Kontrak) | G62: =IF(EXACT($F62, ""), "", VLOOKUP($F62, 'MAIN - OrgDepartment'!$C$3:$D$104, 2, FALSE)) | I62: =IF(EXACT($H62, ""), "", VLOOKUP($H62, 'MAIN - OrgJobsPos'!$B$2:$C$101, 2, FALSE)) | L62: 1900-12-31 23:59:59+07 | O62: =O61 + IF(EXACT(P62, ""), 0, 1) -> 164000000000059 | P62: =CONCATENATE("PERFORM ""SchData-OLTP-HumanResource"".""Func_TblWorkerCareerInternal_SET""(varSystemLoginSession, null::bigint, null::varchar", CONCATENATE(IF(EXACT($K62, ""), ", null", CONCATENATE(", '", $K62, "'")), "::timestamptz"), CONCATENATE(IF(EXACT($L62, ""), ", null", CONCATENATE(", '", $L62, "'")), "::timestamptz"), ", null::varchar, varInstitutionBranchID, varBaseCurrencyID", CONCATENATE(IF(EXACT($B62, ""), ", null", CONCATENATE(", ", $B62, "")), "::bigint"), CONCATENATE(IF(EXACT($D62, ""), ", null", CONCATENATE(", ", $D62, "")), "::bigint"), CONCATENATE(IF(EXACT($F62, ""), ", null", CONCATENATE(", ", $F62, "")), "::bigint"), CONCATENATE(IF(EXACT($H62, ""), ", null", CONCATENATE(", ", $H62, "")), "::bigint"), CONCATENATE(IF(EXACT($J62, ""), ", null", CONCATENATE(", '", $J62, "'")), "::varchar"), CONCATENATE(IF(EXACT($K62, ""), ", null", CONCATENATE(", '", $K62, "'")), "::timestamptz"), CONCATENATE(IF(EXACT($L62, ""), ", null", CONCATENATE(", '", $L62, "'")), "::timestamptz"), CONCATENATE(IF(EXACT($M62, ""), ", null", CONCATENATE(", ", $M62, "")), "::bigint"), ");") -> PERFORM "SchData-OLTP-HumanResource"."Func_TblWorkerCareerInternal_SET"(varSystemLoginSession, null::bigint, null::varchar, null::timestamptz, '1900-12-31 23:59:59+07'::timestamptz, null::varchar, varInstitutionBranchID, varBaseCurrencyID, 32000000000059::bigint, 163000000000003::bigint, null::bigint, null::bigint, null::varchar, null::timestamptz, '1900-12-31 23:59:59+07'::timestamptz, null::bigint);
B63: =IF(EXACT(DataLookUp!$B63, ""), "", DataLookUp!$B63) -> 32000000000060 | C63: =MAIN!C63 -> Ario Yulianto Wibowo | D63: 163000000000003 | E63: =IF(EXACT($D63, ""), "", VLOOKUP($D63, [2]DataLookUp!$B$4:$D$15, 2, FALSE )) -> Karyawan Tidak Tetap (Kontrak) | G63: =IF(EXACT($F63, ""), "", VLOOKUP($F63, 'MAIN - OrgDepartment'!$C$3:$D$104, 2, FALSE)) | I63: =IF(EXACT($H63, ""), "", VLOOKUP($H63, 'MAIN - OrgJobsPos'!$B$2:$C$101, 2, FALSE)) | L63: 1900-12-31 23:59:59+07 | O63: =O62 + IF(EXACT(P63, ""), 0, 1) -> 164000000000060 | P63: =CONCATENATE("PERFORM ""SchData-OLTP-HumanResource"".""Func_TblWorkerCareerInternal_SET""(varSystemLoginSession, null::bigint, null::varchar", CONCATENATE(IF(EXACT($K63, ""), ", null", CONCATENATE(", '", $K63, "'")), "::timestamptz"), CONCATENATE(IF(EXACT($L63, ""), ", null", CONCATENATE(", '", $L63, "'")), "::timestamptz"), ", null::varchar, varInstitutionBranchID, varBaseCurrencyID", CONCATENATE(IF(EXACT($B63, ""), ", null", CONCATENATE(", ", $B63, "")), "::bigint"), CONCATENATE(IF(EXACT($D63, ""), ", null", CONCATENATE(", ", $D63, "")), "::bigint"), CONCATENATE(IF(EXACT($F63, ""), ", null", CONCATENATE(", ", $F63, "")), "::bigint"), CONCATENATE(IF(EXACT($H63, ""), ", null", CONCATENATE(", ", $H63, "")), "::bigint"), CONCATENATE(IF(EXACT($J63, ""), ", null", CONCATENATE(", '", $J63, "'")), "::varchar"), CONCATENATE(IF(EXACT($K63, ""), ", null", CONCATENATE(", '", $K63, "'")), "::timestamptz"), CONCATENATE(IF(EXACT($L63, ""), ", null", CONCATENATE(", '", $L63, "'")), "::timestamptz"), CONCATENATE(IF(EXACT($M63, ""), ", null", CONCATENATE(", ", $M63, "")), "::bigint"), ");") -> PERFORM "SchData-OLTP-HumanResource"."Func_TblWorkerCareerInternal_SET"(varSystemLoginSession, null::bigint, null::varchar, null::timestamptz, '1900-12-31 23:59:59+07'::timestamptz, null::varchar, varInstitutionBranchID, varBaseCurrencyID, 32000000000060::bigint, 163000000000003::bigint, null::bigint, null::bigint, null::varchar, null::timestamptz, '1900-12-31 23:59:59+07'::timestamptz, null::bigint);
B64: =IF(EXACT(DataLookUp!$B64, ""), "", DataLookUp!$B64) -> 32000000000061 | C64: =MAIN!C64 -> Aris Widodo Pamungkas | D64: 163000000000003 | E64: =IF(EXACT($D64, ""), "", VLOOKUP($D64, [2]DataLookUp!$B$4:$D$15, 2, FALSE )) -> Karyawan Tidak Tetap (Kontrak) | G64: =IF(EXACT($F64, ""), "", VLOOKUP($F64, 'MAIN - OrgDepartment'!$C$3:$D$104, 2, FALSE)) | I64: =IF(EXACT($H64, ""), "", VLOOKUP($H64, 'MAIN - OrgJobsPos'!$B$2:$C$101, 2, FALSE)) | L64: 1900-12-31 23:59:59+07 | O64: =O63 + IF(EXACT(P64, ""), 0, 1) -> 164000000000061 | P64: =CONCATENATE("PERFORM ""SchData-OLTP-HumanResource"".""Func_TblWorkerCareerInternal_SET""(varSystemLoginSession, null::bigint, null::varchar", CONCATENATE(IF(EXACT($K64, ""), ", null", CONCATENATE(", '", $K64, "'")), "::timestamptz"), CONCATENATE(IF(EXACT($L64, ""), ", null", CONCATENATE(", '", $L64, "'")), "::timestamptz"), ", null::varchar, varInstitutionBranchID, varBaseCurrencyID", CONCATENATE(IF(EXACT($B64, ""), ", null", CONCATENATE(", ", $B64, "")), "::bigint"), CONCATENATE(IF(EXACT($D64, ""), ", null", CONCATENATE(", ", $D64, "")), "::bigint"), CONCATENATE(IF(EXACT($F64, ""), ", null", CONCATENATE(", ", $F64, "")), "::bigint"), CONCATENATE(IF(EXACT($H64, ""), ", null", CONCATENATE(", ", $H64, "")), "::bigint"), CONCATENATE(IF(EXACT($J64, ""), ", null", CONCATENATE(", '", $J64, "'")), "::varchar"), CONCATENATE(IF(EXACT($K64, ""), ", null", CONCATENATE(", '", $K64, "'")), "::timestamptz"), CONCATENATE(IF(EXACT($L64, ""), ", null", CONCATENATE(", '", $L64, "'")), "::timestamptz"), CONCATENATE(IF(EXACT($M64, ""), ", null", CONCATENATE(", ", $M64, "")), "::bigint"), ");") -> PERFORM "SchData-OLTP-HumanResource"."Func_TblWorkerCareerInternal_SET"(varSystemLoginSession, null::bigint, null::varchar, null::timestamptz, '1900-12-31 23:59:59+07'::timestamptz, null::varchar, varInstitutionBranchID, varBaseCurrencyID, 32000000000061::bigint, 163000000000003::bigint, null::bigint, null::bigint, null::varchar, null::timestamptz, '1900-12-31 23:59:59+07'::timestamptz, null::bigint);
B65: =IF(EXACT(DataLookUp!$B65, ""), "", DataLookUp!$B65) -> 32000000000062 | C65: =MAIN!C65 -> Arjiyanto | D65: 163000000000003 | E65: =IF(EXACT($D65, ""), "", VLOOKUP($D65, [2]DataLookUp!$B$4:$D$15, 2, FALSE )) -> Karyawan Tidak Tetap (Kontrak) | G65: =IF(EXACT($F65, ""), "", VLOOKUP($F65, 'MAIN - OrgDepartment'!$C$3:$D$104, 2, FALSE)) | I65: =IF(EXACT($H65, ""), "", VLOOKUP($H65, 'MAIN - OrgJobsPos'!$B$2:$C$101, 2, FALSE)) | L65: 1900-12-31 23:59:59+07 | O65: =O64 + IF(EXACT(P65, ""), 0, 1) -> 164000000000062 | P65: =CONCATENATE("PERFORM ""SchData-OLTP-HumanResource"".""Func_TblWorkerCareerInternal_SET""(varSystemLoginSession, null::bigint, null::varchar", CONCATENATE(IF(EXACT($K65, ""), ", null", CONCATENATE(", '", $K65, "'")), "::timestamptz"), CONCATENATE(IF(EXACT($L65, ""), ", null", CONCATENATE(", '", $L65, "'")), "::timestamptz"), ", null::varchar, varInstitutionBranchID, varBaseCurrencyID", CONCATENATE(IF(EXACT($B65, ""), ", null", CONCATENATE(", ", $B65, "")), "::bigint"), CONCATENATE(IF(EXACT($D65, ""), ", null", CONCATENATE(", ", $D65, "")), "::bigint"), CONCATENATE(IF(EXACT($F65, ""), ", null", CONCATENATE(", ", $F65, "")), "::bigint"), CONCATENATE(IF(EXACT($H65, ""), ", null", CONCATENATE(", ", $H65, "")), "::bigint"), CONCATENATE(IF(EXACT($J65, ""), ", null", CONCATENATE(", '", $J65, "'")), "::varchar"), CONCATENATE(IF(EXACT($K65, ""), ", null", CONCATENATE(", '", $K65, "'")), "::timestamptz"), CONCATENATE(IF(EXACT($L65, ""), ", null", CONCATENATE(", '", $L65, "'")), "::timestamptz"), CONCATENATE(IF(EXACT($M65, ""), ", null", CONCATENATE(", ", $M65, "")), "::bigint"), ");") -> PERFORM "SchData-OLTP-HumanResource"."Func_TblWorkerCareerInternal_SET"(varSystemLoginSession, null::bigint, null::varchar, null::timestamptz, '1900-12-31 23:59:59+07'::timestamptz, null::varchar, varInstitutionBranchID, varBaseCurrencyID, 32000000000062::bigint, 163000000000003::bigint, null::bigint, null::bigint, null::varchar, null::timestamptz, '1900-12-31 23:59:59+07'::timestamptz, null::bigint);
B66: =IF(EXACT(DataLookUp!$B66, ""), "", DataLookUp!$B66) -> 32000000000063 | C66: =MAIN!C66 -> Arman | D66: 163000000000003 | E66: =IF(EXACT($D66, ""), "", VLOOKUP($D66, [2]DataLookUp!$B$4:$D$15, 2, FALSE )) -> Karyawan Tidak Tetap (Kontrak) | G66: =IF(EXACT($F66, ""), "", VLOOKUP($F66, 'MAIN - OrgDepartment'!$C$3:$D$104, 2, FALSE)) | I66: =IF(EXACT($H66, ""), "", VLOOKUP($H66, 'MAIN - OrgJobsPos'!$B$2:$C$101, 2, FALSE)) | L66: 1900-12-31 23:59:59+07 | O66: =O65 + IF(EXACT(P66, ""), 0, 1) -> 164000000000063 | P66: =CONCATENATE("PERFORM ""SchData-OLTP-HumanResource"".""Func_TblWorkerCareerInternal_SET""(varSystemLoginSession, null::bigint, null::varchar", CONCATENATE(IF(EXACT($K66, ""), ", null", CONCATENATE(", '", $K66, "'")), "::timestamptz"), CONCATENATE(IF(EXACT($L66, ""), ", null", CONCATENATE(", '", $L66, "'")), "::timestamptz"), ", null::varchar, varInstitutionBranchID, varBaseCurrencyID", CONCATENATE(IF(EXACT($B66, ""), ", null", CONCATENATE(", ", $B66, "")), "::bigint"), CONCATENATE(IF(EXACT($D66, ""), ", null", CONCATENATE(", ", $D66, "")), "::bigint"), CONCATENATE(IF(EXACT($F66, ""), ", null", CONCATENATE(", ", $F66, "")), "::bigint"), CONCATENATE(IF(EXACT($H66, ""), ", null", CONCATENATE(", ", $H66, "")), "::bigint"), CONCATENATE(IF(EXACT($J66, ""), ", null", CONCATENATE(", '", $J66, "'")), "::varchar"), CONCATENATE(IF(EXACT($K66, ""), ", null", CONCATENATE(", '", $K66, "'")), "::timestamptz"), CONCATENATE(IF(EXACT($L66, ""), ", null", CONCATENATE(", '", $L66, "'")), "::timestamptz"), CONCATENATE(IF(EXACT($M66, ""), ", null", CONCATENATE(", ", $M66, "")), "::bigint"), ");") -> PERFORM "SchData-OLTP-HumanResource"."Func_TblWorkerCareerInternal_SET"(varSystemLoginSession, null::bigint, null::varchar, null::timestamptz, '1900-12-31 23:59:59+07'::timestamptz, null::varchar, varInstitutionBranchID, varBaseCurrencyID, 32000000000063::bigint, 163000000000003::bigint, null::bigint, null::bigint, null::varchar, null::timestamptz, '1900-12-31 23:59:59+07'::timestamptz, null::bigint);
... B77: =IF(EXACT(DataLookUp!$B77, ""), "", DataLookUp!$B77) -> 32000000000074 | C77: =MAIN!C77 -> Bela Retmalantika | D77: 163000000000003 | E77: =IF(EXACT($D77, ""), "", VLOOKUP($D77, [2]DataLookUp!$B$4:$D$15, 2, FALSE )) -> Karyawan Tidak Tetap (Kontrak) | G77: =IF(EXACT($F77, ""), "", VLOOKUP($F77, 'MAIN - OrgDepartment'!$C$3:$D$104, 2, FALSE)) | I77: =IF(EXACT($H77, ""), "", VLOOKUP($H77, 'MAIN - OrgJobsPos'!$B$2:$C$101, 2, FALSE)) | L77: 1900-12-31 23:59:59+07 | O77: =O76 + IF(EXACT(P77, ""), 0, 1) -> 164000000000074 | P77: =CONCATENATE("PERFORM ""SchData-OLTP-HumanResource"".""Func_TblWorkerCareerInternal_SET""(varSystemLoginSession, null::bigint, null::varchar", CONCATENATE(IF(EXACT($K77, ""), ", null", CONCATENATE(", '", $K77, "'")), "::timestamptz"), CONCATENATE(IF(EXACT($L77, ""), ", null", CONCATENATE(", '", $L77, "'")), "::timestamptz"), ", null::varchar, varInstitutionBranchID, varBaseCurrencyID", CONCATENATE(IF(EXACT($B77, ""), ", null", CONCATENATE(", ", $B77, "")), "::bigint"), CONCATENATE(IF(EXACT($D77, ""), ", null", CONCATENATE(", ", $D77, "")), "::bigint"), CONCATENATE(IF(EXACT($F77, ""), ", null", CONCATENATE(", ", $F77, "")), "::bigint"), CONCATENATE(IF(EXACT($H77, ""), ", null", CONCATENATE(", ", $H77, "")), "::bigint"), CONCATENATE(IF(EXACT($J77, ""), ", null", CONCATENATE(", '", $J77, "'")), "::varchar"), CONCATENATE(IF(EXACT($K77, ""), ", null", CONCATENATE(", '", $K77, "'")), "::timestamptz"), CONCATENATE(IF(EXACT($L77, ""), ", null", CONCATENATE(", '", $L77, "'")), "::timestamptz"), CONCATENATE(IF(EXACT($M77, ""), ", null", CONCATENATE(", ", $M77, "")), "::bigint"), ");") -> PERFORM "SchData-OLTP-HumanResource"."Func_TblWorkerCareerInternal_SET"(varSystemLoginSession, null::bigint, null::varchar, null::timestamptz, '1900-12-31 23:59:59+07'::timestamptz, null::varchar, varInstitutionBranchID, varBaseCurrencyID, 32000000000074::bigint, 163000000000003::bigint, null::bigint, null::bigint, null::varchar, null::timestamptz, '1900-12-31 23:59:59+07'::timestamptz, null::bigint);
B78: =IF(EXACT(DataLookUp!$B78, ""), "", DataLookUp!$B78) -> 32000000000075 | C78: =MAIN!C78 -> Belina Lindarwani | D78: 163000000000003 | E78: =IF(EXACT($D78, ""), "", VLOOKUP($D78, [2]DataLookUp!$B$4:$D$15, 2, FALSE )) -> Karyawan Tidak Tetap (Kontrak) | F78: 111000000000005 | G78: =IF(EXACT($F78, ""), "", VLOOKUP($F78, 'MAIN - OrgDepartment'!$C$3:$D$104, 2, FALSE)) -> Finance & Accounting | H78: 160000000000003 | I78: =IF(EXACT($H78, ""), "", VLOOKUP($H78, 'MAIN - OrgJobsPos'!$B$2:$C$101, 2, FALSE)) -> Staff | J78: Accounting Staff | K78: 2020-09-10 00:00:00+07 | L78: 9999-12-31 23:59:59+07 | O78: =O77 + IF(EXACT(P78, ""), 0, 1) -> 164000000000075 | P78: =CONCATENATE("PERFORM ""SchData-OLTP-HumanResource"".""Func_TblWorkerCareerInternal_SET""(varSystemLoginSession, null::bigint, null::varchar", CONCATENATE(IF(EXACT($K78, ""), ", null", CONCATENATE(", '", $K78, "'")), "::timestamptz"), CONCATENATE(IF(EXACT($L78, ""), ", null", CONCATENATE(", '", $L78, "'")), "::timestamptz"), ", null::varchar, varInstitutionBranchID, varBaseCurrencyID", CONCATENATE(IF(EXACT($B78, ""), ", null", CONCATENATE(", ", $B78, "")), "::bigint"), CONCATENATE(IF(EXACT($D78, ""), ", null", CONCATENATE(", ", $D78, "")), "::bigint"), CONCATENATE(IF(EXACT($F78, ""), ", null", CONCATENATE(", ", $F78, "")), "::bigint"), CONCATENATE(IF(EXACT($H78, ""), ", null", CONCATENATE(", ", $H78, "")), "::bigint"), CONCATENATE(IF(EXACT($J78, ""), ", null", CONCATENATE(", '", $J78, "'")), "::varchar"), CONCATENATE(IF(EXACT($K78, ""), ", null", CONCATENATE(", '", $K78, "'")), "::timestamptz"), CONCATENATE(IF(EXACT($L78, ""), ", null", CONCATENATE(", '", $L78, "'")), "::timestamptz"), CONCATENATE(IF(EXACT($M78, ""), ", null", CONCATENATE(", ", $M78, "")), "::bigint"), ");") -> PERFORM "SchData-OLTP-HumanResource"."Func_TblWorkerCareerInternal_SET"(varSystemLoginSession, null::bigint, null::varchar, '2020-09-10 00:00:00+07'::timestamptz, '9999-12-31 23:59:59+07'::timestamptz, null::varchar, varInstitutionBranchID, varBaseCurrencyID, 32000000000075::bigint, 163000000000003::bigint, 111000000000005::bigint, 160000000000003::bigint, 'Accounting Staff'::varchar, '2020-09-10 00:00:00+07'::timestamptz, '9999-12-31 23:59:59+07'::timestamptz, null::bigint);
B79: =IF(EXACT(DataLookUp!$B79, ""), "", DataLookUp!$B79) -> 32000000000076 | C79: =MAIN!C79 -> Benita Sofia | D79: 163000000000003 | E79: =IF(EXACT($D79, ""), "", VLOOKUP($D79, [2]DataLookUp!$B$4:$D$15, 2, FALSE )) -> Karyawan Tidak Tetap (Kontrak) | G79: =IF(EXACT($F79, ""), "", VLOOKUP($F79, 'MAIN - OrgDepartment'!$C$3:$D$104, 2, FALSE)) | I79: =IF(EXACT($H79, ""), "", VLOOKUP($H79, 'MAIN - OrgJobsPos'!$B$2:$C$101, 2, FALSE)) | L79: 1900-12-31 23:59:59+07 | O79: =O78 + IF(EXACT(P79, ""), 0, 1) -> 164000000000076 | P79: =CONCATENATE("PERFORM ""SchData-OLTP-HumanResource"".""Func_TblWorkerCareerInternal_SET""(varSystemLoginSession, null::bigint, null::varchar", CONCATENATE(IF(EXACT($K79, ""), ", null", CONCATENATE(", '", $K79, "'")), "::timestamptz"), CONCATENATE(IF(EXACT($L79, ""), ", null", CONCATENATE(", '", $L79, "'")), "::timestamptz"), ", null::varchar, varInstitutionBranchID, varBaseCurrencyID", CONCATENATE(IF(EXACT($B79, ""), ", null", CONCATENATE(", ", $B79, "")), "::bigint"), CONCATENATE(IF(EXACT($D79, ""), ", null", CONCATENATE(", ", $D79, "")), "::bigint"), CONCATENATE(IF(EXACT($F79, ""), ", null", CONCATENATE(", ", $F79, "")), "::bigint"), CONCATENATE(IF(EXACT($H79, ""), ", null", CONCATENATE(", ", $H79, "")), "::bigint"), CONCATENATE(IF(EXACT($J79, ""), ", null", CONCATENATE(", '", $J79, "'")), "::varchar"), CONCATENATE(IF(EXACT($K79, ""), ", null", CONCATENATE(", '", $K79, "'")), "::timestamptz"), CONCATENATE(IF(EXACT($L79, ""), ", null", CONCATENATE(", '", $L79, "'")), "::timestamptz"), CONCATENATE(IF(EXACT($M79, ""), ", null", CONCATENATE(", ", $M79, "")), "::bigint"), ");") -> PERFORM "SchData-OLTP-HumanResource"."Func_TblWorkerCareerInternal_SET"(varSystemLoginSession, null::bigint, null::varchar, null::timestamptz, '1900-12-31 23:59:59+07'::timestamptz, null::varchar, varInstitutionBranchID, varBaseCurrencyID, 32000000000076::bigint, 163000000000003::bigint, null::bigint, null::bigint, null::varchar, null::timestamptz, '1900-12-31 23:59:59+07'::timestamptz, null::bigint);
B80: =IF(EXACT(DataLookUp!$B80, ""), "", DataLookUp!$B80) -> 32000000000077 | C80: =MAIN!C80 -> Bherly Novrandy | D80: 163000000000003 | E80: =IF(EXACT($D80, ""), "", VLOOKUP($D80, [2]DataLookUp!$B$4:$D$15, 2, FALSE )) -> Karyawan Tidak Tetap (Kontrak) | F80: 111000000000003 | G80: =IF(EXACT($F80, ""), "", VLOOKUP($F80, 'MAIN - OrgDepartment'!$C$3:$D$104, 2, FALSE)) -> Information Technology | H80: 160000000000003 | I80: =IF(EXACT($H80, ""), "", VLOOKUP($H80, 'MAIN - OrgJobsPos'!$B$2:$C$101, 2, FALSE)) -> Staff | K80: 2010-03-01 00:00:00+07 | L80: 2014-09-30 23:59:59+07 | O80: =O79 + IF(EXACT(P80, ""), 0, 1) -> 164000000000077 | P80: =CONCATENATE("PERFORM ""SchData-OLTP-HumanResource"".""Func_TblWorkerCareerInternal_SET""(varSystemLoginSession, null::bigint, null::varchar", CONCATENATE(IF(EXACT($K80, ""), ", null", CONCATENATE(", '", $K80, "'")), "::timestamptz"), CONCATENATE(IF(EXACT($L80, ""), ", null", CONCATENATE(", '", $L80, "'")), "::timestamptz"), ", null::varchar, varInstitutionBranchID, varBaseCurrencyID", CONCATENATE(IF(EXACT($B80, ""), ", null", CONCATENATE(", ", $B80, "")), "::bigint"), CONCATENATE(IF(EXACT($D80, ""), ", null", CONCATENATE(", ", $D80, "")), "::bigint"), CONCATENATE(IF(EXACT($F80, ""), ", null", CONCATENATE(", ", $F80, "")), "::bigint"), CONCATENATE(IF(EXACT($H80, ""), ", null", CONCATENATE(", ", $H80, "")), "::bigint"), CONCATENATE(IF(EXACT($J80, ""), ", null", CONCATENATE(", '", $J80, "'")), "::varchar"), CONCATENATE(IF(EXACT($K80, ""), ", null", CONCATENATE(", '", $K80, "'")), "::timestamptz"), CONCATENATE(IF(EXACT($L80, ""), ", null", CONCATENATE(", '", $L80, "'")), "::timestamptz"), CONCATENATE(IF(EXACT($M80, ""), ", null", CONCATENATE(", ", $M80, "")), "::bigint"), ");") -> PERFORM "SchData-OLTP-HumanResource"."Func_TblWorkerCareerInternal_SET"(varSystemLoginSession, null::bigint, null::varchar, '2010-03-01 00:00:00+07'::timestamptz, '2014-09-30 23:59:59+07'::timestamptz, null::varchar, varInstitutionBranchID, varBaseCurrencyID, 32000000000077::bigint, 163000000000003::bigint, 111000000000003::bigint, 160000000000003::bigint, null::varchar, '2010-03-01 00:00:00+07'::timestamptz, '2014-09-30 23:59:59+07'::timestamptz, null::bigint);
B81: =IF(EXACT(DataLookUp!$B81, ""), "", DataLookUp!$B81) -> 32000000000078 | C81: =MAIN!C81 -> Binsar | D81: 163000000000003 | E81: =IF(EXACT($D81, ""), "", VLOOKUP($D81, [2]DataLookUp!$B$4:$D$15, 2, FALSE )) -> Karyawan Tidak Tetap (Kontrak) | G81: =IF(EXACT($F81, ""), "", VLOOKUP($F81, 'MAIN - OrgDepartment'!$C$3:$D$104, 2, FALSE)) | I81: =IF(EXACT($H81, ""), "", VLOOKUP($H81, 'MAIN - OrgJobsPos'!$B$2:$C$101, 2, FALSE)) | L81: 1900-12-31 23:59:59+07 | O81: =O80 + IF(EXACT(P81, ""), 0, 1) -> 164000000000078 | P81: =CONCATENATE("PERFORM ""SchData-OLTP-HumanResource"".""Func_TblWorkerCareerInternal_SET""(varSystemLoginSession, null::bigint, null::varchar", CONCATENATE(IF(EXACT($K81, ""), ", null", CONCATENATE(", '", $K81, "'")), "::timestamptz"), CONCATENATE(IF(EXACT($L81, ""), ", null", CONCATENATE(", '", $L81, "'")), "::timestamptz"), ", null::varchar, varInstitutionBranchID, varBaseCurrencyID", CONCATENATE(IF(EXACT($B81, ""), ", null", CONCATENATE(", ", $B81, "")), "::bigint"), CONCATENATE(IF(EXACT($D81, ""), ", null", CONCATENATE(", ", $D81, "")), "::bigint"), CONCATENATE(IF(EXACT($F81, ""), ", null", CONCATENATE(", ", $F81, "")), "::bigint"), CONCATENATE(IF(EXACT($H81, ""), ", null", CONCATENATE(", ", $H81, "")), "::bigint"), CONCATENATE(IF(EXACT($J81, ""), ", null", CONCATENATE(", '", $J81, "'")), "::varchar"), CONCATENATE(IF(EXACT($K81, ""), ", null", CONCATENATE(", '", $K81, "'")), "::timestamptz"), CONCATENATE(IF(EXACT($L81, ""), ", null", CONCATENATE(", '", $L81, "'")), "::timestamptz"), CONCATENATE(IF(EXACT($M81, ""), ", null", CONCATENATE(", ", $M81, "")), "::bigint"), ");") -> PERFORM "SchData-OLTP-HumanResource"."Func_TblWorkerCareerInternal_SET"(varSystemLoginSession, null::bigint, null::varchar, null::timestamptz, '1900-12-31 23:59:59+07'::timestamptz, null::varchar, varInstitutionBranchID, varBaseCurrencyID, 32000000000078::bigint, 163000000000003::bigint, null::bigint, null::bigint, null::varchar, null::timestamptz, '1900-12-31 23:59:59+07'::timestamptz, null::bigint);
