Workbook

Sheet MAIN
B2: Ref ID Worker Career Internal | C2: Worker Name | D2: Ref ID User Role | E2: User Role Name | F2: Ref ID Combined Budget | H2: SYS_PID Prediction | I2: SQL Syntax
H3: 225000000000000
B4: =IF(EXACT('[1]DataLookUp - InternalCareer(LP)'!$B4, ""), "", '[1]DataLookUp - InternalCareer(LP)'!$B4) -> 164000000000001 | C4: =IF(EXACT($B4, ""), "", VLOOKUP(B4, '[1]DataLookUp - InternalCareer(LP)'!$B$4:$D$620, 3, FALSE)) -> Abdollah Syani Siregar | E4: =IF(EXACT($D4, ""), "", VLOOKUP($D4, [2]DataLookUp!$B$4:$C$84, 2, FALSE)) | H4: =H3 + IF(EXACT(I4, ""), 0, 1) -> 225000000000000 | I4: =IF(EXACT(D4, ""), "", CONCATENATE("PERFORM ""SchData-OLTP-HumanResource"".""Func_TblMapper_WorkerCareerInternalToUserRole_SET""(varSystemLoginSession, null::bigint, null::varchar, null::timestamptz, null::timestamptz, null::varchar, varInstitutionBranchID, varBaseCurrencyID, ", IF(EXACT(B4, ""), "null", B4), "::bigint, ", IF(EXACT(D4, ""), "null", D4), "::bigint, ", IF(EXACT(F4, ""), "null", F4), "::bigint);"))
B5: =IF(EXACT('[1]DataLookUp - InternalCareer(LP)'!$B5, ""), "", '[1]DataLookUp - InternalCareer(LP)'!$B5) -> 164000000000002 | C5: =IF(EXACT($B5, ""), "", VLOOKUP(B5, '[1]DataLookUp - InternalCareer(LP)'!$B$4:$D$620, 3, FALSE)) -> Abdul Karim | E5: =IF(EXACT($D5, ""), "", VLOOKUP($D5, [2]DataLookUp!$B$4:$C$84, 2, FALSE)) | H5: =H4 + IF(EXACT(I5, ""), 0, 1) -> 225000000000000 | I5: =IF(EXACT(D5, ""), "", CONCATENATE("PERFORM ""SchData-OLTP-HumanResource"".""Func_TblMapper_WorkerCareerInternalToUserRole_SET""(varSystemLoginSession, null::bigint, null::varchar, null::timestamptz, null::timestamptz, null::varchar, varInstitutionBranchID, varBaseCurrencyID, ", IF(EXACT(B5, ""), "null", B5), "::bigint, ", IF(EXACT(D5, ""), "null", D5), "::bigint, ", IF(EXACT(F5, ""), "null", F5), "::bigint);"))
B6: =IF(EXACT('[1]DataLookUp - InternalCareer(LP)'!$B6, ""), "", '[1]DataLookUp - InternalCareer(LP)'!$B6) -> 164000000000003 | C6: =IF(EXACT($B6, ""), "", VLOOKUP(B6, '[1]DataLookUp - InternalCareer(LP)'!$B$4:$D$620, 3, FALSE)) -> Abdul Rahman Sitompul | E6: =IF(EXACT($D6, ""), "", VLOOKUP($D6, [2]DataLookUp!$B$4:$C$84, 2, FALSE)) | H6: =H5 + IF(EXACT(I6, ""), 0, 1) -> 225000000000000 | I6: =IF(EXACT(D6, ""), "", CONCATENATE("PERFORM ""SchData-OLTP-HumanResource"".""Func_TblMapper_WorkerCareerInternalToUserRole_SET""(varSystemLoginSession, null::bigint, null::varchar, null::timestamptz, null::timestamptz, null::varchar, varInstitutionBranchID, varBaseCurrencyID, ", IF(EXACT(B6, ""), "null", B6), "::bigint, ", IF(EXACT(D6, ""), "null", D6), "::bigint, ", IF(EXACT(F6, ""), "null", F6), "::bigint);"))
B7: =IF(EXACT('[1]DataLookUp - InternalCareer(LP)'!$B7, ""), "", '[1]DataLookUp - InternalCareer(LP)'!$B7) -> 164000000000004 | C7: =IF(EXACT($B7, ""), "", VLOOKUP(B7, '[1]DataLookUp - InternalCareer(LP)'!$B$4:$D$620, 3, FALSE)) -> Abdul Risan | E7: =IF(EXACT($D7, ""), "", VLOOKUP($D7, [2]DataLookUp!$B$4:$C$84, 2, FALSE)) | H7: =H6 + IF(EXACT(I7, ""), 0, 1) -> 225000000000000 | I7: =IF(EXACT(D7, ""), "", CONCATENATE("PERFORM ""SchData-OLTP-HumanResource"".""Func_TblMapper_WorkerCareerInternalToUserRole_SET""(varSystemLoginSession, null::bigint, null::varchar, null::timestamptz, null::timestamptz, null::varchar, varInstitutionBranchID, varBaseCurrencyID, ", IF(EXACT(B7, ""), "null", B7), "::bigint, ", IF(EXACT(D7, ""), "null", D7), "::bigint, ", IF(EXACT(F7, ""), "null", F7), "::bigint);"))
B8: =IF(EXACT('[1]DataLookUp - InternalCareer(LP)'!$B8, ""), "", '[1]DataLookUp - InternalCareer(LP)'!$B8) -> 164000000000005 | C8: =IF(EXACT($B8, ""), "", VLOOKUP(B8, '[1]DataLookUp - InternalCareer(LP)'!$B$4:$D$620, 3, FALSE)) -> Abdullah Nabil | E8: =IF(EXACT($D8, ""), "", VLOOKUP($D8, [2]DataLookUp!$B$4:$C$84, 2, FALSE)) | H8: =H7 + IF(EXACT(I8, ""), 0, 1) -> 225000000000000 | I8: =IF(EXACT(D8, ""), "", CONCATENATE("PERFORM ""SchData-OLTP-HumanResource"".""Func_TblMapper_WorkerCareerInternalToUserRole_SET""(varSystemLoginSession, null::bigint, null::varchar, null::timestamptz, null::timestamptz, null::varchar, varInstitutionBranchID, varBaseCurrencyID, ", IF(EXACT(B8, ""), "null", B8), "::bigint, ", IF(EXACT(D8, ""), "null", D8), "::bigint, ", IF(EXACT(F8, ""), "null", F8), "::bigint);"))
B9: =IF(EXACT('[1]DataLookUp - InternalCareer(LP)'!$B9, ""), "", '[1]DataLookUp - InternalCareer(LP)'!$B9) -> 164000000000006 | C9: =IF(EXACT($B9, ""), "", VLOOKUP(B9, '[1]DataLookUp - InternalCareer(LP)'!$B$4:$D$620, 3, FALSE)) -> Adhitya Danar | E9: =IF(EXACT($D9, ""), "", VLOOKUP($D9, [2]DataLookUp!$B$4:$C$84, 2, FALSE)) | H9: =H8 + IF(EXACT(I9, ""), 0, 1) -> 225000000000000 | I9: =IF(EXACT(D9, ""), "", CONCATENATE("PERFORM ""SchData-OLTP-HumanResource"".""Func_TblMapper_WorkerCareerInternalToUserRole_SET""(varSystemLoginSession, null::bigint, null::varchar, null::timestamptz, null::timestamptz, null::varchar, varInstitutionBranchID, varBaseCurrencyID, ", IF(EXACT(B9, ""), "null", B9), "::bigint, ", IF(EXACT(D9, ""), "null", D9), "::bigint, ", IF(EXACT(F9, ""), "null", F9), "::bigint);"))
B10: =IF(EXACT('[1]DataLookUp - InternalCareer(LP)'!$B10, ""), "", '[1]DataLookUp - InternalCareer(LP)'!$B10) -> 164000000000007 | C10: =IF(EXACT($B10, ""), "", VLOOKUP(B10, '[1]DataLookUp - InternalCareer(LP)'!$B$4:$D$620, 3, FALSE)) -> Adi Ruswandi | E10: =IF(EXACT($D10, ""), "", VLOOKUP($D10, [2]DataLookUp!$B$4:$C$84, 2, FALSE)) | H10: =H9 + IF(EXACT(I10, ""), 0, 1) -> 225000000000000 | I10: =IF(EXACT(D10, ""), "", CONCATENATE("PERFORM ""SchData-OLTP-HumanResource"".""Func_TblMapper_WorkerCareerInternalToUserRole_SET""(varSystemLoginSession, null::bigint, null::varchar, null::timestamptz, null::timestamptz, null::varchar, varInstitutionBranchID, varBaseCurrencyID, ", IF(EXACT(B10, ""), "null", B10), "::bigint, ", IF(EXACT(D10, ""), "null", D10), "::bigint, ", IF(EXACT(F10, ""), "null", F10), "::bigint);"))
B11: =IF(EXACT('[1]DataLookUp - InternalCareer(LP)'!$B11, ""), "", '[1]DataLookUp - InternalCareer(LP)'!$B11) -> 164000000000008 | C11: =IF(EXACT($B11, ""), "", VLOOKUP(B11, '[1]DataLookUp - InternalCareer(LP)'!$B$4:$D$620, 3, FALSE)) -> Adietya Dharmawan | E11: =IF(EXACT($D11, ""), "", VLOOKUP($D11, [2]DataLookUp!$B$4:$C$84, 2, FALSE)) | H11: =H10 + IF(EXACT(I11, ""), 0, 1) -> 225000000000000 | I11: =IF(EXACT(D11, ""), "", CONCATENATE("PERFORM ""SchData-OLTP-HumanResource"".""Func_TblMapper_WorkerCareerInternalToUserRole_SET""(varSystemLoginSession, null::bigint, null::varchar, null::timestamptz, null::timestamptz, null::varchar, varInstitutionBranchID, varBaseCurrencyID, ", IF(EXACT(B11, ""), "null", B11), "::bigint, ", IF(EXACT(D11, ""), "null", D11), "::bigint, ", IF(EXACT(F11, ""), "null", F11), "::bigint);"))
B12: =IF(EXACT('[1]DataLookUp - InternalCareer(LP)'!$B12, ""), "", '[1]DataLookUp - InternalCareer(LP)'!$B12) -> 164000000000009 | C12: =IF(EXACT($B12, ""), "", VLOOKUP(B12, '[1]DataLookUp - InternalCareer(LP)'!$B$4:$D$620, 3, FALSE)) -> Aditya Yudha Prawira | E12: =IF(EXACT($D12, ""), "", VLOOKUP($D12, [2]DataLookUp!$B$4:$C$84, 2, FALSE)) | H12: =H11 + IF(EXACT(I12, ""), 0, 1) -> 225000000000000 | I12: =IF(EXACT(D12, ""), "", CONCATENATE("PERFORM ""SchData-OLTP-HumanResource"".""Func_TblMapper_WorkerCareerInternalToUserRole_SET""(varSystemLoginSession, null::bigint, null::varchar, null::timestamptz, null::timestamptz, null::varchar, varInstitutionBranchID, varBaseCurrencyID, ", IF(EXACT(B12, ""), "null", B12), "::bigint, ", IF(EXACT(D12, ""), "null", D12), "::bigint, ", IF(EXACT(F12, ""), "null", F12), "::bigint);"))
B13: =IF(EXACT('[1]DataLookUp - InternalCareer(LP)'!$B13, ""), "", '[1]DataLookUp - InternalCareer(LP)'!$B13) -> 164000000000010 | C13: =IF(EXACT($B13, ""), "", VLOOKUP(B13, '[1]DataLookUp - InternalCareer(LP)'!$B$4:$D$620, 3, FALSE)) -> Adli Margie | E13: =IF(EXACT($D13, ""), "", VLOOKUP($D13, [2]DataLookUp!$B$4:$C$84, 2, FALSE)) | H13: =H12 + IF(EXACT(I13, ""), 0, 1) -> 225000000000000 | I13: =IF(EXACT(D13, ""), "", CONCATENATE("PERFORM ""SchData-OLTP-HumanResource"".""Func_TblMapper_WorkerCareerInternalToUserRole_SET""(varSystemLoginSession, null::bigint, null::varchar, null::timestamptz, null::timestamptz, null::varchar, varInstitutionBranchID, varBaseCurrencyID, ", IF(EXACT(B13, ""), "null", B13), "::bigint, ", IF(EXACT(D13, ""), "null", D13), "::bigint, ", IF(EXACT(F13, ""), "null", F13), "::bigint);"))
B14: =IF(EXACT('[1]DataLookUp - InternalCareer(LP)'!$B14, ""), "", '[1]DataLookUp - InternalCareer(LP)'!$B14) -> 164000000000011 | C14: =IF(EXACT($B14, ""), "", VLOOKUP(B14, '[1]DataLookUp - InternalCareer(LP)'!$B$4:$D$620, 3, FALSE)) -> Afrida Eka Putri | E14: =IF(EXACT($D14, ""), "", VLOOKUP($D14, [2]DataLookUp!$B$4:$C$84, 2, FALSE)) | H14: =H13 + IF(EXACT(I14, ""), 0, 1) -> 225000000000000 | I14: =IF(EXACT(D14, ""), "", CONCATENATE("PERFORM ""SchData-OLTP-HumanResource"".""Func_TblMapper_WorkerCareerInternalToUserRole_SET""(varSystemLoginSession, null::bigint, null::varchar, null::timestamptz, null::timestamptz, null::varchar, varInstitutionBranchID, varBaseCurrencyID, ", IF(EXACT(B14, ""), "null", B14), "::bigint, ", IF(EXACT(D14, ""), "null", D14), "::bigint, ", IF(EXACT(F14, ""), "null", F14), "::bigint);"))
B15: =IF(EXACT('[1]DataLookUp - InternalCareer(LP)'!$B15, ""), "", '[1]DataLookUp - InternalCareer(LP)'!$B15) -> 164000000000012 | C15: =IF(EXACT($B15, ""), "", VLOOKUP(B15, '[1]DataLookUp - InternalCareer(LP)'!$B$4:$D$620, 3, FALSE)) -> Agnes Sutedja | D15: =[2]MAIN!$D$62 -> 95000000000048 | E15: =IF(EXACT($D15, ""), "", VLOOKUP($D15, [2]DataLookUp!$B$4:$C$84, 2, FALSE)) -> Health Safety Environment Manager | H15: =H14 + IF(EXACT(I15, ""), 0, 1) -> 225000000000001 | I15: =IF(EXACT(D15, ""), "", CONCATENATE("PERFORM ""SchData-OLTP-HumanResource"".""Func_TblMapper_WorkerCareerInternalToUserRole_SET""(varSystemLoginSession, null::bigint, null::varchar, null::timestamptz, null::timestamptz, null::varchar, varInstitutionBranchID, varBaseCurrencyID, ", IF(EXACT(B15, ""), "null", B15), "::bigint, ", IF(EXACT(D15, ""), "null", D15), "::bigint, ", IF(EXACT(F15, ""), "null", F15), "::bigint);")) -> PERFORM "SchData-OLTP-HumanResource"."Func_TblMapper_WorkerCareerInternalToUserRole_SET"(varSystemLoginSession, null::bigint, null::varchar, null::timestamptz, null::timestamptz, null::varchar, varInstitutionBranchID, varBaseCurrencyID, 164000000000012::bigint, 95000000000048::bigint, null::bigint);
B16: =IF(EXACT('[1]DataLookUp - InternalCareer(LP)'!$B16, ""), "", '[1]DataLookUp - InternalCareer(LP)'!$B16) -> 164000000000013 | C16: =IF(EXACT($B16, ""), "", VLOOKUP(B16, '[1]DataLookUp - InternalCareer(LP)'!$B$4:$D$620, 3, FALSE)) -> Agung Hendarto | E16: =IF(EXACT($D16, ""), "", VLOOKUP($D16, [2]DataLookUp!$B$4:$C$84, 2, FALSE)) | H16: =H15 + IF(EXACT(I16, ""), 0, 1) -> 225000000000001 | I16: =IF(EXACT(D16, ""), "", CONCATENATE("PERFORM ""SchData-OLTP-HumanResource"".""Func_TblMapper_WorkerCareerInternalToUserRole_SET""(varSystemLoginSession, null::bigint, null::varchar, null::timestamptz, null::timestamptz, null::varchar, varInstitutionBranchID, varBaseCurrencyID, ", IF(EXACT(B16, ""), "null", B16), "::bigint, ", IF(EXACT(D16, ""), "null", D16), "::bigint, ", IF(EXACT(F16, ""), "null", F16), "::bigint);"))
B17: =IF(EXACT('[1]DataLookUp - InternalCareer(LP)'!$B17, ""), "", '[1]DataLookUp - InternalCareer(LP)'!$B17) -> 164000000000014 | C17: =IF(EXACT($B17, ""), "", VLOOKUP(B17, '[1]DataLookUp - InternalCareer(LP)'!$B$4:$D$620, 3, FALSE)) -> Agus Priyatno Mahmudo | E17: =IF(EXACT($D17, ""), "", VLOOKUP($D17, [2]DataLookUp!$B$4:$C$84, 2, FALSE)) | H17: =H16 + IF(EXACT(I17, ""), 0, 1) -> 225000000000001 | I17: =IF(EXACT(D17, ""), "", CONCATENATE("PERFORM ""SchData-OLTP-HumanResource"".""Func_TblMapper_WorkerCareerInternalToUserRole_SET""(varSystemLoginSession, null::bigint, null::varchar, null::timestamptz, null::timestamptz, null::varchar, varInstitutionBranchID, varBaseCurrencyID, ", IF(EXACT(B17, ""), "null", B17), "::bigint, ", IF(EXACT(D17, ""), "null", D17), "::bigint, ", IF(EXACT(F17, ""), "null", F17), "::bigint);"))
B18: =IF(EXACT('[1]DataLookUp - InternalCareer(LP)'!$B18, ""), "", '[1]DataLookUp - InternalCareer(LP)'!$B18) -> 164000000000015 | C18: =IF(EXACT($B18, ""), "", VLOOKUP(B18, '[1]DataLookUp - InternalCareer(LP)'!$B$4:$D$620, 3, FALSE)) -> Agus Salim | E18: =IF(EXACT($D18, ""), "", VLOOKUP($D18, [2]DataLookUp!$B$4:$C$84, 2, FALSE)) | H18: =H17 + IF(EXACT(I18, ""), 0, 1) -> 225000000000001 | I18: =IF(EXACT(D18, ""), "", CONCATENATE("PERFORM ""SchData-OLTP-HumanResource"".""Func_TblMapper_WorkerCareerInternalToUserRole_SET""(varSystemLoginSession, null::bigint, null::varchar, null::timestamptz, null::timestamptz, null::varchar, varInstitutionBranchID, varBaseCurrencyID, ", IF(EXACT(B18, ""), "null", B18), "::bigint, ", IF(EXACT(D18, ""), "null", D18), "::bigint, ", IF(EXACT(F18, ""), "null", F18), "::bigint);"))
B19: =IF(EXACT('[1]DataLookUp - InternalCareer(LP)'!$B19, ""), "", '[1]DataLookUp - InternalCareer(LP)'!$B19) -> 164000000000016 | C19: =IF(EXACT($B19, ""), "", VLOOKUP(B19, '[1]DataLookUp - InternalCareer(LP)'!$B$4:$D$620, 3, FALSE)) -> Agus Tanto | E19: =IF(EXACT($D19, ""), "", VLOOKUP($D19, [2]DataLookUp!$B$4:$C$84, 2, FALSE)) | H19: =H18 + IF(EXACT(I19, ""), 0, 1) -> 225000000000001 | I19: =IF(EXACT(D19, ""), "", CONCATENATE("PERFORM ""SchData-OLTP-HumanResource"".""Func_TblMapper_WorkerCareerInternalToUserRole_SET""(varSystemLoginSession, null::bigint, null::varchar, null::timestamptz, null::timestamptz, null::varchar, varInstitutionBranchID, varBaseCurrencyID, ", IF(EXACT(B19, ""), "null", B19), "::bigint, ", IF(EXACT(D19, ""), "null", D19), "::bigint, ", IF(EXACT(F19, ""), "null", F19), "::bigint);"))
B20: =IF(EXACT('[1]DataLookUp - InternalCareer(LP)'!$B20, ""), "", '[1]DataLookUp - InternalCareer(LP)'!$B20) -> 164000000000017 | C20: =IF(EXACT($B20, ""), "", VLOOKUP(B20, '[1]DataLookUp - InternalCareer(LP)'!$B$4:$D$620, 3, FALSE)) -> Ahmad Faiz Haems Muda | D20: =[2]MAIN!$D$24 -> 95000000000017 | E20: =IF(EXACT($D20, ""), "", VLOOKUP($D20, [2]DataLookUp!$B$4:$C$84, 2, FALSE)) -> HR, GA, & TAM General Manager | H20: =H19 + IF(EXACT(I20, ""), 0, 1) -> 225000000000002 | I20: =IF(EXACT(D20, ""), "", CONCATENATE("PERFORM ""SchData-OLTP-HumanResource"".""Func_TblMapper_WorkerCareerInternalToUserRole_SET""(varSystemLoginSession, null::bigint, null::varchar, null::timestamptz, null::timestamptz, null::varchar, varInstitutionBranchID, varBaseCurrencyID, ", IF(EXACT(B20, ""), "null", B20), "::bigint, ", IF(EXACT(D20, ""), "null", D20), "::bigint, ", IF(EXACT(F20, ""), "null", F20), "::bigint);")) -> PERFORM "SchData-OLTP-HumanResource"."Func_TblMapper_WorkerCareerInternalToUserRole_SET"(varSystemLoginSession, null::bigint, null::varchar, null::timestamptz, null::timestamptz, null::varchar, varInstitutionBranchID, varBaseCurrencyID, 164000000000017::bigint, 95000000000017::bigint, null::bigint);
B21: =IF(EXACT('[1]DataLookUp - InternalCareer(LP)'!$B21, ""), "", '[1]DataLookUp - InternalCareer(LP)'!$B21) -> 164000000000018 | C21: =IF(EXACT($B21, ""), "", VLOOKUP(B21, '[1]DataLookUp - InternalCareer(LP)'!$B$4:$D$620, 3, FALSE)) -> Ahmad Faza | E21: =IF(EXACT($D21, ""), "", VLOOKUP($D21, [2]DataLookUp!$B$4:$C$84, 2, FALSE)) | H21: =H20 + IF(EXACT(I21, ""), 0, 1) -> 225000000000002 | I21: =IF(EXACT(D21, ""), "", CONCATENATE("PERFORM ""SchData-OLTP-HumanResource"".""Func_TblMapper_WorkerCareerInternalToUserRole_SET""(varSystemLoginSession, null::bigint, null::varchar, null::timestamptz, null::timestamptz, null::varchar, varInstitutionBranchID, varBaseCurrencyID, ", IF(EXACT(B21, ""), "null", B21), "::bigint, ", IF(EXACT(D21, ""), "null", D21), "::bigint, ", IF(EXACT(F21, ""), "null", F21), "::bigint);"))
B22: =IF(EXACT('[1]DataLookUp - InternalCareer(LP)'!$B22, ""), "", '[1]DataLookUp - InternalCareer(LP)'!$B22) -> 164000000000019 | C22: =IF(EXACT($B22, ""), "", VLOOKUP(B22, '[1]DataLookUp - InternalCareer(LP)'!$B$4:$D$620, 3, FALSE)) -> Ahmad Syaifulloh | E22: =IF(EXACT($D22, ""), "", VLOOKUP($D22, [2]DataLookUp!$B$4:$C$84, 2, FALSE)) | H22: =H21 + IF(EXACT(I22, ""), 0, 1) -> 225000000000002 | I22: =IF(EXACT(D22, ""), "", CONCATENATE("PERFORM ""SchData-OLTP-HumanResource"".""Func_TblMapper_WorkerCareerInternalToUserRole_SET""(varSystemLoginSession, null::bigint, null::varchar, null::timestamptz, null::timestamptz, null::varchar, varInstitutionBranchID, varBaseCurrencyID, ", IF(EXACT(B22, ""), "null", B22), "::bigint, ", IF(EXACT(D22, ""), "null", D22), "::bigint, ", IF(EXACT(F22, ""), "null", F22), "::bigint);"))
B23: =IF(EXACT('[1]DataLookUp - InternalCareer(LP)'!$B23, ""), "", '[1]DataLookUp - InternalCareer(LP)'!$B23) -> 164000000000020 | C23: =IF(EXACT($B23, ""), "", VLOOKUP(B23, '[1]DataLookUp - InternalCareer(LP)'!$B$4:$D$620, 3, FALSE)) -> Ahmad Zulkarnaen | E23: =IF(EXACT($D23, ""), "", VLOOKUP($D23, [2]DataLookUp!$B$4:$C$84, 2, FALSE)) | H23: =H22 + IF(EXACT(I23, ""), 0, 1) -> 225000000000002 | I23: =IF(EXACT(D23, ""), "", CONCATENATE("PERFORM ""SchData-OLTP-HumanResource"".""Func_TblMapper_WorkerCareerInternalToUserRole_SET""(varSystemLoginSession, null::bigint, null::varchar, null::timestamptz, null::timestamptz, null::varchar, varInstitutionBranchID, varBaseCurrencyID, ", IF(EXACT(B23, ""), "null", B23), "::bigint, ", IF(EXACT(D23, ""), "null", D23), "::bigint, ", IF(EXACT(F23, ""), "null", F23), "::bigint);"))
B24: =IF(EXACT('[1]DataLookUp - InternalCareer(LP)'!$B24, ""), "", '[1]DataLookUp - InternalCareer(LP)'!$B24) -> 164000000000021 | C24: =IF(EXACT($B24, ""), "", VLOOKUP(B24, '[1]DataLookUp - InternalCareer(LP)'!$B$4:$D$620, 3, FALSE)) -> Ajan | E24: =IF(EXACT($D24, ""), "", VLOOKUP($D24, [2]DataLookUp!$B$4:$C$84, 2, FALSE)) | H24: =H23 + IF(EXACT(I24, ""), 0, 1) -> 225000000000002 | I24: =IF(EXACT(D24, ""), "", CONCATENATE("PERFORM ""SchData-OLTP-HumanResource"".""Func_TblMapper_WorkerCareerInternalToUserRole_SET""(varSystemLoginSession, null::bigint, null::varchar, null::timestamptz, null::timestamptz, null::varchar, varInstitutionBranchID, varBaseCurrencyID, ", IF(EXACT(B24, ""), "null", B24), "::bigint, ", IF(EXACT(D24, ""), "null", D24), "::bigint, ", IF(EXACT(F24, ""), "null", F24), "::bigint);"))
B25: =IF(EXACT('[1]DataLookUp - InternalCareer(LP)'!$B25, ""), "", '[1]DataLookUp - InternalCareer(LP)'!$B25) -> 164000000000022 | C25: =IF(EXACT($B25, ""), "", VLOOKUP(B25, '[1]DataLookUp - InternalCareer(LP)'!$B$4:$D$620, 3, FALSE)) -> Al Amin | E25: =IF(EXACT($D25, ""), "", VLOOKUP($D25, [2]DataLookUp!$B$4:$C$84, 2, FALSE)) | H25: =H24 + IF(EXACT(I25, ""), 0, 1) -> 225000000000002 | I25: =IF(EXACT(D25, ""), "", CONCATENATE("PERFORM ""SchData-OLTP-HumanResource"".""Func_TblMapper_WorkerCareerInternalToUserRole_SET""(varSystemLoginSession, null::bigint, null::varchar, null::timestamptz, null::timestamptz, null::varchar, varInstitutionBranchID, varBaseCurrencyID, ", IF(EXACT(B25, ""), "null", B25), "::bigint, ", IF(EXACT(D25, ""), "null", D25), "::bigint, ", IF(EXACT(F25, ""), "null", F25), "::bigint);"))
B26: =IF(EXACT('[1]DataLookUp - InternalCareer(LP)'!$B26, ""), "", '[1]DataLookUp - InternalCareer(LP)'!$B26) -> 164000000000023 | C26: =IF(EXACT($B26, ""), "", VLOOKUP(B26, '[1]DataLookUp - InternalCareer(LP)'!$B$4:$D$620, 3, FALSE)) -> Aldi Mulyadi | D26: =[2]MAIN!$D$50 -> 95000000000039 | E26: =IF(EXACT($D26, ""), "", VLOOKUP($D26, [2]DataLookUp!$B$4:$C$84, 2, FALSE)) -> IT Software Engineer Staff | H26: =H25 + IF(EXACT(I26, ""), 0, 1) -> 225000000000003 | I26: =IF(EXACT(D26, ""), "", CONCATENATE("PERFORM ""SchData-OLTP-HumanResource"".""Func_TblMapper_WorkerCareerInternalToUserRole_SET""(varSystemLoginSession, null::bigint, null::varchar, null::timestamptz, null::timestamptz, null::varchar, varInstitutionBranchID, varBaseCurrencyID, ", IF(EXACT(B26, ""), "null", B26), "::bigint, ", IF(EXACT(D26, ""), "null", D26), "::bigint, ", IF(EXACT(F26, ""), "null", F26), "::bigint);")) -> PERFORM "SchData-OLTP-HumanResource"."Func_TblMapper_WorkerCareerInternalToUserRole_SET"(varSystemLoginSession, null::bigint, null::varchar, null::timestamptz, null::timestamptz, null::varchar, varInstitutionBranchID, varBaseCurrencyID, 164000000000023::bigint, 95000000000039::bigint, null::bigint);
B27: =IF(EXACT('[1]DataLookUp - InternalCareer(LP)'!$B27, ""), "", '[1]DataLookUp - InternalCareer(LP)'!$B27) -> 164000000000024 | C27: =IF(EXACT($B27, ""), "", VLOOKUP(B27, '[1]DataLookUp - InternalCareer(LP)'!$B$4:$D$620, 3, FALSE)) -> Alexandri | E27: =IF(EXACT($D27, ""), "", VLOOKUP($D27, [2]DataLookUp!$B$4:$C$84, 2, FALSE)) | H27: =H26 + IF(EXACT(I27, ""), 0, 1) -> 225000000000003 | I27: =IF(EXACT(D27, ""), "", CONCATENATE("PERFORM ""SchData-OLTP-HumanResource"".""Func_TblMapper_WorkerCareerInternalToUserRole_SET""(varSystemLoginSession, null::bigint, null::varchar, null::timestamptz, null::timestamptz, null::varchar, varInstitutionBranchID, varBaseCurrencyID, ", IF(EXACT(B27, ""), "null", B27), "::bigint, ", IF(EXACT(D27, ""), "null", D27), "::bigint, ", IF(EXACT(F27, ""), "null", F27), "::bigint);"))
B28: =IF(EXACT('[1]DataLookUp - InternalCareer(LP)'!$B28, ""), "", '[1]DataLookUp - InternalCareer(LP)'!$B28) -> 164000000000025 | C28: =IF(EXACT($B28, ""), "", VLOOKUP(B28, '[1]DataLookUp - InternalCareer(LP)'!$B$4:$D$620, 3, FALSE)) -> Alfaedi | E28: =IF(EXACT($D28, ""), "", VLOOKUP($D28, [2]DataLookUp!$B$4:$C$84, 2, FALSE)) | H28: =H27 + IF(EXACT(I28, ""), 0, 1) -> 225000000000003 | I28: =IF(EXACT(D28, ""), "", CONCATENATE("PERFORM ""SchData-OLTP-HumanResource"".""Func_TblMapper_WorkerCareerInternalToUserRole_SET""(varSystemLoginSession, null::bigint, null::varchar, null::timestamptz, null::timestamptz, null::varchar, varInstitutionBranchID, varBaseCurrencyID, ", IF(EXACT(B28, ""), "null", B28), "::bigint, ", IF(EXACT(D28, ""), "null", D28), "::bigint, ", IF(EXACT(F28, ""), "null", F28), "::bigint);"))
B29: =IF(EXACT('[1]DataLookUp - InternalCareer(LP)'!$B29, ""), "", '[1]DataLookUp - InternalCareer(LP)'!$B29) -> 164000000000026 | C29: =IF(EXACT($B29, ""), "", VLOOKUP(B29, '[1]DataLookUp - InternalCareer(LP)'!$B$4:$D$620, 3, FALSE)) -> Ali Wahono | E29: =IF(EXACT($D29, ""), "", VLOOKUP($D29, [2]DataLookUp!$B$4:$C$84, 2, FALSE)) | H29: =H28 + IF(EXACT(I29, ""), 0, 1) -> 225000000000003 | I29: =IF(EXACT(D29, ""), "", CONCATENATE("PERFORM ""SchData-OLTP-HumanResource"".""Func_TblMapper_WorkerCareerInternalToUserRole_SET""(varSystemLoginSession, null::bigint, null::varchar, null::timestamptz, null::timestamptz, null::varchar, varInstitutionBranchID, varBaseCurrencyID, ", IF(EXACT(B29, ""), "null", B29), "::bigint, ", IF(EXACT(D29, ""), "null", D29), "::bigint, ", IF(EXACT(F29, ""), "null", F29), "::bigint);"))
B30: =IF(EXACT('[1]DataLookUp - InternalCareer(LP)'!$B30, ""), "", '[1]DataLookUp - InternalCareer(LP)'!$B30) -> 164000000000027 | C30: =IF(EXACT($B30, ""), "", VLOOKUP(B30, '[1]DataLookUp - InternalCareer(LP)'!$B$4:$D$620, 3, FALSE)) -> Alphaliyanri Lasria | E30: =IF(EXACT($D30, ""), "", VLOOKUP($D30, [2]DataLookUp!$B$4:$C$84, 2, FALSE)) | H30: =H29 + IF(EXACT(I30, ""), 0, 1) -> 225000000000003 | I30: =IF(EXACT(D30, ""), "", CONCATENATE("PERFORM ""SchData-OLTP-HumanResource"".""Func_TblMapper_WorkerCareerInternalToUserRole_SET""(varSystemLoginSession, null::bigint, null::varchar, null::timestamptz, null::timestamptz, null::varchar, varInstitutionBranchID, varBaseCurrencyID, ", IF(EXACT(B30, ""), "null", B30), "::bigint, ", IF(EXACT(D30, ""), "null", D30), "::bigint, ", IF(EXACT(F30, ""), "null", F30), "::bigint);"))
B31: =IF(EXACT('[1]DataLookUp - InternalCareer(LP)'!$B31, ""), "", '[1]DataLookUp - InternalCareer(LP)'!$B31) -> 164000000000028 | C31: =IF(EXACT($B31, ""), "", VLOOKUP(B31, '[1]DataLookUp - InternalCareer(LP)'!$B$4:$D$620, 3, FALSE)) -> Ambon Rumalean | E31: =IF(EXACT($D31, ""), "", VLOOKUP($D31, [2]DataLookUp!$B$4:$C$84, 2, FALSE)) | H31: =H30 + IF(EXACT(I31, ""), 0, 1) -> 225000000000003 | I31: =IF(EXACT(D31, ""), "", CONCATENATE("PERFORM ""SchData-OLTP-HumanResource"".""Func_TblMapper_WorkerCareerInternalToUserRole_SET""(varSystemLoginSession, null::bigint, null::varchar, null::timestamptz, null::timestamptz, null::varchar, varInstitutionBranchID, varBaseCurrencyID, ", IF(EXACT(B31, ""), "null", B31), "::bigint, ", IF(EXACT(D31, ""), "null", D31), "::bigint, ", IF(EXACT(F31, ""), "null", F31), "::bigint);"))
B32: =IF(EXACT('[1]DataLookUp - InternalCareer(LP)'!$B32, ""), "", '[1]DataLookUp - InternalCareer(LP)'!$B32) -> 164000000000029 | C32: =IF(EXACT($B32, ""), "", VLOOKUP(B32, '[1]DataLookUp - InternalCareer(LP)'!$B$4:$D$620, 3, FALSE)) -> Amir Sofyan Hadi | E32: =IF(EXACT($D32, ""), "", VLOOKUP($D32, [2]DataLookUp!$B$4:$C$84, 2, FALSE)) | H32: =H31 + IF(EXACT(I32, ""), 0, 1) -> 225000000000003 | I32: =IF(EXACT(D32, ""), "", CONCATENATE("PERFORM ""SchData-OLTP-HumanResource"".""Func_TblMapper_WorkerCareerInternalToUserRole_SET""(varSystemLoginSession, null::bigint, null::varchar, null::timestamptz, null::timestamptz, null::varchar, varInstitutionBranchID, varBaseCurrencyID, ", IF(EXACT(B32, ""), "null", B32), "::bigint, ", IF(EXACT(D32, ""), "null", D32), "::bigint, ", IF(EXACT(F32, ""), "null", F32), "::bigint);"))
B33: =IF(EXACT('[1]DataLookUp - InternalCareer(LP)'!$B33, ""), "", '[1]DataLookUp - InternalCareer(LP)'!$B33) -> 164000000000030 | C33: =IF(EXACT($B33, ""), "", VLOOKUP(B33, '[1]DataLookUp - InternalCareer(LP)'!$B$4:$D$620, 3, FALSE)) -> Anak Agung Netti Ariani | E33: =IF(EXACT($D33, ""), "", VLOOKUP($D33, [2]DataLookUp!$B$4:$C$84, 2, FALSE)) | H33: =H32 + IF(EXACT(I33, ""), 0, 1) -> 225000000000003 | I33: =IF(EXACT(D33, ""), "", CONCATENATE("PERFORM ""SchData-OLTP-HumanResource"".""Func_TblMapper_WorkerCareerInternalToUserRole_SET""(varSystemLoginSession, null::bigint, null::varchar, null::timestamptz, null::timestamptz, null::varchar, varInstitutionBranchID, varBaseCurrencyID, ", IF(EXACT(B33, ""), "null", B33), "::bigint, ", IF(EXACT(D33, ""), "null", D33), "::bigint, ", IF(EXACT(F33, ""), "null", F33), "::bigint);"))
B34: =IF(EXACT('[1]DataLookUp - InternalCareer(LP)'!$B34, ""), "", '[1]DataLookUp - InternalCareer(LP)'!$B34) -> 164000000000031 | C34: =IF(EXACT($B34, ""), "", VLOOKUP(B34, '[1]DataLookUp - InternalCareer(LP)'!$B$4:$D$620, 3, FALSE)) -> Andri Gunawan | E34: =IF(EXACT($D34, ""), "", VLOOKUP($D34, [2]DataLookUp!$B$4:$C$84, 2, FALSE)) | H34: =H33 + IF(EXACT(I34, ""), 0, 1) -> 225000000000003 | I34: =IF(EXACT(D34, ""), "", CONCATENATE("PERFORM ""SchData-OLTP-HumanResource"".""Func_TblMapper_WorkerCareerInternalToUserRole_SET""(varSystemLoginSession, null::bigint, null::varchar, null::timestamptz, null::timestamptz, null::varchar, varInstitutionBranchID, varBaseCurrencyID, ", IF(EXACT(B34, ""), "null", B34), "::bigint, ", IF(EXACT(D34, ""), "null", D34), "::bigint, ", IF(EXACT(F34, ""), "null", F34), "::bigint);"))
B35: =IF(EXACT('[1]DataLookUp - InternalCareer(LP)'!$B35, ""), "", '[1]DataLookUp - InternalCareer(LP)'!$B35) -> 164000000000032 | C35: =IF(EXACT($B35, ""), "", VLOOKUP(B35, '[1]DataLookUp - InternalCareer(LP)'!$B$4:$D$620, 3, FALSE)) -> Andri Herdiansyah | E35: =IF(EXACT($D35, ""), "", VLOOKUP($D35, [2]DataLookUp!$B$4:$C$84, 2, FALSE)) | H35: =H34 + IF(EXACT(I35, ""), 0, 1) -> 225000000000003 | I35: =IF(EXACT(D35, ""), "", CONCATENATE("PERFORM ""SchData-OLTP-HumanResource"".""Func_TblMapper_WorkerCareerInternalToUserRole_SET""(varSystemLoginSession, null::bigint, null::varchar, null::timestamptz, null::timestamptz, null::varchar, varInstitutionBranchID, varBaseCurrencyID, ", IF(EXACT(B35, ""), "null", B35), "::bigint, ", IF(EXACT(D35, ""), "null", D35), "::bigint, ", IF(EXACT(F35, ""), "null", F35), "::bigint);"))
B36: =IF(EXACT('[1]DataLookUp - InternalCareer(LP)'!$B36, ""), "", '[1]DataLookUp - InternalCareer(LP)'!$B36) -> 164000000000033 | C36: =IF(EXACT($B36, ""), "", VLOOKUP(B36, '[1]DataLookUp - InternalCareer(LP)'!$B$4:$D$620, 3, FALSE)) -> Andrie | E36: =IF(EXACT($D36, ""), "", VLOOKUP($D36, [2]DataLookUp!$B$4:$C$84, 2, FALSE)) | H36: =H35 + IF(EXACT(I36, ""), 0, 1) -> 225000000000003 | I36: =IF(EXACT(D36, ""), "", CONCATENATE("PERFORM ""SchData-OLTP-HumanResource"".""Func_TblMapper_WorkerCareerInternalToUserRole_SET""(varSystemLoginSession, null::bigint, null::varchar, null::timestamptz, null::timestamptz, null::varchar, varInstitutionBranchID, varBaseCurrencyID, ", IF(EXACT(B36, ""), "null", B36), "::bigint, ", IF(EXACT(D36, ""), "null", D36), "::bigint, ", IF(EXACT(F36, ""), "null", F36), "::bigint);"))
B37: =IF(EXACT('[1]DataLookUp - InternalCareer(LP)'!$B37, ""), "", '[1]DataLookUp - InternalCareer(LP)'!$B37) -> 164000000000034 | C37: =IF(EXACT($B37, ""), "", VLOOKUP(B37, '[1]DataLookUp - InternalCareer(LP)'!$B$4:$D$620, 3, FALSE)) -> Anggina Tri Yudandi | E37: =IF(EXACT($D37, ""), "", VLOOKUP($D37, [2]DataLookUp!$B$4:$C$84, 2, FALSE)) | H37: =H36 + IF(EXACT(I37, ""), 0, 1) -> 225000000000003 | I37: =IF(EXACT(D37, ""), "", CONCATENATE("PERFORM ""SchData-OLTP-HumanResource"".""Func_TblMapper_WorkerCareerInternalToUserRole_SET""(varSystemLoginSession, null::bigint, null::varchar, null::timestamptz, null::timestamptz, null::varchar, varInstitutionBranchID, varBaseCurrencyID, ", IF(EXACT(B37, ""), "null", B37), "::bigint, ", IF(EXACT(D37, ""), "null", D37), "::bigint, ", IF(EXACT(F37, ""), "null", F37), "::bigint);"))
B38: =IF(EXACT('[1]DataLookUp - InternalCareer(LP)'!$B38, ""), "", '[1]DataLookUp - InternalCareer(LP)'!$B38) -> 164000000000035 | C38: =IF(EXACT($B38, ""), "", VLOOKUP(B38, '[1]DataLookUp - InternalCareer(LP)'!$B$4:$D$620, 3, FALSE)) -> Anggit Ismiyanto | E38: =IF(EXACT($D38, ""), "", VLOOKUP($D38, [2]DataLookUp!$B$4:$C$84, 2, FALSE)) | H38: =H37 + IF(EXACT(I38, ""), 0, 1) -> 225000000000003 | I38: =IF(EXACT(D38, ""), "", CONCATENATE("PERFORM ""SchData-OLTP-HumanResource"".""Func_TblMapper_WorkerCareerInternalToUserRole_SET""(varSystemLoginSession, null::bigint, null::varchar, null::timestamptz, null::timestamptz, null::varchar, varInstitutionBranchID, varBaseCurrencyID, ", IF(EXACT(B38, ""), "null", B38), "::bigint, ", IF(EXACT(D38, ""), "null", D38), "::bigint, ", IF(EXACT(F38, ""), "null", F38), "::bigint);"))
... B77: =IF(EXACT('[1]DataLookUp - InternalCareer(LP)'!$B77, ""), "", '[1]DataLookUp - InternalCareer(LP)'!$B77) -> 164000000000074 | C77: =IF(EXACT($B77, ""), "", VLOOKUP(B77, '[1]DataLookUp - InternalCareer(LP)'!$B$4:$D$620, 3, FALSE)) -> Bela Retmalantika | E77: =IF(EXACT($D77, ""), "", VLOOKUP($D77, [2]DataLookUp!$B$4:$C$84, 2, FALSE)) | H77: =H76 + IF(EXACT(I77, ""), 0, 1) -> 225000000000003 | I77: =IF(EXACT(D77, ""), "", CONCATENATE("PERFORM ""SchData-OLTP-HumanResource"".""Func_TblMapper_WorkerCareerInternalToUserRole_SET""(varSystemLoginSession, null::bigint, null::varchar, null::timestamptz, null::timestamptz, null::varchar, varInstitutionBranchID, varBaseCurrencyID, ", IF(EXACT(B77, ""), "null", B77), "::bigint, ", IF(EXACT(D77, ""), "null", D77), "::bigint, ", IF(EXACT(F77, ""), "null", F77), "::bigint);"))
B78: =IF(EXACT('[1]DataLookUp - InternalCareer(LP)'!$B78, ""), "", '[1]DataLookUp - InternalCareer(LP)'!$B78) -> 164000000000075 | C78: =IF(EXACT($B78, ""), "", VLOOKUP(B78, '[1]DataLookUp - InternalCareer(LP)'!$B$4:$D$620, 3, FALSE)) -> Belina Lindarwani | D78: =[2]MAIN!$D$44 -> 95000000000034 | E78: =IF(EXACT($D78, ""), "", VLOOKUP($D78, [2]DataLookUp!$B$4:$C$84, 2, FALSE)) -> Accounting & Tax Staff | H78: =H77 + IF(EXACT(I78, ""), 0, 1) -> 225000000000004 | I78: =IF(EXACT(D78, ""), "", CONCATENATE("PERFORM ""SchData-OLTP-HumanResource"".""Func_TblMapper_WorkerCareerInternalToUserRole_SET""(varSystemLoginSession, null::bigint, null::varchar, null::timestamptz, null::timestamptz, null::varchar, varInstitutionBranchID, varBaseCurrencyID, ", IF(EXACT(B78, ""), "null", B78), "::bigint, ", IF(EXACT(D78, ""), "null", D78), "::bigint, ", IF(EXACT(F78, ""), "null", F78), "::bigint);")) -> PERFORM "SchData-OLTP-HumanResource"."Func_TblMapper_WorkerCareerInternalToUserRole_SET"(varSystemLoginSession, null::bigint, null::varchar, null::timestamptz, null::timestamptz, null::varchar, varInstitutionBranchID, varBaseCurrencyID, 164000000000075::bigint, 95000000000034::bigint, null::bigint);
B79: =IF(EXACT('[1]DataLookUp - InternalCareer(LP)'!$B79, ""), "", '[1]DataLookUp - InternalCareer(LP)'!$B79) -> 164000000000076 | C79: =IF(EXACT($B79, ""), "", VLOOKUP(B79, '[1]DataLookUp - InternalCareer(LP)'!$B$4:$D$620, 3, FALSE)) -> Benita Sofia | E79: =IF(EXACT($D79, ""), "", VLOOKUP($D79, [2]DataLookUp!$B$4:$C$84, 2, FALSE)) | H79: =H78 + IF(EXACT(I79, ""), 0, 1) -> 225000000000004 | I79: =IF(EXACT(D79, ""), "", CONCATENATE("PERFORM ""SchData-OLTP-HumanResource"".""Func_TblMapper_WorkerCareerInternalToUserRole_SET""(varSystemLoginSession, null::bigint, null::varchar, null::timestamptz, null::timestamptz, null::varchar, varInstitutionBranchID, varBaseCurrencyID, ", IF(EXACT(B79, ""), "null", B79), "::bigint, ", IF(EXACT(D79, ""), "null", D79), "::bigint, ", IF(EXACT(F79, ""), "null", F79), "::bigint);"))
B80: =IF(EXACT('[1]DataLookUp - InternalCareer(LP)'!$B80, ""), "", '[1]DataLookUp - InternalCareer(LP)'!$B80) -> 164000000000077 | C80: =IF(EXACT($B80, ""), "", VLOOKUP(B80, '[1]DataLookUp - InternalCareer(LP)'!$B$4:$D$620, 3, FALSE)) -> Bherly Novrandy | E80: =IF(EXACT($D80, ""), "", VLOOKUP($D80, [2]DataLookUp!$B$4:$C$84, 2, FALSE)) | H80: =H79 + IF(EXACT(I80, ""), 0, 1) -> 225000000000004 | I80: =IF(EXACT(D80, ""), "", CONCATENATE("PERFORM ""SchData-OLTP-HumanResource"".""Func_TblMapper_WorkerCareerInternalToUserRole_SET""(varSystemLoginSession, null::bigint, null::varchar, null::timestamptz, null::timestamptz, null::varchar, varInstitutionBranchID, varBaseCurrencyID, ", IF(EXACT(B80, ""), "null", B80), "::bigint, ", IF(EXACT(D80, ""), "null", D80), "::bigint, ", IF(EXACT(F80, ""), "null", F80), "::bigint);"))
B81: =IF(EXACT('[1]DataLookUp - InternalCareer(LP)'!$B81, ""), "", '[1]DataLookUp - InternalCareer(LP)'!$B81) -> 164000000000078 | C81: =IF(EXACT($B81, ""), "", VLOOKUP(B81, '[1]DataLookUp - InternalCareer(LP)'!$B$4:$D$620, 3, FALSE)) -> Binsar | E81: =IF(EXACT($D81, ""), "", VLOOKUP($D81, [2]DataLookUp!$B$4:$C$84, 2, FALSE)) | H81: =H80 + IF(EXACT(I81, ""), 0, 1) -> 225000000000004 | I81: =IF(EXACT(D81, ""), "", CONCATENATE("PERFORM ""SchData-OLTP-HumanResource"".""Func_TblMapper_WorkerCareerInternalToUserRole_SET""(varSystemLoginSession, null::bigint, null::varchar, null::timestamptz, null::timestamptz, null::varchar, varInstitutionBranchID, varBaseCurrencyID, ", IF(EXACT(B81, ""), "null", B81), "::bigint, ", IF(EXACT(D81, ""), "null", D81), "::bigint, ", IF(EXACT(F81, ""), "null", F81), "::bigint);"))
B82: =IF(EXACT('[1]DataLookUp - InternalCareer(LP)'!$B82, ""), "", '[1]DataLookUp - InternalCareer(LP)'!$B82) -> 164000000000079 | C82: =IF(EXACT($B82, ""), "", VLOOKUP(B82, '[1]DataLookUp - InternalCareer(LP)'!$B$4:$D$620, 3, FALSE)) -> Bondhan Sosiarta | E82: =IF(EXACT($D82, ""), "", VLOOKUP($D82, [2]DataLookUp!$B$4:$C$84, 2, FALSE)) | H82: =H81 + IF(EXACT(I82, ""), 0, 1) -> 225000000000004 | I82: =IF(EXACT(D82, ""), "", CONCATENATE("PERFORM ""SchData-OLTP-HumanResource"".""Func_TblMapper_WorkerCareerInternalToUserRole_SET""(varSystemLoginSession, null::bigint, null::varchar, null::timestamptz, null::timestamptz, null::varchar, varInstitutionBranchID, varBaseCurrencyID, ", IF(EXACT(B82, ""), "null", B82), "::bigint, ", IF(EXACT(D82, ""), "null", D82), "::bigint, ", IF(EXACT(F82, ""), "null", F82), "::bigint);"))
B83: =IF(EXACT('[1]DataLookUp - InternalCareer(LP)'!$B83, ""), "", '[1]DataLookUp - InternalCareer(LP)'!$B83) -> 164000000000080 | C83: =IF(EXACT($B83, ""), "", VLOOKUP(B83, '[1]DataLookUp - InternalCareer(LP)'!$B$4:$D$620, 3, FALSE)) -> Budi Pranata Sinaga | E83: =IF(EXACT($D83, ""), "", VLOOKUP($D83, [2]DataLookUp!$B$4:$C$84, 2, FALSE)) | H83: =H82 + IF(EXACT(I83, ""), 0, 1) -> 225000000000004 | I83: =IF(EXACT(D83, ""), "", CONCATENATE("PERFORM ""SchData-OLTP-HumanResource"".""Func_TblMapper_WorkerCareerInternalToUserRole_SET""(varSystemLoginSession, null::bigint, null::varchar, null::timestamptz, null::timestamptz, null::varchar, varInstitutionBranchID, varBaseCurrencyID, ", IF(EXACT(B83, ""), "null", B83), "::bigint, ", IF(EXACT(D83, ""), "null", D83), "::bigint, ", IF(EXACT(F83, ""), "null", F83), "::bigint);"))
B84: =IF(EXACT('[1]DataLookUp - InternalCareer(LP)'!$B84, ""), "", '[1]DataLookUp - InternalCareer(LP)'!$B84) -> 164000000000081 | C84: =IF(EXACT($B84, ""), "", VLOOKUP(B84, '[1]DataLookUp - InternalCareer(LP)'!$B$4:$D$620, 3, FALSE)) -> Budi Satrio | E84: =IF(EXACT($D84, ""), "", VLOOKUP($D84, [2]DataLookUp!$B$4:$C$84, 2, FALSE)) | H84: =H83 + IF(EXACT(I84, ""), 0, 1) -> 225000000000004 | I84: =IF(EXACT(D84, ""), "", CONCATENATE("PERFORM ""SchData-OLTP-HumanResource"".""Func_TblMapper_WorkerCareerInternalToUserRole_SET""(varSystemLoginSession, null::bigint, null::varchar, null::timestamptz, null::timestamptz, null::varchar, varInstitutionBranchID, varBaseCurrencyID, ", IF(EXACT(B84, ""), "null", B84), "::bigint, ", IF(EXACT(D84, ""), "null", D84), "::bigint, ", IF(EXACT(F84, ""), "null", F84), "::bigint);"))
B85: =IF(EXACT('[1]DataLookUp - InternalCareer(LP)'!$B85, ""), "", '[1]DataLookUp - InternalCareer(LP)'!$B85) -> 164000000000082 | C85: =IF(EXACT($B85, ""), "", VLOOKUP(B85, '[1]DataLookUp - InternalCareer(LP)'!$B$4:$D$620, 3, FALSE)) -> Budianto | D85: =[2]MAIN!$D$42 -> 95000000000032 | E85: =IF(EXACT($D85, ""), "", VLOOKUP($D85, [2]DataLookUp!$B$4:$C$84, 2, FALSE)) -> Accounting & Tax Manager | H85: =H84 + IF(EXACT(I85, ""), 0, 1) -> 225000000000005 | I85: =IF(EXACT(D85, ""), "", CONCATENATE("PERFORM ""SchData-OLTP-HumanResource"".""Func_TblMapper_WorkerCareerInternalToUserRole_SET""(varSystemLoginSession, null::bigint, null::varchar, null::timestamptz, null::timestamptz, null::varchar, varInstitutionBranchID, varBaseCurrencyID, ", IF(EXACT(B85, ""), "null", B85), "::bigint, ", IF(EXACT(D85, ""), "null", D85), "::bigint, ", IF(EXACT(F85, ""), "null", F85), "::bigint);")) -> PERFORM "SchData-OLTP-HumanResource"."Func_TblMapper_WorkerCareerInternalToUserRole_SET"(varSystemLoginSession, null::bigint, null::varchar, null::timestamptz, null::timestamptz, null::varchar, varInstitutionBranchID, varBaseCurrencyID, 164000000000082::bigint, 95000000000032::bigint, null::bigint);
B86: =IF(EXACT('[1]DataLookUp - InternalCareer(LP)'!$B86, ""), "", '[1]DataLookUp - InternalCareer(LP)'!$B86) -> 164000000000083 | C86: =IF(EXACT($B86, ""), "", VLOOKUP(B86, '[1]DataLookUp - InternalCareer(LP)'!$B$4:$D$620, 3, FALSE)) -> Budiman | E86: =IF(EXACT($D86, ""), "", VLOOKUP($D86, [2]DataLookUp!$B$4:$C$84, 2, FALSE)) | H86: =H85 + IF(EXACT(I86, ""), 0, 1) -> 225000000000005 | I86: =IF(EXACT(D86, ""), "", CONCATENATE("PERFORM ""SchData-OLTP-HumanResource"".""Func_TblMapper_WorkerCareerInternalToUserRole_SET""(varSystemLoginSession, null::bigint, null::varchar, null::timestamptz, null::timestamptz, null::varchar, varInstitutionBranchID, varBaseCurrencyID, ", IF(EXACT(B86, ""), "null", B86), "::bigint, ", IF(EXACT(D86, ""), "null", D86), "::bigint, ", IF(EXACT(F86, ""), "null", F86), "::bigint);"))
B87: =IF(EXACT('[1]DataLookUp - InternalCareer(LP)'!$B87, ""), "", '[1]DataLookUp - InternalCareer(LP)'!$B87) -> 164000000000084 | C87: =IF(EXACT($B87, ""), "", VLOOKUP(B87, '[1]DataLookUp - InternalCareer(LP)'!$B$4:$D$620, 3, FALSE)) -> Cahyaning Annisa | E87: =IF(EXACT($D87, ""), "", VLOOKUP($D87, [2]DataLookUp!$B$4:$C$84, 2, FALSE)) | H87: =H86 + IF(EXACT(I87, ""), 0, 1) -> 225000000000005 | I87: =IF(EXACT(D87, ""), "", CONCATENATE("PERFORM ""SchData-OLTP-HumanResource"".""Func_TblMapper_WorkerCareerInternalToUserRole_SET""(varSystemLoginSession, null::bigint, null::varchar, null::timestamptz, null::timestamptz, null::varchar, varInstitutionBranchID, varBaseCurrencyID, ", IF(EXACT(B87, ""), "null", B87), "::bigint, ", IF(EXACT(D87, ""), "null", D87), "::bigint, ", IF(EXACT(F87, ""), "null", F87), "::bigint);"))
B88: =IF(EXACT('[1]DataLookUp - InternalCareer(LP)'!$B88, ""), "", '[1]DataLookUp - InternalCareer(LP)'!$B88) -> 164000000000085 | C88: =IF(EXACT($B88, ""), "", VLOOKUP(B88, '[1]DataLookUp - InternalCareer(LP)'!$B$4:$D$620, 3, FALSE)) -> Cahyaningrum Widiastuti | E88: =IF(EXACT($D88, ""), "", VLOOKUP($D88, [2]DataLookUp!$B$4:$C$84, 2, FALSE)) | H88: =H87 + IF(EXACT(I88, ""), 0, 1) -> 225000000000005 | I88: =IF(EXACT(D88, ""), "", CONCATENATE("PERFORM ""SchData-OLTP-HumanResource"".""Func_TblMapper_WorkerCareerInternalToUserRole_SET""(varSystemLoginSession, null::bigint, null::varchar, null::timestamptz, null::timestamptz, null::varchar, varInstitutionBranchID, varBaseCurrencyID, ", IF(EXACT(B88, ""), "null", B88), "::bigint, ", IF(EXACT(D88, ""), "null", D88), "::bigint, ", IF(EXACT(F88, ""), "null", F88), "::bigint);"))
B89: =IF(EXACT('[1]DataLookUp - InternalCareer(LP)'!$B89, ""), "", '[1]DataLookUp - InternalCareer(LP)'!$B89) -> 164000000000086 | C89: =IF(EXACT($B89, ""), "", VLOOKUP(B89, '[1]DataLookUp - InternalCareer(LP)'!$B$4:$D$620, 3, FALSE)) -> Cecep Maulana | E89: =IF(EXACT($D89, ""), "", VLOOKUP($D89, [2]DataLookUp!$B$4:$C$84, 2, FALSE)) | H89: =H88 + IF(EXACT(I89, ""), 0, 1) -> 225000000000005 | I89: =IF(EXACT(D89, ""), "", CONCATENATE("PERFORM ""SchData-OLTP-HumanResource"".""Func_TblMapper_WorkerCareerInternalToUserRole_SET""(varSystemLoginSession, null::bigint, null::varchar, null::timestamptz, null::timestamptz, null::varchar, varInstitutionBranchID, varBaseCurrencyID, ", IF(EXACT(B89, ""), "null", B89), "::bigint, ", IF(EXACT(D89, ""), "null", D89), "::bigint, ", IF(EXACT(F89, ""), "null", F89), "::bigint);"))
B90: =IF(EXACT('[1]DataLookUp - InternalCareer(LP)'!$B90, ""), "", '[1]DataLookUp - InternalCareer(LP)'!$B90) -> 164000000000087 | C90: =IF(EXACT($B90, ""), "", VLOOKUP(B90, '[1]DataLookUp - InternalCareer(LP)'!$B$4:$D$620, 3, FALSE)) -> Chairul Musaddat | E90: =IF(EXACT($D90, ""), "", VLOOKUP($D90, [2]DataLookUp!$B$4:$C$84, 2, FALSE)) | H90: =H89 + IF(EXACT(I90, ""), 0, 1) -> 225000000000005 | I90: =IF(EXACT(D90, ""), "", CONCATENATE("PERFORM ""SchData-OLTP-HumanResource"".""Func_TblMapper_WorkerCareerInternalToUserRole_SET""(varSystemLoginSession, null::bigint, null::varchar, null::timestamptz, null::timestamptz, null::varchar, varInstitutionBranchID, varBaseCurrencyID, ", IF(EXACT(B90, ""), "null", B90), "::bigint, ", IF(EXACT(D90, ""), "null", D90), "::bigint, ", IF(EXACT(F90, ""), "null", F90), "::bigint);"))
B91: =IF(EXACT('[1]DataLookUp - InternalCareer(LP)'!$B91, ""), "", '[1]DataLookUp - InternalCareer(LP)'!$B91) -> 164000000000088 | C91: =IF(EXACT($B91, ""), "", VLOOKUP(B91, '[1]DataLookUp - InternalCareer(LP)'!$B$4:$D$620, 3, FALSE)) -> Christianto | E91: =IF(EXACT($D91, ""), "", VLOOKUP($D91, [2]DataLookUp!$B$4:$C$84, 2, FALSE)) | H91: =H90 + IF(EXACT(I91, ""), 0, 1) -> 225000000000005 | I91: =IF(EXACT(D91, ""), "", CONCATENATE("PERFORM ""SchData-OLTP-HumanResource"".""Func_TblMapper_WorkerCareerInternalToUserRole_SET""(varSystemLoginSession, null::bigint, null::varchar, null::timestamptz, null::timestamptz, null::varchar, varInstitutionBranchID, varBaseCurrencyID, ", IF(EXACT(B91, ""), "null", B91), "::bigint, ", IF(EXACT(D91, ""), "null", D91), "::bigint, ", IF(EXACT(F91, ""), "null", F91), "::bigint);"))
B92: =IF(EXACT('[1]DataLookUp - InternalCareer(LP)'!$B92, ""), "", '[1]DataLookUp - InternalCareer(LP)'!$B92) -> 164000000000089 | C92: =IF(EXACT($B92, ""), "", VLOOKUP(B92, '[1]DataLookUp - InternalCareer(LP)'!$B$4:$D$620, 3, FALSE)) -> Dadan Hermawan | E92: =IF(EXACT($D92, ""), "", VLOOKUP($D92, [2]DataLookUp!$B$4:$C$84, 2, FALSE)) | H92: =H91 + IF(EXACT(I92, ""), 0, 1) -> 225000000000005 | I92: =IF(EXACT(D92, ""), "", CONCATENATE("PERFORM ""SchData-OLTP-HumanResource"".""Func_TblMapper_WorkerCareerInternalToUserRole_SET""(varSystemLoginSession, null::bigint, null::varchar, null::timestamptz, null::timestamptz, null::varchar, varInstitutionBranchID, varBaseCurrencyID, ", IF(EXACT(B92, ""), "null", B92), "::bigint, ", IF(EXACT(D92, ""), "null", D92), "::bigint, ", IF(EXACT(F92, ""), "null", F92), "::bigint);"))
B93: =IF(EXACT('[1]DataLookUp - InternalCareer(LP)'!$B93, ""), "", '[1]DataLookUp - InternalCareer(LP)'!$B93) -> 164000000000090 | C93: =IF(EXACT($B93, ""), "", VLOOKUP(B93, '[1]DataLookUp - InternalCareer(LP)'!$B$4:$D$620, 3, FALSE)) -> Dadan Suhendar | E93: =IF(EXACT($D93, ""), "", VLOOKUP($D93, [2]DataLookUp!$B$4:$C$84, 2, FALSE)) | H93: =H92 + IF(EXACT(I93, ""), 0, 1) -> 225000000000005 | I93: =IF(EXACT(D93, ""), "", CONCATENATE("PERFORM ""SchData-OLTP-HumanResource"".""Func_TblMapper_WorkerCareerInternalToUserRole_SET""(varSystemLoginSession, null::bigint, null::varchar, null::timestamptz, null::timestamptz, null::varchar, varInstitutionBranchID, varBaseCurrencyID, ", IF(EXACT(B93, ""), "null", B93), "::bigint, ", IF(EXACT(D93, ""), "null", D93), "::bigint, ", IF(EXACT(F93, ""), "null", F93), "::bigint);"))
B94: =IF(EXACT('[1]DataLookUp - InternalCareer(LP)'!$B94, ""), "", '[1]DataLookUp - InternalCareer(LP)'!$B94) -> 164000000000091 | C94: =IF(EXACT($B94, ""), "", VLOOKUP(B94, '[1]DataLookUp - InternalCareer(LP)'!$B$4:$D$620, 3, FALSE)) -> Dadi Anda Zuchradi | E94: =IF(EXACT($D94, ""), "", VLOOKUP($D94, [2]DataLookUp!$B$4:$C$84, 2, FALSE)) | H94: =H93 + IF(EXACT(I94, ""), 0, 1) -> 225000000000005 | I94: =IF(EXACT(D94, ""), "", CONCATENATE("PERFORM ""SchData-OLTP-HumanResource"".""Func_TblMapper_WorkerCareerInternalToUserRole_SET""(varSystemLoginSession, null::bigint, null::varchar, null::timestamptz, null::timestamptz, null::varchar, varInstitutionBranchID, varBaseCurrencyID, ", IF(EXACT(B94, ""), "null", B94), "::bigint, ", IF(EXACT(D94, ""), "null", D94), "::bigint, ", IF(EXACT(F94, ""), "null", F94), "::bigint);"))
B95: =IF(EXACT('[1]DataLookUp - InternalCareer(LP)'!$B95, ""), "", '[1]DataLookUp - InternalCareer(LP)'!$B95) -> 164000000000092 | C95: =IF(EXACT($B95, ""), "", VLOOKUP(B95, '[1]DataLookUp - InternalCareer(LP)'!$B$4:$D$620, 3, FALSE)) -> Darsito | E95: =IF(EXACT($D95, ""), "", VLOOKUP($D95, [2]DataLookUp!$B$4:$C$84, 2, FALSE)) | H95: =H94 + IF(EXACT(I95, ""), 0, 1) -> 225000000000005 | I95: =IF(EXACT(D95, ""), "", CONCATENATE("PERFORM ""SchData-OLTP-HumanResource"".""Func_TblMapper_WorkerCareerInternalToUserRole_SET""(varSystemLoginSession, null::bigint, null::varchar, null::timestamptz, null::timestamptz, null::varchar, varInstitutionBranchID, varBaseCurrencyID, ", IF(EXACT(B95, ""), "null", B95), "::bigint, ", IF(EXACT(D95, ""), "null", D95), "::bigint, ", IF(EXACT(F95, ""), "null", F95), "::bigint);"))
B96: =IF(EXACT('[1]DataLookUp - InternalCareer(LP)'!$B96, ""), "", '[1]DataLookUp - InternalCareer(LP)'!$B96) -> 164000000000093 | C96: =IF(EXACT($B96, ""), "", VLOOKUP(B96, '[1]DataLookUp - InternalCareer(LP)'!$B$4:$D$620, 3, FALSE)) -> Davit Lumban Gaol | E96: =IF(EXACT($D96, ""), "", VLOOKUP($D96, [2]DataLookUp!$B$4:$C$84, 2, FALSE)) | H96: =H95 + IF(EXACT(I96, ""), 0, 1) -> 225000000000005 | I96: =IF(EXACT(D96, ""), "", CONCATENATE("PERFORM ""SchData-OLTP-HumanResource"".""Func_TblMapper_WorkerCareerInternalToUserRole_SET""(varSystemLoginSession, null::bigint, null::varchar, null::timestamptz, null::timestamptz, null::varchar, varInstitutionBranchID, varBaseCurrencyID, ", IF(EXACT(B96, ""), "null", B96), "::bigint, ", IF(EXACT(D96, ""), "null", D96), "::bigint, ", IF(EXACT(F96, ""), "null", F96), "::bigint);"))
B97: =IF(EXACT('[1]DataLookUp - InternalCareer(LP)'!$B97, ""), "", '[1]DataLookUp - InternalCareer(LP)'!$B97) -> 164000000000094 | C97: =IF(EXACT($B97, ""), "", VLOOKUP(B97, '[1]DataLookUp - InternalCareer(LP)'!$B$4:$D$620, 3, FALSE)) -> Deddy Rochman | E97: =IF(EXACT($D97, ""), "", VLOOKUP($D97, [2]DataLookUp!$B$4:$C$84, 2, FALSE)) | H97: =H96 + IF(EXACT(I97, ""), 0, 1) -> 225000000000005 | I97: =IF(EXACT(D97, ""), "", CONCATENATE("PERFORM ""SchData-OLTP-HumanResource"".""Func_TblMapper_WorkerCareerInternalToUserRole_SET""(varSystemLoginSession, null::bigint, null::varchar, null::timestamptz, null::timestamptz, null::varchar, varInstitutionBranchID, varBaseCurrencyID, ", IF(EXACT(B97, ""), "null", B97), "::bigint, ", IF(EXACT(D97, ""), "null", D97), "::bigint, ", IF(EXACT(F97, ""), "null", F97), "::bigint);"))
... B102: =IF(EXACT('[1]DataLookUp - InternalCareer(LP)'!$B102, ""), "", '[1]DataLookUp - InternalCareer(LP)'!$B102) -> 164000000000099 | C102: =IF(EXACT($B102, ""), "", VLOOKUP(B102, '[1]DataLookUp - InternalCareer(LP)'!$B$4:$D$620, 3, FALSE)) -> Deni Setiawan | E102: =IF(EXACT($D102, ""), "", VLOOKUP($D102, [2]DataLookUp!$B$4:$C$84, 2, FALSE)) | H102: =H101 + IF(EXACT(I102, ""), 0, 1) -> 225000000000005 | I102: =IF(EXACT(D102, ""), "", CONCATENATE("PERFORM ""SchData-OLTP-HumanResource"".""Func_TblMapper_WorkerCareerInternalToUserRole_SET""(varSystemLoginSession, null::bigint, null::varchar, null::timestamptz, null::timestamptz, null::varchar, varInstitutionBranchID, varBaseCurrencyID, ", IF(EXACT(B102, ""), "null", B102), "::bigint, ", IF(EXACT(D102, ""), "null", D102), "::bigint, ", IF(EXACT(F102, ""), "null", F102), "::bigint);"))
B103: =IF(EXACT('[1]DataLookUp - InternalCareer(LP)'!$B103, ""), "", '[1]DataLookUp - InternalCareer(LP)'!$B103) -> 164000000000100 | C103: =IF(EXACT($B103, ""), "", VLOOKUP(B103, '[1]DataLookUp - InternalCareer(LP)'!$B$4:$D$620, 3, FALSE)) -> Deny Adi Purnama | D103: =[2]MAIN!$D$38 -> 95000000000029 | E103: =IF(EXACT($D103, ""), "", VLOOKUP($D103, [2]DataLookUp!$B$4:$C$84, 2, FALSE)) -> Cashier & Treasury Staff | H103: =H102 + IF(EXACT(I103, ""), 0, 1) -> 225000000000006 | I103: =IF(EXACT(D103, ""), "", CONCATENATE("PERFORM ""SchData-OLTP-HumanResource"".""Func_TblMapper_WorkerCareerInternalToUserRole_SET""(varSystemLoginSession, null::bigint, null::varchar, null::timestamptz, null::timestamptz, null::varchar, varInstitutionBranchID, varBaseCurrencyID, ", IF(EXACT(B103, ""), "null", B103), "::bigint, ", IF(EXACT(D103, ""), "null", D103), "::bigint, ", IF(EXACT(F103, ""), "null", F103), "::bigint);")) -> PERFORM "SchData-OLTP-HumanResource"."Func_TblMapper_WorkerCareerInternalToUserRole_SET"(varSystemLoginSession, null::bigint, null::varchar, null::timestamptz, null::timestamptz, null::varchar, varInstitutionBranchID, varBaseCurrencyID, 164000000000100::bigint, 95000000000029::bigint, null::bigint);
B104: =IF(EXACT('[1]DataLookUp - InternalCareer(LP)'!$B104, ""), "", '[1]DataLookUp - InternalCareer(LP)'!$B104) -> 164000000000101 | C104: =IF(EXACT($B104, ""), "", VLOOKUP(B104, '[1]DataLookUp - InternalCareer(LP)'!$B$4:$D$620, 3, FALSE)) -> Desi Herawati | E104: =IF(EXACT($D104, ""), "", VLOOKUP($D104, [2]DataLookUp!$B$4:$C$84, 2, FALSE)) | H104: =H103 + IF(EXACT(I104, ""), 0, 1) -> 225000000000006 | I104: =IF(EXACT(D104, ""), "", CONCATENATE("PERFORM ""SchData-OLTP-HumanResource"".""Func_TblMapper_WorkerCareerInternalToUserRole_SET""(varSystemLoginSession, null::bigint, null::varchar, null::timestamptz, null::timestamptz, null::varchar, varInstitutionBranchID, varBaseCurrencyID, ", IF(EXACT(B104, ""), "null", B104), "::bigint, ", IF(EXACT(D104, ""), "null", D104), "::bigint, ", IF(EXACT(F104, ""), "null", F104), "::bigint);"))
B105: =IF(EXACT('[1]DataLookUp - InternalCareer(LP)'!$B105, ""), "", '[1]DataLookUp - InternalCareer(LP)'!$B105) -> 164000000000102 | C105: =IF(EXACT($B105, ""), "", VLOOKUP(B105, '[1]DataLookUp - InternalCareer(LP)'!$B$4:$D$620, 3, FALSE)) -> Desi Setiowati | E105: =IF(EXACT($D105, ""), "", VLOOKUP($D105, [2]DataLookUp!$B$4:$C$84, 2, FALSE)) | H105: =H104 + IF(EXACT(I105, ""), 0, 1) -> 225000000000006 | I105: =IF(EXACT(D105, ""), "", CONCATENATE("PERFORM ""SchData-OLTP-HumanResource"".""Func_TblMapper_WorkerCareerInternalToUserRole_SET""(varSystemLoginSession, null::bigint, null::varchar, null::timestamptz, null::timestamptz, null::varchar, varInstitutionBranchID, varBaseCurrencyID, ", IF(EXACT(B105, ""), "null", B105), "::bigint, ", IF(EXACT(D105, ""), "null", D105), "::bigint, ", IF(EXACT(F105, ""), "null", F105), "::bigint);"))
B106: =IF(EXACT('[1]DataLookUp - InternalCareer(LP)'!$B106, ""), "", '[1]DataLookUp - InternalCareer(LP)'!$B106) -> 164000000000103 | C106: =IF(EXACT($B106, ""), "", VLOOKUP(B106, '[1]DataLookUp - InternalCareer(LP)'!$B$4:$D$620, 3, FALSE)) -> Dian Firdaus | E106: =IF(EXACT($D106, ""), "", VLOOKUP($D106, [2]DataLookUp!$B$4:$C$84, 2, FALSE)) | H106: =H105 + IF(EXACT(I106, ""), 0, 1) -> 225000000000006 | I106: =IF(EXACT(D106, ""), "", CONCATENATE("PERFORM ""SchData-OLTP-HumanResource"".""Func_TblMapper_WorkerCareerInternalToUserRole_SET""(varSystemLoginSession, null::bigint, null::varchar, null::timestamptz, null::timestamptz, null::varchar, varInstitutionBranchID, varBaseCurrencyID, ", IF(EXACT(B106, ""), "null", B106), "::bigint, ", IF(EXACT(D106, ""), "null", D106), "::bigint, ", IF(EXACT(F106, ""), "null", F106), "::bigint);"))
B107: =IF(EXACT('[1]DataLookUp - InternalCareer(LP)'!$B107, ""), "", '[1]DataLookUp - InternalCareer(LP)'!$B107) -> 164000000000104 | C107: =IF(EXACT($B107, ""), "", VLOOKUP(B107, '[1]DataLookUp - InternalCareer(LP)'!$B$4:$D$620, 3, FALSE)) -> Dian Hariyana | E107: =IF(EXACT($D107, ""), "", VLOOKUP($D107, [2]DataLookUp!$B$4:$C$84, 2, FALSE)) | H107: =H106 + IF(EXACT(I107, ""), 0, 1) -> 225000000000006 | I107: =IF(EXACT(D107, ""), "", CONCATENATE("PERFORM ""SchData-OLTP-HumanResource"".""Func_TblMapper_WorkerCareerInternalToUserRole_SET""(varSystemLoginSession, null::bigint, null::varchar, null::timestamptz, null::timestamptz, null::varchar, varInstitutionBranchID, varBaseCurrencyID, ", IF(EXACT(B107, ""), "null", B107), "::bigint, ", IF(EXACT(D107, ""), "null", D107), "::bigint, ", IF(EXACT(F107, ""), "null", F107), "::bigint);"))
B108: =IF(EXACT('[1]DataLookUp - InternalCareer(LP)'!$B108, ""), "", '[1]DataLookUp - InternalCareer(LP)'!$B108) -> 164000000000105 | C108: =IF(EXACT($B108, ""), "", VLOOKUP(B108, '[1]DataLookUp - InternalCareer(LP)'!$B$4:$D$620, 3, FALSE)) -> Dinnar Budiarti | E108: =IF(EXACT($D108, ""), "", VLOOKUP($D108, [2]DataLookUp!$B$4:$C$84, 2, FALSE)) | H108: =H107 + IF(EXACT(I108, ""), 0, 1) -> 225000000000006 | I108: =IF(EXACT(D108, ""), "", CONCATENATE("PERFORM ""SchData-OLTP-HumanResource"".""Func_TblMapper_WorkerCareerInternalToUserRole_SET""(varSystemLoginSession, null::bigint, null::varchar, null::timestamptz, null::timestamptz, null::varchar, varInstitutionBranchID, varBaseCurrencyID, ", IF(EXACT(B108, ""), "null", B108), "::bigint, ", IF(EXACT(D108, ""), "null", D108), "::bigint, ", IF(EXACT(F108, ""), "null", F108), "::bigint);"))
B109: =IF(EXACT('[1]DataLookUp - InternalCareer(LP)'!$B109, ""), "", '[1]DataLookUp - InternalCareer(LP)'!$B109) -> 164000000000106 | C109: =IF(EXACT($B109, ""), "", VLOOKUP(B109, '[1]DataLookUp - InternalCareer(LP)'!$B$4:$D$620, 3, FALSE)) -> Dionesius Sostenist Duka | E109: =IF(EXACT($D109, ""), "", VLOOKUP($D109, [2]DataLookUp!$B$4:$C$84, 2, FALSE)) | H109: =H108 + IF(EXACT(I109, ""), 0, 1) -> 225000000000006 | I109: =IF(EXACT(D109, ""), "", CONCATENATE("PERFORM ""SchData-OLTP-HumanResource"".""Func_TblMapper_WorkerCareerInternalToUserRole_SET""(varSystemLoginSession, null::bigint, null::varchar, null::timestamptz, null::timestamptz, null::varchar, varInstitutionBranchID, varBaseCurrencyID, ", IF(EXACT(B109, ""), "null", B109), "::bigint, ", IF(EXACT(D109, ""), "null", D109), "::bigint, ", IF(EXACT(F109, ""), "null", F109), "::bigint);"))
B110: =IF(EXACT('[1]DataLookUp - InternalCareer(LP)'!$B110, ""), "", '[1]DataLookUp - InternalCareer(LP)'!$B110) -> 164000000000107 | C110: =IF(EXACT($B110, ""), "", VLOOKUP(B110, '[1]DataLookUp - InternalCareer(LP)'!$B$4:$D$620, 3, FALSE)) -> Diyah Martina | E110: =IF(EXACT($D110, ""), "", VLOOKUP($D110, [2]DataLookUp!$B$4:$C$84, 2, FALSE)) | H110: =H109 + IF(EXACT(I110, ""), 0, 1) -> 225000000000006 | I110: =IF(EXACT(D110, ""), "", CONCATENATE("PERFORM ""SchData-OLTP-HumanResource"".""Func_TblMapper_WorkerCareerInternalToUserRole_SET""(varSystemLoginSession, null::bigint, null::varchar, null::timestamptz, null::timestamptz, null::varchar, varInstitutionBranchID, varBaseCurrencyID, ", IF(EXACT(B110, ""), "null", B110), "::bigint, ", IF(EXACT(D110, ""), "null", D110), "::bigint, ", IF(EXACT(F110, ""), "null", F110), "::bigint);"))
B111: =IF(EXACT('[1]DataLookUp - InternalCareer(LP)'!$B111, ""), "", '[1]DataLookUp - InternalCareer(LP)'!$B111) -> 164000000000108 | C111: =IF(EXACT($B111, ""), "", VLOOKUP(B111, '[1]DataLookUp - InternalCareer(LP)'!$B$4:$D$620, 3, FALSE)) -> Djuang Tampubolon | E111: =IF(EXACT($D111, ""), "", VLOOKUP($D111, [2]DataLookUp!$B$4:$C$84, 2, FALSE)) | H111: =H110 + IF(EXACT(I111, ""), 0, 1) -> 225000000000006 | I111: =IF(EXACT(D111, ""), "", CONCATENATE("PERFORM ""SchData-OLTP-HumanResource"".""Func_TblMapper_WorkerCareerInternalToUserRole_SET""(varSystemLoginSession, null::bigint, null::varchar, null::timestamptz, null::timestamptz, null::varchar, varInstitutionBranchID, varBaseCurrencyID, ", IF(EXACT(B111, ""), "null", B111), "::bigint, ", IF(EXACT(D111, ""), "null", D111), "::bigint, ", IF(EXACT(F111, ""), "null", F111), "::bigint);"))
B112: =IF(EXACT('[1]DataLookUp - InternalCareer(LP)'!$B112, ""), "", '[1]DataLookUp - InternalCareer(LP)'!$B112) -> 164000000000109 | C112: =IF(EXACT($B112, ""), "", VLOOKUP(B112, '[1]DataLookUp - InternalCareer(LP)'!$B$4:$D$620, 3, FALSE)) -> Dodit Widiarto | E112: =IF(EXACT($D112, ""), "", VLOOKUP($D112, [2]DataLookUp!$B$4:$C$84, 2, FALSE)) | H112: =H111 + IF(EXACT(I112, ""), 0, 1) -> 225000000000006 | I112: =IF(EXACT(D112, ""), "", CONCATENATE("PERFORM ""SchData-OLTP-HumanResource"".""Func_TblMapper_WorkerCareerInternalToUserRole_SET""(varSystemLoginSession, null::bigint, null::varchar, null::timestamptz, null::timestamptz, null::varchar, varInstitutionBranchID, varBaseCurrencyID, ", IF(EXACT(B112, ""), "null", B112), "::bigint, ", IF(EXACT(D112, ""), "null", D112), "::bigint, ", IF(EXACT(F112, ""), "null", F112), "::bigint);"))
B113: =IF(EXACT('[1]DataLookUp - InternalCareer(LP)'!$B113, ""), "", '[1]DataLookUp - InternalCareer(LP)'!$B113) -> 164000000000110 | C113: =IF(EXACT($B113, ""), "", VLOOKUP(B113, '[1]DataLookUp - InternalCareer(LP)'!$B$4:$D$620, 3, FALSE)) -> Dony Darmawan | E113: =IF(EXACT($D113, ""), "", VLOOKUP($D113, [2]DataLookUp!$B$4:$C$84, 2, FALSE)) | H113: =H112 + IF(EXACT(I113, ""), 0, 1) -> 225000000000006 | I113: =IF(EXACT(D113, ""), "", CONCATENATE("PERFORM ""SchData-OLTP-HumanResource"".""Func_TblMapper_WorkerCareerInternalToUserRole_SET""(varSystemLoginSession, null::bigint, null::varchar, null::timestamptz, null::timestamptz, null::varchar, varInstitutionBranchID, varBaseCurrencyID, ", IF(EXACT(B113, ""), "null", B113), "::bigint, ", IF(EXACT(D113, ""), "null", D113), "::bigint, ", IF(EXACT(F113, ""), "null", F113), "::bigint);"))
B114: =IF(EXACT('[1]DataLookUp - InternalCareer(LP)'!$B114, ""), "", '[1]DataLookUp - InternalCareer(LP)'!$B114) -> 164000000000111 | C114: =IF(EXACT($B114, ""), "", VLOOKUP(B114, '[1]DataLookUp - InternalCareer(LP)'!$B$4:$D$620, 3, FALSE)) -> Dony Setiawan | E114: =IF(EXACT($D114, ""), "", VLOOKUP($D114, [2]DataLookUp!$B$4:$C$84, 2, FALSE)) | H114: =H113 + IF(EXACT(I114, ""), 0, 1) -> 225000000000006 | I114: =IF(EXACT(D114, ""), "", CONCATENATE("PERFORM ""SchData-OLTP-HumanResource"".""Func_TblMapper_WorkerCareerInternalToUserRole_SET""(varSystemLoginSession, null::bigint, null::varchar, null::timestamptz, null::timestamptz, null::varchar, varInstitutionBranchID, varBaseCurrencyID, ", IF(EXACT(B114, ""), "null", B114), "::bigint, ", IF(EXACT(D114, ""), "null", D114), "::bigint, ", IF(EXACT(F114, ""), "null", F114), "::bigint);"))
B115: =IF(EXACT('[1]DataLookUp - InternalCareer(LP)'!$B115, ""), "", '[1]DataLookUp - InternalCareer(LP)'!$B115) -> 164000000000112 | C115: =IF(EXACT($B115, ""), "", VLOOKUP(B115, '[1]DataLookUp - InternalCareer(LP)'!$B$4:$D$620, 3, FALSE)) -> Dudi Rustandi | E115: =IF(EXACT($D115, ""), "", VLOOKUP($D115, [2]DataLookUp!$B$4:$C$84, 2, FALSE)) | H115: =H114 + IF(EXACT(I115, ""), 0, 1) -> 225000000000006 | I115: =IF(EXACT(D115, ""), "", CONCATENATE("PERFORM ""SchData-OLTP-HumanResource"".""Func_TblMapper_WorkerCareerInternalToUserRole_SET""(varSystemLoginSession, null::bigint, null::varchar, null::timestamptz, null::timestamptz, null::varchar, varInstitutionBranchID, varBaseCurrencyID, ", IF(EXACT(B115, ""), "null", B115), "::bigint, ", IF(EXACT(D115, ""), "null", D115), "::bigint, ", IF(EXACT(F115, ""), "null", F115), "::bigint);"))
... B125: =IF(EXACT('[1]DataLookUp - InternalCareer(LP)'!$B125, ""), "", '[1]DataLookUp - InternalCareer(LP)'!$B125) -> 164000000000122 | C125: =IF(EXACT($B125, ""), "", VLOOKUP(B125, '[1]DataLookUp - InternalCareer(LP)'!$B$4:$D$620, 3, FALSE)) -> Efrina Dwililia | E125: =IF(EXACT($D125, ""), "", VLOOKUP($D125, [2]DataLookUp!$B$4:$C$84, 2, FALSE)) | H125: =H124 + IF(EXACT(I125, ""), 0, 1) -> 225000000000006 | I125: =IF(EXACT(D125, ""), "", CONCATENATE("PERFORM ""SchData-OLTP-HumanResource"".""Func_TblMapper_WorkerCareerInternalToUserRole_SET""(varSystemLoginSession, null::bigint, null::varchar, null::timestamptz, null::timestamptz, null::varchar, varInstitutionBranchID, varBaseCurrencyID, ", IF(EXACT(B125, ""), "null", B125), "::bigint, ", IF(EXACT(D125, ""), "null", D125), "::bigint, ", IF(EXACT(F125, ""), "null", F125), "::bigint);"))
B126: =IF(EXACT('[1]DataLookUp - InternalCareer(LP)'!$B126, ""), "", '[1]DataLookUp - InternalCareer(LP)'!$B126) -> 164000000000123 | C126: =IF(EXACT($B126, ""), "", VLOOKUP(B126, '[1]DataLookUp - InternalCareer(LP)'!$B$4:$D$620, 3, FALSE)) -> Eka Bagus Dwi Putra | D126: =[2]MAIN!$D$32 -> 95000000000024 | E126: =IF(EXACT($D126, ""), "", VLOOKUP($D126, [2]DataLookUp!$B$4:$C$84, 2, FALSE)) -> Project Administrator Staff | H126: =H125 + IF(EXACT(I126, ""), 0, 1) -> 225000000000007 | I126: =IF(EXACT(D126, ""), "", CONCATENATE("PERFORM ""SchData-OLTP-HumanResource"".""Func_TblMapper_WorkerCareerInternalToUserRole_SET""(varSystemLoginSession, null::bigint, null::varchar, null::timestamptz, null::timestamptz, null::varchar, varInstitutionBranchID, varBaseCurrencyID, ", IF(EXACT(B126, ""), "null", B126), "::bigint, ", IF(EXACT(D126, ""), "null", D126), "::bigint, ", IF(EXACT(F126, ""), "null", F126), "::bigint);")) -> PERFORM "SchData-OLTP-HumanResource"."Func_TblMapper_WorkerCareerInternalToUserRole_SET"(varSystemLoginSession, null::bigint, null::varchar, null::timestamptz, null::timestamptz, null::varchar, varInstitutionBranchID, varBaseCurrencyID, 164000000000123::bigint, 95000000000024::bigint, null::bigint);
B127: =IF(EXACT('[1]DataLookUp - InternalCareer(LP)'!$B127, ""), "", '[1]DataLookUp - InternalCareer(LP)'!$B127) -> 164000000000124 | C127: =IF(EXACT($B127, ""), "", VLOOKUP(B127, '[1]DataLookUp - InternalCareer(LP)'!$B$4:$D$620, 3, FALSE)) -> Eka Hamidah | E127: =IF(EXACT($D127, ""), "", VLOOKUP($D127, [2]DataLookUp!$B$4:$C$84, 2, FALSE)) | H127: =H126 + IF(EXACT(I127, ""), 0, 1) -> 225000000000007 | I127: =IF(EXACT(D127, ""), "", CONCATENATE("PERFORM ""SchData-OLTP-HumanResource"".""Func_TblMapper_WorkerCareerInternalToUserRole_SET""(varSystemLoginSession, null::bigint, null::varchar, null::timestamptz, null::timestamptz, null::varchar, varInstitutionBranchID, varBaseCurrencyID, ", IF(EXACT(B127, ""), "null", B127), "::bigint, ", IF(EXACT(D127, ""), "null", D127), "::bigint, ", IF(EXACT(F127, ""), "null", F127), "::bigint);"))
B128: =IF(EXACT('[1]DataLookUp - InternalCareer(LP)'!$B128, ""), "", '[1]DataLookUp - InternalCareer(LP)'!$B128) -> 164000000000125 | C128: =IF(EXACT($B128, ""), "", VLOOKUP(B128, '[1]DataLookUp - InternalCareer(LP)'!$B$4:$D$620, 3, FALSE)) -> Eka Purwanti | D128: =[2]MAIN!$D$32 -> 95000000000024 | E128: =IF(EXACT($D128, ""), "", VLOOKUP($D128, [2]DataLookUp!$B$4:$C$84, 2, FALSE)) -> Project Administrator Staff | F128: 46000000000009 | H128: =H127 + IF(EXACT(I128, ""), 0, 1) -> 225000000000008 | I128: =IF(EXACT(D128, ""), "", CONCATENATE("PERFORM ""SchData-OLTP-HumanResource"".""Func_TblMapper_WorkerCareerInternalToUserRole_SET""(varSystemLoginSession, null::bigint, null::varchar, null::timestamptz, null::timestamptz, null::varchar, varInstitutionBranchID, varBaseCurrencyID, ", IF(EXACT(B128, ""), "null", B128), "::bigint, ", IF(EXACT(D128, ""), "null", D128), "::bigint, ", IF(EXACT(F128, ""), "null", F128), "::bigint);")) -> PERFORM "SchData-OLTP-HumanResource"."Func_TblMapper_WorkerCareerInternalToUserRole_SET"(varSystemLoginSession, null::bigint, null::varchar, null::timestamptz, null::timestamptz, null::varchar, varInstitutionBranchID, varBaseCurrencyID, 164000000000125::bigint, 95000000000024::bigint, 46000000000009::bigint);
B129: =IF(EXACT('[1]DataLookUp - InternalCareer(LP)'!$B129, ""), "", '[1]DataLookUp - InternalCareer(LP)'!$B129) -> 164000000000126 | C129: =IF(EXACT($B129, ""), "", VLOOKUP(B129, '[1]DataLookUp - InternalCareer(LP)'!$B$4:$D$620, 3, FALSE)) -> Eka Kurniawan Hidayatullah | D129: 95000000000041 | E129: =IF(EXACT($D129, ""), "", VLOOKUP($D129, [2]DataLookUp!$B$4:$C$84, 2, FALSE)) -> Procurement Coordinator | H129: =H128 + IF(EXACT(I129, ""), 0, 1) -> 225000000000009 | I129: =IF(EXACT(D129, ""), "", CONCATENATE("PERFORM ""SchData-OLTP-HumanResource"".""Func_TblMapper_WorkerCareerInternalToUserRole_SET""(varSystemLoginSession, null::bigint, null::varchar, null::timestamptz, null::timestamptz, null::varchar, varInstitutionBranchID, varBaseCurrencyID, ", IF(EXACT(B129, ""), "null", B129), "::bigint, ", IF(EXACT(D129, ""), "null", D129), "::bigint, ", IF(EXACT(F129, ""), "null", F129), "::bigint);")) -> PERFORM "SchData-OLTP-HumanResource"."Func_TblMapper_WorkerCareerInternalToUserRole_SET"(varSystemLoginSession, null::bigint, null::varchar, null::timestamptz, null::timestamptz, null::varchar, varInstitutionBranchID, varBaseCurrencyID, 164000000000126::bigint, 95000000000041::bigint, null::bigint);
B130: =IF(EXACT('[1]DataLookUp - InternalCareer(LP)'!$B130, ""), "", '[1]DataLookUp - InternalCareer(LP)'!$B130) -> 164000000000127 | C130: =IF(EXACT($B130, ""), "", VLOOKUP(B130, '[1]DataLookUp - InternalCareer(LP)'!$B$4:$D$620, 3, FALSE)) -> Eko Laksono | E130: =IF(EXACT($D130, ""), "", VLOOKUP($D130, [2]DataLookUp!$B$4:$C$84, 2, FALSE)) | H130: =H129 + IF(EXACT(I130, ""), 0, 1) -> 225000000000009 | I130: =IF(EXACT(D130, ""), "", CONCATENATE("PERFORM ""SchData-OLTP-HumanResource"".""Func_TblMapper_WorkerCareerInternalToUserRole_SET""(varSystemLoginSession, null::bigint, null::varchar, null::timestamptz, null::timestamptz, null::varchar, varInstitutionBranchID, varBaseCurrencyID, ", IF(EXACT(B130, ""), "null", B130), "::bigint, ", IF(EXACT(D130, ""), "null", D130), "::bigint, ", IF(EXACT(F130, ""), "null", F130), "::bigint);"))
B131: =IF(EXACT('[1]DataLookUp - InternalCareer(LP)'!$B131, ""), "", '[1]DataLookUp - InternalCareer(LP)'!$B131) -> 164000000000128 | C131: =IF(EXACT($B131, ""), "", VLOOKUP(B131, '[1]DataLookUp - InternalCareer(LP)'!$B$4:$D$620, 3, FALSE)) -> Eko Syambudi | E131: =IF(EXACT($D131, ""), "", VLOOKUP($D131, [2]DataLookUp!$B$4:$C$84, 2, FALSE)) | H131: =H130 + IF(EXACT(I131, ""), 0, 1) -> 225000000000009 | I131: =IF(EXACT(D131, ""), "", CONCATENATE("PERFORM ""SchData-OLTP-HumanResource"".""Func_TblMapper_WorkerCareerInternalToUserRole_SET""(varSystemLoginSession, null::bigint, null::varchar, null::timestamptz, null::timestamptz, null::varchar, varInstitutionBranchID, varBaseCurrencyID, ", IF(EXACT(B131, ""), "null", B131), "::bigint, ", IF(EXACT(D131, ""), "null", D131), "::bigint, ", IF(EXACT(F131, ""), "null", F131), "::bigint);"))
B132: =IF(EXACT('[1]DataLookUp - InternalCareer(LP)'!$B132, ""), "", '[1]DataLookUp - InternalCareer(LP)'!$B132) -> 164000000000129 | C132: =IF(EXACT($B132, ""), "", VLOOKUP(B132, '[1]DataLookUp - InternalCareer(LP)'!$B$4:$D$620, 3, FALSE)) -> Elieser Ferdy P. | E132: =IF(EXACT($D132, ""), "", VLOOKUP($D132, [2]DataLookUp!$B$4:$C$84, 2, FALSE)) | H132: =H131 + IF(EXACT(I132, ""), 0, 1) -> 225000000000009 | I132: =IF(EXACT(D132, ""), "", CONCATENATE("PERFORM ""SchData-OLTP-HumanResource"".""Func_TblMapper_WorkerCareerInternalToUserRole_SET""(varSystemLoginSession, null::bigint, null::varchar, null::timestamptz, null::timestamptz, null::varchar, varInstitutionBranchID, varBaseCurrencyID, ", IF(EXACT(B132, ""), "null", B132), "::bigint, ", IF(EXACT(D132, ""), "null", D132), "::bigint, ", IF(EXACT(F132, ""), "null", F132), "::bigint);"))
B133: =IF(EXACT('[1]DataLookUp - InternalCareer(LP)'!$B133, ""), "", '[1]DataLookUp - InternalCareer(LP)'!$B133) -> 164000000000130 | C133: =IF(EXACT($B133, ""), "", VLOOKUP(B133, '[1]DataLookUp - InternalCareer(LP)'!$B$4:$D$620, 3, FALSE)) -> Elisa | E133: =IF(EXACT($D133, ""), "", VLOOKUP($D133, [2]DataLookUp!$B$4:$C$84, 2, FALSE)) | H133: =H132 + IF(EXACT(I133, ""), 0, 1) -> 225000000000009 | I133: =IF(EXACT(D133, ""), "", CONCATENATE("PERFORM ""SchData-OLTP-HumanResource"".""Func_TblMapper_WorkerCareerInternalToUserRole_SET""(varSystemLoginSession, null::bigint, null::varchar, null::timestamptz, null::timestamptz, null::varchar, varInstitutionBranchID, varBaseCurrencyID, ", IF(EXACT(B133, ""), "null", B133), "::bigint, ", IF(EXACT(D133, ""), "null", D133), "::bigint, ", IF(EXACT(F133, ""), "null", F133), "::bigint);"))
B134: =IF(EXACT('[1]DataLookUp - InternalCareer(LP)'!$B134, ""), "", '[1]DataLookUp - InternalCareer(LP)'!$B134) -> 164000000000131 | C134: =IF(EXACT($B134, ""), "", VLOOKUP(B134, '[1]DataLookUp - InternalCareer(LP)'!$B$4:$D$620, 3, FALSE)) -> Elsa Jayanti | E134: =IF(EXACT($D134, ""), "", VLOOKUP($D134, [2]DataLookUp!$B$4:$C$84, 2, FALSE)) | H134: =H133 + IF(EXACT(I134, ""), 0, 1) -> 225000000000009 | I134: =IF(EXACT(D134, ""), "", CONCATENATE("PERFORM ""SchData-OLTP-HumanResource"".""Func_TblMapper_WorkerCareerInternalToUserRole_SET""(varSystemLoginSession, null::bigint, null::varchar, null::timestamptz, null::timestamptz, null::varchar, varInstitutionBranchID, varBaseCurrencyID, ", IF(EXACT(B134, ""), "null", B134), "::bigint, ", IF(EXACT(D134, ""), "null", D134), "::bigint, ", IF(EXACT(F134, ""), "null", F134), "::bigint);"))
B135: =IF(EXACT('[1]DataLookUp - InternalCareer(LP)'!$B135, ""), "", '[1]DataLookUp - InternalCareer(LP)'!$B135) -> 164000000000132 | C135: =IF(EXACT($B135, ""), "", VLOOKUP(B135, '[1]DataLookUp - InternalCareer(LP)'!$B$4:$D$620, 3, FALSE)) -> Elsa Mardian | E135: =IF(EXACT($D135, ""), "", VLOOKUP($D135, [2]DataLookUp!$B$4:$C$84, 2, FALSE)) | H135: =H134 + IF(EXACT(I135, ""), 0, 1) -> 225000000000009 | I135: =IF(EXACT(D135, ""), "", CONCATENATE("PERFORM ""SchData-OLTP-HumanResource"".""Func_TblMapper_WorkerCareerInternalToUserRole_SET""(varSystemLoginSession, null::bigint, null::varchar, null::timestamptz, null::timestamptz, null::varchar, varInstitutionBranchID, varBaseCurrencyID, ", IF(EXACT(B135, ""), "null", B135), "::bigint, ", IF(EXACT(D135, ""), "null", D135), "::bigint, ", IF(EXACT(F135, ""), "null", F135), "::bigint);"))
B136: =IF(EXACT('[1]DataLookUp - InternalCareer(LP)'!$B136, ""), "", '[1]DataLookUp - InternalCareer(LP)'!$B136) -> 164000000000133 | C136: =IF(EXACT($B136, ""), "", VLOOKUP(B136, '[1]DataLookUp - InternalCareer(LP)'!$B$4:$D$620, 3, FALSE)) -> Emir Paranita Nasution | E136: =IF(EXACT($D136, ""), "", VLOOKUP($D136, [2]DataLookUp!$B$4:$C$84, 2, FALSE)) | H136: =H135 + IF(EXACT(I136, ""), 0, 1) -> 225000000000009 | I136: =IF(EXACT(D136, ""), "", CONCATENATE("PERFORM ""SchData-OLTP-HumanResource"".""Func_TblMapper_WorkerCareerInternalToUserRole_SET""(varSystemLoginSession, null::bigint, null::varchar, null::timestamptz, null::timestamptz, null::varchar, varInstitutionBranchID, varBaseCurrencyID, ", IF(EXACT(B136, ""), "null", B136), "::bigint, ", IF(EXACT(D136, ""), "null", D136), "::bigint, ", IF(EXACT(F136, ""), "null", F136), "::bigint);"))
B137: =IF(EXACT('[1]DataLookUp - InternalCareer(LP)'!$B137, ""), "", '[1]DataLookUp - InternalCareer(LP)'!$B137) -> 164000000000134 | C137: =IF(EXACT($B137, ""), "", VLOOKUP(B137, '[1]DataLookUp - InternalCareer(LP)'!$B$4:$D$620, 3, FALSE)) -> Enceng Hemawan | E137: =IF(EXACT($D137, ""), "", VLOOKUP($D137, [2]DataLookUp!$B$4:$C$84, 2, FALSE)) | H137: =H136 + IF(EXACT(I137, ""), 0, 1) -> 225000000000009 | I137: =IF(EXACT(D137, ""), "", CONCATENATE("PERFORM ""SchData-OLTP-HumanResource"".""Func_TblMapper_WorkerCareerInternalToUserRole_SET""(varSystemLoginSession, null::bigint, null::varchar, null::timestamptz, null::timestamptz, null::varchar, varInstitutionBranchID, varBaseCurrencyID, ", IF(EXACT(B137, ""), "null", B137), "::bigint, ", IF(EXACT(D137, ""), "null", D137), "::bigint, ", IF(EXACT(F137, ""), "null", F137), "::bigint);"))
B138: =IF(EXACT('[1]DataLookUp - InternalCareer(LP)'!$B138, ""), "", '[1]DataLookUp - InternalCareer(LP)'!$B138) -> 164000000000135 | C138: =IF(EXACT($B138, ""), "", VLOOKUP(B138, '[1]DataLookUp - InternalCareer(LP)'!$B$4:$D$620, 3, FALSE)) -> Endang | E138: =IF(EXACT($D138, ""), "", VLOOKUP($D138, [2]DataLookUp!$B$4:$C$84, 2, FALSE)) | H138: =H137 + IF(EXACT(I138, ""), 0, 1) -> 225000000000009 | I138: =IF(EXACT(D138, ""), "", CONCATENATE("PERFORM ""SchData-OLTP-HumanResource"".""Func_TblMapper_WorkerCareerInternalToUserRole_SET""(varSystemLoginSession, null::bigint, null::varchar, null::timestamptz, null::timestamptz, null::varchar, varInstitutionBranchID, varBaseCurrencyID, ", IF(EXACT(B138, ""), "null", B138), "::bigint, ", IF(EXACT(D138, ""), "null", D138), "::bigint, ", IF(EXACT(F138, ""), "null", F138), "::bigint);"))
B139: =IF(EXACT('[1]DataLookUp - InternalCareer(LP)'!$B139, ""), "", '[1]DataLookUp - InternalCareer(LP)'!$B139) -> 164000000000136 | C139: =IF(EXACT($B139, ""), "", VLOOKUP(B139, '[1]DataLookUp - InternalCareer(LP)'!$B$4:$D$620, 3, FALSE)) -> Endang Lestari | E139: =IF(EXACT($D139, ""), "", VLOOKUP($D139, [2]DataLookUp!$B$4:$C$84, 2, FALSE)) | H139: =H138 + IF(EXACT(I139, ""), 0, 1) -> 225000000000009 | I139: =IF(EXACT(D139, ""), "", CONCATENATE("PERFORM ""SchData-OLTP-HumanResource"".""Func_TblMapper_WorkerCareerInternalToUserRole_SET""(varSystemLoginSession, null::bigint, null::varchar, null::timestamptz, null::timestamptz, null::varchar, varInstitutionBranchID, varBaseCurrencyID, ", IF(EXACT(B139, ""), "null", B139), "::bigint, ", IF(EXACT(D139, ""), "null", D139), "::bigint, ", IF(EXACT(F139, ""), "null", F139), "::bigint);"))
B140: =IF(EXACT('[1]DataLookUp - InternalCareer(LP)'!$B140, ""), "", '[1]DataLookUp - InternalCareer(LP)'!$B140) -> 164000000000137 | C140: =IF(EXACT($B140, ""), "", VLOOKUP(B140, '[1]DataLookUp - InternalCareer(LP)'!$B$4:$D$620, 3, FALSE)) -> Endang Sobari | E140: =IF(EXACT($D140, ""), "", VLOOKUP($D140, [2]DataLookUp!$B$4:$C$84, 2, FALSE)) | H140: =H139 + IF(EXACT(I140, ""), 0, 1) -> 225000000000009 | I140: =IF(EXACT(D140, ""), "", CONCATENATE("PERFORM ""SchData-OLTP-HumanResource"".""Func_TblMapper_WorkerCareerInternalToUserRole_SET""(varSystemLoginSession, null::bigint, null::varchar, null::timestamptz, null::timestamptz, null::varchar, varInstitutionBranchID, varBaseCurrencyID, ", IF(EXACT(B140, ""), "null", B140), "::bigint, ", IF(EXACT(D140, ""), "null", D140), "::bigint, ", IF(EXACT(F140, ""), "null", F140), "::bigint);"))
B141: =IF(EXACT('[1]DataLookUp - InternalCareer(LP)'!$B141, ""), "", '[1]DataLookUp - InternalCareer(LP)'!$B141) -> 164000000000138 | C141: =IF(EXACT($B141, ""), "", VLOOKUP(B141, '[1]DataLookUp - InternalCareer(LP)'!$B$4:$D$620, 3, FALSE)) -> Endang Sutrisna | E141: =IF(EXACT($D141, ""), "", VLOOKUP($D141, [2]DataLookUp!$B$4:$C$84, 2, FALSE)) | H141: =H140 + IF(EXACT(I141, ""), 0, 1) -> 225000000000009 | I141: =IF(EXACT(D141, ""), "", CONCATENATE("PERFORM ""SchData-OLTP-HumanResource"".""Func_TblMapper_WorkerCareerInternalToUserRole_SET""(varSystemLoginSession, null::bigint, null::varchar, null::timestamptz, null::timestamptz, null::varchar, varInstitutionBranchID, varBaseCurrencyID, ", IF(EXACT(B141, ""), "null", B141), "::bigint, ", IF(EXACT(D141, ""), "null", D141), "::bigint, ", IF(EXACT(F141, ""), "null", F141), "::bigint);"))
... B157: =IF(EXACT('[1]DataLookUp - InternalCareer(LP)'!$B157, ""), "", '[1]DataLookUp - InternalCareer(LP)'!$B157) -> 164000000000154 | C157: =IF(EXACT($B157, ""), "", VLOOKUP(B157, '[1]DataLookUp - InternalCareer(LP)'!$B$4:$D$620, 3, FALSE)) -> Fikri | E157: =IF(EXACT($D157, ""), "", VLOOKUP($D157, [2]DataLookUp!$B$4:$C$84, 2, FALSE)) | H157: =H156 + IF(EXACT(I157, ""), 0, 1) -> 225000000000009 | I157: =IF(EXACT(D157, ""), "", CONCATENATE("PERFORM ""SchData-OLTP-HumanResource"".""Func_TblMapper_WorkerCareerInternalToUserRole_SET""(varSystemLoginSession, null::bigint, null::varchar, null::timestamptz, null::timestamptz, null::varchar, varInstitutionBranchID, varBaseCurrencyID, ", IF(EXACT(B157, ""), "null", B157), "::bigint, ", IF(EXACT(D157, ""), "null", D157), "::bigint, ", IF(EXACT(F157, ""), "null", F157), "::bigint);"))
B158: =IF(EXACT('[1]DataLookUp - InternalCareer(LP)'!$B158, ""), "", '[1]DataLookUp - InternalCareer(LP)'!$B158) -> 164000000000155 | C158: =IF(EXACT($B158, ""), "", VLOOKUP(B158, '[1]DataLookUp - InternalCareer(LP)'!$B$4:$D$620, 3, FALSE)) -> M. Fikri Caesarandi Hasibuan | D158: =[2]MAIN!$D$32 -> 95000000000024 | E158: =IF(EXACT($D158, ""), "", VLOOKUP($D158, [2]DataLookUp!$B$4:$C$84, 2, FALSE)) -> Project Administrator Staff | F158: 46000000000033 | H158: =H157 + IF(EXACT(I158, ""), 0, 1) -> 225000000000010 | I158: =IF(EXACT(D158, ""), "", CONCATENATE("PERFORM ""SchData-OLTP-HumanResource"".""Func_TblMapper_WorkerCareerInternalToUserRole_SET""(varSystemLoginSession, null::bigint, null::varchar, null::timestamptz, null::timestamptz, null::varchar, varInstitutionBranchID, varBaseCurrencyID, ", IF(EXACT(B158, ""), "null", B158), "::bigint, ", IF(EXACT(D158, ""), "null", D158), "::bigint, ", IF(EXACT(F158, ""), "null", F158), "::bigint);")) -> PERFORM "SchData-OLTP-HumanResource"."Func_TblMapper_WorkerCareerInternalToUserRole_SET"(varSystemLoginSession, null::bigint, null::varchar, null::timestamptz, null::timestamptz, null::varchar, varInstitutionBranchID, varBaseCurrencyID, 164000000000155::bigint, 95000000000024::bigint, 46000000000033::bigint);
B159: =IF(EXACT('[1]DataLookUp - InternalCareer(LP)'!$B159, ""), "", '[1]DataLookUp - InternalCareer(LP)'!$B159) -> 164000000000156 | C159: =IF(EXACT($B159, ""), "", VLOOKUP(B159, '[1]DataLookUp - InternalCareer(LP)'!$B$4:$D$620, 3, FALSE)) -> Firman Akbar | E159: =IF(EXACT($D159, ""), "", VLOOKUP($D159, [2]DataLookUp!$B$4:$C$84, 2, FALSE)) | H159: =H158 + IF(EXACT(I159, ""), 0, 1) -> 225000000000010 | I159: =IF(EXACT(D159, ""), "", CONCATENATE("PERFORM ""SchData-OLTP-HumanResource"".""Func_TblMapper_WorkerCareerInternalToUserRole_SET""(varSystemLoginSession, null::bigint, null::varchar, null::timestamptz, null::timestamptz, null::varchar, varInstitutionBranchID, varBaseCurrencyID, ", IF(EXACT(B159, ""), "null", B159), "::bigint, ", IF(EXACT(D159, ""), "null", D159), "::bigint, ", IF(EXACT(F159, ""), "null", F159), "::bigint);"))
B160: =IF(EXACT('[1]DataLookUp - InternalCareer(LP)'!$B160, ""), "", '[1]DataLookUp - InternalCareer(LP)'!$B160) -> 164000000000157 | C160: =IF(EXACT($B160, ""), "", VLOOKUP(B160, '[1]DataLookUp - InternalCareer(LP)'!$B$4:$D$620, 3, FALSE)) -> Fitriastuti Kurnia | D160: =[2]MAIN!$D$32 -> 95000000000024 | E160: =IF(EXACT($D160, ""), "", VLOOKUP($D160, [2]DataLookUp!$B$4:$C$84, 2, FALSE)) -> Project Administrator Staff | H160: =H159 + IF(EXACT(I160, ""), 0, 1) -> 225000000000011 | I160: =IF(EXACT(D160, ""), "", CONCATENATE("PERFORM ""SchData-OLTP-HumanResource"".""Func_TblMapper_WorkerCareerInternalToUserRole_SET""(varSystemLoginSession, null::bigint, null::varchar, null::timestamptz, null::timestamptz, null::varchar, varInstitutionBranchID, varBaseCurrencyID, ", IF(EXACT(B160, ""), "null", B160), "::bigint, ", IF(EXACT(D160, ""), "null", D160), "::bigint, ", IF(EXACT(F160, ""), "null", F160), "::bigint);")) -> PERFORM "SchData-OLTP-HumanResource"."Func_TblMapper_WorkerCareerInternalToUserRole_SET"(varSystemLoginSession, null::bigint, null::varchar, null::timestamptz, null::timestamptz, null::varchar, varInstitutionBranchID, varBaseCurrencyID, 164000000000157::bigint, 95000000000024::bigint, null::bigint);
B161: =IF(EXACT('[1]DataLookUp - InternalCareer(LP)'!$B161, ""), "", '[1]DataLookUp - InternalCareer(LP)'!$B161) -> 164000000000158 | C161: =IF(EXACT($B161, ""), "", VLOOKUP(B161, '[1]DataLookUp - InternalCareer(LP)'!$B$4:$D$620, 3, FALSE)) -> Francis Imanuel | E161: =IF(EXACT($D161, ""), "", VLOOKUP($D161, [2]DataLookUp!$B$4:$C$84, 2, FALSE)) | H161: =H160 + IF(EXACT(I161, ""), 0, 1) -> 225000000000011 | I161: =IF(EXACT(D161, ""), "", CONCATENATE("PERFORM ""SchData-OLTP-HumanResource"".""Func_TblMapper_WorkerCareerInternalToUserRole_SET""(varSystemLoginSession, null::bigint, null::varchar, null::timestamptz, null::timestamptz, null::varchar, varInstitutionBranchID, varBaseCurrencyID, ", IF(EXACT(B161, ""), "null", B161), "::bigint, ", IF(EXACT(D161, ""), "null", D161), "::bigint, ", IF(EXACT(F161, ""), "null", F161), "::bigint);"))
B162: =IF(EXACT('[1]DataLookUp - InternalCareer(LP)'!$B162, ""), "", '[1]DataLookUp - InternalCareer(LP)'!$B162) -> 164000000000159 | C162: =IF(EXACT($B162, ""), "", VLOOKUP(B162, '[1]DataLookUp - InternalCareer(LP)'!$B$4:$D$620, 3, FALSE)) -> Frando Judi Siahaan | E162: =IF(EXACT($D162, ""), "", VLOOKUP($D162, [2]DataLookUp!$B$4:$C$84, 2, FALSE)) | H162: =H161 + IF(EXACT(I162, ""), 0, 1) -> 225000000000011 | I162: =IF(EXACT(D162, ""), "", CONCATENATE("PERFORM ""SchData-OLTP-HumanResource"".""Func_TblMapper_WorkerCareerInternalToUserRole_SET""(varSystemLoginSession, null::bigint, null::varchar, null::timestamptz, null::timestamptz, null::varchar, varInstitutionBranchID, varBaseCurrencyID, ", IF(EXACT(B162, ""), "null", B162), "::bigint, ", IF(EXACT(D162, ""), "null", D162), "::bigint, ", IF(EXACT(F162, ""), "null", F162), "::bigint);"))
B163: =IF(EXACT('[1]DataLookUp - InternalCareer(LP)'!$B163, ""), "", '[1]DataLookUp - InternalCareer(LP)'!$B163) -> 164000000000160 | C163: =IF(EXACT($B163, ""), "", VLOOKUP(B163, '[1]DataLookUp - InternalCareer(LP)'!$B$4:$D$620, 3, FALSE)) -> Frederika Intan | E163: =IF(EXACT($D163, ""), "", VLOOKUP($D163, [2]DataLookUp!$B$4:$C$84, 2, FALSE)) | H163: =H162 + IF(EXACT(I163, ""), 0, 1) -> 225000000000011 | I163: =IF(EXACT(D163, ""), "", CONCATENATE("PERFORM ""SchData-OLTP-HumanResource"".""Func_TblMapper_WorkerCareerInternalToUserRole_SET""(varSystemLoginSession, null::bigint, null::varchar, null::timestamptz, null::timestamptz, null::varchar, varInstitutionBranchID, varBaseCurrencyID, ", IF(EXACT(B163, ""), "null", B163), "::bigint, ", IF(EXACT(D163, ""), "null", D163), "::bigint, ", IF(EXACT(F163, ""), "null", F163), "::bigint);"))
B164: =IF(EXACT('[1]DataLookUp - InternalCareer(LP)'!$B164, ""), "", '[1]DataLookUp - InternalCareer(LP)'!$B164) -> 164000000000161 | C164: =IF(EXACT($B164, ""), "", VLOOKUP(B164, '[1]DataLookUp - InternalCareer(LP)'!$B$4:$D$620, 3, FALSE)) -> Fuad Febrian | E164: =IF(EXACT($D164, ""), "", VLOOKUP($D164, [2]DataLookUp!$B$4:$C$84, 2, FALSE)) | H164: =H163 + IF(EXACT(I164, ""), 0, 1) -> 225000000000011 | I164: =IF(EXACT(D164, ""), "", CONCATENATE("PERFORM ""SchData-OLTP-HumanResource"".""Func_TblMapper_WorkerCareerInternalToUserRole_SET""(varSystemLoginSession, null::bigint, null::varchar, null::timestamptz, null::timestamptz, null::varchar, varInstitutionBranchID, varBaseCurrencyID, ", IF(EXACT(B164, ""), "null", B164), "::bigint, ", IF(EXACT(D164, ""), "null", D164), "::bigint, ", IF(EXACT(F164, ""), "null", F164), "::bigint);"))
B165: =IF(EXACT('[1]DataLookUp - InternalCareer(LP)'!$B165, ""), "", '[1]DataLookUp - InternalCareer(LP)'!$B165) -> 164000000000162 | C165: =IF(EXACT($B165, ""), "", VLOOKUP(B165, '[1]DataLookUp - InternalCareer(LP)'!$B$4:$D$620, 3, FALSE)) -> Wiyadianto | E165: =IF(EXACT($D165, ""), "", VLOOKUP($D165, [2]DataLookUp!$B$4:$C$84, 2, FALSE)) | H165: =H164 + IF(EXACT(I165, ""), 0, 1) -> 225000000000011 | I165: =IF(EXACT(D165, ""), "", CONCATENATE("PERFORM ""SchData-OLTP-HumanResource"".""Func_TblMapper_WorkerCareerInternalToUserRole_SET""(varSystemLoginSession, null::bigint, null::varchar, null::timestamptz, null::timestamptz, null::varchar, varInstitutionBranchID, varBaseCurrencyID, ", IF(EXACT(B165, ""), "null", B165), "::bigint, ", IF(EXACT(D165, ""), "null", D165), "::bigint, ", IF(EXACT(F165, ""), "null", F165), "::bigint);"))
B166: =IF(EXACT('[1]DataLookUp - InternalCareer(LP)'!$B166, ""), "", '[1]DataLookUp - InternalCareer(LP)'!$B166) -> 164000000000163 | C166: =IF(EXACT($B166, ""), "", VLOOKUP(B166, '[1]DataLookUp - InternalCareer(LP)'!$B$4:$D$620, 3, FALSE)) -> Galuh Swastika | E166: =IF(EXACT($D166, ""), "", VLOOKUP($D166, [2]DataLookUp!$B$4:$C$84, 2, FALSE)) | H166: =H165 + IF(EXACT(I166, ""), 0, 1) -> 225000000000011 | I166: =IF(EXACT(D166, ""), "", CONCATENATE("PERFORM ""SchData-OLTP-HumanResource"".""Func_TblMapper_WorkerCareerInternalToUserRole_SET""(varSystemLoginSession, null::bigint, null::varchar, null::timestamptz, null::timestamptz, null::varchar, varInstitutionBranchID, varBaseCurrencyID, ", IF(EXACT(B166, ""), "null", B166), "::bigint, ", IF(EXACT(D166, ""), "null", D166), "::bigint, ", IF(EXACT(F166, ""), "null", F166), "::bigint);"))
B167: =IF(EXACT('[1]DataLookUp - InternalCareer(LP)'!$B167, ""), "", '[1]DataLookUp - InternalCareer(LP)'!$B167) -> 164000000000164 | C167: =IF(EXACT($B167, ""), "", VLOOKUP(B167, '[1]DataLookUp - InternalCareer(LP)'!$B$4:$D$620, 3, FALSE)) -> Ganda Yuharis R. | E167: =IF(EXACT($D167, ""), "", VLOOKUP($D167, [2]DataLookUp!$B$4:$C$84, 2, FALSE)) | H167: =H166 + IF(EXACT(I167, ""), 0, 1) -> 225000000000011 | I167: =IF(EXACT(D167, ""), "", CONCATENATE("PERFORM ""SchData-OLTP-HumanResource"".""Func_TblMapper_WorkerCareerInternalToUserRole_SET""(varSystemLoginSession, null::bigint, null::varchar, null::timestamptz, null::timestamptz, null::varchar, varInstitutionBranchID, varBaseCurrencyID, ", IF(EXACT(B167, ""), "null", B167), "::bigint, ", IF(EXACT(D167, ""), "null", D167), "::bigint, ", IF(EXACT(F167, ""), "null", F167), "::bigint);"))
...

Sheet DataLookUp
B2: Sys_PID | C2: =MAIN!B2 -> Ref ID Worker Career Internal | D2: =MAIN!C2 -> Worker Name | E2: =MAIN!D2 -> Ref ID User Role | F2: =MAIN!F2 -> Ref ID Combined Budget
B4: =IF(EXACT(MAIN!I4, ""), "", MAIN!H4) | C4: =IF(EXACT(MAIN!$I4, ""), "", MAIN!$B4) | D4: =IF(EXACT(MAIN!$I4, ""), "", MAIN!$C4) | E4: =IF(EXACT(MAIN!$I4, ""), "", MAIN!$D4) | F4: =IF(EXACT(MAIN!$I4, ""), "", ""&MAIN!$F4)
B5: =IF(EXACT(MAIN!I5, ""), "", MAIN!H5) | C5: =IF(EXACT(MAIN!$I5, ""), "", MAIN!$B5) | D5: =IF(EXACT(MAIN!$I5, ""), "", MAIN!$C5) | E5: =IF(EXACT(MAIN!$I5, ""), "", MAIN!$D5) | F5: =IF(EXACT(MAIN!$I5, ""), "", ""&MAIN!$F5)
B6: =IF(EXACT(MAIN!I6, ""), "", MAIN!H6) | C6: =IF(EXACT(MAIN!$I6, ""), "", MAIN!$B6) | D6: =IF(EXACT(MAIN!$I6, ""), "", MAIN!$C6) | E6: =IF(EXACT(MAIN!$I6, ""), "", MAIN!$D6) | F6: =IF(EXACT(MAIN!$I6, ""), "", ""&MAIN!$F6)
B7: =IF(EXACT(MAIN!I7, ""), "", MAIN!H7) | C7: =IF(EXACT(MAIN!$I7, ""), "", MAIN!$B7) | D7: =IF(EXACT(MAIN!$I7, ""), "", MAIN!$C7) | E7: =IF(EXACT(MAIN!$I7, ""), "", MAIN!$D7) | F7: =IF(EXACT(MAIN!$I7, ""), "", ""&MAIN!$F7)
B8: =IF(EXACT(MAIN!I8, ""), "", MAIN!H8) | C8: =IF(EXACT(MAIN!$I8, ""), "", MAIN!$B8) | D8: =IF(EXACT(MAIN!$I8, ""), "", MAIN!$C8) | E8: =IF(EXACT(MAIN!$I8, ""), "", MAIN!$D8) | F8: =IF(EXACT(MAIN!$I8, ""), "", ""&MAIN!$F8)
B9: =IF(EXACT(MAIN!I9, ""), "", MAIN!H9) | C9: =IF(EXACT(MAIN!$I9, ""), "", MAIN!$B9) | D9: =IF(EXACT(MAIN!$I9, ""), "", MAIN!$C9) | E9: =IF(EXACT(MAIN!$I9, ""), "", MAIN!$D9) | F9: =IF(EXACT(MAIN!$I9, ""), "", ""&MAIN!$F9)
B10: =IF(EXACT(MAIN!I10, ""), "", MAIN!H10) | C10: =IF(EXACT(MAIN!$I10, ""), "", MAIN!$B10) | D10: =IF(EXACT(MAIN!$I10, ""), "", MAIN!$C10) | E10: =IF(EXACT(MAIN!$I10, ""), "", MAIN!$D10) | F10: =IF(EXACT(MAIN!$I10, ""), "", ""&MAIN!$F10)
B11: =IF(EXACT(MAIN!I11, ""), "", MAIN!H11) | C11: =IF(EXACT(MAIN!$I11, ""), "", MAIN!$B11) | D11: =IF(EXACT(MAIN!$I11, ""), "", MAIN!$C11) | E11: =IF(EXACT(MAIN!$I11, ""), "", MAIN!$D11) | F11: =IF(EXACT(MAIN!$I11, ""), "", ""&MAIN!$F11)
B12: =IF(EXACT(MAIN!I12, ""), "", MAIN!H12) | C12: =IF(EXACT(MAIN!$I12, ""), "", MAIN!$B12) | D12: =IF(EXACT(MAIN!$I12, ""), "", MAIN!$C12) | E12: =IF(EXACT(MAIN!$I12, ""), "", MAIN!$D12) | F12: =IF(EXACT(MAIN!$I12, ""), "", ""&MAIN!$F12)
B13: =IF(EXACT(MAIN!I13, ""), "", MAIN!H13) | C13: =IF(EXACT(MAIN!$I13, ""), "", MAIN!$B13) | D13: =IF(EXACT(MAIN!$I13, ""), "", MAIN!$C13) | E13: =IF(EXACT(MAIN!$I13, ""), "", MAIN!$D13) | F13: =IF(EXACT(MAIN!$I13, ""), "", ""&MAIN!$F13)
B14: =IF(EXACT(MAIN!I14, ""), "", MAIN!H14) | C14: =IF(EXACT(MAIN!$I14, ""), "", MAIN!$B14) | D14: =IF(EXACT(MAIN!$I14, ""), "", MAIN!$C14) | E14: =IF(EXACT(MAIN!$I14, ""), "", MAIN!$D14) | F14: =IF(EXACT(MAIN!$I14, ""), "", ""&MAIN!$F14)
B15: =IF(EXACT(MAIN!$I15, ""), "", MAIN!$H15) -> 225000000000001 | C15: =IF(EXACT(MAIN!$I15, ""), "", MAIN!$B15) -> 164000000000012 | D15: =IF(EXACT(MAIN!$I15, ""), "", MAIN!$C15) -> Agnes Sutedja | E15: =IF(EXACT(MAIN!$I15, ""), "", MAIN!$D15) -> 95000000000048 | F15: =IF(EXACT(MAIN!$I15, ""), "", ""&MAIN!$F15)
B16: =IF(EXACT(MAIN!I16, ""), "", MAIN!H16) | C16: =IF(EXACT(MAIN!$I16, ""), "", MAIN!$B16) | D16: =IF(EXACT(MAIN!$I16, ""), "", MAIN!$C16) | E16: =IF(EXACT(MAIN!$I16, ""), "", MAIN!$D16) | F16: =IF(EXACT(MAIN!$I16, ""), "", ""&MAIN!$F16)
B17: =IF(EXACT(MAIN!I17, ""), "", MAIN!H17) | C17: =IF(EXACT(MAIN!$I17, ""), "", MAIN!$B17) | D17: =IF(EXACT(MAIN!$I17, ""), "", MAIN!$C17) | E17: =IF(EXACT(MAIN!$I17, ""), "", MAIN!$D17) | F17: =IF(EXACT(MAIN!$I17, ""), "", ""&MAIN!$F17)
B18: =IF(EXACT(MAIN!I18, ""), "", MAIN!H18) | C18: =IF(EXACT(MAIN!$I18, ""), "", MAIN!$B18) | D18: =IF(EXACT(MAIN!$I18, ""), "", MAIN!$C18) | E18: =IF(EXACT(MAIN!$I18, ""), "", MAIN!$D18) | F18: =IF(EXACT(MAIN!$I18, ""), "", ""&MAIN!$F18)
B19: =IF(EXACT(MAIN!I19, ""), "", MAIN!H19) | C19: =IF(EXACT(MAIN!$I19, ""), "", MAIN!$B19) | D19: =IF(EXACT(MAIN!$I19, ""), "", MAIN!$C19) | E19: =IF(EXACT(MAIN!$I19, ""), "", MAIN!$D19) | F19: =IF(EXACT(MAIN!$I19, ""), "", ""&MAIN!$F19)
B20: =IF(EXACT(MAIN!I20, ""), "", MAIN!H20) -> 225000000000002 | C20: =IF(EXACT(MAIN!$I20, ""), "", MAIN!$B20) -> 164000000000017 | D20: =IF(EXACT(MAIN!$I20, ""), "", MAIN!$C20) -> Ahmad Faiz Haems Muda | E20: =IF(EXACT(MAIN!$I20, ""), "", MAIN!$D20) -> 95000000000017 | F20: =IF(EXACT(MAIN!$I20, ""), "", ""&MAIN!$F20)
B21: =IF(EXACT(MAIN!I21, ""), "", MAIN!H21) | C21: =IF(EXACT(MAIN!$I21, ""), "", MAIN!$B21) | D21: =IF(EXACT(MAIN!$I21, ""), "", MAIN!$C21) | E21: =IF(EXACT(MAIN!$I21, ""), "", MAIN!$D21) | F21: =IF(EXACT(MAIN!$I21, ""), "", ""&MAIN!$F21)
B22: =IF(EXACT(MAIN!I22, ""), "", MAIN!H22) | C22: =IF(EXACT(MAIN!$I22, ""), "", MAIN!$B22) | D22: =IF(EXACT(MAIN!$I22, ""), "", MAIN!$C22) | E22: =IF(EXACT(MAIN!$I22, ""), "", MAIN!$D22) | F22: =IF(EXACT(MAIN!$I22, ""), "", ""&MAIN!$F22)
B23: =IF(EXACT(MAIN!I23, ""), "", MAIN!H23) | C23: =IF(EXACT(MAIN!$I23, ""), "", MAIN!$B23) | D23: =IF(EXACT(MAIN!$I23, ""), "", MAIN!$C23) | E23: =IF(EXACT(MAIN!$I23, ""), "", MAIN!$D23) | F23: =IF(EXACT(MAIN!$I23, ""), "", ""&MAIN!$F23)
B24: =IF(EXACT(MAIN!I24, ""), "", MAIN!H24) | C24: =IF(EXACT(MAIN!$I24, ""), "", MAIN!$B24) | D24: =IF(EXACT(MAIN!$I24, ""), "", MAIN!$C24) | E24: =IF(EXACT(MAIN!$I24, ""), "", MAIN!$D24) | F24: =IF(EXACT(MAIN!$I24, ""), "", ""&MAIN!$F24)
B25: =IF(EXACT(MAIN!I25, ""), "", MAIN!H25) | C25: =IF(EXACT(MAIN!$I25, ""), "", MAIN!$B25) | D25: =IF(EXACT(MAIN!$I25, ""), "", MAIN!$C25) | E25: =IF(EXACT(MAIN!$I25, ""), "", MAIN!$D25) | F25: =IF(EXACT(MAIN!$I25, ""), "", ""&MAIN!$F25)
B26: =IF(EXACT(MAIN!I26, ""), "", MAIN!H26) -> 225000000000003 | C26: =IF(EXACT(MAIN!$I26, ""), "", MAIN!$B26) -> 164000000000023 | D26: =IF(EXACT(MAIN!$I26, ""), "", MAIN!$C26) -> Aldi Mulyadi | E26: =IF(EXACT(MAIN!$I26, ""), "", MAIN!$D26) -> 95000000000039 | F26: =IF(EXACT(MAIN!$I26, ""), "", ""&MAIN!$F26)
B27: =IF(EXACT(MAIN!I27, ""), "", MAIN!H27) | C27: =IF(EXACT(MAIN!$I27, ""), "", MAIN!$B27) | D27: =IF(EXACT(MAIN!$I27, ""), "", MAIN!$C27) | E27: =IF(EXACT(MAIN!$I27, ""), "", MAIN!$D27) | F27: =IF(EXACT(MAIN!$I27, ""), "", ""&MAIN!$F27)
... B586: =IF(EXACT(MAIN!I586, ""), "", MAIN!H586) | C586: =IF(EXACT(MAIN!$I586, ""), "", MAIN!$B586) | D586: =IF(EXACT(MAIN!$I586, ""), "", MAIN!$C586) | E586: =IF(EXACT(MAIN!$I586, ""), "", MAIN!$D586) | F586: =IF(EXACT(MAIN!$I586, ""), "", ""&MAIN!$F586)
B587: =IF(EXACT(MAIN!I587, ""), "", MAIN!H587) | C587: =IF(EXACT(MAIN!$I587, ""), "", MAIN!$B587) | D587: =IF(EXACT(MAIN!$I587, ""), "", MAIN!$C587) | E587: =IF(EXACT(MAIN!$I587, ""), "", MAIN!$D587)
B588: =IF(EXACT(MAIN!I588, ""), "", MAIN!H588) | C588: =IF(EXACT(MAIN!$I588, ""), "", MAIN!$B588) | D588: =IF(EXACT(MAIN!$I588, ""), "", MAIN!$C588) | E588: =IF(EXACT(MAIN!$I588, ""), "", MAIN!$D588)
B589: =IF(EXACT(MAIN!I589, ""), "", MAIN!H589) | C589: =IF(EXACT(MAIN!$I589, ""), "", MAIN!$B589) | D589: =IF(EXACT(MAIN!$I589, ""), "", MAIN!$C589) | E589: =IF(EXACT(MAIN!$I589, ""), "", MAIN!$D589)
B590: =IF(EXACT(MAIN!I590, ""), "", MAIN!H590) -> 225000000000054 | C590: =IF(EXACT(MAIN!$I590, ""), "", MAIN!$B590) -> 164000000000587 | D590: =IF(EXACT(MAIN!$I590, ""), "", MAIN!$C590) -> Firmansyah Awaludin | E590: =IF(EXACT(MAIN!$I590, ""), "", MAIN!$D590) -> 95000000000029
B591: =IF(EXACT(MAIN!I591, ""), "", MAIN!H591) -> 225000000000055 | C591: =IF(EXACT(MAIN!$I591, ""), "", MAIN!$B591) -> 164000000000588 | D591: =IF(EXACT(MAIN!$I591, ""), "", MAIN!$C591) -> Iman Faisal Abdurahman | E591: =IF(EXACT(MAIN!$I591, ""), "", MAIN!$D591) -> 95000000000008 | F591: =IF(EXACT(MAIN!$I587, ""), "", ""&MAIN!$F587)
B592: =IF(EXACT(MAIN!I592, ""), "", MAIN!H592) | C592: =IF(EXACT(MAIN!$I592, ""), "", MAIN!$B592) | D592: =IF(EXACT(MAIN!$I592, ""), "", MAIN!$C592) | E592: =IF(EXACT(MAIN!$I592, ""), "", MAIN!$D592) | F592: =IF(EXACT(MAIN!$I588, ""), "", ""&MAIN!$F588)
B593: =IF(EXACT(MAIN!I593, ""), "", MAIN!H593) | C593: =IF(EXACT(MAIN!$I593, ""), "", MAIN!$B593) | D593: =IF(EXACT(MAIN!$I593, ""), "", MAIN!$C593) | E593: =IF(EXACT(MAIN!$I593, ""), "", MAIN!$D593) | F593: =IF(EXACT(MAIN!$I589, ""), "", ""&MAIN!$F589)
B594: =IF(EXACT(MAIN!I594, ""), "", MAIN!H594) | C594: =IF(EXACT(MAIN!$I594, ""), "", MAIN!$B594) | D594: =IF(EXACT(MAIN!$I594, ""), "", MAIN!$C594) | E594: =IF(EXACT(MAIN!$I594, ""), "", MAIN!$D594) | F594: =IF(EXACT(MAIN!$I590, ""), "", ""&MAIN!$F590)
B595: =IF(EXACT(MAIN!I595, ""), "", MAIN!H595) -> 225000000000056 | C595: =IF(EXACT(MAIN!$I595, ""), "", MAIN!$B595) -> 164000000000592 | D595: =IF(EXACT(MAIN!$I595, ""), "", MAIN!$C595) -> Ahmad Sandi Asyuri | E595: =IF(EXACT(MAIN!$I595, ""), "", MAIN!$D595) -> 95000000000065 | F595: =IF(EXACT(MAIN!$I591, ""), "", ""&MAIN!$F591)
B596: =IF(EXACT(MAIN!I596, ""), "", MAIN!H596) -> 225000000000057 | C596: =IF(EXACT(MAIN!$I596, ""), "", MAIN!$B596) -> 164000000000593 | D596: =IF(EXACT(MAIN!$I596, ""), "", MAIN!$C596) -> Andi Mapasoro | E596: =IF(EXACT(MAIN!$I596, ""), "", MAIN!$D596) -> 95000000000019 | F596: =IF(EXACT(MAIN!$I592, ""), "", ""&MAIN!$F592)
B597: =IF(EXACT(MAIN!I597, ""), "", MAIN!H597) | C597: =IF(EXACT(MAIN!$I597, ""), "", MAIN!$B597) | D597: =IF(EXACT(MAIN!$I597, ""), "", MAIN!$C597) | E597: =IF(EXACT(MAIN!$I597, ""), "", MAIN!$D597) | F597: =IF(EXACT(MAIN!$I593, ""), "", ""&MAIN!$F593)
B598: =IF(EXACT(MAIN!I598, ""), "", MAIN!H598) | C598: =IF(EXACT(MAIN!$I598, ""), "", MAIN!$B598) | D598: =IF(EXACT(MAIN!$I598, ""), "", MAIN!$C598) | E598: =IF(EXACT(MAIN!$I598, ""), "", MAIN!$D598) | F598: =IF(EXACT(MAIN!$I594, ""), "", ""&MAIN!$F594)
B599: =IF(EXACT(MAIN!I599, ""), "", MAIN!H599) -> 225000000000058 | C599: =IF(EXACT(MAIN!$I599, ""), "", MAIN!$B599) -> 164000000000596 | D599: =IF(EXACT(MAIN!$I599, ""), "", MAIN!$C599) -> Burhan | E599: =IF(EXACT(MAIN!$I599, ""), "", MAIN!$D599) -> 95000000000003 | F599: =IF(EXACT(MAIN!$I595, ""), "", ""&MAIN!$F595)
B600: =IF(EXACT(MAIN!I600, ""), "", MAIN!H600) | C600: =IF(EXACT(MAIN!$I600, ""), "", MAIN!$B600) | D600: =IF(EXACT(MAIN!$I600, ""), "", MAIN!$C600) | E600: =IF(EXACT(MAIN!$I600, ""), "", MAIN!$D600) | F600: =IF(EXACT(MAIN!$I596, ""), "", ""&MAIN!$F596)
B601: =IF(EXACT(MAIN!I601, ""), "", MAIN!H601) -> 225000000000059 | C601: =IF(EXACT(MAIN!$I601, ""), "", MAIN!$B601) -> 164000000000598 | D601: =IF(EXACT(MAIN!$I601, ""), "", MAIN!$C601) -> Ibrahim Arya Yuda | E601: =IF(EXACT(MAIN!$I601, ""), "", MAIN!$D601) -> 95000000000065 | F601: =IF(EXACT(MAIN!$I597, ""), "", ""&MAIN!$F597)
B602: =IF(EXACT(MAIN!I602, ""), "", MAIN!H602) | C602: =IF(EXACT(MAIN!$I602, ""), "", MAIN!$B602) | D602: =IF(EXACT(MAIN!$I602, ""), "", MAIN!$C602) | E602: =IF(EXACT(MAIN!$I602, ""), "", MAIN!$D602) | F602: =IF(EXACT(MAIN!$I598, ""), "", ""&MAIN!$F598)
... B618: =IF(EXACT(MAIN!I618, ""), "", MAIN!H618) -> 225000000000070 | C618: =IF(EXACT(MAIN!$I618, ""), "", MAIN!$B618) -> 164000000000615 | D618: =IF(EXACT(MAIN!$I618, ""), "", MAIN!$C618) -> Adi | E618: =IF(EXACT(MAIN!$I618, ""), "", MAIN!$D618) -> 95000000000003 | F618: =IF(EXACT(MAIN!$I614, ""), "", ""&MAIN!$F614)
B619: =IF(EXACT(MAIN!I622, ""), "", MAIN!H622) | C619: =IF(EXACT(MAIN!$I622, ""), "", MAIN!$B622) | D619: =IF(EXACT(MAIN!$I622, ""), "", MAIN!$C622) | E619: =IF(EXACT(MAIN!$I622, ""), "", MAIN!$D622) | F619: =IF(EXACT(MAIN!$I615, ""), "", ""&MAIN!$F615)
