Workbook

Sheet RAW EDITED 3 Years
A1: sup_kode | B1: statussupplier | C1: sup_nama | D1: alamat | E1: jenisupplier | F1: subjenisupplier | G1: ket | H1: tlp | I1: email | J1: fax | K1: ket_ASLI | L1: alamat2 | M1: master_kota | N1: master_propinsi | O1: negara | P1: orang | Q1: finance | R1: direktur | S1: hp | T1: namabank | U1: rekbank | V1: reknamabank | W1: tahunoperasi | X1: tahunberdiri | Y1: cabang | Z1: skala | AA1: daftarcabang | AB1: karyawan | AC1: aktif | AD1: npwp | AE1: pkp | AF1: tgl_pkp | AG1: bi_code | AH1: bank_branch | AI1: bank_city
A2: VDR3827 | B2: CV | C2: Alfa Link Mandiri | D2: WJV2+3WV, Lamokato, Kec. Kolaka, Kabupaten Kolaka, Sulawesi Tenggara | E2: Supplier Material Civil | F2: Tools | G2: Untuk Tools dan APD di Kolaka | H2: 081299000537 | I2: - | J2: - | M2: KABUPATEN KOLAKA | N2: SULAWESI TENGGARA | O2: Indonesia | P2: Fransisca | Q2: - | R2: - | T2: Bank Mandiri | U2: 1620002256992 | V2: CV Alfalink Mandiri | W2: - | X2: - | Y2: - | Z2: National | AA2: - | AB2: - | AC2: Y | AE2: f | AF2: 0000-00-00
A3: VDR3823 | B3: CV | C3: Alodia Makmur Abadi | D3: Jalan Garuda No 03 Lamokato , Kolaka | E3: Jasa Kesehatan | F3: Rumah Sakit | G3: untuk MCU | H3: 081356000488 | I3: - | J3: - | M3: KABUPATEN KOLAKA | N3: SULAWESI TENGGARA | O3: Indonesia | P3: Alodia | Q3: - | R3: - | T3: Bank Mandiri | U3: 1620033008800 | V3: Kilinik Alodia | W3: - | X3: - | Y3: - | Z3: National | AA3: - | AB3: - | AC3: Y | AD3: 45.578.379.2-815.000 | AE3: t | AF3: 0000-00-00
A4: VDR3828 | B4: CV | C4: Anugerah Karya Magantha | D4: Jalan Camp Security No. 4 , Sorowako , Luwu Timur | E4: Supplier | F4: Tools Kerja | G4: Pembelian APD di area Site | H4: 08114129780 | I4: anugrah_kry@yahoo.com | J4: - | L4: Jalan Poros Kolaka, Desa Samaenre Kecamatan Wolo | M4: KABUPATEN LUWU TIMUR | N4: SULAWESI SELATAN | O4: Indonesia | P4: Leonardo Sampetoding | Q4: - | R4: - | T4: - | U4: - | V4: - | W4: - | X4: - | Y4: - | Z4: National | AA4: - | AB4: - | AC4: Y | AD4: 02.031.309.4-803.000 | AE4: t | AF4: 0000-00-00
A5: VDR3970 | B5: CV | C5: Artha Jaya Mulya | D5: Jalan Melon No. 265 A RT 001 RW 004 Tanah Merah, Siak Hulu, Kab. Kampar - Riau | E5: Supplier Material Civil | F5: Tanah, Sirtu, Makadam | H5: +62 813-7833-4428 | M5: KABUPATEN KAMPAR | N5: RIAU | O5: Indonesia | P5: Sugito | Q5: - | R5: Sugito | T5: Bank Mandiri | U5: 108 00 2487725 1 | V5: CV Artha Jaya Mulya | Z5: National | AC5: Y | AE5: f | AF5: 0000-00-00
A6: VDR3939 | B6: CV | C6: Borneo Geotec Engginering | D6: Jl Menteng X No 18 RT 003 RW 008 Kel.Menteng Kec. Jekan Raya Palangkaraya Kalimantan tengah | E6: Soil Test | F6: Soil Test | H6: +62 812-5641-5655 | M6: Palangkara Raya | N6: Kalimantan Tengah | O6: Indonesia | P6: Atikah Harahap / Ikhwan | Q6: - | R6: - | T6: Kalimantan Tengah | U6: 1000030000032705 | V6: CV Borneo Geotec Engginering | Z6: National | AC6: Y | AD6: 706175718711000 | AE6: f | AF6: 0000-00-00
A7: VDR3784 | B7: CV | C7: Cipta Aneka Sarana | D7: Jl. M.T. Haryono, Bende, Kec. Kendari, Kota Kendari, Sulawesi Tenggara 93117 | E7: Supplier | F7: Bahan Bangunan | G7: Untuk pembelian bahan Bangunan, tools , alat kerja project Kolaka | H7: 04013192000 | I7: maxcell_dpt@yahoo.co.id | L7: https://www.maxcell.co.id | M7: KOTA KENDARI | N7: SULAWESI TENGGARA | O7: Indonesia | P7: Maxcell Online Service | Q7: - | R7: - | T7: Mandiri | U7: 1620000878888 | V7: CV Cipta Aneka Sarana | W7: - | X7: - | Y7: - | Z7: National | AA7: - | AB7: - | AC7: Y | AD7: 03.242.269.3.811.000 | AE7: t | AF7: 0000-00-00
A8: VDR3696 | B8: CV | C8: CV. Didi Dan Darwis Survey | D8: Komplek Sukamenak Blok Q-90, Kel. Sukamenak Kec. Margahayu Kab. Bandung Prov. Jawa Barat. | E8: Supplier | F8: Survey | G8: Toko Alat2 surveyor dibandung | H8: 082116167001 / +62 821-2990-0025 | I8: dndsurvey90@gmail.com | J8: - | L8: - | M8: KABUPATEN BANDUNG | N8: JAWA BARAT | O8: INDONESIA | P8: DnD Survey Bandung | Q8: - | R8: - | T8: BCA | U8: 8105588948 | V8: Novi Dahlia | W8: - | X8: - | Y8: - | Z8: National | AB8: - | AC8: Y | AE8: f | AF8: 0000-00-00
A9: VDR3516 | B9: CV | C9: CV. Surya Pandawa Nusa | D9: Jl. Utan Kayu Raya No. 104 D Utan Kayu Utara, Matraman Jakarat Timur | E9: Transportation | F9: Trucking | G9: Tranpsorter bisa cover giro pengiriman pole ACPD ke sanana maluku utara | H9: 081314800075 | I9: - | J9: - | L9: - | M9: KOTA JAKARTA TIMUR | N9: DKI JAKARTA | O9: INDONESIA | P9: Juana/Erwin | Q9: - | R9: - | T9: MANDIRI | U9: 0060050150170 | V9: CV. SURYA PANDAWA NUSA | W9: - | X9: - | Y9: - | Z9: National | AA9: - | AB9: - | AC9: Y | AD9: 84.355.656.4-002.000 | AE9: f | AF9: 0000-00-00
A10: VDR3971 | B10: CV | C10: Direct Linus Logistik | D10: Jl. Mawar Dalam Tengah No. 33, Desa/Kelurahan Lagoa, Kec. Koja, Kota Adm. Jakarta Utara, Provinsi DKI Jakarta, Kode Pos: 14270 | E10: Transportation | F10: Trucking | G10: Vendor Transportasi untuk ke Siak (CDD, Fuso, Tronton) | H10: +62 852-1832-5540 | M10: KOTA JAKARTA UTARA | N10: DKI JAKARTA | O10: Indonesia | P10: Nur Excellog | Q10: - | R10: Siti Masitoh | T10: Bank Mandiri | U10: 156 001 930 9493 | V10: Siti Masitoh | Z10: National | AC10: Y | AE10: f | AF10: 0000-00-00
A11: VDR4046 | B11: CV | C11: Edi Jaya Bangunan | D11: Jl. A. yani km. 21, Kel. Pangkalan Durin, Kec. Pangkalan Lada, Kab. Kotawaringin Barat Pmp. Kalimantan Tengah 92.612.879.4-7 I 3.000 | E11: Supplier | F11: Terpal plastik | G11: Terpal | H11: 0813 4970 3982 / | I11: ejbpbun@gmail.com | M11: KABUPATEN KOTAWARINGIN BARAT | N11: KALIMANTAN TENGAH | O11: Indonesia | P11: Edi Nuryanto | Q11: - | R11: - | T11: Bank Mandiri | U11: 159 000 798 6655 | V11: Edy Nuryanto | Z11: National | AC11: Y | AE11: f | AF11: 0000-00-00
A12: VDR3982 | B12: CV | C12: Elang Sega | D12: Jl. Pasanah Gg. Rusa No. 4, Kel. Sidorejo, Kec. Arut Selatan, Kab. Kotawaringin Barat, Prov. Kalimantan Tengah | E12: Supplier Material Civil | F12: Tanah, Sirtu, Makadam | G12: Supplier pasir beton untuk Pangkalan Bun CV. Elang Sega (Priyo Handoko) | H12: 0813 4924 6427 | M12: KABUPATEN KOTAWARINGIN BARAT | N12: KALIMANTAN TENGAH | O12: Indonesia | P12: Priyo Handoko | Q12: - | R12: - | T12: Bank Kalteng | U12: 4000103001616 | V12: Elang Sega | Z12: National | AC12: Y | AE12: f | AF12: 0000-00-00
A13: VDR3773 | B13: CV | C13: Gallazka Teknik | D13: JL. SYECH MUBAROK PERUMAHAN TRIRAKSA VILLAGE 2 BLOK P9 NO 38 KP LENGSIR | E13: Alat dan mesin teknik | F13: Aneka Mesin Diesel, Dynamo & G | G13: Untuk Perbaikan Mesin | H13: 083891165959 | I13: gallazkateknik@gmail.com | J13: - | M13: KABUPATEN TANGERANG | N13: BANTEN | O13: Indonesia | P13: Wartim | Q13: - | R13: Wartim | T13: - | U13: - | V13: - | W13: - | X13: - | Y13: - | Z13: National | AA13: - | AB13: - | AC13: Y | AD13: 62.240.566.0-451.000 | AE13: t | AF13: 0000-00-00
A14: VDR4106 | B14: CV | C14: Ghania Mandiri | D14: Perum. Taman Walet GWA.6 No. 28 RT004/013, Sindang Sari, Pasar Kemis, Kab. Tangerang - Banten | E14: Workshop | F14: Fabrikasi | G14: Pembuatan Name Plate | H14: +62 812-1934-5800 | M14: KABUPATEN TANGERANG | N14: BANTEN | O14: Indonesia | P14: Rahmat Rasyid | Q14: - | R14: - | T14: Bank BNI | U14: 0617 459 363 | V14: CV Ghania Mandiri | Z14: National | AC14: Y | AE14: f | AF14: 0000-00-00
A15: VDR3783 | B15: CV | C15: Istana Gemilang Mandiri | D15: Jalan Haluoleo, BTN Margahayu Regency Blok P Mokau Kambu, Kendari | E15: mobil | F15: Rental Mobil | G15: Untuk kendaraan Project di Kolala | H15: 082254016520 | I15: - | J15: - | M15: KOTA KENDARI | N15: SULAWESI TENGGARA | O15: Indonesia | P15: Hairul Amirudin | Q15: Hairul Amirudin | R15: Hairul Amirudin | T15: - | U15: - | V15: - | W15: - | X15: - | Y15: - | Z15: National | AA15: - | AB15: - | AC15: Y | AD15: 60.862.963.0-811.000 | AE15: t | AF15: 0000-00-00
A16: VDR2001 | B16: CV | C16: Jember Elektrindo Gemilang | D16: Pasar Kenari Lama Lantai Dasar Unit AKS No.184, JL Salemba Raya â€“ Jakarta Pusat | E16: Supplier Material ME | F16: Alat elektrical | G16: Cable AAACS dan AAAC, Peralatan grounding. Berubah nama, sebelumnya Toko Ground Rod | H16: 021-3158970 /0852 15866584 | I16: owner.grd@gmail.com | M16: KOTA JAKARTA PUSAT | N16: DKI JAKARTA | O16: Indonesia | P16: Sigit | Q16: - | R16: - | T16: BRI | U16: 002101020767565 | V16: CV Jember Elektrindo Gemilang | Z16: National | AC16: Y | AE16: f | AF16: 0000-00-00
A17: VDR4023 | B17: CV | C17: Karya Baru | D17: Jl. Utama Pasir Panjang, Kel. Pasir Panjang, Kec. Arut Selatan, Kab. Kotawaringin Barat, Kalimantan Tengah | E17: Supplier Material Civil | F17: Tanah, Sirtu, Makadam | G17: Kuari Pasir, split, gravel | H17: +62 812-5640-4650 / 053223788 | M17: KABUPATEN KOTAWARINGIN BARAT | N17: KALIMANTAN TENGAH | O17: Indonesia | P17: Ninum | Q17: - | R17: - | T17: Bank Mandiri | U17: 159 00 0245500 3 | V17: CV Karya Baru | Z17: National | AC17: Y | AE17: f | AF17: 0000-00-00
A18: VDR3990 | B18: CV | C18: Kawan Inti Jaya | D18: Jl. Peta Selatan Ruko Duta Indah Alpha Blok B.23 Kel. Kalideres Kec. Kalideres, Kota Jakarta Barat. Provinisi DKI Jakarta | E18: Workshop | F18: Alat, Mesin dan suku cadang | G18: Vendor Perbaikan alat bar bending | H18: +62 852-1771-8198 / 021 223 016 73 | M18: KOTA JAKARTA BARAT | N18: DKI JAKARTA | O18: Indonesia | P18: Karyadi | Q18: - | R18: - | T18: Bank BCA | U18: 866-040-8330 | V18: CV. Kawan Inti Jaya | Z18: National | AC18: Y | AE18: f | AF18: 0000-00-00
A19: VDR3803 | B19: CV | C19: Laba Mandiri Lapaopao | D19: Dusun III Polewali Belakang Kantor Desa Lapao | E19: Bahan Bakar | F19: Bahan Bakar Minyak | G19: Untuk suplay BBM kendaraan operational dan mesin | H19: 082187739295 | I19: - | J19: - | L19: RT 001 RW 003 | M19: KABUPATEN KOLAKA | N19: SULAWESI TENGGARA | O19: Indonesia | P19: Musdalifah | Q19: - | R19: Musdalifah | T19: Bank Rakyat Indonesia | U19: 493801020255535 | V19: Musdalifah | W19: - | X19: - | Y19: - | Z19: National | AA19: - | AB19: - | AC19: Y | AD19: 96.960.780.3-815.000 | AE19: f | AF19: 0000-00-00
A20: VDR1025 | B20: CV | C20: Mitra Bengawan Trans | D20: Jl. Ahmad Yani, Desa Bumiharjo RT/RW 009/005 Kec. Kumai Kab. Kotawaringin Barat Prov. Kalimantan Tengah | E20: Rental | F20: Alat Berat | G20: Sewa Forklift | H20: +62 811-5230-808 | K20: Supplier Rolling Door | M20: KABUPATEN KOTAWARINGIN BARAT | N20: KALIMANTAN TENGAH | O20: Indonesia | P20: Annisa | Q20: - | R20: - | S20: "" | T20: Bank Mandiri | U20: 159-00-0075222-9 | V20: Abdullah Nurrahman | Z20: National | AC20: Y | AE20: f | AF20: 0000-00-00
A21: VDR3787 | B21: CV | C21: Mulia Jaya Steel | D21: Jl.H Banawula Sin Apoy, Kendari, Sulawesi Tenggara | E21: Supplier Material Civil | F21: Bahan Bangunan | G21: Penyediaan beton bersertifikat, pipa bulat dll | H21: 081341905779 / 08114099189 | I21: - | J21: - | L21: - | M21: KOTA KENDARI | N21: SULAWESI TENGGARA | O21: Indonesia | P21: - | Q21: - | R21: - | T21: Bank Mandiri | U21: 1620007090909 | V21: Mulia Jaya Steel | W21: - | X21: - | Y21: - | Z21: National | AA21: - | AB21: - | AC21: Y | AE21: f | AF21: 0000-00-00
A22: VDR3866 | B22: CV | C22: Muzima | D22: Perumahan Cikande Permai Blok O, 4 No 23 , Cikande Permai , Serang 42186 | E22: Manufactur | F22: Steel | G22: Fabrikasi Angkur custom | H22: 081295709029 | I22: - | J22: - | M22: KOTA SERANG | N22: BANTEN | O22: Indonesia | P22: Rosid | Q22: - | R22: - | T22: Bank Central Asia | U22: 4921189723 | V22: CV Muzima | W22: - | X22: - | Y22: - | Z22: National | AA22: - | AB22: - | AC22: Y | AE22: f | AF22: 0000-00-00
A23: VDR4179 | B23: CV | C23: Punokawan | D23: Jl Borobudur Utara XV no 11, Manyaran | E23: Rental | F23: Alat Berat | G23: Rental Alat di Semarang untuk pengambilan Tower TE di Gardu Induk Ungaran, untuk kebutuhan proyek SUTT Indorama | H23: 024-76634217 | I23: punokawan_smrg@yahoo.co.id | J23: - | M23: KOTA SEMARANG | N23: JAWA TENGAH | O23: Indonesia | P23: Heri | Q23: - | R23: Budi | T23: BCA | U23: 8035497087 | V23: Dian Permana Sari | W23: - | X23: - | Z23: National | AC23: Y | AE23: f | AF23: 0000-00-00
A24: VDR4045 | B24: CV | C24: Putra Bintang Api | D24: Jl. Utama Pasir Panjang, Kel. Pasir Panjang, Kec. Arut Selatan, Kab. Kotawaringin Barat, Prov. Kalimantan Tengah | E24: Supplier | F24: Tools Kerja | G24: Selang, Tangki Air, Pompa Air | H24: 053224793 | M24: KABUPATEN KOTAWARINGIN BARAT | N24: KALIMANTAN TENGAH | O24: Indonesia | P24: Kian Fung | Q24: - | R24: - | T24: Bank BRI | U24: 0282-01-000302-561 | V24: CV Putra Bintang Api | Z24: National | AC24: Y | AE24: f | AF24: 0000-00-00
A25: VDR4166 | B25: CV | C25: Sangiang Teknik Perkasa | D25: Jl Industri No 27, Babakan cikao | E25: Rental | F25: Alat Berat | G25: Rental Alat Berat Purwakarta | H25: 081222631116 | I25: - | J25: - | M25: KABUPATEN PURWAKARTA | N25: JAWA BARAT | O25: Indonesia | P25: Ishak | Q25: - | R25: - | T25: BNI | U25: 0912901272 | V25: CV Sangiang Teknik Perkasa | W25: - | X25: - | Z25: National | AC25: Y | AE25: f | AF25: 0000-00-00
A26: VDR2981 | B26: CV | C26: Siliwangi jaya | D26: JL. Raya Bojongsoang No.224 (depan SPBU bojongsoang) RT001/007 Buah Batu | E26: Workshop | F26: Alat, Mesin dan suku cadang | G26: Borepile | H26: +62 821-1979-9987 | M26: KOTA BANDUNG | N26: JAWA BARAT | O26: Indonesia | P26: Ira | Q26: Ira | R26: 0 | T26: BCA | U26: 2803000409 | V26: Rachmat Sudrajat | Z26: National | AC26: Y | AE26: f | AF26: 0000-00-00
A27: VDR3912 | B27: CV | C27: Sukses Indo Pratama | D27: Rukan Exclusive Mediterania I No. 10 PIK, Kamal Muara, Penjaringan, Jakarta Utara | E27: Supplier Material ME | F27: Alat elektrical | G27: Distributor kabel merk Federal | H27: +62 811-1909-4011 | M27: Jakarta Utara | N27: DKI Jakarta | O27: Indonesia | P27: Eswin Gozali | Q27: - | R27: - | T27: Bank BCA | U27: 012-791-2029 | V27: CV. Sukses Indo Pratama | Z27: National | AC27: Y | AE27: f | AF27: 0000-00-00
A28: VDR4039 | B28: CV | C28: SUmber Rezeki | D28: Jalan Enggano Nomor 75, Kel. Tanjung Priok, Kec. Tanjung Priok, Kota Adm. Jakarta Utara, Provinsi DKI Jakarta | E28: Rental | F28: Alat Berat | G28: Rental forklift dan crane | H28: 02143931292 / +62 811-9650-3201 | M28: KOTA JAKARTA UTARA | N28: DKI JAKARTA | O28: Indonesia | P28: Evi Sinaga | Q28: - | R28: Dani Santoso | T28: Bank BCA | U28: 007 372 3768 | V28: CV. Sumber Rezeki | Z28: National | AC28: Y | AE28: f | AF28: 0000-00-00
A29: VDR4026 | B29: CV | C29: Sumber Sarana Karya | D29: Jl. Raya Pasir Panjang, Kel. Pasir Panjang, Kec. Arut Selatan, Kab. Kotawaringin Barat, Kalimantan Tengah | E29: Transportation | F29: Trucking | G29: Transporter khusus kuari di pangkalan bun | H29: 053223788 | M29: KABUPATEN KOTAWARINGIN BARAT | N29: KALIMANTAN TENGAH | O29: Indonesia | P29: Ninum | Q29: - | R29: - | T29: Bank Mandiri | U29: 159-00-0310388-3 | V29: CV Sumber Sarana Karya | Z29: National | AC29: Y | AE29: f | AF29: 0000-00-00
A30: VDR3888 | B30: Mandor | C30: Abd Karim | D30: Demanggala, RT 002 RW 004, Desa Balleangin , Pangkajene | E30: Mandor/Subcon | F30: Mandor Civil | G30: Mandor Pekerja Kolaka | H30: 085249859628 | I30: - | J30: - | M30: KABUPATEN PANGKAJENE DAN KEPULAUAN | N30: SULAWESI SELATAN | O30: Indonesia | P30: Abd Karim | Q30: - | R30: - | T30: Bank Rakyat Indonesia | U30: 500901019325533 | V30: Abd Karim | W30: - | X30: - | Y30: - | Z30: National | AB30: - | AC30: Y | AE30: f | AF30: 0000-00-00
A31: VDR4055 | B31: Mandor | C31: Ade Gunawan | D31: Lingk. II Toparuni RT 002 RW 002 Kel. Ulu Wolo Kec. Wolo Kabupaten Kolaka | E31: Mandor/Subcon | F31: Mandor Civil | G31: Mandor untuk pekerjaan pendingan STP dan BW | H31: - | M31: KABUPATEN KOLAKA | N31: SULAWESI TENGGARA | O31: Indonesia | P31: Ade Gunawan | Q31: - | R31: - | T31: Bank Mandiri | U31: 1620007350089 | V31: Ade Gunawan | Z31: National | AC31: Y | AE31: f | AF31: 0000-00-00
A32: VDR3843 | B32: Mandor | C32: Adi Sutrisno | D32: Perum Griya Inti Permata No. J-18 RT 003 RW 027 Martopuro , Purwosari | E32: Mandor/Subcon | F32: Mandor Civil | G32: Untuk Pekerjaan Civil Works Batch 2 Kolaka , rekomendasi PP | H32: 0821571923000 | I32: - | J32: - | M32: KABUPATEN PASURUAN | N32: JAWA TIMUR | O32: Indonesia | P32: Adi Sutrisno | Q32: - | R32: - | T32: Bank Mandiri | U32: 1400004374410 | V32: Adi Sutrisno | W32: - | X32: - | Y32: - | Z32: National | AA32: - | AB32: - | AC32: Y | AE32: f | AF32: 0000-00-00
A33: VDR3987 | B33: Mandor | C33: Afrizal | D33: Jl. Arifin Achmad RT 001 RW 015 Kel. Tangkerang Tengah Kec. Marpoyan Damai Kota Pekanbaru | E33: Mandor/Subcon | F33: Borepile | H33: +62 812-6865-2373 | M33: KOTA PEKANBARU | N33: RIAU | O33: Indonesia | P33: Afrizal | Q33: - | R33: - | T33: Bank Mandiri | U33: 108 001 741 9301 | V33: Afrizal | Z33: National | AC33: Y | AE33: f | AF33: 0000-00-00
A34: VDR4180 | B34: Mandor | C34: Ahmad Sholeh | D34: Kp Cipeuteuy RT 006 RW 002 Cilegong, Kec. Jatiluhur | E34: Mandor/Subcon | F34: Mandor Civil | G34: Mandor Pekerjaan Sipil di Purwakarta | H34: 087754475373 | I34: - | J34: - | M34: KABUPATEN PURWAKARTA | N34: JAWA BARAT | O34: Indonesia | P34: Ahmad Sholeh | Q34: - | R34: - | T34: BNI | U34: 0464850620 | V34: Yuyun | W34: - | X34: - | Z34: National | AC34: Y | AE34: f | AF34: 0000-00-00
A35: VDR4159 | B35: Mandor | C35: Ahmad Syamsudin | D35: Jl. Ahmad Yani Km 18 RT 005 RW 001 Bumi Harjo, Kumai, Kab. Kotawaringin Barat | E35: Mandor/Subcon | F35: Mandor Civil | G35: Pembuatan Site Storage / Office | H35: +62 812-3694-9841 | M35: KABUPATEN KOTAWARINGIN BARAT | N35: KALIMANTAN TENGAH | O35: Indonesia | P35: Ahmad | Q35: - | R35: - | T35: Bank BRI | U35: 7715-01-012518-53-0 | V35: Solikhati | Z35: National | AC35: Y | AE35: f | AF35: 0000-00-00
A36: VDR4251 | B36: Mandor | C36: Ajay | D36: Kp Bojong Sari Kaleur RT 01/05 Balebandung Jaya, Kec. Pabuaran | E36: Mandor/Subcon | F36: Mandor Civil | G36: Pekerjaan Batu Belah | H36: 087778930682 | I36: - | J36: - | M36: KABUPATEN SUBANG | N36: JAWA BARAT | O36: Indonesia | P36: Ajay | Q36: - | R36: - | T36: BCA | U36: 4600297665 | V36: Ajay | W36: - | X36: - | Z36: National | AC36: Y | AE36: f | AF36: 0000-00-00
A37: VDR4221 | B37: Mandor | C37: Alfian Dani | D37: Jln. Sultan Agung Blk LK. III Pantai Burung, Tanjungbalai Selatan, Kota Tanjungbalai | E37: Mandor/Subcon | F37: Mandor Civil | G37: Daily Worker | H37: +62 851-2619-9395 | L37: Jl. Merempan Hilir No. 20 Mempura, Kab. Siak | M37: KOTA TANJUNG BALAI | N37: SUMATERA UTARA | O37: Indonesia | P37: Dani | Q37: - | R37: - | T37: Sea Bank | U37: 901 577 241 697 | V37: Alfian Dani | Z37: National | AC37: Y | AE37: f | AF37: 0000-00-00
A38: VDR3887 | B38: Mandor | C38: Alimuddin | D38: Marranu , RT 000 RW 000 , Kec Lau , Maros | E38: Mandor/Subcon | F38: Mandor Civil | G38: Untuk pekerjaan Kolaka | H38: 081931448554 | I38: - | J38: - | M38: KABUPATEN MAROS | N38: SULAWESI SELATAN | O38: Indonesia | P38: Alimuddin | Q38: - | R38: - | T38: Bank Rakyat Indonesia | U38: 496701016566533 | V38: Alimuddin | W38: - | X38: - | Y38: - | Z38: National | AA38: - | AB38: - | AC38: Y | AE38: f | AF38: 0000-00-00
A39: VDR3109 | B39: Mandor | C39: Ari Setiawan | D39: Wlahar RT 004 RW 001 Wangon - Banyumas | E39: Mandor/Subcon | F39: Mandor Civil | H39: +62 859-7597-3027 | M39: KABUPATEN BANYUMAS | N39: JAWA TENGAH | O39: Indonesia | P39: Ari Setiawan | Q39: 0 | R39: 0 | T39: BCA | U39: 8015507612 | V39: ARI SETIAWAN | Z39: National | AC39: Y | AE39: f | AF39: 0000-00-00
A40: VDR3884 | B40: Mandor | C40: Baharuddin | D40: Dusun II Sratiombo, Kel Tamborasi , Kecamatan Wolo , Kolaka | E40: Mandor/Subcon | F40: Mandor Civil | H40: 082141000545 | I40: - | J40: - | M40: KABUPATEN KOLAKA | N40: SULAWESI TENGGARA | O40: Indonesia | P40: Baharuddin | Q40: - | R40: - | T40: Bank Rakyat Indonesia | U40: 493801029337538 | V40: Baharuddin | W40: - | X40: - | Y40: - | Z40: National | AA40: - | AB40: - | AC40: Y | AE40: f | AF40: 0000-00-00
A41: VDR4144 | B41: Mandor | C41: Budi Prihatin | D41: Kp Citapen 011/004 Desa Sukajaya, Kec. Sukatani | E41: Mandor/Subcon | F41: Sumur Bor | G41: Jasa Sumur Bor di Purwakarta | H41: 085759447668 | I41: - | J41: - | M41: KABUPATEN PURWAKARTA | N41: JAWA BARAT | O41: Indonesia | P41: Budi | Q41: - | R41: - | T41: Seabank Indonesia | U41: 901052691932 | V41: Budi Prihatin | W41: - | X41: - | Z41: National | AC41: Y | AE41: f | AF41: 0000-00-00
A42: VDR4084 | B42: Mandor | C42: Burhanudin | D42: Prum Nirwana Bojong Residence Blok B8 No. 27 RT 003 RW 012 Kel. Bojong Kec. Klapanunggal Kab. Bogor | E42: Mandor/Subcon | F42: Seting Relay | G42: Konfigurasi relay main protection | H42: +62 813-1067-7754 | M42: KABUPATEN BOGOR | N42: JAWA BARAT | O42: Indonesia | P42: Burhanudin | Q42: - | R42: - | T42: Bank BCA | U42: 5520404874 | V42: Burhanudin | Z42: National | AC42: Y | AE42: f | AF42: 0000-00-00
A43: VDR4167 | B43: Mandor | C43: Dian Effendi | D43: Kp Cipeuteuy RT 011 RW 002, Cilegong Kec. Jatiluhur | E43: Mandor/Subcon | F43: Mandor Civil | G43: Mandor Pembuatan Pintu dan Kusen Aluminium | H43: 087820020484 | I43: - | J43: - | M43: KABUPATEN PURWAKARTA | N43: JAWA BARAT | O43: Indonesia | P43: Effendi | Q43: - | R43: - | T43: BNI | U43: 0464850620 | V43: Dian Effendi | W43: - | X43: - | Z43: National | AC43: Y | AE43: f | AF43: 0000-00-00
A44: VDR3819 | B44: Mandor | C44: Dwi Trisno Utomo | D44: Desa Winong RT 004 RW 002 Kedungalar, Ngawi | E44: Mandor/Subcon | F44: Mandor Civil | G44: Untuk pekerjaan di Project Kolaka | H44: 085894327516 | I44: - | J44: - | M44: KABUPATEN NGAWI | N44: JAWA TIMUR | O44: Indonesia | P44: Dwi Trisno Utomo | Q44: - | R44: - | T44: Bank Rakyat Indonesia | U44: 003901117239509 | V44: Dwi Trisno Utomo | W44: - | X44: - | Y44: - | Z44: National | AA44: - | AB44: - | AC44: Y | AE44: f | AF44: 0000-00-00
A45: VDR3905 | B45: Mandor | C45: Erizal | D45: Jl. Abdul Hamid Noor LK. I RT 000 RW 000 Tangsi Binjai Kota | E45: Mandor/Subcon | F45: Mandor Civil | G45: Mandor untuk pekerjaan oxigen station di Kolaka | H45: 0882015386047 | I45: - | J45: - | M45: KOTA BINJAI | N45: SUMATERA UTARA | O45: Indonesia | P45: Erizal | Q45: - | R45: - | T45: BCA | U45: 2490790601 | V45: Erizal | W45: - | X45: - | Y45: - | Z45: National | AA45: - | AB45: - | AC45: Y | AE45: f | AF45: 0000-00-00
A46: VDR4127 | B46: Mandor | C46: Galih Ramadhan | D46: Kp. Cilegong RT 013 RW 003 Kel. Cilegong Kec. Jatiluhur Kab. Purwarkarta - Jawa Barat | E46: Mandor/Subcon | F46: Mandor Civil | G46: Pagar temporary | H46: +62 821-2308-9655 | M46: KABUPATEN PURWAKARTA | N46: JAWA BARAT | O46: Indonesia | P46: Galih | Q46: - | R46: - | T46: Bank Mandiri | U46: 1320013561031 | V46: Galih Ramadhan | Z46: National | AC46: Y | AE46: f | AF46: 0000-00-00
A47: VDR3885 | B47: Mandor | C47: Haerul Gunawan | D47: Dusun II Sinjai , Desa Ulundoro , Kecamatan Aere , Kolaka Timur | E47: Mandor/Subcon | F47: Mandor Civil | G47: Mandor Pekerjaan Kolaka | H47: 085338573116 | I47: - | J47: - | M47: KABUPATEN KOLAKA | N47: SULAWESI TENGGARA | O47: Indonesia | P47: Haerul Gunawan | Q47: - | R47: - | T47: Bank Rakyat Indonesia | U47: 493801030254537 | V47: Haerul Gunawan | W47: - | X47: - | Y47: - | Z47: National | AA47: - | AB47: - | AC47: Y | AE47: f | AF47: 0000-00-00
A48: VDR3782 | B48: Mandor | C48: Harno | D48: Desa Wolo, RT 009 RW 002, Kecamatan Penawangan Grobogan | E48: Mandor/Subcon | F48: Konstruksi Sipil | G48: Untuk Project Kolaka | H48: 081227026200 | I48: - | J48: - | M48: KABUPATEN GROBOGAN | N48: JAWA TENGAH | O48: Indonesia | P48: Harno | Q48: - | R48: - | T48: - | U48: - | V48: - | W48: - | X48: - | Y48: - | Z48: National | AA48: - | AB48: - | AC48: Y | AD48: 76.029.966.9-514.000 | AE48: t | AF48: 0000-00-00
A49: VDR3837 | B49: Mandor | C49: Haswanuddin | D49: Ulu Wolo RT 00 RW 002 Kec Wolo | E49: Mandor/Subcon | F49: Mandor Civil | G49: Pekerja Lokal Wolo untuk pekerjaan Civil Work 2 Kolaka | H49: 085242771124 | I49: - | J49: - | M49: KABUPATEN KOLAKA | N49: SULAWESI TENGGARA | O49: Indonesia | P49: Haswanuddin | Q49: - | R49: - | T49: - | U49: - | V49: - | W49: - | X49: - | Y49: - | Z49: National | AA49: - | AB49: - | AC49: Y | AE49: f | AF49: 0000-00-00
A50: VDR4126 | B50: Mandor | C50: Heryanto Tanjong | D50: Dusun Sepakat RT 000 RW 000 Kel. Sepang Kec. Blangkejereh Kab. Gayo Lues - Aceh | E50: Mandor/Subcon | F50: Mandor Civil | G50: Site Office, Site Storage, Bongkar Pasang Pagar Temporary | H50: +62 852-5516-0961 | M50: KABUPATEN GAYO LUES | N50: ACEH | O50: Indonesia | P50: Heryanto Tanjong | Q50: - | R50: - | T50: Bank BSI | U50: 7240601208 | V50: Heryanto Tanjong | Z50: National | AC50: Y | AE50: f | AF50: 0000-00-00
A51: VDR3074 | B51: Mandor | C51: Iwan Risnawan | D51: Kp Cireureup, RT004/001, Kel Neglasari, Kec Banjaran, Kab Bandung | E51: Mandor/Subcon | F51: Erector | G51: MAndor Erection Busbar | H51: 0853-1796-2234 | M51: KABUPATEN BANDUNG | N51: JAWA BARAT | O51: Indonesia | P51: Bp Iwan | Q51: 0 | R51: 0 | T51: BRI | U51: 114001011972502 | V51: Iwan Risnawan | Z51: National | AC51: Y | AE51: f | AF51: 0000-00-00
A52: VDR3785 | B52: Mandor | C52: Jaelani W | D52: Komplek BTN Mutiara Permai L No 18 RT 002 RW 007 | E52: Mandor/Subcon | F52: Mandor Civil | G52: Untuk Pekerjaan Harian di Kolaka | H52: 082142424216 | I52: - | J52: - | L52: Paccnongang Somba Opu , Gowa | M52: KABUPATEN GOWA | N52: SULAWESI SELATAN | O52: Indonesia | P52: Jaelani W | Q52: - | R52: - | T52: BNI | U52: 821524997 | V52: Jaelani W | W52: - | X52: - | Y52: - | Z52: National | AA52: - | AB52: - | AC52: Y | AD52: 94.613.743.7-807.000 | AE52: t | AF52: 0000-00-00
A53: VDR4171 | B53: Mandor | C53: Jusrial | D53: Bungaraya 01/001, Bungaraya | E53: Mandor/Subcon | F53: Mandor Civil | G53: Mandor Sipil di Kabupaten Siak | H53: 081365559618 | I53: - | J53: - | M53: KABUPATEN S I A K | N53: RIAU | O53: Indonesia | P53: Jusrial | Q53: - | R53: - | T53: BRI | U53: 018901016154508 | V53: Jusrial | W53: - | X53: - | Z53: National | AC53: Y | AE53: f | AF53: 0000-00-00
A54: VDR4114 | B54: Mandor | C54: Kasiyono | D54: Tuah Indrapura RT001/005 Bunga Raya Kabupaten Siak | E54: Mandor/Subcon | F54: Konstruksi Sipil | G54: Pasang Plafon, lampu, dll | H54: 0823-2381-6333 | M54: KABUPATEN S I A K | N54: RIAU | O54: Indonesia | P54: Kasiyono | Q54: - | R54: - | T54: Bank BRI | U54: 7494-01-005080-53-4 | V54: Kasiyono | Z54: National | AC54: Y | AE54: f | AF54: 0000-00-00
A55: VDR3900 | B55: Mandor | C55: Lulus Pastiono | D55: DSN Coyo Rt.004 Rw.009 Mlowo Karangtalun Pulokulon Grobogan | E55: Mandor/Subcon | F55: Mandor Civil | G55: Mandor borongan untuk pekerjaan SS Building area Kolaka | H55: 088294684138 | M55: KABUPATEN GROBOGAN | N55: JAWA TENGAH | O55: Indonesia | P55: Lulus Pastiono | Q55: - | R55: - | T55: BRI | U55: 493801032121536 | V55: Lulus Pastiono | Z55: National | AC55: Y | AE55: f | AF55: 0000-00-00
A56: VDR3909 | B56: Mandor | C56: M. Nasir | D56: Dusun Kenteng RT 002 RW 008 , Kenteng Kec Toroh Grobogan | E56: Mandor/Subcon | F56: Mandor Civil | G56: Untuk Pekerjaan Borongan Oxigen dan Fire Resque Building Kolaka | H56: 081266523419 | I56: - | J56: - | M56: KABUPATEN GROBOGAN | N56: JAWA TENGAH | O56: Indonesia | P56: M Nasir | Q56: - | R56: - | T56: Bank Central Asia | U56: 0811757527 | V56: M Nasir | W56: - | X56: - | Y56: - | Z56: National | AA56: - | AB56: - | AC56: Y | AE56: f | AF56: 0000-00-00
A57: VDR4098 | B57: Mandor | C57: Maikel | D57: Banjarsari 001/02 Bengle, Wonosamodro | E57: Mandor/Subcon | F57: Mandor Civil | G57: Mandor Borongan Rumah Subsidi/ Bangunan Gedung | H57: 082138703832 | I57: - | J57: - | M57: KABUPATEN BOYOLALI | N57: JAWA TENGAH | O57: Indonesia | P57: - | Q57: - | R57: - | T57: BRI | U57: Maikel | V57: 665001044322538 | W57: - | X57: - | Z57: National | AC57: Y | AE57: f | AF57: 0000-00-00
A58: VDR3835 | B58: Mandor | C58: Moh Agus Muslimin | D58: KP Serang RT 001 RW 001 Serang , Cikarang Selatan | E58: Mandor/Subcon | F58: Mandor Civil | G58: Untuk Pekerjaan di Kolaka | H58: 081317883839 | I58: - | J58: - | M58: KABUPATEN BEKASI | N58: JAWA BARAT | O58: Indonesia | P58: Moh Agus Muslimin | Q58: - | R58: - | T58: Bank Central Asia | U58: 8851051201 | V58: Moh Agus Muslimin | W58: - | X58: - | Y58: - | Z58: National | AA58: - | AB58: - | AC58: Y | AE58: f | AF58: 0000-00-00
A59: VDR3938 | B59: Mandor | C59: Muchribian Novianto | D59: Jl Ahmad Yani GG Mihau Rt021/Rw007 Kel. Baru Kec. Arut Selatan Lan Kotawaringin Barat Prov Kalimantan Tengah | E59: Soil Test | F59: Lab Uji Mutu Beton Site Mix De | H59: 081350276481 | M59: KABUPATEN KOTAWARINGIN BARAT | N59: KALIMANTAN TENGAH | O59: Indonesia | P59: Muchribian | Q59: - | R59: - | T59: BRI | U59: 180601003628507 | V59: Muchribian Novianto | Z59: National | AB59: 0813502764 | AC59: Y | AD59: 61.846.905.0-713.000 | AE59: f | AF59: 0000-00-00
A60: VDR3863 | B60: Mandor | C60: Muh Amir Pasang | D60: Dusun Marana , RT 002/001 Marannu, Maros | E60: Mandor/Subcon | F60: Mandor Civil | G60: Untuk Pekerjaan Switch yard dan Lab / CCR | H60: 081931448554 | I60: - | J60: - | M60: KABUPATEN MAROS | N60: SULAWESI SELATAN | O60: Indonesia | P60: Muh Amir Pasang | Q60: - | R60: - | T60: Bank Rakyat Indonesia | U60: 496701016566533 | V60: Alimurdin | W60: - | X60: - | Y60: - | Z60: National | AA60: - | AB60: - | AC60: Y | AE60: f | AF60: 0000-00-00
A61: VDR3993 | B61: Mandor | C61: Muntaji | D61: Desa Bumi Harjo RT008 / RW002 Kel. Bumi Harjo Kec. Kumai Kab. Kotawaringin Barat | E61: Mandor/Subcon | F61: Mandor Civil | G61: Mandor Fence Temporary dan Site Office Storage | H61: +62 821-4999-9290 | M61: KABUPATEN KOTAWARINGIN BARAT | N61: KALIMANTAN TENGAH | O61: Indonesia | P61: Muntaji | Q61: - | R61: - | T61: Bank BRI | U61: 7715 01 017340 53 4 | V61: Sri Warjumi | Z61: National | AC61: Y | AE61: f | AF61: 0000-00-00
A62: VDR4104 | B62: Mandor | C62: Nanda Arista | D62: Jl. Abdu Hamid gg. Kapuk RT014/004 Kumai Hulu Kec. Kumai Kab. Kotawaringin Barat | E62: Mandor/Subcon | F62: Test Commisioning | G62: Mandor untuk test commissioning GI Bun | H62: +62 812-5116-2446 | M62: KABUPATEN KOTAWARINGIN BARAT | N62: KALIMANTAN TENGAH | O62: Indonesia | P62: Nanda | Q62: - | R62: - | T62: Bank BNI | U62: 0457092720 | V62: Nanda Arista | Z62: National | AC62: Y | AE62: f | AF62: 0000-00-00
A63: VDR2466 | B63: Mandor | C63: Nardi Bin Suwirto | D63: Dusun Nenggeng RT008/003 | E63: Mandor/Subcon | F63: Erector | H63: 081294435775 | L63: Cimayasari - Cipendeuy | M63: KABUPATEN SUBANG | N63: JAWA BARAT | O63: Indonesia | P63: Nardi Bin Suwirto | Q63: 0 | R63: 0 | T63: BRI | U63: 377801015351531 | V63: Nata Bin Nardi | Z63: National | AC63: Y | AE63: f | AF63: 0000-00-00
A64: VDR4074 | B64: Mandor | C64: Pirmansyah | D64: Merempan Hilir RT002/001 Merempan Hilir Kec. Mempura Kab. Siak | E64: Mandor/Subcon | F64: Langsir | G64: Mandor untuk pekerjaan pembersihan lumpur bekas bore pile | H64: +62 838-7314-3615 | M64: KABUPATEN S I A K | N64: RIAU | O64: Indonesia | P64: Pirmansyah | Q64: - | R64: - | T64: Bank BRI | U64: 338 601 045 759 532 | V64: M. Syahiril | Z64: National | AC64: Y | AE64: f | AF64: 0000-00-00
A65: VDR4061 | B65: Mandor | C65: Pristianda Erwin Pauzi | D65: Dusun Manggis RT 000/000 Kel. Pulau Banyak Kec. Tanjung Pura Kab. langkat - Sumatera Utara | E65: Mandor/Subcon | F65: Borepile | G65: Mandor Borepile | H65: +62 812-9122-8186 | M65: KABUPATEN LANGKAT | N65: SUMATERA UTARA | O65: Indonesia | P65: Pristianda Erwin Pauzi | Q65: - | R65: - | T65: Bank BRI | U65: 109301032460503 | V65: Pristianda Erwin Pauzi | Z65: National | AC65: Y | AE65: f | AF65: 0000-00-00
A66: VDR3999 | B66: Mandor | C66: Priyo Handoko | D66: Jl. Pasanah Gg. Rusa 4 RT027/000 Sidorejo, Arut Selatan, Kab. Kotawaringin Barat, Kalimantan Tengah | E66: Mandor/Subcon | F66: Mandor Civil | G66: Pekerjaan dinding penahan tanah dan pondasi | H66: 0813 4924 6427 | M66: KABUPATEN KOTAWARINGIN BARAT | N66: KALLIMANTAN TENGAH | O66: Indonesia | P66: Priyo | Q66: - | R66: - | T66: Bank BRI | U66: 0282-01-025770-50-3 | V66: Priyo Handoko | Z66: National | AC66: Y | AE66: f | AF66: 0000-00-00
A67: VDR4207 | B67: Mandor | C67: Ricardo Manurung | D67: Kmp Sukapura 06/01 Kec. Cilincing | E67: Mandor/Subcon | F67: Mandor Civil | G67: Mandor Pekerjaan Civil | H67: 087865313633 | I67: - | J67: - | M67: KOTA JAKARTA UTARA | N67: DKI JAKARTA | O67: Indonesia | P67: Ricardo | Q67: - | R67: - | T67: Mandiri | U67: 1140004375872 | V67: Ricardo Manurung | W67: - | X67: - | Z67: National | AC67: Y | AE67: f | AF67: 0000-00-00
A68: VDR4190 | B68: Mandor | C68: Ryan Prasetyo | D68: Griya Karawaci Blok A 5 No 9 Sukabakti, Kec. Curug | E68: Mandor/Subcon | F68: Mandor Civil | G68: Mandor Jasa Pabrikasi Tiang Pancang | H68: 081293950080 | I68: - | J68: - | M68: KABUPATEN TANGERANG | N68: BANTEN | O68: Indonesia | P68: Ryan | Q68: - | R68: - | T68: BCA | U68: 8840387764 | V68: Ryan Prasetyo | W68: - | X68: - | Z68: National | AC68: Y | AE68: f | AF68: 0000-00-00
A69: VDR4080 | B69: Mandor | C69: Sattria | D69: Jl. Melati Indah Perumahan Jasmine City Garden RT02/01 Kel. Tobekgodang Kec. Briawidya Kota Pekanbaru Provinsi Riau | E69: Mandor/Subcon | F69: Mandor Civil | G69: Pekerjaan Pilecap | H69: +62 852-6065-7666 | M69: KOTA PEKANBARU | N69: RIAU | O69: Indonesia | P69: Sattria | Q69: - | R69: - | T69: Bank BNI | U69: 0503669979 | V69: Sattria | Z69: National | AC69: Y | AE69: f | AF69: 0000-00-00
A70: VDR2478 | B70: Mandor | C70: Solikhin | D70: Saron RT003/004 Tirtomulyo - Plantungan | E70: Mandor/Subcon | F70: Erector | H70: 082294066686 | M70: KABUPATEN KENDAL | N70: JAWA TENGAH | O70: Indonesia | P70: Solikhin | Q70: 0 | R70: 0 | T70: BRI | U70: 591901007200530 | V70: Solikhin | Z70: National | AC70: Y | AE70: f | AF70: 0000-00-00
A71: VDR4058 | B71: Mandor | C71: Suhendri | D71: Dusun Manggis RT 000/000 Kel. Pulau Banyak Kec. Tanjung Pura Kab. Langkat | E71: Mandor/Subcon | F71: Borepile | G71: Mandor Borepile | H71: +62 813-1413-0158 | M71: KABUPATEN LANGKAT | N71: SUMATERA UTARA | O71: Indonesia | P71: Suhendri | Q71: - | R71: - | T71: Bank BRI | U71: 1205 114 106 71 0004 | V71: Mardiah | Z71: National | AC71: Y | AE71: f | AF71: 0000-00-00
A72: VDR4014 | B72: Mandor | C72: Sunanda | D72: Jl Simpang Empat Wajok Hilir Rt001 rw 009 Wajok Hilir Jungkat Kab Mempawah Kalimantan barat | E72: Mandor/Subcon | F72: Bahan Bangunan | H72: - | I72: - | J72: - | M72: KABUPATEN KUBU RAYA | N72: KALIMANTAN BARAT | O72: Indonesia | P72: - | Q72: - | R72: - | T72: BCA | U72: 8855370391 | V72: Sunanda | W72: - | X72: - | Z72: National | AC72: Y | AD72: 6102082012920004 | AE72: t | AF72: 0000-00-00
A73: VDR1777 | B73: Mandor | C73: Sunardi | D73: Dsn Ngloram RT002/002 Kelurahan Pilang Payung Kec Toroh Kab Grobogan | E73: Mandor/Subcon | F73: Mandor OSP | H73: 082317074886 | L73: NIK33150628060001 | M73: KABUPATEN GROBOGAN | N73: JAWA TENGAH | O73: Indonesia | P73: Sunardi | Q73: 0 | R73: 0 | T73: BNI | U73: 0369801434 | V73: Sunardi | Z73: National | AC73: Y | AE73: N | AF73: 0000-00-00
A74: VDR4121 | B74: Mandor | C74: Suprianto | D74: Dusun II B RT000/000 Silomlom, Simpang Empat, Kab. Asahan, Provinsi Sumatera Utara | E74: Mandor/Subcon | F74: Mandor Civil | G74: Mandor dinding penahan tanah | H74: +62 852-7711-5058 | M74: KABUPATEN ASAHAN | N74: SUMATERA UTARA | O74: Indonesia | P74: Suprianto | Q74: - | R74: - | T74: Bank BRI | U74: 3355-01-030717-53-4 | V74: Suprianto | Z74: National | AC74: Y | AE74: f | AF74: 0000-00-00
A75: VDR4168 | B75: Mandor | C75: Susanto | D75: Kp Cikandu 05/06 Bunder, Jatiluhur | E75: Mandor/Subcon | F75: Sumur Bor | G75: Mandor Sumur Bor di Purwakarta | H75: +62 859-6634-4195 | I75: - | J75: - | M75: KABUPATEN PURWAKARTA | N75: JAWA BARAT | O75: Indonesia | P75: Susanto | Q75: - | R75: - | T75: BRI | U75: 325901026209539 | V75: Susanto | W75: - | X75: - | Z75: National | AC75: Y | AE75: f | AF75: 0000-00-00
A76: VDR3962 | B76: Mandor | C76: Sutikno | D76: Sungai Raya RT003/001 Kel. Bunga Raya Kec. Bunga Raya Kab. Siak - Riau | E76: Mandor/Subcon | F76: Mandor Civil | G76: untuk pekerjaan site office dan storage di proyek siak | H76: 085212119241 | M76: KABUPATEN S I A K | N76: RIAU | O76: Indonesia | P76: Sutikno | Q76: - | R76: - | T76: Bank BRI | U76: 749401018094530 | V76: Sutikno | Z76: National | AC76: Y | AE76: f | AF76: 0000-00-00
A77: VDR3859 | B77: Mandor | C77: Sutoyo Bin Durajak | D77: Kp Pondok Ranggon , RT 002 RW 006 Jatimurni Pondok Melati , Bekasi | E77: Mandor/Subcon | F77: Mandor Civil | G77: Mandor yang akan mengerjakan cutting pile di ccr dan laboratory Kolaka | H77: 0813-8806-3146 | I77: - | J77: - | M77: KOTA BEKASI | N77: JAWA BARAT | O77: Indonesia | P77: Sutoyo Bin Durajak | Q77: - | R77: - | T77: Bank Central Asia | U77: 1290007331420 | V77: Sotoyo Bin Durajak | W77: - | X77: - | Y77: - | Z77: National | AA77: - | AB77: - | AC77: Y | AE77: f | AF77: 0000-00-00
A78: VDR3877, VDR3913 | B78: Mandor | C78: Suwarjono | D78: Kedung Waru Kidul RT 002 RW 005, Karangayar | E78: Mandor/Subcon | F78: Mandor Civil | G78: Untuk Project Kolaka | H78: 0853-1312-5585 | I78: - | J78: - | M78: KABUPATEN DEMAK | N78: JAWA TENGAH | O78: Indonesia | P78: Suwarjono | Q78: - | R78: - | T78: Bank Negara Indonesia | U78: 0950737145 | V78: Suwarjono | W78: - | X78: - | Y78: - | Z78: National | AA78: - | AB78: - | AC78: Y | AE78: f | AF78: 0000-00-00
A79: VDR2891 | B79: Mandor | C79: Suyoto | D79: Dusun Kenteng RT 005/008 Kenteng - Toroh | E79: Mandor/Subcon | F79: Mandor Civil | H79: +62 812-6878-8809 | M79: KABUPATEN GROBOGAN | N79: JAWA TENGAH | O79: Indonesia | P79: Suyoto | Q79: 0 | R79: 0 | T79: BCA | U79: 0810665378 | V79: Suyoto | Z79: National | AC79: Y | AE79: f | AF79: 0000-00-00
A80: VDR2362 | B80: Mandor | C80: Tajudin | D80: KP Bongkok RT 004 RW 014 Kel/Desa Mekarjaya Kec. Cikalong Wetan Kab. Bandung Barat Jawa Barat | E80: Mandor/Subcon | F80: Mandor Civil | G80: Mandor Sipil Cibatu | H80: 0 | I80: 0 | J80: 0 | L80: KP Bongkok RT 004 RW 014 Kel/Desa Mekarjaya Kec. C | M80: KABUPATEN BANDUNG BARAT | N80: JAWA BARAT | O80: Indonesia | P80: 0 | Q80: 0 | R80: 0 | T80: Bank BRI | U80: 3267-01-046088-53-6 | V80: Tajudin | W80: 0 | X80: 0 | Y80: 0 | Z80: National | AA80: 0 | AB80: 0 | AC80: Y | AE80: f | AF80: 0000-00-00
A81: VDR3886 | B81: Mandor | C81: Teguh Ari Wibowo | D81: Dusun Pelemsari RT 05 RW 08 Desa Pojok, Kecamatan Pulokulon Grobogan | E81: Mandor/Subcon | F81: Mandor Civil | G81: Mandor pekerjaan di Kolaka | H81: 0895324841841 | I81: - | J81: - | M81: KABUPATEN GROBOGAN | N81: JAWA TENGAH | O81: Indonesia | P81: Tegyh Ari wibowo | Q81: - | R81: - | T81: Bank Rakyat Indonesia | U81: 021601017128539 | V81: Teguh Ari Wibowo | W81: - | X81: - | Y81: - | Z81: National | AA81: - | AB81: - | AC81: Y | AE81: f | AF81: 0000-00-00
A82: VDR4184 | B82: Mandor | C82: Tengku Wahyudi | D82: Jl Raya Cilincing No 51 07/001, Kec. Koja | E82: Mandor/Subcon | F82: Mandor Civil | G82: Mandor Pekerjaan Civil dan Struktur | H82: +62 822-4970-0074 | I82: - | J82: - | M82: KOTA JAKARTA UTARA | N82: DKI JAKARTA | O82: Indonesia | P82: Yudhi | Q82: - | R82: - | T82: BNI | U82: 0983231814 | V82: Tengku Wahyudi | W82: - | X82: - | Z82: National | AC82: Y | AE82: f | AF82: 0000-00-00
A83: VDR2640 | B83: Mandor | C83: Usman | D83: Dusun Ciawitali RT004/004 Pamotan - Kalipucang | E83: Supplier Material Civil | F83: Stringing | H83: +62 853-5989-1916 | M83: KABUPATEN TASIKMALAYA | N83: JAWA BARAT | O83: Indonesia | P83: Usman | Q83: 0 | R83: 0 | T83: BRI | U83: 4021 0102 8632 534 | V83: Usman | Z83: National | AC83: Y | AE83: f | AF83: 0000-00-00
A84: VDR4173 | B84: Mandor | C84: Yeyet Abdulrahman | D84: Jl SIliwangi 9, Nagri Kidul, Kec. Purwakarta | E84: Mandor/Subcon | F84: Service AC | G84: Jasa Service dan Instalasi AC di Purwakarta | H84: 081314712177 | I84: - | J84: - | M84: KABUPATEN PURWAKARTA | N84: JAWA BARAT | O84: Indonesia | P84: Yeyet | Q84: - | R84: - | T84: BCA | U84: 2312390737 | V84: Yeyet Abdulrahman | W84: - | X84: - | Z84: National | AC84: Y | AE84: f | AF84: 0000-00-00
A85: VDR4203 | B85: Mandor | C85: Yosefa Trisna Aroma Furi | D85: Nirwana Estate blok . J NO. 03 RT. 003 RW. 013 pakansari Cibinong | E85: Mandor/Subcon | F85: Mandor Civil | G85: jasa sipil pemasangan tiang pancang | H85: +62 812-9828-0909 | M85: Bogor | N85: jawa barat | O85: Indonesia | P85: Yosefa Trisna Aroma Furi | Q85: - | R85: - | T85: BCA | U85: 4780 789 099 | V85: Yosefa Trisna Aroma Furi | Z85: National | AC85: Y | AD85: 42.734.367.8-403.000 | AE85: f | AF85: 0000-00-00
A86: VDR3286 | B86: Mandor | C86: Zepridani M K | D86: Kp. Cimuning RT 004/002 - Mustika jaya | E86: Mandor/Subcon | F86: Borepile | H86: +62 813-8053-6580 | M86: KOTA BEKASI | N86: JAWA BARAT | O86: Indonesia | P86: Zepridani | Q86: 0 | R86: 0 | T86: BCA | U86: 8850401943 | V86: Zepridani M K | Z86: National | AC86: Y | AD86: NIK 3275040210760023 | AE86: t | AF86: 0000-00-00
A87: VDR0131 | B87: Other | C87: Toko Berkah | D87: Jl. Mess Dalam RT 012 RW 017 Kel. Kebon Melati Kec. Tanah Abang, Jakarta Pusat, DKI Jakarta | E87: Supplier Others | F87: Terpal plastik | G87: Terpal Plastik A20 | H87: +62 856-4375-6205 / 021-3160282 | M87: Jakarta Pusat | N87: DKI Jakarta | O87: Indonesia | P87: Abdurrahman | Q87: - | R87: - | S87: "" | T87: Bank BCA | U87: 7060532731 | V87: Abdurrahman | AC87: Y | AE87: f | AF87: 0000-00-00
A88: VDR4035 | B88: Other | C88: Ade Saputra | D88: Kp. Godang RT 002 RW 002 Kel. Tambang Kec. Tambang Kab. Kampar | E88: Supplier Material Civil | F88: Tanah, Sirtu, Makadam | G88: Supplier Pasir dari Teratak Buluh | H88: 0822-8555-7077 | M88: KABUPATEN KAMPAR | N88: RIAU | O88: Indonesia | P88: Ade | Q88: - | R88: - | T88: Bank BNI | U88: 0828186596 | V88: Ade Saputra | Z88: National | AC88: Y | AE88: f | AF88: 0000-00-00
A89: VDR4069 | B89: Other | C89: Aef Sugihartono | D89: Dusun 02 RT 004 RW 004 Karangwuni Sedong Kab. Cirebon, Jawa Barat | E89: Rental | F89: Rental Alat Berat | G89: Dump Truck | H89: 0813-1187-3910 | M89: KABUPATEN CIREBON | N89: JAWA BARAT | O89: Indonesia | P89: Aef | Q89: - | R89: - | T89: Bank BCA | U89: 3040644856 | V89: Aefsugihartono | Z89: National | AC89: Y | AE89: f | AF89: 0000-00-00
A90: VDR3942 | B90: Other | C90: Agung Pranata | D90: Jl. Beringin Perum BSD perdana Blok T No. 15 RT 003 RW 004 Kel Sungaisibam Kec Dinawidya | E90: Soil Test | F90: Soil Test | G90: SONDIR BORING | H90: 081371428400 | M90: Pekanbaru | N90: KEPULAUAN RIAU | O90: Indonesia | P90: Agung Pranata | Q90: - | R90: - | T90: BCA | U90: 8456016150 | V90: Agung Pranata | Z90: National | AC90: Y | AE90: f | AF90: 0000-00-00
A91: VDR3954 | B91: Other | C91: Ahmad Hamidi | D91: Jl. Manungga RT 002 RW 005 Desa Tuahmadani Kec. Tampan Kota Pekanbaru Prov. Riau | E91: Supplier Others | F91: Lab | H91: +62 812-7717-8717 | M91: KOTA PEKANBARU | N91: RIAU | O91: Indonesia | P91: Ridho - Staff Ahmad Hamid | Q91: - | R91: - | T91: Bank BNI | U91: 978797025 | V91: Ahmad Hamidi | Z91: National | AC91: Y | AE91: f | AF91: 0000-00-00
A92: VDR4033 | B92: Other | C92: Ahmad Suhadi | D92: DK Banteng Urip RT 004 RW 002 Kedungwinong Kec. Sukolilo Kab. Pati | E92: Mandor/Subcon | F92: Borepile | G92: Mandor Borepile | H92: +62 822-5274-8523 | M92: KABUPATEN PATI | N92: JAWA TENGAH | O92: Indonesia | P92: Ahmad Suhadi | Q92: - | R92: - | T92: Bank BNI | U92: 07-30000-339 | V92: Bpk Ahmad Suhadi | Z92: National | AC92: Y | AE92: f | AF92: 0000-00-00
A93: VDR3875 | B93: Other | C93: Aksesmandiri - Tokopedia | D93: Jakarta | E93: Toko Online | F93: Internet Dan Networking | G93: Fingerprint | H93: - | I93: - | J93: - | L93: - | M93: KOTA JAKARTA PUSAT | N93: DKI JAKARTA | O93: Indonesia | P93: Aksesmandiri - Tokopedia | Q93: - | R93: - | T93: Virtual Account | U93: Virtual Account | V93: Virtual Account | W93: - | X93: - | Y93: - | Z93: National | AA93: - | AB93: - | AC93: Y | AE93: f | AF93: 0000-00-00
A94: VDR4027 | B94: Other | C94: Ali Mufti Wardhani | D94: Jl. Panglima Utar RT 006 RW 000 Kel. Sungai Tendang Kec. Kumai Kab. Kotawaringin Barat | E94: Transportation | F94: Trucking | G94: Transporter Lokal | H94: +62 853-5033-4280 | M94: KABUPATEN KOTAWARINGIN BARAT | N94: KALIMANTAN TENGAH | O94: Indonesia | P94: Ali Mufti | Q94: - | R94: - | T94: Bank Mandiri | U94: 1590002966207 | V94: Ali Mufti Wardhani | Z94: National | AC94: Y | AE94: f | AF94: 0000-00-00
A95: VDR4186 | B95: Other | C95: Ali Sopandi | D95: Cilegong Utara RT 002 RW 001 Jatiluhur, Kec. Jatiluhur | E95: Pemilik Lahan | F95: Sewa Rumah | G95: Sewa Mess Purwakarta | H95: 081381828537 | I95: - | J95: - | M95: KABUPATEN PURWAKARTA | N95: JAWA BARAT | O95: Indonesia | P95: Ali | Q95: - | R95: - | T95: BCA | U95: 2311110502 | V95: Ali Sopandi | W95: - | X95: - | Z95: National | AC95: Y | AE95: f | AF95: 0000-00-00
A96: VDR4017 | B96: Other | C96: Apriati Isna Mulia (Toko Ocu Intan) | D96: Balai Kayang RT 004 RW 003 Kel. Kampung Rempak Kec. Siak Kab. Siak | E96: Supplier | F96: General | G96: Kayu, Kayu Kaso, Papan | H96: +62 813-7496-6558 | M96: KABUPATEN S I A K | N96: RIAU | O96: Indonesia | P96: Apriati Isna Mulia | Q96: - | R96: - | T96: Bank BRI | U96: 338 601 005 409 509 | V96: Intan Arini | Z96: National | AC96: Y | AE96: f | AF96: 0000-00-00
A97: VDR1326 | B97: Other | C97: ARDHIS COLLECTION | D97: Harapan Indah, Jl. Nusa Indah XIV Blok MD. 16-17 Pejuang Medan Satria, Bekasi | E97: Supplier | F97: Overhead | H97: 021-88865032, HP : 081388272713 | I97: iwanridwantaufiq@ymail.com, ha | J97: 021-88865032 | M97: KABUPATEN BEKASI | N97: JAWA BARAT | O97: Indonesia | P97: Iwan Ridwan Taufiq | Q97: - | R97: - | T97: BCA | U97: 5210538218 | V97: Iwan Ridwan Taufiq | W97: 10 | X97: 2003 | Z97: National | AB97: 12 | AC97: Y | AE97: N | AF97: 0000-00-00
A98: VDR4229 | B98: Other | C98: Arsyad | D98: Jl. Kubang Raya RT 003 RW 017 Kel. Tuahkarya Kec. Tuah Madani, Kota Pekanbaru, Prov. Riau | E98: Rental | F98: Tools | G98: Mesin Stamper | H98: 0812-3037-1112 | M98: KOTA PEKANBARU | N98: RIAU | O98: Indonesia | P98: Arsyad | Q98: - | R98: - | T98: BCA | U98: 8455966805 | V98: Arsyad | Z98: National | AC98: Y | AE98: f | AF98: 0000-00-00
A99: VDR0967 | B99: Other | C99: Asuransi Ramayana | D99: Jl. Kebon Sirih No. 48 | E99: Insurance Consultant, Guarante | F99: Overhead | G99: Pass Without Comment | H99: 62 2131937148 | J99: 62 2131934825 | M99: Jakarta | O99: Indonesia | P99: Lusi Andriani | S99: "" | T99: Mandiri Cab Thamrin | U99: 103 00 9951364 4 | V99: PT. Asuransi Ramayana | Z99: National | AC99: Y
A100: VDR3841 | B100: Other | C100: Bambang Setiawan ( Wilda Trans ) | D100: Jalan Abdullah DG Sirua , RT 001 RW 001 Batua Manggala | E100: Transportation | F100: Trucking | G100: Pengiriman Material Makassar Wolo | H100: - | I100: - | J100: - | M100: KOTA MAKASSAR | N100: SULAWESI SELATAN | O100: Indonesia | P100: Bambang Setiawan | Q100: - | R100: - | T100: Bank Central Asia | U100: 7891135002 | V100: Bambang Setiawan | W100: - | X100: - | Y100: - | Z100: National | AA100: - | AB100: - | AC100: Y | AD100: 13.253.972.7-805.000 | AE100: t | AF100: 0000-00-00
...

Sheet PLN
A1: VDR0704 | B1: Other | C1: Dewan Pimpinan Pusat Serikat PT PLN | D1: Jl.Trinojoyo Blok M1/135 kebayoran baru jakarta se | E1: Supplier Others | G1: Pass Without Comment | H1: 021-7261122/7262234 | L1: Partisipasi Iklan | N1: Jakarta Selatan | P1: Indonesia | Q1: Frita | T1: Bank Mandiri Cabang Utama Roxy Mas Jakarta Pusat | U1: 117.00000.65086 | V1: PT Bagassindo Media Persada | Z1: National | AC1: Y
A2: VDR1410 | B2: Other | C2: Koperasi Pegawai PLN Pusat | D2: Jakarta Pusat | E2: Badan Pemerintah | F2: General | H2: 0 | J2: 0 | N2: KOTA JAKARTA PUSAT | O2: DKI JAKARTA | P2: Indonesia | Q2: 0 | R2: 0 | S2: 0 | T2: Mandiri | U2: 1260004878756 | V2: Koperasi Pegawai PLN Pusat | Z2: National | AC2: Y | AE2: N | AF2: 0000-00-00
A4: VDR3614 | C4: PERUSAHAAN LISTRIK NEGARA (PLN) | D4: Jl. Trunojoyo M I No. 135 Melawai Kebayoran, Jakarta Selatan Baru DKI Jakarta | E4: Sertifikasi | F4: Jasa Sertifikasi | G4: SLO Transmisi BATAM SUTT 150KV (46 Tower) | H4: 81317528644 | I4: - | J4: - | K4: - | N4: KOTA JAKARTA SELATAN | O4: DKI JAKARTA | P4: INDONESIA | Q4: Mba Rizki Andin | R4: - | S4: - | T4: MANDIRI | U4: PLN | V4: 127.000.424.2366 | W4: - | X4: - | Y4: - | Z4: National | AC4: Y | AD4: 01.001.629.3-051.000 | AE4: t | AF4: 0000-00-00
A5: VDR0724 | C5: PLN (PERSERO) | D5: Wilayah Riau dan Kepulauan Riau Cabang Tanjung Pin | E5: Supplier Others | G5: Pass Without Comment | H5: 0771-23755-24406-210 | I5: TBA | J5: 0771-21148 | K5: TBA | L5: PLN (PERSERO) | N5: Tanung Pinang | P5: Indonesia | Q5: Dedi J | T5: Bayar Langsung | U5: Bayar Langsung | V5: Bayar Langsung | W5: TBA | X5: TBA | Y5: TBA | Z5: National | AA5: TBA | AC5: Y
A6: VDR1401 | C6: PLN (Persero) Area Pelayanan Jaringan Klaten | D6: Jl, Perintis Kemerdekaan No. 3A Klaten | E6: Supplier Others | F6: AKLI | G6: PLN cabang KLaten utk pembayaran BP | H6: 0272-320912 | I6: apklaten@telkom.net | J6: 0272-326073 | K6: apklaten@telkom.net | N6: KABUPATEN KLATEN | O6: JAWA TENGAH | P6: Indonesia | Q6: I Ketut Wiriana | R6: Budi Pratomo | S6: Nur Pamuji | T6: bayar langsung di Loket PLN | U6: bayar langsung di Loket PLN | V6: bayar langsung di Loket PLN | Z6: National | AC6: Y | AE6: N | AF6: 0000-00-00
A7: VDR1161 | C7: PLN (Persero) Area Pelayanan Jaringan Salatiga | D7: Jl. Diponegoro No. 19 | E7: Mandor/Subcon | F7: Alat elektrical | G7: utk pembayaran BP site hotel grand wahid | H7: 0298-326883 | I7: pln-slg@indo.net.id | J7: 0298-324671 | K7: pln-slg@indo.net.id | N7: Salatiga | P7: Indonesia | Q7: Zubaidah (Manager APJ Sal | R7: Sri Wahyuni | S7: Zubaidah (Manager APJ Sal | T7: Dibayar langsung di Loket PLN | U7: Dibayar langsung di Loket PLN | V7: Dibayar langsung di Loket PLN | Z7: National | AC7: Y | AE7: N | AF7: 0000-00-00
A8: VDR3615 | C8: PLN (Persero) Pusat Sertifikasi | D8: Jalan Laboratorium, Duren Tiga, Jakarta Selatan Jakarta, 12760 | E8: Sertifikasi | F8: Jasa Sertifikasi | G8: Pusat Sertifikasi | H8: (021) 790 0034 | I8: niaga.pusertif@pln.co.id | J8: (021) 798 2034 | K8: niaga.pusertif@pln.co.id | N8: KOTA JAKARTA SELATAN | O8: DKI JAKARTA | P8: INDONESIA | Q8: PLN (Persero) Pusat Serti | R8: - | S8: - | T8: MANDIRI | U8: 127.000.424.2366 | V8: PLN | W8: - | X8: - | Y8: - | Z8: National | AB8: - | AC8: Y | AD8: 01.001.629.3-051.000 | AE8: t | AF8: 0000-00-00
A9: VDR2799 | C9: PLN (PERSERO) UIW SUMATERA UTARA, UP3 RANTAU PRAPAT, ULP TANJUNG BALAI | D9: TANJUNG BALAI | E9: Supplier Others | F9: Transmisi | G9: PLN untuk Penerangan Sementara | H9: 061-000000 | N9: KOTA TANJUNG BALAI | O9: SUMATERA UTARA | P9: INDONESIA | Q9: PT PLN | R9: 0 | S9: 0 | T9: Bank | U9: 1251129001298 | V9: PLN | Z9: National | AC9: Y | AE9: f | AF9: 0000-00-00
A10: VDR1073 | C10: PLN (Persero) Wilayah Aceh | D10: Jl. Malikussaleh No. 01 Lcg Garam | E10: Mandor/Subcon | F10: AKLI | G10: Pass Without Comment | H10: 0645-630255 | J10: 0645-48000 | N10: Lhokseumawe | P10: Indonesia | Q10: Kamaddin | R10: tba | S10: tba | T10: handcarry by finance PJO Medan | U10: handcarry by finance PJO Medan | V10: handcarry by finance PJO Medan | Z10: National | AC10: Y | AE10: N | AF10: 0000-00-00
A11: VDR1458 | C11: PLN Area Pelayanan Jaringan Pacitan | D11: Jl. Jendral A. Yani No. 94 Pacitan | E11: Distributor | F11: Alat elektrical | G11: PLN di area Pacitan (utk pengurusan BP site PLTU Pacitan) | H11: (0357)-881010 | J11: (0357)-881010. | N11: KABUPATEN PACITAN | O11: JAWA TIMUR | P11: Indonesia | Q11: Susanto Ardyanto | R11: Susanto Ardyanto | S11: Susanto Ardyanto | T11: dibayar langsung di loket PLN | U11: dibayar langsung di loket PLN | V11: dibayar langsung di loket PLN | Z11: National | AC11: Y | AE11: N | AF11: 0000-00-00
A12: VDR1566 | C12: PLN area pelayanan jaringan Surabaya | D12: Jl. Bratang Binangun Komp Manyaran Megah Indah Plaza BI A No. 31 | E12: Badan Pemerintah | F12: AKLI | G12: utk pembayaran BPUJL di area surabaya | H12: 031-5026556 | J12: 031-5029769 | N12: KOTA SURABAYA | O12: JAWA TIMUR | P12: Indonesia | Q12: Heru Subagyo | R12: Heru Subagyo | S12: Heru Subagyo | T12: dibayar langsung di loket | U12: dibayar langsung di loket | V12: dibayar langsung di loket | Z12: National | AC12: Y | AE12: N | AF12: 0000-00-00
A13: VDR0750 | C13: PLN Cab Medan | D13: Jl. Pembakitan Listirk No. 1 Paya Pasir Medan Ma | E13: Akli | G13: Pass Without Comment | H13: 061-6850064 | I13: TBA | J13: 061-6853842 | K13: TBA | N13: Medan | P13: Indonesia | Q13: Pak Marbun | T13: BCA | U13: 217305001 | V13: PT Qdc Technologies | W13: TBA | X13: TBA | Y13: TBA | Z13: National | AA13: TBA | AB13: TBA | AC13: Y
A14: VDR0962 | C14: PLN Distribusi Jawa Barat dan Banten Unit Jaringan | D14: Jl Raya Jakarta Bogor Km 31 No 16 Cimanggis | E14: Mandor/Subcon | F14: General | G14: Pass Without Comment | H14: 8730325 | J14: 8730324 | N14: Jakarta | P14: Indonesia | Q14: Tirta Rachim | T14: Mandiri Cab Gandaria | U14: 129.000.102.9467 | V14: PT. PLN Distribusi Jawa Barat dan Banten Unit Jari | Z14: National | AC14: Y
A15: VDR0875 | C15: PLN Kantor Layanan Pondok Kopi | D15: l. Sentra Primer Baru Timur, Pulogebang | E15: Travel Agency | G15: Pass Without Comment | H15: 021) 4806504, 480650 | I15: www.pln.co.id | J15: (021) 4807160 | K15: www.pln.co.id | L15: PLN PERSERO-URGENT | N15: Pondok Kopi | P15: Indonesia | Q15: Customer Service | T15: Cash Bayar langsung di Loket PLN | U15: Cash Bayar langsung di Loket PLN | V15: Cash Bayar langsung di Loket PLN | W15: TBA | X15: TBA | Y15: TBA | Z15: National | AA15: TBA | AB15: TBA | AC15: Y
A16: VDR0674 | C16: PLN Rayon PANAM | D16: Jl. H. Subrantas, PANAM, Kec. Tampan | E16: Akli | G16: Pass Without Comment | H16: 0761-62481 | I16: TBA | J16: 0761-66444 | K16: TBA | N16: Kota Pekanbaru | P16: Indonesia | Q16: TBA | T16: TBA | U16: TAB | V16: TBA | W16: TBA | X16: TBA | Y16: TBA | Z16: National | AA16: TBA | AC16: Y
A17: VDR0486 | C17: PT .PLN (PERSERO) - UPJ Garut Leles | D17: JL Raya Leles No.64 Leles Kab.Garut | E17: "" | G17: Pass Without Comment | H17: 0262-455671 | J17: 0262-457974 | N17: Garut | P17: Jawa Barat | AC17: Y
A18: VDR0487 | C18: PT PLN (PERSERO) - UPJ Majalaya | D18: JL Pamagersari No.26 Majalaya Kab.Bandung 40382 | E18: "" | G18: Pass Without Comment | H18: 022-5950354 | J18: 022-5951530 | N18: Bandung | P18: Indonesia | AC18: Y
A19: VDR0823 | C19: PT PLN (PERSERO) Salatiga Kota | D19: Jl Salatiga Kota Jawa Tengah | E19: Akli | G19: Pass Without Comment | H19: 024-123 | I19: www.pln.co.id | J19: 024-123 | K19: www.pln.co.id | L19: PLN | N19: Salatiga | P19: Jawa Tengah | Q19: Customer Service | T19: Dibayar langsung ke Loket PLN | U19: Dibayar langsung ke Loket PLN | V19: Dibayar langsung ke Loket PLN | W19: tba | X19: tba | Y19: tba | Z19: National | AA19: tba | AB19: tba | AC19: Y
A20: VDR0488 | C20: PT PLN PERSERO -UPJ BATAM | D20: Jl.Engku Putri, Batam Center | E20: "" | G20: Pass Without Comment | H20: (62-778) 463 150-153 | J20: (62-778) 463 143 | N20: Batam | P20: Indonesia | T20: Bank BRI | U20: 0621-01-000048-30-3 | V20: PT PLN | AC20: Y
A21: VDR0879 | C21: PT. PLN (PERSERO) DISTRIBUSI JAKARTA RAYA DAN TANG | D21: Jl. MIR Rais no. 1 Jakarta 10110 | E21: Supplier Others | G21: Pass Without Comment | H21: 021-345 4000 | I21: humasjaya@pln.co.id | J21: 021-385 6761 | K21: humasjaya@pln.co.id | L21: PLN Connection | M21: - | N21: Jakarta | P21: INDONESIA | Q21: - | T21: - | U21: - | V21: - | W21: - | X21: - | Y21: - | Z21: National | AA21: - | AB21: - | AC21: Y
A22: VDR2071 | C22: PT. PLN Persero | D22: Jl. Trunojoyo Blok M I/135 Melawai Kebayoran Baru Jakarta Selatan | E22: Supplier | F22: Building Management | G22: 0 | H22: (021) 7261122 | I22: 0 | J22: 0 | K22: 0 | M22: Jl. Trunojoyo Blok M I/135 Melawai Kebayoran Baru | N22: KOTA JAKARTA SELATAN | O22: DKI JAKARTA | P22: Indonesia | Q22: 0 | R22: 0 | S22: 0 | T22: 0 | U22: 0 | V22: 0 | W22: 0 | X22: 0 | Y22: 0 | Z22: National | AA22: 0 | AB22: 0 | AC22: Y | AE22: N | AF22: 0000-00-00
A23: VDR2236 | C23: PT. PLN Persero Jasa Diklat | D23: Jl. Harsono RM No. 59 Ragunan Pasar Minggu Jakarta Selatan 12550 | E23: University | F23: General | G23: Training | H23: 021 782 9525 | I23: 0 | J23: 021 7811 294 | K23: 0 | M23: Jl. Harsono RM No. 59 Ragunan Pasar Minggu Jakarta | N23: KOTA JAKARTA SELATAN | O23: DKI JAKARTA | P23: Indonesia | Q23: 0 | R23: 0 | S23: 0 | T23: Bank BRI | U23: 0339 01 000171 301 | V23: PT. PLN (Persero) Jasa Diklat | W23: 0 | X23: 0 | Y23: 0 | Z23: National | AA23: 0 | AB23: 0 | AC23: Y | AE23: N | AF23: 0000-00-00
A24: VDR0545 | C24: UPT - PLN CIANJUR KOTA | D24: CIANJUR | G24: Pass Without Comment | L24: PLN CIANJUR | N24: Jawa Barat | AC24: Y

Sheet REF - InstitutionType
B2: Sys_PID | C2: Name | D2: Prefix | E2: Suffix
B4: 141000000000001 | C4: Others
B5: 141000000000002 | C5: Persekutuan Komanditer | D5: CV.
B6: 141000000000003 | C6: Perusahaan Perorangan
B7: 141000000000004 | C7: Swasta Perseroan Terbatas (Tertutup) | D7: PT.
B8: 141000000000005 | C8: Swasta Perseroan Terbatas (Terbuka) | D8: PT. | E8: , Tbk
B9: 141000000000006 | C9: BUMN Perseroan Terbatas (Tertutup) | D9: PT. | E9: (Persero)
B10: 141000000000007 | C10: BUMN Perseroan Terbatas (Terbuka) | D10: PT. | E10: (Persero), Tbk
B11: 141000000000008 | C11: Perseroan Terbatas Perorangan | D11: PT.
B12: 141000000000009 | C12: BUMN Perusahaan Jawatan | D12: Perjan
B13: 141000000000010 | C13: BUMN Perusahaan Umum | D13: Perum
B14: 141000000000011 | C14: Firma | D14: FA.
B15: 141000000000012 | C15: Koperasi | D15: Koperasi
B16: 141000000000013 | C16: Yayasan
B17: 141000000000014 | C17: Lembaga Pemerintah
B18: 141000000000015 | C18: Usaha Dagang | D18: UD.
B19: 141000000000016 | C19: Perusahaan Dagang | D19: PD.
B20: 141000000000017 | C20: Perusahaan Otobus | D20: PO.
B21: 141000000000018 | C21: Toko | D21: Toko
B22: 141000000000019 | C22: Toko Bangunan | D22: TB.
B23: 141000000000020 | C23: Toko Online Market Place | D23: Toko Online
B24: 141000000000021 | C24: Mandor | D24: Mandor
B25: 141000000000022 | C25: Badan Penyelenggara Jaminan Sosial | D25: BPJS
B26: 141000000000023 | C26: Asosiasi Perusahaan

Sheet SEED - Institution
B2: Name | C2: InstitutionType _RefID | D2: Full Name | E2: Commercial Name | F2: Old Code | G2: Jenis Supplier | H2: Sub Jenis Supplier | I2: Keterangan | J2: NPWP | K2: Nama PKP / NPWP | L2: Entity Type | N2: SYS_PID Prediction | O2: SQL Syntax
N3: 123000000000000
A4: =IF( COUNTIF( $D$4:$D$1000, $D4 ) = 1, "", "Duplicated") | B4: QDC Technologies | C4: 141000000000004 | D4: =IF(EXACT($C4, ""), B4, CONCATENATE(VLOOKUP($C4, 'REF - InstitutionType'!$B$4:$E$102, 3, FALSE), IF(EXACT(VLOOKUP($C4, 'REF - InstitutionType'!$B$4:$E$102, 3, FALSE), ""), "", " "), $B4, "", VLOOKUP($C4, 'REF - InstitutionType'!$B$4:$E$102, 4, FALSE), IF(EXACT($E4, ""), "", " [a.k.a : "&$E4&"]"))) -> PT. QDC Technologies | F4: QDC | L4: Corporate | N4: =N3 + IF(EXACT(O4, ""), 0, 1) -> 123000000000001 | O4: =CONCATENATE("PERFORM ""SchData-OLTP-Master"".""Func_TblInstitution_SET""(varSystemLoginSession::bigint, null::bigint, null::varchar, null::timestamptz, null::timestamptz, null::varchar, varInstitutionBranchID::bigint, varBaseCurrencyID::bigint, '", B4, "'::varchar, ", IF(EXACT(C4, ""), "null", C4), "::bigint); ") -> PERFORM "SchData-OLTP-Master"."Func_TblInstitution_SET"(varSystemLoginSession::bigint, null::bigint, null::varchar, null::timestamptz, null::timestamptz, null::varchar, varInstitutionBranchID::bigint, varBaseCurrencyID::bigint, 'QDC Technologies'::varchar, 141000000000004::bigint);
A5: =IF( COUNTIF( $D$4:$D$1000, $D5 ) = 1, "", "Duplicated") | B5: Infra Media Dinamika | C5: 141000000000004 | D5: =IF(EXACT($C5, ""), B5, CONCATENATE(VLOOKUP($C5, 'REF - InstitutionType'!$B$4:$E$102, 3, FALSE), IF(EXACT(VLOOKUP($C5, 'REF - InstitutionType'!$B$4:$E$102, 3, FALSE), ""), "", " "), $B5, "", VLOOKUP($C5, 'REF - InstitutionType'!$B$4:$E$102, 4, FALSE), IF(EXACT($E5, ""), "", " [a.k.a : "&$E5&"]"))) -> PT. Infra Media Dinamika | F5: IMD | L5: Corporate | N5: =N4 + IF(EXACT(O5, ""), 0, 1) -> 123000000000002 | O5: =CONCATENATE("PERFORM ""SchData-OLTP-Master"".""Func_TblInstitution_SET""(varSystemLoginSession::bigint, null::bigint, null::varchar, null::timestamptz, null::timestamptz, null::varchar, varInstitutionBranchID::bigint, varBaseCurrencyID::bigint, '", B5, "'::varchar, ", IF(EXACT(C5, ""), "null", C5), "::bigint); ") -> PERFORM "SchData-OLTP-Master"."Func_TblInstitution_SET"(varSystemLoginSession::bigint, null::bigint, null::varchar, null::timestamptz, null::timestamptz, null::varchar, varInstitutionBranchID::bigint, varBaseCurrencyID::bigint, 'Infra Media Dinamika'::varchar, 141000000000004::bigint);
A6: =IF( COUNTIF( $D$4:$D$1000, $D6 ) = 1, "", "Duplicated") | B6: Daya Hidro Dinamika | C6: 141000000000004 | D6: =IF(EXACT($C6, ""), B6, CONCATENATE(VLOOKUP($C6, 'REF - InstitutionType'!$B$4:$E$102, 3, FALSE), IF(EXACT(VLOOKUP($C6, 'REF - InstitutionType'!$B$4:$E$102, 3, FALSE), ""), "", " "), $B6, "", VLOOKUP($C6, 'REF - InstitutionType'!$B$4:$E$102, 4, FALSE), IF(EXACT($E6, ""), "", " [a.k.a : "&$E6&"]"))) -> PT. Daya Hidro Dinamika | F6: DHD | L6: Corporate | N6: =N5 + IF(EXACT(O6, ""), 0, 1) -> 123000000000003 | O6: =CONCATENATE("PERFORM ""SchData-OLTP-Master"".""Func_TblInstitution_SET""(varSystemLoginSession::bigint, null::bigint, null::varchar, null::timestamptz, null::timestamptz, null::varchar, varInstitutionBranchID::bigint, varBaseCurrencyID::bigint, '", B6, "'::varchar, ", IF(EXACT(C6, ""), "null", C6), "::bigint); ") -> PERFORM "SchData-OLTP-Master"."Func_TblInstitution_SET"(varSystemLoginSession::bigint, null::bigint, null::varchar, null::timestamptz, null::timestamptz, null::varchar, varInstitutionBranchID::bigint, varBaseCurrencyID::bigint, 'Daya Hidro Dinamika'::varchar, 141000000000004::bigint);
A7: =IF( COUNTIF( $D$4:$D$1000, $D7 ) = 1, "", "Duplicated") -> Duplicated | B7: Energi Mekar Lestari | C7: 141000000000004 | D7: =IF(EXACT($C7, ""), B7, CONCATENATE(VLOOKUP($C7, 'REF - InstitutionType'!$B$4:$E$102, 3, FALSE), IF(EXACT(VLOOKUP($C7, 'REF - InstitutionType'!$B$4:$E$102, 3, FALSE), ""), "", " "), $B7, "", VLOOKUP($C7, 'REF - InstitutionType'!$B$4:$E$102, 4, FALSE), IF(EXACT($E7, ""), "", " [a.k.a : "&$E7&"]"))) -> PT. Energi Mekar Lestari | F7: EML | L7: Corporate | N7: =N6 + IF(EXACT(O7, ""), 0, 1) -> 123000000000004 | O7: =CONCATENATE("PERFORM ""SchData-OLTP-Master"".""Func_TblInstitution_SET""(varSystemLoginSession::bigint, null::bigint, null::varchar, null::timestamptz, null::timestamptz, null::varchar, varInstitutionBranchID::bigint, varBaseCurrencyID::bigint, '", B7, "'::varchar, ", IF(EXACT(C7, ""), "null", C7), "::bigint); ") -> PERFORM "SchData-OLTP-Master"."Func_TblInstitution_SET"(varSystemLoginSession::bigint, null::bigint, null::varchar, null::timestamptz, null::timestamptz, null::varchar, varInstitutionBranchID::bigint, varBaseCurrencyID::bigint, 'Energi Mekar Lestari'::varchar, 141000000000004::bigint);
A8: =IF( COUNTIF( $D$4:$D$1000, $D8 ) = 1, "", "Duplicated") | B8: KHA | C8: 141000000000004 | D8: =IF(EXACT($C8, ""), B8, CONCATENATE(VLOOKUP($C8, 'REF - InstitutionType'!$B$4:$E$102, 3, FALSE), IF(EXACT(VLOOKUP($C8, 'REF - InstitutionType'!$B$4:$E$102, 3, FALSE), ""), "", " "), $B8, "", VLOOKUP($C8, 'REF - InstitutionType'!$B$4:$E$102, 4, FALSE), IF(EXACT($E8, ""), "", " [a.k.a : "&$E8&"]"))) -> PT. KHA | F8: KHA | L8: Corporate | N8: =N7 + IF(EXACT(O8, ""), 0, 1) -> 123000000000005 | O8: =CONCATENATE("PERFORM ""SchData-OLTP-Master"".""Func_TblInstitution_SET""(varSystemLoginSession::bigint, null::bigint, null::varchar, null::timestamptz, null::timestamptz, null::varchar, varInstitutionBranchID::bigint, varBaseCurrencyID::bigint, '", B8, "'::varchar, ", IF(EXACT(C8, ""), "null", C8), "::bigint); ") -> PERFORM "SchData-OLTP-Master"."Func_TblInstitution_SET"(varSystemLoginSession::bigint, null::bigint, null::varchar, null::timestamptz, null::timestamptz, null::varchar, varInstitutionBranchID::bigint, varBaseCurrencyID::bigint, 'KHA'::varchar, 141000000000004::bigint);
A9: =IF( COUNTIF( $D$4:$D$1000, $D9 ) = 1, "", "Duplicated") | B9: Abhitama Citra Abadi | C9: 141000000000004 | D9: =IF(EXACT($C9, ""), B9, CONCATENATE(VLOOKUP($C9, 'REF - InstitutionType'!$B$4:$E$102, 3, FALSE), IF(EXACT(VLOOKUP($C9, 'REF - InstitutionType'!$B$4:$E$102, 3, FALSE), ""), "", " "), $B9, "", VLOOKUP($C9, 'REF - InstitutionType'!$B$4:$E$102, 4, FALSE), IF(EXACT($E9, ""), "", " [a.k.a : "&$E9&"]"))) -> PT. Abhitama Citra Abadi | F9: ACA | L9: Customer | N9: =N8 + IF(EXACT(O9, ""), 0, 1) -> 123000000000006 | O9: =CONCATENATE("PERFORM ""SchData-OLTP-Master"".""Func_TblInstitution_SET""(varSystemLoginSession::bigint, null::bigint, null::varchar, null::timestamptz, null::timestamptz, null::varchar, varInstitutionBranchID::bigint, varBaseCurrencyID::bigint, '", B9, "'::varchar, ", IF(EXACT(C9, ""), "null", C9), "::bigint); ") -> PERFORM "SchData-OLTP-Master"."Func_TblInstitution_SET"(varSystemLoginSession::bigint, null::bigint, null::varchar, null::timestamptz, null::timestamptz, null::varchar, varInstitutionBranchID::bigint, varBaseCurrencyID::bigint, 'Abhitama Citra Abadi'::varchar, 141000000000004::bigint);
A10: =IF( COUNTIF( $D$4:$D$1000, $D10 ) = 1, "", "Duplicated") | B10: Abiyasa Tunggal | C10: 141000000000004 | D10: =IF(EXACT($C10, ""), B10, CONCATENATE(VLOOKUP($C10, 'REF - InstitutionType'!$B$4:$E$102, 3, FALSE), IF(EXACT(VLOOKUP($C10, 'REF - InstitutionType'!$B$4:$E$102, 3, FALSE), ""), "", " "), $B10, "", VLOOKUP($C10, 'REF - InstitutionType'!$B$4:$E$102, 4, FALSE), IF(EXACT($E10, ""), "", " [a.k.a : "&$E10&"]"))) -> PT. Abiyasa Tunggal | F10: ABI | L10: Customer | N10: =N9 + IF(EXACT(O10, ""), 0, 1) -> 123000000000007 | O10: =CONCATENATE("PERFORM ""SchData-OLTP-Master"".""Func_TblInstitution_SET""(varSystemLoginSession::bigint, null::bigint, null::varchar, null::timestamptz, null::timestamptz, null::varchar, varInstitutionBranchID::bigint, varBaseCurrencyID::bigint, '", B10, "'::varchar, ", IF(EXACT(C10, ""), "null", C10), "::bigint); ") -> PERFORM "SchData-OLTP-Master"."Func_TblInstitution_SET"(varSystemLoginSession::bigint, null::bigint, null::varchar, null::timestamptz, null::timestamptz, null::varchar, varInstitutionBranchID::bigint, varBaseCurrencyID::bigint, 'Abiyasa Tunggal'::varchar, 141000000000004::bigint);
A11: =IF( COUNTIF( $D$4:$D$1000, $D11 ) = 1, "", "Duplicated") | B11: Aplika Nusa Lintas Arta | C11: =141000000000004*1 -> 141000000000004 | D11: =IF(EXACT($C11, ""), B11, CONCATENATE(VLOOKUP($C11, 'REF - InstitutionType'!$B$4:$E$102, 3, FALSE), IF(EXACT(VLOOKUP($C11, 'REF - InstitutionType'!$B$4:$E$102, 3, FALSE), ""), "", " "), $B11, "", VLOOKUP($C11, 'REF - InstitutionType'!$B$4:$E$102, 4, FALSE), IF(EXACT($E11, ""), "", " [a.k.a : "&$E11&"]"))) -> PT. Aplika Nusa Lintas Arta | F11: LTA | L11: Customer | N11: =N10 + IF(EXACT(O11, ""), 0, 1) -> 123000000000008 | O11: =CONCATENATE("PERFORM ""SchData-OLTP-Master"".""Func_TblInstitution_SET""(varSystemLoginSession::bigint, null::bigint, null::varchar, null::timestamptz, null::timestamptz, null::varchar, varInstitutionBranchID::bigint, varBaseCurrencyID::bigint, '", B11, "'::varchar, ", IF(EXACT(C11, ""), "null", C11), "::bigint); ") -> PERFORM "SchData-OLTP-Master"."Func_TblInstitution_SET"(varSystemLoginSession::bigint, null::bigint, null::varchar, null::timestamptz, null::timestamptz, null::varchar, varInstitutionBranchID::bigint, varBaseCurrencyID::bigint, 'Aplika Nusa Lintas Arta'::varchar, 141000000000004::bigint);
A12: =IF( COUNTIF( $D$4:$D$1000, $D12 ) = 1, "", "Duplicated") | B12: Bakrie Telecom | C12: 141000000000005 | D12: =IF(EXACT($C12, ""), B12, CONCATENATE(VLOOKUP($C12, 'REF - InstitutionType'!$B$4:$E$102, 3, FALSE), IF(EXACT(VLOOKUP($C12, 'REF - InstitutionType'!$B$4:$E$102, 3, FALSE), ""), "", " "), $B12, "", VLOOKUP($C12, 'REF - InstitutionType'!$B$4:$E$102, 4, FALSE), IF(EXACT($E12, ""), "", " [a.k.a : "&$E12&"]"))) -> PT. Bakrie Telecom, Tbk | F12: ESI | L12: Customer | N12: =N11 + IF(EXACT(O12, ""), 0, 1) -> 123000000000009 | O12: =CONCATENATE("PERFORM ""SchData-OLTP-Master"".""Func_TblInstitution_SET""(varSystemLoginSession::bigint, null::bigint, null::varchar, null::timestamptz, null::timestamptz, null::varchar, varInstitutionBranchID::bigint, varBaseCurrencyID::bigint, '", B12, "'::varchar, ", IF(EXACT(C12, ""), "null", C12), "::bigint); ") -> PERFORM "SchData-OLTP-Master"."Func_TblInstitution_SET"(varSystemLoginSession::bigint, null::bigint, null::varchar, null::timestamptz, null::timestamptz, null::varchar, varInstitutionBranchID::bigint, varBaseCurrencyID::bigint, 'Bakrie Telecom'::varchar, 141000000000005::bigint);
A13: =IF( COUNTIF( $D$4:$D$1000, $D13 ) = 1, "", "Duplicated") | B13: Bukaka Teknik Utama | C13: 141000000000005 | D13: =IF(EXACT($C13, ""), B13, CONCATENATE(VLOOKUP($C13, 'REF - InstitutionType'!$B$4:$E$102, 3, FALSE), IF(EXACT(VLOOKUP($C13, 'REF - InstitutionType'!$B$4:$E$102, 3, FALSE), ""), "", " "), $B13, "", VLOOKUP($C13, 'REF - InstitutionType'!$B$4:$E$102, 4, FALSE), IF(EXACT($E13, ""), "", " [a.k.a : "&$E13&"]"))) -> PT. Bukaka Teknik Utama, Tbk | F13: BTU, VDR0015 | L13: Customer | N13: =N12 + IF(EXACT(O13, ""), 0, 1) -> 123000000000010 | O13: =CONCATENATE("PERFORM ""SchData-OLTP-Master"".""Func_TblInstitution_SET""(varSystemLoginSession::bigint, null::bigint, null::varchar, null::timestamptz, null::timestamptz, null::varchar, varInstitutionBranchID::bigint, varBaseCurrencyID::bigint, '", B13, "'::varchar, ", IF(EXACT(C13, ""), "null", C13), "::bigint); ") -> PERFORM "SchData-OLTP-Master"."Func_TblInstitution_SET"(varSystemLoginSession::bigint, null::bigint, null::varchar, null::timestamptz, null::timestamptz, null::varchar, varInstitutionBranchID::bigint, varBaseCurrencyID::bigint, 'Bukaka Teknik Utama'::varchar, 141000000000005::bigint);
A14: =IF( COUNTIF( $D$4:$D$1000, $D14 ) = 1, "", "Duplicated") | B14: Citra Panji Manunggal | C14: 141000000000004 | D14: =IF(EXACT($C14, ""), B14, CONCATENATE(VLOOKUP($C14, 'REF - InstitutionType'!$B$4:$E$102, 3, FALSE), IF(EXACT(VLOOKUP($C14, 'REF - InstitutionType'!$B$4:$E$102, 3, FALSE), ""), "", " "), $B14, "", VLOOKUP($C14, 'REF - InstitutionType'!$B$4:$E$102, 4, FALSE), IF(EXACT($E14, ""), "", " [a.k.a : "&$E14&"]"))) -> PT. Citra Panji Manunggal | F14: CPM | L14: Customer | N14: =N13 + IF(EXACT(O14, ""), 0, 1) -> 123000000000011 | O14: =CONCATENATE("PERFORM ""SchData-OLTP-Master"".""Func_TblInstitution_SET""(varSystemLoginSession::bigint, null::bigint, null::varchar, null::timestamptz, null::timestamptz, null::varchar, varInstitutionBranchID::bigint, varBaseCurrencyID::bigint, '", B14, "'::varchar, ", IF(EXACT(C14, ""), "null", C14), "::bigint); ") -> PERFORM "SchData-OLTP-Master"."Func_TblInstitution_SET"(varSystemLoginSession::bigint, null::bigint, null::varchar, null::timestamptz, null::timestamptz, null::varchar, varInstitutionBranchID::bigint, varBaseCurrencyID::bigint, 'Citra Panji Manunggal'::varchar, 141000000000004::bigint);
A15: =IF( COUNTIF( $D$4:$D$1000, $D15 ) = 1, "", "Duplicated") | B15: Dayamitra Telekomunikasi | C15: 141000000000004 | D15: =IF(EXACT($C15, ""), B15, CONCATENATE(VLOOKUP($C15, 'REF - InstitutionType'!$B$4:$E$102, 3, FALSE), IF(EXACT(VLOOKUP($C15, 'REF - InstitutionType'!$B$4:$E$102, 3, FALSE), ""), "", " "), $B15, "", VLOOKUP($C15, 'REF - InstitutionType'!$B$4:$E$102, 4, FALSE), IF(EXACT($E15, ""), "", " [a.k.a : "&$E15&"]"))) -> PT. Dayamitra Telekomunikasi | F15: DAYA | L15: Customer | N15: =N14 + IF(EXACT(O15, ""), 0, 1) -> 123000000000012 | O15: =CONCATENATE("PERFORM ""SchData-OLTP-Master"".""Func_TblInstitution_SET""(varSystemLoginSession::bigint, null::bigint, null::varchar, null::timestamptz, null::timestamptz, null::varchar, varInstitutionBranchID::bigint, varBaseCurrencyID::bigint, '", B15, "'::varchar, ", IF(EXACT(C15, ""), "null", C15), "::bigint); ") -> PERFORM "SchData-OLTP-Master"."Func_TblInstitution_SET"(varSystemLoginSession::bigint, null::bigint, null::varchar, null::timestamptz, null::timestamptz, null::varchar, varInstitutionBranchID::bigint, varBaseCurrencyID::bigint, 'Dayamitra Telekomunikasi'::varchar, 141000000000004::bigint);
A16: =IF( COUNTIF( $D$4:$D$1000, $D16 ) = 1, "", "Duplicated") | B16: Departemen Dalam Negeri | C16: 141000000000014 | D16: =IF(EXACT($C16, ""), B16, CONCATENATE(VLOOKUP($C16, 'REF - InstitutionType'!$B$4:$E$102, 3, FALSE), IF(EXACT(VLOOKUP($C16, 'REF - InstitutionType'!$B$4:$E$102, 3, FALSE), ""), "", " "), $B16, "", VLOOKUP($C16, 'REF - InstitutionType'!$B$4:$E$102, 4, FALSE), IF(EXACT($E16, ""), "", " [a.k.a : "&$E16&"]"))) -> Departemen Dalam Negeri | F16: DDN | L16: Customer | N16: =N15 + IF(EXACT(O16, ""), 0, 1) -> 123000000000013 | O16: =CONCATENATE("PERFORM ""SchData-OLTP-Master"".""Func_TblInstitution_SET""(varSystemLoginSession::bigint, null::bigint, null::varchar, null::timestamptz, null::timestamptz, null::varchar, varInstitutionBranchID::bigint, varBaseCurrencyID::bigint, '", B16, "'::varchar, ", IF(EXACT(C16, ""), "null", C16), "::bigint); ") -> PERFORM "SchData-OLTP-Master"."Func_TblInstitution_SET"(varSystemLoginSession::bigint, null::bigint, null::varchar, null::timestamptz, null::timestamptz, null::varchar, varInstitutionBranchID::bigint, varBaseCurrencyID::bigint, 'Departemen Dalam Negeri'::varchar, 141000000000014::bigint);
A17: =IF( COUNTIF( $D$4:$D$1000, $D17 ) = 1, "", "Duplicated") | B17: Duta Hita Jaya | C17: 141000000000004 | D17: =IF(EXACT($C17, ""), B17, CONCATENATE(VLOOKUP($C17, 'REF - InstitutionType'!$B$4:$E$102, 3, FALSE), IF(EXACT(VLOOKUP($C17, 'REF - InstitutionType'!$B$4:$E$102, 3, FALSE), ""), "", " "), $B17, "", VLOOKUP($C17, 'REF - InstitutionType'!$B$4:$E$102, 4, FALSE), IF(EXACT($E17, ""), "", " [a.k.a : "&$E17&"]"))) -> PT. Duta Hita Jaya | F17: DHJ | G17: Manufactur | H17: Fabrikator Tower | L17: Customer | N17: =N16 + IF(EXACT(O17, ""), 0, 1) -> 123000000000014 | O17: =CONCATENATE("PERFORM ""SchData-OLTP-Master"".""Func_TblInstitution_SET""(varSystemLoginSession::bigint, null::bigint, null::varchar, null::timestamptz, null::timestamptz, null::varchar, varInstitutionBranchID::bigint, varBaseCurrencyID::bigint, '", B17, "'::varchar, ", IF(EXACT(C17, ""), "null", C17), "::bigint); ") -> PERFORM "SchData-OLTP-Master"."Func_TblInstitution_SET"(varSystemLoginSession::bigint, null::bigint, null::varchar, null::timestamptz, null::timestamptz, null::varchar, varInstitutionBranchID::bigint, varBaseCurrencyID::bigint, 'Duta Hita Jaya'::varchar, 141000000000004::bigint);
A18: =IF( COUNTIF( $D$4:$D$1000, $D18 ) = 1, "", "Duplicated") | B18: Duta Pertiwi | C18: 141000000000005 | D18: =IF(EXACT($C18, ""), B18, CONCATENATE(VLOOKUP($C18, 'REF - InstitutionType'!$B$4:$E$102, 3, FALSE), IF(EXACT(VLOOKUP($C18, 'REF - InstitutionType'!$B$4:$E$102, 3, FALSE), ""), "", " "), $B18, "", VLOOKUP($C18, 'REF - InstitutionType'!$B$4:$E$102, 4, FALSE), IF(EXACT($E18, ""), "", " [a.k.a : "&$E18&"]"))) -> PT. Duta Pertiwi, Tbk | F18: DPS | L18: Customer | N18: =N17 + IF(EXACT(O18, ""), 0, 1) -> 123000000000015 | O18: =CONCATENATE("PERFORM ""SchData-OLTP-Master"".""Func_TblInstitution_SET""(varSystemLoginSession::bigint, null::bigint, null::varchar, null::timestamptz, null::timestamptz, null::varchar, varInstitutionBranchID::bigint, varBaseCurrencyID::bigint, '", B18, "'::varchar, ", IF(EXACT(C18, ""), "null", C18), "::bigint); ") -> PERFORM "SchData-OLTP-Master"."Func_TblInstitution_SET"(varSystemLoginSession::bigint, null::bigint, null::varchar, null::timestamptz, null::timestamptz, null::varchar, varInstitutionBranchID::bigint, varBaseCurrencyID::bigint, 'Duta Pertiwi'::varchar, 141000000000005::bigint);
A19: =IF( COUNTIF( $D$4:$D$1000, $D19 ) = 1, "", "Duplicated") -> Duplicated | B19: Duta Realtindo Perkasa | C19: 141000000000004 | D19: =IF(EXACT($C19, ""), B19, CONCATENATE(VLOOKUP($C19, 'REF - InstitutionType'!$B$4:$E$102, 3, FALSE), IF(EXACT(VLOOKUP($C19, 'REF - InstitutionType'!$B$4:$E$102, 3, FALSE), ""), "", " "), $B19, "", VLOOKUP($C19, 'REF - InstitutionType'!$B$4:$E$102, 4, FALSE), IF(EXACT($E19, ""), "", " [a.k.a : "&$E19&"]"))) -> PT. Duta Realtindo Perkasa | F19: DRP | L19: Customer | N19: =N18 + IF(EXACT(O19, ""), 0, 1) -> 123000000000016 | O19: =CONCATENATE("PERFORM ""SchData-OLTP-Master"".""Func_TblInstitution_SET""(varSystemLoginSession::bigint, null::bigint, null::varchar, null::timestamptz, null::timestamptz, null::varchar, varInstitutionBranchID::bigint, varBaseCurrencyID::bigint, '", B19, "'::varchar, ", IF(EXACT(C19, ""), "null", C19), "::bigint); ") -> PERFORM "SchData-OLTP-Master"."Func_TblInstitution_SET"(varSystemLoginSession::bigint, null::bigint, null::varchar, null::timestamptz, null::timestamptz, null::varchar, varInstitutionBranchID::bigint, varBaseCurrencyID::bigint, 'Duta Realtindo Perkasa'::varchar, 141000000000004::bigint);
A20: =IF( COUNTIF( $D$4:$D$1000, $D20 ) = 1, "", "Duplicated") -> Duplicated | B20: Energi Mekar Lestari | C20: 141000000000004 | D20: =IF(EXACT($C20, ""), B20, CONCATENATE(VLOOKUP($C20, 'REF - InstitutionType'!$B$4:$E$102, 3, FALSE), IF(EXACT(VLOOKUP($C20, 'REF - InstitutionType'!$B$4:$E$102, 3, FALSE), ""), "", " "), $B20, "", VLOOKUP($C20, 'REF - InstitutionType'!$B$4:$E$102, 4, FALSE), IF(EXACT($E20, ""), "", " [a.k.a : "&$E20&"]"))) -> PT. Energi Mekar Lestari | F20: EML | L20: Customer | N20: =N19 + IF(EXACT(O20, ""), 0, 1) -> 123000000000017 | O20: =CONCATENATE("PERFORM ""SchData-OLTP-Master"".""Func_TblInstitution_SET""(varSystemLoginSession::bigint, null::bigint, null::varchar, null::timestamptz, null::timestamptz, null::varchar, varInstitutionBranchID::bigint, varBaseCurrencyID::bigint, '", B20, "'::varchar, ", IF(EXACT(C20, ""), "null", C20), "::bigint); ") -> PERFORM "SchData-OLTP-Master"."Func_TblInstitution_SET"(varSystemLoginSession::bigint, null::bigint, null::varchar, null::timestamptz, null::timestamptz, null::varchar, varInstitutionBranchID::bigint, varBaseCurrencyID::bigint, 'Energi Mekar Lestari'::varchar, 141000000000004::bigint);
A21: =IF( COUNTIF( $D$4:$D$1000, $D21 ) = 1, "", "Duplicated") | B21: Ericsson Indonesia | C21: 141000000000004 | D21: =IF(EXACT($C21, ""), B21, CONCATENATE(VLOOKUP($C21, 'REF - InstitutionType'!$B$4:$E$102, 3, FALSE), IF(EXACT(VLOOKUP($C21, 'REF - InstitutionType'!$B$4:$E$102, 3, FALSE), ""), "", " "), $B21, "", VLOOKUP($C21, 'REF - InstitutionType'!$B$4:$E$102, 4, FALSE), IF(EXACT($E21, ""), "", " [a.k.a : "&$E21&"]"))) -> PT. Ericsson Indonesia | F21: ERI | L21: Customer | N21: =N20 + IF(EXACT(O21, ""), 0, 1) -> 123000000000018 | O21: =CONCATENATE("PERFORM ""SchData-OLTP-Master"".""Func_TblInstitution_SET""(varSystemLoginSession::bigint, null::bigint, null::varchar, null::timestamptz, null::timestamptz, null::varchar, varInstitutionBranchID::bigint, varBaseCurrencyID::bigint, '", B21, "'::varchar, ", IF(EXACT(C21, ""), "null", C21), "::bigint); ") -> PERFORM "SchData-OLTP-Master"."Func_TblInstitution_SET"(varSystemLoginSession::bigint, null::bigint, null::varchar, null::timestamptz, null::timestamptz, null::varchar, varInstitutionBranchID::bigint, varBaseCurrencyID::bigint, 'Ericsson Indonesia'::varchar, 141000000000004::bigint);
A22: =IF( COUNTIF( $D$4:$D$1000, $D22 ) = 1, "", "Duplicated") | B22: Esa Mitra Teknologi | C22: 141000000000004 | D22: =IF(EXACT($C22, ""), B22, CONCATENATE(VLOOKUP($C22, 'REF - InstitutionType'!$B$4:$E$102, 3, FALSE), IF(EXACT(VLOOKUP($C22, 'REF - InstitutionType'!$B$4:$E$102, 3, FALSE), ""), "", " "), $B22, "", VLOOKUP($C22, 'REF - InstitutionType'!$B$4:$E$102, 4, FALSE), IF(EXACT($E22, ""), "", " [a.k.a : "&$E22&"]"))) -> PT. Esa Mitra Teknologi | F22: ESA | L22: Customer | N22: =N21 + IF(EXACT(O22, ""), 0, 1) -> 123000000000019 | O22: =CONCATENATE("PERFORM ""SchData-OLTP-Master"".""Func_TblInstitution_SET""(varSystemLoginSession::bigint, null::bigint, null::varchar, null::timestamptz, null::timestamptz, null::varchar, varInstitutionBranchID::bigint, varBaseCurrencyID::bigint, '", B22, "'::varchar, ", IF(EXACT(C22, ""), "null", C22), "::bigint); ") -> PERFORM "SchData-OLTP-Master"."Func_TblInstitution_SET"(varSystemLoginSession::bigint, null::bigint, null::varchar, null::timestamptz, null::timestamptz, null::varchar, varInstitutionBranchID::bigint, varBaseCurrencyID::bigint, 'Esa Mitra Teknologi'::varchar, 141000000000004::bigint);
A23: =IF( COUNTIF( $D$4:$D$1000, $D23 ) = 1, "", "Duplicated") | B23: First Media | C23: 141000000000005 | D23: =IF(EXACT($C23, ""), B23, CONCATENATE(VLOOKUP($C23, 'REF - InstitutionType'!$B$4:$E$102, 3, FALSE), IF(EXACT(VLOOKUP($C23, 'REF - InstitutionType'!$B$4:$E$102, 3, FALSE), ""), "", " "), $B23, "", VLOOKUP($C23, 'REF - InstitutionType'!$B$4:$E$102, 4, FALSE), IF(EXACT($E23, ""), "", " [a.k.a : "&$E23&"]"))) -> PT. First Media, Tbk | F23: FIRST | L23: Customer | N23: =N22 + IF(EXACT(O23, ""), 0, 1) -> 123000000000020 | O23: =CONCATENATE("PERFORM ""SchData-OLTP-Master"".""Func_TblInstitution_SET""(varSystemLoginSession::bigint, null::bigint, null::varchar, null::timestamptz, null::timestamptz, null::varchar, varInstitutionBranchID::bigint, varBaseCurrencyID::bigint, '", B23, "'::varchar, ", IF(EXACT(C23, ""), "null", C23), "::bigint); ") -> PERFORM "SchData-OLTP-Master"."Func_TblInstitution_SET"(varSystemLoginSession::bigint, null::bigint, null::varchar, null::timestamptz, null::timestamptz, null::varchar, varInstitutionBranchID::bigint, varBaseCurrencyID::bigint, 'First Media'::varchar, 141000000000005::bigint);
A24: =IF( COUNTIF( $D$4:$D$1000, $D24 ) = 1, "", "Duplicated") | B24: Flexi | D24: =IF(EXACT($C24, ""), B24, CONCATENATE(VLOOKUP($C24, 'REF - InstitutionType'!$B$4:$E$102, 3, FALSE), IF(EXACT(VLOOKUP($C24, 'REF - InstitutionType'!$B$4:$E$102, 3, FALSE), ""), "", " "), $B24, "", VLOOKUP($C24, 'REF - InstitutionType'!$B$4:$E$102, 4, FALSE), IF(EXACT($E24, ""), "", " [a.k.a : "&$E24&"]"))) -> Flexi | F24: FLEX | L24: Customer | N24: =N23 + IF(EXACT(O24, ""), 0, 1) -> 123000000000021 | O24: =CONCATENATE("PERFORM ""SchData-OLTP-Master"".""Func_TblInstitution_SET""(varSystemLoginSession::bigint, null::bigint, null::varchar, null::timestamptz, null::timestamptz, null::varchar, varInstitutionBranchID::bigint, varBaseCurrencyID::bigint, '", B24, "'::varchar, ", IF(EXACT(C24, ""), "null", C24), "::bigint); ") -> PERFORM "SchData-OLTP-Master"."Func_TblInstitution_SET"(varSystemLoginSession::bigint, null::bigint, null::varchar, null::timestamptz, null::timestamptz, null::varchar, varInstitutionBranchID::bigint, varBaseCurrencyID::bigint, 'Flexi '::varchar, null::bigint);
A25: =IF( COUNTIF( $D$4:$D$1000, $D25 ) = 1, "", "Duplicated") | B25: Flexi Mitrayasa | D25: =IF(EXACT($C25, ""), B25, CONCATENATE(VLOOKUP($C25, 'REF - InstitutionType'!$B$4:$E$102, 3, FALSE), IF(EXACT(VLOOKUP($C25, 'REF - InstitutionType'!$B$4:$E$102, 3, FALSE), ""), "", " "), $B25, "", VLOOKUP($C25, 'REF - InstitutionType'!$B$4:$E$102, 4, FALSE), IF(EXACT($E25, ""), "", " [a.k.a : "&$E25&"]"))) -> Flexi Mitrayasa | F25: FLM | L25: Customer | N25: =N24 + IF(EXACT(O25, ""), 0, 1) -> 123000000000022 | O25: =CONCATENATE("PERFORM ""SchData-OLTP-Master"".""Func_TblInstitution_SET""(varSystemLoginSession::bigint, null::bigint, null::varchar, null::timestamptz, null::timestamptz, null::varchar, varInstitutionBranchID::bigint, varBaseCurrencyID::bigint, '", B25, "'::varchar, ", IF(EXACT(C25, ""), "null", C25), "::bigint); ") -> PERFORM "SchData-OLTP-Master"."Func_TblInstitution_SET"(varSystemLoginSession::bigint, null::bigint, null::varchar, null::timestamptz, null::timestamptz, null::varchar, varInstitutionBranchID::bigint, varBaseCurrencyID::bigint, 'Flexi Mitrayasa'::varchar, null::bigint);
A26: =IF( COUNTIF( $D$4:$D$1000, $D26 ) = 1, "", "Duplicated") | B26: Huawei Tech Investment | C26: 141000000000004 | D26: =IF(EXACT($C26, ""), B26, CONCATENATE(VLOOKUP($C26, 'REF - InstitutionType'!$B$4:$E$102, 3, FALSE), IF(EXACT(VLOOKUP($C26, 'REF - InstitutionType'!$B$4:$E$102, 3, FALSE), ""), "", " "), $B26, "", VLOOKUP($C26, 'REF - InstitutionType'!$B$4:$E$102, 4, FALSE), IF(EXACT($E26, ""), "", " [a.k.a : "&$E26&"]"))) -> PT. Huawei Tech Investment | F26: HWEI | L26: Customer | N26: =N25 + IF(EXACT(O26, ""), 0, 1) -> 123000000000023 | O26: =CONCATENATE("PERFORM ""SchData-OLTP-Master"".""Func_TblInstitution_SET""(varSystemLoginSession::bigint, null::bigint, null::varchar, null::timestamptz, null::timestamptz, null::varchar, varInstitutionBranchID::bigint, varBaseCurrencyID::bigint, '", B26, "'::varchar, ", IF(EXACT(C26, ""), "null", C26), "::bigint); ") -> PERFORM "SchData-OLTP-Master"."Func_TblInstitution_SET"(varSystemLoginSession::bigint, null::bigint, null::varchar, null::timestamptz, null::timestamptz, null::varchar, varInstitutionBranchID::bigint, varBaseCurrencyID::bigint, 'Huawei Tech Investment'::varchar, 141000000000004::bigint);
A27: =IF( COUNTIF( $D$4:$D$1000, $D27 ) = 1, "", "Duplicated") | B27: Hutchinson 3 Indonesia | C27: 141000000000004 | D27: =IF(EXACT($C27, ""), B27, CONCATENATE(VLOOKUP($C27, 'REF - InstitutionType'!$B$4:$E$102, 3, FALSE), IF(EXACT(VLOOKUP($C27, 'REF - InstitutionType'!$B$4:$E$102, 3, FALSE), ""), "", " "), $B27, "", VLOOKUP($C27, 'REF - InstitutionType'!$B$4:$E$102, 4, FALSE), IF(EXACT($E27, ""), "", " [a.k.a : "&$E27&"]"))) -> PT. Hutchinson 3 Indonesia | F27: HCPT | L27: Customer | N27: =N26 + IF(EXACT(O27, ""), 0, 1) -> 123000000000024 | O27: =CONCATENATE("PERFORM ""SchData-OLTP-Master"".""Func_TblInstitution_SET""(varSystemLoginSession::bigint, null::bigint, null::varchar, null::timestamptz, null::timestamptz, null::varchar, varInstitutionBranchID::bigint, varBaseCurrencyID::bigint, '", B27, "'::varchar, ", IF(EXACT(C27, ""), "null", C27), "::bigint); ") -> PERFORM "SchData-OLTP-Master"."Func_TblInstitution_SET"(varSystemLoginSession::bigint, null::bigint, null::varchar, null::timestamptz, null::timestamptz, null::varchar, varInstitutionBranchID::bigint, varBaseCurrencyID::bigint, 'Hutchinson 3 Indonesia'::varchar, 141000000000004::bigint);
A28: =IF( COUNTIF( $D$4:$D$1000, $D28 ) = 1, "", "Duplicated") | B28: Indoprima Seluler | C28: 141000000000004 | D28: =IF(EXACT($C28, ""), B28, CONCATENATE(VLOOKUP($C28, 'REF - InstitutionType'!$B$4:$E$102, 3, FALSE), IF(EXACT(VLOOKUP($C28, 'REF - InstitutionType'!$B$4:$E$102, 3, FALSE), ""), "", " "), $B28, "", VLOOKUP($C28, 'REF - InstitutionType'!$B$4:$E$102, 4, FALSE), IF(EXACT($E28, ""), "", " [a.k.a : "&$E28&"]"))) -> PT. Indoprima Seluler | F28: IDP | L28: Customer | N28: =N27 + IF(EXACT(O28, ""), 0, 1) -> 123000000000025 | O28: =CONCATENATE("PERFORM ""SchData-OLTP-Master"".""Func_TblInstitution_SET""(varSystemLoginSession::bigint, null::bigint, null::varchar, null::timestamptz, null::timestamptz, null::varchar, varInstitutionBranchID::bigint, varBaseCurrencyID::bigint, '", B28, "'::varchar, ", IF(EXACT(C28, ""), "null", C28), "::bigint); ") -> PERFORM "SchData-OLTP-Master"."Func_TblInstitution_SET"(varSystemLoginSession::bigint, null::bigint, null::varchar, null::timestamptz, null::timestamptz, null::varchar, varInstitutionBranchID::bigint, varBaseCurrencyID::bigint, 'Indoprima Seluler'::varchar, 141000000000004::bigint);
A29: =IF( COUNTIF( $D$4:$D$1000, $D29 ) = 1, "", "Duplicated") | B29: Indosat | C29: 141000000000005 | D29: =IF(EXACT($C29, ""), B29, CONCATENATE(VLOOKUP($C29, 'REF - InstitutionType'!$B$4:$E$102, 3, FALSE), IF(EXACT(VLOOKUP($C29, 'REF - InstitutionType'!$B$4:$E$102, 3, FALSE), ""), "", " "), $B29, "", VLOOKUP($C29, 'REF - InstitutionType'!$B$4:$E$102, 4, FALSE), IF(EXACT($E29, ""), "", " [a.k.a : "&$E29&"]"))) -> PT. Indosat, Tbk [a.k.a : Indosat] | E29: Indosat | F29: IND | L29: Customer | N29: =N28 + IF(EXACT(O29, ""), 0, 1) -> 123000000000026 | O29: =CONCATENATE("PERFORM ""SchData-OLTP-Master"".""Func_TblInstitution_SET""(varSystemLoginSession::bigint, null::bigint, null::varchar, null::timestamptz, null::timestamptz, null::varchar, varInstitutionBranchID::bigint, varBaseCurrencyID::bigint, '", B29, "'::varchar, ", IF(EXACT(C29, ""), "null", C29), "::bigint); ") -> PERFORM "SchData-OLTP-Master"."Func_TblInstitution_SET"(varSystemLoginSession::bigint, null::bigint, null::varchar, null::timestamptz, null::timestamptz, null::varchar, varInstitutionBranchID::bigint, varBaseCurrencyID::bigint, 'Indosat'::varchar, 141000000000005::bigint);
A30: =IF( COUNTIF( $D$4:$D$1000, $D30 ) = 1, "", "Duplicated") | B30: Industri Telekomunikasi Indonesia | C30: 141000000000006 | D30: =IF(EXACT($C30, ""), B30, CONCATENATE(VLOOKUP($C30, 'REF - InstitutionType'!$B$4:$E$102, 3, FALSE), IF(EXACT(VLOOKUP($C30, 'REF - InstitutionType'!$B$4:$E$102, 3, FALSE), ""), "", " "), $B30, "", VLOOKUP($C30, 'REF - InstitutionType'!$B$4:$E$102, 4, FALSE), IF(EXACT($E30, ""), "", " [a.k.a : "&$E30&"]"))) -> PT. Industri Telekomunikasi Indonesia (Persero) [a.k.a : INTI] | E30: INTI | F30: INTI | L30: Customer | N30: =N29 + IF(EXACT(O30, ""), 0, 1) -> 123000000000027 | O30: =CONCATENATE("PERFORM ""SchData-OLTP-Master"".""Func_TblInstitution_SET""(varSystemLoginSession::bigint, null::bigint, null::varchar, null::timestamptz, null::timestamptz, null::varchar, varInstitutionBranchID::bigint, varBaseCurrencyID::bigint, '", B30, "'::varchar, ", IF(EXACT(C30, ""), "null", C30), "::bigint); ") -> PERFORM "SchData-OLTP-Master"."Func_TblInstitution_SET"(varSystemLoginSession::bigint, null::bigint, null::varchar, null::timestamptz, null::timestamptz, null::varchar, varInstitutionBranchID::bigint, varBaseCurrencyID::bigint, 'Industri Telekomunikasi Indonesia'::varchar, 141000000000006::bigint);
A31: =IF( COUNTIF( $D$4:$D$1000, $D31 ) = 1, "", "Duplicated") | B31: Infrastruktur Bisnis Sejahtera | C31: 141000000000004 | D31: =IF(EXACT($C31, ""), B31, CONCATENATE(VLOOKUP($C31, 'REF - InstitutionType'!$B$4:$E$102, 3, FALSE), IF(EXACT(VLOOKUP($C31, 'REF - InstitutionType'!$B$4:$E$102, 3, FALSE), ""), "", " "), $B31, "", VLOOKUP($C31, 'REF - InstitutionType'!$B$4:$E$102, 4, FALSE), IF(EXACT($E31, ""), "", " [a.k.a : "&$E31&"]"))) -> PT. Infrastruktur Bisnis Sejahtera | F31: MIT | L31: Customer | N31: =N30 + IF(EXACT(O31, ""), 0, 1) -> 123000000000028 | O31: =CONCATENATE("PERFORM ""SchData-OLTP-Master"".""Func_TblInstitution_SET""(varSystemLoginSession::bigint, null::bigint, null::varchar, null::timestamptz, null::timestamptz, null::varchar, varInstitutionBranchID::bigint, varBaseCurrencyID::bigint, '", B31, "'::varchar, ", IF(EXACT(C31, ""), "null", C31), "::bigint); ") -> PERFORM "SchData-OLTP-Master"."Func_TblInstitution_SET"(varSystemLoginSession::bigint, null::bigint, null::varchar, null::timestamptz, null::timestamptz, null::varchar, varInstitutionBranchID::bigint, varBaseCurrencyID::bigint, 'Infrastruktur Bisnis Sejahtera'::varchar, 141000000000004::bigint);
A32: =IF( COUNTIF( $D$4:$D$1000, $D32 ) = 1, "", "Duplicated") | B32: Intershop Prima Center | C32: 141000000000004 | D32: =IF(EXACT($C32, ""), B32, CONCATENATE(VLOOKUP($C32, 'REF - InstitutionType'!$B$4:$E$102, 3, FALSE), IF(EXACT(VLOOKUP($C32, 'REF - InstitutionType'!$B$4:$E$102, 3, FALSE), ""), "", " "), $B32, "", VLOOKUP($C32, 'REF - InstitutionType'!$B$4:$E$102, 4, FALSE), IF(EXACT($E32, ""), "", " [a.k.a : "&$E32&"]"))) -> PT. Intershop Prima Center | F32: IPC | L32: Customer | N32: =N31 + IF(EXACT(O32, ""), 0, 1) -> 123000000000029 | O32: =CONCATENATE("PERFORM ""SchData-OLTP-Master"".""Func_TblInstitution_SET""(varSystemLoginSession::bigint, null::bigint, null::varchar, null::timestamptz, null::timestamptz, null::varchar, varInstitutionBranchID::bigint, varBaseCurrencyID::bigint, '", B32, "'::varchar, ", IF(EXACT(C32, ""), "null", C32), "::bigint); ") -> PERFORM "SchData-OLTP-Master"."Func_TblInstitution_SET"(varSystemLoginSession::bigint, null::bigint, null::varchar, null::timestamptz, null::timestamptz, null::varchar, varInstitutionBranchID::bigint, varBaseCurrencyID::bigint, 'Intershop Prima Center'::varchar, 141000000000004::bigint);
A33: =IF( COUNTIF( $D$4:$D$1000, $D33 ) = 1, "", "Duplicated") | B33: Inti Bangun Sejahtera | C33: 141000000000005 | D33: =IF(EXACT($C33, ""), B33, CONCATENATE(VLOOKUP($C33, 'REF - InstitutionType'!$B$4:$E$102, 3, FALSE), IF(EXACT(VLOOKUP($C33, 'REF - InstitutionType'!$B$4:$E$102, 3, FALSE), ""), "", " "), $B33, "", VLOOKUP($C33, 'REF - InstitutionType'!$B$4:$E$102, 4, FALSE), IF(EXACT($E33, ""), "", " [a.k.a : "&$E33&"]"))) -> PT. Inti Bangun Sejahtera, Tbk | F33: IBS | L33: Customer | N33: =N32 + IF(EXACT(O33, ""), 0, 1) -> 123000000000030 | O33: =CONCATENATE("PERFORM ""SchData-OLTP-Master"".""Func_TblInstitution_SET""(varSystemLoginSession::bigint, null::bigint, null::varchar, null::timestamptz, null::timestamptz, null::varchar, varInstitutionBranchID::bigint, varBaseCurrencyID::bigint, '", B33, "'::varchar, ", IF(EXACT(C33, ""), "null", C33), "::bigint); ") -> PERFORM "SchData-OLTP-Master"."Func_TblInstitution_SET"(varSystemLoginSession::bigint, null::bigint, null::varchar, null::timestamptz, null::timestamptz, null::varchar, varInstitutionBranchID::bigint, varBaseCurrencyID::bigint, 'Inti Bangun Sejahtera'::varchar, 141000000000005::bigint);
A34: =IF( COUNTIF( $D$4:$D$1000, $D34 ) = 1, "", "Duplicated") | B34: Karya Mitra Nugraha | C34: 141000000000004 | D34: =IF(EXACT($C34, ""), B34, CONCATENATE(VLOOKUP($C34, 'REF - InstitutionType'!$B$4:$E$102, 3, FALSE), IF(EXACT(VLOOKUP($C34, 'REF - InstitutionType'!$B$4:$E$102, 3, FALSE), ""), "", " "), $B34, "", VLOOKUP($C34, 'REF - InstitutionType'!$B$4:$E$102, 4, FALSE), IF(EXACT($E34, ""), "", " [a.k.a : "&$E34&"]"))) -> PT. Karya Mitra Nugraha | F34: KMN | L34: Customer | N34: =N33 + IF(EXACT(O34, ""), 0, 1) -> 123000000000031 | O34: =CONCATENATE("PERFORM ""SchData-OLTP-Master"".""Func_TblInstitution_SET""(varSystemLoginSession::bigint, null::bigint, null::varchar, null::timestamptz, null::timestamptz, null::varchar, varInstitutionBranchID::bigint, varBaseCurrencyID::bigint, '", B34, "'::varchar, ", IF(EXACT(C34, ""), "null", C34), "::bigint); ") -> PERFORM "SchData-OLTP-Master"."Func_TblInstitution_SET"(varSystemLoginSession::bigint, null::bigint, null::varchar, null::timestamptz, null::timestamptz, null::varchar, varInstitutionBranchID::bigint, varBaseCurrencyID::bigint, 'Karya Mitra Nugraha'::varchar, 141000000000004::bigint);
A35: =IF( COUNTIF( $D$4:$D$1000, $D35 ) = 1, "", "Duplicated") | B35: Lektrika Karyatama | C35: 141000000000004 | D35: =IF(EXACT($C35, ""), B35, CONCATENATE(VLOOKUP($C35, 'REF - InstitutionType'!$B$4:$E$102, 3, FALSE), IF(EXACT(VLOOKUP($C35, 'REF - InstitutionType'!$B$4:$E$102, 3, FALSE), ""), "", " "), $B35, "", VLOOKUP($C35, 'REF - InstitutionType'!$B$4:$E$102, 4, FALSE), IF(EXACT($E35, ""), "", " [a.k.a : "&$E35&"]"))) -> PT. Lektrika Karyatama | F35: LRK | L35: Customer | N35: =N34 + IF(EXACT(O35, ""), 0, 1) -> 123000000000032 | O35: =CONCATENATE("PERFORM ""SchData-OLTP-Master"".""Func_TblInstitution_SET""(varSystemLoginSession::bigint, null::bigint, null::varchar, null::timestamptz, null::timestamptz, null::varchar, varInstitutionBranchID::bigint, varBaseCurrencyID::bigint, '", B35, "'::varchar, ", IF(EXACT(C35, ""), "null", C35), "::bigint); ") -> PERFORM "SchData-OLTP-Master"."Func_TblInstitution_SET"(varSystemLoginSession::bigint, null::bigint, null::varchar, null::timestamptz, null::timestamptz, null::varchar, varInstitutionBranchID::bigint, varBaseCurrencyID::bigint, 'Lektrika Karyatama'::varchar, 141000000000004::bigint);
A36: =IF( COUNTIF( $D$4:$D$1000, $D36 ) = 1, "", "Duplicated") | B36: Link Net | C36: 141000000000004 | D36: =IF(EXACT($C36, ""), B36, CONCATENATE(VLOOKUP($C36, 'REF - InstitutionType'!$B$4:$E$102, 3, FALSE), IF(EXACT(VLOOKUP($C36, 'REF - InstitutionType'!$B$4:$E$102, 3, FALSE), ""), "", " "), $B36, "", VLOOKUP($C36, 'REF - InstitutionType'!$B$4:$E$102, 4, FALSE), IF(EXACT($E36, ""), "", " [a.k.a : "&$E36&"]"))) -> PT. Link Net | F36: LINK | L36: Customer | N36: =N35 + IF(EXACT(O36, ""), 0, 1) -> 123000000000033 | O36: =CONCATENATE("PERFORM ""SchData-OLTP-Master"".""Func_TblInstitution_SET""(varSystemLoginSession::bigint, null::bigint, null::varchar, null::timestamptz, null::timestamptz, null::varchar, varInstitutionBranchID::bigint, varBaseCurrencyID::bigint, '", B36, "'::varchar, ", IF(EXACT(C36, ""), "null", C36), "::bigint); ") -> PERFORM "SchData-OLTP-Master"."Func_TblInstitution_SET"(varSystemLoginSession::bigint, null::bigint, null::varchar, null::timestamptz, null::timestamptz, null::varchar, varInstitutionBranchID::bigint, varBaseCurrencyID::bigint, 'Link Net'::varchar, 141000000000004::bigint);
A37: =IF( COUNTIF( $D$4:$D$1000, $D37 ) = 1, "", "Duplicated") | B37: Lintas Teknologi Indonesia | C37: 141000000000004 | D37: =IF(EXACT($C37, ""), B37, CONCATENATE(VLOOKUP($C37, 'REF - InstitutionType'!$B$4:$E$102, 3, FALSE), IF(EXACT(VLOOKUP($C37, 'REF - InstitutionType'!$B$4:$E$102, 3, FALSE), ""), "", " "), $B37, "", VLOOKUP($C37, 'REF - InstitutionType'!$B$4:$E$102, 4, FALSE), IF(EXACT($E37, ""), "", " [a.k.a : "&$E37&"]"))) -> PT. Lintas Teknologi Indonesia | F37: Lts | L37: Customer | N37: =N36 + IF(EXACT(O37, ""), 0, 1) -> 123000000000034 | O37: =CONCATENATE("PERFORM ""SchData-OLTP-Master"".""Func_TblInstitution_SET""(varSystemLoginSession::bigint, null::bigint, null::varchar, null::timestamptz, null::timestamptz, null::varchar, varInstitutionBranchID::bigint, varBaseCurrencyID::bigint, '", B37, "'::varchar, ", IF(EXACT(C37, ""), "null", C37), "::bigint); ") -> PERFORM "SchData-OLTP-Master"."Func_TblInstitution_SET"(varSystemLoginSession::bigint, null::bigint, null::varchar, null::timestamptz, null::timestamptz, null::varchar, varInstitutionBranchID::bigint, varBaseCurrencyID::bigint, 'Lintas Teknologi Indonesia'::varchar, 141000000000004::bigint);
A38: =IF( COUNTIF( $D$4:$D$1000, $D38 ) = 1, "", "Duplicated") | B38: Mega Eltra | C38: 141000000000004 | D38: =IF(EXACT($C38, ""), B38, CONCATENATE(VLOOKUP($C38, 'REF - InstitutionType'!$B$4:$E$102, 3, FALSE), IF(EXACT(VLOOKUP($C38, 'REF - InstitutionType'!$B$4:$E$102, 3, FALSE), ""), "", " "), $B38, "", VLOOKUP($C38, 'REF - InstitutionType'!$B$4:$E$102, 4, FALSE), IF(EXACT($E38, ""), "", " [a.k.a : "&$E38&"]"))) -> PT. Mega Eltra | F38: MEL | L38: Customer | N38: =N37 + IF(EXACT(O38, ""), 0, 1) -> 123000000000035 | O38: =CONCATENATE("PERFORM ""SchData-OLTP-Master"".""Func_TblInstitution_SET""(varSystemLoginSession::bigint, null::bigint, null::varchar, null::timestamptz, null::timestamptz, null::varchar, varInstitutionBranchID::bigint, varBaseCurrencyID::bigint, '", B38, "'::varchar, ", IF(EXACT(C38, ""), "null", C38), "::bigint); ") -> PERFORM "SchData-OLTP-Master"."Func_TblInstitution_SET"(varSystemLoginSession::bigint, null::bigint, null::varchar, null::timestamptz, null::timestamptz, null::varchar, varInstitutionBranchID::bigint, varBaseCurrencyID::bigint, 'Mega Eltra'::varchar, 141000000000004::bigint);
A39: =IF( COUNTIF( $D$4:$D$1000, $D39 ) = 1, "", "Duplicated") | B39: Megatel Jaya Swastikarya | C39: 141000000000004 | D39: =IF(EXACT($C39, ""), B39, CONCATENATE(VLOOKUP($C39, 'REF - InstitutionType'!$B$4:$E$102, 3, FALSE), IF(EXACT(VLOOKUP($C39, 'REF - InstitutionType'!$B$4:$E$102, 3, FALSE), ""), "", " "), $B39, "", VLOOKUP($C39, 'REF - InstitutionType'!$B$4:$E$102, 4, FALSE), IF(EXACT($E39, ""), "", " [a.k.a : "&$E39&"]"))) -> PT. Megatel Jaya Swastikarya | F39: MGT | L39: Customer | N39: =N38 + IF(EXACT(O39, ""), 0, 1) -> 123000000000036 | O39: =CONCATENATE("PERFORM ""SchData-OLTP-Master"".""Func_TblInstitution_SET""(varSystemLoginSession::bigint, null::bigint, null::varchar, null::timestamptz, null::timestamptz, null::varchar, varInstitutionBranchID::bigint, varBaseCurrencyID::bigint, '", B39, "'::varchar, ", IF(EXACT(C39, ""), "null", C39), "::bigint); ") -> PERFORM "SchData-OLTP-Master"."Func_TblInstitution_SET"(varSystemLoginSession::bigint, null::bigint, null::varchar, null::timestamptz, null::timestamptz, null::varchar, varInstitutionBranchID::bigint, varBaseCurrencyID::bigint, 'Megatel Jaya Swastikarya'::varchar, 141000000000004::bigint);
A40: =IF( COUNTIF( $D$4:$D$1000, $D40 ) = 1, "", "Duplicated") | B40: Nokia Indonesia | C40: 141000000000004 | D40: =IF(EXACT($C40, ""), B40, CONCATENATE(VLOOKUP($C40, 'REF - InstitutionType'!$B$4:$E$102, 3, FALSE), IF(EXACT(VLOOKUP($C40, 'REF - InstitutionType'!$B$4:$E$102, 3, FALSE), ""), "", " "), $B40, "", VLOOKUP($C40, 'REF - InstitutionType'!$B$4:$E$102, 4, FALSE), IF(EXACT($E40, ""), "", " [a.k.a : "&$E40&"]"))) -> PT. Nokia Indonesia | F40: NOK | L40: Customer | N40: =N39 + IF(EXACT(O40, ""), 0, 1) -> 123000000000037 | O40: =CONCATENATE("PERFORM ""SchData-OLTP-Master"".""Func_TblInstitution_SET""(varSystemLoginSession::bigint, null::bigint, null::varchar, null::timestamptz, null::timestamptz, null::varchar, varInstitutionBranchID::bigint, varBaseCurrencyID::bigint, '", B40, "'::varchar, ", IF(EXACT(C40, ""), "null", C40), "::bigint); ") -> PERFORM "SchData-OLTP-Master"."Func_TblInstitution_SET"(varSystemLoginSession::bigint, null::bigint, null::varchar, null::timestamptz, null::timestamptz, null::varchar, varInstitutionBranchID::bigint, varBaseCurrencyID::bigint, 'Nokia Indonesia'::varchar, 141000000000004::bigint);
A41: =IF( COUNTIF( $D$4:$D$1000, $D41 ) = 1, "", "Duplicated") | B41: Nokia Siemens Network Indonesia | C41: 141000000000004 | D41: =IF(EXACT($C41, ""), B41, CONCATENATE(VLOOKUP($C41, 'REF - InstitutionType'!$B$4:$E$102, 3, FALSE), IF(EXACT(VLOOKUP($C41, 'REF - InstitutionType'!$B$4:$E$102, 3, FALSE), ""), "", " "), $B41, "", VLOOKUP($C41, 'REF - InstitutionType'!$B$4:$E$102, 4, FALSE), IF(EXACT($E41, ""), "", " [a.k.a : "&$E41&"]"))) -> PT. Nokia Siemens Network Indonesia | F41: NSN | L41: Customer | N41: =N40 + IF(EXACT(O41, ""), 0, 1) -> 123000000000038 | O41: =CONCATENATE("PERFORM ""SchData-OLTP-Master"".""Func_TblInstitution_SET""(varSystemLoginSession::bigint, null::bigint, null::varchar, null::timestamptz, null::timestamptz, null::varchar, varInstitutionBranchID::bigint, varBaseCurrencyID::bigint, '", B41, "'::varchar, ", IF(EXACT(C41, ""), "null", C41), "::bigint); ") -> PERFORM "SchData-OLTP-Master"."Func_TblInstitution_SET"(varSystemLoginSession::bigint, null::bigint, null::varchar, null::timestamptz, null::timestamptz, null::varchar, varInstitutionBranchID::bigint, varBaseCurrencyID::bigint, 'Nokia Siemens Network Indonesia'::varchar, 141000000000004::bigint);
A42: =IF( COUNTIF( $D$4:$D$1000, $D42 ) = 1, "", "Duplicated") | B42: Pertamina Geothermal Energy | C42: 141000000000004 | D42: =IF(EXACT($C42, ""), B42, CONCATENATE(VLOOKUP($C42, 'REF - InstitutionType'!$B$4:$E$102, 3, FALSE), IF(EXACT(VLOOKUP($C42, 'REF - InstitutionType'!$B$4:$E$102, 3, FALSE), ""), "", " "), $B42, "", VLOOKUP($C42, 'REF - InstitutionType'!$B$4:$E$102, 4, FALSE), IF(EXACT($E42, ""), "", " [a.k.a : "&$E42&"]"))) -> PT. Pertamina Geothermal Energy | F42: PGE | L42: Customer | N42: =N41 + IF(EXACT(O42, ""), 0, 1) -> 123000000000039 | O42: =CONCATENATE("PERFORM ""SchData-OLTP-Master"".""Func_TblInstitution_SET""(varSystemLoginSession::bigint, null::bigint, null::varchar, null::timestamptz, null::timestamptz, null::varchar, varInstitutionBranchID::bigint, varBaseCurrencyID::bigint, '", B42, "'::varchar, ", IF(EXACT(C42, ""), "null", C42), "::bigint); ") -> PERFORM "SchData-OLTP-Master"."Func_TblInstitution_SET"(varSystemLoginSession::bigint, null::bigint, null::varchar, null::timestamptz, null::timestamptz, null::varchar, varInstitutionBranchID::bigint, varBaseCurrencyID::bigint, 'Pertamina Geothermal Energy'::varchar, 141000000000004::bigint);
A43: =IF( COUNTIF( $D$4:$D$1000, $D43 ) = 1, "", "Duplicated") | B43: Pelayanan Listrik Nasional | C43: 141000000000006 | D43: =IF(EXACT($C43, ""), B43, CONCATENATE(VLOOKUP($C43, 'REF - InstitutionType'!$B$4:$E$102, 3, FALSE), IF(EXACT(VLOOKUP($C43, 'REF - InstitutionType'!$B$4:$E$102, 3, FALSE), ""), "", " "), $B43, "", VLOOKUP($C43, 'REF - InstitutionType'!$B$4:$E$102, 4, FALSE), IF(EXACT($E43, ""), "", " [a.k.a : "&$E43&"]"))) -> PT. Pelayanan Listrik Nasional (Persero) [a.k.a : PLN] | E43: PLN | F43: PLN | L43: Customer | N43: =N42 + IF(EXACT(O43, ""), 0, 1) -> 123000000000040 | O43: =CONCATENATE("PERFORM ""SchData-OLTP-Master"".""Func_TblInstitution_SET""(varSystemLoginSession::bigint, null::bigint, null::varchar, null::timestamptz, null::timestamptz, null::varchar, varInstitutionBranchID::bigint, varBaseCurrencyID::bigint, '", B43, "'::varchar, ", IF(EXACT(C43, ""), "null", C43), "::bigint); ") -> PERFORM "SchData-OLTP-Master"."Func_TblInstitution_SET"(varSystemLoginSession::bigint, null::bigint, null::varchar, null::timestamptz, null::timestamptz, null::varchar, varInstitutionBranchID::bigint, varBaseCurrencyID::bigint, 'Pelayanan Listrik Nasional'::varchar, 141000000000006::bigint);
A44: =IF( COUNTIF( $D$4:$D$1000, $D44 ) = 1, "", "Duplicated") | B44: Protelindo | C44: 141000000000004 | D44: =IF(EXACT($C44, ""), B44, CONCATENATE(VLOOKUP($C44, 'REF - InstitutionType'!$B$4:$E$102, 3, FALSE), IF(EXACT(VLOOKUP($C44, 'REF - InstitutionType'!$B$4:$E$102, 3, FALSE), ""), "", " "), $B44, "", VLOOKUP($C44, 'REF - InstitutionType'!$B$4:$E$102, 4, FALSE), IF(EXACT($E44, ""), "", " [a.k.a : "&$E44&"]"))) -> PT. Protelindo | F44: PROTEL | L44: Customer | N44: =N43 + IF(EXACT(O44, ""), 0, 1) -> 123000000000041 | O44: =CONCATENATE("PERFORM ""SchData-OLTP-Master"".""Func_TblInstitution_SET""(varSystemLoginSession::bigint, null::bigint, null::varchar, null::timestamptz, null::timestamptz, null::varchar, varInstitutionBranchID::bigint, varBaseCurrencyID::bigint, '", B44, "'::varchar, ", IF(EXACT(C44, ""), "null", C44), "::bigint); ") -> PERFORM "SchData-OLTP-Master"."Func_TblInstitution_SET"(varSystemLoginSession::bigint, null::bigint, null::varchar, null::timestamptz, null::timestamptz, null::varchar, varInstitutionBranchID::bigint, varBaseCurrencyID::bigint, 'Protelindo'::varchar, 141000000000004::bigint);
A45: =IF( COUNTIF( $D$4:$D$1000, $D45 ) = 1, "", "Duplicated") | B45: Ramayana Lestari Sentosa | C45: 141000000000005 | D45: =IF(EXACT($C45, ""), B45, CONCATENATE(VLOOKUP($C45, 'REF - InstitutionType'!$B$4:$E$102, 3, FALSE), IF(EXACT(VLOOKUP($C45, 'REF - InstitutionType'!$B$4:$E$102, 3, FALSE), ""), "", " "), $B45, "", VLOOKUP($C45, 'REF - InstitutionType'!$B$4:$E$102, 4, FALSE), IF(EXACT($E45, ""), "", " [a.k.a : "&$E45&"]"))) -> PT. Ramayana Lestari Sentosa, Tbk [a.k.a : Ramayana Departement Store] | E45: Ramayana Departement Store | F45: RAM | L45: Customer | N45: =N44 + IF(EXACT(O45, ""), 0, 1) -> 123000000000042 | O45: =CONCATENATE("PERFORM ""SchData-OLTP-Master"".""Func_TblInstitution_SET""(varSystemLoginSession::bigint, null::bigint, null::varchar, null::timestamptz, null::timestamptz, null::varchar, varInstitutionBranchID::bigint, varBaseCurrencyID::bigint, '", B45, "'::varchar, ", IF(EXACT(C45, ""), "null", C45), "::bigint); ") -> PERFORM "SchData-OLTP-Master"."Func_TblInstitution_SET"(varSystemLoginSession::bigint, null::bigint, null::varchar, null::timestamptz, null::timestamptz, null::varchar, varInstitutionBranchID::bigint, varBaseCurrencyID::bigint, 'Ramayana Lestari Sentosa'::varchar, 141000000000005::bigint);
A46: =IF( COUNTIF( $D$4:$D$1000, $D46 ) = 1, "", "Duplicated") | B46: Rekadaya Elektrika | C46: 141000000000004 | D46: =IF(EXACT($C46, ""), B46, CONCATENATE(VLOOKUP($C46, 'REF - InstitutionType'!$B$4:$E$102, 3, FALSE), IF(EXACT(VLOOKUP($C46, 'REF - InstitutionType'!$B$4:$E$102, 3, FALSE), ""), "", " "), $B46, "", VLOOKUP($C46, 'REF - InstitutionType'!$B$4:$E$102, 4, FALSE), IF(EXACT($E46, ""), "", " [a.k.a : "&$E46&"]"))) -> PT. Rekadaya Elektrika | F46: RDEL | L46: Customer | N46: =N45 + IF(EXACT(O46, ""), 0, 1) -> 123000000000043 | O46: =CONCATENATE("PERFORM ""SchData-OLTP-Master"".""Func_TblInstitution_SET""(varSystemLoginSession::bigint, null::bigint, null::varchar, null::timestamptz, null::timestamptz, null::varchar, varInstitutionBranchID::bigint, varBaseCurrencyID::bigint, '", B46, "'::varchar, ", IF(EXACT(C46, ""), "null", C46), "::bigint); ") -> PERFORM "SchData-OLTP-Master"."Func_TblInstitution_SET"(varSystemLoginSession::bigint, null::bigint, null::varchar, null::timestamptz, null::timestamptz, null::varchar, varInstitutionBranchID::bigint, varBaseCurrencyID::bigint, 'Rekadaya Elektrika'::varchar, 141000000000004::bigint);
A47: =IF( COUNTIF( $D$4:$D$1000, $D47 ) = 1, "", "Duplicated") | B47: Sejahtera Mandiri | C47: 141000000000002 | D47: =IF(EXACT($C47, ""), B47, CONCATENATE(VLOOKUP($C47, 'REF - InstitutionType'!$B$4:$E$102, 3, FALSE), IF(EXACT(VLOOKUP($C47, 'REF - InstitutionType'!$B$4:$E$102, 3, FALSE), ""), "", " "), $B47, "", VLOOKUP($C47, 'REF - InstitutionType'!$B$4:$E$102, 4, FALSE), IF(EXACT($E47, ""), "", " [a.k.a : "&$E47&"]"))) -> CV. Sejahtera Mandiri | F47: CVSM | L47: Customer | N47: =N46 + IF(EXACT(O47, ""), 0, 1) -> 123000000000044 | O47: =CONCATENATE("PERFORM ""SchData-OLTP-Master"".""Func_TblInstitution_SET""(varSystemLoginSession::bigint, null::bigint, null::varchar, null::timestamptz, null::timestamptz, null::varchar, varInstitutionBranchID::bigint, varBaseCurrencyID::bigint, '", B47, "'::varchar, ", IF(EXACT(C47, ""), "null", C47), "::bigint); ") -> PERFORM "SchData-OLTP-Master"."Func_TblInstitution_SET"(varSystemLoginSession::bigint, null::bigint, null::varchar, null::timestamptz, null::timestamptz, null::varchar, varInstitutionBranchID::bigint, varBaseCurrencyID::bigint, 'Sejahtera Mandiri'::varchar, 141000000000002::bigint);
A48: =IF( COUNTIF( $D$4:$D$1000, $D48 ) = 1, "", "Duplicated") | B48: Sigindo Kemas | C48: 141000000000004 | D48: =IF(EXACT($C48, ""), B48, CONCATENATE(VLOOKUP($C48, 'REF - InstitutionType'!$B$4:$E$102, 3, FALSE), IF(EXACT(VLOOKUP($C48, 'REF - InstitutionType'!$B$4:$E$102, 3, FALSE), ""), "", " "), $B48, "", VLOOKUP($C48, 'REF - InstitutionType'!$B$4:$E$102, 4, FALSE), IF(EXACT($E48, ""), "", " [a.k.a : "&$E48&"]"))) -> PT. Sigindo Kemas | F48: SGK | L48: Customer | N48: =N47 + IF(EXACT(O48, ""), 0, 1) -> 123000000000045 | O48: =CONCATENATE("PERFORM ""SchData-OLTP-Master"".""Func_TblInstitution_SET""(varSystemLoginSession::bigint, null::bigint, null::varchar, null::timestamptz, null::timestamptz, null::varchar, varInstitutionBranchID::bigint, varBaseCurrencyID::bigint, '", B48, "'::varchar, ", IF(EXACT(C48, ""), "null", C48), "::bigint); ") -> PERFORM "SchData-OLTP-Master"."Func_TblInstitution_SET"(varSystemLoginSession::bigint, null::bigint, null::varchar, null::timestamptz, null::timestamptz, null::varchar, varInstitutionBranchID::bigint, varBaseCurrencyID::bigint, 'Sigindo Kemas'::varchar, 141000000000004::bigint);
A49: =IF( COUNTIF( $D$4:$D$1000, $D49 ) = 1, "", "Duplicated") | B49: Smart Telecom | C49: 141000000000004 | D49: =IF(EXACT($C49, ""), B49, CONCATENATE(VLOOKUP($C49, 'REF - InstitutionType'!$B$4:$E$102, 3, FALSE), IF(EXACT(VLOOKUP($C49, 'REF - InstitutionType'!$B$4:$E$102, 3, FALSE), ""), "", " "), $B49, "", VLOOKUP($C49, 'REF - InstitutionType'!$B$4:$E$102, 4, FALSE), IF(EXACT($E49, ""), "", " [a.k.a : "&$E49&"]"))) -> PT. Smart Telecom | F49: SMA | L49: Customer | N49: =N48 + IF(EXACT(O49, ""), 0, 1) -> 123000000000046 | O49: =CONCATENATE("PERFORM ""SchData-OLTP-Master"".""Func_TblInstitution_SET""(varSystemLoginSession::bigint, null::bigint, null::varchar, null::timestamptz, null::timestamptz, null::varchar, varInstitutionBranchID::bigint, varBaseCurrencyID::bigint, '", B49, "'::varchar, ", IF(EXACT(C49, ""), "null", C49), "::bigint); ") -> PERFORM "SchData-OLTP-Master"."Func_TblInstitution_SET"(varSystemLoginSession::bigint, null::bigint, null::varchar, null::timestamptz, null::timestamptz, null::varchar, varInstitutionBranchID::bigint, varBaseCurrencyID::bigint, 'Smart Telecom'::varchar, 141000000000004::bigint);
A50: =IF( COUNTIF( $D$4:$D$1000, $D50 ) = 1, "", "Duplicated") | B50: Telekomunikasi Indonesia | C50: 141000000000007 | D50: =IF(EXACT($C50, ""), B50, CONCATENATE(VLOOKUP($C50, 'REF - InstitutionType'!$B$4:$E$102, 3, FALSE), IF(EXACT(VLOOKUP($C50, 'REF - InstitutionType'!$B$4:$E$102, 3, FALSE), ""), "", " "), $B50, "", VLOOKUP($C50, 'REF - InstitutionType'!$B$4:$E$102, 4, FALSE), IF(EXACT($E50, ""), "", " [a.k.a : "&$E50&"]"))) -> PT. Telekomunikasi Indonesia (Persero), Tbk [a.k.a : Telkom] | E50: Telkom | F50: INTEL | L50: Customer | N50: =N49 + IF(EXACT(O50, ""), 0, 1) -> 123000000000047 | O50: =CONCATENATE("PERFORM ""SchData-OLTP-Master"".""Func_TblInstitution_SET""(varSystemLoginSession::bigint, null::bigint, null::varchar, null::timestamptz, null::timestamptz, null::varchar, varInstitutionBranchID::bigint, varBaseCurrencyID::bigint, '", B50, "'::varchar, ", IF(EXACT(C50, ""), "null", C50), "::bigint); ") -> PERFORM "SchData-OLTP-Master"."Func_TblInstitution_SET"(varSystemLoginSession::bigint, null::bigint, null::varchar, null::timestamptz, null::timestamptz, null::varchar, varInstitutionBranchID::bigint, varBaseCurrencyID::bigint, 'Telekomunikasi Indonesia'::varchar, 141000000000007::bigint);
A51: =IF( COUNTIF( $D$4:$D$1000, $D51 ) = 1, "", "Duplicated") | B51: Telekomunikasi Selular | C51: 141000000000005 | D51: =IF(EXACT($C51, ""), B51, CONCATENATE(VLOOKUP($C51, 'REF - InstitutionType'!$B$4:$E$102, 3, FALSE), IF(EXACT(VLOOKUP($C51, 'REF - InstitutionType'!$B$4:$E$102, 3, FALSE), ""), "", " "), $B51, "", VLOOKUP($C51, 'REF - InstitutionType'!$B$4:$E$102, 4, FALSE), IF(EXACT($E51, ""), "", " [a.k.a : "&$E51&"]"))) -> PT. Telekomunikasi Selular, Tbk [a.k.a : Telkomsel] | E51: Telkomsel | F51: TSEL | L51: Customer | N51: =N50 + IF(EXACT(O51, ""), 0, 1) -> 123000000000048 | O51: =CONCATENATE("PERFORM ""SchData-OLTP-Master"".""Func_TblInstitution_SET""(varSystemLoginSession::bigint, null::bigint, null::varchar, null::timestamptz, null::timestamptz, null::varchar, varInstitutionBranchID::bigint, varBaseCurrencyID::bigint, '", B51, "'::varchar, ", IF(EXACT(C51, ""), "null", C51), "::bigint); ") -> PERFORM "SchData-OLTP-Master"."Func_TblInstitution_SET"(varSystemLoginSession::bigint, null::bigint, null::varchar, null::timestamptz, null::timestamptz, null::varchar, varInstitutionBranchID::bigint, varBaseCurrencyID::bigint, 'Telekomunikasi Selular'::varchar, 141000000000005::bigint);
A52: =IF( COUNTIF( $D$4:$D$1000, $D52 ) = 1, "", "Duplicated") | B52: Telkom Akses | C52: 141000000000004 | D52: =IF(EXACT($C52, ""), B52, CONCATENATE(VLOOKUP($C52, 'REF - InstitutionType'!$B$4:$E$102, 3, FALSE), IF(EXACT(VLOOKUP($C52, 'REF - InstitutionType'!$B$4:$E$102, 3, FALSE), ""), "", " "), $B52, "", VLOOKUP($C52, 'REF - InstitutionType'!$B$4:$E$102, 4, FALSE), IF(EXACT($E52, ""), "", " [a.k.a : "&$E52&"]"))) -> PT. Telkom Akses | F52: TA | L52: Customer | N52: =N51 + IF(EXACT(O52, ""), 0, 1) -> 123000000000049 | O52: =CONCATENATE("PERFORM ""SchData-OLTP-Master"".""Func_TblInstitution_SET""(varSystemLoginSession::bigint, null::bigint, null::varchar, null::timestamptz, null::timestamptz, null::varchar, varInstitutionBranchID::bigint, varBaseCurrencyID::bigint, '", B52, "'::varchar, ", IF(EXACT(C52, ""), "null", C52), "::bigint); ") -> PERFORM "SchData-OLTP-Master"."Func_TblInstitution_SET"(varSystemLoginSession::bigint, null::bigint, null::varchar, null::timestamptz, null::timestamptz, null::varchar, varInstitutionBranchID::bigint, varBaseCurrencyID::bigint, 'Telkom Akses'::varchar, 141000000000004::bigint);
A53: =IF( COUNTIF( $D$4:$D$1000, $D53 ) = 1, "", "Duplicated") | B53: Tosan Permai Lestari | C53: 141000000000004 | D53: =IF(EXACT($C53, ""), B53, CONCATENATE(VLOOKUP($C53, 'REF - InstitutionType'!$B$4:$E$102, 3, FALSE), IF(EXACT(VLOOKUP($C53, 'REF - InstitutionType'!$B$4:$E$102, 3, FALSE), ""), "", " "), $B53, "", VLOOKUP($C53, 'REF - InstitutionType'!$B$4:$E$102, 4, FALSE), IF(EXACT($E53, ""), "", " [a.k.a : "&$E53&"]"))) -> PT. Tosan Permai Lestari | F53: TOS | L53: Customer | N53: =N52 + IF(EXACT(O53, ""), 0, 1) -> 123000000000050 | O53: =CONCATENATE("PERFORM ""SchData-OLTP-Master"".""Func_TblInstitution_SET""(varSystemLoginSession::bigint, null::bigint, null::varchar, null::timestamptz, null::timestamptz, null::varchar, varInstitutionBranchID::bigint, varBaseCurrencyID::bigint, '", B53, "'::varchar, ", IF(EXACT(C53, ""), "null", C53), "::bigint); ") -> PERFORM "SchData-OLTP-Master"."Func_TblInstitution_SET"(varSystemLoginSession::bigint, null::bigint, null::varchar, null::timestamptz, null::timestamptz, null::varchar, varInstitutionBranchID::bigint, varBaseCurrencyID::bigint, 'Tosan Permai Lestari'::varchar, 141000000000004::bigint);
A54: =IF( COUNTIF( $D$4:$D$1000, $D54 ) = 1, "", "Duplicated") | B54: Tower Capital Indonesia | C54: 141000000000004 | D54: =IF(EXACT($C54, ""), B54, CONCATENATE(VLOOKUP($C54, 'REF - InstitutionType'!$B$4:$E$102, 3, FALSE), IF(EXACT(VLOOKUP($C54, 'REF - InstitutionType'!$B$4:$E$102, 3, FALSE), ""), "", " "), $B54, "", VLOOKUP($C54, 'REF - InstitutionType'!$B$4:$E$102, 4, FALSE), IF(EXACT($E54, ""), "", " [a.k.a : "&$E54&"]"))) -> PT. Tower Capital Indonesia | F54: TCI | L54: Customer | N54: =N53 + IF(EXACT(O54, ""), 0, 1) -> 123000000000051 | O54: =CONCATENATE("PERFORM ""SchData-OLTP-Master"".""Func_TblInstitution_SET""(varSystemLoginSession::bigint, null::bigint, null::varchar, null::timestamptz, null::timestamptz, null::varchar, varInstitutionBranchID::bigint, varBaseCurrencyID::bigint, '", B54, "'::varchar, ", IF(EXACT(C54, ""), "null", C54), "::bigint); ") -> PERFORM "SchData-OLTP-Master"."Func_TblInstitution_SET"(varSystemLoginSession::bigint, null::bigint, null::varchar, null::timestamptz, null::timestamptz, null::varchar, varInstitutionBranchID::bigint, varBaseCurrencyID::bigint, 'Tower Capital Indonesia'::varchar, 141000000000004::bigint);
A55: =IF( COUNTIF( $D$4:$D$1000, $D55 ) = 1, "", "Duplicated") | B55: Waskita Karya | C55: 141000000000007 | D55: =IF(EXACT($C55, ""), B55, CONCATENATE(VLOOKUP($C55, 'REF - InstitutionType'!$B$4:$E$102, 3, FALSE), IF(EXACT(VLOOKUP($C55, 'REF - InstitutionType'!$B$4:$E$102, 3, FALSE), ""), "", " "), $B55, "", VLOOKUP($C55, 'REF - InstitutionType'!$B$4:$E$102, 4, FALSE), IF(EXACT($E55, ""), "", " [a.k.a : "&$E55&"]"))) -> PT. Waskita Karya (Persero), Tbk | F55: WAS | L55: Customer | N55: =N54 + IF(EXACT(O55, ""), 0, 1) -> 123000000000052 | O55: =CONCATENATE("PERFORM ""SchData-OLTP-Master"".""Func_TblInstitution_SET""(varSystemLoginSession::bigint, null::bigint, null::varchar, null::timestamptz, null::timestamptz, null::varchar, varInstitutionBranchID::bigint, varBaseCurrencyID::bigint, '", B55, "'::varchar, ", IF(EXACT(C55, ""), "null", C55), "::bigint); ") -> PERFORM "SchData-OLTP-Master"."Func_TblInstitution_SET"(varSystemLoginSession::bigint, null::bigint, null::varchar, null::timestamptz, null::timestamptz, null::varchar, varInstitutionBranchID::bigint, varBaseCurrencyID::bigint, 'Waskita Karya'::varchar, 141000000000007::bigint);
A56: =IF( COUNTIF( $D$4:$D$1000, $D56 ) = 1, "", "Duplicated") | B56: Widodo Karya Sejahtera | C56: 141000000000004 | D56: =IF(EXACT($C56, ""), B56, CONCATENATE(VLOOKUP($C56, 'REF - InstitutionType'!$B$4:$E$102, 3, FALSE), IF(EXACT(VLOOKUP($C56, 'REF - InstitutionType'!$B$4:$E$102, 3, FALSE), ""), "", " "), $B56, "", VLOOKUP($C56, 'REF - InstitutionType'!$B$4:$E$102, 4, FALSE), IF(EXACT($E56, ""), "", " [a.k.a : "&$E56&"]"))) -> PT. Widodo Karya Sejahtera | F56: WKS | L56: Customer | N56: =N55 + IF(EXACT(O56, ""), 0, 1) -> 123000000000053 | O56: =CONCATENATE("PERFORM ""SchData-OLTP-Master"".""Func_TblInstitution_SET""(varSystemLoginSession::bigint, null::bigint, null::varchar, null::timestamptz, null::timestamptz, null::varchar, varInstitutionBranchID::bigint, varBaseCurrencyID::bigint, '", B56, "'::varchar, ", IF(EXACT(C56, ""), "null", C56), "::bigint); ") -> PERFORM "SchData-OLTP-Master"."Func_TblInstitution_SET"(varSystemLoginSession::bigint, null::bigint, null::varchar, null::timestamptz, null::timestamptz, null::varchar, varInstitutionBranchID::bigint, varBaseCurrencyID::bigint, 'Widodo Karya Sejahtera'::varchar, 141000000000004::bigint);
A57: =IF( COUNTIF( $D$4:$D$1000, $D57 ) = 1, "", "Duplicated") | B57: XL Axiata | C57: 141000000000005 | D57: =IF(EXACT($C57, ""), B57, CONCATENATE(VLOOKUP($C57, 'REF - InstitutionType'!$B$4:$E$102, 3, FALSE), IF(EXACT(VLOOKUP($C57, 'REF - InstitutionType'!$B$4:$E$102, 3, FALSE), ""), "", " "), $B57, "", VLOOKUP($C57, 'REF - InstitutionType'!$B$4:$E$102, 4, FALSE), IF(EXACT($E57, ""), "", " [a.k.a : "&$E57&"]"))) -> PT. XL Axiata, Tbk [a.k.a : XL] | E57: XL | F57: XL | L57: Customer | N57: =N56 + IF(EXACT(O57, ""), 0, 1) -> 123000000000054 | O57: =CONCATENATE("PERFORM ""SchData-OLTP-Master"".""Func_TblInstitution_SET""(varSystemLoginSession::bigint, null::bigint, null::varchar, null::timestamptz, null::timestamptz, null::varchar, varInstitutionBranchID::bigint, varBaseCurrencyID::bigint, '", B57, "'::varchar, ", IF(EXACT(C57, ""), "null", C57), "::bigint); ") -> PERFORM "SchData-OLTP-Master"."Func_TblInstitution_SET"(varSystemLoginSession::bigint, null::bigint, null::varchar, null::timestamptz, null::timestamptz, null::varchar, varInstitutionBranchID::bigint, varBaseCurrencyID::bigint, 'XL Axiata'::varchar, 141000000000005::bigint);
A58: =IF( COUNTIF( $D$4:$D$1000, $D58 ) = 1, "", "Duplicated") | B58: XL Mitrayasa | C58: 141000000000004 | D58: =IF(EXACT($C58, ""), B58, CONCATENATE(VLOOKUP($C58, 'REF - InstitutionType'!$B$4:$E$102, 3, FALSE), IF(EXACT(VLOOKUP($C58, 'REF - InstitutionType'!$B$4:$E$102, 3, FALSE), ""), "", " "), $B58, "", VLOOKUP($C58, 'REF - InstitutionType'!$B$4:$E$102, 4, FALSE), IF(EXACT($E58, ""), "", " [a.k.a : "&$E58&"]"))) -> PT. XL Mitrayasa | F58: XLM | L58: Customer | N58: =N57 + IF(EXACT(O58, ""), 0, 1) -> 123000000000055 | O58: =CONCATENATE("PERFORM ""SchData-OLTP-Master"".""Func_TblInstitution_SET""(varSystemLoginSession::bigint, null::bigint, null::varchar, null::timestamptz, null::timestamptz, null::varchar, varInstitutionBranchID::bigint, varBaseCurrencyID::bigint, '", B58, "'::varchar, ", IF(EXACT(C58, ""), "null", C58), "::bigint); ") -> PERFORM "SchData-OLTP-Master"."Func_TblInstitution_SET"(varSystemLoginSession::bigint, null::bigint, null::varchar, null::timestamptz, null::timestamptz, null::varchar, varInstitutionBranchID::bigint, varBaseCurrencyID::bigint, 'XL Mitrayasa'::varchar, 141000000000004::bigint);
A59: =IF( COUNTIF( $D$4:$D$1000, $D59 ) = 1, "", "Duplicated") | B59: ZTE Indonesia | C59: 141000000000004 | D59: =IF(EXACT($C59, ""), B59, CONCATENATE(VLOOKUP($C59, 'REF - InstitutionType'!$B$4:$E$102, 3, FALSE), IF(EXACT(VLOOKUP($C59, 'REF - InstitutionType'!$B$4:$E$102, 3, FALSE), ""), "", " "), $B59, "", VLOOKUP($C59, 'REF - InstitutionType'!$B$4:$E$102, 4, FALSE), IF(EXACT($E59, ""), "", " [a.k.a : "&$E59&"]"))) -> PT. ZTE Indonesia | F59: ZTE | L59: Customer | N59: =N58 + IF(EXACT(O59, ""), 0, 1) -> 123000000000056 | O59: =CONCATENATE("PERFORM ""SchData-OLTP-Master"".""Func_TblInstitution_SET""(varSystemLoginSession::bigint, null::bigint, null::varchar, null::timestamptz, null::timestamptz, null::varchar, varInstitutionBranchID::bigint, varBaseCurrencyID::bigint, '", B59, "'::varchar, ", IF(EXACT(C59, ""), "null", C59), "::bigint); ") -> PERFORM "SchData-OLTP-Master"."Func_TblInstitution_SET"(varSystemLoginSession::bigint, null::bigint, null::varchar, null::timestamptz, null::timestamptz, null::varchar, varInstitutionBranchID::bigint, varBaseCurrencyID::bigint, 'ZTE Indonesia'::varchar, 141000000000004::bigint);
A60: =IF( COUNTIF( $D$4:$D$1000, $D60 ) = 1, "", "Duplicated") | B60: Sansaine Exindo | C60: 141000000000004 | D60: =IF(EXACT($C60, ""), B60, CONCATENATE(VLOOKUP($C60, 'REF - InstitutionType'!$B$4:$E$102, 3, FALSE), IF(EXACT(VLOOKUP($C60, 'REF - InstitutionType'!$B$4:$E$102, 3, FALSE), ""), "", " "), $B60, "", VLOOKUP($C60, 'REF - InstitutionType'!$B$4:$E$102, 4, FALSE), IF(EXACT($E60, ""), "", " [a.k.a : "&$E60&"]"))) -> PT. Sansaine Exindo | F60: SANE | L60: Customer | N60: =N59 + IF(EXACT(O60, ""), 0, 1) -> 123000000000057 | O60: =CONCATENATE("PERFORM ""SchData-OLTP-Master"".""Func_TblInstitution_SET""(varSystemLoginSession::bigint, null::bigint, null::varchar, null::timestamptz, null::timestamptz, null::varchar, varInstitutionBranchID::bigint, varBaseCurrencyID::bigint, '", B60, "'::varchar, ", IF(EXACT(C60, ""), "null", C60), "::bigint); ") -> PERFORM "SchData-OLTP-Master"."Func_TblInstitution_SET"(varSystemLoginSession::bigint, null::bigint, null::varchar, null::timestamptz, null::timestamptz, null::varchar, varInstitutionBranchID::bigint, varBaseCurrencyID::bigint, 'Sansaine Exindo'::varchar, 141000000000004::bigint);
A61: =IF( COUNTIF( $D$4:$D$1000, $D61 ) = 1, "", "Duplicated") | B61: Indo Jaya Scaffolding | D61: =IF(EXACT($C61, ""), B61, CONCATENATE(VLOOKUP($C61, 'REF - InstitutionType'!$B$4:$E$102, 3, FALSE), IF(EXACT(VLOOKUP($C61, 'REF - InstitutionType'!$B$4:$E$102, 3, FALSE), ""), "", " "), $B61, "", VLOOKUP($C61, 'REF - InstitutionType'!$B$4:$E$102, 4, FALSE), IF(EXACT($E61, ""), "", " [a.k.a : "&$E61&"]"))) -> Indo Jaya Scaffolding | F61: IJS | L61: Customer | N61: =N60 + IF(EXACT(O61, ""), 0, 1) -> 123000000000058 | O61: =CONCATENATE("PERFORM ""SchData-OLTP-Master"".""Func_TblInstitution_SET""(varSystemLoginSession::bigint, null::bigint, null::varchar, null::timestamptz, null::timestamptz, null::varchar, varInstitutionBranchID::bigint, varBaseCurrencyID::bigint, '", B61, "'::varchar, ", IF(EXACT(C61, ""), "null", C61), "::bigint); ") -> PERFORM "SchData-OLTP-Master"."Func_TblInstitution_SET"(varSystemLoginSession::bigint, null::bigint, null::varchar, null::timestamptz, null::timestamptz, null::varchar, varInstitutionBranchID::bigint, varBaseCurrencyID::bigint, 'Indo Jaya Scaffolding'::varchar, null::bigint);
A62: =IF( COUNTIF( $D$4:$D$1000, $D62 ) = 1, "", "Duplicated") | B62: Pembangunan Perumahan | C62: 141000000000007 | D62: =IF(EXACT($C62, ""), B62, CONCATENATE(VLOOKUP($C62, 'REF - InstitutionType'!$B$4:$E$102, 3, FALSE), IF(EXACT(VLOOKUP($C62, 'REF - InstitutionType'!$B$4:$E$102, 3, FALSE), ""), "", " "), $B62, "", VLOOKUP($C62, 'REF - InstitutionType'!$B$4:$E$102, 4, FALSE), IF(EXACT($E62, ""), "", " [a.k.a : "&$E62&"]"))) -> PT. Pembangunan Perumahan (Persero), Tbk [a.k.a : PP] | E62: PP | F62: PP | L62: Customer | N62: =N61 + IF(EXACT(O62, ""), 0, 1) -> 123000000000059 | O62: =CONCATENATE("PERFORM ""SchData-OLTP-Master"".""Func_TblInstitution_SET""(varSystemLoginSession::bigint, null::bigint, null::varchar, null::timestamptz, null::timestamptz, null::varchar, varInstitutionBranchID::bigint, varBaseCurrencyID::bigint, '", B62, "'::varchar, ", IF(EXACT(C62, ""), "null", C62), "::bigint); ") -> PERFORM "SchData-OLTP-Master"."Func_TblInstitution_SET"(varSystemLoginSession::bigint, null::bigint, null::varchar, null::timestamptz, null::timestamptz, null::varchar, varInstitutionBranchID::bigint, varBaseCurrencyID::bigint, 'Pembangunan Perumahan'::varchar, 141000000000007::bigint);
A63: =IF( COUNTIF( $D$4:$D$1000, $D63 ) = 1, "", "Duplicated") | B63: Linus Nusa Express | D63: =IF(EXACT($C63, ""), B63, CONCATENATE(VLOOKUP($C63, 'REF - InstitutionType'!$B$4:$E$102, 3, FALSE), IF(EXACT(VLOOKUP($C63, 'REF - InstitutionType'!$B$4:$E$102, 3, FALSE), ""), "", " "), $B63, "", VLOOKUP($C63, 'REF - InstitutionType'!$B$4:$E$102, 4, FALSE), IF(EXACT($E63, ""), "", " [a.k.a : "&$E63&"]"))) -> Linus Nusa Express | F63: Linus | L63: Customer | N63: =N62 + IF(EXACT(O63, ""), 0, 1) -> 123000000000060 | O63: =CONCATENATE("PERFORM ""SchData-OLTP-Master"".""Func_TblInstitution_SET""(varSystemLoginSession::bigint, null::bigint, null::varchar, null::timestamptz, null::timestamptz, null::varchar, varInstitutionBranchID::bigint, varBaseCurrencyID::bigint, '", B63, "'::varchar, ", IF(EXACT(C63, ""), "null", C63), "::bigint); ") -> PERFORM "SchData-OLTP-Master"."Func_TblInstitution_SET"(varSystemLoginSession::bigint, null::bigint, null::varchar, null::timestamptz, null::timestamptz, null::varchar, varInstitutionBranchID::bigint, varBaseCurrencyID::bigint, 'Linus Nusa Express'::varchar, null::bigint);
A64: =IF( COUNTIF( $D$4:$D$1000, $D64 ) = 1, "", "Duplicated") | B64: Penjaminan Jamkrindo Syariah | C64: 141000000000004 | D64: =IF(EXACT($C64, ""), B64, CONCATENATE(VLOOKUP($C64, 'REF - InstitutionType'!$B$4:$E$102, 3, FALSE), IF(EXACT(VLOOKUP($C64, 'REF - InstitutionType'!$B$4:$E$102, 3, FALSE), ""), "", " "), $B64, "", VLOOKUP($C64, 'REF - InstitutionType'!$B$4:$E$102, 4, FALSE), IF(EXACT($E64, ""), "", " [a.k.a : "&$E64&"]"))) -> PT. Penjaminan Jamkrindo Syariah | F64: JAMKR | L64: Customer | N64: =N63 + IF(EXACT(O64, ""), 0, 1) -> 123000000000061 | O64: =CONCATENATE("PERFORM ""SchData-OLTP-Master"".""Func_TblInstitution_SET""(varSystemLoginSession::bigint, null::bigint, null::varchar, null::timestamptz, null::timestamptz, null::varchar, varInstitutionBranchID::bigint, varBaseCurrencyID::bigint, '", B64, "'::varchar, ", IF(EXACT(C64, ""), "null", C64), "::bigint); ") -> PERFORM "SchData-OLTP-Master"."Func_TblInstitution_SET"(varSystemLoginSession::bigint, null::bigint, null::varchar, null::timestamptz, null::timestamptz, null::varchar, varInstitutionBranchID::bigint, varBaseCurrencyID::bigint, 'Penjaminan Jamkrindo Syariah'::varchar, 141000000000004::bigint);
A65: =IF( COUNTIF( $D$4:$D$1000, $D65 ) = 1, "", "Duplicated") | B65: Larsen And Tourbo | C65: 141000000000004 | D65: =IF(EXACT($C65, ""), B65, CONCATENATE(VLOOKUP($C65, 'REF - InstitutionType'!$B$4:$E$102, 3, FALSE), IF(EXACT(VLOOKUP($C65, 'REF - InstitutionType'!$B$4:$E$102, 3, FALSE), ""), "", " "), $B65, "", VLOOKUP($C65, 'REF - InstitutionType'!$B$4:$E$102, 4, FALSE), IF(EXACT($E65, ""), "", " [a.k.a : "&$E65&"]"))) -> PT. Larsen And Tourbo | F65: L&T | L65: Customer | N65: =N64 + IF(EXACT(O65, ""), 0, 1) -> 123000000000062 | O65: =CONCATENATE("PERFORM ""SchData-OLTP-Master"".""Func_TblInstitution_SET""(varSystemLoginSession::bigint, null::bigint, null::varchar, null::timestamptz, null::timestamptz, null::varchar, varInstitutionBranchID::bigint, varBaseCurrencyID::bigint, '", B65, "'::varchar, ", IF(EXACT(C65, ""), "null", C65), "::bigint); ") -> PERFORM "SchData-OLTP-Master"."Func_TblInstitution_SET"(varSystemLoginSession::bigint, null::bigint, null::varchar, null::timestamptz, null::timestamptz, null::varchar, varInstitutionBranchID::bigint, varBaseCurrencyID::bigint, 'Larsen And Tourbo'::varchar, 141000000000004::bigint);
A66: =IF( COUNTIF( $D$4:$D$1000, $D66 ) = 1, "", "Duplicated") | B66: Asuransi Sinar Mas | C66: 141000000000004 | D66: =IF(EXACT($C66, ""), B66, CONCATENATE(VLOOKUP($C66, 'REF - InstitutionType'!$B$4:$E$102, 3, FALSE), IF(EXACT(VLOOKUP($C66, 'REF - InstitutionType'!$B$4:$E$102, 3, FALSE), ""), "", " "), $B66, "", VLOOKUP($C66, 'REF - InstitutionType'!$B$4:$E$102, 4, FALSE), IF(EXACT($E66, ""), "", " [a.k.a : "&$E66&"]"))) -> PT. Asuransi Sinar Mas | F66: ASM | L66: Customer | N66: =N65 + IF(EXACT(O66, ""), 0, 1) -> 123000000000063 | O66: =CONCATENATE("PERFORM ""SchData-OLTP-Master"".""Func_TblInstitution_SET""(varSystemLoginSession::bigint, null::bigint, null::varchar, null::timestamptz, null::timestamptz, null::varchar, varInstitutionBranchID::bigint, varBaseCurrencyID::bigint, '", B66, "'::varchar, ", IF(EXACT(C66, ""), "null", C66), "::bigint); ") -> PERFORM "SchData-OLTP-Master"."Func_TblInstitution_SET"(varSystemLoginSession::bigint, null::bigint, null::varchar, null::timestamptz, null::timestamptz, null::varchar, varInstitutionBranchID::bigint, varBaseCurrencyID::bigint, 'Asuransi Sinar Mas '::varchar, 141000000000004::bigint);
A67: =IF( COUNTIF( $D$4:$D$1000, $D67 ) = 1, "", "Duplicated") | B67: ='RAW - Supplier'!A2 -> Agung Jaya | D67: =IF(EXACT($C67, ""), B67, CONCATENATE(VLOOKUP($C67, 'REF - InstitutionType'!$B$4:$E$102, 3, FALSE), IF(EXACT(VLOOKUP($C67, 'REF - InstitutionType'!$B$4:$E$102, 3, FALSE), ""), "", " "), $B67, "", VLOOKUP($C67, 'REF - InstitutionType'!$B$4:$E$102, 4, FALSE), IF(EXACT($E67, ""), "", " [a.k.a : "&$E67&"]"))) -> Agung Jaya | F67: ='RAW - Supplier'!B2 -> VDR0002 | L67: Supplier | N67: =N66 + IF(EXACT(O67, ""), 0, 1) -> 123000000000064 | O67: =CONCATENATE("PERFORM ""SchData-OLTP-Master"".""Func_TblInstitution_SET""(varSystemLoginSession::bigint, null::bigint, null::varchar, null::timestamptz, null::timestamptz, null::varchar, varInstitutionBranchID::bigint, varBaseCurrencyID::bigint, '", B67, "'::varchar, ", IF(EXACT(C67, ""), "null", C67), "::bigint); ") -> PERFORM "SchData-OLTP-Master"."Func_TblInstitution_SET"(varSystemLoginSession::bigint, null::bigint, null::varchar, null::timestamptz, null::timestamptz, null::varchar, varInstitutionBranchID::bigint, varBaseCurrencyID::bigint, 'Agung Jaya'::varchar, null::bigint);
A68: =IF( COUNTIF( $D$4:$D$1000, $D68 ) = 1, "", "Duplicated") | B68: ='RAW - Supplier'!A3 -> Aji Perkasa | D68: =IF(EXACT($C68, ""), B68, CONCATENATE(VLOOKUP($C68, 'REF - InstitutionType'!$B$4:$E$102, 3, FALSE), IF(EXACT(VLOOKUP($C68, 'REF - InstitutionType'!$B$4:$E$102, 3, FALSE), ""), "", " "), $B68, "", VLOOKUP($C68, 'REF - InstitutionType'!$B$4:$E$102, 4, FALSE), IF(EXACT($E68, ""), "", " [a.k.a : "&$E68&"]"))) -> Aji Perkasa | F68: ='RAW - Supplier'!B3 -> VDR0003 | L68: Supplier | N68: =N67 + IF(EXACT(O68, ""), 0, 1) -> 123000000000065 | O68: =CONCATENATE("PERFORM ""SchData-OLTP-Master"".""Func_TblInstitution_SET""(varSystemLoginSession::bigint, null::bigint, null::varchar, null::timestamptz, null::timestamptz, null::varchar, varInstitutionBranchID::bigint, varBaseCurrencyID::bigint, '", B68, "'::varchar, ", IF(EXACT(C68, ""), "null", C68), "::bigint); ") -> PERFORM "SchData-OLTP-Master"."Func_TblInstitution_SET"(varSystemLoginSession::bigint, null::bigint, null::varchar, null::timestamptz, null::timestamptz, null::varchar, varInstitutionBranchID::bigint, varBaseCurrencyID::bigint, 'Aji Perkasa'::varchar, null::bigint);
A69: =IF( COUNTIF( $D$4:$D$1000, $D69 ) = 1, "", "Duplicated") | B69: ='RAW - Supplier'!A4 -> Aledro Duta Jaya | D69: =IF(EXACT($C69, ""), B69, CONCATENATE(VLOOKUP($C69, 'REF - InstitutionType'!$B$4:$E$102, 3, FALSE), IF(EXACT(VLOOKUP($C69, 'REF - InstitutionType'!$B$4:$E$102, 3, FALSE), ""), "", " "), $B69, "", VLOOKUP($C69, 'REF - InstitutionType'!$B$4:$E$102, 4, FALSE), IF(EXACT($E69, ""), "", " [a.k.a : "&$E69&"]"))) -> Aledro Duta Jaya | F69: ='RAW - Supplier'!B4 -> VDR0004 | L69: Supplier | N69: =N68 + IF(EXACT(O69, ""), 0, 1) -> 123000000000066 | O69: =CONCATENATE("PERFORM ""SchData-OLTP-Master"".""Func_TblInstitution_SET""(varSystemLoginSession::bigint, null::bigint, null::varchar, null::timestamptz, null::timestamptz, null::varchar, varInstitutionBranchID::bigint, varBaseCurrencyID::bigint, '", B69, "'::varchar, ", IF(EXACT(C69, ""), "null", C69), "::bigint); ") -> PERFORM "SchData-OLTP-Master"."Func_TblInstitution_SET"(varSystemLoginSession::bigint, null::bigint, null::varchar, null::timestamptz, null::timestamptz, null::varchar, varInstitutionBranchID::bigint, varBaseCurrencyID::bigint, 'Aledro Duta Jaya'::varchar, null::bigint);
A70: =IF( COUNTIF( $D$4:$D$1000, $D70 ) = 1, "", "Duplicated") | B70: ='RAW - Supplier'!A5 -> Alpine Cool Utama | D70: =IF(EXACT($C70, ""), B70, CONCATENATE(VLOOKUP($C70, 'REF - InstitutionType'!$B$4:$E$102, 3, FALSE), IF(EXACT(VLOOKUP($C70, 'REF - InstitutionType'!$B$4:$E$102, 3, FALSE), ""), "", " "), $B70, "", VLOOKUP($C70, 'REF - InstitutionType'!$B$4:$E$102, 4, FALSE), IF(EXACT($E70, ""), "", " [a.k.a : "&$E70&"]"))) -> Alpine Cool Utama | F70: ='RAW - Supplier'!B5 -> VDR0005 | L70: Supplier | N70: =N69 + IF(EXACT(O70, ""), 0, 1) -> 123000000000067 | O70: =CONCATENATE("PERFORM ""SchData-OLTP-Master"".""Func_TblInstitution_SET""(varSystemLoginSession::bigint, null::bigint, null::varchar, null::timestamptz, null::timestamptz, null::varchar, varInstitutionBranchID::bigint, varBaseCurrencyID::bigint, '", B70, "'::varchar, ", IF(EXACT(C70, ""), "null", C70), "::bigint); ") -> PERFORM "SchData-OLTP-Master"."Func_TblInstitution_SET"(varSystemLoginSession::bigint, null::bigint, null::varchar, null::timestamptz, null::timestamptz, null::varchar, varInstitutionBranchID::bigint, varBaseCurrencyID::bigint, 'Alpine Cool Utama'::varchar, null::bigint);
A71: =IF( COUNTIF( $D$4:$D$1000, $D71 ) = 1, "", "Duplicated") | B71: ='RAW - Supplier'!A6 -> Alumagada Jaya Mandiri | D71: =IF(EXACT($C71, ""), B71, CONCATENATE(VLOOKUP($C71, 'REF - InstitutionType'!$B$4:$E$102, 3, FALSE), IF(EXACT(VLOOKUP($C71, 'REF - InstitutionType'!$B$4:$E$102, 3, FALSE), ""), "", " "), $B71, "", VLOOKUP($C71, 'REF - InstitutionType'!$B$4:$E$102, 4, FALSE), IF(EXACT($E71, ""), "", " [a.k.a : "&$E71&"]"))) -> Alumagada Jaya Mandiri | F71: ='RAW - Supplier'!B6 -> VDR0006 | L71: Supplier | N71: =N70 + IF(EXACT(O71, ""), 0, 1) -> 123000000000068 | O71: =CONCATENATE("PERFORM ""SchData-OLTP-Master"".""Func_TblInstitution_SET""(varSystemLoginSession::bigint, null::bigint, null::varchar, null::timestamptz, null::timestamptz, null::varchar, varInstitutionBranchID::bigint, varBaseCurrencyID::bigint, '", B71, "'::varchar, ", IF(EXACT(C71, ""), "null", C71), "::bigint); ") -> PERFORM "SchData-OLTP-Master"."Func_TblInstitution_SET"(varSystemLoginSession::bigint, null::bigint, null::varchar, null::timestamptz, null::timestamptz, null::varchar, varInstitutionBranchID::bigint, varBaseCurrencyID::bigint, 'Alumagada Jaya Mandiri'::varchar, null::bigint);
A72: =IF( COUNTIF( $D$4:$D$1000, $D72 ) = 1, "", "Duplicated") | B72: Karawang Dinamika Lestari | C72: 141000000000004 | D72: =IF(EXACT($C72, ""), B72, CONCATENATE(VLOOKUP($C72, 'REF - InstitutionType'!$B$4:$E$102, 3, FALSE), IF(EXACT(VLOOKUP($C72, 'REF - InstitutionType'!$B$4:$E$102, 3, FALSE), ""), "", " "), $B72, "", VLOOKUP($C72, 'REF - InstitutionType'!$B$4:$E$102, 4, FALSE), IF(EXACT($E72, ""), "", " [a.k.a : "&$E72&"]"))) -> PT. Karawang Dinamika Lestari | F72: PTKDL | L72: Customer | N72: =N71 + IF(EXACT(O72, ""), 0, 1) -> 123000000000069 | O72: =CONCATENATE("PERFORM ""SchData-OLTP-Master"".""Func_TblInstitution_SET""(varSystemLoginSession::bigint, null::bigint, null::varchar, null::timestamptz, null::timestamptz, null::varchar, varInstitutionBranchID::bigint, varBaseCurrencyID::bigint, '", B72, "'::varchar, ", IF(EXACT(C72, ""), "null", C72), "::bigint); ") -> PERFORM "SchData-OLTP-Master"."Func_TblInstitution_SET"(varSystemLoginSession::bigint, null::bigint, null::varchar, null::timestamptz, null::timestamptz, null::varchar, varInstitutionBranchID::bigint, varBaseCurrencyID::bigint, 'Karawang Dinamika Lestari'::varchar, 141000000000004::bigint);
A73: =IF( COUNTIF( $D$4:$D$1000, $D73 ) = 1, "", "Duplicated") | B73: KSO WST-QDC | D73: =IF(EXACT($C73, ""), B73, CONCATENATE(VLOOKUP($C73, 'REF - InstitutionType'!$B$4:$E$102, 3, FALSE), IF(EXACT(VLOOKUP($C73, 'REF - InstitutionType'!$B$4:$E$102, 3, FALSE), ""), "", " "), $B73, "", VLOOKUP($C73, 'REF - InstitutionType'!$B$4:$E$102, 4, FALSE), IF(EXACT($E73, ""), "", " [a.k.a : "&$E73&"]"))) -> KSO WST-QDC | F73: KSO1 | L73: Customer | N73: =N72 + IF(EXACT(O73, ""), 0, 1) -> 123000000000070 | O73: =CONCATENATE("PERFORM ""SchData-OLTP-Master"".""Func_TblInstitution_SET""(varSystemLoginSession::bigint, null::bigint, null::varchar, null::timestamptz, null::timestamptz, null::varchar, varInstitutionBranchID::bigint, varBaseCurrencyID::bigint, '", B73, "'::varchar, ", IF(EXACT(C73, ""), "null", C73), "::bigint); ") -> PERFORM "SchData-OLTP-Master"."Func_TblInstitution_SET"(varSystemLoginSession::bigint, null::bigint, null::varchar, null::timestamptz, null::timestamptz, null::varchar, varInstitutionBranchID::bigint, varBaseCurrencyID::bigint, 'KSO WST-QDC'::varchar, null::bigint);
A74: =IF( COUNTIF( $D$4:$D$1000, $D74 ) = 1, "", "Duplicated") | B74: Adhi Commuter Properti | C74: 141000000000004 | D74: =IF(EXACT($C74, ""), B74, CONCATENATE(VLOOKUP($C74, 'REF - InstitutionType'!$B$4:$E$102, 3, FALSE), IF(EXACT(VLOOKUP($C74, 'REF - InstitutionType'!$B$4:$E$102, 3, FALSE), ""), "", " "), $B74, "", VLOOKUP($C74, 'REF - InstitutionType'!$B$4:$E$102, 4, FALSE), IF(EXACT($E74, ""), "", " [a.k.a : "&$E74&"]"))) -> PT. Adhi Commuter Properti | F74: ADCP | L74: Customer | N74: =N73 + IF(EXACT(O74, ""), 0, 1) -> 123000000000071 | O74: =CONCATENATE("PERFORM ""SchData-OLTP-Master"".""Func_TblInstitution_SET""(varSystemLoginSession::bigint, null::bigint, null::varchar, null::timestamptz, null::timestamptz, null::varchar, varInstitutionBranchID::bigint, varBaseCurrencyID::bigint, '", B74, "'::varchar, ", IF(EXACT(C74, ""), "null", C74), "::bigint); ") -> PERFORM "SchData-OLTP-Master"."Func_TblInstitution_SET"(varSystemLoginSession::bigint, null::bigint, null::varchar, null::timestamptz, null::timestamptz, null::varchar, varInstitutionBranchID::bigint, varBaseCurrencyID::bigint, 'Adhi Commuter Properti'::varchar, 141000000000004::bigint);
A75: =IF( COUNTIF( $D$4:$D$1000, $D75 ) = 1, "", "Duplicated") | B75: Alfa Link Mandiri | C75: 141000000000002 | D75: =IF(EXACT($C75, ""), B75, CONCATENATE(VLOOKUP($C75, 'REF - InstitutionType'!$B$4:$E$102, 3, FALSE), IF(EXACT(VLOOKUP($C75, 'REF - InstitutionType'!$B$4:$E$102, 3, FALSE), ""), "", " "), $B75, "", VLOOKUP($C75, 'REF - InstitutionType'!$B$4:$E$102, 4, FALSE), IF(EXACT($E75, ""), "", " [a.k.a : "&$E75&"]"))) -> CV. Alfa Link Mandiri | F75: VDR3827 | G75: =IF(EXACT($F75, ""), "", VLOOKUP($F75, 'RAW EDITED 3 Years'!$A$2:$G$438, 5, FALSE)) -> Supplier Material Civil | H75: =IF(EXACT($F75, ""), "", VLOOKUP($F75, 'RAW EDITED 3 Years'!$A$2:$G$438, 6, FALSE)) -> Tools | I75: =IF(EXACT($F75, ""), "", VLOOKUP($F75, 'RAW EDITED 3 Years'!$A$2:$G$438, 7, FALSE)) -> Untuk Tools dan APD di Kolaka | L75: Supplier | N75: =N74 + IF(EXACT(O75, ""), 0, 1) -> 123000000000072 | O75: =CONCATENATE("PERFORM ""SchData-OLTP-Master"".""Func_TblInstitution_SET""(varSystemLoginSession::bigint, null::bigint, null::varchar, null::timestamptz, null::timestamptz, null::varchar, varInstitutionBranchID::bigint, varBaseCurrencyID::bigint, '", B75, "'::varchar, ", IF(EXACT(C75, ""), "null", C75), "::bigint); ") -> PERFORM "SchData-OLTP-Master"."Func_TblInstitution_SET"(varSystemLoginSession::bigint, null::bigint, null::varchar, null::timestamptz, null::timestamptz, null::varchar, varInstitutionBranchID::bigint, varBaseCurrencyID::bigint, 'Alfa Link Mandiri'::varchar, 141000000000002::bigint);
A76: =IF( COUNTIF( $D$4:$D$1000, $D76 ) = 1, "", "Duplicated") | B76: Alodia Makmur Abadi | C76: 141000000000002 | D76: =IF(EXACT($C76, ""), B76, CONCATENATE(VLOOKUP($C76, 'REF - InstitutionType'!$B$4:$E$102, 3, FALSE), IF(EXACT(VLOOKUP($C76, 'REF - InstitutionType'!$B$4:$E$102, 3, FALSE), ""), "", " "), $B76, "", VLOOKUP($C76, 'REF - InstitutionType'!$B$4:$E$102, 4, FALSE), IF(EXACT($E76, ""), "", " [a.k.a : "&$E76&"]"))) -> CV. Alodia Makmur Abadi | F76: VDR3823 | G76: =IF(EXACT($F76, ""), "", VLOOKUP($F76, 'RAW EDITED 3 Years'!$A$2:$G$438, 5, FALSE)) -> Jasa Kesehatan | H76: =IF(EXACT($F76, ""), "", VLOOKUP($F76, 'RAW EDITED 3 Years'!$A$2:$G$438, 6, FALSE)) -> Rumah Sakit | I76: =IF(EXACT($F76, ""), "", VLOOKUP($F76, 'RAW EDITED 3 Years'!$A$2:$G$438, 7, FALSE)) -> untuk MCU | L76: Supplier | N76: =N75 + IF(EXACT(O76, ""), 0, 1) -> 123000000000073 | O76: =CONCATENATE("PERFORM ""SchData-OLTP-Master"".""Func_TblInstitution_SET""(varSystemLoginSession::bigint, null::bigint, null::varchar, null::timestamptz, null::timestamptz, null::varchar, varInstitutionBranchID::bigint, varBaseCurrencyID::bigint, '", B76, "'::varchar, ", IF(EXACT(C76, ""), "null", C76), "::bigint); ") -> PERFORM "SchData-OLTP-Master"."Func_TblInstitution_SET"(varSystemLoginSession::bigint, null::bigint, null::varchar, null::timestamptz, null::timestamptz, null::varchar, varInstitutionBranchID::bigint, varBaseCurrencyID::bigint, 'Alodia Makmur Abadi'::varchar, 141000000000002::bigint);
A77: =IF( COUNTIF( $D$4:$D$1000, $D77 ) = 1, "", "Duplicated") | B77: Anugerah Karya Magantha | C77: 141000000000002 | D77: =IF(EXACT($C77, ""), B77, CONCATENATE(VLOOKUP($C77, 'REF - InstitutionType'!$B$4:$E$102, 3, FALSE), IF(EXACT(VLOOKUP($C77, 'REF - InstitutionType'!$B$4:$E$102, 3, FALSE), ""), "", " "), $B77, "", VLOOKUP($C77, 'REF - InstitutionType'!$B$4:$E$102, 4, FALSE), IF(EXACT($E77, ""), "", " [a.k.a : "&$E77&"]"))) -> CV. Anugerah Karya Magantha | F77: VDR3828 | G77: =IF(EXACT($F77, ""), "", VLOOKUP($F77, 'RAW EDITED 3 Years'!$A$2:$G$438, 5, FALSE)) -> Supplier | H77: =IF(EXACT($F77, ""), "", VLOOKUP($F77, 'RAW EDITED 3 Years'!$A$2:$G$438, 6, FALSE)) -> Tools Kerja | I77: =IF(EXACT($F77, ""), "", VLOOKUP($F77, 'RAW EDITED 3 Years'!$A$2:$G$438, 7, FALSE)) -> Pembelian APD di area Site | L77: Supplier | N77: =N76 + IF(EXACT(O77, ""), 0, 1) -> 123000000000074 | O77: =CONCATENATE("PERFORM ""SchData-OLTP-Master"".""Func_TblInstitution_SET""(varSystemLoginSession::bigint, null::bigint, null::varchar, null::timestamptz, null::timestamptz, null::varchar, varInstitutionBranchID::bigint, varBaseCurrencyID::bigint, '", B77, "'::varchar, ", IF(EXACT(C77, ""), "null", C77), "::bigint); ") -> PERFORM "SchData-OLTP-Master"."Func_TblInstitution_SET"(varSystemLoginSession::bigint, null::bigint, null::varchar, null::timestamptz, null::timestamptz, null::varchar, varInstitutionBranchID::bigint, varBaseCurrencyID::bigint, 'Anugerah Karya Magantha'::varchar, 141000000000002::bigint);
A78: =IF( COUNTIF( $D$4:$D$1000, $D78 ) = 1, "", "Duplicated") | B78: Artha Jaya Mulya | C78: 141000000000002 | D78: =IF(EXACT($C78, ""), B78, CONCATENATE(VLOOKUP($C78, 'REF - InstitutionType'!$B$4:$E$102, 3, FALSE), IF(EXACT(VLOOKUP($C78, 'REF - InstitutionType'!$B$4:$E$102, 3, FALSE), ""), "", " "), $B78, "", VLOOKUP($C78, 'REF - InstitutionType'!$B$4:$E$102, 4, FALSE), IF(EXACT($E78, ""), "", " [a.k.a : "&$E78&"]"))) -> CV. Artha Jaya Mulya | F78: VDR3970 | G78: =IF(EXACT($F78, ""), "", VLOOKUP($F78, 'RAW EDITED 3 Years'!$A$2:$G$438, 5, FALSE)) -> Supplier Material Civil | H78: =IF(EXACT($F78, ""), "", VLOOKUP($F78, 'RAW EDITED 3 Years'!$A$2:$G$438, 6, FALSE)) -> Tanah, Sirtu, Makadam | I78: =IF(EXACT($F78, ""), "", VLOOKUP($F78, 'RAW EDITED 3 Years'!$A$2:$G$438, 7, FALSE)) | L78: Supplier | N78: =N77 + IF(EXACT(O78, ""), 0, 1) -> 123000000000075 | O78: =CONCATENATE("PERFORM ""SchData-OLTP-Master"".""Func_TblInstitution_SET""(varSystemLoginSession::bigint, null::bigint, null::varchar, null::timestamptz, null::timestamptz, null::varchar, varInstitutionBranchID::bigint, varBaseCurrencyID::bigint, '", B78, "'::varchar, ", IF(EXACT(C78, ""), "null", C78), "::bigint); ") -> PERFORM "SchData-OLTP-Master"."Func_TblInstitution_SET"(varSystemLoginSession::bigint, null::bigint, null::varchar, null::timestamptz, null::timestamptz, null::varchar, varInstitutionBranchID::bigint, varBaseCurrencyID::bigint, 'Artha Jaya Mulya'::varchar, 141000000000002::bigint);
A79: =IF( COUNTIF( $D$4:$D$1000, $D79 ) = 1, "", "Duplicated") | B79: Borneo Geotec Engginering | C79: 141000000000002 | D79: =IF(EXACT($C79, ""), B79, CONCATENATE(VLOOKUP($C79, 'REF - InstitutionType'!$B$4:$E$102, 3, FALSE), IF(EXACT(VLOOKUP($C79, 'REF - InstitutionType'!$B$4:$E$102, 3, FALSE), ""), "", " "), $B79, "", VLOOKUP($C79, 'REF - InstitutionType'!$B$4:$E$102, 4, FALSE), IF(EXACT($E79, ""), "", " [a.k.a : "&$E79&"]"))) -> CV. Borneo Geotec Engginering | F79: VDR3939 | G79: =IF(EXACT($F79, ""), "", VLOOKUP($F79, 'RAW EDITED 3 Years'!$A$2:$G$438, 5, FALSE)) -> Soil Test | H79: =IF(EXACT($F79, ""), "", VLOOKUP($F79, 'RAW EDITED 3 Years'!$A$2:$G$438, 6, FALSE)) -> Soil Test | I79: =IF(EXACT($F79, ""), "", VLOOKUP($F79, 'RAW EDITED 3 Years'!$A$2:$G$438, 7, FALSE)) | L79: Supplier | N79: =N78 + IF(EXACT(O79, ""), 0, 1) -> 123000000000076 | O79: =CONCATENATE("PERFORM ""SchData-OLTP-Master"".""Func_TblInstitution_SET""(varSystemLoginSession::bigint, null::bigint, null::varchar, null::timestamptz, null::timestamptz, null::varchar, varInstitutionBranchID::bigint, varBaseCurrencyID::bigint, '", B79, "'::varchar, ", IF(EXACT(C79, ""), "null", C79), "::bigint); ") -> PERFORM "SchData-OLTP-Master"."Func_TblInstitution_SET"(varSystemLoginSession::bigint, null::bigint, null::varchar, null::timestamptz, null::timestamptz, null::varchar, varInstitutionBranchID::bigint, varBaseCurrencyID::bigint, 'Borneo Geotec Engginering'::varchar, 141000000000002::bigint);
A80: =IF( COUNTIF( $D$4:$D$1000, $D80 ) = 1, "", "Duplicated") | B80: Cipta Aneka Sarana | C80: 141000000000002 | D80: =IF(EXACT($C80, ""), B80, CONCATENATE(VLOOKUP($C80, 'REF - InstitutionType'!$B$4:$E$102, 3, FALSE), IF(EXACT(VLOOKUP($C80, 'REF - InstitutionType'!$B$4:$E$102, 3, FALSE), ""), "", " "), $B80, "", VLOOKUP($C80, 'REF - InstitutionType'!$B$4:$E$102, 4, FALSE), IF(EXACT($E80, ""), "", " [a.k.a : "&$E80&"]"))) -> CV. Cipta Aneka Sarana | F80: VDR3784 | G80: =IF(EXACT($F80, ""), "", VLOOKUP($F80, 'RAW EDITED 3 Years'!$A$2:$G$438, 5, FALSE)) -> Supplier | H80: =IF(EXACT($F80, ""), "", VLOOKUP($F80, 'RAW EDITED 3 Years'!$A$2:$G$438, 6, FALSE)) -> Bahan Bangunan | I80: =IF(EXACT($F80, ""), "", VLOOKUP($F80, 'RAW EDITED 3 Years'!$A$2:$G$438, 7, FALSE)) -> Untuk pembelian bahan Bangunan, tools , alat kerja project Kolaka | L80: Supplier | N80: =N79 + IF(EXACT(O80, ""), 0, 1) -> 123000000000077 | O80: =CONCATENATE("PERFORM ""SchData-OLTP-Master"".""Func_TblInstitution_SET""(varSystemLoginSession::bigint, null::bigint, null::varchar, null::timestamptz, null::timestamptz, null::varchar, varInstitutionBranchID::bigint, varBaseCurrencyID::bigint, '", B80, "'::varchar, ", IF(EXACT(C80, ""), "null", C80), "::bigint); ") -> PERFORM "SchData-OLTP-Master"."Func_TblInstitution_SET"(varSystemLoginSession::bigint, null::bigint, null::varchar, null::timestamptz, null::timestamptz, null::varchar, varInstitutionBranchID::bigint, varBaseCurrencyID::bigint, 'Cipta Aneka Sarana'::varchar, 141000000000002::bigint);
A81: =IF( COUNTIF( $D$4:$D$1000, $D81 ) = 1, "", "Duplicated") | B81: Didi Dan Darwis Survey | C81: 141000000000002 | D81: =IF(EXACT($C81, ""), B81, CONCATENATE(VLOOKUP($C81, 'REF - InstitutionType'!$B$4:$E$102, 3, FALSE), IF(EXACT(VLOOKUP($C81, 'REF - InstitutionType'!$B$4:$E$102, 3, FALSE), ""), "", " "), $B81, "", VLOOKUP($C81, 'REF - InstitutionType'!$B$4:$E$102, 4, FALSE), IF(EXACT($E81, ""), "", " [a.k.a : "&$E81&"]"))) -> CV. Didi Dan Darwis Survey | F81: VDR3696 | G81: =IF(EXACT($F81, ""), "", VLOOKUP($F81, 'RAW EDITED 3 Years'!$A$2:$G$438, 5, FALSE)) -> Supplier | H81: =IF(EXACT($F81, ""), "", VLOOKUP($F81, 'RAW EDITED 3 Years'!$A$2:$G$438, 6, FALSE)) -> Survey | I81: =IF(EXACT($F81, ""), "", VLOOKUP($F81, 'RAW EDITED 3 Years'!$A$2:$G$438, 7, FALSE)) -> Toko Alat2 surveyor dibandung | L81: Supplier | N81: =N80 + IF(EXACT(O81, ""), 0, 1) -> 123000000000078 | O81: =CONCATENATE("PERFORM ""SchData-OLTP-Master"".""Func_TblInstitution_SET""(varSystemLoginSession::bigint, null::bigint, null::varchar, null::timestamptz, null::timestamptz, null::varchar, varInstitutionBranchID::bigint, varBaseCurrencyID::bigint, '", B81, "'::varchar, ", IF(EXACT(C81, ""), "null", C81), "::bigint); ") -> PERFORM "SchData-OLTP-Master"."Func_TblInstitution_SET"(varSystemLoginSession::bigint, null::bigint, null::varchar, null::timestamptz, null::timestamptz, null::varchar, varInstitutionBranchID::bigint, varBaseCurrencyID::bigint, 'Didi Dan Darwis Survey '::varchar, 141000000000002::bigint);
A82: =IF( COUNTIF( $D$4:$D$1000, $D82 ) = 1, "", "Duplicated") | B82: Dinargeo Survey | C82: 141000000000002 | D82: =IF(EXACT($C82, ""), B82, CONCATENATE(VLOOKUP($C82, 'REF - InstitutionType'!$B$4:$E$102, 3, FALSE), IF(EXACT(VLOOKUP($C82, 'REF - InstitutionType'!$B$4:$E$102, 3, FALSE), ""), "", " "), $B82, "", VLOOKUP($C82, 'REF - InstitutionType'!$B$4:$E$102, 4, FALSE), IF(EXACT($E82, ""), "", " [a.k.a : "&$E82&"]"))) -> CV. Dinargeo Survey | F82: VDR4201 | G82: =IF(EXACT($F82, ""), "", VLOOKUP($F82, 'RAW EDITED 3 Years'!$A$2:$G$438, 5, FALSE)) -> Survey | H82: =IF(EXACT($F82, ""), "", VLOOKUP($F82, 'RAW EDITED 3 Years'!$A$2:$G$438, 6, FALSE)) -> Survey | I82: =IF(EXACT($F82, ""), "", VLOOKUP($F82, 'RAW EDITED 3 Years'!$A$2:$G$438, 7, FALSE)) -> Rental Alat Survey dan Pemetaan Jakarta | L82: Supplier | N82: =N81 + IF(EXACT(O82, ""), 0, 1) -> 123000000000079 | O82: =CONCATENATE("PERFORM ""SchData-OLTP-Master"".""Func_TblInstitution_SET""(varSystemLoginSession::bigint, null::bigint, null::varchar, null::timestamptz, null::timestamptz, null::varchar, varInstitutionBranchID::bigint, varBaseCurrencyID::bigint, '", B82, "'::varchar, ", IF(EXACT(C82, ""), "null", C82), "::bigint); ") -> PERFORM "SchData-OLTP-Master"."Func_TblInstitution_SET"(varSystemLoginSession::bigint, null::bigint, null::varchar, null::timestamptz, null::timestamptz, null::varchar, varInstitutionBranchID::bigint, varBaseCurrencyID::bigint, 'Dinargeo Survey'::varchar, 141000000000002::bigint);
A83: =IF( COUNTIF( $D$4:$D$1000, $D83 ) = 1, "", "Duplicated") | B83: Direct Linus Logistik | C83: 141000000000002 | D83: =IF(EXACT($C83, ""), B83, CONCATENATE(VLOOKUP($C83, 'REF - InstitutionType'!$B$4:$E$102, 3, FALSE), IF(EXACT(VLOOKUP($C83, 'REF - InstitutionType'!$B$4:$E$102, 3, FALSE), ""), "", " "), $B83, "", VLOOKUP($C83, 'REF - InstitutionType'!$B$4:$E$102, 4, FALSE), IF(EXACT($E83, ""), "", " [a.k.a : "&$E83&"]"))) -> CV. Direct Linus Logistik | F83: VDR3971 | G83: =IF(EXACT($F83, ""), "", VLOOKUP($F83, 'RAW EDITED 3 Years'!$A$2:$G$438, 5, FALSE)) -> Transportation | H83: =IF(EXACT($F83, ""), "", VLOOKUP($F83, 'RAW EDITED 3 Years'!$A$2:$G$438, 6, FALSE)) -> Trucking | I83: =IF(EXACT($F83, ""), "", VLOOKUP($F83, 'RAW EDITED 3 Years'!$A$2:$G$438, 7, FALSE)) -> Vendor Transportasi untuk ke Siak (CDD, Fuso, Tronton) | L83: Supplier | N83: =N82 + IF(EXACT(O83, ""), 0, 1) -> 123000000000080 | O83: =CONCATENATE("PERFORM ""SchData-OLTP-Master"".""Func_TblInstitution_SET""(varSystemLoginSession::bigint, null::bigint, null::varchar, null::timestamptz, null::timestamptz, null::varchar, varInstitutionBranchID::bigint, varBaseCurrencyID::bigint, '", B83, "'::varchar, ", IF(EXACT(C83, ""), "null", C83), "::bigint); ") -> PERFORM "SchData-OLTP-Master"."Func_TblInstitution_SET"(varSystemLoginSession::bigint, null::bigint, null::varchar, null::timestamptz, null::timestamptz, null::varchar, varInstitutionBranchID::bigint, varBaseCurrencyID::bigint, 'Direct Linus Logistik'::varchar, 141000000000002::bigint);
A84: =IF( COUNTIF( $D$4:$D$1000, $D84 ) = 1, "", "Duplicated") | B84: Edi Jaya Bangunan | C84: 141000000000002 | D84: =IF(EXACT($C84, ""), B84, CONCATENATE(VLOOKUP($C84, 'REF - InstitutionType'!$B$4:$E$102, 3, FALSE), IF(EXACT(VLOOKUP($C84, 'REF - InstitutionType'!$B$4:$E$102, 3, FALSE), ""), "", " "), $B84, "", VLOOKUP($C84, 'REF - InstitutionType'!$B$4:$E$102, 4, FALSE), IF(EXACT($E84, ""), "", " [a.k.a : "&$E84&"]"))) -> CV. Edi Jaya Bangunan | F84: VDR4046 | G84: =IF(EXACT($F84, ""), "", VLOOKUP($F84, 'RAW EDITED 3 Years'!$A$2:$G$438, 5, FALSE)) -> Supplier | H84: =IF(EXACT($F84, ""), "", VLOOKUP($F84, 'RAW EDITED 3 Years'!$A$2:$G$438, 6, FALSE)) -> Terpal plastik | I84: =IF(EXACT($F84, ""), "", VLOOKUP($F84, 'RAW EDITED 3 Years'!$A$2:$G$438, 7, FALSE)) -> Terpal | L84: Supplier | N84: =N83 + IF(EXACT(O84, ""), 0, 1) -> 123000000000081 | O84: =CONCATENATE("PERFORM ""SchData-OLTP-Master"".""Func_TblInstitution_SET""(varSystemLoginSession::bigint, null::bigint, null::varchar, null::timestamptz, null::timestamptz, null::varchar, varInstitutionBranchID::bigint, varBaseCurrencyID::bigint, '", B84, "'::varchar, ", IF(EXACT(C84, ""), "null", C84), "::bigint); ") -> PERFORM "SchData-OLTP-Master"."Func_TblInstitution_SET"(varSystemLoginSession::bigint, null::bigint, null::varchar, null::timestamptz, null::timestamptz, null::varchar, varInstitutionBranchID::bigint, varBaseCurrencyID::bigint, 'Edi Jaya Bangunan'::varchar, 141000000000002::bigint);
A85: =IF( COUNTIF( $D$4:$D$1000, $D85 ) = 1, "", "Duplicated") | B85: Elang Sega | C85: 141000000000002 | D85: =IF(EXACT($C85, ""), B85, CONCATENATE(VLOOKUP($C85, 'REF - InstitutionType'!$B$4:$E$102, 3, FALSE), IF(EXACT(VLOOKUP($C85, 'REF - InstitutionType'!$B$4:$E$102, 3, FALSE), ""), "", " "), $B85, "", VLOOKUP($C85, 'REF - InstitutionType'!$B$4:$E$102, 4, FALSE), IF(EXACT($E85, ""), "", " [a.k.a : "&$E85&"]"))) -> CV. Elang Sega | F85: VDR3982 | G85: =IF(EXACT($F85, ""), "", VLOOKUP($F85, 'RAW EDITED 3 Years'!$A$2:$G$438, 5, FALSE)) -> Supplier Material Civil | H85: =IF(EXACT($F85, ""), "", VLOOKUP($F85, 'RAW EDITED 3 Years'!$A$2:$G$438, 6, FALSE)) -> Tanah, Sirtu, Makadam | I85: =IF(EXACT($F85, ""), "", VLOOKUP($F85, 'RAW EDITED 3 Years'!$A$2:$G$438, 7, FALSE)) -> Supplier pasir beton untuk Pangkalan Bun CV. Elang Sega (Priyo Handoko) | L85: Supplier | N85: =N84 + IF(EXACT(O85, ""), 0, 1) -> 123000000000082 | O85: =CONCATENATE("PERFORM ""SchData-OLTP-Master"".""Func_TblInstitution_SET""(varSystemLoginSession::bigint, null::bigint, null::varchar, null::timestamptz, null::timestamptz, null::varchar, varInstitutionBranchID::bigint, varBaseCurrencyID::bigint, '", B85, "'::varchar, ", IF(EXACT(C85, ""), "null", C85), "::bigint); ") -> PERFORM "SchData-OLTP-Master"."Func_TblInstitution_SET"(varSystemLoginSession::bigint, null::bigint, null::varchar, null::timestamptz, null::timestamptz, null::varchar, varInstitutionBranchID::bigint, varBaseCurrencyID::bigint, 'Elang Sega'::varchar, 141000000000002::bigint);
A86: =IF( COUNTIF( $D$4:$D$1000, $D86 ) = 1, "", "Duplicated") | B86: Gallazka Teknik | C86: 141000000000002 | D86: =IF(EXACT($C86, ""), B86, CONCATENATE(VLOOKUP($C86, 'REF - InstitutionType'!$B$4:$E$102, 3, FALSE), IF(EXACT(VLOOKUP($C86, 'REF - InstitutionType'!$B$4:$E$102, 3, FALSE), ""), "", " "), $B86, "", VLOOKUP($C86, 'REF - InstitutionType'!$B$4:$E$102, 4, FALSE), IF(EXACT($E86, ""), "", " [a.k.a : "&$E86&"]"))) -> CV. Gallazka Teknik | F86: VDR3773 | G86: =IF(EXACT($F86, ""), "", VLOOKUP($F86, 'RAW EDITED 3 Years'!$A$2:$G$438, 5, FALSE)) -> Alat dan mesin teknik | H86: =IF(EXACT($F86, ""), "", VLOOKUP($F86, 'RAW EDITED 3 Years'!$A$2:$G$438, 6, FALSE)) -> Aneka Mesin Diesel, Dynamo & G | I86: =IF(EXACT($F86, ""), "", VLOOKUP($F86, 'RAW EDITED 3 Years'!$A$2:$G$438, 7, FALSE)) -> Untuk Perbaikan Mesin | L86: Supplier | N86: =N85 + IF(EXACT(O86, ""), 0, 1) -> 123000000000083 | O86: =CONCATENATE("PERFORM ""SchData-OLTP-Master"".""Func_TblInstitution_SET""(varSystemLoginSession::bigint, null::bigint, null::varchar, null::timestamptz, null::timestamptz, null::varchar, varInstitutionBranchID::bigint, varBaseCurrencyID::bigint, '", B86, "'::varchar, ", IF(EXACT(C86, ""), "null", C86), "::bigint); ") -> PERFORM "SchData-OLTP-Master"."Func_TblInstitution_SET"(varSystemLoginSession::bigint, null::bigint, null::varchar, null::timestamptz, null::timestamptz, null::varchar, varInstitutionBranchID::bigint, varBaseCurrencyID::bigint, 'Gallazka Teknik'::varchar, 141000000000002::bigint);
... A247: =IF( COUNTIF( $D$4:$D$1000, $D247 ) = 1, "", "Duplicated") | B247: ZTT Cable Indonesia | C247: 141000000000004 | D247: =IF(EXACT($C247, ""), B247, CONCATENATE(VLOOKUP($C247, 'REF - InstitutionType'!$B$4:$E$102, 3, FALSE), IF(EXACT(VLOOKUP($C247, 'REF - InstitutionType'!$B$4:$E$102, 3, FALSE), ""), "", " "), $B247, "", VLOOKUP($C247, 'REF - InstitutionType'!$B$4:$E$102, 4, FALSE), IF(EXACT($E247, ""), "", " [a.k.a : "&$E247&"]"))) -> PT. ZTT Cable Indonesia | F247: VDR2391 | G247: =IF(EXACT($F247, ""), "", VLOOKUP($F247, 'RAW EDITED 3 Years'!$A$2:$G$438, 5, FALSE)) -> Supplier Material ME | H247: =IF(EXACT($F247, ""), "", VLOOKUP($F247, 'RAW EDITED 3 Years'!$A$2:$G$438, 6, FALSE)) -> Material RF | I247: =IF(EXACT($F247, ""), "", VLOOKUP($F247, 'RAW EDITED 3 Years'!$A$2:$G$438, 7, FALSE)) -> Supplier Cable | L247: Supplier | N247: =N246 + IF(EXACT(O247, ""), 0, 1) -> 123000000000244 | O247: =CONCATENATE("PERFORM ""SchData-OLTP-Master"".""Func_TblInstitution_SET""(varSystemLoginSession::bigint, null::bigint, null::varchar, null::timestamptz, null::timestamptz, null::varchar, varInstitutionBranchID::bigint, varBaseCurrencyID::bigint, '", B247, "'::varchar, ", IF(EXACT(C247, ""), "null", C247), "::bigint); ") -> PERFORM "SchData-OLTP-Master"."Func_TblInstitution_SET"(varSystemLoginSession::bigint, null::bigint, null::varchar, null::timestamptz, null::timestamptz, null::varchar, varInstitutionBranchID::bigint, varBaseCurrencyID::bigint, 'ZTT Cable Indonesia '::varchar, 141000000000004::bigint);
A248: =IF( COUNTIF( $D$4:$D$1000, $D248 ) = 1, "", "Duplicated") | B248: KMI Wire and Cable | C248: 141000000000005 | D248: =IF(EXACT($C248, ""), B248, CONCATENATE(VLOOKUP($C248, 'REF - InstitutionType'!$B$4:$E$102, 3, FALSE), IF(EXACT(VLOOKUP($C248, 'REF - InstitutionType'!$B$4:$E$102, 3, FALSE), ""), "", " "), $B248, "", VLOOKUP($C248, 'REF - InstitutionType'!$B$4:$E$102, 4, FALSE), IF(EXACT($E248, ""), "", " [a.k.a : "&$E248&"]"))) -> PT. KMI Wire and Cable, Tbk [a.k.a : Kabel Metal Indonesia] | E248: Kabel Metal Indonesia | F248: VDR0383, VDR0384 | G248: =IF(EXACT($F248, ""), "", VLOOKUP($F248, 'RAW EDITED 3 Years'!$A$2:$G$438, 5, FALSE)) -> Supplier | H248: =IF(EXACT($F248, ""), "", VLOOKUP($F248, 'RAW EDITED 3 Years'!$A$2:$G$438, 6, FALSE)) -> Kabel | I248: =IF(EXACT($F248, ""), "", VLOOKUP($F248, 'RAW EDITED 3 Years'!$A$2:$G$438, 7, FALSE)) -> Pass Without Comment | L248: Supplier | N248: =N247 + IF(EXACT(O248, ""), 0, 1) -> 123000000000245 | O248: =CONCATENATE("PERFORM ""SchData-OLTP-Master"".""Func_TblInstitution_SET""(varSystemLoginSession::bigint, null::bigint, null::varchar, null::timestamptz, null::timestamptz, null::varchar, varInstitutionBranchID::bigint, varBaseCurrencyID::bigint, '", B248, "'::varchar, ", IF(EXACT(C248, ""), "null", C248), "::bigint); ") -> PERFORM "SchData-OLTP-Master"."Func_TblInstitution_SET"(varSystemLoginSession::bigint, null::bigint, null::varchar, null::timestamptz, null::timestamptz, null::varchar, varInstitutionBranchID::bigint, varBaseCurrencyID::bigint, 'KMI Wire and Cable'::varchar, 141000000000005::bigint);
A249: =IF( COUNTIF( $D$4:$D$1000, $D249 ) = 1, "", "Duplicated") | B249: Kokoh Inti Arebama | C249: 141000000000005 | D249: =IF(EXACT($C249, ""), B249, CONCATENATE(VLOOKUP($C249, 'REF - InstitutionType'!$B$4:$E$102, 3, FALSE), IF(EXACT(VLOOKUP($C249, 'REF - InstitutionType'!$B$4:$E$102, 3, FALSE), ""), "", " "), $B249, "", VLOOKUP($C249, 'REF - InstitutionType'!$B$4:$E$102, 4, FALSE), IF(EXACT($E249, ""), "", " [a.k.a : "&$E249&"]"))) -> PT. Kokoh Inti Arebama, Tbk | F249: VDR3351 | G249: =IF(EXACT($F249, ""), "", VLOOKUP($F249, 'RAW EDITED 3 Years'!$A$2:$G$438, 5, FALSE)) -> Supplier Material Civil | H249: =IF(EXACT($F249, ""), "", VLOOKUP($F249, 'RAW EDITED 3 Years'!$A$2:$G$438, 6, FALSE)) -> Beton Kontruksi | I249: =IF(EXACT($F249, ""), "", VLOOKUP($F249, 'RAW EDITED 3 Years'!$A$2:$G$438, 7, FALSE)) -> Supplier Beton konstruksi Jayamix (PT SCG) | L249: Supplier | N249: =N248 + IF(EXACT(O249, ""), 0, 1) -> 123000000000246 | O249: =CONCATENATE("PERFORM ""SchData-OLTP-Master"".""Func_TblInstitution_SET""(varSystemLoginSession::bigint, null::bigint, null::varchar, null::timestamptz, null::timestamptz, null::varchar, varInstitutionBranchID::bigint, varBaseCurrencyID::bigint, '", B249, "'::varchar, ", IF(EXACT(C249, ""), "null", C249), "::bigint); ") -> PERFORM "SchData-OLTP-Master"."Func_TblInstitution_SET"(varSystemLoginSession::bigint, null::bigint, null::varchar, null::timestamptz, null::timestamptz, null::varchar, varInstitutionBranchID::bigint, varBaseCurrencyID::bigint, 'Kokoh Inti Arebama'::varchar, 141000000000005::bigint);
A250: =IF( COUNTIF( $D$4:$D$1000, $D250 ) = 1, "", "Duplicated") | B250: Ketenagakerjaan | C250: 141000000000022 | D250: =IF(EXACT($C250, ""), B250, CONCATENATE(VLOOKUP($C250, 'REF - InstitutionType'!$B$4:$E$102, 3, FALSE), IF(EXACT(VLOOKUP($C250, 'REF - InstitutionType'!$B$4:$E$102, 3, FALSE), ""), "", " "), $B250, "", VLOOKUP($C250, 'REF - InstitutionType'!$B$4:$E$102, 4, FALSE), IF(EXACT($E250, ""), "", " [a.k.a : "&$E250&"]"))) -> BPJS Ketenagakerjaan | F250: VDR0736 | G250: =IF(EXACT($F250, ""), "", VLOOKUP($F250, 'RAW EDITED 3 Years'!$A$2:$G$438, 5, FALSE)) -> Mandor/Subcon | H250: =IF(EXACT($F250, ""), "", VLOOKUP($F250, 'RAW EDITED 3 Years'!$A$2:$G$438, 6, FALSE)) | I250: =IF(EXACT($F250, ""), "", VLOOKUP($F250, 'RAW EDITED 3 Years'!$A$2:$G$438, 7, FALSE)) -> Pass Without Comment | L250: Supplier | N250: =N249 + IF(EXACT(O250, ""), 0, 1) -> 123000000000247 | O250: =CONCATENATE("PERFORM ""SchData-OLTP-Master"".""Func_TblInstitution_SET""(varSystemLoginSession::bigint, null::bigint, null::varchar, null::timestamptz, null::timestamptz, null::varchar, varInstitutionBranchID::bigint, varBaseCurrencyID::bigint, '", B250, "'::varchar, ", IF(EXACT(C250, ""), "null", C250), "::bigint); ") -> PERFORM "SchData-OLTP-Master"."Func_TblInstitution_SET"(varSystemLoginSession::bigint, null::bigint, null::varchar, null::timestamptz, null::timestamptz, null::varchar, varInstitutionBranchID::bigint, varBaseCurrencyID::bigint, 'Ketenagakerjaan'::varchar, 141000000000022::bigint);
A251: =IF( COUNTIF( $D$4:$D$1000, $D251 ) = 1, "", "Duplicated") | B251: Kesehatan | C251: 141000000000022 | D251: =IF(EXACT($C251, ""), B251, CONCATENATE(VLOOKUP($C251, 'REF - InstitutionType'!$B$4:$E$102, 3, FALSE), IF(EXACT(VLOOKUP($C251, 'REF - InstitutionType'!$B$4:$E$102, 3, FALSE), ""), "", " "), $B251, "", VLOOKUP($C251, 'REF - InstitutionType'!$B$4:$E$102, 4, FALSE), IF(EXACT($E251, ""), "", " [a.k.a : "&$E251&"]"))) -> BPJS Kesehatan | F251: VDR1591 | G251: =IF(EXACT($F251, ""), "", VLOOKUP($F251, 'RAW EDITED 3 Years'!$A$2:$G$438, 5, FALSE)) -> Badan Pemerintah | H251: =IF(EXACT($F251, ""), "", VLOOKUP($F251, 'RAW EDITED 3 Years'!$A$2:$G$438, 6, FALSE)) -> Overhead | I251: =IF(EXACT($F251, ""), "", VLOOKUP($F251, 'RAW EDITED 3 Years'!$A$2:$G$438, 7, FALSE)) -> BPJS Kesehatan | L251: Supplier | N251: =N250 + IF(EXACT(O251, ""), 0, 1) -> 123000000000248 | O251: =CONCATENATE("PERFORM ""SchData-OLTP-Master"".""Func_TblInstitution_SET""(varSystemLoginSession::bigint, null::bigint, null::varchar, null::timestamptz, null::timestamptz, null::varchar, varInstitutionBranchID::bigint, varBaseCurrencyID::bigint, '", B251, "'::varchar, ", IF(EXACT(C251, ""), "null", C251), "::bigint); ") -> PERFORM "SchData-OLTP-Master"."Func_TblInstitution_SET"(varSystemLoginSession::bigint, null::bigint, null::varchar, null::timestamptz, null::timestamptz, null::varchar, varInstitutionBranchID::bigint, varBaseCurrencyID::bigint, 'Kesehatan'::varchar, 141000000000022::bigint);
A252: =IF( COUNTIF( $D$4:$D$1000, $D252 ) = 1, "", "Duplicated") | B252: Bank Rakyat Indonesia | C252: 141000000000007 | D252: =IF(EXACT($C252, ""), B252, CONCATENATE(VLOOKUP($C252, 'REF - InstitutionType'!$B$4:$E$102, 3, FALSE), IF(EXACT(VLOOKUP($C252, 'REF - InstitutionType'!$B$4:$E$102, 3, FALSE), ""), "", " "), $B252, "", VLOOKUP($C252, 'REF - InstitutionType'!$B$4:$E$102, 4, FALSE), IF(EXACT($E252, ""), "", " [a.k.a : "&$E252&"]"))) -> PT. Bank Rakyat Indonesia (Persero), Tbk | F252: VDR3944 | G252: =IF(EXACT($F252, ""), "", VLOOKUP($F252, 'RAW EDITED 3 Years'!$A$2:$G$438, 5, FALSE)) -> Badan Pemerintah | H252: =IF(EXACT($F252, ""), "", VLOOKUP($F252, 'RAW EDITED 3 Years'!$A$2:$G$438, 6, FALSE)) -> Bank Garansi | I252: =IF(EXACT($F252, ""), "", VLOOKUP($F252, 'RAW EDITED 3 Years'!$A$2:$G$438, 7, FALSE)) | L252: Supplier | N252: =N251 + IF(EXACT(O252, ""), 0, 1) -> 123000000000249 | O252: =CONCATENATE("PERFORM ""SchData-OLTP-Master"".""Func_TblInstitution_SET""(varSystemLoginSession::bigint, null::bigint, null::varchar, null::timestamptz, null::timestamptz, null::varchar, varInstitutionBranchID::bigint, varBaseCurrencyID::bigint, '", B252, "'::varchar, ", IF(EXACT(C252, ""), "null", C252), "::bigint); ") -> PERFORM "SchData-OLTP-Master"."Func_TblInstitution_SET"(varSystemLoginSession::bigint, null::bigint, null::varchar, null::timestamptz, null::timestamptz, null::varchar, varInstitutionBranchID::bigint, varBaseCurrencyID::bigint, 'Bank Rakyat Indonesia'::varchar, 141000000000007::bigint);
A253: =IF( COUNTIF( $D$4:$D$1000, $D253 ) = 1, "", "Duplicated") | B253: Mekar | C253: 141000000000012 | D253: =IF(EXACT($C253, ""), B253, CONCATENATE(VLOOKUP($C253, 'REF - InstitutionType'!$B$4:$E$102, 3, FALSE), IF(EXACT(VLOOKUP($C253, 'REF - InstitutionType'!$B$4:$E$102, 3, FALSE), ""), "", " "), $B253, "", VLOOKUP($C253, 'REF - InstitutionType'!$B$4:$E$102, 4, FALSE), IF(EXACT($E253, ""), "", " [a.k.a : "&$E253&"]"))) -> Koperasi Mekar | F253: VDR2588 | G253: =IF(EXACT($F253, ""), "", VLOOKUP($F253, 'RAW EDITED 3 Years'!$A$2:$G$438, 5, FALSE)) -> Supplier | H253: =IF(EXACT($F253, ""), "", VLOOKUP($F253, 'RAW EDITED 3 Years'!$A$2:$G$438, 6, FALSE)) -> Building Management | I253: =IF(EXACT($F253, ""), "", VLOOKUP($F253, 'RAW EDITED 3 Years'!$A$2:$G$438, 7, FALSE)) -> APAR | L253: Supplier | N253: =N252 + IF(EXACT(O253, ""), 0, 1) -> 123000000000250 | O253: =CONCATENATE("PERFORM ""SchData-OLTP-Master"".""Func_TblInstitution_SET""(varSystemLoginSession::bigint, null::bigint, null::varchar, null::timestamptz, null::timestamptz, null::varchar, varInstitutionBranchID::bigint, varBaseCurrencyID::bigint, '", B253, "'::varchar, ", IF(EXACT(C253, ""), "null", C253), "::bigint); ") -> PERFORM "SchData-OLTP-Master"."Func_TblInstitution_SET"(varSystemLoginSession::bigint, null::bigint, null::varchar, null::timestamptz, null::timestamptz, null::varchar, varInstitutionBranchID::bigint, varBaseCurrencyID::bigint, 'Mekar'::varchar, 141000000000012::bigint);
A254: =IF( COUNTIF( $D$4:$D$1000, $D254 ) = 1, "", "Duplicated") | B254: Athar Marzuki Plywood | C254: 141000000000015 | D254: =IF(EXACT($C254, ""), B254, CONCATENATE(VLOOKUP($C254, 'REF - InstitutionType'!$B$4:$E$102, 3, FALSE), IF(EXACT(VLOOKUP($C254, 'REF - InstitutionType'!$B$4:$E$102, 3, FALSE), ""), "", " "), $B254, "", VLOOKUP($C254, 'REF - InstitutionType'!$B$4:$E$102, 4, FALSE), IF(EXACT($E254, ""), "", " [a.k.a : "&$E254&"]"))) -> UD. Athar Marzuki Plywood | F254: VDR4113 | G254: =IF(EXACT($F254, ""), "", VLOOKUP($F254, 'RAW EDITED 3 Years'!$A$2:$G$438, 5, FALSE)) -> Supplier Others | H254: =IF(EXACT($F254, ""), "", VLOOKUP($F254, 'RAW EDITED 3 Years'!$A$2:$G$438, 6, FALSE)) -> Bahan Bangunan | I254: =IF(EXACT($F254, ""), "", VLOOKUP($F254, 'RAW EDITED 3 Years'!$A$2:$G$438, 7, FALSE)) -> triplek | L254: Supplier | N254: =N253 + IF(EXACT(O254, ""), 0, 1) -> 123000000000251 | O254: =CONCATENATE("PERFORM ""SchData-OLTP-Master"".""Func_TblInstitution_SET""(varSystemLoginSession::bigint, null::bigint, null::varchar, null::timestamptz, null::timestamptz, null::varchar, varInstitutionBranchID::bigint, varBaseCurrencyID::bigint, '", B254, "'::varchar, ", IF(EXACT(C254, ""), "null", C254), "::bigint); ") -> PERFORM "SchData-OLTP-Master"."Func_TblInstitution_SET"(varSystemLoginSession::bigint, null::bigint, null::varchar, null::timestamptz, null::timestamptz, null::varchar, varInstitutionBranchID::bigint, varBaseCurrencyID::bigint, 'Athar Marzuki Plywood'::varchar, 141000000000015::bigint);
A255: =IF( COUNTIF( $D$4:$D$1000, $D255 ) = 1, "", "Duplicated") | B255: Gajah Mungkur | C255: 141000000000015 | D255: =IF(EXACT($C255, ""), B255, CONCATENATE(VLOOKUP($C255, 'REF - InstitutionType'!$B$4:$E$102, 3, FALSE), IF(EXACT(VLOOKUP($C255, 'REF - InstitutionType'!$B$4:$E$102, 3, FALSE), ""), "", " "), $B255, "", VLOOKUP($C255, 'REF - InstitutionType'!$B$4:$E$102, 4, FALSE), IF(EXACT($E255, ""), "", " [a.k.a : "&$E255&"]"))) -> UD. Gajah Mungkur | F255: VDR3984 | G255: =IF(EXACT($F255, ""), "", VLOOKUP($F255, 'RAW EDITED 3 Years'!$A$2:$G$438, 5, FALSE)) -> Toko Bangunan | H255: =IF(EXACT($F255, ""), "", VLOOKUP($F255, 'RAW EDITED 3 Years'!$A$2:$G$438, 6, FALSE)) -> Bahan Bangunan | I255: =IF(EXACT($F255, ""), "", VLOOKUP($F255, 'RAW EDITED 3 Years'!$A$2:$G$438, 7, FALSE)) -> Paku, Seng, Palu, Gergaji, Triple dll | L255: Supplier | N255: =N254 + IF(EXACT(O255, ""), 0, 1) -> 123000000000252 | O255: =CONCATENATE("PERFORM ""SchData-OLTP-Master"".""Func_TblInstitution_SET""(varSystemLoginSession::bigint, null::bigint, null::varchar, null::timestamptz, null::timestamptz, null::varchar, varInstitutionBranchID::bigint, varBaseCurrencyID::bigint, '", B255, "'::varchar, ", IF(EXACT(C255, ""), "null", C255), "::bigint); ") -> PERFORM "SchData-OLTP-Master"."Func_TblInstitution_SET"(varSystemLoginSession::bigint, null::bigint, null::varchar, null::timestamptz, null::timestamptz, null::varchar, varInstitutionBranchID::bigint, varBaseCurrencyID::bigint, 'Gajah Mungkur'::varchar, 141000000000015::bigint);
A256: =IF( COUNTIF( $D$4:$D$1000, $D256 ) = 1, "", "Duplicated") | B256: Kalam Hidup kendari | C256: 141000000000015 | D256: =IF(EXACT($C256, ""), B256, CONCATENATE(VLOOKUP($C256, 'REF - InstitutionType'!$B$4:$E$102, 3, FALSE), IF(EXACT(VLOOKUP($C256, 'REF - InstitutionType'!$B$4:$E$102, 3, FALSE), ""), "", " "), $B256, "", VLOOKUP($C256, 'REF - InstitutionType'!$B$4:$E$102, 4, FALSE), IF(EXACT($E256, ""), "", " [a.k.a : "&$E256&"]"))) -> UD. Kalam Hidup kendari | F256: VDR3798 | G256: =IF(EXACT($F256, ""), "", VLOOKUP($F256, 'RAW EDITED 3 Years'!$A$2:$G$438, 5, FALSE)) -> Supplier Others | H256: =IF(EXACT($F256, ""), "", VLOOKUP($F256, 'RAW EDITED 3 Years'!$A$2:$G$438, 6, FALSE)) -> ATK Stationary | I256: =IF(EXACT($F256, ""), "", VLOOKUP($F256, 'RAW EDITED 3 Years'!$A$2:$G$438, 7, FALSE)) -> Pembelian ATK Lokal | L256: Supplier | N256: =N255 + IF(EXACT(O256, ""), 0, 1) -> 123000000000253 | O256: =CONCATENATE("PERFORM ""SchData-OLTP-Master"".""Func_TblInstitution_SET""(varSystemLoginSession::bigint, null::bigint, null::varchar, null::timestamptz, null::timestamptz, null::varchar, varInstitutionBranchID::bigint, varBaseCurrencyID::bigint, '", B256, "'::varchar, ", IF(EXACT(C256, ""), "null", C256), "::bigint); ") -> PERFORM "SchData-OLTP-Master"."Func_TblInstitution_SET"(varSystemLoginSession::bigint, null::bigint, null::varchar, null::timestamptz, null::timestamptz, null::varchar, varInstitutionBranchID::bigint, varBaseCurrencyID::bigint, 'Kalam Hidup kendari'::varchar, 141000000000015::bigint);
A257: =IF( COUNTIF( $D$4:$D$1000, $D257 ) = 1, "", "Duplicated") | B257: Mandiri Jaya | C257: 141000000000015 | D257: =IF(EXACT($C257, ""), B257, CONCATENATE(VLOOKUP($C257, 'REF - InstitutionType'!$B$4:$E$102, 3, FALSE), IF(EXACT(VLOOKUP($C257, 'REF - InstitutionType'!$B$4:$E$102, 3, FALSE), ""), "", " "), $B257, "", VLOOKUP($C257, 'REF - InstitutionType'!$B$4:$E$102, 4, FALSE), IF(EXACT($E257, ""), "", " [a.k.a : "&$E257&"]"))) -> UD. Mandiri Jaya | F257: VDR3527 | G257: =IF(EXACT($F257, ""), "", VLOOKUP($F257, 'RAW EDITED 3 Years'!$A$2:$G$438, 5, FALSE)) -> Supplier Others | H257: =IF(EXACT($F257, ""), "", VLOOKUP($F257, 'RAW EDITED 3 Years'!$A$2:$G$438, 6, FALSE)) -> Karung Plastik | I257: =IF(EXACT($F257, ""), "", VLOOKUP($F257, 'RAW EDITED 3 Years'!$A$2:$G$438, 7, FALSE)) | L257: Supplier | N257: =N256 + IF(EXACT(O257, ""), 0, 1) -> 123000000000254 | O257: =CONCATENATE("PERFORM ""SchData-OLTP-Master"".""Func_TblInstitution_SET""(varSystemLoginSession::bigint, null::bigint, null::varchar, null::timestamptz, null::timestamptz, null::varchar, varInstitutionBranchID::bigint, varBaseCurrencyID::bigint, '", B257, "'::varchar, ", IF(EXACT(C257, ""), "null", C257), "::bigint); ") -> PERFORM "SchData-OLTP-Master"."Func_TblInstitution_SET"(varSystemLoginSession::bigint, null::bigint, null::varchar, null::timestamptz, null::timestamptz, null::varchar, varInstitutionBranchID::bigint, varBaseCurrencyID::bigint, 'Mandiri Jaya'::varchar, 141000000000015::bigint);
A258: =IF( COUNTIF( $D$4:$D$1000, $D258 ) = 1, "", "Duplicated") | B258: Subur | C258: 141000000000015 | D258: =IF(EXACT($C258, ""), B258, CONCATENATE(VLOOKUP($C258, 'REF - InstitutionType'!$B$4:$E$102, 3, FALSE), IF(EXACT(VLOOKUP($C258, 'REF - InstitutionType'!$B$4:$E$102, 3, FALSE), ""), "", " "), $B258, "", VLOOKUP($C258, 'REF - InstitutionType'!$B$4:$E$102, 4, FALSE), IF(EXACT($E258, ""), "", " [a.k.a : "&$E258&"]"))) -> UD. Subur | F258: VDR4062 | G258: =IF(EXACT($F258, ""), "", VLOOKUP($F258, 'RAW EDITED 3 Years'!$A$2:$G$438, 5, FALSE)) -> Supplier | H258: =IF(EXACT($F258, ""), "", VLOOKUP($F258, 'RAW EDITED 3 Years'!$A$2:$G$438, 6, FALSE)) -> Bahan Bangunan | I258: =IF(EXACT($F258, ""), "", VLOOKUP($F258, 'RAW EDITED 3 Years'!$A$2:$G$438, 7, FALSE)) -> Kayu Kaso | L258: Supplier | N258: =N257 + IF(EXACT(O258, ""), 0, 1) -> 123000000000255 | O258: =CONCATENATE("PERFORM ""SchData-OLTP-Master"".""Func_TblInstitution_SET""(varSystemLoginSession::bigint, null::bigint, null::varchar, null::timestamptz, null::timestamptz, null::varchar, varInstitutionBranchID::bigint, varBaseCurrencyID::bigint, '", B258, "'::varchar, ", IF(EXACT(C258, ""), "null", C258), "::bigint); ") -> PERFORM "SchData-OLTP-Master"."Func_TblInstitution_SET"(varSystemLoginSession::bigint, null::bigint, null::varchar, null::timestamptz, null::timestamptz, null::varchar, varInstitutionBranchID::bigint, varBaseCurrencyID::bigint, 'Subur'::varchar, 141000000000015::bigint);
A259: =IF( COUNTIF( $D$4:$D$1000, $D259 ) = 1, "", "Duplicated") | B259: Thufail | C259: 141000000000015 | D259: =IF(EXACT($C259, ""), B259, CONCATENATE(VLOOKUP($C259, 'REF - InstitutionType'!$B$4:$E$102, 3, FALSE), IF(EXACT(VLOOKUP($C259, 'REF - InstitutionType'!$B$4:$E$102, 3, FALSE), ""), "", " "), $B259, "", VLOOKUP($C259, 'REF - InstitutionType'!$B$4:$E$102, 4, FALSE), IF(EXACT($E259, ""), "", " [a.k.a : "&$E259&"]"))) -> UD. Thufail | F259: VDR3880 | G259: =IF(EXACT($F259, ""), "", VLOOKUP($F259, 'RAW EDITED 3 Years'!$A$2:$G$438, 5, FALSE)) -> Supplier Material Civil | H259: =IF(EXACT($F259, ""), "", VLOOKUP($F259, 'RAW EDITED 3 Years'!$A$2:$G$438, 6, FALSE)) -> Bahan Bangunan | I259: =IF(EXACT($F259, ""), "", VLOOKUP($F259, 'RAW EDITED 3 Years'!$A$2:$G$438, 7, FALSE)) | L259: Supplier | N259: =N258 + IF(EXACT(O259, ""), 0, 1) -> 123000000000256 | O259: =CONCATENATE("PERFORM ""SchData-OLTP-Master"".""Func_TblInstitution_SET""(varSystemLoginSession::bigint, null::bigint, null::varchar, null::timestamptz, null::timestamptz, null::varchar, varInstitutionBranchID::bigint, varBaseCurrencyID::bigint, '", B259, "'::varchar, ", IF(EXACT(C259, ""), "null", C259), "::bigint); ") -> PERFORM "SchData-OLTP-Master"."Func_TblInstitution_SET"(varSystemLoginSession::bigint, null::bigint, null::varchar, null::timestamptz, null::timestamptz, null::varchar, varInstitutionBranchID::bigint, varBaseCurrencyID::bigint, 'Thufail'::varchar, 141000000000015::bigint);
A260: =IF( COUNTIF( $D$4:$D$1000, $D260 ) = 1, "", "Duplicated") | B260: Asep Saprudin | C260: 141000000000019 | D260: =IF(EXACT($C260, ""), B260, CONCATENATE(VLOOKUP($C260, 'REF - InstitutionType'!$B$4:$E$102, 3, FALSE), IF(EXACT(VLOOKUP($C260, 'REF - InstitutionType'!$B$4:$E$102, 3, FALSE), ""), "", " "), $B260, "", VLOOKUP($C260, 'REF - InstitutionType'!$B$4:$E$102, 4, FALSE), IF(EXACT($E260, ""), "", " [a.k.a : "&$E260&"]"))) -> TB. Asep Saprudin | F260: VDR4145 | G260: =IF(EXACT($F260, ""), "", VLOOKUP($F260, 'RAW EDITED 3 Years'!$A$2:$G$438, 5, FALSE)) -> Toko Bangunan | H260: =IF(EXACT($F260, ""), "", VLOOKUP($F260, 'RAW EDITED 3 Years'!$A$2:$G$438, 6, FALSE)) -> Bahan Bangunan | I260: =IF(EXACT($F260, ""), "", VLOOKUP($F260, 'RAW EDITED 3 Years'!$A$2:$G$438, 7, FALSE)) -> Tb dan Supplier Jatiluhur | L260: Supplier | N260: =N259 + IF(EXACT(O260, ""), 0, 1) -> 123000000000257 | O260: =CONCATENATE("PERFORM ""SchData-OLTP-Master"".""Func_TblInstitution_SET""(varSystemLoginSession::bigint, null::bigint, null::varchar, null::timestamptz, null::timestamptz, null::varchar, varInstitutionBranchID::bigint, varBaseCurrencyID::bigint, '", B260, "'::varchar, ", IF(EXACT(C260, ""), "null", C260), "::bigint); ") -> PERFORM "SchData-OLTP-Master"."Func_TblInstitution_SET"(varSystemLoginSession::bigint, null::bigint, null::varchar, null::timestamptz, null::timestamptz, null::varchar, varInstitutionBranchID::bigint, varBaseCurrencyID::bigint, 'Asep Saprudin'::varchar, 141000000000019::bigint);
... A498: =IF( COUNTIF( $D$4:$D$1000, $D498 ) = 1, "", "Duplicated") | B498: Wilda Trans | C498: 141000000000001 | D498: =IF(EXACT($C498, ""), B498, CONCATENATE(VLOOKUP($C498, 'REF - InstitutionType'!$B$4:$E$102, 3, FALSE), IF(EXACT(VLOOKUP($C498, 'REF - InstitutionType'!$B$4:$E$102, 3, FALSE), ""), "", " "), $B498, "", VLOOKUP($C498, 'REF - InstitutionType'!$B$4:$E$102, 4, FALSE), IF(EXACT($E498, ""), "", " [a.k.a : "&$E498&"]"))) -> Wilda Trans | F498: VDR3841 | G498: =IF(EXACT($F498, ""), "", VLOOKUP($F498, 'RAW EDITED 3 Years'!$A$2:$G$438, 5, FALSE)) -> Transportation | H498: =IF(EXACT($F498, ""), "", VLOOKUP($F498, 'RAW EDITED 3 Years'!$A$2:$G$438, 6, FALSE)) -> Trucking | I498: =IF(EXACT($F498, ""), "", VLOOKUP($F498, 'RAW EDITED 3 Years'!$A$2:$G$438, 7, FALSE)) -> Pengiriman Material Makassar Wolo | L498: Supplier | N498: =N497 + IF(EXACT(O498, ""), 0, 1) -> 123000000000495 | O498: =CONCATENATE("PERFORM ""SchData-OLTP-Master"".""Func_TblInstitution_SET""(varSystemLoginSession::bigint, null::bigint, null::varchar, null::timestamptz, null::timestamptz, null::varchar, varInstitutionBranchID::bigint, varBaseCurrencyID::bigint, '", B498, "'::varchar, ", IF(EXACT(C498, ""), "null", C498), "::bigint); ") -> PERFORM "SchData-OLTP-Master"."Func_TblInstitution_SET"(varSystemLoginSession::bigint, null::bigint, null::varchar, null::timestamptz, null::timestamptz, null::varchar, varInstitutionBranchID::bigint, varBaseCurrencyID::bigint, 'Wilda Trans'::varchar, 141000000000001::bigint);
...

Sheet RAW EDITED All Years
A1: sup_kode | B1: statussupplier | C1: sup_nama | D1: alamat | E1: jenisupplier | F1: subjenisupplier | G1: ket | H1: tlp | I1: email | J1: fax
A2: VDR0704 | B2: Other | C2: Dewan Pimpinan Pusat Serikat PT PLN | D2: Jl.Trinojoyo Blok M1/135 kebayoran baru jakarta se | E2: Supplier Others | G2: Pass Without Comment | H2: 021-7261122/7262234 | L2: Partisipasi Iklan | N2: Jakarta Selatan | P2: Indonesia | Q2: Frita | T2: Bank Mandiri Cabang Utama Roxy Mas Jakarta Pusat | U2: 117.00000.65086 | V2: PT Bagassindo Media Persada | Z2: National | AC2: Y
A3: VDR1410 | B3: Other | C3: Koperasi Pegawai PLN Pusat | D3: Jakarta Pusat | E3: Badan Pemerintah | F3: General | H3: 0 | J3: 0 | N3: KOTA JAKARTA PUSAT | O3: DKI JAKARTA | P3: Indonesia | Q3: 0 | R3: 0 | S3: 0 | T3: Mandiri | U3: 1260004878756 | V3: Koperasi Pegawai PLN Pusat | Z3: National | AC3: Y | AE3: N | AF3: 0000-00-00
A4: VDR1456 | B4: PT | C4: Abadi Gondola Perkasa | D4: Jl. Raya Duri Kosambi No.135 RT06/01, Kel. Duri Kosambi, Jakarta Barat | E4: Supplier Others | F4: Overhead | G4: Penyewaan Gondola | H4: 021 70080222 | I4: abadigondola@yahoo.com | J4: 021 5410448 | K4: abadigondola@yahoo.com | N4: KOTA JAKARTA BARAT | O4: DKI JAKARTA | P4: Indonesia | Q4: Mr. Yuliono | R4: N/A | S4: Mr. Yuliono | T4: BCA | U4: 5490638689 | V4: Shanty Liman | Z4: National | AC4: Y | AE4: N | AF4: 0000-00-00
A5: VDR4134 | B5: PT | C5: Abadi Rajawali Semesta | D5: Jl Pajajaran 04/03 Bambu Apus, Pamulang | E5: Mandor/Subcon | F5: Konsultan | G5: IT Konsultan, Analis Digital Banking & EBITDA digital solution | H5: 81289956068 | I5: office@ptasrs.id | J5: - | K5: office@ptasrs.id | N5: KOTA TANGERANG SELATAN | O5: BANTEN | P5: Indonesia | Q5: Shira | R5: - | S5: Muhammad Badi Akmal | T5: CIMB Niaga | U5: 800166024100 | V5: PT Abadi Rajawali Semesta | W5: - | X5: - | Z5: National | AC5: Y | AD5: 25801747216000 | AE5: t | AF5: 0000-00-00
A6: VDR2113 | B6: PT | C6: ABC POWER | D6: Rukan sedayu square Blok M No. 19 RT 006 RW 012 . Jl Kamal Raya Lingkar Luar Kel. Cengkareng Barat Kec. Cengkareng Jakarta Barat 11730 | E6: Rental | F6: Tools | H6: 021 22557715 / 22552536 | I6: sales@abcpowergenset.com | J6: 021 5596 1204 | K6: sales@abcpowergenset.com | M6: Rukan sedayu square Blok M No. 19 RT 006 RW 012 . | N6: KOTA JAKARTA BARAT | O6: DKI JAKARTA | P6: Indonesia | Q6: 0 | R6: 0 | S6: 0 | T6: 0 | U6: 0 | V6: 0 | W6: 0 | X6: 0 | Y6: 0 | Z6: National | AA6: 0 | AB6: 0 | AC6: Y | AE6: N | AF6: 0000-00-00
A7: VDR0152 | B7: PT | C7: Abdi Electra | D7: Jl. Bakti Karang No 72 Kupang | E7: "" | G7: Pass Without Comment | H7: 0380 825 004 | J7: 0380 832 974 | N7: Kupang | P7: Indonesia | Q7: Bp. Frans Tasuab | T7: "" | U7: "" | V7: "" | AC7: Y
A8: VDR0862 | B8: PT | C8: ACE Hardware Indonesia | D8: Pasaraya Grande Lt. B2 Jl. Iskandarsyah II No.2 Bl | E8: Supplier Material Civil | G8: Pass Without Comment | H8: 722 7635-36 | I8: www.acehardware.co.id | J8: 725 1009 | K8: www.acehardware.co.id | L8: URGENT | N8: Jakarta Selatan | P8: Indonesia | Q8: Direct Sales | T8: Cash Only | U8: Cash Only | V8: Cash Only | W8: TBA | X8: TBA | Y8: TBA | Z8: National | AA8: TBA | AB8: TBA | AC8: Y
A9: VDR2667 | B9: PT | C9: Acommerce Jaya Abadi | D9: Jl.Raya Bekasi KM 28 (Jl.Wahab Af fan ) Medan satria,Bekasi | E9: Supplier | F9: Building Management | G9: TV | H9: 0 | N9: KOTA BEKASI | O9: JAWA BARAT | P9: Indonesia | Q9: 0 | R9: 0 | S9: 0 | T9: 0 | U9: 0 | V9: 0 | Z9: National | AC9: Y | AE9: f | AF9: 0000-00-00
A10: VDR3162 | B10: PT | C10: Adhi Gana Nusantara | D10: APL Tower 26th Floor unit T3-5 | E10: Supplier | F10: Besi Beton | H10: +62 821-2269-0281 | N10: KOTA JAKARTA BARAT | O10: DKI JAKARTA | P10: Indonesia | Q10: Efsa | R10: 0 | S10: 0 | T10: Mandiri | U10: 1230000022212 | V10: Adhi Gana Nusantara | Z10: National | AC10: Y | AD10: 943716100036000 | AE10: t | AF10: 0000-00-00
A11: VDR4157 | B11: PT | C11: Adhimix PCI Indonesia | D11: LAvenue Office Tower Lt. 16, Jl Guru Amin Kav. 16, Pancoran | E11: Pabrik | F11: Tiang | G11: Pabrik Tiang Pancang dan material precast lainnya (saluran, spun pile dll) | H11: 021 7994666 | I11: cs@adhimixpci.co.id | J11: 021 799 1666 | K11: cs@adhimixpci.co.id | N11: KOTA JAKARTA SELATAN | O11: DKI JAKARTA | P11: Indonesia | Q11: Rina | R11: Haryono | S11: Elvi Fadilah | T11: BCA | U11: 5230777782 | V11: PT Adhimix PCI Indonesia | W11: - | X11: - | Z11: National | AC11: Y | AD11: 84.046.376.4-061.000 | AE11: t | AF11: 0000-00-00
A12: VDR2363 | B12: PT | C12: Adhimix RMC Indonesia | D12: Gedung Graha Anugerah Lt 4, Jl. Raya Pasar Minggu No. 17 A Pancoran Jakarta 12780 | E12: Supplier Material Civil | F12: Bahan Bangunan | G12: Supplier Beton Ready Mix | H12: 0812 1037 9711 | I12: 0 | J12: 0 | K12: 0 | M12: Gedung Graha Anugerah Lt 4, Jl. Raya Pasar Minggu | N12: KOTA JAKARTA SELATAN | O12: DKI JAKARTA | P12: Indonesia | Q12: Pak Moch Ilham Fajar | R12: 0 | S12: 0 | T12: 0 | U12: 0 | V12: 0 | W12: 0 | X12: 0 | Y12: 0 | Z12: National | AA12: 0 | AB12: 0 | AC12: Y | AE12: N | AF12: 0000-00-00
A13: VDR4031 | B13: PT | C13: Adici Crane Pratama | D13: Jalan Seroja No. 25, Kel. Tobekgodang, Kec. Binawidya, Kota Pekanbaru, Riau | E13: Rental | F13: Alat Berat | G13: Penyewaan Truck Crane / MB Telescopic Boom (Tronton) | H13: 08127511245 / +62 812-7511-245 | N13: KOTA PEKANBARU | O13: RIAU | P13: Indonesia | Q13: Eci | R13: - | S13: - | T13: Bank BNI | U13: 21-4646-46-22 | V13: PT Adici Crane Pratama | Z13: National | AC13: Y | AE13: f | AF13: 0000-00-00
A14: VDR1703 | B14: PT | C14: Adimitra Karunia | D14: Perak Timur 564 B1 RT 002 RW 003 Perak Utara Pabean Cantian Surabaya | E14: Transportation | F14: Trucking | H14: 031 3282356 | I14: adikarunia121601@gmail.com | J14: 031 3282361 | K14: adikarunia121601@gmail.com | N14: KOTA SURABAYA | O14: JAWA TIMUR | P14: Indonesia | Q14: Aristyawan Soehartojo | R14: 0 | S14: 0 | T14: BCA Cabang Indrapura | U14: 468.222.8800 | V14: PT. Adimitra Karunia | Z14: National | AC14: Y | AE14: N | AF14: 0000-00-00
A15: VDR3124 | B15: PT | C15: Adinaga Distribution Jakarta | D15: Rukan Sedayu Square No 19 | E15: Supplier | F15: Alat, Mesin dan suku cadang | G15: Water treatment ,service&, suku cadang | H15: +62 813-8186-7799 | N15: KOTA JAKARTA BARAT | O15: DKI JAKARTA | P15: Indonesia | Q15: Desi | R15: 0 | S15: 0 | T15: BCA | U15: 5310767770 | V15: Adinaga Distribution Jakarta | Z15: National | AC15: Y | AD15: 75.544.412.2.044.000 | AE15: t | AF15: 0000-00-00
A16: VDR1109 | B16: PT | C16: Advancednet Indonesia | D16: Komplek Prima Centre I Blok A9 Jl Pool PPD Pesing Poglar No 11, jakarta Barat | E16: Distributor | F16: Material OSP | G16: Pass Without Comment | H16: 021 - 5437 6802 | I16: hisar@advancednet.com.my | J16: 021 - 5436 7377 | K16: hisar@advancednet.com.my | L16: Material OTB & Joint Clousure | N16: DKI Jakarta | O16: DKI Jakarta | P16: Indonesia | Q16: Bp Hizar | R16: Lusi Ana Wati | S16: Antonie | T16: Bank BCA, Jembatan Lima | U16: 1053009186 | V16: PT. ADVANCEDNET INDONESIA | W16: 4 Tahun | X16: 2008 | Y16: 8 Cabang | Z16: National | AA16: - | AB16: - | AC16: Y | AD16: 21.030.113.1-026.000 | AE16: Y | AF16: 1970-01-01
A17: VDR0134 | B17: PT | C17: Adyawansa Dinamika | D17: Gunung Sahari aya no. 2 | E17: "" | G17: Pass Without Comment | H17: 021-6454950 | N17: Jakarta | P17: Indonesia | T17: "" | U17: "" | V17: "" | AC17: Y
A18: VDR0189 | B18: PT | C18: Aegisindo Mitra Sejati | D18: Jl. Deltamas Boulevard Ruko Porto Square Blok D No. 1 Kota Deltamas, Kel. Hegarmukti Kec. Cikarang Pusat Kab. Bekasi - Jawa Barat | E18: Supplier | F18: K3 Equipment | G18: APD Seperti Sepatu safety, rompi, helm, kacamata. Authorized Dealer Safety Boot merk LEGION TERASTEEL | H18: 02189976688 / +62 822-9988-8008 | N18: Bekasi | O18: Jawa Barat | P18: Indonesia | Q18: Admin | R18: - | S18: - | T18: Bank BCA | U18: 703 58 88 88 8 | V18: Aegisindo Mitra Sejati PT | AC18: Y | AE18: f | AF18: 0000-00-00
A19: VDR0001 | B19: PT. | C19: Aerotrans Metropolitan Express | D19: Komp. Perkantoran Griya Intan No. 3 | E19: Transp | G19: Pass Without Comment | H19: 021-79198419 | J19: 021-79198421 | M19: Jl Buncit Raya | N19: Jakarta Selatan | P19: Indonesia | Q19: Nugroho | T19: "" | U19: "" | V19: "" | AC19: Y
A20: VDR3778 | B20: PT | C20: Agape Biomedi Investama | D20: Mayapada Tower 1 Lantai 07. Unit 07-01, Jalan Jendral Sudirman Kav.28 Setiabudi Jakarta Selatan, 12920, Indonesia | E20: Rumah Sakit | F20: Lab | G20: Medical Check Up pekerja | H20: 8118600123 | I20: info@biomedilab.co.id | J20: - | K20: info@biomedilab.co.id | M20: - | N20: KOTA JAKARTA SELATAN | O20: DKI JAKARTA | P20: INDONESIA | Q20: PT. Agape Biomedi Investa | R20: Bambang Wibowo | S20: - | T20: Mandiri | U20: 1020010571583 | V20: PT. Agape Biomedi Investama | W20: - | X20: - | Y20: - | Z20: National | AA20: - | AB20: - | AC20: Y | AD20: 31.479.507.1-416.000 | AE20: t | AF20: 0000-00-00
A21: VDR2425 | B21: PT | C21: Agape Sukses Abadi | D21: Jl. Dewi Sartika No. 357. Kel. Cawang. Kec. Kramat Jati. | E21: Transportation | F21: Trucking | G21: 0 | H21: 82111567101 | I21: ptagape.asa@gmail.com | J21: 0 | K21: ptagape.asa@gmail.com | M21: 0 | N21: KOTA JAKARTA TIMUR | O21: DKI JAKARTA | P21: Indonesia | Q21: Riris Armada | R21: Gunawan | S21: Riris Armada | T21: Bank Mandiri | U21: 166-00-0218579-1 | V21: PT Agape Sukses Abadi | W21: 0 | X21: 0 | Y21: 0 | Z21: National | AA21: 0 | AB21: 0 | AC21: Y | AE21: f | AF21: 0000-00-00
A22: VDR2172 | B22: PT | C22: Agung Bersama Indonesia | D22: Jl KH Ahmad Dahlan No.2 RT001/001, Kel Petir, Kec Cipondoh, Kota Tangerang | E22: Supplier | F22: Tiang | G22: Supplier Tiang PJU | H22: 021-55703219 | I22: bersama.abi@gmail.com | J22: 021-55703186 | K22: bersama.abi@gmail.com | N22: KOTA TANGERANG | O22: BANTEN | P22: Indonesia | Q22: Ibu Anita | R22: 0 | S22: 0 | T22: Mandiri | U22: 1180013118996 | V22: Suparmin | Z22: National | AC22: Y | AE22: N | AF22: 0000-00-00
A23: VDR1223 | B23: PT | C23: Agung Karunia Utama | D23: JL. LINGKAR SELATAN BATOK BALI SERANG 42115 | E23: Survey | F23: Survey | G23: VENDOR UNTUK JASA SURVE FTTH BANDUNG. DATA PERUSAHAAN SEDANG DIMINTAKAN | H23: 0254-205141, 0254-204595 | I23: amitono@gmail.com | J23: 0254-7400038 | K23: amitono@gmail.com | N23: KOTA SERANG | O23: BANTEN | P23: INDONESIA | Q23: PARMI SUWASTY | R23: PARMI SUWASTY | S23: PARMI SUWASTY | T23: BCA | U23: 8800224714 | V23: TBA | Z23: National | AC23: Y | AE23: N | AF23: 0000-00-00
A24: VDR2111 | B24: PT | C24: Agusta Mitra Sukses | D24: H Muchtar Raya, Prapatan Joglo No.30 RT009 RW008, Kel Joglo, Kec Kembangan, Jakarta Barat | E24: Rental | F24: Rental Alat Berat | G24: Rental Barbending & Barcutter | H24: 021-22540184 | N24: KOTA JAKARTA BARAT | O24: DKI JAKARTA | P24: Indonesia | Q24: Bp Sutanto | R24: 0 | S24: 0 | T24: Mandiri | U24: 1180007855892 | V24: PT Agusta Mitra Sukses | Z24: National | AC24: Y | AE24: N | AF24: 0000-00-00
A25: VDR1473 | B25: PT | C25: AIA Financial | D25: Jl. Boulevard Palem Raya Menara Matahari Lt.7 Bencongan Kelapa Dua Tangerang | E25: Insurance Consultant, Guarante | F25: Overhead | G25: Asuransi pengganti Aviva | H25: 021 2994 8900 Ext. 22054 | I25: randy.zuchra@aia-corporate.com | J25: 021 5795 7434 | K25: randy.zuchra@aia-corporate.com | N25: KABUPATEN TANGERANG | O25: BANTEN | P25: Indonesia | Q25: Mr. Randy Zuchra | R25: M | S25: Mr. Carl Gustini | T25: Bank CIMB Niaga | U25: 8.7092014e+15 | V25: PT AIA Financial | Z25: National | AC25: Y | AD25: 01.788.469.3-058.000 | AE25: Y | AF25: 2009-07-21
A26: VDR1040 | B26: PT | C26: Akira Data Pratama | D26: Jl. Persada Raya No. 43 Jakarta Selatan 12810 (WorkShop) | E26: Supplier Others | F26: Overhead | G26: Pass Without Comment | H26: (021) 8303894 | I26: sanan@akiradata.co.id | J26: (021) 8295777 | K26: sanan@akiradata.co.id | L26: Pembelian printer HP | N26: Jakarta | P26: Indonesia | Q26: Munawar Ilham (021-989480 | T26: BANK NEGARA INDONESIA GD. CHESE PLAZA JL. SUDIRMAN | U26: 47921507 | V26: PT AKIRA DATA PRATAMA | Z26: National | AC26: Y | AD26: 02.342.459.1.015.000 | AE26: Y | AF26: 2009-07-17
A27: VDR2568 | B27: PT | C27: Alam Insektindo | D27: Gedung Graha Lantai 3 SUITE 305, Jl mampang Prapatan raya No. 100 | E27: Supplier | F27: Stringing | H27: +62 812-1949-7931 | M27: Duren Tiga - Pancoran | N27: KOTA JAKARTA SELATAN | O27: DKI JAKARTA | P27: IndonesiaPriypno | Q27: Priyono | R27: 0 | S27: 0 | T27: BNI Fatmawati Raya | U27: 324415088 | V27: PT. ALAM INSEKTINDO | Z27: National | AC27: Y | AD27: 21851555061000 | AE27: t | AF27: 0000-00-00
A28: VDR2808 | B28: PT | C28: Alam Loka Bersama | D28: Jl. mangga dua dalam Blok J no.23 mangga dua selatan | E28: Rental | F28: Alat Berat | G28: hammer diesel pilling | H28: +62 813-1076-0234 | N28: KOTA JAKARTA PUSAT | O28: DKI JAKARTA | P28: Indonesia | Q28: Ahmad Sarwi | R28: 0 | S28: 0 | T28: BCA | U28: 7630271147 | V28: PT. ALAM LOKA BERSAMA | Z28: National | AC28: Y | AD28: 15368376026 | AE28: t | AF28: 0000-00-00
A29: VDR0887 | B29: PT | C29: Aldina Krida Tama | D29: Jl. Bungur IV No. 35 Kampung Rambutan Ciracas Jakarta Timur | E29: Akli | G29: Pass Without Comment | H29: 021-87790373 | I29: khairudin@yahoo.com | J29: 021-87790373 | K29: khairudin@yahoo.com | L29: KONSULTAN PLN dan AKLI | N29: Jakarta Timur | P29: Indonesia | Q29: Bpk Khairudin | T29: BUKOPIN Capem. Sunter II | U29: KHAIRUDIN | V29: 4505050117 | W29: TBA | X29: TBA | Y29: TBA | Z29: National | AA29: TBA | AB29: TBA | AC29: Y
A30: VDR0004 | B30: PT | C30: Aledro Duta Jaya | D30: Jl. Gading griya Lestari Blok E3. No 11 | E30: Supplier Material ME | F30: Alat elektrical | G30: Pass Without Comment | H30: 021-44834291 | J30: 021-4405723 | N30: Jakarta Timur | P30: Indonesia | Q30: Narko | T30: Jasa Jakarta cab Kelapa gading | U30: CV. Aledro Duta Jaya | V30: 03 00 00 709 739 | AC30: Y
A31: VDR3377 | B31: PT | C31: Alhadi Berkah Sukses | D31: Komplek Paradesa Cinere Blok A No6 RT005/003, Pondok Cabe Ilir, Pamulang, Kota Tangerang Selatan, Banten | E31: Supplier Material Civil | F31: Beton Kontruksi | G31: Supplier Readymix / Beton Konstruksi (Sales divisi Jayamix) | H31: 0812-2505-5287 | N31: KOTA TANGERANG SELATAN | O31: BANTEN | P31: Indonesia | Q31: Bp Nono | R31: 0 | S31: 0 | T31: BCA | U31: 2677300881 | V31: PT Alhadi Berkah Sukses | Z31: National | AC31: Y | AD31: 950342741453000 | AE31: t | AF31: 0000-00-00
A32: VDR3937 | B32: PT | C32: Ali Sejahtera | D32: Jl. Kelapa Gading Boulevard Complek Blok RA 1 No. 15 Kelapa Gading Permai 14240 | E32: Insurance Consultant, Guarante | F32: Asuransi | H32: 021 46619470 | N32: KOTA JAKARTA UTARA | O32: DKI JAKARTA | P32: Indonesia | Q32: Syaeful Basar | R32: - | S32: Ali Subhan | T32: - | U32: - | V32: - | Z32: National | AC32: Y | AE32: f | AF32: 0000-00-00
A33: VDR1921 | B33: PT | C33: Allysa Puteri Mandiri | D33: Jl. Bintara Raya, Bintara Loka No.19 Lt.2 Rt 001/008 Kel. Bintara, Kec. Bekasi Barat | E33: Transportation | F33: Trucking | H33: 021-91262537 | I33: Allysaputerimandiri@yahoo.co.i | J33: 0 | K33: Allysaputerimandiri@yahoo.co.i | M33: 0 | N33: KABUPATEN BEKASI | O33: JAWA BARAT | P33: INDONESIA | Q33: Affandi | R33: 0 | S33: Hendro Yudotomo | T33: BCA | U33: 663-0489898 | V33: ALYSSA PUTERI MANDIRI PT | W33: 0 | X33: 0 | Y33: 0 | Z33: National | AC33: Y | AE33: N | AF33: 0000-00-00
A34: VDR0991 | B34: PT | C34: Alma Cipta Mandiri | D34: Jl. Salemba Tengah I No.C 220 B Senen-Jakarta Pusat | E34: Supplier Material RF | F34: Material RF | G34: Pass Without Comment | H34: 021-319 08738 | I34: marketing@acm-telekomindo.com | J34: 021-319 08219 | K34: marketing@acm-telekomindo.com | L34: Supplier Material RF & Accesories | N34: DKI Jakarta | O34: DKI Jakarta | P34: Indonesia | Q34: Muhammad Faisal | R34: Irfan Indragunawan | S34: Irfan Indragunawan | T34: Bank BCA, KCP Raden Saleh | U34: Irfan Indragunawan | V34: 6340206566 | W34: 6 Tahun | X34: 12 Januari | Z34: National | AB34: 8 | AC34: Y | AD34: 03.283.552.2-023.000 | AE34: Y | AF34: 1970-01-01
A35: VDR0168 | B35: PT | C35: Alpha Cikupa Makmur | D35: Jl. raya Otonom Cikupa | E35: "" | G35: Pass Without Comment | H35: 021 5963563, | J35: 021 596 9941 | M35: Tanggerang | N35: Tanggerang | P35: Indonesia | Q35: Sugeng Sugianto | T35: "" | U35: "" | V35: "" | AC35: Y
A36: VDR0005 | B36: PT | C36: Alpine Cool Utama | D36: Jl. Pangeran jayakarta No. 87 | E36: Manufactur | F36: Panel Maker | G36: Pass Without Comment | H36: 021-6268211 | I36: sonny@frigostar | J36: 021-6596407 | K36: sonny@frigostar | L36: Shelter | N36: Jakarta Pusat | P36: Indonesia | Q36: SOnny | T36: Bank BCA | U36: PT Alpin Cool Utama | V36: 833009955 | W36: 2001 | X36: 24-07-2001 | Y36: TBA | Z36: National | AA36: TBA | AB36: TBA | AC36: Y | AD36: 02.094.575.4-026.000 & PEM-004242/WPJ.06/KP.0403/2 | AE36: Y | AF36: 2011-03-04
A37: VDR1761 | B37: PT | C37: Alstom Grid Indonesia | D37: PLAZA ALZTOM, 6th Floor Jl. TB Simatupang Kav. IS-1, Cilandak, Jakarta Selatan - Indonesia 12310 | E37: Supplier Others | F37: Alat elektrical | G37: Supplier CRP utk GI DOmpu | H37: 29244754 | I37: ardian.asril@alstom.com | J37: 29244501 | K37: ardian.asril@alstom.com | N37: KOTA JAKARTA SELATAN | O37: DKI JAKARTA | P37: INDONESIA | Q37: Ardian Asril | R37: Mery Susilowati | S37: John Murlgren | T37: Citibank | U37: 106317518 | V37: PT. ALSTOM GRID | Z37: National | AC37: Y | AD37: 01.000.593.2-055.000 | AE37: Y | AF37: 1970-01-01
A38: VDR2605 | B38: PT | C38: Alvasta Teknologi | D38: Rukan City Square Blok C No. 8 | E38: Supplier Material RF | F38: Material RF | H38: 021-22052127 / 22052205 | I38: Sales@alvasta-tech.com | K38: Sales@alvasta-tech.com | M38: Jl Peta Selatan RT 010/001 Kalideres | N38: KOTA JAKARTA BARAT | O38: DKI JAKARTA | P38: Indonesia | Q38: Bunardi | R38: 0 | S38: 0 | T38: BCA | U38: 5390427788 | V38: PT. Alvasta Teknologi | Z38: National | AC38: Y | AD38: 32669335085000 | AE38: t | AF38: 0000-00-00
A39: VDR0518 | B39: PT | C39: Alvinta Yoga Pratama | D39: Jl. Anggrek Rosliana Blok F No. 1, Slipi | E39: Mandor/Subcon | G39: Pass Without Comment | H39: 53651165, 53670589 | J39: 021 53670607 | M39: Jakarta Barat 08161660243 | N39: Jakarta | P39: Indonesia | Q39: Alwien Desry | T39: BRI | U39: 57801000086152 | V39: PT. Alvinta Yoga Pratama | AC39: Y
A40: VDR3801 | B40: PT | C40: Amerika Sistem Registrasi Internasional Indonesia | D40: Jl. TB. Simatupang Kav TALAVERA OFFICE PARK, 28 Floor, 22-26, Jakarta 12430 - Indonesia | E40: Sertifikasi | F40: Jasa Sertifikasi | G40: 1 st Surveillance Audit of SNI ISO 37001:2016 PT. QDC Technologies | H40: +62 812-9607-2465 | I40: - | J40: 021-2912 4996 | K40: - | M40: - | N40: KOTA JAKARTA BARAT | O40: DKI JAKARTA | P40: Indonesia | Q40: BCA KCP Talavera Jakarta | R40: - | S40: - | T40: Bank Central Asia | U40: 5225 032 987 | V40: BCA KCP Talavera Jakarta | W40: - | X40: - | Y40: - | Z40: National | AA40: - | AB40: - | AC40: Y | AD40: 03.027.904.6-016.000 | AE40: t | AF40: 0000-00-00
