Workbook

Sheet MAIN
B2: User Role Name | D2: SYS_PID Prediction | E2: SQL Syntax
D3: 95000000000000
B4: Super User | D4: =D3 + IF(EXACT(E4, ""), 0, 1) -> 95000000000001 | E4: =IF(EXACT(B4, ""), "", CONCATENATE("PERFORM ""SchSysConfig"".""Func_TblAppObject_UserRole_SET""(varSystemLoginSession, null::bigint, null::varchar, null::timestamptz, null::timestamptz, null::varchar, varInstitutionBranchID, varBaseCurrencyID, ", (IF(EXACT(B4, ""), "NULL", CONCATENATE("'", B4, "'"))),"::varchar);")) -> PERFORM "SchSysConfig"."Func_TblAppObject_UserRole_SET"(varSystemLoginSession, null::bigint, null::varchar, null::timestamptz, null::timestamptz, null::varchar, varInstitutionBranchID, varBaseCurrencyID, 'Super User'::varchar); | G4: =IF(EXACT($E4, ""), "", CONCATENATE( "varSQL := varSQL || (CASE WHEN (varSQL = '') THEN '' ELSE ', ' END) || (SELECT JSON_BUILD_OBJECT (", "'recordID', NULL::bigint,", "'entities', ", "JSON_BUILD_OBJECT (", "'sysLoginSession_RefID', varSystemLoginSession::bigint,", "'sysDataAnnotation', NULL::varchar,", "'sysDataSetDateTimeTZ', NULL::timestamptz,", "'sysDataValidityStartDateTimeTZ', NULL::timestamptz,", "'sysDataValidityFinishDateTimeTZ', NULL::timestamptz,", "'sysPartitionRemovableRecordKey_RefID', NULL::bigint,", "'sysBranch_RefID', varInstitutionBranchID::bigint,", "'sysBaseCurrency_RefID',varBaseCurrencyID::bigint,", "'name', ", IF(EXACT($B4, ""), "null", CONCATENATE("'", SUBSTITUTE($B4, "'", "\'"), "'")), "::varchar", ")))::varchar;")) -> varSQL := varSQL || (CASE WHEN (varSQL = '') THEN '' ELSE ', ' END) || (SELECT JSON_BUILD_OBJECT ('recordID', NULL::bigint,'entities', JSON_BUILD_OBJECT ('sysLoginSession_RefID', varSystemLoginSession::bigint,'sysDataAnnotation', NULL::varchar,'sysDataSetDateTimeTZ', NULL::timestamptz,'sysDataValidityStartDateTimeTZ', NULL::timestamptz,'sysDataValidityFinishDateTimeTZ', NULL::timestamptz,'sysPartitionRemovableRecordKey_RefID', NULL::bigint,'sysBranch_RefID', varInstitutionBranchID::bigint,'sysBaseCurrency_RefID',varBaseCurrencyID::bigint,'name', 'Super User'::varchar)))::varchar;
B5: Guest | D5: =D4 + IF(EXACT(E5, ""), 0, 1) -> 95000000000002 | E5: =IF(EXACT(B5, ""), "", CONCATENATE("PERFORM ""SchSysConfig"".""Func_TblAppObject_UserRole_SET""(varSystemLoginSession, null::bigint, null::varchar, null::timestamptz, null::timestamptz, null::varchar, varInstitutionBranchID, varBaseCurrencyID, ", (IF(EXACT(B5, ""), "NULL", CONCATENATE("'", B5, "'"))),"::varchar);")) -> PERFORM "SchSysConfig"."Func_TblAppObject_UserRole_SET"(varSystemLoginSession, null::bigint, null::varchar, null::timestamptz, null::timestamptz, null::varchar, varInstitutionBranchID, varBaseCurrencyID, 'Guest'::varchar); | G5: =IF(EXACT($E5, ""), "", CONCATENATE( "varSQL := varSQL || (CASE WHEN (varSQL = '') THEN '' ELSE ', ' END) || (SELECT JSON_BUILD_OBJECT (", "'recordID', NULL::bigint,", "'entities', ", "JSON_BUILD_OBJECT (", "'sysLoginSession_RefID', varSystemLoginSession::bigint,", "'sysDataAnnotation', NULL::varchar,", "'sysDataSetDateTimeTZ', NULL::timestamptz,", "'sysDataValidityStartDateTimeTZ', NULL::timestamptz,", "'sysDataValidityFinishDateTimeTZ', NULL::timestamptz,", "'sysPartitionRemovableRecordKey_RefID', NULL::bigint,", "'sysBranch_RefID', varInstitutionBranchID::bigint,", "'sysBaseCurrency_RefID',varBaseCurrencyID::bigint,", "'name', ", IF(EXACT($B5, ""), "null", CONCATENATE("'", SUBSTITUTE($B5, "'", "\'"), "'")), "::varchar", ")))::varchar;")) -> varSQL := varSQL || (CASE WHEN (varSQL = '') THEN '' ELSE ', ' END) || (SELECT JSON_BUILD_OBJECT ('recordID', NULL::bigint,'entities', JSON_BUILD_OBJECT ('sysLoginSession_RefID', varSystemLoginSession::bigint,'sysDataAnnotation', NULL::varchar,'sysDataSetDateTimeTZ', NULL::timestamptz,'sysDataValidityStartDateTimeTZ', NULL::timestamptz,'sysDataValidityFinishDateTimeTZ', NULL::timestamptz,'sysPartitionRemovableRecordKey_RefID', NULL::bigint,'sysBranch_RefID', varInstitutionBranchID::bigint,'sysBaseCurrency_RefID',varBaseCurrencyID::bigint,'name', 'Guest'::varchar)))::varchar;
D6: =D5 + IF(EXACT(E6, ""), 0, 1) -> 95000000000002 | E6: =IF(EXACT(B6, ""), "", CONCATENATE("PERFORM ""SchSysConfig"".""Func_TblAppObject_UserRole_SET""(varSystemLoginSession, null::bigint, null::varchar, null::timestamptz, null::timestamptz, null::varchar, varInstitutionBranchID, varBaseCurrencyID, ", (IF(EXACT(B6, ""), "NULL", CONCATENATE("'", B6, "'"))),"::varchar);")) | G6: =IF(EXACT($E6, ""), "", CONCATENATE( "varSQL := varSQL || (CASE WHEN (varSQL = '') THEN '' ELSE ', ' END) || (SELECT JSON_BUILD_OBJECT (", "'recordID', NULL::bigint,", "'entities', ", "JSON_BUILD_OBJECT (", "'sysLoginSession_RefID', varSystemLoginSession::bigint,", "'sysDataAnnotation', NULL::varchar,", "'sysDataSetDateTimeTZ', NULL::timestamptz,", "'sysDataValidityStartDateTimeTZ', NULL::timestamptz,", "'sysDataValidityFinishDateTimeTZ', NULL::timestamptz,", "'sysPartitionRemovableRecordKey_RefID', NULL::bigint,", "'sysBranch_RefID', varInstitutionBranchID::bigint,", "'sysBaseCurrency_RefID',varBaseCurrencyID::bigint,", "'name', ", IF(EXACT($B6, ""), "null", CONCATENATE("'", SUBSTITUTE($B6, "'", "\'"), "'")), "::varchar", ")))::varchar;"))
B7: Default Employee Role | D7: =D6 + IF(EXACT(E7, ""), 0, 1) -> 95000000000003 | E7: =IF(EXACT(B7, ""), "", CONCATENATE("PERFORM ""SchSysConfig"".""Func_TblAppObject_UserRole_SET""(varSystemLoginSession, null::bigint, null::varchar, null::timestamptz, null::timestamptz, null::varchar, varInstitutionBranchID, varBaseCurrencyID, ", (IF(EXACT(B7, ""), "NULL", CONCATENATE("'", B7, "'"))),"::varchar);")) -> PERFORM "SchSysConfig"."Func_TblAppObject_UserRole_SET"(varSystemLoginSession, null::bigint, null::varchar, null::timestamptz, null::timestamptz, null::varchar, varInstitutionBranchID, varBaseCurrencyID, 'Default Employee Role'::varchar); | G7: =IF(EXACT($E7, ""), "", CONCATENATE( "varSQL := varSQL || (CASE WHEN (varSQL = '') THEN '' ELSE ', ' END) || (SELECT JSON_BUILD_OBJECT (", "'recordID', NULL::bigint,", "'entities', ", "JSON_BUILD_OBJECT (", "'sysLoginSession_RefID', varSystemLoginSession::bigint,", "'sysDataAnnotation', NULL::varchar,", "'sysDataSetDateTimeTZ', NULL::timestamptz,", "'sysDataValidityStartDateTimeTZ', NULL::timestamptz,", "'sysDataValidityFinishDateTimeTZ', NULL::timestamptz,", "'sysPartitionRemovableRecordKey_RefID', NULL::bigint,", "'sysBranch_RefID', varInstitutionBranchID::bigint,", "'sysBaseCurrency_RefID',varBaseCurrencyID::bigint,", "'name', ", IF(EXACT($B7, ""), "null", CONCATENATE("'", SUBSTITUTE($B7, "'", "\'"), "'")), "::varchar", ")))::varchar;")) -> varSQL := varSQL || (CASE WHEN (varSQL = '') THEN '' ELSE ', ' END) || (SELECT JSON_BUILD_OBJECT ('recordID', NULL::bigint,'entities', JSON_BUILD_OBJECT ('sysLoginSession_RefID', varSystemLoginSession::bigint,'sysDataAnnotation', NULL::varchar,'sysDataSetDateTimeTZ', NULL::timestamptz,'sysDataValidityStartDateTimeTZ', NULL::timestamptz,'sysDataValidityFinishDateTimeTZ', NULL::timestamptz,'sysPartitionRemovableRecordKey_RefID', NULL::bigint,'sysBranch_RefID', varInstitutionBranchID::bigint,'sysBaseCurrency_RefID',varBaseCurrencyID::bigint,'name', 'Default Employee Role'::varchar)))::varchar;
D8: =D7 + IF(EXACT(E8, ""), 0, 1) -> 95000000000003 | E8: =IF(EXACT(B8, ""), "", CONCATENATE("PERFORM ""SchSysConfig"".""Func_TblAppObject_UserRole_SET""(varSystemLoginSession, null::bigint, null::varchar, null::timestamptz, null::timestamptz, null::varchar, varInstitutionBranchID, varBaseCurrencyID, ", (IF(EXACT(B8, ""), "NULL", CONCATENATE("'", B8, "'"))),"::varchar);")) | G8: =IF(EXACT($E8, ""), "", CONCATENATE( "varSQL := varSQL || (CASE WHEN (varSQL = '') THEN '' ELSE ', ' END) || (SELECT JSON_BUILD_OBJECT (", "'recordID', NULL::bigint,", "'entities', ", "JSON_BUILD_OBJECT (", "'sysLoginSession_RefID', varSystemLoginSession::bigint,", "'sysDataAnnotation', NULL::varchar,", "'sysDataSetDateTimeTZ', NULL::timestamptz,", "'sysDataValidityStartDateTimeTZ', NULL::timestamptz,", "'sysDataValidityFinishDateTimeTZ', NULL::timestamptz,", "'sysPartitionRemovableRecordKey_RefID', NULL::bigint,", "'sysBranch_RefID', varInstitutionBranchID::bigint,", "'sysBaseCurrency_RefID',varBaseCurrencyID::bigint,", "'name', ", IF(EXACT($B8, ""), "null", CONCATENATE("'", SUBSTITUTE($B8, "'", "\'"), "'")), "::varchar", ")))::varchar;"))
B9: Share Holder | D9: =D8 + IF(EXACT(E9, ""), 0, 1) -> 95000000000004 | E9: =IF(EXACT(B9, ""), "", CONCATENATE("PERFORM ""SchSysConfig"".""Func_TblAppObject_UserRole_SET""(varSystemLoginSession, null::bigint, null::varchar, null::timestamptz, null::timestamptz, null::varchar, varInstitutionBranchID, varBaseCurrencyID, ", (IF(EXACT(B9, ""), "NULL", CONCATENATE("'", B9, "'"))),"::varchar);")) -> PERFORM "SchSysConfig"."Func_TblAppObject_UserRole_SET"(varSystemLoginSession, null::bigint, null::varchar, null::timestamptz, null::timestamptz, null::varchar, varInstitutionBranchID, varBaseCurrencyID, 'Share Holder'::varchar); | G9: =IF(EXACT($E9, ""), "", CONCATENATE( "varSQL := varSQL || (CASE WHEN (varSQL = '') THEN '' ELSE ', ' END) || (SELECT JSON_BUILD_OBJECT (", "'recordID', NULL::bigint,", "'entities', ", "JSON_BUILD_OBJECT (", "'sysLoginSession_RefID', varSystemLoginSession::bigint,", "'sysDataAnnotation', NULL::varchar,", "'sysDataSetDateTimeTZ', NULL::timestamptz,", "'sysDataValidityStartDateTimeTZ', NULL::timestamptz,", "'sysDataValidityFinishDateTimeTZ', NULL::timestamptz,", "'sysPartitionRemovableRecordKey_RefID', NULL::bigint,", "'sysBranch_RefID', varInstitutionBranchID::bigint,", "'sysBaseCurrency_RefID',varBaseCurrencyID::bigint,", "'name', ", IF(EXACT($B9, ""), "null", CONCATENATE("'", SUBSTITUTE($B9, "'", "\'"), "'")), "::varchar", ")))::varchar;")) -> varSQL := varSQL || (CASE WHEN (varSQL = '') THEN '' ELSE ', ' END) || (SELECT JSON_BUILD_OBJECT ('recordID', NULL::bigint,'entities', JSON_BUILD_OBJECT ('sysLoginSession_RefID', varSystemLoginSession::bigint,'sysDataAnnotation', NULL::varchar,'sysDataSetDateTimeTZ', NULL::timestamptz,'sysDataValidityStartDateTimeTZ', NULL::timestamptz,'sysDataValidityFinishDateTimeTZ', NULL::timestamptz,'sysPartitionRemovableRecordKey_RefID', NULL::bigint,'sysBranch_RefID', varInstitutionBranchID::bigint,'sysBaseCurrency_RefID',varBaseCurrencyID::bigint,'name', 'Share Holder'::varchar)))::varchar;
B10: Stack Holder | D10: =D9 + IF(EXACT(E10, ""), 0, 1) -> 95000000000005 | E10: =IF(EXACT(B10, ""), "", CONCATENATE("PERFORM ""SchSysConfig"".""Func_TblAppObject_UserRole_SET""(varSystemLoginSession, null::bigint, null::varchar, null::timestamptz, null::timestamptz, null::varchar, varInstitutionBranchID, varBaseCurrencyID, ", (IF(EXACT(B10, ""), "NULL", CONCATENATE("'", B10, "'"))),"::varchar);")) -> PERFORM "SchSysConfig"."Func_TblAppObject_UserRole_SET"(varSystemLoginSession, null::bigint, null::varchar, null::timestamptz, null::timestamptz, null::varchar, varInstitutionBranchID, varBaseCurrencyID, 'Stack Holder'::varchar); | G10: =IF(EXACT($E10, ""), "", CONCATENATE( "varSQL := varSQL || (CASE WHEN (varSQL = '') THEN '' ELSE ', ' END) || (SELECT JSON_BUILD_OBJECT (", "'recordID', NULL::bigint,", "'entities', ", "JSON_BUILD_OBJECT (", "'sysLoginSession_RefID', varSystemLoginSession::bigint,", "'sysDataAnnotation', NULL::varchar,", "'sysDataSetDateTimeTZ', NULL::timestamptz,", "'sysDataValidityStartDateTimeTZ', NULL::timestamptz,", "'sysDataValidityFinishDateTimeTZ', NULL::timestamptz,", "'sysPartitionRemovableRecordKey_RefID', NULL::bigint,", "'sysBranch_RefID', varInstitutionBranchID::bigint,", "'sysBaseCurrency_RefID',varBaseCurrencyID::bigint,", "'name', ", IF(EXACT($B10, ""), "null", CONCATENATE("'", SUBSTITUTE($B10, "'", "\'"), "'")), "::varchar", ")))::varchar;")) -> varSQL := varSQL || (CASE WHEN (varSQL = '') THEN '' ELSE ', ' END) || (SELECT JSON_BUILD_OBJECT ('recordID', NULL::bigint,'entities', JSON_BUILD_OBJECT ('sysLoginSession_RefID', varSystemLoginSession::bigint,'sysDataAnnotation', NULL::varchar,'sysDataSetDateTimeTZ', NULL::timestamptz,'sysDataValidityStartDateTimeTZ', NULL::timestamptz,'sysDataValidityFinishDateTimeTZ', NULL::timestamptz,'sysPartitionRemovableRecordKey_RefID', NULL::bigint,'sysBranch_RefID', varInstitutionBranchID::bigint,'sysBaseCurrency_RefID',varBaseCurrencyID::bigint,'name', 'Stack Holder'::varchar)))::varchar;
B11: Public Accounting Firm | D11: =D10 + IF(EXACT(E11, ""), 0, 1) -> 95000000000006 | E11: =IF(EXACT(B11, ""), "", CONCATENATE("PERFORM ""SchSysConfig"".""Func_TblAppObject_UserRole_SET""(varSystemLoginSession, null::bigint, null::varchar, null::timestamptz, null::timestamptz, null::varchar, varInstitutionBranchID, varBaseCurrencyID, ", (IF(EXACT(B11, ""), "NULL", CONCATENATE("'", B11, "'"))),"::varchar);")) -> PERFORM "SchSysConfig"."Func_TblAppObject_UserRole_SET"(varSystemLoginSession, null::bigint, null::varchar, null::timestamptz, null::timestamptz, null::varchar, varInstitutionBranchID, varBaseCurrencyID, 'Public Accounting Firm'::varchar); | G11: =IF(EXACT($E11, ""), "", CONCATENATE( "varSQL := varSQL || (CASE WHEN (varSQL = '') THEN '' ELSE ', ' END) || (SELECT JSON_BUILD_OBJECT (", "'recordID', NULL::bigint,", "'entities', ", "JSON_BUILD_OBJECT (", "'sysLoginSession_RefID', varSystemLoginSession::bigint,", "'sysDataAnnotation', NULL::varchar,", "'sysDataSetDateTimeTZ', NULL::timestamptz,", "'sysDataValidityStartDateTimeTZ', NULL::timestamptz,", "'sysDataValidityFinishDateTimeTZ', NULL::timestamptz,", "'sysPartitionRemovableRecordKey_RefID', NULL::bigint,", "'sysBranch_RefID', varInstitutionBranchID::bigint,", "'sysBaseCurrency_RefID',varBaseCurrencyID::bigint,", "'name', ", IF(EXACT($B11, ""), "null", CONCATENATE("'", SUBSTITUTE($B11, "'", "\'"), "'")), "::varchar", ")))::varchar;")) -> varSQL := varSQL || (CASE WHEN (varSQL = '') THEN '' ELSE ', ' END) || (SELECT JSON_BUILD_OBJECT ('recordID', NULL::bigint,'entities', JSON_BUILD_OBJECT ('sysLoginSession_RefID', varSystemLoginSession::bigint,'sysDataAnnotation', NULL::varchar,'sysDataSetDateTimeTZ', NULL::timestamptz,'sysDataValidityStartDateTimeTZ', NULL::timestamptz,'sysDataValidityFinishDateTimeTZ', NULL::timestamptz,'sysPartitionRemovableRecordKey_RefID', NULL::bigint,'sysBranch_RefID', varInstitutionBranchID::bigint,'sysBaseCurrency_RefID',varBaseCurrencyID::bigint,'name', 'Public Accounting Firm'::varchar)))::varchar;
B12: Commissary | D12: =D11 + IF(EXACT(E12, ""), 0, 1) -> 95000000000007 | E12: =IF(EXACT(B12, ""), "", CONCATENATE("PERFORM ""SchSysConfig"".""Func_TblAppObject_UserRole_SET""(varSystemLoginSession, null::bigint, null::varchar, null::timestamptz, null::timestamptz, null::varchar, varInstitutionBranchID, varBaseCurrencyID, ", (IF(EXACT(B12, ""), "NULL", CONCATENATE("'", B12, "'"))),"::varchar);")) -> PERFORM "SchSysConfig"."Func_TblAppObject_UserRole_SET"(varSystemLoginSession, null::bigint, null::varchar, null::timestamptz, null::timestamptz, null::varchar, varInstitutionBranchID, varBaseCurrencyID, 'Commissary'::varchar); | G12: =IF(EXACT($E12, ""), "", CONCATENATE( "varSQL := varSQL || (CASE WHEN (varSQL = '') THEN '' ELSE ', ' END) || (SELECT JSON_BUILD_OBJECT (", "'recordID', NULL::bigint,", "'entities', ", "JSON_BUILD_OBJECT (", "'sysLoginSession_RefID', varSystemLoginSession::bigint,", "'sysDataAnnotation', NULL::varchar,", "'sysDataSetDateTimeTZ', NULL::timestamptz,", "'sysDataValidityStartDateTimeTZ', NULL::timestamptz,", "'sysDataValidityFinishDateTimeTZ', NULL::timestamptz,", "'sysPartitionRemovableRecordKey_RefID', NULL::bigint,", "'sysBranch_RefID', varInstitutionBranchID::bigint,", "'sysBaseCurrency_RefID',varBaseCurrencyID::bigint,", "'name', ", IF(EXACT($B12, ""), "null", CONCATENATE("'", SUBSTITUTE($B12, "'", "\'"), "'")), "::varchar", ")))::varchar;")) -> varSQL := varSQL || (CASE WHEN (varSQL = '') THEN '' ELSE ', ' END) || (SELECT JSON_BUILD_OBJECT ('recordID', NULL::bigint,'entities', JSON_BUILD_OBJECT ('sysLoginSession_RefID', varSystemLoginSession::bigint,'sysDataAnnotation', NULL::varchar,'sysDataSetDateTimeTZ', NULL::timestamptz,'sysDataValidityStartDateTimeTZ', NULL::timestamptz,'sysDataValidityFinishDateTimeTZ', NULL::timestamptz,'sysPartitionRemovableRecordKey_RefID', NULL::bigint,'sysBranch_RefID', varInstitutionBranchID::bigint,'sysBaseCurrency_RefID',varBaseCurrencyID::bigint,'name', 'Commissary'::varchar)))::varchar;
D13: =D12 + IF(EXACT(E13, ""), 0, 1) -> 95000000000007 | E13: =IF(EXACT(B13, ""), "", CONCATENATE("PERFORM ""SchSysConfig"".""Func_TblAppObject_UserRole_SET""(varSystemLoginSession, null::bigint, null::varchar, null::timestamptz, null::timestamptz, null::varchar, varInstitutionBranchID, varBaseCurrencyID, ", (IF(EXACT(B13, ""), "NULL", CONCATENATE("'", B13, "'"))),"::varchar);")) | G13: =IF(EXACT($E13, ""), "", CONCATENATE( "varSQL := varSQL || (CASE WHEN (varSQL = '') THEN '' ELSE ', ' END) || (SELECT JSON_BUILD_OBJECT (", "'recordID', NULL::bigint,", "'entities', ", "JSON_BUILD_OBJECT (", "'sysLoginSession_RefID', varSystemLoginSession::bigint,", "'sysDataAnnotation', NULL::varchar,", "'sysDataSetDateTimeTZ', NULL::timestamptz,", "'sysDataValidityStartDateTimeTZ', NULL::timestamptz,", "'sysDataValidityFinishDateTimeTZ', NULL::timestamptz,", "'sysPartitionRemovableRecordKey_RefID', NULL::bigint,", "'sysBranch_RefID', varInstitutionBranchID::bigint,", "'sysBaseCurrency_RefID',varBaseCurrencyID::bigint,", "'name', ", IF(EXACT($B13, ""), "null", CONCATENATE("'", SUBSTITUTE($B13, "'", "\'"), "'")), "::varchar", ")))::varchar;"))
B14: Director | D14: =D13 + IF(EXACT(E14, ""), 0, 1) -> 95000000000008 | E14: =IF(EXACT(B14, ""), "", CONCATENATE("PERFORM ""SchSysConfig"".""Func_TblAppObject_UserRole_SET""(varSystemLoginSession, null::bigint, null::varchar, null::timestamptz, null::timestamptz, null::varchar, varInstitutionBranchID, varBaseCurrencyID, ", (IF(EXACT(B14, ""), "NULL", CONCATENATE("'", B14, "'"))),"::varchar);")) -> PERFORM "SchSysConfig"."Func_TblAppObject_UserRole_SET"(varSystemLoginSession, null::bigint, null::varchar, null::timestamptz, null::timestamptz, null::varchar, varInstitutionBranchID, varBaseCurrencyID, 'Director'::varchar); | G14: =IF(EXACT($E14, ""), "", CONCATENATE( "varSQL := varSQL || (CASE WHEN (varSQL = '') THEN '' ELSE ', ' END) || (SELECT JSON_BUILD_OBJECT (", "'recordID', NULL::bigint,", "'entities', ", "JSON_BUILD_OBJECT (", "'sysLoginSession_RefID', varSystemLoginSession::bigint,", "'sysDataAnnotation', NULL::varchar,", "'sysDataSetDateTimeTZ', NULL::timestamptz,", "'sysDataValidityStartDateTimeTZ', NULL::timestamptz,", "'sysDataValidityFinishDateTimeTZ', NULL::timestamptz,", "'sysPartitionRemovableRecordKey_RefID', NULL::bigint,", "'sysBranch_RefID', varInstitutionBranchID::bigint,", "'sysBaseCurrency_RefID',varBaseCurrencyID::bigint,", "'name', ", IF(EXACT($B14, ""), "null", CONCATENATE("'", SUBSTITUTE($B14, "'", "\'"), "'")), "::varchar", ")))::varchar;")) -> varSQL := varSQL || (CASE WHEN (varSQL = '') THEN '' ELSE ', ' END) || (SELECT JSON_BUILD_OBJECT ('recordID', NULL::bigint,'entities', JSON_BUILD_OBJECT ('sysLoginSession_RefID', varSystemLoginSession::bigint,'sysDataAnnotation', NULL::varchar,'sysDataSetDateTimeTZ', NULL::timestamptz,'sysDataValidityStartDateTimeTZ', NULL::timestamptz,'sysDataValidityFinishDateTimeTZ', NULL::timestamptz,'sysPartitionRemovableRecordKey_RefID', NULL::bigint,'sysBranch_RefID', varInstitutionBranchID::bigint,'sysBaseCurrency_RefID',varBaseCurrencyID::bigint,'name', 'Director'::varchar)))::varchar;
B15: President Director | D15: =D14 + IF(EXACT(E15, ""), 0, 1) -> 95000000000009 | E15: =IF(EXACT(B15, ""), "", CONCATENATE("PERFORM ""SchSysConfig"".""Func_TblAppObject_UserRole_SET""(varSystemLoginSession, null::bigint, null::varchar, null::timestamptz, null::timestamptz, null::varchar, varInstitutionBranchID, varBaseCurrencyID, ", (IF(EXACT(B15, ""), "NULL", CONCATENATE("'", B15, "'"))),"::varchar);")) -> PERFORM "SchSysConfig"."Func_TblAppObject_UserRole_SET"(varSystemLoginSession, null::bigint, null::varchar, null::timestamptz, null::timestamptz, null::varchar, varInstitutionBranchID, varBaseCurrencyID, 'President Director'::varchar); | G15: =IF(EXACT($E15, ""), "", CONCATENATE( "varSQL := varSQL || (CASE WHEN (varSQL = '') THEN '' ELSE ', ' END) || (SELECT JSON_BUILD_OBJECT (", "'recordID', NULL::bigint,", "'entities', ", "JSON_BUILD_OBJECT (", "'sysLoginSession_RefID', varSystemLoginSession::bigint,", "'sysDataAnnotation', NULL::varchar,", "'sysDataSetDateTimeTZ', NULL::timestamptz,", "'sysDataValidityStartDateTimeTZ', NULL::timestamptz,", "'sysDataValidityFinishDateTimeTZ', NULL::timestamptz,", "'sysPartitionRemovableRecordKey_RefID', NULL::bigint,", "'sysBranch_RefID', varInstitutionBranchID::bigint,", "'sysBaseCurrency_RefID',varBaseCurrencyID::bigint,", "'name', ", IF(EXACT($B15, ""), "null", CONCATENATE("'", SUBSTITUTE($B15, "'", "\'"), "'")), "::varchar", ")))::varchar;")) -> varSQL := varSQL || (CASE WHEN (varSQL = '') THEN '' ELSE ', ' END) || (SELECT JSON_BUILD_OBJECT ('recordID', NULL::bigint,'entities', JSON_BUILD_OBJECT ('sysLoginSession_RefID', varSystemLoginSession::bigint,'sysDataAnnotation', NULL::varchar,'sysDataSetDateTimeTZ', NULL::timestamptz,'sysDataValidityStartDateTimeTZ', NULL::timestamptz,'sysDataValidityFinishDateTimeTZ', NULL::timestamptz,'sysPartitionRemovableRecordKey_RefID', NULL::bigint,'sysBranch_RefID', varInstitutionBranchID::bigint,'sysBaseCurrency_RefID',varBaseCurrencyID::bigint,'name', 'President Director'::varchar)))::varchar;
B16: Finance Director | D16: =D15 + IF(EXACT(E16, ""), 0, 1) -> 95000000000010 | E16: =IF(EXACT(B16, ""), "", CONCATENATE("PERFORM ""SchSysConfig"".""Func_TblAppObject_UserRole_SET""(varSystemLoginSession, null::bigint, null::varchar, null::timestamptz, null::timestamptz, null::varchar, varInstitutionBranchID, varBaseCurrencyID, ", (IF(EXACT(B16, ""), "NULL", CONCATENATE("'", B16, "'"))),"::varchar);")) -> PERFORM "SchSysConfig"."Func_TblAppObject_UserRole_SET"(varSystemLoginSession, null::bigint, null::varchar, null::timestamptz, null::timestamptz, null::varchar, varInstitutionBranchID, varBaseCurrencyID, 'Finance Director'::varchar); | G16: =IF(EXACT($E16, ""), "", CONCATENATE( "varSQL := varSQL || (CASE WHEN (varSQL = '') THEN '' ELSE ', ' END) || (SELECT JSON_BUILD_OBJECT (", "'recordID', NULL::bigint,", "'entities', ", "JSON_BUILD_OBJECT (", "'sysLoginSession_RefID', varSystemLoginSession::bigint,", "'sysDataAnnotation', NULL::varchar,", "'sysDataSetDateTimeTZ', NULL::timestamptz,", "'sysDataValidityStartDateTimeTZ', NULL::timestamptz,", "'sysDataValidityFinishDateTimeTZ', NULL::timestamptz,", "'sysPartitionRemovableRecordKey_RefID', NULL::bigint,", "'sysBranch_RefID', varInstitutionBranchID::bigint,", "'sysBaseCurrency_RefID',varBaseCurrencyID::bigint,", "'name', ", IF(EXACT($B16, ""), "null", CONCATENATE("'", SUBSTITUTE($B16, "'", "\'"), "'")), "::varchar", ")))::varchar;")) -> varSQL := varSQL || (CASE WHEN (varSQL = '') THEN '' ELSE ', ' END) || (SELECT JSON_BUILD_OBJECT ('recordID', NULL::bigint,'entities', JSON_BUILD_OBJECT ('sysLoginSession_RefID', varSystemLoginSession::bigint,'sysDataAnnotation', NULL::varchar,'sysDataSetDateTimeTZ', NULL::timestamptz,'sysDataValidityStartDateTimeTZ', NULL::timestamptz,'sysDataValidityFinishDateTimeTZ', NULL::timestamptz,'sysPartitionRemovableRecordKey_RefID', NULL::bigint,'sysBranch_RefID', varInstitutionBranchID::bigint,'sysBaseCurrency_RefID',varBaseCurrencyID::bigint,'name', 'Finance Director'::varchar)))::varchar;
B17: Operational Director | D17: =D16 + IF(EXACT(E17, ""), 0, 1) -> 95000000000011 | E17: =IF(EXACT(B17, ""), "", CONCATENATE("PERFORM ""SchSysConfig"".""Func_TblAppObject_UserRole_SET""(varSystemLoginSession, null::bigint, null::varchar, null::timestamptz, null::timestamptz, null::varchar, varInstitutionBranchID, varBaseCurrencyID, ", (IF(EXACT(B17, ""), "NULL", CONCATENATE("'", B17, "'"))),"::varchar);")) -> PERFORM "SchSysConfig"."Func_TblAppObject_UserRole_SET"(varSystemLoginSession, null::bigint, null::varchar, null::timestamptz, null::timestamptz, null::varchar, varInstitutionBranchID, varBaseCurrencyID, 'Operational Director'::varchar); | G17: =IF(EXACT($E17, ""), "", CONCATENATE( "varSQL := varSQL || (CASE WHEN (varSQL = '') THEN '' ELSE ', ' END) || (SELECT JSON_BUILD_OBJECT (", "'recordID', NULL::bigint,", "'entities', ", "JSON_BUILD_OBJECT (", "'sysLoginSession_RefID', varSystemLoginSession::bigint,", "'sysDataAnnotation', NULL::varchar,", "'sysDataSetDateTimeTZ', NULL::timestamptz,", "'sysDataValidityStartDateTimeTZ', NULL::timestamptz,", "'sysDataValidityFinishDateTimeTZ', NULL::timestamptz,", "'sysPartitionRemovableRecordKey_RefID', NULL::bigint,", "'sysBranch_RefID', varInstitutionBranchID::bigint,", "'sysBaseCurrency_RefID',varBaseCurrencyID::bigint,", "'name', ", IF(EXACT($B17, ""), "null", CONCATENATE("'", SUBSTITUTE($B17, "'", "\'"), "'")), "::varchar", ")))::varchar;")) -> varSQL := varSQL || (CASE WHEN (varSQL = '') THEN '' ELSE ', ' END) || (SELECT JSON_BUILD_OBJECT ('recordID', NULL::bigint,'entities', JSON_BUILD_OBJECT ('sysLoginSession_RefID', varSystemLoginSession::bigint,'sysDataAnnotation', NULL::varchar,'sysDataSetDateTimeTZ', NULL::timestamptz,'sysDataValidityStartDateTimeTZ', NULL::timestamptz,'sysDataValidityFinishDateTimeTZ', NULL::timestamptz,'sysPartitionRemovableRecordKey_RefID', NULL::bigint,'sysBranch_RefID', varInstitutionBranchID::bigint,'sysBaseCurrency_RefID',varBaseCurrencyID::bigint,'name', 'Operational Director'::varchar)))::varchar;
B18: Marketing Director | D18: =D17 + IF(EXACT(E18, ""), 0, 1) -> 95000000000012 | E18: =IF(EXACT(B18, ""), "", CONCATENATE("PERFORM ""SchSysConfig"".""Func_TblAppObject_UserRole_SET""(varSystemLoginSession, null::bigint, null::varchar, null::timestamptz, null::timestamptz, null::varchar, varInstitutionBranchID, varBaseCurrencyID, ", (IF(EXACT(B18, ""), "NULL", CONCATENATE("'", B18, "'"))),"::varchar);")) -> PERFORM "SchSysConfig"."Func_TblAppObject_UserRole_SET"(varSystemLoginSession, null::bigint, null::varchar, null::timestamptz, null::timestamptz, null::varchar, varInstitutionBranchID, varBaseCurrencyID, 'Marketing Director'::varchar); | G18: =IF(EXACT($E18, ""), "", CONCATENATE( "varSQL := varSQL || (CASE WHEN (varSQL = '') THEN '' ELSE ', ' END) || (SELECT JSON_BUILD_OBJECT (", "'recordID', NULL::bigint,", "'entities', ", "JSON_BUILD_OBJECT (", "'sysLoginSession_RefID', varSystemLoginSession::bigint,", "'sysDataAnnotation', NULL::varchar,", "'sysDataSetDateTimeTZ', NULL::timestamptz,", "'sysDataValidityStartDateTimeTZ', NULL::timestamptz,", "'sysDataValidityFinishDateTimeTZ', NULL::timestamptz,", "'sysPartitionRemovableRecordKey_RefID', NULL::bigint,", "'sysBranch_RefID', varInstitutionBranchID::bigint,", "'sysBaseCurrency_RefID',varBaseCurrencyID::bigint,", "'name', ", IF(EXACT($B18, ""), "null", CONCATENATE("'", SUBSTITUTE($B18, "'", "\'"), "'")), "::varchar", ")))::varchar;")) -> varSQL := varSQL || (CASE WHEN (varSQL = '') THEN '' ELSE ', ' END) || (SELECT JSON_BUILD_OBJECT ('recordID', NULL::bigint,'entities', JSON_BUILD_OBJECT ('sysLoginSession_RefID', varSystemLoginSession::bigint,'sysDataAnnotation', NULL::varchar,'sysDataSetDateTimeTZ', NULL::timestamptz,'sysDataValidityStartDateTimeTZ', NULL::timestamptz,'sysDataValidityFinishDateTimeTZ', NULL::timestamptz,'sysPartitionRemovableRecordKey_RefID', NULL::bigint,'sysBranch_RefID', varInstitutionBranchID::bigint,'sysBaseCurrency_RefID',varBaseCurrencyID::bigint,'name', 'Marketing Director'::varchar)))::varchar;
B19: Information Technology Director | D19: =D18 + IF(EXACT(E19, ""), 0, 1) -> 95000000000013 | E19: =IF(EXACT(B19, ""), "", CONCATENATE("PERFORM ""SchSysConfig"".""Func_TblAppObject_UserRole_SET""(varSystemLoginSession, null::bigint, null::varchar, null::timestamptz, null::timestamptz, null::varchar, varInstitutionBranchID, varBaseCurrencyID, ", (IF(EXACT(B19, ""), "NULL", CONCATENATE("'", B19, "'"))),"::varchar);")) -> PERFORM "SchSysConfig"."Func_TblAppObject_UserRole_SET"(varSystemLoginSession, null::bigint, null::varchar, null::timestamptz, null::timestamptz, null::varchar, varInstitutionBranchID, varBaseCurrencyID, 'Information Technology Director'::varchar); | G19: =IF(EXACT($E19, ""), "", CONCATENATE( "varSQL := varSQL || (CASE WHEN (varSQL = '') THEN '' ELSE ', ' END) || (SELECT JSON_BUILD_OBJECT (", "'recordID', NULL::bigint,", "'entities', ", "JSON_BUILD_OBJECT (", "'sysLoginSession_RefID', varSystemLoginSession::bigint,", "'sysDataAnnotation', NULL::varchar,", "'sysDataSetDateTimeTZ', NULL::timestamptz,", "'sysDataValidityStartDateTimeTZ', NULL::timestamptz,", "'sysDataValidityFinishDateTimeTZ', NULL::timestamptz,", "'sysPartitionRemovableRecordKey_RefID', NULL::bigint,", "'sysBranch_RefID', varInstitutionBranchID::bigint,", "'sysBaseCurrency_RefID',varBaseCurrencyID::bigint,", "'name', ", IF(EXACT($B19, ""), "null", CONCATENATE("'", SUBSTITUTE($B19, "'", "\'"), "'")), "::varchar", ")))::varchar;")) -> varSQL := varSQL || (CASE WHEN (varSQL = '') THEN '' ELSE ', ' END) || (SELECT JSON_BUILD_OBJECT ('recordID', NULL::bigint,'entities', JSON_BUILD_OBJECT ('sysLoginSession_RefID', varSystemLoginSession::bigint,'sysDataAnnotation', NULL::varchar,'sysDataSetDateTimeTZ', NULL::timestamptz,'sysDataValidityStartDateTimeTZ', NULL::timestamptz,'sysDataValidityFinishDateTimeTZ', NULL::timestamptz,'sysPartitionRemovableRecordKey_RefID', NULL::bigint,'sysBranch_RefID', varInstitutionBranchID::bigint,'sysBaseCurrency_RefID',varBaseCurrencyID::bigint,'name', 'Information Technology Director'::varchar)))::varchar;
D20: =D19 + IF(EXACT(E20, ""), 0, 1) -> 95000000000013 | E20: =IF(EXACT(B20, ""), "", CONCATENATE("PERFORM ""SchSysConfig"".""Func_TblAppObject_UserRole_SET""(varSystemLoginSession, null::bigint, null::varchar, null::timestamptz, null::timestamptz, null::varchar, varInstitutionBranchID, varBaseCurrencyID, ", (IF(EXACT(B20, ""), "NULL", CONCATENATE("'", B20, "'"))),"::varchar);")) | G20: =IF(EXACT($E20, ""), "", CONCATENATE( "varSQL := varSQL || (CASE WHEN (varSQL = '') THEN '' ELSE ', ' END) || (SELECT JSON_BUILD_OBJECT (", "'recordID', NULL::bigint,", "'entities', ", "JSON_BUILD_OBJECT (", "'sysLoginSession_RefID', varSystemLoginSession::bigint,", "'sysDataAnnotation', NULL::varchar,", "'sysDataSetDateTimeTZ', NULL::timestamptz,", "'sysDataValidityStartDateTimeTZ', NULL::timestamptz,", "'sysDataValidityFinishDateTimeTZ', NULL::timestamptz,", "'sysPartitionRemovableRecordKey_RefID', NULL::bigint,", "'sysBranch_RefID', varInstitutionBranchID::bigint,", "'sysBaseCurrency_RefID',varBaseCurrencyID::bigint,", "'name', ", IF(EXACT($B20, ""), "null", CONCATENATE("'", SUBSTITUTE($B20, "'", "\'"), "'")), "::varchar", ")))::varchar;"))
B21: Project General Manager | D21: =D20 + IF(EXACT(E21, ""), 0, 1) -> 95000000000014 | E21: =IF(EXACT(B21, ""), "", CONCATENATE("PERFORM ""SchSysConfig"".""Func_TblAppObject_UserRole_SET""(varSystemLoginSession, null::bigint, null::varchar, null::timestamptz, null::timestamptz, null::varchar, varInstitutionBranchID, varBaseCurrencyID, ", (IF(EXACT(B21, ""), "NULL", CONCATENATE("'", B21, "'"))),"::varchar);")) -> PERFORM "SchSysConfig"."Func_TblAppObject_UserRole_SET"(varSystemLoginSession, null::bigint, null::varchar, null::timestamptz, null::timestamptz, null::varchar, varInstitutionBranchID, varBaseCurrencyID, 'Project General Manager'::varchar); | G21: =IF(EXACT($E21, ""), "", CONCATENATE( "varSQL := varSQL || (CASE WHEN (varSQL = '') THEN '' ELSE ', ' END) || (SELECT JSON_BUILD_OBJECT (", "'recordID', NULL::bigint,", "'entities', ", "JSON_BUILD_OBJECT (", "'sysLoginSession_RefID', varSystemLoginSession::bigint,", "'sysDataAnnotation', NULL::varchar,", "'sysDataSetDateTimeTZ', NULL::timestamptz,", "'sysDataValidityStartDateTimeTZ', NULL::timestamptz,", "'sysDataValidityFinishDateTimeTZ', NULL::timestamptz,", "'sysPartitionRemovableRecordKey_RefID', NULL::bigint,", "'sysBranch_RefID', varInstitutionBranchID::bigint,", "'sysBaseCurrency_RefID',varBaseCurrencyID::bigint,", "'name', ", IF(EXACT($B21, ""), "null", CONCATENATE("'", SUBSTITUTE($B21, "'", "\'"), "'")), "::varchar", ")))::varchar;")) -> varSQL := varSQL || (CASE WHEN (varSQL = '') THEN '' ELSE ', ' END) || (SELECT JSON_BUILD_OBJECT ('recordID', NULL::bigint,'entities', JSON_BUILD_OBJECT ('sysLoginSession_RefID', varSystemLoginSession::bigint,'sysDataAnnotation', NULL::varchar,'sysDataSetDateTimeTZ', NULL::timestamptz,'sysDataValidityStartDateTimeTZ', NULL::timestamptz,'sysDataValidityFinishDateTimeTZ', NULL::timestamptz,'sysPartitionRemovableRecordKey_RefID', NULL::bigint,'sysBranch_RefID', varInstitutionBranchID::bigint,'sysBaseCurrency_RefID',varBaseCurrencyID::bigint,'name', 'Project General Manager'::varchar)))::varchar;
B22: Project Management Officer | D22: =D21 + IF(EXACT(E22, ""), 0, 1) -> 95000000000015 | E22: =IF(EXACT(B22, ""), "", CONCATENATE("PERFORM ""SchSysConfig"".""Func_TblAppObject_UserRole_SET""(varSystemLoginSession, null::bigint, null::varchar, null::timestamptz, null::timestamptz, null::varchar, varInstitutionBranchID, varBaseCurrencyID, ", (IF(EXACT(B22, ""), "NULL", CONCATENATE("'", B22, "'"))),"::varchar);")) -> PERFORM "SchSysConfig"."Func_TblAppObject_UserRole_SET"(varSystemLoginSession, null::bigint, null::varchar, null::timestamptz, null::timestamptz, null::varchar, varInstitutionBranchID, varBaseCurrencyID, 'Project Management Officer'::varchar); | G22: =IF(EXACT($E22, ""), "", CONCATENATE( "varSQL := varSQL || (CASE WHEN (varSQL = '') THEN '' ELSE ', ' END) || (SELECT JSON_BUILD_OBJECT (", "'recordID', NULL::bigint,", "'entities', ", "JSON_BUILD_OBJECT (", "'sysLoginSession_RefID', varSystemLoginSession::bigint,", "'sysDataAnnotation', NULL::varchar,", "'sysDataSetDateTimeTZ', NULL::timestamptz,", "'sysDataValidityStartDateTimeTZ', NULL::timestamptz,", "'sysDataValidityFinishDateTimeTZ', NULL::timestamptz,", "'sysPartitionRemovableRecordKey_RefID', NULL::bigint,", "'sysBranch_RefID', varInstitutionBranchID::bigint,", "'sysBaseCurrency_RefID',varBaseCurrencyID::bigint,", "'name', ", IF(EXACT($B22, ""), "null", CONCATENATE("'", SUBSTITUTE($B22, "'", "\'"), "'")), "::varchar", ")))::varchar;")) -> varSQL := varSQL || (CASE WHEN (varSQL = '') THEN '' ELSE ', ' END) || (SELECT JSON_BUILD_OBJECT ('recordID', NULL::bigint,'entities', JSON_BUILD_OBJECT ('sysLoginSession_RefID', varSystemLoginSession::bigint,'sysDataAnnotation', NULL::varchar,'sysDataSetDateTimeTZ', NULL::timestamptz,'sysDataValidityStartDateTimeTZ', NULL::timestamptz,'sysDataValidityFinishDateTimeTZ', NULL::timestamptz,'sysPartitionRemovableRecordKey_RefID', NULL::bigint,'sysBranch_RefID', varInstitutionBranchID::bigint,'sysBaseCurrency_RefID',varBaseCurrencyID::bigint,'name', 'Project Management Officer'::varchar)))::varchar;
B23: Finance, Accounting, & Tax General Manager | D23: =D22 + IF(EXACT(E23, ""), 0, 1) -> 95000000000016 | E23: =IF(EXACT(B23, ""), "", CONCATENATE("PERFORM ""SchSysConfig"".""Func_TblAppObject_UserRole_SET""(varSystemLoginSession, null::bigint, null::varchar, null::timestamptz, null::timestamptz, null::varchar, varInstitutionBranchID, varBaseCurrencyID, ", (IF(EXACT(B23, ""), "NULL", CONCATENATE("'", B23, "'"))),"::varchar);")) -> PERFORM "SchSysConfig"."Func_TblAppObject_UserRole_SET"(varSystemLoginSession, null::bigint, null::varchar, null::timestamptz, null::timestamptz, null::varchar, varInstitutionBranchID, varBaseCurrencyID, 'Finance, Accounting, & Tax General Manager'::varchar); | G23: =IF(EXACT($E23, ""), "", CONCATENATE( "varSQL := varSQL || (CASE WHEN (varSQL = '') THEN '' ELSE ', ' END) || (SELECT JSON_BUILD_OBJECT (", "'recordID', NULL::bigint,", "'entities', ", "JSON_BUILD_OBJECT (", "'sysLoginSession_RefID', varSystemLoginSession::bigint,", "'sysDataAnnotation', NULL::varchar,", "'sysDataSetDateTimeTZ', NULL::timestamptz,", "'sysDataValidityStartDateTimeTZ', NULL::timestamptz,", "'sysDataValidityFinishDateTimeTZ', NULL::timestamptz,", "'sysPartitionRemovableRecordKey_RefID', NULL::bigint,", "'sysBranch_RefID', varInstitutionBranchID::bigint,", "'sysBaseCurrency_RefID',varBaseCurrencyID::bigint,", "'name', ", IF(EXACT($B23, ""), "null", CONCATENATE("'", SUBSTITUTE($B23, "'", "\'"), "'")), "::varchar", ")))::varchar;")) -> varSQL := varSQL || (CASE WHEN (varSQL = '') THEN '' ELSE ', ' END) || (SELECT JSON_BUILD_OBJECT ('recordID', NULL::bigint,'entities', JSON_BUILD_OBJECT ('sysLoginSession_RefID', varSystemLoginSession::bigint,'sysDataAnnotation', NULL::varchar,'sysDataSetDateTimeTZ', NULL::timestamptz,'sysDataValidityStartDateTimeTZ', NULL::timestamptz,'sysDataValidityFinishDateTimeTZ', NULL::timestamptz,'sysPartitionRemovableRecordKey_RefID', NULL::bigint,'sysBranch_RefID', varInstitutionBranchID::bigint,'sysBaseCurrency_RefID',varBaseCurrencyID::bigint,'name', 'Finance, Accounting, & Tax General Manager'::varchar)))::varchar;
B24: HR, GA, & TAM General Manager | D24: =D23 + IF(EXACT(E24, ""), 0, 1) -> 95000000000017 | E24: =IF(EXACT(B24, ""), "", CONCATENATE("PERFORM ""SchSysConfig"".""Func_TblAppObject_UserRole_SET""(varSystemLoginSession, null::bigint, null::varchar, null::timestamptz, null::timestamptz, null::varchar, varInstitutionBranchID, varBaseCurrencyID, ", (IF(EXACT(B24, ""), "NULL", CONCATENATE("'", B24, "'"))),"::varchar);")) -> PERFORM "SchSysConfig"."Func_TblAppObject_UserRole_SET"(varSystemLoginSession, null::bigint, null::varchar, null::timestamptz, null::timestamptz, null::varchar, varInstitutionBranchID, varBaseCurrencyID, 'HR, GA, & TAM General Manager'::varchar); | G24: =IF(EXACT($E24, ""), "", CONCATENATE( "varSQL := varSQL || (CASE WHEN (varSQL = '') THEN '' ELSE ', ' END) || (SELECT JSON_BUILD_OBJECT (", "'recordID', NULL::bigint,", "'entities', ", "JSON_BUILD_OBJECT (", "'sysLoginSession_RefID', varSystemLoginSession::bigint,", "'sysDataAnnotation', NULL::varchar,", "'sysDataSetDateTimeTZ', NULL::timestamptz,", "'sysDataValidityStartDateTimeTZ', NULL::timestamptz,", "'sysDataValidityFinishDateTimeTZ', NULL::timestamptz,", "'sysPartitionRemovableRecordKey_RefID', NULL::bigint,", "'sysBranch_RefID', varInstitutionBranchID::bigint,", "'sysBaseCurrency_RefID',varBaseCurrencyID::bigint,", "'name', ", IF(EXACT($B24, ""), "null", CONCATENATE("'", SUBSTITUTE($B24, "'", "\'"), "'")), "::varchar", ")))::varchar;")) -> varSQL := varSQL || (CASE WHEN (varSQL = '') THEN '' ELSE ', ' END) || (SELECT JSON_BUILD_OBJECT ('recordID', NULL::bigint,'entities', JSON_BUILD_OBJECT ('sysLoginSession_RefID', varSystemLoginSession::bigint,'sysDataAnnotation', NULL::varchar,'sysDataSetDateTimeTZ', NULL::timestamptz,'sysDataValidityStartDateTimeTZ', NULL::timestamptz,'sysDataValidityFinishDateTimeTZ', NULL::timestamptz,'sysPartitionRemovableRecordKey_RefID', NULL::bigint,'sysBranch_RefID', varInstitutionBranchID::bigint,'sysBaseCurrency_RefID',varBaseCurrencyID::bigint,'name', 'HR, GA, & TAM General Manager'::varchar)))::varchar;
B25: Sales General Manager | D25: =D24 + IF(EXACT(E25, ""), 0, 1) -> 95000000000018 | E25: =IF(EXACT(B25, ""), "", CONCATENATE("PERFORM ""SchSysConfig"".""Func_TblAppObject_UserRole_SET""(varSystemLoginSession, null::bigint, null::varchar, null::timestamptz, null::timestamptz, null::varchar, varInstitutionBranchID, varBaseCurrencyID, ", (IF(EXACT(B25, ""), "NULL", CONCATENATE("'", B25, "'"))),"::varchar);")) -> PERFORM "SchSysConfig"."Func_TblAppObject_UserRole_SET"(varSystemLoginSession, null::bigint, null::varchar, null::timestamptz, null::timestamptz, null::varchar, varInstitutionBranchID, varBaseCurrencyID, 'Sales General Manager'::varchar); | G25: =IF(EXACT($E25, ""), "", CONCATENATE( "varSQL := varSQL || (CASE WHEN (varSQL = '') THEN '' ELSE ', ' END) || (SELECT JSON_BUILD_OBJECT (", "'recordID', NULL::bigint,", "'entities', ", "JSON_BUILD_OBJECT (", "'sysLoginSession_RefID', varSystemLoginSession::bigint,", "'sysDataAnnotation', NULL::varchar,", "'sysDataSetDateTimeTZ', NULL::timestamptz,", "'sysDataValidityStartDateTimeTZ', NULL::timestamptz,", "'sysDataValidityFinishDateTimeTZ', NULL::timestamptz,", "'sysPartitionRemovableRecordKey_RefID', NULL::bigint,", "'sysBranch_RefID', varInstitutionBranchID::bigint,", "'sysBaseCurrency_RefID',varBaseCurrencyID::bigint,", "'name', ", IF(EXACT($B25, ""), "null", CONCATENATE("'", SUBSTITUTE($B25, "'", "\'"), "'")), "::varchar", ")))::varchar;")) -> varSQL := varSQL || (CASE WHEN (varSQL = '') THEN '' ELSE ', ' END) || (SELECT JSON_BUILD_OBJECT ('recordID', NULL::bigint,'entities', JSON_BUILD_OBJECT ('sysLoginSession_RefID', varSystemLoginSession::bigint,'sysDataAnnotation', NULL::varchar,'sysDataSetDateTimeTZ', NULL::timestamptz,'sysDataValidityStartDateTimeTZ', NULL::timestamptz,'sysDataValidityFinishDateTimeTZ', NULL::timestamptz,'sysPartitionRemovableRecordKey_RefID', NULL::bigint,'sysBranch_RefID', varInstitutionBranchID::bigint,'sysBaseCurrency_RefID',varBaseCurrencyID::bigint,'name', 'Sales General Manager'::varchar)))::varchar;
D26: =D25 + IF(EXACT(E26, ""), 0, 1) -> 95000000000018 | E26: =IF(EXACT(B26, ""), "", CONCATENATE("PERFORM ""SchSysConfig"".""Func_TblAppObject_UserRole_SET""(varSystemLoginSession, null::bigint, null::varchar, null::timestamptz, null::timestamptz, null::varchar, varInstitutionBranchID, varBaseCurrencyID, ", (IF(EXACT(B26, ""), "NULL", CONCATENATE("'", B26, "'"))),"::varchar);")) | G26: =IF(EXACT($E26, ""), "", CONCATENATE( "varSQL := varSQL || (CASE WHEN (varSQL = '') THEN '' ELSE ', ' END) || (SELECT JSON_BUILD_OBJECT (", "'recordID', NULL::bigint,", "'entities', ", "JSON_BUILD_OBJECT (", "'sysLoginSession_RefID', varSystemLoginSession::bigint,", "'sysDataAnnotation', NULL::varchar,", "'sysDataSetDateTimeTZ', NULL::timestamptz,", "'sysDataValidityStartDateTimeTZ', NULL::timestamptz,", "'sysDataValidityFinishDateTimeTZ', NULL::timestamptz,", "'sysPartitionRemovableRecordKey_RefID', NULL::bigint,", "'sysBranch_RefID', varInstitutionBranchID::bigint,", "'sysBaseCurrency_RefID',varBaseCurrencyID::bigint,", "'name', ", IF(EXACT($B26, ""), "null", CONCATENATE("'", SUBSTITUTE($B26, "'", "\'"), "'")), "::varchar", ")))::varchar;"))
B27: Project Manager | D27: =D26 + IF(EXACT(E27, ""), 0, 1) -> 95000000000019 | E27: =IF(EXACT(B27, ""), "", CONCATENATE("PERFORM ""SchSysConfig"".""Func_TblAppObject_UserRole_SET""(varSystemLoginSession, null::bigint, null::varchar, null::timestamptz, null::timestamptz, null::varchar, varInstitutionBranchID, varBaseCurrencyID, ", (IF(EXACT(B27, ""), "NULL", CONCATENATE("'", B27, "'"))),"::varchar);")) -> PERFORM "SchSysConfig"."Func_TblAppObject_UserRole_SET"(varSystemLoginSession, null::bigint, null::varchar, null::timestamptz, null::timestamptz, null::varchar, varInstitutionBranchID, varBaseCurrencyID, 'Project Manager'::varchar); | G27: =IF(EXACT($E27, ""), "", CONCATENATE( "varSQL := varSQL || (CASE WHEN (varSQL = '') THEN '' ELSE ', ' END) || (SELECT JSON_BUILD_OBJECT (", "'recordID', NULL::bigint,", "'entities', ", "JSON_BUILD_OBJECT (", "'sysLoginSession_RefID', varSystemLoginSession::bigint,", "'sysDataAnnotation', NULL::varchar,", "'sysDataSetDateTimeTZ', NULL::timestamptz,", "'sysDataValidityStartDateTimeTZ', NULL::timestamptz,", "'sysDataValidityFinishDateTimeTZ', NULL::timestamptz,", "'sysPartitionRemovableRecordKey_RefID', NULL::bigint,", "'sysBranch_RefID', varInstitutionBranchID::bigint,", "'sysBaseCurrency_RefID',varBaseCurrencyID::bigint,", "'name', ", IF(EXACT($B27, ""), "null", CONCATENATE("'", SUBSTITUTE($B27, "'", "\'"), "'")), "::varchar", ")))::varchar;")) -> varSQL := varSQL || (CASE WHEN (varSQL = '') THEN '' ELSE ', ' END) || (SELECT JSON_BUILD_OBJECT ('recordID', NULL::bigint,'entities', JSON_BUILD_OBJECT ('sysLoginSession_RefID', varSystemLoginSession::bigint,'sysDataAnnotation', NULL::varchar,'sysDataSetDateTimeTZ', NULL::timestamptz,'sysDataValidityStartDateTimeTZ', NULL::timestamptz,'sysDataValidityFinishDateTimeTZ', NULL::timestamptz,'sysPartitionRemovableRecordKey_RefID', NULL::bigint,'sysBranch_RefID', varInstitutionBranchID::bigint,'sysBaseCurrency_RefID',varBaseCurrencyID::bigint,'name', 'Project Manager'::varchar)))::varchar;
B28: Site Manager | D28: =D27 + IF(EXACT(E28, ""), 0, 1) -> 95000000000020 | E28: =IF(EXACT(B28, ""), "", CONCATENATE("PERFORM ""SchSysConfig"".""Func_TblAppObject_UserRole_SET""(varSystemLoginSession, null::bigint, null::varchar, null::timestamptz, null::timestamptz, null::varchar, varInstitutionBranchID, varBaseCurrencyID, ", (IF(EXACT(B28, ""), "NULL", CONCATENATE("'", B28, "'"))),"::varchar);")) -> PERFORM "SchSysConfig"."Func_TblAppObject_UserRole_SET"(varSystemLoginSession, null::bigint, null::varchar, null::timestamptz, null::timestamptz, null::varchar, varInstitutionBranchID, varBaseCurrencyID, 'Site Manager'::varchar); | G28: =IF(EXACT($E28, ""), "", CONCATENATE( "varSQL := varSQL || (CASE WHEN (varSQL = '') THEN '' ELSE ', ' END) || (SELECT JSON_BUILD_OBJECT (", "'recordID', NULL::bigint,", "'entities', ", "JSON_BUILD_OBJECT (", "'sysLoginSession_RefID', varSystemLoginSession::bigint,", "'sysDataAnnotation', NULL::varchar,", "'sysDataSetDateTimeTZ', NULL::timestamptz,", "'sysDataValidityStartDateTimeTZ', NULL::timestamptz,", "'sysDataValidityFinishDateTimeTZ', NULL::timestamptz,", "'sysPartitionRemovableRecordKey_RefID', NULL::bigint,", "'sysBranch_RefID', varInstitutionBranchID::bigint,", "'sysBaseCurrency_RefID',varBaseCurrencyID::bigint,", "'name', ", IF(EXACT($B28, ""), "null", CONCATENATE("'", SUBSTITUTE($B28, "'", "\'"), "'")), "::varchar", ")))::varchar;")) -> varSQL := varSQL || (CASE WHEN (varSQL = '') THEN '' ELSE ', ' END) || (SELECT JSON_BUILD_OBJECT ('recordID', NULL::bigint,'entities', JSON_BUILD_OBJECT ('sysLoginSession_RefID', varSystemLoginSession::bigint,'sysDataAnnotation', NULL::varchar,'sysDataSetDateTimeTZ', NULL::timestamptz,'sysDataValidityStartDateTimeTZ', NULL::timestamptz,'sysDataValidityFinishDateTimeTZ', NULL::timestamptz,'sysPartitionRemovableRecordKey_RefID', NULL::bigint,'sysBranch_RefID', varInstitutionBranchID::bigint,'sysBaseCurrency_RefID',varBaseCurrencyID::bigint,'name', 'Site Manager'::varchar)))::varchar;
B29: Project Controller Coordinator | D29: =D28 + IF(EXACT(E29, ""), 0, 1) -> 95000000000021 | E29: =IF(EXACT(B29, ""), "", CONCATENATE("PERFORM ""SchSysConfig"".""Func_TblAppObject_UserRole_SET""(varSystemLoginSession, null::bigint, null::varchar, null::timestamptz, null::timestamptz, null::varchar, varInstitutionBranchID, varBaseCurrencyID, ", (IF(EXACT(B29, ""), "NULL", CONCATENATE("'", B29, "'"))),"::varchar);")) -> PERFORM "SchSysConfig"."Func_TblAppObject_UserRole_SET"(varSystemLoginSession, null::bigint, null::varchar, null::timestamptz, null::timestamptz, null::varchar, varInstitutionBranchID, varBaseCurrencyID, 'Project Controller Coordinator'::varchar); | G29: =IF(EXACT($E29, ""), "", CONCATENATE( "varSQL := varSQL || (CASE WHEN (varSQL = '') THEN '' ELSE ', ' END) || (SELECT JSON_BUILD_OBJECT (", "'recordID', NULL::bigint,", "'entities', ", "JSON_BUILD_OBJECT (", "'sysLoginSession_RefID', varSystemLoginSession::bigint,", "'sysDataAnnotation', NULL::varchar,", "'sysDataSetDateTimeTZ', NULL::timestamptz,", "'sysDataValidityStartDateTimeTZ', NULL::timestamptz,", "'sysDataValidityFinishDateTimeTZ', NULL::timestamptz,", "'sysPartitionRemovableRecordKey_RefID', NULL::bigint,", "'sysBranch_RefID', varInstitutionBranchID::bigint,", "'sysBaseCurrency_RefID',varBaseCurrencyID::bigint,", "'name', ", IF(EXACT($B29, ""), "null", CONCATENATE("'", SUBSTITUTE($B29, "'", "\'"), "'")), "::varchar", ")))::varchar;")) -> varSQL := varSQL || (CASE WHEN (varSQL = '') THEN '' ELSE ', ' END) || (SELECT JSON_BUILD_OBJECT ('recordID', NULL::bigint,'entities', JSON_BUILD_OBJECT ('sysLoginSession_RefID', varSystemLoginSession::bigint,'sysDataAnnotation', NULL::varchar,'sysDataSetDateTimeTZ', NULL::timestamptz,'sysDataValidityStartDateTimeTZ', NULL::timestamptz,'sysDataValidityFinishDateTimeTZ', NULL::timestamptz,'sysPartitionRemovableRecordKey_RefID', NULL::bigint,'sysBranch_RefID', varInstitutionBranchID::bigint,'sysBaseCurrency_RefID',varBaseCurrencyID::bigint,'name', 'Project Controller Coordinator'::varchar)))::varchar;
B30: Project Controller Staff | D30: =D29 + IF(EXACT(E30, ""), 0, 1) -> 95000000000022 | E30: =IF(EXACT(B30, ""), "", CONCATENATE("PERFORM ""SchSysConfig"".""Func_TblAppObject_UserRole_SET""(varSystemLoginSession, null::bigint, null::varchar, null::timestamptz, null::timestamptz, null::varchar, varInstitutionBranchID, varBaseCurrencyID, ", (IF(EXACT(B30, ""), "NULL", CONCATENATE("'", B30, "'"))),"::varchar);")) -> PERFORM "SchSysConfig"."Func_TblAppObject_UserRole_SET"(varSystemLoginSession, null::bigint, null::varchar, null::timestamptz, null::timestamptz, null::varchar, varInstitutionBranchID, varBaseCurrencyID, 'Project Controller Staff'::varchar); | G30: =IF(EXACT($E30, ""), "", CONCATENATE( "varSQL := varSQL || (CASE WHEN (varSQL = '') THEN '' ELSE ', ' END) || (SELECT JSON_BUILD_OBJECT (", "'recordID', NULL::bigint,", "'entities', ", "JSON_BUILD_OBJECT (", "'sysLoginSession_RefID', varSystemLoginSession::bigint,", "'sysDataAnnotation', NULL::varchar,", "'sysDataSetDateTimeTZ', NULL::timestamptz,", "'sysDataValidityStartDateTimeTZ', NULL::timestamptz,", "'sysDataValidityFinishDateTimeTZ', NULL::timestamptz,", "'sysPartitionRemovableRecordKey_RefID', NULL::bigint,", "'sysBranch_RefID', varInstitutionBranchID::bigint,", "'sysBaseCurrency_RefID',varBaseCurrencyID::bigint,", "'name', ", IF(EXACT($B30, ""), "null", CONCATENATE("'", SUBSTITUTE($B30, "'", "\'"), "'")), "::varchar", ")))::varchar;")) -> varSQL := varSQL || (CASE WHEN (varSQL = '') THEN '' ELSE ', ' END) || (SELECT JSON_BUILD_OBJECT ('recordID', NULL::bigint,'entities', JSON_BUILD_OBJECT ('sysLoginSession_RefID', varSystemLoginSession::bigint,'sysDataAnnotation', NULL::varchar,'sysDataSetDateTimeTZ', NULL::timestamptz,'sysDataValidityStartDateTimeTZ', NULL::timestamptz,'sysDataValidityFinishDateTimeTZ', NULL::timestamptz,'sysPartitionRemovableRecordKey_RefID', NULL::bigint,'sysBranch_RefID', varInstitutionBranchID::bigint,'sysBaseCurrency_RefID',varBaseCurrencyID::bigint,'name', 'Project Controller Staff'::varchar)))::varchar;
B31: Project Administrator Coordinator | D31: =D30 + IF(EXACT(E31, ""), 0, 1) -> 95000000000023 | E31: =IF(EXACT(B31, ""), "", CONCATENATE("PERFORM ""SchSysConfig"".""Func_TblAppObject_UserRole_SET""(varSystemLoginSession, null::bigint, null::varchar, null::timestamptz, null::timestamptz, null::varchar, varInstitutionBranchID, varBaseCurrencyID, ", (IF(EXACT(B31, ""), "NULL", CONCATENATE("'", B31, "'"))),"::varchar);")) -> PERFORM "SchSysConfig"."Func_TblAppObject_UserRole_SET"(varSystemLoginSession, null::bigint, null::varchar, null::timestamptz, null::timestamptz, null::varchar, varInstitutionBranchID, varBaseCurrencyID, 'Project Administrator Coordinator'::varchar); | G31: =IF(EXACT($E31, ""), "", CONCATENATE( "varSQL := varSQL || (CASE WHEN (varSQL = '') THEN '' ELSE ', ' END) || (SELECT JSON_BUILD_OBJECT (", "'recordID', NULL::bigint,", "'entities', ", "JSON_BUILD_OBJECT (", "'sysLoginSession_RefID', varSystemLoginSession::bigint,", "'sysDataAnnotation', NULL::varchar,", "'sysDataSetDateTimeTZ', NULL::timestamptz,", "'sysDataValidityStartDateTimeTZ', NULL::timestamptz,", "'sysDataValidityFinishDateTimeTZ', NULL::timestamptz,", "'sysPartitionRemovableRecordKey_RefID', NULL::bigint,", "'sysBranch_RefID', varInstitutionBranchID::bigint,", "'sysBaseCurrency_RefID',varBaseCurrencyID::bigint,", "'name', ", IF(EXACT($B31, ""), "null", CONCATENATE("'", SUBSTITUTE($B31, "'", "\'"), "'")), "::varchar", ")))::varchar;")) -> varSQL := varSQL || (CASE WHEN (varSQL = '') THEN '' ELSE ', ' END) || (SELECT JSON_BUILD_OBJECT ('recordID', NULL::bigint,'entities', JSON_BUILD_OBJECT ('sysLoginSession_RefID', varSystemLoginSession::bigint,'sysDataAnnotation', NULL::varchar,'sysDataSetDateTimeTZ', NULL::timestamptz,'sysDataValidityStartDateTimeTZ', NULL::timestamptz,'sysDataValidityFinishDateTimeTZ', NULL::timestamptz,'sysPartitionRemovableRecordKey_RefID', NULL::bigint,'sysBranch_RefID', varInstitutionBranchID::bigint,'sysBaseCurrency_RefID',varBaseCurrencyID::bigint,'name', 'Project Administrator Coordinator'::varchar)))::varchar;
B32: Project Administrator Staff | D32: =D31 + IF(EXACT(E32, ""), 0, 1) -> 95000000000024 | E32: =IF(EXACT(B32, ""), "", CONCATENATE("PERFORM ""SchSysConfig"".""Func_TblAppObject_UserRole_SET""(varSystemLoginSession, null::bigint, null::varchar, null::timestamptz, null::timestamptz, null::varchar, varInstitutionBranchID, varBaseCurrencyID, ", (IF(EXACT(B32, ""), "NULL", CONCATENATE("'", B32, "'"))),"::varchar);")) -> PERFORM "SchSysConfig"."Func_TblAppObject_UserRole_SET"(varSystemLoginSession, null::bigint, null::varchar, null::timestamptz, null::timestamptz, null::varchar, varInstitutionBranchID, varBaseCurrencyID, 'Project Administrator Staff'::varchar); | G32: =IF(EXACT($E32, ""), "", CONCATENATE( "varSQL := varSQL || (CASE WHEN (varSQL = '') THEN '' ELSE ', ' END) || (SELECT JSON_BUILD_OBJECT (", "'recordID', NULL::bigint,", "'entities', ", "JSON_BUILD_OBJECT (", "'sysLoginSession_RefID', varSystemLoginSession::bigint,", "'sysDataAnnotation', NULL::varchar,", "'sysDataSetDateTimeTZ', NULL::timestamptz,", "'sysDataValidityStartDateTimeTZ', NULL::timestamptz,", "'sysDataValidityFinishDateTimeTZ', NULL::timestamptz,", "'sysPartitionRemovableRecordKey_RefID', NULL::bigint,", "'sysBranch_RefID', varInstitutionBranchID::bigint,", "'sysBaseCurrency_RefID',varBaseCurrencyID::bigint,", "'name', ", IF(EXACT($B32, ""), "null", CONCATENATE("'", SUBSTITUTE($B32, "'", "\'"), "'")), "::varchar", ")))::varchar;")) -> varSQL := varSQL || (CASE WHEN (varSQL = '') THEN '' ELSE ', ' END) || (SELECT JSON_BUILD_OBJECT ('recordID', NULL::bigint,'entities', JSON_BUILD_OBJECT ('sysLoginSession_RefID', varSystemLoginSession::bigint,'sysDataAnnotation', NULL::varchar,'sysDataSetDateTimeTZ', NULL::timestamptz,'sysDataValidityStartDateTimeTZ', NULL::timestamptz,'sysDataValidityFinishDateTimeTZ', NULL::timestamptz,'sysPartitionRemovableRecordKey_RefID', NULL::bigint,'sysBranch_RefID', varInstitutionBranchID::bigint,'sysBaseCurrency_RefID',varBaseCurrencyID::bigint,'name', 'Project Administrator Staff'::varchar)))::varchar;
B33: Project Worker Coordinator | D33: =D32 + IF(EXACT(E33, ""), 0, 1) -> 95000000000025 | E33: =IF(EXACT(B33, ""), "", CONCATENATE("PERFORM ""SchSysConfig"".""Func_TblAppObject_UserRole_SET""(varSystemLoginSession, null::bigint, null::varchar, null::timestamptz, null::timestamptz, null::varchar, varInstitutionBranchID, varBaseCurrencyID, ", (IF(EXACT(B33, ""), "NULL", CONCATENATE("'", B33, "'"))),"::varchar);")) -> PERFORM "SchSysConfig"."Func_TblAppObject_UserRole_SET"(varSystemLoginSession, null::bigint, null::varchar, null::timestamptz, null::timestamptz, null::varchar, varInstitutionBranchID, varBaseCurrencyID, 'Project Worker Coordinator'::varchar); | G33: =IF(EXACT($E33, ""), "", CONCATENATE( "varSQL := varSQL || (CASE WHEN (varSQL = '') THEN '' ELSE ', ' END) || (SELECT JSON_BUILD_OBJECT (", "'recordID', NULL::bigint,", "'entities', ", "JSON_BUILD_OBJECT (", "'sysLoginSession_RefID', varSystemLoginSession::bigint,", "'sysDataAnnotation', NULL::varchar,", "'sysDataSetDateTimeTZ', NULL::timestamptz,", "'sysDataValidityStartDateTimeTZ', NULL::timestamptz,", "'sysDataValidityFinishDateTimeTZ', NULL::timestamptz,", "'sysPartitionRemovableRecordKey_RefID', NULL::bigint,", "'sysBranch_RefID', varInstitutionBranchID::bigint,", "'sysBaseCurrency_RefID',varBaseCurrencyID::bigint,", "'name', ", IF(EXACT($B33, ""), "null", CONCATENATE("'", SUBSTITUTE($B33, "'", "\'"), "'")), "::varchar", ")))::varchar;")) -> varSQL := varSQL || (CASE WHEN (varSQL = '') THEN '' ELSE ', ' END) || (SELECT JSON_BUILD_OBJECT ('recordID', NULL::bigint,'entities', JSON_BUILD_OBJECT ('sysLoginSession_RefID', varSystemLoginSession::bigint,'sysDataAnnotation', NULL::varchar,'sysDataSetDateTimeTZ', NULL::timestamptz,'sysDataValidityStartDateTimeTZ', NULL::timestamptz,'sysDataValidityFinishDateTimeTZ', NULL::timestamptz,'sysPartitionRemovableRecordKey_RefID', NULL::bigint,'sysBranch_RefID', varInstitutionBranchID::bigint,'sysBaseCurrency_RefID',varBaseCurrencyID::bigint,'name', 'Project Worker Coordinator'::varchar)))::varchar;
B34: Project Worker Staff | D34: =D33 + IF(EXACT(E34, ""), 0, 1) -> 95000000000026 | E34: =IF(EXACT(B34, ""), "", CONCATENATE("PERFORM ""SchSysConfig"".""Func_TblAppObject_UserRole_SET""(varSystemLoginSession, null::bigint, null::varchar, null::timestamptz, null::timestamptz, null::varchar, varInstitutionBranchID, varBaseCurrencyID, ", (IF(EXACT(B34, ""), "NULL", CONCATENATE("'", B34, "'"))),"::varchar);")) -> PERFORM "SchSysConfig"."Func_TblAppObject_UserRole_SET"(varSystemLoginSession, null::bigint, null::varchar, null::timestamptz, null::timestamptz, null::varchar, varInstitutionBranchID, varBaseCurrencyID, 'Project Worker Staff'::varchar); | G34: =IF(EXACT($E34, ""), "", CONCATENATE( "varSQL := varSQL || (CASE WHEN (varSQL = '') THEN '' ELSE ', ' END) || (SELECT JSON_BUILD_OBJECT (", "'recordID', NULL::bigint,", "'entities', ", "JSON_BUILD_OBJECT (", "'sysLoginSession_RefID', varSystemLoginSession::bigint,", "'sysDataAnnotation', NULL::varchar,", "'sysDataSetDateTimeTZ', NULL::timestamptz,", "'sysDataValidityStartDateTimeTZ', NULL::timestamptz,", "'sysDataValidityFinishDateTimeTZ', NULL::timestamptz,", "'sysPartitionRemovableRecordKey_RefID', NULL::bigint,", "'sysBranch_RefID', varInstitutionBranchID::bigint,", "'sysBaseCurrency_RefID',varBaseCurrencyID::bigint,", "'name', ", IF(EXACT($B34, ""), "null", CONCATENATE("'", SUBSTITUTE($B34, "'", "\'"), "'")), "::varchar", ")))::varchar;")) -> varSQL := varSQL || (CASE WHEN (varSQL = '') THEN '' ELSE ', ' END) || (SELECT JSON_BUILD_OBJECT ('recordID', NULL::bigint,'entities', JSON_BUILD_OBJECT ('sysLoginSession_RefID', varSystemLoginSession::bigint,'sysDataAnnotation', NULL::varchar,'sysDataSetDateTimeTZ', NULL::timestamptz,'sysDataValidityStartDateTimeTZ', NULL::timestamptz,'sysDataValidityFinishDateTimeTZ', NULL::timestamptz,'sysPartitionRemovableRecordKey_RefID', NULL::bigint,'sysBranch_RefID', varInstitutionBranchID::bigint,'sysBaseCurrency_RefID',varBaseCurrencyID::bigint,'name', 'Project Worker Staff'::varchar)))::varchar;
D35: =D34 + IF(EXACT(E35, ""), 0, 1) -> 95000000000026 | E35: =IF(EXACT(B35, ""), "", CONCATENATE("PERFORM ""SchSysConfig"".""Func_TblAppObject_UserRole_SET""(varSystemLoginSession, null::bigint, null::varchar, null::timestamptz, null::timestamptz, null::varchar, varInstitutionBranchID, varBaseCurrencyID, ", (IF(EXACT(B35, ""), "NULL", CONCATENATE("'", B35, "'"))),"::varchar);")) | G35: =IF(EXACT($E35, ""), "", CONCATENATE( "varSQL := varSQL || (CASE WHEN (varSQL = '') THEN '' ELSE ', ' END) || (SELECT JSON_BUILD_OBJECT (", "'recordID', NULL::bigint,", "'entities', ", "JSON_BUILD_OBJECT (", "'sysLoginSession_RefID', varSystemLoginSession::bigint,", "'sysDataAnnotation', NULL::varchar,", "'sysDataSetDateTimeTZ', NULL::timestamptz,", "'sysDataValidityStartDateTimeTZ', NULL::timestamptz,", "'sysDataValidityFinishDateTimeTZ', NULL::timestamptz,", "'sysPartitionRemovableRecordKey_RefID', NULL::bigint,", "'sysBranch_RefID', varInstitutionBranchID::bigint,", "'sysBaseCurrency_RefID',varBaseCurrencyID::bigint,", "'name', ", IF(EXACT($B35, ""), "null", CONCATENATE("'", SUBSTITUTE($B35, "'", "\'"), "'")), "::varchar", ")))::varchar;"))
B36: Finance Manager | D36: =D35 + IF(EXACT(E36, ""), 0, 1) -> 95000000000027 | E36: =IF(EXACT(B36, ""), "", CONCATENATE("PERFORM ""SchSysConfig"".""Func_TblAppObject_UserRole_SET""(varSystemLoginSession, null::bigint, null::varchar, null::timestamptz, null::timestamptz, null::varchar, varInstitutionBranchID, varBaseCurrencyID, ", (IF(EXACT(B36, ""), "NULL", CONCATENATE("'", B36, "'"))),"::varchar);")) -> PERFORM "SchSysConfig"."Func_TblAppObject_UserRole_SET"(varSystemLoginSession, null::bigint, null::varchar, null::timestamptz, null::timestamptz, null::varchar, varInstitutionBranchID, varBaseCurrencyID, 'Finance Manager'::varchar); | G36: =IF(EXACT($E36, ""), "", CONCATENATE( "varSQL := varSQL || (CASE WHEN (varSQL = '') THEN '' ELSE ', ' END) || (SELECT JSON_BUILD_OBJECT (", "'recordID', NULL::bigint,", "'entities', ", "JSON_BUILD_OBJECT (", "'sysLoginSession_RefID', varSystemLoginSession::bigint,", "'sysDataAnnotation', NULL::varchar,", "'sysDataSetDateTimeTZ', NULL::timestamptz,", "'sysDataValidityStartDateTimeTZ', NULL::timestamptz,", "'sysDataValidityFinishDateTimeTZ', NULL::timestamptz,", "'sysPartitionRemovableRecordKey_RefID', NULL::bigint,", "'sysBranch_RefID', varInstitutionBranchID::bigint,", "'sysBaseCurrency_RefID',varBaseCurrencyID::bigint,", "'name', ", IF(EXACT($B36, ""), "null", CONCATENATE("'", SUBSTITUTE($B36, "'", "\'"), "'")), "::varchar", ")))::varchar;")) -> varSQL := varSQL || (CASE WHEN (varSQL = '') THEN '' ELSE ', ' END) || (SELECT JSON_BUILD_OBJECT ('recordID', NULL::bigint,'entities', JSON_BUILD_OBJECT ('sysLoginSession_RefID', varSystemLoginSession::bigint,'sysDataAnnotation', NULL::varchar,'sysDataSetDateTimeTZ', NULL::timestamptz,'sysDataValidityStartDateTimeTZ', NULL::timestamptz,'sysDataValidityFinishDateTimeTZ', NULL::timestamptz,'sysPartitionRemovableRecordKey_RefID', NULL::bigint,'sysBranch_RefID', varInstitutionBranchID::bigint,'sysBaseCurrency_RefID',varBaseCurrencyID::bigint,'name', 'Finance Manager'::varchar)))::varchar;
B37: Cashier & Treasury Coordinator | D37: =D36 + IF(EXACT(E37, ""), 0, 1) -> 95000000000028 | E37: =IF(EXACT(B37, ""), "", CONCATENATE("PERFORM ""SchSysConfig"".""Func_TblAppObject_UserRole_SET""(varSystemLoginSession, null::bigint, null::varchar, null::timestamptz, null::timestamptz, null::varchar, varInstitutionBranchID, varBaseCurrencyID, ", (IF(EXACT(B37, ""), "NULL", CONCATENATE("'", B37, "'"))),"::varchar);")) -> PERFORM "SchSysConfig"."Func_TblAppObject_UserRole_SET"(varSystemLoginSession, null::bigint, null::varchar, null::timestamptz, null::timestamptz, null::varchar, varInstitutionBranchID, varBaseCurrencyID, 'Cashier & Treasury Coordinator'::varchar); | G37: =IF(EXACT($E37, ""), "", CONCATENATE( "varSQL := varSQL || (CASE WHEN (varSQL = '') THEN '' ELSE ', ' END) || (SELECT JSON_BUILD_OBJECT (", "'recordID', NULL::bigint,", "'entities', ", "JSON_BUILD_OBJECT (", "'sysLoginSession_RefID', varSystemLoginSession::bigint,", "'sysDataAnnotation', NULL::varchar,", "'sysDataSetDateTimeTZ', NULL::timestamptz,", "'sysDataValidityStartDateTimeTZ', NULL::timestamptz,", "'sysDataValidityFinishDateTimeTZ', NULL::timestamptz,", "'sysPartitionRemovableRecordKey_RefID', NULL::bigint,", "'sysBranch_RefID', varInstitutionBranchID::bigint,", "'sysBaseCurrency_RefID',varBaseCurrencyID::bigint,", "'name', ", IF(EXACT($B37, ""), "null", CONCATENATE("'", SUBSTITUTE($B37, "'", "\'"), "'")), "::varchar", ")))::varchar;")) -> varSQL := varSQL || (CASE WHEN (varSQL = '') THEN '' ELSE ', ' END) || (SELECT JSON_BUILD_OBJECT ('recordID', NULL::bigint,'entities', JSON_BUILD_OBJECT ('sysLoginSession_RefID', varSystemLoginSession::bigint,'sysDataAnnotation', NULL::varchar,'sysDataSetDateTimeTZ', NULL::timestamptz,'sysDataValidityStartDateTimeTZ', NULL::timestamptz,'sysDataValidityFinishDateTimeTZ', NULL::timestamptz,'sysPartitionRemovableRecordKey_RefID', NULL::bigint,'sysBranch_RefID', varInstitutionBranchID::bigint,'sysBaseCurrency_RefID',varBaseCurrencyID::bigint,'name', 'Cashier & Treasury Coordinator'::varchar)))::varchar;
B38: Cashier & Treasury Staff | D38: =D37 + IF(EXACT(E38, ""), 0, 1) -> 95000000000029 | E38: =IF(EXACT(B38, ""), "", CONCATENATE("PERFORM ""SchSysConfig"".""Func_TblAppObject_UserRole_SET""(varSystemLoginSession, null::bigint, null::varchar, null::timestamptz, null::timestamptz, null::varchar, varInstitutionBranchID, varBaseCurrencyID, ", (IF(EXACT(B38, ""), "NULL", CONCATENATE("'", B38, "'"))),"::varchar);")) -> PERFORM "SchSysConfig"."Func_TblAppObject_UserRole_SET"(varSystemLoginSession, null::bigint, null::varchar, null::timestamptz, null::timestamptz, null::varchar, varInstitutionBranchID, varBaseCurrencyID, 'Cashier & Treasury Staff'::varchar); | G38: =IF(EXACT($E38, ""), "", CONCATENATE( "varSQL := varSQL || (CASE WHEN (varSQL = '') THEN '' ELSE ', ' END) || (SELECT JSON_BUILD_OBJECT (", "'recordID', NULL::bigint,", "'entities', ", "JSON_BUILD_OBJECT (", "'sysLoginSession_RefID', varSystemLoginSession::bigint,", "'sysDataAnnotation', NULL::varchar,", "'sysDataSetDateTimeTZ', NULL::timestamptz,", "'sysDataValidityStartDateTimeTZ', NULL::timestamptz,", "'sysDataValidityFinishDateTimeTZ', NULL::timestamptz,", "'sysPartitionRemovableRecordKey_RefID', NULL::bigint,", "'sysBranch_RefID', varInstitutionBranchID::bigint,", "'sysBaseCurrency_RefID',varBaseCurrencyID::bigint,", "'name', ", IF(EXACT($B38, ""), "null", CONCATENATE("'", SUBSTITUTE($B38, "'", "\'"), "'")), "::varchar", ")))::varchar;")) -> varSQL := varSQL || (CASE WHEN (varSQL = '') THEN '' ELSE ', ' END) || (SELECT JSON_BUILD_OBJECT ('recordID', NULL::bigint,'entities', JSON_BUILD_OBJECT ('sysLoginSession_RefID', varSystemLoginSession::bigint,'sysDataAnnotation', NULL::varchar,'sysDataSetDateTimeTZ', NULL::timestamptz,'sysDataValidityStartDateTimeTZ', NULL::timestamptz,'sysDataValidityFinishDateTimeTZ', NULL::timestamptz,'sysPartitionRemovableRecordKey_RefID', NULL::bigint,'sysBranch_RefID', varInstitutionBranchID::bigint,'sysBaseCurrency_RefID',varBaseCurrencyID::bigint,'name', 'Cashier & Treasury Staff'::varchar)))::varchar;
B39: Cost Controller Coordinator | D39: =D38 + IF(EXACT(E39, ""), 0, 1) -> 95000000000030 | E39: =IF(EXACT(B39, ""), "", CONCATENATE("PERFORM ""SchSysConfig"".""Func_TblAppObject_UserRole_SET""(varSystemLoginSession, null::bigint, null::varchar, null::timestamptz, null::timestamptz, null::varchar, varInstitutionBranchID, varBaseCurrencyID, ", (IF(EXACT(B39, ""), "NULL", CONCATENATE("'", B39, "'"))),"::varchar);")) -> PERFORM "SchSysConfig"."Func_TblAppObject_UserRole_SET"(varSystemLoginSession, null::bigint, null::varchar, null::timestamptz, null::timestamptz, null::varchar, varInstitutionBranchID, varBaseCurrencyID, 'Cost Controller Coordinator'::varchar); | G39: =IF(EXACT($E39, ""), "", CONCATENATE( "varSQL := varSQL || (CASE WHEN (varSQL = '') THEN '' ELSE ', ' END) || (SELECT JSON_BUILD_OBJECT (", "'recordID', NULL::bigint,", "'entities', ", "JSON_BUILD_OBJECT (", "'sysLoginSession_RefID', varSystemLoginSession::bigint,", "'sysDataAnnotation', NULL::varchar,", "'sysDataSetDateTimeTZ', NULL::timestamptz,", "'sysDataValidityStartDateTimeTZ', NULL::timestamptz,", "'sysDataValidityFinishDateTimeTZ', NULL::timestamptz,", "'sysPartitionRemovableRecordKey_RefID', NULL::bigint,", "'sysBranch_RefID', varInstitutionBranchID::bigint,", "'sysBaseCurrency_RefID',varBaseCurrencyID::bigint,", "'name', ", IF(EXACT($B39, ""), "null", CONCATENATE("'", SUBSTITUTE($B39, "'", "\'"), "'")), "::varchar", ")))::varchar;")) -> varSQL := varSQL || (CASE WHEN (varSQL = '') THEN '' ELSE ', ' END) || (SELECT JSON_BUILD_OBJECT ('recordID', NULL::bigint,'entities', JSON_BUILD_OBJECT ('sysLoginSession_RefID', varSystemLoginSession::bigint,'sysDataAnnotation', NULL::varchar,'sysDataSetDateTimeTZ', NULL::timestamptz,'sysDataValidityStartDateTimeTZ', NULL::timestamptz,'sysDataValidityFinishDateTimeTZ', NULL::timestamptz,'sysPartitionRemovableRecordKey_RefID', NULL::bigint,'sysBranch_RefID', varInstitutionBranchID::bigint,'sysBaseCurrency_RefID',varBaseCurrencyID::bigint,'name', 'Cost Controller Coordinator'::varchar)))::varchar;
B40: Cost Controller Staff | D40: =D39 + IF(EXACT(E40, ""), 0, 1) -> 95000000000031 | E40: =IF(EXACT(B40, ""), "", CONCATENATE("PERFORM ""SchSysConfig"".""Func_TblAppObject_UserRole_SET""(varSystemLoginSession, null::bigint, null::varchar, null::timestamptz, null::timestamptz, null::varchar, varInstitutionBranchID, varBaseCurrencyID, ", (IF(EXACT(B40, ""), "NULL", CONCATENATE("'", B40, "'"))),"::varchar);")) -> PERFORM "SchSysConfig"."Func_TblAppObject_UserRole_SET"(varSystemLoginSession, null::bigint, null::varchar, null::timestamptz, null::timestamptz, null::varchar, varInstitutionBranchID, varBaseCurrencyID, 'Cost Controller Staff'::varchar); | G40: =IF(EXACT($E40, ""), "", CONCATENATE( "varSQL := varSQL || (CASE WHEN (varSQL = '') THEN '' ELSE ', ' END) || (SELECT JSON_BUILD_OBJECT (", "'recordID', NULL::bigint,", "'entities', ", "JSON_BUILD_OBJECT (", "'sysLoginSession_RefID', varSystemLoginSession::bigint,", "'sysDataAnnotation', NULL::varchar,", "'sysDataSetDateTimeTZ', NULL::timestamptz,", "'sysDataValidityStartDateTimeTZ', NULL::timestamptz,", "'sysDataValidityFinishDateTimeTZ', NULL::timestamptz,", "'sysPartitionRemovableRecordKey_RefID', NULL::bigint,", "'sysBranch_RefID', varInstitutionBranchID::bigint,", "'sysBaseCurrency_RefID',varBaseCurrencyID::bigint,", "'name', ", IF(EXACT($B40, ""), "null", CONCATENATE("'", SUBSTITUTE($B40, "'", "\'"), "'")), "::varchar", ")))::varchar;")) -> varSQL := varSQL || (CASE WHEN (varSQL = '') THEN '' ELSE ', ' END) || (SELECT JSON_BUILD_OBJECT ('recordID', NULL::bigint,'entities', JSON_BUILD_OBJECT ('sysLoginSession_RefID', varSystemLoginSession::bigint,'sysDataAnnotation', NULL::varchar,'sysDataSetDateTimeTZ', NULL::timestamptz,'sysDataValidityStartDateTimeTZ', NULL::timestamptz,'sysDataValidityFinishDateTimeTZ', NULL::timestamptz,'sysPartitionRemovableRecordKey_RefID', NULL::bigint,'sysBranch_RefID', varInstitutionBranchID::bigint,'sysBaseCurrency_RefID',varBaseCurrencyID::bigint,'name', 'Cost Controller Staff'::varchar)))::varchar;
D41: =D40 + IF(EXACT(E41, ""), 0, 1) -> 95000000000031 | E41: =IF(EXACT(B41, ""), "", CONCATENATE("PERFORM ""SchSysConfig"".""Func_TblAppObject_UserRole_SET""(varSystemLoginSession, null::bigint, null::varchar, null::timestamptz, null::timestamptz, null::varchar, varInstitutionBranchID, varBaseCurrencyID, ", (IF(EXACT(B41, ""), "NULL", CONCATENATE("'", B41, "'"))),"::varchar);")) | G41: =IF(EXACT($E41, ""), "", CONCATENATE( "varSQL := varSQL || (CASE WHEN (varSQL = '') THEN '' ELSE ', ' END) || (SELECT JSON_BUILD_OBJECT (", "'recordID', NULL::bigint,", "'entities', ", "JSON_BUILD_OBJECT (", "'sysLoginSession_RefID', varSystemLoginSession::bigint,", "'sysDataAnnotation', NULL::varchar,", "'sysDataSetDateTimeTZ', NULL::timestamptz,", "'sysDataValidityStartDateTimeTZ', NULL::timestamptz,", "'sysDataValidityFinishDateTimeTZ', NULL::timestamptz,", "'sysPartitionRemovableRecordKey_RefID', NULL::bigint,", "'sysBranch_RefID', varInstitutionBranchID::bigint,", "'sysBaseCurrency_RefID',varBaseCurrencyID::bigint,", "'name', ", IF(EXACT($B41, ""), "null", CONCATENATE("'", SUBSTITUTE($B41, "'", "\'"), "'")), "::varchar", ")))::varchar;"))
B42: Accounting & Tax Manager | D42: =D41 + IF(EXACT(E42, ""), 0, 1) -> 95000000000032 | E42: =IF(EXACT(B42, ""), "", CONCATENATE("PERFORM ""SchSysConfig"".""Func_TblAppObject_UserRole_SET""(varSystemLoginSession, null::bigint, null::varchar, null::timestamptz, null::timestamptz, null::varchar, varInstitutionBranchID, varBaseCurrencyID, ", (IF(EXACT(B42, ""), "NULL", CONCATENATE("'", B42, "'"))),"::varchar);")) -> PERFORM "SchSysConfig"."Func_TblAppObject_UserRole_SET"(varSystemLoginSession, null::bigint, null::varchar, null::timestamptz, null::timestamptz, null::varchar, varInstitutionBranchID, varBaseCurrencyID, 'Accounting & Tax Manager'::varchar); | G42: =IF(EXACT($E42, ""), "", CONCATENATE( "varSQL := varSQL || (CASE WHEN (varSQL = '') THEN '' ELSE ', ' END) || (SELECT JSON_BUILD_OBJECT (", "'recordID', NULL::bigint,", "'entities', ", "JSON_BUILD_OBJECT (", "'sysLoginSession_RefID', varSystemLoginSession::bigint,", "'sysDataAnnotation', NULL::varchar,", "'sysDataSetDateTimeTZ', NULL::timestamptz,", "'sysDataValidityStartDateTimeTZ', NULL::timestamptz,", "'sysDataValidityFinishDateTimeTZ', NULL::timestamptz,", "'sysPartitionRemovableRecordKey_RefID', NULL::bigint,", "'sysBranch_RefID', varInstitutionBranchID::bigint,", "'sysBaseCurrency_RefID',varBaseCurrencyID::bigint,", "'name', ", IF(EXACT($B42, ""), "null", CONCATENATE("'", SUBSTITUTE($B42, "'", "\'"), "'")), "::varchar", ")))::varchar;")) -> varSQL := varSQL || (CASE WHEN (varSQL = '') THEN '' ELSE ', ' END) || (SELECT JSON_BUILD_OBJECT ('recordID', NULL::bigint,'entities', JSON_BUILD_OBJECT ('sysLoginSession_RefID', varSystemLoginSession::bigint,'sysDataAnnotation', NULL::varchar,'sysDataSetDateTimeTZ', NULL::timestamptz,'sysDataValidityStartDateTimeTZ', NULL::timestamptz,'sysDataValidityFinishDateTimeTZ', NULL::timestamptz,'sysPartitionRemovableRecordKey_RefID', NULL::bigint,'sysBranch_RefID', varInstitutionBranchID::bigint,'sysBaseCurrency_RefID',varBaseCurrencyID::bigint,'name', 'Accounting & Tax Manager'::varchar)))::varchar;
B43: Accounting & Tax Coordinator | D43: =D42 + IF(EXACT(E43, ""), 0, 1) -> 95000000000033 | E43: =IF(EXACT(B43, ""), "", CONCATENATE("PERFORM ""SchSysConfig"".""Func_TblAppObject_UserRole_SET""(varSystemLoginSession, null::bigint, null::varchar, null::timestamptz, null::timestamptz, null::varchar, varInstitutionBranchID, varBaseCurrencyID, ", (IF(EXACT(B43, ""), "NULL", CONCATENATE("'", B43, "'"))),"::varchar);")) -> PERFORM "SchSysConfig"."Func_TblAppObject_UserRole_SET"(varSystemLoginSession, null::bigint, null::varchar, null::timestamptz, null::timestamptz, null::varchar, varInstitutionBranchID, varBaseCurrencyID, 'Accounting & Tax Coordinator'::varchar); | G43: =IF(EXACT($E43, ""), "", CONCATENATE( "varSQL := varSQL || (CASE WHEN (varSQL = '') THEN '' ELSE ', ' END) || (SELECT JSON_BUILD_OBJECT (", "'recordID', NULL::bigint,", "'entities', ", "JSON_BUILD_OBJECT (", "'sysLoginSession_RefID', varSystemLoginSession::bigint,", "'sysDataAnnotation', NULL::varchar,", "'sysDataSetDateTimeTZ', NULL::timestamptz,", "'sysDataValidityStartDateTimeTZ', NULL::timestamptz,", "'sysDataValidityFinishDateTimeTZ', NULL::timestamptz,", "'sysPartitionRemovableRecordKey_RefID', NULL::bigint,", "'sysBranch_RefID', varInstitutionBranchID::bigint,", "'sysBaseCurrency_RefID',varBaseCurrencyID::bigint,", "'name', ", IF(EXACT($B43, ""), "null", CONCATENATE("'", SUBSTITUTE($B43, "'", "\'"), "'")), "::varchar", ")))::varchar;")) -> varSQL := varSQL || (CASE WHEN (varSQL = '') THEN '' ELSE ', ' END) || (SELECT JSON_BUILD_OBJECT ('recordID', NULL::bigint,'entities', JSON_BUILD_OBJECT ('sysLoginSession_RefID', varSystemLoginSession::bigint,'sysDataAnnotation', NULL::varchar,'sysDataSetDateTimeTZ', NULL::timestamptz,'sysDataValidityStartDateTimeTZ', NULL::timestamptz,'sysDataValidityFinishDateTimeTZ', NULL::timestamptz,'sysPartitionRemovableRecordKey_RefID', NULL::bigint,'sysBranch_RefID', varInstitutionBranchID::bigint,'sysBaseCurrency_RefID',varBaseCurrencyID::bigint,'name', 'Accounting & Tax Coordinator'::varchar)))::varchar;
B44: Accounting & Tax Staff | D44: =D43 + IF(EXACT(E44, ""), 0, 1) -> 95000000000034 | E44: =IF(EXACT(B44, ""), "", CONCATENATE("PERFORM ""SchSysConfig"".""Func_TblAppObject_UserRole_SET""(varSystemLoginSession, null::bigint, null::varchar, null::timestamptz, null::timestamptz, null::varchar, varInstitutionBranchID, varBaseCurrencyID, ", (IF(EXACT(B44, ""), "NULL", CONCATENATE("'", B44, "'"))),"::varchar);")) -> PERFORM "SchSysConfig"."Func_TblAppObject_UserRole_SET"(varSystemLoginSession, null::bigint, null::varchar, null::timestamptz, null::timestamptz, null::varchar, varInstitutionBranchID, varBaseCurrencyID, 'Accounting & Tax Staff'::varchar); | G44: =IF(EXACT($E44, ""), "", CONCATENATE( "varSQL := varSQL || (CASE WHEN (varSQL = '') THEN '' ELSE ', ' END) || (SELECT JSON_BUILD_OBJECT (", "'recordID', NULL::bigint,", "'entities', ", "JSON_BUILD_OBJECT (", "'sysLoginSession_RefID', varSystemLoginSession::bigint,", "'sysDataAnnotation', NULL::varchar,", "'sysDataSetDateTimeTZ', NULL::timestamptz,", "'sysDataValidityStartDateTimeTZ', NULL::timestamptz,", "'sysDataValidityFinishDateTimeTZ', NULL::timestamptz,", "'sysPartitionRemovableRecordKey_RefID', NULL::bigint,", "'sysBranch_RefID', varInstitutionBranchID::bigint,", "'sysBaseCurrency_RefID',varBaseCurrencyID::bigint,", "'name', ", IF(EXACT($B44, ""), "null", CONCATENATE("'", SUBSTITUTE($B44, "'", "\'"), "'")), "::varchar", ")))::varchar;")) -> varSQL := varSQL || (CASE WHEN (varSQL = '') THEN '' ELSE ', ' END) || (SELECT JSON_BUILD_OBJECT ('recordID', NULL::bigint,'entities', JSON_BUILD_OBJECT ('sysLoginSession_RefID', varSystemLoginSession::bigint,'sysDataAnnotation', NULL::varchar,'sysDataSetDateTimeTZ', NULL::timestamptz,'sysDataValidityStartDateTimeTZ', NULL::timestamptz,'sysDataValidityFinishDateTimeTZ', NULL::timestamptz,'sysPartitionRemovableRecordKey_RefID', NULL::bigint,'sysBranch_RefID', varInstitutionBranchID::bigint,'sysBaseCurrency_RefID',varBaseCurrencyID::bigint,'name', 'Accounting & Tax Staff'::varchar)))::varchar;
D45: =D44 + IF(EXACT(E45, ""), 0, 1) -> 95000000000034 | E45: =IF(EXACT(B45, ""), "", CONCATENATE("PERFORM ""SchSysConfig"".""Func_TblAppObject_UserRole_SET""(varSystemLoginSession, null::bigint, null::varchar, null::timestamptz, null::timestamptz, null::varchar, varInstitutionBranchID, varBaseCurrencyID, ", (IF(EXACT(B45, ""), "NULL", CONCATENATE("'", B45, "'"))),"::varchar);")) | G45: =IF(EXACT($E45, ""), "", CONCATENATE( "varSQL := varSQL || (CASE WHEN (varSQL = '') THEN '' ELSE ', ' END) || (SELECT JSON_BUILD_OBJECT (", "'recordID', NULL::bigint,", "'entities', ", "JSON_BUILD_OBJECT (", "'sysLoginSession_RefID', varSystemLoginSession::bigint,", "'sysDataAnnotation', NULL::varchar,", "'sysDataSetDateTimeTZ', NULL::timestamptz,", "'sysDataValidityStartDateTimeTZ', NULL::timestamptz,", "'sysDataValidityFinishDateTimeTZ', NULL::timestamptz,", "'sysPartitionRemovableRecordKey_RefID', NULL::bigint,", "'sysBranch_RefID', varInstitutionBranchID::bigint,", "'sysBaseCurrency_RefID',varBaseCurrencyID::bigint,", "'name', ", IF(EXACT($B45, ""), "null", CONCATENATE("'", SUBSTITUTE($B45, "'", "\'"), "'")), "::varchar", ")))::varchar;"))
B46: IT System Manager | D46: =D45 + IF(EXACT(E46, ""), 0, 1) -> 95000000000035 | E46: =IF(EXACT(B46, ""), "", CONCATENATE("PERFORM ""SchSysConfig"".""Func_TblAppObject_UserRole_SET""(varSystemLoginSession, null::bigint, null::varchar, null::timestamptz, null::timestamptz, null::varchar, varInstitutionBranchID, varBaseCurrencyID, ", (IF(EXACT(B46, ""), "NULL", CONCATENATE("'", B46, "'"))),"::varchar);")) -> PERFORM "SchSysConfig"."Func_TblAppObject_UserRole_SET"(varSystemLoginSession, null::bigint, null::varchar, null::timestamptz, null::timestamptz, null::varchar, varInstitutionBranchID, varBaseCurrencyID, 'IT System Manager'::varchar); | G46: =IF(EXACT($E46, ""), "", CONCATENATE( "varSQL := varSQL || (CASE WHEN (varSQL = '') THEN '' ELSE ', ' END) || (SELECT JSON_BUILD_OBJECT (", "'recordID', NULL::bigint,", "'entities', ", "JSON_BUILD_OBJECT (", "'sysLoginSession_RefID', varSystemLoginSession::bigint,", "'sysDataAnnotation', NULL::varchar,", "'sysDataSetDateTimeTZ', NULL::timestamptz,", "'sysDataValidityStartDateTimeTZ', NULL::timestamptz,", "'sysDataValidityFinishDateTimeTZ', NULL::timestamptz,", "'sysPartitionRemovableRecordKey_RefID', NULL::bigint,", "'sysBranch_RefID', varInstitutionBranchID::bigint,", "'sysBaseCurrency_RefID',varBaseCurrencyID::bigint,", "'name', ", IF(EXACT($B46, ""), "null", CONCATENATE("'", SUBSTITUTE($B46, "'", "\'"), "'")), "::varchar", ")))::varchar;")) -> varSQL := varSQL || (CASE WHEN (varSQL = '') THEN '' ELSE ', ' END) || (SELECT JSON_BUILD_OBJECT ('recordID', NULL::bigint,'entities', JSON_BUILD_OBJECT ('sysLoginSession_RefID', varSystemLoginSession::bigint,'sysDataAnnotation', NULL::varchar,'sysDataSetDateTimeTZ', NULL::timestamptz,'sysDataValidityStartDateTimeTZ', NULL::timestamptz,'sysDataValidityFinishDateTimeTZ', NULL::timestamptz,'sysPartitionRemovableRecordKey_RefID', NULL::bigint,'sysBranch_RefID', varInstitutionBranchID::bigint,'sysBaseCurrency_RefID',varBaseCurrencyID::bigint,'name', 'IT System Manager'::varchar)))::varchar;
B47: IT System Engineer Coordinator | D47: =D46 + IF(EXACT(E47, ""), 0, 1) -> 95000000000036 | E47: =IF(EXACT(B47, ""), "", CONCATENATE("PERFORM ""SchSysConfig"".""Func_TblAppObject_UserRole_SET""(varSystemLoginSession, null::bigint, null::varchar, null::timestamptz, null::timestamptz, null::varchar, varInstitutionBranchID, varBaseCurrencyID, ", (IF(EXACT(B47, ""), "NULL", CONCATENATE("'", B47, "'"))),"::varchar);")) -> PERFORM "SchSysConfig"."Func_TblAppObject_UserRole_SET"(varSystemLoginSession, null::bigint, null::varchar, null::timestamptz, null::timestamptz, null::varchar, varInstitutionBranchID, varBaseCurrencyID, 'IT System Engineer Coordinator'::varchar); | G47: =IF(EXACT($E47, ""), "", CONCATENATE( "varSQL := varSQL || (CASE WHEN (varSQL = '') THEN '' ELSE ', ' END) || (SELECT JSON_BUILD_OBJECT (", "'recordID', NULL::bigint,", "'entities', ", "JSON_BUILD_OBJECT (", "'sysLoginSession_RefID', varSystemLoginSession::bigint,", "'sysDataAnnotation', NULL::varchar,", "'sysDataSetDateTimeTZ', NULL::timestamptz,", "'sysDataValidityStartDateTimeTZ', NULL::timestamptz,", "'sysDataValidityFinishDateTimeTZ', NULL::timestamptz,", "'sysPartitionRemovableRecordKey_RefID', NULL::bigint,", "'sysBranch_RefID', varInstitutionBranchID::bigint,", "'sysBaseCurrency_RefID',varBaseCurrencyID::bigint,", "'name', ", IF(EXACT($B47, ""), "null", CONCATENATE("'", SUBSTITUTE($B47, "'", "\'"), "'")), "::varchar", ")))::varchar;")) -> varSQL := varSQL || (CASE WHEN (varSQL = '') THEN '' ELSE ', ' END) || (SELECT JSON_BUILD_OBJECT ('recordID', NULL::bigint,'entities', JSON_BUILD_OBJECT ('sysLoginSession_RefID', varSystemLoginSession::bigint,'sysDataAnnotation', NULL::varchar,'sysDataSetDateTimeTZ', NULL::timestamptz,'sysDataValidityStartDateTimeTZ', NULL::timestamptz,'sysDataValidityFinishDateTimeTZ', NULL::timestamptz,'sysPartitionRemovableRecordKey_RefID', NULL::bigint,'sysBranch_RefID', varInstitutionBranchID::bigint,'sysBaseCurrency_RefID',varBaseCurrencyID::bigint,'name', 'IT System Engineer Coordinator'::varchar)))::varchar;
B48: IT System Engineer Staff | D48: =D47 + IF(EXACT(E48, ""), 0, 1) -> 95000000000037 | E48: =IF(EXACT(B48, ""), "", CONCATENATE("PERFORM ""SchSysConfig"".""Func_TblAppObject_UserRole_SET""(varSystemLoginSession, null::bigint, null::varchar, null::timestamptz, null::timestamptz, null::varchar, varInstitutionBranchID, varBaseCurrencyID, ", (IF(EXACT(B48, ""), "NULL", CONCATENATE("'", B48, "'"))),"::varchar);")) -> PERFORM "SchSysConfig"."Func_TblAppObject_UserRole_SET"(varSystemLoginSession, null::bigint, null::varchar, null::timestamptz, null::timestamptz, null::varchar, varInstitutionBranchID, varBaseCurrencyID, 'IT System Engineer Staff'::varchar); | G48: =IF(EXACT($E48, ""), "", CONCATENATE( "varSQL := varSQL || (CASE WHEN (varSQL = '') THEN '' ELSE ', ' END) || (SELECT JSON_BUILD_OBJECT (", "'recordID', NULL::bigint,", "'entities', ", "JSON_BUILD_OBJECT (", "'sysLoginSession_RefID', varSystemLoginSession::bigint,", "'sysDataAnnotation', NULL::varchar,", "'sysDataSetDateTimeTZ', NULL::timestamptz,", "'sysDataValidityStartDateTimeTZ', NULL::timestamptz,", "'sysDataValidityFinishDateTimeTZ', NULL::timestamptz,", "'sysPartitionRemovableRecordKey_RefID', NULL::bigint,", "'sysBranch_RefID', varInstitutionBranchID::bigint,", "'sysBaseCurrency_RefID',varBaseCurrencyID::bigint,", "'name', ", IF(EXACT($B48, ""), "null", CONCATENATE("'", SUBSTITUTE($B48, "'", "\'"), "'")), "::varchar", ")))::varchar;")) -> varSQL := varSQL || (CASE WHEN (varSQL = '') THEN '' ELSE ', ' END) || (SELECT JSON_BUILD_OBJECT ('recordID', NULL::bigint,'entities', JSON_BUILD_OBJECT ('sysLoginSession_RefID', varSystemLoginSession::bigint,'sysDataAnnotation', NULL::varchar,'sysDataSetDateTimeTZ', NULL::timestamptz,'sysDataValidityStartDateTimeTZ', NULL::timestamptz,'sysDataValidityFinishDateTimeTZ', NULL::timestamptz,'sysPartitionRemovableRecordKey_RefID', NULL::bigint,'sysBranch_RefID', varInstitutionBranchID::bigint,'sysBaseCurrency_RefID',varBaseCurrencyID::bigint,'name', 'IT System Engineer Staff'::varchar)))::varchar;
B49: IT Software Engineer Coordinator | D49: =D48 + IF(EXACT(E49, ""), 0, 1) -> 95000000000038 | E49: =IF(EXACT(B49, ""), "", CONCATENATE("PERFORM ""SchSysConfig"".""Func_TblAppObject_UserRole_SET""(varSystemLoginSession, null::bigint, null::varchar, null::timestamptz, null::timestamptz, null::varchar, varInstitutionBranchID, varBaseCurrencyID, ", (IF(EXACT(B49, ""), "NULL", CONCATENATE("'", B49, "'"))),"::varchar);")) -> PERFORM "SchSysConfig"."Func_TblAppObject_UserRole_SET"(varSystemLoginSession, null::bigint, null::varchar, null::timestamptz, null::timestamptz, null::varchar, varInstitutionBranchID, varBaseCurrencyID, 'IT Software Engineer Coordinator'::varchar); | G49: =IF(EXACT($E49, ""), "", CONCATENATE( "varSQL := varSQL || (CASE WHEN (varSQL = '') THEN '' ELSE ', ' END) || (SELECT JSON_BUILD_OBJECT (", "'recordID', NULL::bigint,", "'entities', ", "JSON_BUILD_OBJECT (", "'sysLoginSession_RefID', varSystemLoginSession::bigint,", "'sysDataAnnotation', NULL::varchar,", "'sysDataSetDateTimeTZ', NULL::timestamptz,", "'sysDataValidityStartDateTimeTZ', NULL::timestamptz,", "'sysDataValidityFinishDateTimeTZ', NULL::timestamptz,", "'sysPartitionRemovableRecordKey_RefID', NULL::bigint,", "'sysBranch_RefID', varInstitutionBranchID::bigint,", "'sysBaseCurrency_RefID',varBaseCurrencyID::bigint,", "'name', ", IF(EXACT($B49, ""), "null", CONCATENATE("'", SUBSTITUTE($B49, "'", "\'"), "'")), "::varchar", ")))::varchar;")) -> varSQL := varSQL || (CASE WHEN (varSQL = '') THEN '' ELSE ', ' END) || (SELECT JSON_BUILD_OBJECT ('recordID', NULL::bigint,'entities', JSON_BUILD_OBJECT ('sysLoginSession_RefID', varSystemLoginSession::bigint,'sysDataAnnotation', NULL::varchar,'sysDataSetDateTimeTZ', NULL::timestamptz,'sysDataValidityStartDateTimeTZ', NULL::timestamptz,'sysDataValidityFinishDateTimeTZ', NULL::timestamptz,'sysPartitionRemovableRecordKey_RefID', NULL::bigint,'sysBranch_RefID', varInstitutionBranchID::bigint,'sysBaseCurrency_RefID',varBaseCurrencyID::bigint,'name', 'IT Software Engineer Coordinator'::varchar)))::varchar;
B50: IT Software Engineer Staff | D50: =D49 + IF(EXACT(E50, ""), 0, 1) -> 95000000000039 | E50: =IF(EXACT(B50, ""), "", CONCATENATE("PERFORM ""SchSysConfig"".""Func_TblAppObject_UserRole_SET""(varSystemLoginSession, null::bigint, null::varchar, null::timestamptz, null::timestamptz, null::varchar, varInstitutionBranchID, varBaseCurrencyID, ", (IF(EXACT(B50, ""), "NULL", CONCATENATE("'", B50, "'"))),"::varchar);")) -> PERFORM "SchSysConfig"."Func_TblAppObject_UserRole_SET"(varSystemLoginSession, null::bigint, null::varchar, null::timestamptz, null::timestamptz, null::varchar, varInstitutionBranchID, varBaseCurrencyID, 'IT Software Engineer Staff'::varchar); | G50: =IF(EXACT($E50, ""), "", CONCATENATE( "varSQL := varSQL || (CASE WHEN (varSQL = '') THEN '' ELSE ', ' END) || (SELECT JSON_BUILD_OBJECT (", "'recordID', NULL::bigint,", "'entities', ", "JSON_BUILD_OBJECT (", "'sysLoginSession_RefID', varSystemLoginSession::bigint,", "'sysDataAnnotation', NULL::varchar,", "'sysDataSetDateTimeTZ', NULL::timestamptz,", "'sysDataValidityStartDateTimeTZ', NULL::timestamptz,", "'sysDataValidityFinishDateTimeTZ', NULL::timestamptz,", "'sysPartitionRemovableRecordKey_RefID', NULL::bigint,", "'sysBranch_RefID', varInstitutionBranchID::bigint,", "'sysBaseCurrency_RefID',varBaseCurrencyID::bigint,", "'name', ", IF(EXACT($B50, ""), "null", CONCATENATE("'", SUBSTITUTE($B50, "'", "\'"), "'")), "::varchar", ")))::varchar;")) -> varSQL := varSQL || (CASE WHEN (varSQL = '') THEN '' ELSE ', ' END) || (SELECT JSON_BUILD_OBJECT ('recordID', NULL::bigint,'entities', JSON_BUILD_OBJECT ('sysLoginSession_RefID', varSystemLoginSession::bigint,'sysDataAnnotation', NULL::varchar,'sysDataSetDateTimeTZ', NULL::timestamptz,'sysDataValidityStartDateTimeTZ', NULL::timestamptz,'sysDataValidityFinishDateTimeTZ', NULL::timestamptz,'sysPartitionRemovableRecordKey_RefID', NULL::bigint,'sysBranch_RefID', varInstitutionBranchID::bigint,'sysBaseCurrency_RefID',varBaseCurrencyID::bigint,'name', 'IT Software Engineer Staff'::varchar)))::varchar;
D51: =D50 + IF(EXACT(E51, ""), 0, 1) -> 95000000000039 | E51: =IF(EXACT(B51, ""), "", CONCATENATE("PERFORM ""SchSysConfig"".""Func_TblAppObject_UserRole_SET""(varSystemLoginSession, null::bigint, null::varchar, null::timestamptz, null::timestamptz, null::varchar, varInstitutionBranchID, varBaseCurrencyID, ", (IF(EXACT(B51, ""), "NULL", CONCATENATE("'", B51, "'"))),"::varchar);")) | G51: =IF(EXACT($E51, ""), "", CONCATENATE( "varSQL := varSQL || (CASE WHEN (varSQL = '') THEN '' ELSE ', ' END) || (SELECT JSON_BUILD_OBJECT (", "'recordID', NULL::bigint,", "'entities', ", "JSON_BUILD_OBJECT (", "'sysLoginSession_RefID', varSystemLoginSession::bigint,", "'sysDataAnnotation', NULL::varchar,", "'sysDataSetDateTimeTZ', NULL::timestamptz,", "'sysDataValidityStartDateTimeTZ', NULL::timestamptz,", "'sysDataValidityFinishDateTimeTZ', NULL::timestamptz,", "'sysPartitionRemovableRecordKey_RefID', NULL::bigint,", "'sysBranch_RefID', varInstitutionBranchID::bigint,", "'sysBaseCurrency_RefID',varBaseCurrencyID::bigint,", "'name', ", IF(EXACT($B51, ""), "null", CONCATENATE("'", SUBSTITUTE($B51, "'", "\'"), "'")), "::varchar", ")))::varchar;"))
B52: Procurement Manager | D52: =D51 + IF(EXACT(E52, ""), 0, 1) -> 95000000000040 | E52: =IF(EXACT(B52, ""), "", CONCATENATE("PERFORM ""SchSysConfig"".""Func_TblAppObject_UserRole_SET""(varSystemLoginSession, null::bigint, null::varchar, null::timestamptz, null::timestamptz, null::varchar, varInstitutionBranchID, varBaseCurrencyID, ", (IF(EXACT(B52, ""), "NULL", CONCATENATE("'", B52, "'"))),"::varchar);")) -> PERFORM "SchSysConfig"."Func_TblAppObject_UserRole_SET"(varSystemLoginSession, null::bigint, null::varchar, null::timestamptz, null::timestamptz, null::varchar, varInstitutionBranchID, varBaseCurrencyID, 'Procurement Manager'::varchar); | G52: =IF(EXACT($E52, ""), "", CONCATENATE( "varSQL := varSQL || (CASE WHEN (varSQL = '') THEN '' ELSE ', ' END) || (SELECT JSON_BUILD_OBJECT (", "'recordID', NULL::bigint,", "'entities', ", "JSON_BUILD_OBJECT (", "'sysLoginSession_RefID', varSystemLoginSession::bigint,", "'sysDataAnnotation', NULL::varchar,", "'sysDataSetDateTimeTZ', NULL::timestamptz,", "'sysDataValidityStartDateTimeTZ', NULL::timestamptz,", "'sysDataValidityFinishDateTimeTZ', NULL::timestamptz,", "'sysPartitionRemovableRecordKey_RefID', NULL::bigint,", "'sysBranch_RefID', varInstitutionBranchID::bigint,", "'sysBaseCurrency_RefID',varBaseCurrencyID::bigint,", "'name', ", IF(EXACT($B52, ""), "null", CONCATENATE("'", SUBSTITUTE($B52, "'", "\'"), "'")), "::varchar", ")))::varchar;")) -> varSQL := varSQL || (CASE WHEN (varSQL = '') THEN '' ELSE ', ' END) || (SELECT JSON_BUILD_OBJECT ('recordID', NULL::bigint,'entities', JSON_BUILD_OBJECT ('sysLoginSession_RefID', varSystemLoginSession::bigint,'sysDataAnnotation', NULL::varchar,'sysDataSetDateTimeTZ', NULL::timestamptz,'sysDataValidityStartDateTimeTZ', NULL::timestamptz,'sysDataValidityFinishDateTimeTZ', NULL::timestamptz,'sysPartitionRemovableRecordKey_RefID', NULL::bigint,'sysBranch_RefID', varInstitutionBranchID::bigint,'sysBaseCurrency_RefID',varBaseCurrencyID::bigint,'name', 'Procurement Manager'::varchar)))::varchar;
B53: Procurement Coordinator | D53: =D52 + IF(EXACT(E53, ""), 0, 1) -> 95000000000041 | E53: =IF(EXACT(B53, ""), "", CONCATENATE("PERFORM ""SchSysConfig"".""Func_TblAppObject_UserRole_SET""(varSystemLoginSession, null::bigint, null::varchar, null::timestamptz, null::timestamptz, null::varchar, varInstitutionBranchID, varBaseCurrencyID, ", (IF(EXACT(B53, ""), "NULL", CONCATENATE("'", B53, "'"))),"::varchar);")) -> PERFORM "SchSysConfig"."Func_TblAppObject_UserRole_SET"(varSystemLoginSession, null::bigint, null::varchar, null::timestamptz, null::timestamptz, null::varchar, varInstitutionBranchID, varBaseCurrencyID, 'Procurement Coordinator'::varchar); | G53: =IF(EXACT($E53, ""), "", CONCATENATE( "varSQL := varSQL || (CASE WHEN (varSQL = '') THEN '' ELSE ', ' END) || (SELECT JSON_BUILD_OBJECT (", "'recordID', NULL::bigint,", "'entities', ", "JSON_BUILD_OBJECT (", "'sysLoginSession_RefID', varSystemLoginSession::bigint,", "'sysDataAnnotation', NULL::varchar,", "'sysDataSetDateTimeTZ', NULL::timestamptz,", "'sysDataValidityStartDateTimeTZ', NULL::timestamptz,", "'sysDataValidityFinishDateTimeTZ', NULL::timestamptz,", "'sysPartitionRemovableRecordKey_RefID', NULL::bigint,", "'sysBranch_RefID', varInstitutionBranchID::bigint,", "'sysBaseCurrency_RefID',varBaseCurrencyID::bigint,", "'name', ", IF(EXACT($B53, ""), "null", CONCATENATE("'", SUBSTITUTE($B53, "'", "\'"), "'")), "::varchar", ")))::varchar;")) -> varSQL := varSQL || (CASE WHEN (varSQL = '') THEN '' ELSE ', ' END) || (SELECT JSON_BUILD_OBJECT ('recordID', NULL::bigint,'entities', JSON_BUILD_OBJECT ('sysLoginSession_RefID', varSystemLoginSession::bigint,'sysDataAnnotation', NULL::varchar,'sysDataSetDateTimeTZ', NULL::timestamptz,'sysDataValidityStartDateTimeTZ', NULL::timestamptz,'sysDataValidityFinishDateTimeTZ', NULL::timestamptz,'sysPartitionRemovableRecordKey_RefID', NULL::bigint,'sysBranch_RefID', varInstitutionBranchID::bigint,'sysBaseCurrency_RefID',varBaseCurrencyID::bigint,'name', 'Procurement Coordinator'::varchar)))::varchar;
B54: Procurement Staff | D54: =D53 + IF(EXACT(E54, ""), 0, 1) -> 95000000000042 | E54: =IF(EXACT(B54, ""), "", CONCATENATE("PERFORM ""SchSysConfig"".""Func_TblAppObject_UserRole_SET""(varSystemLoginSession, null::bigint, null::varchar, null::timestamptz, null::timestamptz, null::varchar, varInstitutionBranchID, varBaseCurrencyID, ", (IF(EXACT(B54, ""), "NULL", CONCATENATE("'", B54, "'"))),"::varchar);")) -> PERFORM "SchSysConfig"."Func_TblAppObject_UserRole_SET"(varSystemLoginSession, null::bigint, null::varchar, null::timestamptz, null::timestamptz, null::varchar, varInstitutionBranchID, varBaseCurrencyID, 'Procurement Staff'::varchar); | G54: =IF(EXACT($E54, ""), "", CONCATENATE( "varSQL := varSQL || (CASE WHEN (varSQL = '') THEN '' ELSE ', ' END) || (SELECT JSON_BUILD_OBJECT (", "'recordID', NULL::bigint,", "'entities', ", "JSON_BUILD_OBJECT (", "'sysLoginSession_RefID', varSystemLoginSession::bigint,", "'sysDataAnnotation', NULL::varchar,", "'sysDataSetDateTimeTZ', NULL::timestamptz,", "'sysDataValidityStartDateTimeTZ', NULL::timestamptz,", "'sysDataValidityFinishDateTimeTZ', NULL::timestamptz,", "'sysPartitionRemovableRecordKey_RefID', NULL::bigint,", "'sysBranch_RefID', varInstitutionBranchID::bigint,", "'sysBaseCurrency_RefID',varBaseCurrencyID::bigint,", "'name', ", IF(EXACT($B54, ""), "null", CONCATENATE("'", SUBSTITUTE($B54, "'", "\'"), "'")), "::varchar", ")))::varchar;")) -> varSQL := varSQL || (CASE WHEN (varSQL = '') THEN '' ELSE ', ' END) || (SELECT JSON_BUILD_OBJECT ('recordID', NULL::bigint,'entities', JSON_BUILD_OBJECT ('sysLoginSession_RefID', varSystemLoginSession::bigint,'sysDataAnnotation', NULL::varchar,'sysDataSetDateTimeTZ', NULL::timestamptz,'sysDataValidityStartDateTimeTZ', NULL::timestamptz,'sysDataValidityFinishDateTimeTZ', NULL::timestamptz,'sysPartitionRemovableRecordKey_RefID', NULL::bigint,'sysBranch_RefID', varInstitutionBranchID::bigint,'sysBaseCurrency_RefID',varBaseCurrencyID::bigint,'name', 'Procurement Staff'::varchar)))::varchar;
D55: =D54 + IF(EXACT(E55, ""), 0, 1) -> 95000000000042 | E55: =IF(EXACT(B55, ""), "", CONCATENATE("PERFORM ""SchSysConfig"".""Func_TblAppObject_UserRole_SET""(varSystemLoginSession, null::bigint, null::varchar, null::timestamptz, null::timestamptz, null::varchar, varInstitutionBranchID, varBaseCurrencyID, ", (IF(EXACT(B55, ""), "NULL", CONCATENATE("'", B55, "'"))),"::varchar);")) | G55: =IF(EXACT($E55, ""), "", CONCATENATE( "varSQL := varSQL || (CASE WHEN (varSQL = '') THEN '' ELSE ', ' END) || (SELECT JSON_BUILD_OBJECT (", "'recordID', NULL::bigint,", "'entities', ", "JSON_BUILD_OBJECT (", "'sysLoginSession_RefID', varSystemLoginSession::bigint,", "'sysDataAnnotation', NULL::varchar,", "'sysDataSetDateTimeTZ', NULL::timestamptz,", "'sysDataValidityStartDateTimeTZ', NULL::timestamptz,", "'sysDataValidityFinishDateTimeTZ', NULL::timestamptz,", "'sysPartitionRemovableRecordKey_RefID', NULL::bigint,", "'sysBranch_RefID', varInstitutionBranchID::bigint,", "'sysBaseCurrency_RefID',varBaseCurrencyID::bigint,", "'name', ", IF(EXACT($B55, ""), "null", CONCATENATE("'", SUBSTITUTE($B55, "'", "\'"), "'")), "::varchar", ")))::varchar;"))
B56: Sales Manager | D56: =D55 + IF(EXACT(E56, ""), 0, 1) -> 95000000000043 | E56: =IF(EXACT(B56, ""), "", CONCATENATE("PERFORM ""SchSysConfig"".""Func_TblAppObject_UserRole_SET""(varSystemLoginSession, null::bigint, null::varchar, null::timestamptz, null::timestamptz, null::varchar, varInstitutionBranchID, varBaseCurrencyID, ", (IF(EXACT(B56, ""), "NULL", CONCATENATE("'", B56, "'"))),"::varchar);")) -> PERFORM "SchSysConfig"."Func_TblAppObject_UserRole_SET"(varSystemLoginSession, null::bigint, null::varchar, null::timestamptz, null::timestamptz, null::varchar, varInstitutionBranchID, varBaseCurrencyID, 'Sales Manager'::varchar); | G56: =IF(EXACT($E56, ""), "", CONCATENATE( "varSQL := varSQL || (CASE WHEN (varSQL = '') THEN '' ELSE ', ' END) || (SELECT JSON_BUILD_OBJECT (", "'recordID', NULL::bigint,", "'entities', ", "JSON_BUILD_OBJECT (", "'sysLoginSession_RefID', varSystemLoginSession::bigint,", "'sysDataAnnotation', NULL::varchar,", "'sysDataSetDateTimeTZ', NULL::timestamptz,", "'sysDataValidityStartDateTimeTZ', NULL::timestamptz,", "'sysDataValidityFinishDateTimeTZ', NULL::timestamptz,", "'sysPartitionRemovableRecordKey_RefID', NULL::bigint,", "'sysBranch_RefID', varInstitutionBranchID::bigint,", "'sysBaseCurrency_RefID',varBaseCurrencyID::bigint,", "'name', ", IF(EXACT($B56, ""), "null", CONCATENATE("'", SUBSTITUTE($B56, "'", "\'"), "'")), "::varchar", ")))::varchar;")) -> varSQL := varSQL || (CASE WHEN (varSQL = '') THEN '' ELSE ', ' END) || (SELECT JSON_BUILD_OBJECT ('recordID', NULL::bigint,'entities', JSON_BUILD_OBJECT ('sysLoginSession_RefID', varSystemLoginSession::bigint,'sysDataAnnotation', NULL::varchar,'sysDataSetDateTimeTZ', NULL::timestamptz,'sysDataValidityStartDateTimeTZ', NULL::timestamptz,'sysDataValidityFinishDateTimeTZ', NULL::timestamptz,'sysPartitionRemovableRecordKey_RefID', NULL::bigint,'sysBranch_RefID', varInstitutionBranchID::bigint,'sysBaseCurrency_RefID',varBaseCurrencyID::bigint,'name', 'Sales Manager'::varchar)))::varchar;
B57: Sales Coordinator | D57: =D56 + IF(EXACT(E57, ""), 0, 1) -> 95000000000044 | E57: =IF(EXACT(B57, ""), "", CONCATENATE("PERFORM ""SchSysConfig"".""Func_TblAppObject_UserRole_SET""(varSystemLoginSession, null::bigint, null::varchar, null::timestamptz, null::timestamptz, null::varchar, varInstitutionBranchID, varBaseCurrencyID, ", (IF(EXACT(B57, ""), "NULL", CONCATENATE("'", B57, "'"))),"::varchar);")) -> PERFORM "SchSysConfig"."Func_TblAppObject_UserRole_SET"(varSystemLoginSession, null::bigint, null::varchar, null::timestamptz, null::timestamptz, null::varchar, varInstitutionBranchID, varBaseCurrencyID, 'Sales Coordinator'::varchar); | G57: =IF(EXACT($E57, ""), "", CONCATENATE( "varSQL := varSQL || (CASE WHEN (varSQL = '') THEN '' ELSE ', ' END) || (SELECT JSON_BUILD_OBJECT (", "'recordID', NULL::bigint,", "'entities', ", "JSON_BUILD_OBJECT (", "'sysLoginSession_RefID', varSystemLoginSession::bigint,", "'sysDataAnnotation', NULL::varchar,", "'sysDataSetDateTimeTZ', NULL::timestamptz,", "'sysDataValidityStartDateTimeTZ', NULL::timestamptz,", "'sysDataValidityFinishDateTimeTZ', NULL::timestamptz,", "'sysPartitionRemovableRecordKey_RefID', NULL::bigint,", "'sysBranch_RefID', varInstitutionBranchID::bigint,", "'sysBaseCurrency_RefID',varBaseCurrencyID::bigint,", "'name', ", IF(EXACT($B57, ""), "null", CONCATENATE("'", SUBSTITUTE($B57, "'", "\'"), "'")), "::varchar", ")))::varchar;")) -> varSQL := varSQL || (CASE WHEN (varSQL = '') THEN '' ELSE ', ' END) || (SELECT JSON_BUILD_OBJECT ('recordID', NULL::bigint,'entities', JSON_BUILD_OBJECT ('sysLoginSession_RefID', varSystemLoginSession::bigint,'sysDataAnnotation', NULL::varchar,'sysDataSetDateTimeTZ', NULL::timestamptz,'sysDataValidityStartDateTimeTZ', NULL::timestamptz,'sysDataValidityFinishDateTimeTZ', NULL::timestamptz,'sysPartitionRemovableRecordKey_RefID', NULL::bigint,'sysBranch_RefID', varInstitutionBranchID::bigint,'sysBaseCurrency_RefID',varBaseCurrencyID::bigint,'name', 'Sales Coordinator'::varchar)))::varchar;
B58: Bid And Sales Administrator Staff | D58: =D57 + IF(EXACT(E58, ""), 0, 1) -> 95000000000045 | E58: =IF(EXACT(B58, ""), "", CONCATENATE("PERFORM ""SchSysConfig"".""Func_TblAppObject_UserRole_SET""(varSystemLoginSession, null::bigint, null::varchar, null::timestamptz, null::timestamptz, null::varchar, varInstitutionBranchID, varBaseCurrencyID, ", (IF(EXACT(B58, ""), "NULL", CONCATENATE("'", B58, "'"))),"::varchar);")) -> PERFORM "SchSysConfig"."Func_TblAppObject_UserRole_SET"(varSystemLoginSession, null::bigint, null::varchar, null::timestamptz, null::timestamptz, null::varchar, varInstitutionBranchID, varBaseCurrencyID, 'Bid And Sales Administrator Staff'::varchar); | G58: =IF(EXACT($E58, ""), "", CONCATENATE( "varSQL := varSQL || (CASE WHEN (varSQL = '') THEN '' ELSE ', ' END) || (SELECT JSON_BUILD_OBJECT (", "'recordID', NULL::bigint,", "'entities', ", "JSON_BUILD_OBJECT (", "'sysLoginSession_RefID', varSystemLoginSession::bigint,", "'sysDataAnnotation', NULL::varchar,", "'sysDataSetDateTimeTZ', NULL::timestamptz,", "'sysDataValidityStartDateTimeTZ', NULL::timestamptz,", "'sysDataValidityFinishDateTimeTZ', NULL::timestamptz,", "'sysPartitionRemovableRecordKey_RefID', NULL::bigint,", "'sysBranch_RefID', varInstitutionBranchID::bigint,", "'sysBaseCurrency_RefID',varBaseCurrencyID::bigint,", "'name', ", IF(EXACT($B58, ""), "null", CONCATENATE("'", SUBSTITUTE($B58, "'", "\'"), "'")), "::varchar", ")))::varchar;")) -> varSQL := varSQL || (CASE WHEN (varSQL = '') THEN '' ELSE ', ' END) || (SELECT JSON_BUILD_OBJECT ('recordID', NULL::bigint,'entities', JSON_BUILD_OBJECT ('sysLoginSession_RefID', varSystemLoginSession::bigint,'sysDataAnnotation', NULL::varchar,'sysDataSetDateTimeTZ', NULL::timestamptz,'sysDataValidityStartDateTimeTZ', NULL::timestamptz,'sysDataValidityFinishDateTimeTZ', NULL::timestamptz,'sysPartitionRemovableRecordKey_RefID', NULL::bigint,'sysBranch_RefID', varInstitutionBranchID::bigint,'sysBaseCurrency_RefID',varBaseCurrencyID::bigint,'name', 'Bid And Sales Administrator Staff'::varchar)))::varchar;
B59: Sales Estimator Coordinator | D59: =D58 + IF(EXACT(E59, ""), 0, 1) -> 95000000000046 | E59: =IF(EXACT(B59, ""), "", CONCATENATE("PERFORM ""SchSysConfig"".""Func_TblAppObject_UserRole_SET""(varSystemLoginSession, null::bigint, null::varchar, null::timestamptz, null::timestamptz, null::varchar, varInstitutionBranchID, varBaseCurrencyID, ", (IF(EXACT(B59, ""), "NULL", CONCATENATE("'", B59, "'"))),"::varchar);")) -> PERFORM "SchSysConfig"."Func_TblAppObject_UserRole_SET"(varSystemLoginSession, null::bigint, null::varchar, null::timestamptz, null::timestamptz, null::varchar, varInstitutionBranchID, varBaseCurrencyID, 'Sales Estimator Coordinator'::varchar); | G59: =IF(EXACT($E59, ""), "", CONCATENATE( "varSQL := varSQL || (CASE WHEN (varSQL = '') THEN '' ELSE ', ' END) || (SELECT JSON_BUILD_OBJECT (", "'recordID', NULL::bigint,", "'entities', ", "JSON_BUILD_OBJECT (", "'sysLoginSession_RefID', varSystemLoginSession::bigint,", "'sysDataAnnotation', NULL::varchar,", "'sysDataSetDateTimeTZ', NULL::timestamptz,", "'sysDataValidityStartDateTimeTZ', NULL::timestamptz,", "'sysDataValidityFinishDateTimeTZ', NULL::timestamptz,", "'sysPartitionRemovableRecordKey_RefID', NULL::bigint,", "'sysBranch_RefID', varInstitutionBranchID::bigint,", "'sysBaseCurrency_RefID',varBaseCurrencyID::bigint,", "'name', ", IF(EXACT($B59, ""), "null", CONCATENATE("'", SUBSTITUTE($B59, "'", "\'"), "'")), "::varchar", ")))::varchar;")) -> varSQL := varSQL || (CASE WHEN (varSQL = '') THEN '' ELSE ', ' END) || (SELECT JSON_BUILD_OBJECT ('recordID', NULL::bigint,'entities', JSON_BUILD_OBJECT ('sysLoginSession_RefID', varSystemLoginSession::bigint,'sysDataAnnotation', NULL::varchar,'sysDataSetDateTimeTZ', NULL::timestamptz,'sysDataValidityStartDateTimeTZ', NULL::timestamptz,'sysDataValidityFinishDateTimeTZ', NULL::timestamptz,'sysPartitionRemovableRecordKey_RefID', NULL::bigint,'sysBranch_RefID', varInstitutionBranchID::bigint,'sysBaseCurrency_RefID',varBaseCurrencyID::bigint,'name', 'Sales Estimator Coordinator'::varchar)))::varchar;
B60: Sales Estimator Staff | D60: =D59 + IF(EXACT(E60, ""), 0, 1) -> 95000000000047 | E60: =IF(EXACT(B60, ""), "", CONCATENATE("PERFORM ""SchSysConfig"".""Func_TblAppObject_UserRole_SET""(varSystemLoginSession, null::bigint, null::varchar, null::timestamptz, null::timestamptz, null::varchar, varInstitutionBranchID, varBaseCurrencyID, ", (IF(EXACT(B60, ""), "NULL", CONCATENATE("'", B60, "'"))),"::varchar);")) -> PERFORM "SchSysConfig"."Func_TblAppObject_UserRole_SET"(varSystemLoginSession, null::bigint, null::varchar, null::timestamptz, null::timestamptz, null::varchar, varInstitutionBranchID, varBaseCurrencyID, 'Sales Estimator Staff'::varchar); | G60: =IF(EXACT($E60, ""), "", CONCATENATE( "varSQL := varSQL || (CASE WHEN (varSQL = '') THEN '' ELSE ', ' END) || (SELECT JSON_BUILD_OBJECT (", "'recordID', NULL::bigint,", "'entities', ", "JSON_BUILD_OBJECT (", "'sysLoginSession_RefID', varSystemLoginSession::bigint,", "'sysDataAnnotation', NULL::varchar,", "'sysDataSetDateTimeTZ', NULL::timestamptz,", "'sysDataValidityStartDateTimeTZ', NULL::timestamptz,", "'sysDataValidityFinishDateTimeTZ', NULL::timestamptz,", "'sysPartitionRemovableRecordKey_RefID', NULL::bigint,", "'sysBranch_RefID', varInstitutionBranchID::bigint,", "'sysBaseCurrency_RefID',varBaseCurrencyID::bigint,", "'name', ", IF(EXACT($B60, ""), "null", CONCATENATE("'", SUBSTITUTE($B60, "'", "\'"), "'")), "::varchar", ")))::varchar;")) -> varSQL := varSQL || (CASE WHEN (varSQL = '') THEN '' ELSE ', ' END) || (SELECT JSON_BUILD_OBJECT ('recordID', NULL::bigint,'entities', JSON_BUILD_OBJECT ('sysLoginSession_RefID', varSystemLoginSession::bigint,'sysDataAnnotation', NULL::varchar,'sysDataSetDateTimeTZ', NULL::timestamptz,'sysDataValidityStartDateTimeTZ', NULL::timestamptz,'sysDataValidityFinishDateTimeTZ', NULL::timestamptz,'sysPartitionRemovableRecordKey_RefID', NULL::bigint,'sysBranch_RefID', varInstitutionBranchID::bigint,'sysBaseCurrency_RefID',varBaseCurrencyID::bigint,'name', 'Sales Estimator Staff'::varchar)))::varchar;
D61: =D60 + IF(EXACT(E61, ""), 0, 1) -> 95000000000047 | E61: =IF(EXACT(B61, ""), "", CONCATENATE("PERFORM ""SchSysConfig"".""Func_TblAppObject_UserRole_SET""(varSystemLoginSession, null::bigint, null::varchar, null::timestamptz, null::timestamptz, null::varchar, varInstitutionBranchID, varBaseCurrencyID, ", (IF(EXACT(B61, ""), "NULL", CONCATENATE("'", B61, "'"))),"::varchar);")) | G61: =IF(EXACT($E61, ""), "", CONCATENATE( "varSQL := varSQL || (CASE WHEN (varSQL = '') THEN '' ELSE ', ' END) || (SELECT JSON_BUILD_OBJECT (", "'recordID', NULL::bigint,", "'entities', ", "JSON_BUILD_OBJECT (", "'sysLoginSession_RefID', varSystemLoginSession::bigint,", "'sysDataAnnotation', NULL::varchar,", "'sysDataSetDateTimeTZ', NULL::timestamptz,", "'sysDataValidityStartDateTimeTZ', NULL::timestamptz,", "'sysDataValidityFinishDateTimeTZ', NULL::timestamptz,", "'sysPartitionRemovableRecordKey_RefID', NULL::bigint,", "'sysBranch_RefID', varInstitutionBranchID::bigint,", "'sysBaseCurrency_RefID',varBaseCurrencyID::bigint,", "'name', ", IF(EXACT($B61, ""), "null", CONCATENATE("'", SUBSTITUTE($B61, "'", "\'"), "'")), "::varchar", ")))::varchar;"))
B62: Health Safety Environment Manager | D62: =D61 + IF(EXACT(E62, ""), 0, 1) -> 95000000000048 | E62: =IF(EXACT(B62, ""), "", CONCATENATE("PERFORM ""SchSysConfig"".""Func_TblAppObject_UserRole_SET""(varSystemLoginSession, null::bigint, null::varchar, null::timestamptz, null::timestamptz, null::varchar, varInstitutionBranchID, varBaseCurrencyID, ", (IF(EXACT(B62, ""), "NULL", CONCATENATE("'", B62, "'"))),"::varchar);")) -> PERFORM "SchSysConfig"."Func_TblAppObject_UserRole_SET"(varSystemLoginSession, null::bigint, null::varchar, null::timestamptz, null::timestamptz, null::varchar, varInstitutionBranchID, varBaseCurrencyID, 'Health Safety Environment Manager'::varchar); | G62: =IF(EXACT($E62, ""), "", CONCATENATE( "varSQL := varSQL || (CASE WHEN (varSQL = '') THEN '' ELSE ', ' END) || (SELECT JSON_BUILD_OBJECT (", "'recordID', NULL::bigint,", "'entities', ", "JSON_BUILD_OBJECT (", "'sysLoginSession_RefID', varSystemLoginSession::bigint,", "'sysDataAnnotation', NULL::varchar,", "'sysDataSetDateTimeTZ', NULL::timestamptz,", "'sysDataValidityStartDateTimeTZ', NULL::timestamptz,", "'sysDataValidityFinishDateTimeTZ', NULL::timestamptz,", "'sysPartitionRemovableRecordKey_RefID', NULL::bigint,", "'sysBranch_RefID', varInstitutionBranchID::bigint,", "'sysBaseCurrency_RefID',varBaseCurrencyID::bigint,", "'name', ", IF(EXACT($B62, ""), "null", CONCATENATE("'", SUBSTITUTE($B62, "'", "\'"), "'")), "::varchar", ")))::varchar;")) -> varSQL := varSQL || (CASE WHEN (varSQL = '') THEN '' ELSE ', ' END) || (SELECT JSON_BUILD_OBJECT ('recordID', NULL::bigint,'entities', JSON_BUILD_OBJECT ('sysLoginSession_RefID', varSystemLoginSession::bigint,'sysDataAnnotation', NULL::varchar,'sysDataSetDateTimeTZ', NULL::timestamptz,'sysDataValidityStartDateTimeTZ', NULL::timestamptz,'sysDataValidityFinishDateTimeTZ', NULL::timestamptz,'sysPartitionRemovableRecordKey_RefID', NULL::bigint,'sysBranch_RefID', varInstitutionBranchID::bigint,'sysBaseCurrency_RefID',varBaseCurrencyID::bigint,'name', 'Health Safety Environment Manager'::varchar)))::varchar;
B63: Health Safety Environment Coordinator | D63: =D62 + IF(EXACT(E63, ""), 0, 1) -> 95000000000049 | E63: =IF(EXACT(B63, ""), "", CONCATENATE("PERFORM ""SchSysConfig"".""Func_TblAppObject_UserRole_SET""(varSystemLoginSession, null::bigint, null::varchar, null::timestamptz, null::timestamptz, null::varchar, varInstitutionBranchID, varBaseCurrencyID, ", (IF(EXACT(B63, ""), "NULL", CONCATENATE("'", B63, "'"))),"::varchar);")) -> PERFORM "SchSysConfig"."Func_TblAppObject_UserRole_SET"(varSystemLoginSession, null::bigint, null::varchar, null::timestamptz, null::timestamptz, null::varchar, varInstitutionBranchID, varBaseCurrencyID, 'Health Safety Environment Coordinator'::varchar); | G63: =IF(EXACT($E63, ""), "", CONCATENATE( "varSQL := varSQL || (CASE WHEN (varSQL = '') THEN '' ELSE ', ' END) || (SELECT JSON_BUILD_OBJECT (", "'recordID', NULL::bigint,", "'entities', ", "JSON_BUILD_OBJECT (", "'sysLoginSession_RefID', varSystemLoginSession::bigint,", "'sysDataAnnotation', NULL::varchar,", "'sysDataSetDateTimeTZ', NULL::timestamptz,", "'sysDataValidityStartDateTimeTZ', NULL::timestamptz,", "'sysDataValidityFinishDateTimeTZ', NULL::timestamptz,", "'sysPartitionRemovableRecordKey_RefID', NULL::bigint,", "'sysBranch_RefID', varInstitutionBranchID::bigint,", "'sysBaseCurrency_RefID',varBaseCurrencyID::bigint,", "'name', ", IF(EXACT($B63, ""), "null", CONCATENATE("'", SUBSTITUTE($B63, "'", "\'"), "'")), "::varchar", ")))::varchar;")) -> varSQL := varSQL || (CASE WHEN (varSQL = '') THEN '' ELSE ', ' END) || (SELECT JSON_BUILD_OBJECT ('recordID', NULL::bigint,'entities', JSON_BUILD_OBJECT ('sysLoginSession_RefID', varSystemLoginSession::bigint,'sysDataAnnotation', NULL::varchar,'sysDataSetDateTimeTZ', NULL::timestamptz,'sysDataValidityStartDateTimeTZ', NULL::timestamptz,'sysDataValidityFinishDateTimeTZ', NULL::timestamptz,'sysPartitionRemovableRecordKey_RefID', NULL::bigint,'sysBranch_RefID', varInstitutionBranchID::bigint,'sysBaseCurrency_RefID',varBaseCurrencyID::bigint,'name', 'Health Safety Environment Coordinator'::varchar)))::varchar;
B64: Health Safety Environment Staff | D64: =D63 + IF(EXACT(E64, ""), 0, 1) -> 95000000000050 | E64: =IF(EXACT(B64, ""), "", CONCATENATE("PERFORM ""SchSysConfig"".""Func_TblAppObject_UserRole_SET""(varSystemLoginSession, null::bigint, null::varchar, null::timestamptz, null::timestamptz, null::varchar, varInstitutionBranchID, varBaseCurrencyID, ", (IF(EXACT(B64, ""), "NULL", CONCATENATE("'", B64, "'"))),"::varchar);")) -> PERFORM "SchSysConfig"."Func_TblAppObject_UserRole_SET"(varSystemLoginSession, null::bigint, null::varchar, null::timestamptz, null::timestamptz, null::varchar, varInstitutionBranchID, varBaseCurrencyID, 'Health Safety Environment Staff'::varchar); | G64: =IF(EXACT($E64, ""), "", CONCATENATE( "varSQL := varSQL || (CASE WHEN (varSQL = '') THEN '' ELSE ', ' END) || (SELECT JSON_BUILD_OBJECT (", "'recordID', NULL::bigint,", "'entities', ", "JSON_BUILD_OBJECT (", "'sysLoginSession_RefID', varSystemLoginSession::bigint,", "'sysDataAnnotation', NULL::varchar,", "'sysDataSetDateTimeTZ', NULL::timestamptz,", "'sysDataValidityStartDateTimeTZ', NULL::timestamptz,", "'sysDataValidityFinishDateTimeTZ', NULL::timestamptz,", "'sysPartitionRemovableRecordKey_RefID', NULL::bigint,", "'sysBranch_RefID', varInstitutionBranchID::bigint,", "'sysBaseCurrency_RefID',varBaseCurrencyID::bigint,", "'name', ", IF(EXACT($B64, ""), "null", CONCATENATE("'", SUBSTITUTE($B64, "'", "\'"), "'")), "::varchar", ")))::varchar;")) -> varSQL := varSQL || (CASE WHEN (varSQL = '') THEN '' ELSE ', ' END) || (SELECT JSON_BUILD_OBJECT ('recordID', NULL::bigint,'entities', JSON_BUILD_OBJECT ('sysLoginSession_RefID', varSystemLoginSession::bigint,'sysDataAnnotation', NULL::varchar,'sysDataSetDateTimeTZ', NULL::timestamptz,'sysDataValidityStartDateTimeTZ', NULL::timestamptz,'sysDataValidityFinishDateTimeTZ', NULL::timestamptz,'sysPartitionRemovableRecordKey_RefID', NULL::bigint,'sysBranch_RefID', varInstitutionBranchID::bigint,'sysBaseCurrency_RefID',varBaseCurrencyID::bigint,'name', 'Health Safety Environment Staff'::varchar)))::varchar;
D65: =D64 + IF(EXACT(E65, ""), 0, 1) -> 95000000000050 | E65: =IF(EXACT(B65, ""), "", CONCATENATE("PERFORM ""SchSysConfig"".""Func_TblAppObject_UserRole_SET""(varSystemLoginSession, null::bigint, null::varchar, null::timestamptz, null::timestamptz, null::varchar, varInstitutionBranchID, varBaseCurrencyID, ", (IF(EXACT(B65, ""), "NULL", CONCATENATE("'", B65, "'"))),"::varchar);")) | G65: =IF(EXACT($E65, ""), "", CONCATENATE( "varSQL := varSQL || (CASE WHEN (varSQL = '') THEN '' ELSE ', ' END) || (SELECT JSON_BUILD_OBJECT (", "'recordID', NULL::bigint,", "'entities', ", "JSON_BUILD_OBJECT (", "'sysLoginSession_RefID', varSystemLoginSession::bigint,", "'sysDataAnnotation', NULL::varchar,", "'sysDataSetDateTimeTZ', NULL::timestamptz,", "'sysDataValidityStartDateTimeTZ', NULL::timestamptz,", "'sysDataValidityFinishDateTimeTZ', NULL::timestamptz,", "'sysPartitionRemovableRecordKey_RefID', NULL::bigint,", "'sysBranch_RefID', varInstitutionBranchID::bigint,", "'sysBaseCurrency_RefID',varBaseCurrencyID::bigint,", "'name', ", IF(EXACT($B65, ""), "null", CONCATENATE("'", SUBSTITUTE($B65, "'", "\'"), "'")), "::varchar", ")))::varchar;"))
B66: Human Resource Development Manager | D66: =D65 + IF(EXACT(E66, ""), 0, 1) -> 95000000000051 | E66: =IF(EXACT(B66, ""), "", CONCATENATE("PERFORM ""SchSysConfig"".""Func_TblAppObject_UserRole_SET""(varSystemLoginSession, null::bigint, null::varchar, null::timestamptz, null::timestamptz, null::varchar, varInstitutionBranchID, varBaseCurrencyID, ", (IF(EXACT(B66, ""), "NULL", CONCATENATE("'", B66, "'"))),"::varchar);")) -> PERFORM "SchSysConfig"."Func_TblAppObject_UserRole_SET"(varSystemLoginSession, null::bigint, null::varchar, null::timestamptz, null::timestamptz, null::varchar, varInstitutionBranchID, varBaseCurrencyID, 'Human Resource Development Manager'::varchar); | G66: =IF(EXACT($E66, ""), "", CONCATENATE( "varSQL := varSQL || (CASE WHEN (varSQL = '') THEN '' ELSE ', ' END) || (SELECT JSON_BUILD_OBJECT (", "'recordID', NULL::bigint,", "'entities', ", "JSON_BUILD_OBJECT (", "'sysLoginSession_RefID', varSystemLoginSession::bigint,", "'sysDataAnnotation', NULL::varchar,", "'sysDataSetDateTimeTZ', NULL::timestamptz,", "'sysDataValidityStartDateTimeTZ', NULL::timestamptz,", "'sysDataValidityFinishDateTimeTZ', NULL::timestamptz,", "'sysPartitionRemovableRecordKey_RefID', NULL::bigint,", "'sysBranch_RefID', varInstitutionBranchID::bigint,", "'sysBaseCurrency_RefID',varBaseCurrencyID::bigint,", "'name', ", IF(EXACT($B66, ""), "null", CONCATENATE("'", SUBSTITUTE($B66, "'", "\'"), "'")), "::varchar", ")))::varchar;")) -> varSQL := varSQL || (CASE WHEN (varSQL = '') THEN '' ELSE ', ' END) || (SELECT JSON_BUILD_OBJECT ('recordID', NULL::bigint,'entities', JSON_BUILD_OBJECT ('sysLoginSession_RefID', varSystemLoginSession::bigint,'sysDataAnnotation', NULL::varchar,'sysDataSetDateTimeTZ', NULL::timestamptz,'sysDataValidityStartDateTimeTZ', NULL::timestamptz,'sysDataValidityFinishDateTimeTZ', NULL::timestamptz,'sysPartitionRemovableRecordKey_RefID', NULL::bigint,'sysBranch_RefID', varInstitutionBranchID::bigint,'sysBaseCurrency_RefID',varBaseCurrencyID::bigint,'name', 'Human Resource Development Manager'::varchar)))::varchar;
B67: Human Resource Development Coordinator | D67: =D66 + IF(EXACT(E67, ""), 0, 1) -> 95000000000052 | E67: =IF(EXACT(B67, ""), "", CONCATENATE("PERFORM ""SchSysConfig"".""Func_TblAppObject_UserRole_SET""(varSystemLoginSession, null::bigint, null::varchar, null::timestamptz, null::timestamptz, null::varchar, varInstitutionBranchID, varBaseCurrencyID, ", (IF(EXACT(B67, ""), "NULL", CONCATENATE("'", B67, "'"))),"::varchar);")) -> PERFORM "SchSysConfig"."Func_TblAppObject_UserRole_SET"(varSystemLoginSession, null::bigint, null::varchar, null::timestamptz, null::timestamptz, null::varchar, varInstitutionBranchID, varBaseCurrencyID, 'Human Resource Development Coordinator'::varchar); | G67: =IF(EXACT($E67, ""), "", CONCATENATE( "varSQL := varSQL || (CASE WHEN (varSQL = '') THEN '' ELSE ', ' END) || (SELECT JSON_BUILD_OBJECT (", "'recordID', NULL::bigint,", "'entities', ", "JSON_BUILD_OBJECT (", "'sysLoginSession_RefID', varSystemLoginSession::bigint,", "'sysDataAnnotation', NULL::varchar,", "'sysDataSetDateTimeTZ', NULL::timestamptz,", "'sysDataValidityStartDateTimeTZ', NULL::timestamptz,", "'sysDataValidityFinishDateTimeTZ', NULL::timestamptz,", "'sysPartitionRemovableRecordKey_RefID', NULL::bigint,", "'sysBranch_RefID', varInstitutionBranchID::bigint,", "'sysBaseCurrency_RefID',varBaseCurrencyID::bigint,", "'name', ", IF(EXACT($B67, ""), "null", CONCATENATE("'", SUBSTITUTE($B67, "'", "\'"), "'")), "::varchar", ")))::varchar;")) -> varSQL := varSQL || (CASE WHEN (varSQL = '') THEN '' ELSE ', ' END) || (SELECT JSON_BUILD_OBJECT ('recordID', NULL::bigint,'entities', JSON_BUILD_OBJECT ('sysLoginSession_RefID', varSystemLoginSession::bigint,'sysDataAnnotation', NULL::varchar,'sysDataSetDateTimeTZ', NULL::timestamptz,'sysDataValidityStartDateTimeTZ', NULL::timestamptz,'sysDataValidityFinishDateTimeTZ', NULL::timestamptz,'sysPartitionRemovableRecordKey_RefID', NULL::bigint,'sysBranch_RefID', varInstitutionBranchID::bigint,'sysBaseCurrency_RefID',varBaseCurrencyID::bigint,'name', 'Human Resource Development Coordinator'::varchar)))::varchar;
B68: Human Resource Development Staff | D68: =D67 + IF(EXACT(E68, ""), 0, 1) -> 95000000000053 | E68: =IF(EXACT(B68, ""), "", CONCATENATE("PERFORM ""SchSysConfig"".""Func_TblAppObject_UserRole_SET""(varSystemLoginSession, null::bigint, null::varchar, null::timestamptz, null::timestamptz, null::varchar, varInstitutionBranchID, varBaseCurrencyID, ", (IF(EXACT(B68, ""), "NULL", CONCATENATE("'", B68, "'"))),"::varchar);")) -> PERFORM "SchSysConfig"."Func_TblAppObject_UserRole_SET"(varSystemLoginSession, null::bigint, null::varchar, null::timestamptz, null::timestamptz, null::varchar, varInstitutionBranchID, varBaseCurrencyID, 'Human Resource Development Staff'::varchar); | G68: =IF(EXACT($E68, ""), "", CONCATENATE( "varSQL := varSQL || (CASE WHEN (varSQL = '') THEN '' ELSE ', ' END) || (SELECT JSON_BUILD_OBJECT (", "'recordID', NULL::bigint,", "'entities', ", "JSON_BUILD_OBJECT (", "'sysLoginSession_RefID', varSystemLoginSession::bigint,", "'sysDataAnnotation', NULL::varchar,", "'sysDataSetDateTimeTZ', NULL::timestamptz,", "'sysDataValidityStartDateTimeTZ', NULL::timestamptz,", "'sysDataValidityFinishDateTimeTZ', NULL::timestamptz,", "'sysPartitionRemovableRecordKey_RefID', NULL::bigint,", "'sysBranch_RefID', varInstitutionBranchID::bigint,", "'sysBaseCurrency_RefID',varBaseCurrencyID::bigint,", "'name', ", IF(EXACT($B68, ""), "null", CONCATENATE("'", SUBSTITUTE($B68, "'", "\'"), "'")), "::varchar", ")))::varchar;")) -> varSQL := varSQL || (CASE WHEN (varSQL = '') THEN '' ELSE ', ' END) || (SELECT JSON_BUILD_OBJECT ('recordID', NULL::bigint,'entities', JSON_BUILD_OBJECT ('sysLoginSession_RefID', varSystemLoginSession::bigint,'sysDataAnnotation', NULL::varchar,'sysDataSetDateTimeTZ', NULL::timestamptz,'sysDataValidityStartDateTimeTZ', NULL::timestamptz,'sysDataValidityFinishDateTimeTZ', NULL::timestamptz,'sysPartitionRemovableRecordKey_RefID', NULL::bigint,'sysBranch_RefID', varInstitutionBranchID::bigint,'sysBaseCurrency_RefID',varBaseCurrencyID::bigint,'name', 'Human Resource Development Staff'::varchar)))::varchar;
D69: =D68 + IF(EXACT(E69, ""), 0, 1) -> 95000000000053 | E69: =IF(EXACT(B69, ""), "", CONCATENATE("PERFORM ""SchSysConfig"".""Func_TblAppObject_UserRole_SET""(varSystemLoginSession, null::bigint, null::varchar, null::timestamptz, null::timestamptz, null::varchar, varInstitutionBranchID, varBaseCurrencyID, ", (IF(EXACT(B69, ""), "NULL", CONCATENATE("'", B69, "'"))),"::varchar);")) | G69: =IF(EXACT($E69, ""), "", CONCATENATE( "varSQL := varSQL || (CASE WHEN (varSQL = '') THEN '' ELSE ', ' END) || (SELECT JSON_BUILD_OBJECT (", "'recordID', NULL::bigint,", "'entities', ", "JSON_BUILD_OBJECT (", "'sysLoginSession_RefID', varSystemLoginSession::bigint,", "'sysDataAnnotation', NULL::varchar,", "'sysDataSetDateTimeTZ', NULL::timestamptz,", "'sysDataValidityStartDateTimeTZ', NULL::timestamptz,", "'sysDataValidityFinishDateTimeTZ', NULL::timestamptz,", "'sysPartitionRemovableRecordKey_RefID', NULL::bigint,", "'sysBranch_RefID', varInstitutionBranchID::bigint,", "'sysBaseCurrency_RefID',varBaseCurrencyID::bigint,", "'name', ", IF(EXACT($B69, ""), "null", CONCATENATE("'", SUBSTITUTE($B69, "'", "\'"), "'")), "::varchar", ")))::varchar;"))
B70: General Affairs Manager | D70: =D69 + IF(EXACT(E70, ""), 0, 1) -> 95000000000054 | E70: =IF(EXACT(B70, ""), "", CONCATENATE("PERFORM ""SchSysConfig"".""Func_TblAppObject_UserRole_SET""(varSystemLoginSession, null::bigint, null::varchar, null::timestamptz, null::timestamptz, null::varchar, varInstitutionBranchID, varBaseCurrencyID, ", (IF(EXACT(B70, ""), "NULL", CONCATENATE("'", B70, "'"))),"::varchar);")) -> PERFORM "SchSysConfig"."Func_TblAppObject_UserRole_SET"(varSystemLoginSession, null::bigint, null::varchar, null::timestamptz, null::timestamptz, null::varchar, varInstitutionBranchID, varBaseCurrencyID, 'General Affairs Manager'::varchar); | G70: =IF(EXACT($E70, ""), "", CONCATENATE( "varSQL := varSQL || (CASE WHEN (varSQL = '') THEN '' ELSE ', ' END) || (SELECT JSON_BUILD_OBJECT (", "'recordID', NULL::bigint,", "'entities', ", "JSON_BUILD_OBJECT (", "'sysLoginSession_RefID', varSystemLoginSession::bigint,", "'sysDataAnnotation', NULL::varchar,", "'sysDataSetDateTimeTZ', NULL::timestamptz,", "'sysDataValidityStartDateTimeTZ', NULL::timestamptz,", "'sysDataValidityFinishDateTimeTZ', NULL::timestamptz,", "'sysPartitionRemovableRecordKey_RefID', NULL::bigint,", "'sysBranch_RefID', varInstitutionBranchID::bigint,", "'sysBaseCurrency_RefID',varBaseCurrencyID::bigint,", "'name', ", IF(EXACT($B70, ""), "null", CONCATENATE("'", SUBSTITUTE($B70, "'", "\'"), "'")), "::varchar", ")))::varchar;")) -> varSQL := varSQL || (CASE WHEN (varSQL = '') THEN '' ELSE ', ' END) || (SELECT JSON_BUILD_OBJECT ('recordID', NULL::bigint,'entities', JSON_BUILD_OBJECT ('sysLoginSession_RefID', varSystemLoginSession::bigint,'sysDataAnnotation', NULL::varchar,'sysDataSetDateTimeTZ', NULL::timestamptz,'sysDataValidityStartDateTimeTZ', NULL::timestamptz,'sysDataValidityFinishDateTimeTZ', NULL::timestamptz,'sysPartitionRemovableRecordKey_RefID', NULL::bigint,'sysBranch_RefID', varInstitutionBranchID::bigint,'sysBaseCurrency_RefID',varBaseCurrencyID::bigint,'name', 'General Affairs Manager'::varchar)))::varchar;
B71: General Affairs Coordinator | D71: =D70 + IF(EXACT(E71, ""), 0, 1) -> 95000000000055 | E71: =IF(EXACT(B71, ""), "", CONCATENATE("PERFORM ""SchSysConfig"".""Func_TblAppObject_UserRole_SET""(varSystemLoginSession, null::bigint, null::varchar, null::timestamptz, null::timestamptz, null::varchar, varInstitutionBranchID, varBaseCurrencyID, ", (IF(EXACT(B71, ""), "NULL", CONCATENATE("'", B71, "'"))),"::varchar);")) -> PERFORM "SchSysConfig"."Func_TblAppObject_UserRole_SET"(varSystemLoginSession, null::bigint, null::varchar, null::timestamptz, null::timestamptz, null::varchar, varInstitutionBranchID, varBaseCurrencyID, 'General Affairs Coordinator'::varchar); | G71: =IF(EXACT($E71, ""), "", CONCATENATE( "varSQL := varSQL || (CASE WHEN (varSQL = '') THEN '' ELSE ', ' END) || (SELECT JSON_BUILD_OBJECT (", "'recordID', NULL::bigint,", "'entities', ", "JSON_BUILD_OBJECT (", "'sysLoginSession_RefID', varSystemLoginSession::bigint,", "'sysDataAnnotation', NULL::varchar,", "'sysDataSetDateTimeTZ', NULL::timestamptz,", "'sysDataValidityStartDateTimeTZ', NULL::timestamptz,", "'sysDataValidityFinishDateTimeTZ', NULL::timestamptz,", "'sysPartitionRemovableRecordKey_RefID', NULL::bigint,", "'sysBranch_RefID', varInstitutionBranchID::bigint,", "'sysBaseCurrency_RefID',varBaseCurrencyID::bigint,", "'name', ", IF(EXACT($B71, ""), "null", CONCATENATE("'", SUBSTITUTE($B71, "'", "\'"), "'")), "::varchar", ")))::varchar;")) -> varSQL := varSQL || (CASE WHEN (varSQL = '') THEN '' ELSE ', ' END) || (SELECT JSON_BUILD_OBJECT ('recordID', NULL::bigint,'entities', JSON_BUILD_OBJECT ('sysLoginSession_RefID', varSystemLoginSession::bigint,'sysDataAnnotation', NULL::varchar,'sysDataSetDateTimeTZ', NULL::timestamptz,'sysDataValidityStartDateTimeTZ', NULL::timestamptz,'sysDataValidityFinishDateTimeTZ', NULL::timestamptz,'sysPartitionRemovableRecordKey_RefID', NULL::bigint,'sysBranch_RefID', varInstitutionBranchID::bigint,'sysBaseCurrency_RefID',varBaseCurrencyID::bigint,'name', 'General Affairs Coordinator'::varchar)))::varchar;
B72: General Affairs Staff | D72: =D71 + IF(EXACT(E72, ""), 0, 1) -> 95000000000056 | E72: =IF(EXACT(B72, ""), "", CONCATENATE("PERFORM ""SchSysConfig"".""Func_TblAppObject_UserRole_SET""(varSystemLoginSession, null::bigint, null::varchar, null::timestamptz, null::timestamptz, null::varchar, varInstitutionBranchID, varBaseCurrencyID, ", (IF(EXACT(B72, ""), "NULL", CONCATENATE("'", B72, "'"))),"::varchar);")) -> PERFORM "SchSysConfig"."Func_TblAppObject_UserRole_SET"(varSystemLoginSession, null::bigint, null::varchar, null::timestamptz, null::timestamptz, null::varchar, varInstitutionBranchID, varBaseCurrencyID, 'General Affairs Staff'::varchar); | G72: =IF(EXACT($E72, ""), "", CONCATENATE( "varSQL := varSQL || (CASE WHEN (varSQL = '') THEN '' ELSE ', ' END) || (SELECT JSON_BUILD_OBJECT (", "'recordID', NULL::bigint,", "'entities', ", "JSON_BUILD_OBJECT (", "'sysLoginSession_RefID', varSystemLoginSession::bigint,", "'sysDataAnnotation', NULL::varchar,", "'sysDataSetDateTimeTZ', NULL::timestamptz,", "'sysDataValidityStartDateTimeTZ', NULL::timestamptz,", "'sysDataValidityFinishDateTimeTZ', NULL::timestamptz,", "'sysPartitionRemovableRecordKey_RefID', NULL::bigint,", "'sysBranch_RefID', varInstitutionBranchID::bigint,", "'sysBaseCurrency_RefID',varBaseCurrencyID::bigint,", "'name', ", IF(EXACT($B72, ""), "null", CONCATENATE("'", SUBSTITUTE($B72, "'", "\'"), "'")), "::varchar", ")))::varchar;")) -> varSQL := varSQL || (CASE WHEN (varSQL = '') THEN '' ELSE ', ' END) || (SELECT JSON_BUILD_OBJECT ('recordID', NULL::bigint,'entities', JSON_BUILD_OBJECT ('sysLoginSession_RefID', varSystemLoginSession::bigint,'sysDataAnnotation', NULL::varchar,'sysDataSetDateTimeTZ', NULL::timestamptz,'sysDataValidityStartDateTimeTZ', NULL::timestamptz,'sysDataValidityFinishDateTimeTZ', NULL::timestamptz,'sysPartitionRemovableRecordKey_RefID', NULL::bigint,'sysBranch_RefID', varInstitutionBranchID::bigint,'sysBaseCurrency_RefID',varBaseCurrencyID::bigint,'name', 'General Affairs Staff'::varchar)))::varchar;
D73: =D72 + IF(EXACT(E73, ""), 0, 1) -> 95000000000056 | E73: =IF(EXACT(B73, ""), "", CONCATENATE("PERFORM ""SchSysConfig"".""Func_TblAppObject_UserRole_SET""(varSystemLoginSession, null::bigint, null::varchar, null::timestamptz, null::timestamptz, null::varchar, varInstitutionBranchID, varBaseCurrencyID, ", (IF(EXACT(B73, ""), "NULL", CONCATENATE("'", B73, "'"))),"::varchar);")) | G73: =IF(EXACT($E73, ""), "", CONCATENATE( "varSQL := varSQL || (CASE WHEN (varSQL = '') THEN '' ELSE ', ' END) || (SELECT JSON_BUILD_OBJECT (", "'recordID', NULL::bigint,", "'entities', ", "JSON_BUILD_OBJECT (", "'sysLoginSession_RefID', varSystemLoginSession::bigint,", "'sysDataAnnotation', NULL::varchar,", "'sysDataSetDateTimeTZ', NULL::timestamptz,", "'sysDataValidityStartDateTimeTZ', NULL::timestamptz,", "'sysDataValidityFinishDateTimeTZ', NULL::timestamptz,", "'sysPartitionRemovableRecordKey_RefID', NULL::bigint,", "'sysBranch_RefID', varInstitutionBranchID::bigint,", "'sysBaseCurrency_RefID',varBaseCurrencyID::bigint,", "'name', ", IF(EXACT($B73, ""), "null", CONCATENATE("'", SUBSTITUTE($B73, "'", "\'"), "'")), "::varchar", ")))::varchar;"))
B74: Legal Manager | D74: =D73 + IF(EXACT(E74, ""), 0, 1) -> 95000000000057 | E74: =IF(EXACT(B74, ""), "", CONCATENATE("PERFORM ""SchSysConfig"".""Func_TblAppObject_UserRole_SET""(varSystemLoginSession, null::bigint, null::varchar, null::timestamptz, null::timestamptz, null::varchar, varInstitutionBranchID, varBaseCurrencyID, ", (IF(EXACT(B74, ""), "NULL", CONCATENATE("'", B74, "'"))),"::varchar);")) -> PERFORM "SchSysConfig"."Func_TblAppObject_UserRole_SET"(varSystemLoginSession, null::bigint, null::varchar, null::timestamptz, null::timestamptz, null::varchar, varInstitutionBranchID, varBaseCurrencyID, 'Legal Manager'::varchar); | G74: =IF(EXACT($E74, ""), "", CONCATENATE( "varSQL := varSQL || (CASE WHEN (varSQL = '') THEN '' ELSE ', ' END) || (SELECT JSON_BUILD_OBJECT (", "'recordID', NULL::bigint,", "'entities', ", "JSON_BUILD_OBJECT (", "'sysLoginSession_RefID', varSystemLoginSession::bigint,", "'sysDataAnnotation', NULL::varchar,", "'sysDataSetDateTimeTZ', NULL::timestamptz,", "'sysDataValidityStartDateTimeTZ', NULL::timestamptz,", "'sysDataValidityFinishDateTimeTZ', NULL::timestamptz,", "'sysPartitionRemovableRecordKey_RefID', NULL::bigint,", "'sysBranch_RefID', varInstitutionBranchID::bigint,", "'sysBaseCurrency_RefID',varBaseCurrencyID::bigint,", "'name', ", IF(EXACT($B74, ""), "null", CONCATENATE("'", SUBSTITUTE($B74, "'", "\'"), "'")), "::varchar", ")))::varchar;")) -> varSQL := varSQL || (CASE WHEN (varSQL = '') THEN '' ELSE ', ' END) || (SELECT JSON_BUILD_OBJECT ('recordID', NULL::bigint,'entities', JSON_BUILD_OBJECT ('sysLoginSession_RefID', varSystemLoginSession::bigint,'sysDataAnnotation', NULL::varchar,'sysDataSetDateTimeTZ', NULL::timestamptz,'sysDataValidityStartDateTimeTZ', NULL::timestamptz,'sysDataValidityFinishDateTimeTZ', NULL::timestamptz,'sysPartitionRemovableRecordKey_RefID', NULL::bigint,'sysBranch_RefID', varInstitutionBranchID::bigint,'sysBaseCurrency_RefID',varBaseCurrencyID::bigint,'name', 'Legal Manager'::varchar)))::varchar;
B75: Legal Coordinator | D75: =D74 + IF(EXACT(E75, ""), 0, 1) -> 95000000000058 | E75: =IF(EXACT(B75, ""), "", CONCATENATE("PERFORM ""SchSysConfig"".""Func_TblAppObject_UserRole_SET""(varSystemLoginSession, null::bigint, null::varchar, null::timestamptz, null::timestamptz, null::varchar, varInstitutionBranchID, varBaseCurrencyID, ", (IF(EXACT(B75, ""), "NULL", CONCATENATE("'", B75, "'"))),"::varchar);")) -> PERFORM "SchSysConfig"."Func_TblAppObject_UserRole_SET"(varSystemLoginSession, null::bigint, null::varchar, null::timestamptz, null::timestamptz, null::varchar, varInstitutionBranchID, varBaseCurrencyID, 'Legal Coordinator'::varchar); | G75: =IF(EXACT($E75, ""), "", CONCATENATE( "varSQL := varSQL || (CASE WHEN (varSQL = '') THEN '' ELSE ', ' END) || (SELECT JSON_BUILD_OBJECT (", "'recordID', NULL::bigint,", "'entities', ", "JSON_BUILD_OBJECT (", "'sysLoginSession_RefID', varSystemLoginSession::bigint,", "'sysDataAnnotation', NULL::varchar,", "'sysDataSetDateTimeTZ', NULL::timestamptz,", "'sysDataValidityStartDateTimeTZ', NULL::timestamptz,", "'sysDataValidityFinishDateTimeTZ', NULL::timestamptz,", "'sysPartitionRemovableRecordKey_RefID', NULL::bigint,", "'sysBranch_RefID', varInstitutionBranchID::bigint,", "'sysBaseCurrency_RefID',varBaseCurrencyID::bigint,", "'name', ", IF(EXACT($B75, ""), "null", CONCATENATE("'", SUBSTITUTE($B75, "'", "\'"), "'")), "::varchar", ")))::varchar;")) -> varSQL := varSQL || (CASE WHEN (varSQL = '') THEN '' ELSE ', ' END) || (SELECT JSON_BUILD_OBJECT ('recordID', NULL::bigint,'entities', JSON_BUILD_OBJECT ('sysLoginSession_RefID', varSystemLoginSession::bigint,'sysDataAnnotation', NULL::varchar,'sysDataSetDateTimeTZ', NULL::timestamptz,'sysDataValidityStartDateTimeTZ', NULL::timestamptz,'sysDataValidityFinishDateTimeTZ', NULL::timestamptz,'sysPartitionRemovableRecordKey_RefID', NULL::bigint,'sysBranch_RefID', varInstitutionBranchID::bigint,'sysBaseCurrency_RefID',varBaseCurrencyID::bigint,'name', 'Legal Coordinator'::varchar)))::varchar;
B76: Legal Staff | D76: =D75 + IF(EXACT(E76, ""), 0, 1) -> 95000000000059 | E76: =IF(EXACT(B76, ""), "", CONCATENATE("PERFORM ""SchSysConfig"".""Func_TblAppObject_UserRole_SET""(varSystemLoginSession, null::bigint, null::varchar, null::timestamptz, null::timestamptz, null::varchar, varInstitutionBranchID, varBaseCurrencyID, ", (IF(EXACT(B76, ""), "NULL", CONCATENATE("'", B76, "'"))),"::varchar);")) -> PERFORM "SchSysConfig"."Func_TblAppObject_UserRole_SET"(varSystemLoginSession, null::bigint, null::varchar, null::timestamptz, null::timestamptz, null::varchar, varInstitutionBranchID, varBaseCurrencyID, 'Legal Staff'::varchar); | G76: =IF(EXACT($E76, ""), "", CONCATENATE( "varSQL := varSQL || (CASE WHEN (varSQL = '') THEN '' ELSE ', ' END) || (SELECT JSON_BUILD_OBJECT (", "'recordID', NULL::bigint,", "'entities', ", "JSON_BUILD_OBJECT (", "'sysLoginSession_RefID', varSystemLoginSession::bigint,", "'sysDataAnnotation', NULL::varchar,", "'sysDataSetDateTimeTZ', NULL::timestamptz,", "'sysDataValidityStartDateTimeTZ', NULL::timestamptz,", "'sysDataValidityFinishDateTimeTZ', NULL::timestamptz,", "'sysPartitionRemovableRecordKey_RefID', NULL::bigint,", "'sysBranch_RefID', varInstitutionBranchID::bigint,", "'sysBaseCurrency_RefID',varBaseCurrencyID::bigint,", "'name', ", IF(EXACT($B76, ""), "null", CONCATENATE("'", SUBSTITUTE($B76, "'", "\'"), "'")), "::varchar", ")))::varchar;")) -> varSQL := varSQL || (CASE WHEN (varSQL = '') THEN '' ELSE ', ' END) || (SELECT JSON_BUILD_OBJECT ('recordID', NULL::bigint,'entities', JSON_BUILD_OBJECT ('sysLoginSession_RefID', varSystemLoginSession::bigint,'sysDataAnnotation', NULL::varchar,'sysDataSetDateTimeTZ', NULL::timestamptz,'sysDataValidityStartDateTimeTZ', NULL::timestamptz,'sysDataValidityFinishDateTimeTZ', NULL::timestamptz,'sysPartitionRemovableRecordKey_RefID', NULL::bigint,'sysBranch_RefID', varInstitutionBranchID::bigint,'sysBaseCurrency_RefID',varBaseCurrencyID::bigint,'name', 'Legal Staff'::varchar)))::varchar;
D77: =D76 + IF(EXACT(E77, ""), 0, 1) -> 95000000000059 | E77: =IF(EXACT(B77, ""), "", CONCATENATE("PERFORM ""SchSysConfig"".""Func_TblAppObject_UserRole_SET""(varSystemLoginSession, null::bigint, null::varchar, null::timestamptz, null::timestamptz, null::varchar, varInstitutionBranchID, varBaseCurrencyID, ", (IF(EXACT(B77, ""), "NULL", CONCATENATE("'", B77, "'"))),"::varchar);")) | G77: =IF(EXACT($E77, ""), "", CONCATENATE( "varSQL := varSQL || (CASE WHEN (varSQL = '') THEN '' ELSE ', ' END) || (SELECT JSON_BUILD_OBJECT (", "'recordID', NULL::bigint,", "'entities', ", "JSON_BUILD_OBJECT (", "'sysLoginSession_RefID', varSystemLoginSession::bigint,", "'sysDataAnnotation', NULL::varchar,", "'sysDataSetDateTimeTZ', NULL::timestamptz,", "'sysDataValidityStartDateTimeTZ', NULL::timestamptz,", "'sysDataValidityFinishDateTimeTZ', NULL::timestamptz,", "'sysPartitionRemovableRecordKey_RefID', NULL::bigint,", "'sysBranch_RefID', varInstitutionBranchID::bigint,", "'sysBaseCurrency_RefID',varBaseCurrencyID::bigint,", "'name', ", IF(EXACT($B77, ""), "null", CONCATENATE("'", SUBSTITUTE($B77, "'", "\'"), "'")), "::varchar", ")))::varchar;"))
B78: Tools And Asset Manager | D78: =D77 + IF(EXACT(E78, ""), 0, 1) -> 95000000000060 | E78: =IF(EXACT(B78, ""), "", CONCATENATE("PERFORM ""SchSysConfig"".""Func_TblAppObject_UserRole_SET""(varSystemLoginSession, null::bigint, null::varchar, null::timestamptz, null::timestamptz, null::varchar, varInstitutionBranchID, varBaseCurrencyID, ", (IF(EXACT(B78, ""), "NULL", CONCATENATE("'", B78, "'"))),"::varchar);")) -> PERFORM "SchSysConfig"."Func_TblAppObject_UserRole_SET"(varSystemLoginSession, null::bigint, null::varchar, null::timestamptz, null::timestamptz, null::varchar, varInstitutionBranchID, varBaseCurrencyID, 'Tools And Asset Manager'::varchar); | G78: =IF(EXACT($E78, ""), "", CONCATENATE( "varSQL := varSQL || (CASE WHEN (varSQL = '') THEN '' ELSE ', ' END) || (SELECT JSON_BUILD_OBJECT (", "'recordID', NULL::bigint,", "'entities', ", "JSON_BUILD_OBJECT (", "'sysLoginSession_RefID', varSystemLoginSession::bigint,", "'sysDataAnnotation', NULL::varchar,", "'sysDataSetDateTimeTZ', NULL::timestamptz,", "'sysDataValidityStartDateTimeTZ', NULL::timestamptz,", "'sysDataValidityFinishDateTimeTZ', NULL::timestamptz,", "'sysPartitionRemovableRecordKey_RefID', NULL::bigint,", "'sysBranch_RefID', varInstitutionBranchID::bigint,", "'sysBaseCurrency_RefID',varBaseCurrencyID::bigint,", "'name', ", IF(EXACT($B78, ""), "null", CONCATENATE("'", SUBSTITUTE($B78, "'", "\'"), "'")), "::varchar", ")))::varchar;")) -> varSQL := varSQL || (CASE WHEN (varSQL = '') THEN '' ELSE ', ' END) || (SELECT JSON_BUILD_OBJECT ('recordID', NULL::bigint,'entities', JSON_BUILD_OBJECT ('sysLoginSession_RefID', varSystemLoginSession::bigint,'sysDataAnnotation', NULL::varchar,'sysDataSetDateTimeTZ', NULL::timestamptz,'sysDataValidityStartDateTimeTZ', NULL::timestamptz,'sysDataValidityFinishDateTimeTZ', NULL::timestamptz,'sysPartitionRemovableRecordKey_RefID', NULL::bigint,'sysBranch_RefID', varInstitutionBranchID::bigint,'sysBaseCurrency_RefID',varBaseCurrencyID::bigint,'name', 'Tools And Asset Manager'::varchar)))::varchar;
B79: Tools And Asset Coordinator | D79: =D78 + IF(EXACT(E79, ""), 0, 1) -> 95000000000061 | E79: =IF(EXACT(B79, ""), "", CONCATENATE("PERFORM ""SchSysConfig"".""Func_TblAppObject_UserRole_SET""(varSystemLoginSession, null::bigint, null::varchar, null::timestamptz, null::timestamptz, null::varchar, varInstitutionBranchID, varBaseCurrencyID, ", (IF(EXACT(B79, ""), "NULL", CONCATENATE("'", B79, "'"))),"::varchar);")) -> PERFORM "SchSysConfig"."Func_TblAppObject_UserRole_SET"(varSystemLoginSession, null::bigint, null::varchar, null::timestamptz, null::timestamptz, null::varchar, varInstitutionBranchID, varBaseCurrencyID, 'Tools And Asset Coordinator'::varchar); | G79: =IF(EXACT($E79, ""), "", CONCATENATE( "varSQL := varSQL || (CASE WHEN (varSQL = '') THEN '' ELSE ', ' END) || (SELECT JSON_BUILD_OBJECT (", "'recordID', NULL::bigint,", "'entities', ", "JSON_BUILD_OBJECT (", "'sysLoginSession_RefID', varSystemLoginSession::bigint,", "'sysDataAnnotation', NULL::varchar,", "'sysDataSetDateTimeTZ', NULL::timestamptz,", "'sysDataValidityStartDateTimeTZ', NULL::timestamptz,", "'sysDataValidityFinishDateTimeTZ', NULL::timestamptz,", "'sysPartitionRemovableRecordKey_RefID', NULL::bigint,", "'sysBranch_RefID', varInstitutionBranchID::bigint,", "'sysBaseCurrency_RefID',varBaseCurrencyID::bigint,", "'name', ", IF(EXACT($B79, ""), "null", CONCATENATE("'", SUBSTITUTE($B79, "'", "\'"), "'")), "::varchar", ")))::varchar;")) -> varSQL := varSQL || (CASE WHEN (varSQL = '') THEN '' ELSE ', ' END) || (SELECT JSON_BUILD_OBJECT ('recordID', NULL::bigint,'entities', JSON_BUILD_OBJECT ('sysLoginSession_RefID', varSystemLoginSession::bigint,'sysDataAnnotation', NULL::varchar,'sysDataSetDateTimeTZ', NULL::timestamptz,'sysDataValidityStartDateTimeTZ', NULL::timestamptz,'sysDataValidityFinishDateTimeTZ', NULL::timestamptz,'sysPartitionRemovableRecordKey_RefID', NULL::bigint,'sysBranch_RefID', varInstitutionBranchID::bigint,'sysBaseCurrency_RefID',varBaseCurrencyID::bigint,'name', 'Tools And Asset Coordinator'::varchar)))::varchar;
B80: Tools And Asset Staff | D80: =D79 + IF(EXACT(E80, ""), 0, 1) -> 95000000000062 | E80: =IF(EXACT(B80, ""), "", CONCATENATE("PERFORM ""SchSysConfig"".""Func_TblAppObject_UserRole_SET""(varSystemLoginSession, null::bigint, null::varchar, null::timestamptz, null::timestamptz, null::varchar, varInstitutionBranchID, varBaseCurrencyID, ", (IF(EXACT(B80, ""), "NULL", CONCATENATE("'", B80, "'"))),"::varchar);")) -> PERFORM "SchSysConfig"."Func_TblAppObject_UserRole_SET"(varSystemLoginSession, null::bigint, null::varchar, null::timestamptz, null::timestamptz, null::varchar, varInstitutionBranchID, varBaseCurrencyID, 'Tools And Asset Staff'::varchar); | G80: =IF(EXACT($E80, ""), "", CONCATENATE( "varSQL := varSQL || (CASE WHEN (varSQL = '') THEN '' ELSE ', ' END) || (SELECT JSON_BUILD_OBJECT (", "'recordID', NULL::bigint,", "'entities', ", "JSON_BUILD_OBJECT (", "'sysLoginSession_RefID', varSystemLoginSession::bigint,", "'sysDataAnnotation', NULL::varchar,", "'sysDataSetDateTimeTZ', NULL::timestamptz,", "'sysDataValidityStartDateTimeTZ', NULL::timestamptz,", "'sysDataValidityFinishDateTimeTZ', NULL::timestamptz,", "'sysPartitionRemovableRecordKey_RefID', NULL::bigint,", "'sysBranch_RefID', varInstitutionBranchID::bigint,", "'sysBaseCurrency_RefID',varBaseCurrencyID::bigint,", "'name', ", IF(EXACT($B80, ""), "null", CONCATENATE("'", SUBSTITUTE($B80, "'", "\'"), "'")), "::varchar", ")))::varchar;")) -> varSQL := varSQL || (CASE WHEN (varSQL = '') THEN '' ELSE ', ' END) || (SELECT JSON_BUILD_OBJECT ('recordID', NULL::bigint,'entities', JSON_BUILD_OBJECT ('sysLoginSession_RefID', varSystemLoginSession::bigint,'sysDataAnnotation', NULL::varchar,'sysDataSetDateTimeTZ', NULL::timestamptz,'sysDataValidityStartDateTimeTZ', NULL::timestamptz,'sysDataValidityFinishDateTimeTZ', NULL::timestamptz,'sysPartitionRemovableRecordKey_RefID', NULL::bigint,'sysBranch_RefID', varInstitutionBranchID::bigint,'sysBaseCurrency_RefID',varBaseCurrencyID::bigint,'name', 'Tools And Asset Staff'::varchar)))::varchar;
D81: =D80 + IF(EXACT(E81, ""), 0, 1) -> 95000000000062 | E81: =IF(EXACT(B81, ""), "", CONCATENATE("PERFORM ""SchSysConfig"".""Func_TblAppObject_UserRole_SET""(varSystemLoginSession, null::bigint, null::varchar, null::timestamptz, null::timestamptz, null::varchar, varInstitutionBranchID, varBaseCurrencyID, ", (IF(EXACT(B81, ""), "NULL", CONCATENATE("'", B81, "'"))),"::varchar);")) | G81: =IF(EXACT($E81, ""), "", CONCATENATE( "varSQL := varSQL || (CASE WHEN (varSQL = '') THEN '' ELSE ', ' END) || (SELECT JSON_BUILD_OBJECT (", "'recordID', NULL::bigint,", "'entities', ", "JSON_BUILD_OBJECT (", "'sysLoginSession_RefID', varSystemLoginSession::bigint,", "'sysDataAnnotation', NULL::varchar,", "'sysDataSetDateTimeTZ', NULL::timestamptz,", "'sysDataValidityStartDateTimeTZ', NULL::timestamptz,", "'sysDataValidityFinishDateTimeTZ', NULL::timestamptz,", "'sysPartitionRemovableRecordKey_RefID', NULL::bigint,", "'sysBranch_RefID', varInstitutionBranchID::bigint,", "'sysBaseCurrency_RefID',varBaseCurrencyID::bigint,", "'name', ", IF(EXACT($B81, ""), "null", CONCATENATE("'", SUBSTITUTE($B81, "'", "\'"), "'")), "::varchar", ")))::varchar;"))
B82: Engineering Manager | D82: =D81 + IF(EXACT(E82, ""), 0, 1) -> 95000000000063 | E82: =IF(EXACT(B82, ""), "", CONCATENATE("PERFORM ""SchSysConfig"".""Func_TblAppObject_UserRole_SET""(varSystemLoginSession, null::bigint, null::varchar, null::timestamptz, null::timestamptz, null::varchar, varInstitutionBranchID, varBaseCurrencyID, ", (IF(EXACT(B82, ""), "NULL", CONCATENATE("'", B82, "'"))),"::varchar);")) -> PERFORM "SchSysConfig"."Func_TblAppObject_UserRole_SET"(varSystemLoginSession, null::bigint, null::varchar, null::timestamptz, null::timestamptz, null::varchar, varInstitutionBranchID, varBaseCurrencyID, 'Engineering Manager'::varchar); | G82: =IF(EXACT($E82, ""), "", CONCATENATE( "varSQL := varSQL || (CASE WHEN (varSQL = '') THEN '' ELSE ', ' END) || (SELECT JSON_BUILD_OBJECT (", "'recordID', NULL::bigint,", "'entities', ", "JSON_BUILD_OBJECT (", "'sysLoginSession_RefID', varSystemLoginSession::bigint,", "'sysDataAnnotation', NULL::varchar,", "'sysDataSetDateTimeTZ', NULL::timestamptz,", "'sysDataValidityStartDateTimeTZ', NULL::timestamptz,", "'sysDataValidityFinishDateTimeTZ', NULL::timestamptz,", "'sysPartitionRemovableRecordKey_RefID', NULL::bigint,", "'sysBranch_RefID', varInstitutionBranchID::bigint,", "'sysBaseCurrency_RefID',varBaseCurrencyID::bigint,", "'name', ", IF(EXACT($B82, ""), "null", CONCATENATE("'", SUBSTITUTE($B82, "'", "\'"), "'")), "::varchar", ")))::varchar;")) -> varSQL := varSQL || (CASE WHEN (varSQL = '') THEN '' ELSE ', ' END) || (SELECT JSON_BUILD_OBJECT ('recordID', NULL::bigint,'entities', JSON_BUILD_OBJECT ('sysLoginSession_RefID', varSystemLoginSession::bigint,'sysDataAnnotation', NULL::varchar,'sysDataSetDateTimeTZ', NULL::timestamptz,'sysDataValidityStartDateTimeTZ', NULL::timestamptz,'sysDataValidityFinishDateTimeTZ', NULL::timestamptz,'sysPartitionRemovableRecordKey_RefID', NULL::bigint,'sysBranch_RefID', varInstitutionBranchID::bigint,'sysBaseCurrency_RefID',varBaseCurrencyID::bigint,'name', 'Engineering Manager'::varchar)))::varchar;
B83: Engineering Coordinator | D83: =D82 + IF(EXACT(E83, ""), 0, 1) -> 95000000000064 | E83: =IF(EXACT(B83, ""), "", CONCATENATE("PERFORM ""SchSysConfig"".""Func_TblAppObject_UserRole_SET""(varSystemLoginSession, null::bigint, null::varchar, null::timestamptz, null::timestamptz, null::varchar, varInstitutionBranchID, varBaseCurrencyID, ", (IF(EXACT(B83, ""), "NULL", CONCATENATE("'", B83, "'"))),"::varchar);")) -> PERFORM "SchSysConfig"."Func_TblAppObject_UserRole_SET"(varSystemLoginSession, null::bigint, null::varchar, null::timestamptz, null::timestamptz, null::varchar, varInstitutionBranchID, varBaseCurrencyID, 'Engineering Coordinator'::varchar); | G83: =IF(EXACT($E83, ""), "", CONCATENATE( "varSQL := varSQL || (CASE WHEN (varSQL = '') THEN '' ELSE ', ' END) || (SELECT JSON_BUILD_OBJECT (", "'recordID', NULL::bigint,", "'entities', ", "JSON_BUILD_OBJECT (", "'sysLoginSession_RefID', varSystemLoginSession::bigint,", "'sysDataAnnotation', NULL::varchar,", "'sysDataSetDateTimeTZ', NULL::timestamptz,", "'sysDataValidityStartDateTimeTZ', NULL::timestamptz,", "'sysDataValidityFinishDateTimeTZ', NULL::timestamptz,", "'sysPartitionRemovableRecordKey_RefID', NULL::bigint,", "'sysBranch_RefID', varInstitutionBranchID::bigint,", "'sysBaseCurrency_RefID',varBaseCurrencyID::bigint,", "'name', ", IF(EXACT($B83, ""), "null", CONCATENATE("'", SUBSTITUTE($B83, "'", "\'"), "'")), "::varchar", ")))::varchar;")) -> varSQL := varSQL || (CASE WHEN (varSQL = '') THEN '' ELSE ', ' END) || (SELECT JSON_BUILD_OBJECT ('recordID', NULL::bigint,'entities', JSON_BUILD_OBJECT ('sysLoginSession_RefID', varSystemLoginSession::bigint,'sysDataAnnotation', NULL::varchar,'sysDataSetDateTimeTZ', NULL::timestamptz,'sysDataValidityStartDateTimeTZ', NULL::timestamptz,'sysDataValidityFinishDateTimeTZ', NULL::timestamptz,'sysPartitionRemovableRecordKey_RefID', NULL::bigint,'sysBranch_RefID', varInstitutionBranchID::bigint,'sysBaseCurrency_RefID',varBaseCurrencyID::bigint,'name', 'Engineering Coordinator'::varchar)))::varchar;
B84: Engineering Staff | D84: =D83 + IF(EXACT(E84, ""), 0, 1) -> 95000000000065 | E84: =IF(EXACT(B84, ""), "", CONCATENATE("PERFORM ""SchSysConfig"".""Func_TblAppObject_UserRole_SET""(varSystemLoginSession, null::bigint, null::varchar, null::timestamptz, null::timestamptz, null::varchar, varInstitutionBranchID, varBaseCurrencyID, ", (IF(EXACT(B84, ""), "NULL", CONCATENATE("'", B84, "'"))),"::varchar);")) -> PERFORM "SchSysConfig"."Func_TblAppObject_UserRole_SET"(varSystemLoginSession, null::bigint, null::varchar, null::timestamptz, null::timestamptz, null::varchar, varInstitutionBranchID, varBaseCurrencyID, 'Engineering Staff'::varchar); | G84: =IF(EXACT($E84, ""), "", CONCATENATE( "varSQL := varSQL || (CASE WHEN (varSQL = '') THEN '' ELSE ', ' END) || (SELECT JSON_BUILD_OBJECT (", "'recordID', NULL::bigint,", "'entities', ", "JSON_BUILD_OBJECT (", "'sysLoginSession_RefID', varSystemLoginSession::bigint,", "'sysDataAnnotation', NULL::varchar,", "'sysDataSetDateTimeTZ', NULL::timestamptz,", "'sysDataValidityStartDateTimeTZ', NULL::timestamptz,", "'sysDataValidityFinishDateTimeTZ', NULL::timestamptz,", "'sysPartitionRemovableRecordKey_RefID', NULL::bigint,", "'sysBranch_RefID', varInstitutionBranchID::bigint,", "'sysBaseCurrency_RefID',varBaseCurrencyID::bigint,", "'name', ", IF(EXACT($B84, ""), "null", CONCATENATE("'", SUBSTITUTE($B84, "'", "\'"), "'")), "::varchar", ")))::varchar;")) -> varSQL := varSQL || (CASE WHEN (varSQL = '') THEN '' ELSE ', ' END) || (SELECT JSON_BUILD_OBJECT ('recordID', NULL::bigint,'entities', JSON_BUILD_OBJECT ('sysLoginSession_RefID', varSystemLoginSession::bigint,'sysDataAnnotation', NULL::varchar,'sysDataSetDateTimeTZ', NULL::timestamptz,'sysDataValidityStartDateTimeTZ', NULL::timestamptz,'sysDataValidityFinishDateTimeTZ', NULL::timestamptz,'sysPartitionRemovableRecordKey_RefID', NULL::bigint,'sysBranch_RefID', varInstitutionBranchID::bigint,'sysBaseCurrency_RefID',varBaseCurrencyID::bigint,'name', 'Engineering Staff'::varchar)))::varchar;

Sheet DataLookUp
B2: Sys_PID | C2: =MAIN!B2 -> User Role Name
B4: =IF(EXACT(MAIN!$B4, ""), "", MAIN!$D4) -> 95000000000001 | C4: =IF(EXACT(B4, ""), "", MAIN!B4) -> Super User
B5: =IF(EXACT(MAIN!$B5, ""), "", MAIN!$D5) -> 95000000000002 | C5: =IF(EXACT(B5, ""), "", MAIN!B5) -> Guest
B6: =IF(EXACT(MAIN!$B6, ""), "", MAIN!$D6) | C6: =IF(EXACT(B6, ""), "", MAIN!B6)
B7: =IF(EXACT(MAIN!$B7, ""), "", MAIN!$D7) -> 95000000000003 | C7: =IF(EXACT(B7, ""), "", MAIN!B7) -> Default Employee Role
B8: =IF(EXACT(MAIN!$B8, ""), "", MAIN!$D8) | C8: =IF(EXACT(B8, ""), "", MAIN!B8)
B9: =IF(EXACT(MAIN!$B9, ""), "", MAIN!$D9) -> 95000000000004 | C9: =IF(EXACT(B9, ""), "", MAIN!B9) -> Share Holder
B10: =IF(EXACT(MAIN!$B10, ""), "", MAIN!$D10) -> 95000000000005 | C10: =IF(EXACT(B10, ""), "", MAIN!B10) -> Stack Holder
B11: =IF(EXACT(MAIN!$B11, ""), "", MAIN!$D11) -> 95000000000006 | C11: =IF(EXACT(B11, ""), "", MAIN!B11) -> Public Accounting Firm
B12: =IF(EXACT(MAIN!$B12, ""), "", MAIN!$D12) -> 95000000000007 | C12: =IF(EXACT(B12, ""), "", MAIN!B12) -> Commissary
B13: =IF(EXACT(MAIN!$B13, ""), "", MAIN!$D13) | C13: =IF(EXACT(B13, ""), "", MAIN!B13)
B14: =IF(EXACT(MAIN!$B14, ""), "", MAIN!$D14) -> 95000000000008 | C14: =IF(EXACT(B14, ""), "", MAIN!B14) -> Director
B15: =IF(EXACT(MAIN!$B15, ""), "", MAIN!$D15) -> 95000000000009 | C15: =IF(EXACT(B15, ""), "", MAIN!B15) -> President Director
... B88: =IF(EXACT(MAIN!$B88, ""), "", MAIN!$D88) | C88: =IF(EXACT(B88, ""), "", MAIN!B88)
