Workbook

Sheet MAIN
B2: User Role RefID | C2: User Role Name | D2: User Role Group RefID | E2: User Role Group Name | G2: SYS_PID Prediction | H2: SQL Syntax
G3: 253000000000000
B4: =IF(EXACT([1]DataLookUp!$B4, ""), "", [1]DataLookUp!$B4) -> 95000000000001 | C4: =IF(EXACT(B4, ""), "", [1]DataLookUp!$C4) -> Super User | D4: 252000000000001 | E4: =IF(EXACT(D4, ""), "", VLOOKUP(D4, [2]DataLookUp!$B$4:$C$32, 2, FALSE)) -> System | G4: =G3 + IF(EXACT(H4, ""), 0, 1) -> 253000000000001 | H4: =IF(AND(EXACT(B4, ""), EXACT(D4, "")), "", CONCATENATE("PERFORM ""SchSysConfig"".""Func_TblAppObject_UserRole_SET""(varSystemLoginSession, null::bigint, null::varchar, null::timestamptz, null::timestamptz, null::varchar, varInstitutionBranchID, varBaseCurrencyID, ", (IF(EXACT(B4, ""), "NULL", CONCATENATE("'", B4, "'"))),"::varchar);")) -> PERFORM "SchSysConfig"."Func_TblAppObject_UserRole_SET"(varSystemLoginSession, null::bigint, null::varchar, null::timestamptz, null::timestamptz, null::varchar, varInstitutionBranchID, varBaseCurrencyID, '95000000000001'::varchar); | J4: =IF(EXACT($H4, ""), "", CONCATENATE( "varSQL := varSQL || (CASE WHEN (varSQL = '') THEN '' ELSE ', ' END) || (SELECT JSON_BUILD_OBJECT (", "'recordID', NULL::bigint,", "'entities', ", "JSON_BUILD_OBJECT (", "'sysLoginSession_RefID', varSystemLoginSession::bigint,", "'sysDataAnnotation', NULL::varchar,", "'sysDataSetDateTimeTZ', NULL::timestamptz,", "'sysDataValidityStartDateTimeTZ', NULL::timestamptz,", "'sysDataValidityFinishDateTimeTZ', NULL::timestamptz,", "'sysPartitionRemovableRecordKey_RefID', NULL::bigint,", "'sysBranch_RefID', varInstitutionBranchID::bigint,", "'sysBaseCurrency_RefID',varBaseCurrencyID::bigint,", "'userRoleGroup_RefID', ", IF(EXACT($D4, ""), "null", CONCATENATE("'", SUBSTITUTE($D4, "'", "\'"), "'")), "::bigint, ", "'userRole_RefID', ", IF(EXACT($B4, ""), "null", CONCATENATE("'", SUBSTITUTE($B4, "'", "\'"), "'")), "::bigint", ")))::varchar;")) -> varSQL := varSQL || (CASE WHEN (varSQL = '') THEN '' ELSE ', ' END) || (SELECT JSON_BUILD_OBJECT ('recordID', NULL::bigint,'entities', JSON_BUILD_OBJECT ('sysLoginSession_RefID', varSystemLoginSession::bigint,'sysDataAnnotation', NULL::varchar,'sysDataSetDateTimeTZ', NULL::timestamptz,'sysDataValidityStartDateTimeTZ', NULL::timestamptz,'sysDataValidityFinishDateTimeTZ', NULL::timestamptz,'sysPartitionRemovableRecordKey_RefID', NULL::bigint,'sysBranch_RefID', varInstitutionBranchID::bigint,'sysBaseCurrency_RefID',varBaseCurrencyID::bigint,'userRoleGroup_RefID', '252000000000001'::bigint, 'userRole_RefID', '95000000000001'::bigint)))::varchar;
B5: =IF(EXACT([1]DataLookUp!$B5, ""), "", [1]DataLookUp!$B5) -> 95000000000002 | C5: =IF(EXACT(B5, ""), "", [1]DataLookUp!$C5) -> Guest | D5: 252000000000001 | E5: =IF(EXACT(D5, ""), "", VLOOKUP(D5, [2]DataLookUp!$B$4:$C$32, 2, FALSE)) -> System | G5: =G4 + IF(EXACT(H5, ""), 0, 1) -> 253000000000002 | H5: =IF(AND(EXACT(B5, ""), EXACT(D5, "")), "", CONCATENATE("PERFORM ""SchSysConfig"".""Func_TblAppObject_UserRole_SET""(varSystemLoginSession, null::bigint, null::varchar, null::timestamptz, null::timestamptz, null::varchar, varInstitutionBranchID, varBaseCurrencyID, ", (IF(EXACT(B5, ""), "NULL", CONCATENATE("'", B5, "'"))),"::varchar);")) -> PERFORM "SchSysConfig"."Func_TblAppObject_UserRole_SET"(varSystemLoginSession, null::bigint, null::varchar, null::timestamptz, null::timestamptz, null::varchar, varInstitutionBranchID, varBaseCurrencyID, '95000000000002'::varchar); | J5: =IF(EXACT($H5, ""), "", CONCATENATE( "varSQL := varSQL || (CASE WHEN (varSQL = '') THEN '' ELSE ', ' END) || (SELECT JSON_BUILD_OBJECT (", "'recordID', NULL::bigint,", "'entities', ", "JSON_BUILD_OBJECT (", "'sysLoginSession_RefID', varSystemLoginSession::bigint,", "'sysDataAnnotation', NULL::varchar,", "'sysDataSetDateTimeTZ', NULL::timestamptz,", "'sysDataValidityStartDateTimeTZ', NULL::timestamptz,", "'sysDataValidityFinishDateTimeTZ', NULL::timestamptz,", "'sysPartitionRemovableRecordKey_RefID', NULL::bigint,", "'sysBranch_RefID', varInstitutionBranchID::bigint,", "'sysBaseCurrency_RefID',varBaseCurrencyID::bigint,", "'userRoleGroup_RefID', ", IF(EXACT($D5, ""), "null", CONCATENATE("'", SUBSTITUTE($D5, "'", "\'"), "'")), "::bigint, ", "'userRole_RefID', ", IF(EXACT($B5, ""), "null", CONCATENATE("'", SUBSTITUTE($B5, "'", "\'"), "'")), "::bigint", ")))::varchar;")) -> varSQL := varSQL || (CASE WHEN (varSQL = '') THEN '' ELSE ', ' END) || (SELECT JSON_BUILD_OBJECT ('recordID', NULL::bigint,'entities', JSON_BUILD_OBJECT ('sysLoginSession_RefID', varSystemLoginSession::bigint,'sysDataAnnotation', NULL::varchar,'sysDataSetDateTimeTZ', NULL::timestamptz,'sysDataValidityStartDateTimeTZ', NULL::timestamptz,'sysDataValidityFinishDateTimeTZ', NULL::timestamptz,'sysPartitionRemovableRecordKey_RefID', NULL::bigint,'sysBranch_RefID', varInstitutionBranchID::bigint,'sysBaseCurrency_RefID',varBaseCurrencyID::bigint,'userRoleGroup_RefID', '252000000000001'::bigint, 'userRole_RefID', '95000000000002'::bigint)))::varchar;
B6: =IF(EXACT([1]DataLookUp!$B6, ""), "", [1]DataLookUp!$B6) | C6: =IF(EXACT(B6, ""), "", [1]DataLookUp!$C6) | E6: =IF(EXACT(D6, ""), "", VLOOKUP(D6, [2]DataLookUp!$B$4:$C$32, 2, FALSE)) | G6: =G5 + IF(EXACT(H6, ""), 0, 1) -> 253000000000002 | H6: =IF(AND(EXACT(B6, ""), EXACT(D6, "")), "", CONCATENATE("PERFORM ""SchSysConfig"".""Func_TblAppObject_UserRole_SET""(varSystemLoginSession, null::bigint, null::varchar, null::timestamptz, null::timestamptz, null::varchar, varInstitutionBranchID, varBaseCurrencyID, ", (IF(EXACT(B6, ""), "NULL", CONCATENATE("'", B6, "'"))),"::varchar);")) | J6: =IF(EXACT($H6, ""), "", CONCATENATE( "varSQL := varSQL || (CASE WHEN (varSQL = '') THEN '' ELSE ', ' END) || (SELECT JSON_BUILD_OBJECT (", "'recordID', NULL::bigint,", "'entities', ", "JSON_BUILD_OBJECT (", "'sysLoginSession_RefID', varSystemLoginSession::bigint,", "'sysDataAnnotation', NULL::varchar,", "'sysDataSetDateTimeTZ', NULL::timestamptz,", "'sysDataValidityStartDateTimeTZ', NULL::timestamptz,", "'sysDataValidityFinishDateTimeTZ', NULL::timestamptz,", "'sysPartitionRemovableRecordKey_RefID', NULL::bigint,", "'sysBranch_RefID', varInstitutionBranchID::bigint,", "'sysBaseCurrency_RefID',varBaseCurrencyID::bigint,", "'userRoleGroup_RefID', ", IF(EXACT($D6, ""), "null", CONCATENATE("'", SUBSTITUTE($D6, "'", "\'"), "'")), "::bigint, ", "'userRole_RefID', ", IF(EXACT($B6, ""), "null", CONCATENATE("'", SUBSTITUTE($B6, "'", "\'"), "'")), "::bigint", ")))::varchar;"))
B7: =IF(EXACT([1]DataLookUp!$B7, ""), "", [1]DataLookUp!$B7) -> 95000000000003 | C7: =IF(EXACT(B7, ""), "", [1]DataLookUp!$C7) -> Default Employee Role | D7: 252000000000001 | E7: =IF(EXACT(D7, ""), "", VLOOKUP(D7, [2]DataLookUp!$B$4:$C$32, 2, FALSE)) -> System | G7: =G6 + IF(EXACT(H7, ""), 0, 1) -> 253000000000003 | H7: =IF(AND(EXACT(B7, ""), EXACT(D7, "")), "", CONCATENATE("PERFORM ""SchSysConfig"".""Func_TblAppObject_UserRole_SET""(varSystemLoginSession, null::bigint, null::varchar, null::timestamptz, null::timestamptz, null::varchar, varInstitutionBranchID, varBaseCurrencyID, ", (IF(EXACT(B7, ""), "NULL", CONCATENATE("'", B7, "'"))),"::varchar);")) -> PERFORM "SchSysConfig"."Func_TblAppObject_UserRole_SET"(varSystemLoginSession, null::bigint, null::varchar, null::timestamptz, null::timestamptz, null::varchar, varInstitutionBranchID, varBaseCurrencyID, '95000000000003'::varchar); | J7: =IF(EXACT($H7, ""), "", CONCATENATE( "varSQL := varSQL || (CASE WHEN (varSQL = '') THEN '' ELSE ', ' END) || (SELECT JSON_BUILD_OBJECT (", "'recordID', NULL::bigint,", "'entities', ", "JSON_BUILD_OBJECT (", "'sysLoginSession_RefID', varSystemLoginSession::bigint,", "'sysDataAnnotation', NULL::varchar,", "'sysDataSetDateTimeTZ', NULL::timestamptz,", "'sysDataValidityStartDateTimeTZ', NULL::timestamptz,", "'sysDataValidityFinishDateTimeTZ', NULL::timestamptz,", "'sysPartitionRemovableRecordKey_RefID', NULL::bigint,", "'sysBranch_RefID', varInstitutionBranchID::bigint,", "'sysBaseCurrency_RefID',varBaseCurrencyID::bigint,", "'userRoleGroup_RefID', ", IF(EXACT($D7, ""), "null", CONCATENATE("'", SUBSTITUTE($D7, "'", "\'"), "'")), "::bigint, ", "'userRole_RefID', ", IF(EXACT($B7, ""), "null", CONCATENATE("'", SUBSTITUTE($B7, "'", "\'"), "'")), "::bigint", ")))::varchar;")) -> varSQL := varSQL || (CASE WHEN (varSQL = '') THEN '' ELSE ', ' END) || (SELECT JSON_BUILD_OBJECT ('recordID', NULL::bigint,'entities', JSON_BUILD_OBJECT ('sysLoginSession_RefID', varSystemLoginSession::bigint,'sysDataAnnotation', NULL::varchar,'sysDataSetDateTimeTZ', NULL::timestamptz,'sysDataValidityStartDateTimeTZ', NULL::timestamptz,'sysDataValidityFinishDateTimeTZ', NULL::timestamptz,'sysPartitionRemovableRecordKey_RefID', NULL::bigint,'sysBranch_RefID', varInstitutionBranchID::bigint,'sysBaseCurrency_RefID',varBaseCurrencyID::bigint,'userRoleGroup_RefID', '252000000000001'::bigint, 'userRole_RefID', '95000000000003'::bigint)))::varchar;
B8: =IF(EXACT([1]DataLookUp!$B8, ""), "", [1]DataLookUp!$B8) | C8: =IF(EXACT(B8, ""), "", [1]DataLookUp!$C8) | E8: =IF(EXACT(D8, ""), "", VLOOKUP(D8, [2]DataLookUp!$B$4:$C$32, 2, FALSE)) | G8: =G7 + IF(EXACT(H8, ""), 0, 1) -> 253000000000003 | H8: =IF(AND(EXACT(B8, ""), EXACT(D8, "")), "", CONCATENATE("PERFORM ""SchSysConfig"".""Func_TblAppObject_UserRole_SET""(varSystemLoginSession, null::bigint, null::varchar, null::timestamptz, null::timestamptz, null::varchar, varInstitutionBranchID, varBaseCurrencyID, ", (IF(EXACT(B8, ""), "NULL", CONCATENATE("'", B8, "'"))),"::varchar);")) | J8: =IF(EXACT($H8, ""), "", CONCATENATE( "varSQL := varSQL || (CASE WHEN (varSQL = '') THEN '' ELSE ', ' END) || (SELECT JSON_BUILD_OBJECT (", "'recordID', NULL::bigint,", "'entities', ", "JSON_BUILD_OBJECT (", "'sysLoginSession_RefID', varSystemLoginSession::bigint,", "'sysDataAnnotation', NULL::varchar,", "'sysDataSetDateTimeTZ', NULL::timestamptz,", "'sysDataValidityStartDateTimeTZ', NULL::timestamptz,", "'sysDataValidityFinishDateTimeTZ', NULL::timestamptz,", "'sysPartitionRemovableRecordKey_RefID', NULL::bigint,", "'sysBranch_RefID', varInstitutionBranchID::bigint,", "'sysBaseCurrency_RefID',varBaseCurrencyID::bigint,", "'userRoleGroup_RefID', ", IF(EXACT($D8, ""), "null", CONCATENATE("'", SUBSTITUTE($D8, "'", "\'"), "'")), "::bigint, ", "'userRole_RefID', ", IF(EXACT($B8, ""), "null", CONCATENATE("'", SUBSTITUTE($B8, "'", "\'"), "'")), "::bigint", ")))::varchar;"))
B9: =IF(EXACT([1]DataLookUp!$B9, ""), "", [1]DataLookUp!$B9) -> 95000000000004 | C9: =IF(EXACT(B9, ""), "", [1]DataLookUp!$C9) -> Share Holder | D9: 252000000000002 | E9: =IF(EXACT(D9, ""), "", VLOOKUP(D9, [2]DataLookUp!$B$4:$C$32, 2, FALSE)) -> External | G9: =G8 + IF(EXACT(H9, ""), 0, 1) -> 253000000000004 | H9: =IF(AND(EXACT(B9, ""), EXACT(D9, "")), "", CONCATENATE("PERFORM ""SchSysConfig"".""Func_TblAppObject_UserRole_SET""(varSystemLoginSession, null::bigint, null::varchar, null::timestamptz, null::timestamptz, null::varchar, varInstitutionBranchID, varBaseCurrencyID, ", (IF(EXACT(B9, ""), "NULL", CONCATENATE("'", B9, "'"))),"::varchar);")) -> PERFORM "SchSysConfig"."Func_TblAppObject_UserRole_SET"(varSystemLoginSession, null::bigint, null::varchar, null::timestamptz, null::timestamptz, null::varchar, varInstitutionBranchID, varBaseCurrencyID, '95000000000004'::varchar); | J9: =IF(EXACT($H9, ""), "", CONCATENATE( "varSQL := varSQL || (CASE WHEN (varSQL = '') THEN '' ELSE ', ' END) || (SELECT JSON_BUILD_OBJECT (", "'recordID', NULL::bigint,", "'entities', ", "JSON_BUILD_OBJECT (", "'sysLoginSession_RefID', varSystemLoginSession::bigint,", "'sysDataAnnotation', NULL::varchar,", "'sysDataSetDateTimeTZ', NULL::timestamptz,", "'sysDataValidityStartDateTimeTZ', NULL::timestamptz,", "'sysDataValidityFinishDateTimeTZ', NULL::timestamptz,", "'sysPartitionRemovableRecordKey_RefID', NULL::bigint,", "'sysBranch_RefID', varInstitutionBranchID::bigint,", "'sysBaseCurrency_RefID',varBaseCurrencyID::bigint,", "'userRoleGroup_RefID', ", IF(EXACT($D9, ""), "null", CONCATENATE("'", SUBSTITUTE($D9, "'", "\'"), "'")), "::bigint, ", "'userRole_RefID', ", IF(EXACT($B9, ""), "null", CONCATENATE("'", SUBSTITUTE($B9, "'", "\'"), "'")), "::bigint", ")))::varchar;")) -> varSQL := varSQL || (CASE WHEN (varSQL = '') THEN '' ELSE ', ' END) || (SELECT JSON_BUILD_OBJECT ('recordID', NULL::bigint,'entities', JSON_BUILD_OBJECT ('sysLoginSession_RefID', varSystemLoginSession::bigint,'sysDataAnnotation', NULL::varchar,'sysDataSetDateTimeTZ', NULL::timestamptz,'sysDataValidityStartDateTimeTZ', NULL::timestamptz,'sysDataValidityFinishDateTimeTZ', NULL::timestamptz,'sysPartitionRemovableRecordKey_RefID', NULL::bigint,'sysBranch_RefID', varInstitutionBranchID::bigint,'sysBaseCurrency_RefID',varBaseCurrencyID::bigint,'userRoleGroup_RefID', '252000000000002'::bigint, 'userRole_RefID', '95000000000004'::bigint)))::varchar;
B10: =IF(EXACT([1]DataLookUp!$B10, ""), "", [1]DataLookUp!$B10) -> 95000000000005 | C10: =IF(EXACT(B10, ""), "", [1]DataLookUp!$C10) -> Stack Holder | D10: 252000000000002 | E10: =IF(EXACT(D10, ""), "", VLOOKUP(D10, [2]DataLookUp!$B$4:$C$32, 2, FALSE)) -> External | G10: =G9 + IF(EXACT(H10, ""), 0, 1) -> 253000000000005 | H10: =IF(AND(EXACT(B10, ""), EXACT(D10, "")), "", CONCATENATE("PERFORM ""SchSysConfig"".""Func_TblAppObject_UserRole_SET""(varSystemLoginSession, null::bigint, null::varchar, null::timestamptz, null::timestamptz, null::varchar, varInstitutionBranchID, varBaseCurrencyID, ", (IF(EXACT(B10, ""), "NULL", CONCATENATE("'", B10, "'"))),"::varchar);")) -> PERFORM "SchSysConfig"."Func_TblAppObject_UserRole_SET"(varSystemLoginSession, null::bigint, null::varchar, null::timestamptz, null::timestamptz, null::varchar, varInstitutionBranchID, varBaseCurrencyID, '95000000000005'::varchar); | J10: =IF(EXACT($H10, ""), "", CONCATENATE( "varSQL := varSQL || (CASE WHEN (varSQL = '') THEN '' ELSE ', ' END) || (SELECT JSON_BUILD_OBJECT (", "'recordID', NULL::bigint,", "'entities', ", "JSON_BUILD_OBJECT (", "'sysLoginSession_RefID', varSystemLoginSession::bigint,", "'sysDataAnnotation', NULL::varchar,", "'sysDataSetDateTimeTZ', NULL::timestamptz,", "'sysDataValidityStartDateTimeTZ', NULL::timestamptz,", "'sysDataValidityFinishDateTimeTZ', NULL::timestamptz,", "'sysPartitionRemovableRecordKey_RefID', NULL::bigint,", "'sysBranch_RefID', varInstitutionBranchID::bigint,", "'sysBaseCurrency_RefID',varBaseCurrencyID::bigint,", "'userRoleGroup_RefID', ", IF(EXACT($D10, ""), "null", CONCATENATE("'", SUBSTITUTE($D10, "'", "\'"), "'")), "::bigint, ", "'userRole_RefID', ", IF(EXACT($B10, ""), "null", CONCATENATE("'", SUBSTITUTE($B10, "'", "\'"), "'")), "::bigint", ")))::varchar;")) -> varSQL := varSQL || (CASE WHEN (varSQL = '') THEN '' ELSE ', ' END) || (SELECT JSON_BUILD_OBJECT ('recordID', NULL::bigint,'entities', JSON_BUILD_OBJECT ('sysLoginSession_RefID', varSystemLoginSession::bigint,'sysDataAnnotation', NULL::varchar,'sysDataSetDateTimeTZ', NULL::timestamptz,'sysDataValidityStartDateTimeTZ', NULL::timestamptz,'sysDataValidityFinishDateTimeTZ', NULL::timestamptz,'sysPartitionRemovableRecordKey_RefID', NULL::bigint,'sysBranch_RefID', varInstitutionBranchID::bigint,'sysBaseCurrency_RefID',varBaseCurrencyID::bigint,'userRoleGroup_RefID', '252000000000002'::bigint, 'userRole_RefID', '95000000000005'::bigint)))::varchar;
B11: =IF(EXACT([1]DataLookUp!$B11, ""), "", [1]DataLookUp!$B11) -> 95000000000006 | C11: =IF(EXACT(B11, ""), "", [1]DataLookUp!$C11) -> Public Accounting Firm | D11: 252000000000002 | E11: =IF(EXACT(D11, ""), "", VLOOKUP(D11, [2]DataLookUp!$B$4:$C$32, 2, FALSE)) -> External | G11: =G10 + IF(EXACT(H11, ""), 0, 1) -> 253000000000006 | H11: =IF(AND(EXACT(B11, ""), EXACT(D11, "")), "", CONCATENATE("PERFORM ""SchSysConfig"".""Func_TblAppObject_UserRole_SET""(varSystemLoginSession, null::bigint, null::varchar, null::timestamptz, null::timestamptz, null::varchar, varInstitutionBranchID, varBaseCurrencyID, ", (IF(EXACT(B11, ""), "NULL", CONCATENATE("'", B11, "'"))),"::varchar);")) -> PERFORM "SchSysConfig"."Func_TblAppObject_UserRole_SET"(varSystemLoginSession, null::bigint, null::varchar, null::timestamptz, null::timestamptz, null::varchar, varInstitutionBranchID, varBaseCurrencyID, '95000000000006'::varchar); | J11: =IF(EXACT($H11, ""), "", CONCATENATE( "varSQL := varSQL || (CASE WHEN (varSQL = '') THEN '' ELSE ', ' END) || (SELECT JSON_BUILD_OBJECT (", "'recordID', NULL::bigint,", "'entities', ", "JSON_BUILD_OBJECT (", "'sysLoginSession_RefID', varSystemLoginSession::bigint,", "'sysDataAnnotation', NULL::varchar,", "'sysDataSetDateTimeTZ', NULL::timestamptz,", "'sysDataValidityStartDateTimeTZ', NULL::timestamptz,", "'sysDataValidityFinishDateTimeTZ', NULL::timestamptz,", "'sysPartitionRemovableRecordKey_RefID', NULL::bigint,", "'sysBranch_RefID', varInstitutionBranchID::bigint,", "'sysBaseCurrency_RefID',varBaseCurrencyID::bigint,", "'userRoleGroup_RefID', ", IF(EXACT($D11, ""), "null", CONCATENATE("'", SUBSTITUTE($D11, "'", "\'"), "'")), "::bigint, ", "'userRole_RefID', ", IF(EXACT($B11, ""), "null", CONCATENATE("'", SUBSTITUTE($B11, "'", "\'"), "'")), "::bigint", ")))::varchar;")) -> varSQL := varSQL || (CASE WHEN (varSQL = '') THEN '' ELSE ', ' END) || (SELECT JSON_BUILD_OBJECT ('recordID', NULL::bigint,'entities', JSON_BUILD_OBJECT ('sysLoginSession_RefID', varSystemLoginSession::bigint,'sysDataAnnotation', NULL::varchar,'sysDataSetDateTimeTZ', NULL::timestamptz,'sysDataValidityStartDateTimeTZ', NULL::timestamptz,'sysDataValidityFinishDateTimeTZ', NULL::timestamptz,'sysPartitionRemovableRecordKey_RefID', NULL::bigint,'sysBranch_RefID', varInstitutionBranchID::bigint,'sysBaseCurrency_RefID',varBaseCurrencyID::bigint,'userRoleGroup_RefID', '252000000000002'::bigint, 'userRole_RefID', '95000000000006'::bigint)))::varchar;
B12: =IF(EXACT([1]DataLookUp!$B12, ""), "", [1]DataLookUp!$B12) -> 95000000000007 | C12: =IF(EXACT(B12, ""), "", [1]DataLookUp!$C12) -> Commissary | D12: 252000000000004 | E12: =IF(EXACT(D12, ""), "", VLOOKUP(D12, [2]DataLookUp!$B$4:$C$32, 2, FALSE)) -> Board Of Comissioner | G12: =G11 + IF(EXACT(H12, ""), 0, 1) -> 253000000000007 | H12: =IF(AND(EXACT(B12, ""), EXACT(D12, "")), "", CONCATENATE("PERFORM ""SchSysConfig"".""Func_TblAppObject_UserRole_SET""(varSystemLoginSession, null::bigint, null::varchar, null::timestamptz, null::timestamptz, null::varchar, varInstitutionBranchID, varBaseCurrencyID, ", (IF(EXACT(B12, ""), "NULL", CONCATENATE("'", B12, "'"))),"::varchar);")) -> PERFORM "SchSysConfig"."Func_TblAppObject_UserRole_SET"(varSystemLoginSession, null::bigint, null::varchar, null::timestamptz, null::timestamptz, null::varchar, varInstitutionBranchID, varBaseCurrencyID, '95000000000007'::varchar); | J12: =IF(EXACT($H12, ""), "", CONCATENATE( "varSQL := varSQL || (CASE WHEN (varSQL = '') THEN '' ELSE ', ' END) || (SELECT JSON_BUILD_OBJECT (", "'recordID', NULL::bigint,", "'entities', ", "JSON_BUILD_OBJECT (", "'sysLoginSession_RefID', varSystemLoginSession::bigint,", "'sysDataAnnotation', NULL::varchar,", "'sysDataSetDateTimeTZ', NULL::timestamptz,", "'sysDataValidityStartDateTimeTZ', NULL::timestamptz,", "'sysDataValidityFinishDateTimeTZ', NULL::timestamptz,", "'sysPartitionRemovableRecordKey_RefID', NULL::bigint,", "'sysBranch_RefID', varInstitutionBranchID::bigint,", "'sysBaseCurrency_RefID',varBaseCurrencyID::bigint,", "'userRoleGroup_RefID', ", IF(EXACT($D12, ""), "null", CONCATENATE("'", SUBSTITUTE($D12, "'", "\'"), "'")), "::bigint, ", "'userRole_RefID', ", IF(EXACT($B12, ""), "null", CONCATENATE("'", SUBSTITUTE($B12, "'", "\'"), "'")), "::bigint", ")))::varchar;")) -> varSQL := varSQL || (CASE WHEN (varSQL = '') THEN '' ELSE ', ' END) || (SELECT JSON_BUILD_OBJECT ('recordID', NULL::bigint,'entities', JSON_BUILD_OBJECT ('sysLoginSession_RefID', varSystemLoginSession::bigint,'sysDataAnnotation', NULL::varchar,'sysDataSetDateTimeTZ', NULL::timestamptz,'sysDataValidityStartDateTimeTZ', NULL::timestamptz,'sysDataValidityFinishDateTimeTZ', NULL::timestamptz,'sysPartitionRemovableRecordKey_RefID', NULL::bigint,'sysBranch_RefID', varInstitutionBranchID::bigint,'sysBaseCurrency_RefID',varBaseCurrencyID::bigint,'userRoleGroup_RefID', '252000000000004'::bigint, 'userRole_RefID', '95000000000007'::bigint)))::varchar;
B13: =IF(EXACT([1]DataLookUp!$B13, ""), "", [1]DataLookUp!$B13) | C13: =IF(EXACT(B13, ""), "", [1]DataLookUp!$C13) | E13: =IF(EXACT(D13, ""), "", VLOOKUP(D13, [2]DataLookUp!$B$4:$C$32, 2, FALSE)) | G13: =G12 + IF(EXACT(H13, ""), 0, 1) -> 253000000000007 | H13: =IF(AND(EXACT(B13, ""), EXACT(D13, "")), "", CONCATENATE("PERFORM ""SchSysConfig"".""Func_TblAppObject_UserRole_SET""(varSystemLoginSession, null::bigint, null::varchar, null::timestamptz, null::timestamptz, null::varchar, varInstitutionBranchID, varBaseCurrencyID, ", (IF(EXACT(B13, ""), "NULL", CONCATENATE("'", B13, "'"))),"::varchar);")) | J13: =IF(EXACT($H13, ""), "", CONCATENATE( "varSQL := varSQL || (CASE WHEN (varSQL = '') THEN '' ELSE ', ' END) || (SELECT JSON_BUILD_OBJECT (", "'recordID', NULL::bigint,", "'entities', ", "JSON_BUILD_OBJECT (", "'sysLoginSession_RefID', varSystemLoginSession::bigint,", "'sysDataAnnotation', NULL::varchar,", "'sysDataSetDateTimeTZ', NULL::timestamptz,", "'sysDataValidityStartDateTimeTZ', NULL::timestamptz,", "'sysDataValidityFinishDateTimeTZ', NULL::timestamptz,", "'sysPartitionRemovableRecordKey_RefID', NULL::bigint,", "'sysBranch_RefID', varInstitutionBranchID::bigint,", "'sysBaseCurrency_RefID',varBaseCurrencyID::bigint,", "'userRoleGroup_RefID', ", IF(EXACT($D13, ""), "null", CONCATENATE("'", SUBSTITUTE($D13, "'", "\'"), "'")), "::bigint, ", "'userRole_RefID', ", IF(EXACT($B13, ""), "null", CONCATENATE("'", SUBSTITUTE($B13, "'", "\'"), "'")), "::bigint", ")))::varchar;"))
B14: =IF(EXACT([1]DataLookUp!$B14, ""), "", [1]DataLookUp!$B14) -> 95000000000008 | C14: =IF(EXACT(B14, ""), "", [1]DataLookUp!$C14) -> Director | D14: 252000000000003 | E14: =IF(EXACT(D14, ""), "", VLOOKUP(D14, [2]DataLookUp!$B$4:$C$32, 2, FALSE)) -> Board Of Director | G14: =G13 + IF(EXACT(H14, ""), 0, 1) -> 253000000000008 | H14: =IF(AND(EXACT(B14, ""), EXACT(D14, "")), "", CONCATENATE("PERFORM ""SchSysConfig"".""Func_TblAppObject_UserRole_SET""(varSystemLoginSession, null::bigint, null::varchar, null::timestamptz, null::timestamptz, null::varchar, varInstitutionBranchID, varBaseCurrencyID, ", (IF(EXACT(B14, ""), "NULL", CONCATENATE("'", B14, "'"))),"::varchar);")) -> PERFORM "SchSysConfig"."Func_TblAppObject_UserRole_SET"(varSystemLoginSession, null::bigint, null::varchar, null::timestamptz, null::timestamptz, null::varchar, varInstitutionBranchID, varBaseCurrencyID, '95000000000008'::varchar); | J14: =IF(EXACT($H14, ""), "", CONCATENATE( "varSQL := varSQL || (CASE WHEN (varSQL = '') THEN '' ELSE ', ' END) || (SELECT JSON_BUILD_OBJECT (", "'recordID', NULL::bigint,", "'entities', ", "JSON_BUILD_OBJECT (", "'sysLoginSession_RefID', varSystemLoginSession::bigint,", "'sysDataAnnotation', NULL::varchar,", "'sysDataSetDateTimeTZ', NULL::timestamptz,", "'sysDataValidityStartDateTimeTZ', NULL::timestamptz,", "'sysDataValidityFinishDateTimeTZ', NULL::timestamptz,", "'sysPartitionRemovableRecordKey_RefID', NULL::bigint,", "'sysBranch_RefID', varInstitutionBranchID::bigint,", "'sysBaseCurrency_RefID',varBaseCurrencyID::bigint,", "'userRoleGroup_RefID', ", IF(EXACT($D14, ""), "null", CONCATENATE("'", SUBSTITUTE($D14, "'", "\'"), "'")), "::bigint, ", "'userRole_RefID', ", IF(EXACT($B14, ""), "null", CONCATENATE("'", SUBSTITUTE($B14, "'", "\'"), "'")), "::bigint", ")))::varchar;")) -> varSQL := varSQL || (CASE WHEN (varSQL = '') THEN '' ELSE ', ' END) || (SELECT JSON_BUILD_OBJECT ('recordID', NULL::bigint,'entities', JSON_BUILD_OBJECT ('sysLoginSession_RefID', varSystemLoginSession::bigint,'sysDataAnnotation', NULL::varchar,'sysDataSetDateTimeTZ', NULL::timestamptz,'sysDataValidityStartDateTimeTZ', NULL::timestamptz,'sysDataValidityFinishDateTimeTZ', NULL::timestamptz,'sysPartitionRemovableRecordKey_RefID', NULL::bigint,'sysBranch_RefID', varInstitutionBranchID::bigint,'sysBaseCurrency_RefID',varBaseCurrencyID::bigint,'userRoleGroup_RefID', '252000000000003'::bigint, 'userRole_RefID', '95000000000008'::bigint)))::varchar;
B15: =IF(EXACT([1]DataLookUp!$B15, ""), "", [1]DataLookUp!$B15) -> 95000000000009 | C15: =IF(EXACT(B15, ""), "", [1]DataLookUp!$C15) -> President Director | D15: 252000000000003 | E15: =IF(EXACT(D15, ""), "", VLOOKUP(D15, [2]DataLookUp!$B$4:$C$32, 2, FALSE)) -> Board Of Director | G15: =G14 + IF(EXACT(H15, ""), 0, 1) -> 253000000000009 | H15: =IF(AND(EXACT(B15, ""), EXACT(D15, "")), "", CONCATENATE("PERFORM ""SchSysConfig"".""Func_TblAppObject_UserRole_SET""(varSystemLoginSession, null::bigint, null::varchar, null::timestamptz, null::timestamptz, null::varchar, varInstitutionBranchID, varBaseCurrencyID, ", (IF(EXACT(B15, ""), "NULL", CONCATENATE("'", B15, "'"))),"::varchar);")) -> PERFORM "SchSysConfig"."Func_TblAppObject_UserRole_SET"(varSystemLoginSession, null::bigint, null::varchar, null::timestamptz, null::timestamptz, null::varchar, varInstitutionBranchID, varBaseCurrencyID, '95000000000009'::varchar); | J15: =IF(EXACT($H15, ""), "", CONCATENATE( "varSQL := varSQL || (CASE WHEN (varSQL = '') THEN '' ELSE ', ' END) || (SELECT JSON_BUILD_OBJECT (", "'recordID', NULL::bigint,", "'entities', ", "JSON_BUILD_OBJECT (", "'sysLoginSession_RefID', varSystemLoginSession::bigint,", "'sysDataAnnotation', NULL::varchar,", "'sysDataSetDateTimeTZ', NULL::timestamptz,", "'sysDataValidityStartDateTimeTZ', NULL::timestamptz,", "'sysDataValidityFinishDateTimeTZ', NULL::timestamptz,", "'sysPartitionRemovableRecordKey_RefID', NULL::bigint,", "'sysBranch_RefID', varInstitutionBranchID::bigint,", "'sysBaseCurrency_RefID',varBaseCurrencyID::bigint,", "'userRoleGroup_RefID', ", IF(EXACT($D15, ""), "null", CONCATENATE("'", SUBSTITUTE($D15, "'", "\'"), "'")), "::bigint, ", "'userRole_RefID', ", IF(EXACT($B15, ""), "null", CONCATENATE("'", SUBSTITUTE($B15, "'", "\'"), "'")), "::bigint", ")))::varchar;")) -> varSQL := varSQL || (CASE WHEN (varSQL = '') THEN '' ELSE ', ' END) || (SELECT JSON_BUILD_OBJECT ('recordID', NULL::bigint,'entities', JSON_BUILD_OBJECT ('sysLoginSession_RefID', varSystemLoginSession::bigint,'sysDataAnnotation', NULL::varchar,'sysDataSetDateTimeTZ', NULL::timestamptz,'sysDataValidityStartDateTimeTZ', NULL::timestamptz,'sysDataValidityFinishDateTimeTZ', NULL::timestamptz,'sysPartitionRemovableRecordKey_RefID', NULL::bigint,'sysBranch_RefID', varInstitutionBranchID::bigint,'sysBaseCurrency_RefID',varBaseCurrencyID::bigint,'userRoleGroup_RefID', '252000000000003'::bigint, 'userRole_RefID', '95000000000009'::bigint)))::varchar;
B16: =IF(EXACT([1]DataLookUp!$B16, ""), "", [1]DataLookUp!$B16) -> 95000000000010 | C16: =IF(EXACT(B16, ""), "", [1]DataLookUp!$C16) -> Finance Director | D16: 252000000000003 | E16: =IF(EXACT(D16, ""), "", VLOOKUP(D16, [2]DataLookUp!$B$4:$C$32, 2, FALSE)) -> Board Of Director | G16: =G15 + IF(EXACT(H16, ""), 0, 1) -> 253000000000010 | H16: =IF(AND(EXACT(B16, ""), EXACT(D16, "")), "", CONCATENATE("PERFORM ""SchSysConfig"".""Func_TblAppObject_UserRole_SET""(varSystemLoginSession, null::bigint, null::varchar, null::timestamptz, null::timestamptz, null::varchar, varInstitutionBranchID, varBaseCurrencyID, ", (IF(EXACT(B16, ""), "NULL", CONCATENATE("'", B16, "'"))),"::varchar);")) -> PERFORM "SchSysConfig"."Func_TblAppObject_UserRole_SET"(varSystemLoginSession, null::bigint, null::varchar, null::timestamptz, null::timestamptz, null::varchar, varInstitutionBranchID, varBaseCurrencyID, '95000000000010'::varchar); | J16: =IF(EXACT($H16, ""), "", CONCATENATE( "varSQL := varSQL || (CASE WHEN (varSQL = '') THEN '' ELSE ', ' END) || (SELECT JSON_BUILD_OBJECT (", "'recordID', NULL::bigint,", "'entities', ", "JSON_BUILD_OBJECT (", "'sysLoginSession_RefID', varSystemLoginSession::bigint,", "'sysDataAnnotation', NULL::varchar,", "'sysDataSetDateTimeTZ', NULL::timestamptz,", "'sysDataValidityStartDateTimeTZ', NULL::timestamptz,", "'sysDataValidityFinishDateTimeTZ', NULL::timestamptz,", "'sysPartitionRemovableRecordKey_RefID', NULL::bigint,", "'sysBranch_RefID', varInstitutionBranchID::bigint,", "'sysBaseCurrency_RefID',varBaseCurrencyID::bigint,", "'userRoleGroup_RefID', ", IF(EXACT($D16, ""), "null", CONCATENATE("'", SUBSTITUTE($D16, "'", "\'"), "'")), "::bigint, ", "'userRole_RefID', ", IF(EXACT($B16, ""), "null", CONCATENATE("'", SUBSTITUTE($B16, "'", "\'"), "'")), "::bigint", ")))::varchar;")) -> varSQL := varSQL || (CASE WHEN (varSQL = '') THEN '' ELSE ', ' END) || (SELECT JSON_BUILD_OBJECT ('recordID', NULL::bigint,'entities', JSON_BUILD_OBJECT ('sysLoginSession_RefID', varSystemLoginSession::bigint,'sysDataAnnotation', NULL::varchar,'sysDataSetDateTimeTZ', NULL::timestamptz,'sysDataValidityStartDateTimeTZ', NULL::timestamptz,'sysDataValidityFinishDateTimeTZ', NULL::timestamptz,'sysPartitionRemovableRecordKey_RefID', NULL::bigint,'sysBranch_RefID', varInstitutionBranchID::bigint,'sysBaseCurrency_RefID',varBaseCurrencyID::bigint,'userRoleGroup_RefID', '252000000000003'::bigint, 'userRole_RefID', '95000000000010'::bigint)))::varchar;
B17: =IF(EXACT([1]DataLookUp!$B17, ""), "", [1]DataLookUp!$B17) -> 95000000000011 | C17: =IF(EXACT(B17, ""), "", [1]DataLookUp!$C17) -> Operational Director | D17: 252000000000003 | E17: =IF(EXACT(D17, ""), "", VLOOKUP(D17, [2]DataLookUp!$B$4:$C$32, 2, FALSE)) -> Board Of Director | G17: =G16 + IF(EXACT(H17, ""), 0, 1) -> 253000000000011 | H17: =IF(AND(EXACT(B17, ""), EXACT(D17, "")), "", CONCATENATE("PERFORM ""SchSysConfig"".""Func_TblAppObject_UserRole_SET""(varSystemLoginSession, null::bigint, null::varchar, null::timestamptz, null::timestamptz, null::varchar, varInstitutionBranchID, varBaseCurrencyID, ", (IF(EXACT(B17, ""), "NULL", CONCATENATE("'", B17, "'"))),"::varchar);")) -> PERFORM "SchSysConfig"."Func_TblAppObject_UserRole_SET"(varSystemLoginSession, null::bigint, null::varchar, null::timestamptz, null::timestamptz, null::varchar, varInstitutionBranchID, varBaseCurrencyID, '95000000000011'::varchar); | J17: =IF(EXACT($H17, ""), "", CONCATENATE( "varSQL := varSQL || (CASE WHEN (varSQL = '') THEN '' ELSE ', ' END) || (SELECT JSON_BUILD_OBJECT (", "'recordID', NULL::bigint,", "'entities', ", "JSON_BUILD_OBJECT (", "'sysLoginSession_RefID', varSystemLoginSession::bigint,", "'sysDataAnnotation', NULL::varchar,", "'sysDataSetDateTimeTZ', NULL::timestamptz,", "'sysDataValidityStartDateTimeTZ', NULL::timestamptz,", "'sysDataValidityFinishDateTimeTZ', NULL::timestamptz,", "'sysPartitionRemovableRecordKey_RefID', NULL::bigint,", "'sysBranch_RefID', varInstitutionBranchID::bigint,", "'sysBaseCurrency_RefID',varBaseCurrencyID::bigint,", "'userRoleGroup_RefID', ", IF(EXACT($D17, ""), "null", CONCATENATE("'", SUBSTITUTE($D17, "'", "\'"), "'")), "::bigint, ", "'userRole_RefID', ", IF(EXACT($B17, ""), "null", CONCATENATE("'", SUBSTITUTE($B17, "'", "\'"), "'")), "::bigint", ")))::varchar;")) -> varSQL := varSQL || (CASE WHEN (varSQL = '') THEN '' ELSE ', ' END) || (SELECT JSON_BUILD_OBJECT ('recordID', NULL::bigint,'entities', JSON_BUILD_OBJECT ('sysLoginSession_RefID', varSystemLoginSession::bigint,'sysDataAnnotation', NULL::varchar,'sysDataSetDateTimeTZ', NULL::timestamptz,'sysDataValidityStartDateTimeTZ', NULL::timestamptz,'sysDataValidityFinishDateTimeTZ', NULL::timestamptz,'sysPartitionRemovableRecordKey_RefID', NULL::bigint,'sysBranch_RefID', varInstitutionBranchID::bigint,'sysBaseCurrency_RefID',varBaseCurrencyID::bigint,'userRoleGroup_RefID', '252000000000003'::bigint, 'userRole_RefID', '95000000000011'::bigint)))::varchar;
B18: =IF(EXACT([1]DataLookUp!$B18, ""), "", [1]DataLookUp!$B18) -> 95000000000012 | C18: =IF(EXACT(B18, ""), "", [1]DataLookUp!$C18) -> Marketing Director | D18: 252000000000003 | E18: =IF(EXACT(D18, ""), "", VLOOKUP(D18, [2]DataLookUp!$B$4:$C$32, 2, FALSE)) -> Board Of Director | G18: =G17 + IF(EXACT(H18, ""), 0, 1) -> 253000000000012 | H18: =IF(AND(EXACT(B18, ""), EXACT(D18, "")), "", CONCATENATE("PERFORM ""SchSysConfig"".""Func_TblAppObject_UserRole_SET""(varSystemLoginSession, null::bigint, null::varchar, null::timestamptz, null::timestamptz, null::varchar, varInstitutionBranchID, varBaseCurrencyID, ", (IF(EXACT(B18, ""), "NULL", CONCATENATE("'", B18, "'"))),"::varchar);")) -> PERFORM "SchSysConfig"."Func_TblAppObject_UserRole_SET"(varSystemLoginSession, null::bigint, null::varchar, null::timestamptz, null::timestamptz, null::varchar, varInstitutionBranchID, varBaseCurrencyID, '95000000000012'::varchar); | J18: =IF(EXACT($H18, ""), "", CONCATENATE( "varSQL := varSQL || (CASE WHEN (varSQL = '') THEN '' ELSE ', ' END) || (SELECT JSON_BUILD_OBJECT (", "'recordID', NULL::bigint,", "'entities', ", "JSON_BUILD_OBJECT (", "'sysLoginSession_RefID', varSystemLoginSession::bigint,", "'sysDataAnnotation', NULL::varchar,", "'sysDataSetDateTimeTZ', NULL::timestamptz,", "'sysDataValidityStartDateTimeTZ', NULL::timestamptz,", "'sysDataValidityFinishDateTimeTZ', NULL::timestamptz,", "'sysPartitionRemovableRecordKey_RefID', NULL::bigint,", "'sysBranch_RefID', varInstitutionBranchID::bigint,", "'sysBaseCurrency_RefID',varBaseCurrencyID::bigint,", "'userRoleGroup_RefID', ", IF(EXACT($D18, ""), "null", CONCATENATE("'", SUBSTITUTE($D18, "'", "\'"), "'")), "::bigint, ", "'userRole_RefID', ", IF(EXACT($B18, ""), "null", CONCATENATE("'", SUBSTITUTE($B18, "'", "\'"), "'")), "::bigint", ")))::varchar;")) -> varSQL := varSQL || (CASE WHEN (varSQL = '') THEN '' ELSE ', ' END) || (SELECT JSON_BUILD_OBJECT ('recordID', NULL::bigint,'entities', JSON_BUILD_OBJECT ('sysLoginSession_RefID', varSystemLoginSession::bigint,'sysDataAnnotation', NULL::varchar,'sysDataSetDateTimeTZ', NULL::timestamptz,'sysDataValidityStartDateTimeTZ', NULL::timestamptz,'sysDataValidityFinishDateTimeTZ', NULL::timestamptz,'sysPartitionRemovableRecordKey_RefID', NULL::bigint,'sysBranch_RefID', varInstitutionBranchID::bigint,'sysBaseCurrency_RefID',varBaseCurrencyID::bigint,'userRoleGroup_RefID', '252000000000003'::bigint, 'userRole_RefID', '95000000000012'::bigint)))::varchar;
B19: =IF(EXACT([1]DataLookUp!$B19, ""), "", [1]DataLookUp!$B19) -> 95000000000013 | C19: =IF(EXACT(B19, ""), "", [1]DataLookUp!$C19) -> Information Technology Director | D19: 252000000000003 | E19: =IF(EXACT(D19, ""), "", VLOOKUP(D19, [2]DataLookUp!$B$4:$C$32, 2, FALSE)) -> Board Of Director | G19: =G18 + IF(EXACT(H19, ""), 0, 1) -> 253000000000013 | H19: =IF(AND(EXACT(B19, ""), EXACT(D19, "")), "", CONCATENATE("PERFORM ""SchSysConfig"".""Func_TblAppObject_UserRole_SET""(varSystemLoginSession, null::bigint, null::varchar, null::timestamptz, null::timestamptz, null::varchar, varInstitutionBranchID, varBaseCurrencyID, ", (IF(EXACT(B19, ""), "NULL", CONCATENATE("'", B19, "'"))),"::varchar);")) -> PERFORM "SchSysConfig"."Func_TblAppObject_UserRole_SET"(varSystemLoginSession, null::bigint, null::varchar, null::timestamptz, null::timestamptz, null::varchar, varInstitutionBranchID, varBaseCurrencyID, '95000000000013'::varchar); | J19: =IF(EXACT($H19, ""), "", CONCATENATE( "varSQL := varSQL || (CASE WHEN (varSQL = '') THEN '' ELSE ', ' END) || (SELECT JSON_BUILD_OBJECT (", "'recordID', NULL::bigint,", "'entities', ", "JSON_BUILD_OBJECT (", "'sysLoginSession_RefID', varSystemLoginSession::bigint,", "'sysDataAnnotation', NULL::varchar,", "'sysDataSetDateTimeTZ', NULL::timestamptz,", "'sysDataValidityStartDateTimeTZ', NULL::timestamptz,", "'sysDataValidityFinishDateTimeTZ', NULL::timestamptz,", "'sysPartitionRemovableRecordKey_RefID', NULL::bigint,", "'sysBranch_RefID', varInstitutionBranchID::bigint,", "'sysBaseCurrency_RefID',varBaseCurrencyID::bigint,", "'userRoleGroup_RefID', ", IF(EXACT($D19, ""), "null", CONCATENATE("'", SUBSTITUTE($D19, "'", "\'"), "'")), "::bigint, ", "'userRole_RefID', ", IF(EXACT($B19, ""), "null", CONCATENATE("'", SUBSTITUTE($B19, "'", "\'"), "'")), "::bigint", ")))::varchar;")) -> varSQL := varSQL || (CASE WHEN (varSQL = '') THEN '' ELSE ', ' END) || (SELECT JSON_BUILD_OBJECT ('recordID', NULL::bigint,'entities', JSON_BUILD_OBJECT ('sysLoginSession_RefID', varSystemLoginSession::bigint,'sysDataAnnotation', NULL::varchar,'sysDataSetDateTimeTZ', NULL::timestamptz,'sysDataValidityStartDateTimeTZ', NULL::timestamptz,'sysDataValidityFinishDateTimeTZ', NULL::timestamptz,'sysPartitionRemovableRecordKey_RefID', NULL::bigint,'sysBranch_RefID', varInstitutionBranchID::bigint,'sysBaseCurrency_RefID',varBaseCurrencyID::bigint,'userRoleGroup_RefID', '252000000000003'::bigint, 'userRole_RefID', '95000000000013'::bigint)))::varchar;
B20: =IF(EXACT([1]DataLookUp!$B20, ""), "", [1]DataLookUp!$B20) | C20: =IF(EXACT(B20, ""), "", [1]DataLookUp!$C20) | E20: =IF(EXACT(D20, ""), "", VLOOKUP(D20, [2]DataLookUp!$B$4:$C$32, 2, FALSE)) | G20: =G19 + IF(EXACT(H20, ""), 0, 1) -> 253000000000013 | H20: =IF(AND(EXACT(B20, ""), EXACT(D20, "")), "", CONCATENATE("PERFORM ""SchSysConfig"".""Func_TblAppObject_UserRole_SET""(varSystemLoginSession, null::bigint, null::varchar, null::timestamptz, null::timestamptz, null::varchar, varInstitutionBranchID, varBaseCurrencyID, ", (IF(EXACT(B20, ""), "NULL", CONCATENATE("'", B20, "'"))),"::varchar);")) | J20: =IF(EXACT($H20, ""), "", CONCATENATE( "varSQL := varSQL || (CASE WHEN (varSQL = '') THEN '' ELSE ', ' END) || (SELECT JSON_BUILD_OBJECT (", "'recordID', NULL::bigint,", "'entities', ", "JSON_BUILD_OBJECT (", "'sysLoginSession_RefID', varSystemLoginSession::bigint,", "'sysDataAnnotation', NULL::varchar,", "'sysDataSetDateTimeTZ', NULL::timestamptz,", "'sysDataValidityStartDateTimeTZ', NULL::timestamptz,", "'sysDataValidityFinishDateTimeTZ', NULL::timestamptz,", "'sysPartitionRemovableRecordKey_RefID', NULL::bigint,", "'sysBranch_RefID', varInstitutionBranchID::bigint,", "'sysBaseCurrency_RefID',varBaseCurrencyID::bigint,", "'userRoleGroup_RefID', ", IF(EXACT($D20, ""), "null", CONCATENATE("'", SUBSTITUTE($D20, "'", "\'"), "'")), "::bigint, ", "'userRole_RefID', ", IF(EXACT($B20, ""), "null", CONCATENATE("'", SUBSTITUTE($B20, "'", "\'"), "'")), "::bigint", ")))::varchar;"))
B21: =IF(EXACT([1]DataLookUp!$B21, ""), "", [1]DataLookUp!$B21) -> 95000000000014 | C21: =IF(EXACT(B21, ""), "", [1]DataLookUp!$C21) -> Project General Manager | D21: 252000000000005 | E21: =IF(EXACT(D21, ""), "", VLOOKUP(D21, [2]DataLookUp!$B$4:$C$32, 2, FALSE)) -> Top Level Management | G21: =G20 + IF(EXACT(H21, ""), 0, 1) -> 253000000000014 | H21: =IF(AND(EXACT(B21, ""), EXACT(D21, "")), "", CONCATENATE("PERFORM ""SchSysConfig"".""Func_TblAppObject_UserRole_SET""(varSystemLoginSession, null::bigint, null::varchar, null::timestamptz, null::timestamptz, null::varchar, varInstitutionBranchID, varBaseCurrencyID, ", (IF(EXACT(B21, ""), "NULL", CONCATENATE("'", B21, "'"))),"::varchar);")) -> PERFORM "SchSysConfig"."Func_TblAppObject_UserRole_SET"(varSystemLoginSession, null::bigint, null::varchar, null::timestamptz, null::timestamptz, null::varchar, varInstitutionBranchID, varBaseCurrencyID, '95000000000014'::varchar); | J21: =IF(EXACT($H21, ""), "", CONCATENATE( "varSQL := varSQL || (CASE WHEN (varSQL = '') THEN '' ELSE ', ' END) || (SELECT JSON_BUILD_OBJECT (", "'recordID', NULL::bigint,", "'entities', ", "JSON_BUILD_OBJECT (", "'sysLoginSession_RefID', varSystemLoginSession::bigint,", "'sysDataAnnotation', NULL::varchar,", "'sysDataSetDateTimeTZ', NULL::timestamptz,", "'sysDataValidityStartDateTimeTZ', NULL::timestamptz,", "'sysDataValidityFinishDateTimeTZ', NULL::timestamptz,", "'sysPartitionRemovableRecordKey_RefID', NULL::bigint,", "'sysBranch_RefID', varInstitutionBranchID::bigint,", "'sysBaseCurrency_RefID',varBaseCurrencyID::bigint,", "'userRoleGroup_RefID', ", IF(EXACT($D21, ""), "null", CONCATENATE("'", SUBSTITUTE($D21, "'", "\'"), "'")), "::bigint, ", "'userRole_RefID', ", IF(EXACT($B21, ""), "null", CONCATENATE("'", SUBSTITUTE($B21, "'", "\'"), "'")), "::bigint", ")))::varchar;")) -> varSQL := varSQL || (CASE WHEN (varSQL = '') THEN '' ELSE ', ' END) || (SELECT JSON_BUILD_OBJECT ('recordID', NULL::bigint,'entities', JSON_BUILD_OBJECT ('sysLoginSession_RefID', varSystemLoginSession::bigint,'sysDataAnnotation', NULL::varchar,'sysDataSetDateTimeTZ', NULL::timestamptz,'sysDataValidityStartDateTimeTZ', NULL::timestamptz,'sysDataValidityFinishDateTimeTZ', NULL::timestamptz,'sysPartitionRemovableRecordKey_RefID', NULL::bigint,'sysBranch_RefID', varInstitutionBranchID::bigint,'sysBaseCurrency_RefID',varBaseCurrencyID::bigint,'userRoleGroup_RefID', '252000000000005'::bigint, 'userRole_RefID', '95000000000014'::bigint)))::varchar;
B22: =IF(EXACT([1]DataLookUp!$B22, ""), "", [1]DataLookUp!$B22) -> 95000000000015 | C22: =IF(EXACT(B22, ""), "", [1]DataLookUp!$C22) -> Project Management Officer | D22: 252000000000005 | E22: =IF(EXACT(D22, ""), "", VLOOKUP(D22, [2]DataLookUp!$B$4:$C$32, 2, FALSE)) -> Top Level Management | G22: =G21 + IF(EXACT(H22, ""), 0, 1) -> 253000000000015 | H22: =IF(AND(EXACT(B22, ""), EXACT(D22, "")), "", CONCATENATE("PERFORM ""SchSysConfig"".""Func_TblAppObject_UserRole_SET""(varSystemLoginSession, null::bigint, null::varchar, null::timestamptz, null::timestamptz, null::varchar, varInstitutionBranchID, varBaseCurrencyID, ", (IF(EXACT(B22, ""), "NULL", CONCATENATE("'", B22, "'"))),"::varchar);")) -> PERFORM "SchSysConfig"."Func_TblAppObject_UserRole_SET"(varSystemLoginSession, null::bigint, null::varchar, null::timestamptz, null::timestamptz, null::varchar, varInstitutionBranchID, varBaseCurrencyID, '95000000000015'::varchar); | J22: =IF(EXACT($H22, ""), "", CONCATENATE( "varSQL := varSQL || (CASE WHEN (varSQL = '') THEN '' ELSE ', ' END) || (SELECT JSON_BUILD_OBJECT (", "'recordID', NULL::bigint,", "'entities', ", "JSON_BUILD_OBJECT (", "'sysLoginSession_RefID', varSystemLoginSession::bigint,", "'sysDataAnnotation', NULL::varchar,", "'sysDataSetDateTimeTZ', NULL::timestamptz,", "'sysDataValidityStartDateTimeTZ', NULL::timestamptz,", "'sysDataValidityFinishDateTimeTZ', NULL::timestamptz,", "'sysPartitionRemovableRecordKey_RefID', NULL::bigint,", "'sysBranch_RefID', varInstitutionBranchID::bigint,", "'sysBaseCurrency_RefID',varBaseCurrencyID::bigint,", "'userRoleGroup_RefID', ", IF(EXACT($D22, ""), "null", CONCATENATE("'", SUBSTITUTE($D22, "'", "\'"), "'")), "::bigint, ", "'userRole_RefID', ", IF(EXACT($B22, ""), "null", CONCATENATE("'", SUBSTITUTE($B22, "'", "\'"), "'")), "::bigint", ")))::varchar;")) -> varSQL := varSQL || (CASE WHEN (varSQL = '') THEN '' ELSE ', ' END) || (SELECT JSON_BUILD_OBJECT ('recordID', NULL::bigint,'entities', JSON_BUILD_OBJECT ('sysLoginSession_RefID', varSystemLoginSession::bigint,'sysDataAnnotation', NULL::varchar,'sysDataSetDateTimeTZ', NULL::timestamptz,'sysDataValidityStartDateTimeTZ', NULL::timestamptz,'sysDataValidityFinishDateTimeTZ', NULL::timestamptz,'sysPartitionRemovableRecordKey_RefID', NULL::bigint,'sysBranch_RefID', varInstitutionBranchID::bigint,'sysBaseCurrency_RefID',varBaseCurrencyID::bigint,'userRoleGroup_RefID', '252000000000005'::bigint, 'userRole_RefID', '95000000000015'::bigint)))::varchar;
B23: =IF(EXACT([1]DataLookUp!$B23, ""), "", [1]DataLookUp!$B23) -> 95000000000016 | C23: =IF(EXACT(B23, ""), "", [1]DataLookUp!$C23) -> Finance, Accounting, & Tax General Manager | D23: 252000000000005 | E23: =IF(EXACT(D23, ""), "", VLOOKUP(D23, [2]DataLookUp!$B$4:$C$32, 2, FALSE)) -> Top Level Management | G23: =G22 + IF(EXACT(H23, ""), 0, 1) -> 253000000000016 | H23: =IF(AND(EXACT(B23, ""), EXACT(D23, "")), "", CONCATENATE("PERFORM ""SchSysConfig"".""Func_TblAppObject_UserRole_SET""(varSystemLoginSession, null::bigint, null::varchar, null::timestamptz, null::timestamptz, null::varchar, varInstitutionBranchID, varBaseCurrencyID, ", (IF(EXACT(B23, ""), "NULL", CONCATENATE("'", B23, "'"))),"::varchar);")) -> PERFORM "SchSysConfig"."Func_TblAppObject_UserRole_SET"(varSystemLoginSession, null::bigint, null::varchar, null::timestamptz, null::timestamptz, null::varchar, varInstitutionBranchID, varBaseCurrencyID, '95000000000016'::varchar); | J23: =IF(EXACT($H23, ""), "", CONCATENATE( "varSQL := varSQL || (CASE WHEN (varSQL = '') THEN '' ELSE ', ' END) || (SELECT JSON_BUILD_OBJECT (", "'recordID', NULL::bigint,", "'entities', ", "JSON_BUILD_OBJECT (", "'sysLoginSession_RefID', varSystemLoginSession::bigint,", "'sysDataAnnotation', NULL::varchar,", "'sysDataSetDateTimeTZ', NULL::timestamptz,", "'sysDataValidityStartDateTimeTZ', NULL::timestamptz,", "'sysDataValidityFinishDateTimeTZ', NULL::timestamptz,", "'sysPartitionRemovableRecordKey_RefID', NULL::bigint,", "'sysBranch_RefID', varInstitutionBranchID::bigint,", "'sysBaseCurrency_RefID',varBaseCurrencyID::bigint,", "'userRoleGroup_RefID', ", IF(EXACT($D23, ""), "null", CONCATENATE("'", SUBSTITUTE($D23, "'", "\'"), "'")), "::bigint, ", "'userRole_RefID', ", IF(EXACT($B23, ""), "null", CONCATENATE("'", SUBSTITUTE($B23, "'", "\'"), "'")), "::bigint", ")))::varchar;")) -> varSQL := varSQL || (CASE WHEN (varSQL = '') THEN '' ELSE ', ' END) || (SELECT JSON_BUILD_OBJECT ('recordID', NULL::bigint,'entities', JSON_BUILD_OBJECT ('sysLoginSession_RefID', varSystemLoginSession::bigint,'sysDataAnnotation', NULL::varchar,'sysDataSetDateTimeTZ', NULL::timestamptz,'sysDataValidityStartDateTimeTZ', NULL::timestamptz,'sysDataValidityFinishDateTimeTZ', NULL::timestamptz,'sysPartitionRemovableRecordKey_RefID', NULL::bigint,'sysBranch_RefID', varInstitutionBranchID::bigint,'sysBaseCurrency_RefID',varBaseCurrencyID::bigint,'userRoleGroup_RefID', '252000000000005'::bigint, 'userRole_RefID', '95000000000016'::bigint)))::varchar;
B24: =IF(EXACT([1]DataLookUp!$B24, ""), "", [1]DataLookUp!$B24) -> 95000000000017 | C24: =IF(EXACT(B24, ""), "", [1]DataLookUp!$C24) -> HR, GA, & TAM General Manager | D24: 252000000000005 | E24: =IF(EXACT(D24, ""), "", VLOOKUP(D24, [2]DataLookUp!$B$4:$C$32, 2, FALSE)) -> Top Level Management | G24: =G23 + IF(EXACT(H24, ""), 0, 1) -> 253000000000017 | H24: =IF(AND(EXACT(B24, ""), EXACT(D24, "")), "", CONCATENATE("PERFORM ""SchSysConfig"".""Func_TblAppObject_UserRole_SET""(varSystemLoginSession, null::bigint, null::varchar, null::timestamptz, null::timestamptz, null::varchar, varInstitutionBranchID, varBaseCurrencyID, ", (IF(EXACT(B24, ""), "NULL", CONCATENATE("'", B24, "'"))),"::varchar);")) -> PERFORM "SchSysConfig"."Func_TblAppObject_UserRole_SET"(varSystemLoginSession, null::bigint, null::varchar, null::timestamptz, null::timestamptz, null::varchar, varInstitutionBranchID, varBaseCurrencyID, '95000000000017'::varchar); | J24: =IF(EXACT($H24, ""), "", CONCATENATE( "varSQL := varSQL || (CASE WHEN (varSQL = '') THEN '' ELSE ', ' END) || (SELECT JSON_BUILD_OBJECT (", "'recordID', NULL::bigint,", "'entities', ", "JSON_BUILD_OBJECT (", "'sysLoginSession_RefID', varSystemLoginSession::bigint,", "'sysDataAnnotation', NULL::varchar,", "'sysDataSetDateTimeTZ', NULL::timestamptz,", "'sysDataValidityStartDateTimeTZ', NULL::timestamptz,", "'sysDataValidityFinishDateTimeTZ', NULL::timestamptz,", "'sysPartitionRemovableRecordKey_RefID', NULL::bigint,", "'sysBranch_RefID', varInstitutionBranchID::bigint,", "'sysBaseCurrency_RefID',varBaseCurrencyID::bigint,", "'userRoleGroup_RefID', ", IF(EXACT($D24, ""), "null", CONCATENATE("'", SUBSTITUTE($D24, "'", "\'"), "'")), "::bigint, ", "'userRole_RefID', ", IF(EXACT($B24, ""), "null", CONCATENATE("'", SUBSTITUTE($B24, "'", "\'"), "'")), "::bigint", ")))::varchar;")) -> varSQL := varSQL || (CASE WHEN (varSQL = '') THEN '' ELSE ', ' END) || (SELECT JSON_BUILD_OBJECT ('recordID', NULL::bigint,'entities', JSON_BUILD_OBJECT ('sysLoginSession_RefID', varSystemLoginSession::bigint,'sysDataAnnotation', NULL::varchar,'sysDataSetDateTimeTZ', NULL::timestamptz,'sysDataValidityStartDateTimeTZ', NULL::timestamptz,'sysDataValidityFinishDateTimeTZ', NULL::timestamptz,'sysPartitionRemovableRecordKey_RefID', NULL::bigint,'sysBranch_RefID', varInstitutionBranchID::bigint,'sysBaseCurrency_RefID',varBaseCurrencyID::bigint,'userRoleGroup_RefID', '252000000000005'::bigint, 'userRole_RefID', '95000000000017'::bigint)))::varchar;
B25: =IF(EXACT([1]DataLookUp!$B25, ""), "", [1]DataLookUp!$B25) -> 95000000000018 | C25: =IF(EXACT(B25, ""), "", [1]DataLookUp!$C25) -> Sales General Manager | D25: 252000000000005 | E25: =IF(EXACT(D25, ""), "", VLOOKUP(D25, [2]DataLookUp!$B$4:$C$32, 2, FALSE)) -> Top Level Management | G25: =G24 + IF(EXACT(H25, ""), 0, 1) -> 253000000000018 | H25: =IF(AND(EXACT(B25, ""), EXACT(D25, "")), "", CONCATENATE("PERFORM ""SchSysConfig"".""Func_TblAppObject_UserRole_SET""(varSystemLoginSession, null::bigint, null::varchar, null::timestamptz, null::timestamptz, null::varchar, varInstitutionBranchID, varBaseCurrencyID, ", (IF(EXACT(B25, ""), "NULL", CONCATENATE("'", B25, "'"))),"::varchar);")) -> PERFORM "SchSysConfig"."Func_TblAppObject_UserRole_SET"(varSystemLoginSession, null::bigint, null::varchar, null::timestamptz, null::timestamptz, null::varchar, varInstitutionBranchID, varBaseCurrencyID, '95000000000018'::varchar); | J25: =IF(EXACT($H25, ""), "", CONCATENATE( "varSQL := varSQL || (CASE WHEN (varSQL = '') THEN '' ELSE ', ' END) || (SELECT JSON_BUILD_OBJECT (", "'recordID', NULL::bigint,", "'entities', ", "JSON_BUILD_OBJECT (", "'sysLoginSession_RefID', varSystemLoginSession::bigint,", "'sysDataAnnotation', NULL::varchar,", "'sysDataSetDateTimeTZ', NULL::timestamptz,", "'sysDataValidityStartDateTimeTZ', NULL::timestamptz,", "'sysDataValidityFinishDateTimeTZ', NULL::timestamptz,", "'sysPartitionRemovableRecordKey_RefID', NULL::bigint,", "'sysBranch_RefID', varInstitutionBranchID::bigint,", "'sysBaseCurrency_RefID',varBaseCurrencyID::bigint,", "'userRoleGroup_RefID', ", IF(EXACT($D25, ""), "null", CONCATENATE("'", SUBSTITUTE($D25, "'", "\'"), "'")), "::bigint, ", "'userRole_RefID', ", IF(EXACT($B25, ""), "null", CONCATENATE("'", SUBSTITUTE($B25, "'", "\'"), "'")), "::bigint", ")))::varchar;")) -> varSQL := varSQL || (CASE WHEN (varSQL = '') THEN '' ELSE ', ' END) || (SELECT JSON_BUILD_OBJECT ('recordID', NULL::bigint,'entities', JSON_BUILD_OBJECT ('sysLoginSession_RefID', varSystemLoginSession::bigint,'sysDataAnnotation', NULL::varchar,'sysDataSetDateTimeTZ', NULL::timestamptz,'sysDataValidityStartDateTimeTZ', NULL::timestamptz,'sysDataValidityFinishDateTimeTZ', NULL::timestamptz,'sysPartitionRemovableRecordKey_RefID', NULL::bigint,'sysBranch_RefID', varInstitutionBranchID::bigint,'sysBaseCurrency_RefID',varBaseCurrencyID::bigint,'userRoleGroup_RefID', '252000000000005'::bigint, 'userRole_RefID', '95000000000018'::bigint)))::varchar;
B26: =IF(EXACT([1]DataLookUp!$B26, ""), "", [1]DataLookUp!$B26) | C26: =IF(EXACT(B26, ""), "", [1]DataLookUp!$C26) | E26: =IF(EXACT(D26, ""), "", VLOOKUP(D26, [2]DataLookUp!$B$4:$C$32, 2, FALSE)) | G26: =G25 + IF(EXACT(H26, ""), 0, 1) -> 253000000000018 | H26: =IF(AND(EXACT(B26, ""), EXACT(D26, "")), "", CONCATENATE("PERFORM ""SchSysConfig"".""Func_TblAppObject_UserRole_SET""(varSystemLoginSession, null::bigint, null::varchar, null::timestamptz, null::timestamptz, null::varchar, varInstitutionBranchID, varBaseCurrencyID, ", (IF(EXACT(B26, ""), "NULL", CONCATENATE("'", B26, "'"))),"::varchar);")) | J26: =IF(EXACT($H26, ""), "", CONCATENATE( "varSQL := varSQL || (CASE WHEN (varSQL = '') THEN '' ELSE ', ' END) || (SELECT JSON_BUILD_OBJECT (", "'recordID', NULL::bigint,", "'entities', ", "JSON_BUILD_OBJECT (", "'sysLoginSession_RefID', varSystemLoginSession::bigint,", "'sysDataAnnotation', NULL::varchar,", "'sysDataSetDateTimeTZ', NULL::timestamptz,", "'sysDataValidityStartDateTimeTZ', NULL::timestamptz,", "'sysDataValidityFinishDateTimeTZ', NULL::timestamptz,", "'sysPartitionRemovableRecordKey_RefID', NULL::bigint,", "'sysBranch_RefID', varInstitutionBranchID::bigint,", "'sysBaseCurrency_RefID',varBaseCurrencyID::bigint,", "'userRoleGroup_RefID', ", IF(EXACT($D26, ""), "null", CONCATENATE("'", SUBSTITUTE($D26, "'", "\'"), "'")), "::bigint, ", "'userRole_RefID', ", IF(EXACT($B26, ""), "null", CONCATENATE("'", SUBSTITUTE($B26, "'", "\'"), "'")), "::bigint", ")))::varchar;"))
B27: =IF(EXACT([1]DataLookUp!$B27, ""), "", [1]DataLookUp!$B27) -> 95000000000019 | C27: =IF(EXACT(B27, ""), "", [1]DataLookUp!$C27) -> Project Manager | D27: 252000000000015 | E27: =IF(EXACT(D27, ""), "", VLOOKUP(D27, [2]DataLookUp!$B$4:$C$32, 2, FALSE)) -> Department - Project | G27: =G26 + IF(EXACT(H27, ""), 0, 1) -> 253000000000019 | H27: =IF(AND(EXACT(B27, ""), EXACT(D27, "")), "", CONCATENATE("PERFORM ""SchSysConfig"".""Func_TblAppObject_UserRole_SET""(varSystemLoginSession, null::bigint, null::varchar, null::timestamptz, null::timestamptz, null::varchar, varInstitutionBranchID, varBaseCurrencyID, ", (IF(EXACT(B27, ""), "NULL", CONCATENATE("'", B27, "'"))),"::varchar);")) -> PERFORM "SchSysConfig"."Func_TblAppObject_UserRole_SET"(varSystemLoginSession, null::bigint, null::varchar, null::timestamptz, null::timestamptz, null::varchar, varInstitutionBranchID, varBaseCurrencyID, '95000000000019'::varchar); | J27: =IF(EXACT($H27, ""), "", CONCATENATE( "varSQL := varSQL || (CASE WHEN (varSQL = '') THEN '' ELSE ', ' END) || (SELECT JSON_BUILD_OBJECT (", "'recordID', NULL::bigint,", "'entities', ", "JSON_BUILD_OBJECT (", "'sysLoginSession_RefID', varSystemLoginSession::bigint,", "'sysDataAnnotation', NULL::varchar,", "'sysDataSetDateTimeTZ', NULL::timestamptz,", "'sysDataValidityStartDateTimeTZ', NULL::timestamptz,", "'sysDataValidityFinishDateTimeTZ', NULL::timestamptz,", "'sysPartitionRemovableRecordKey_RefID', NULL::bigint,", "'sysBranch_RefID', varInstitutionBranchID::bigint,", "'sysBaseCurrency_RefID',varBaseCurrencyID::bigint,", "'userRoleGroup_RefID', ", IF(EXACT($D27, ""), "null", CONCATENATE("'", SUBSTITUTE($D27, "'", "\'"), "'")), "::bigint, ", "'userRole_RefID', ", IF(EXACT($B27, ""), "null", CONCATENATE("'", SUBSTITUTE($B27, "'", "\'"), "'")), "::bigint", ")))::varchar;")) -> varSQL := varSQL || (CASE WHEN (varSQL = '') THEN '' ELSE ', ' END) || (SELECT JSON_BUILD_OBJECT ('recordID', NULL::bigint,'entities', JSON_BUILD_OBJECT ('sysLoginSession_RefID', varSystemLoginSession::bigint,'sysDataAnnotation', NULL::varchar,'sysDataSetDateTimeTZ', NULL::timestamptz,'sysDataValidityStartDateTimeTZ', NULL::timestamptz,'sysDataValidityFinishDateTimeTZ', NULL::timestamptz,'sysPartitionRemovableRecordKey_RefID', NULL::bigint,'sysBranch_RefID', varInstitutionBranchID::bigint,'sysBaseCurrency_RefID',varBaseCurrencyID::bigint,'userRoleGroup_RefID', '252000000000015'::bigint, 'userRole_RefID', '95000000000019'::bigint)))::varchar;
B28: =IF(EXACT([1]DataLookUp!$B28, ""), "", [1]DataLookUp!$B28) -> 95000000000020 | C28: =IF(EXACT(B28, ""), "", [1]DataLookUp!$C28) -> Site Manager | D28: 252000000000015 | E28: =IF(EXACT(D28, ""), "", VLOOKUP(D28, [2]DataLookUp!$B$4:$C$32, 2, FALSE)) -> Department - Project | G28: =G27 + IF(EXACT(H28, ""), 0, 1) -> 253000000000020 | H28: =IF(AND(EXACT(B28, ""), EXACT(D28, "")), "", CONCATENATE("PERFORM ""SchSysConfig"".""Func_TblAppObject_UserRole_SET""(varSystemLoginSession, null::bigint, null::varchar, null::timestamptz, null::timestamptz, null::varchar, varInstitutionBranchID, varBaseCurrencyID, ", (IF(EXACT(B28, ""), "NULL", CONCATENATE("'", B28, "'"))),"::varchar);")) -> PERFORM "SchSysConfig"."Func_TblAppObject_UserRole_SET"(varSystemLoginSession, null::bigint, null::varchar, null::timestamptz, null::timestamptz, null::varchar, varInstitutionBranchID, varBaseCurrencyID, '95000000000020'::varchar); | J28: =IF(EXACT($H28, ""), "", CONCATENATE( "varSQL := varSQL || (CASE WHEN (varSQL = '') THEN '' ELSE ', ' END) || (SELECT JSON_BUILD_OBJECT (", "'recordID', NULL::bigint,", "'entities', ", "JSON_BUILD_OBJECT (", "'sysLoginSession_RefID', varSystemLoginSession::bigint,", "'sysDataAnnotation', NULL::varchar,", "'sysDataSetDateTimeTZ', NULL::timestamptz,", "'sysDataValidityStartDateTimeTZ', NULL::timestamptz,", "'sysDataValidityFinishDateTimeTZ', NULL::timestamptz,", "'sysPartitionRemovableRecordKey_RefID', NULL::bigint,", "'sysBranch_RefID', varInstitutionBranchID::bigint,", "'sysBaseCurrency_RefID',varBaseCurrencyID::bigint,", "'userRoleGroup_RefID', ", IF(EXACT($D28, ""), "null", CONCATENATE("'", SUBSTITUTE($D28, "'", "\'"), "'")), "::bigint, ", "'userRole_RefID', ", IF(EXACT($B28, ""), "null", CONCATENATE("'", SUBSTITUTE($B28, "'", "\'"), "'")), "::bigint", ")))::varchar;")) -> varSQL := varSQL || (CASE WHEN (varSQL = '') THEN '' ELSE ', ' END) || (SELECT JSON_BUILD_OBJECT ('recordID', NULL::bigint,'entities', JSON_BUILD_OBJECT ('sysLoginSession_RefID', varSystemLoginSession::bigint,'sysDataAnnotation', NULL::varchar,'sysDataSetDateTimeTZ', NULL::timestamptz,'sysDataValidityStartDateTimeTZ', NULL::timestamptz,'sysDataValidityFinishDateTimeTZ', NULL::timestamptz,'sysPartitionRemovableRecordKey_RefID', NULL::bigint,'sysBranch_RefID', varInstitutionBranchID::bigint,'sysBaseCurrency_RefID',varBaseCurrencyID::bigint,'userRoleGroup_RefID', '252000000000015'::bigint, 'userRole_RefID', '95000000000020'::bigint)))::varchar;
B29: =IF(EXACT([1]DataLookUp!$B29, ""), "", [1]DataLookUp!$B29) -> 95000000000021 | C29: =IF(EXACT(B29, ""), "", [1]DataLookUp!$C29) -> Project Controller Coordinator | D29: 252000000000015 | E29: =IF(EXACT(D29, ""), "", VLOOKUP(D29, [2]DataLookUp!$B$4:$C$32, 2, FALSE)) -> Department - Project | G29: =G28 + IF(EXACT(H29, ""), 0, 1) -> 253000000000021 | H29: =IF(AND(EXACT(B29, ""), EXACT(D29, "")), "", CONCATENATE("PERFORM ""SchSysConfig"".""Func_TblAppObject_UserRole_SET""(varSystemLoginSession, null::bigint, null::varchar, null::timestamptz, null::timestamptz, null::varchar, varInstitutionBranchID, varBaseCurrencyID, ", (IF(EXACT(B29, ""), "NULL", CONCATENATE("'", B29, "'"))),"::varchar);")) -> PERFORM "SchSysConfig"."Func_TblAppObject_UserRole_SET"(varSystemLoginSession, null::bigint, null::varchar, null::timestamptz, null::timestamptz, null::varchar, varInstitutionBranchID, varBaseCurrencyID, '95000000000021'::varchar); | J29: =IF(EXACT($H29, ""), "", CONCATENATE( "varSQL := varSQL || (CASE WHEN (varSQL = '') THEN '' ELSE ', ' END) || (SELECT JSON_BUILD_OBJECT (", "'recordID', NULL::bigint,", "'entities', ", "JSON_BUILD_OBJECT (", "'sysLoginSession_RefID', varSystemLoginSession::bigint,", "'sysDataAnnotation', NULL::varchar,", "'sysDataSetDateTimeTZ', NULL::timestamptz,", "'sysDataValidityStartDateTimeTZ', NULL::timestamptz,", "'sysDataValidityFinishDateTimeTZ', NULL::timestamptz,", "'sysPartitionRemovableRecordKey_RefID', NULL::bigint,", "'sysBranch_RefID', varInstitutionBranchID::bigint,", "'sysBaseCurrency_RefID',varBaseCurrencyID::bigint,", "'userRoleGroup_RefID', ", IF(EXACT($D29, ""), "null", CONCATENATE("'", SUBSTITUTE($D29, "'", "\'"), "'")), "::bigint, ", "'userRole_RefID', ", IF(EXACT($B29, ""), "null", CONCATENATE("'", SUBSTITUTE($B29, "'", "\'"), "'")), "::bigint", ")))::varchar;")) -> varSQL := varSQL || (CASE WHEN (varSQL = '') THEN '' ELSE ', ' END) || (SELECT JSON_BUILD_OBJECT ('recordID', NULL::bigint,'entities', JSON_BUILD_OBJECT ('sysLoginSession_RefID', varSystemLoginSession::bigint,'sysDataAnnotation', NULL::varchar,'sysDataSetDateTimeTZ', NULL::timestamptz,'sysDataValidityStartDateTimeTZ', NULL::timestamptz,'sysDataValidityFinishDateTimeTZ', NULL::timestamptz,'sysPartitionRemovableRecordKey_RefID', NULL::bigint,'sysBranch_RefID', varInstitutionBranchID::bigint,'sysBaseCurrency_RefID',varBaseCurrencyID::bigint,'userRoleGroup_RefID', '252000000000015'::bigint, 'userRole_RefID', '95000000000021'::bigint)))::varchar;
B30: =IF(EXACT([1]DataLookUp!$B30, ""), "", [1]DataLookUp!$B30) -> 95000000000022 | C30: =IF(EXACT(B30, ""), "", [1]DataLookUp!$C30) -> Project Controller Staff | D30: 252000000000015 | E30: =IF(EXACT(D30, ""), "", VLOOKUP(D30, [2]DataLookUp!$B$4:$C$32, 2, FALSE)) -> Department - Project | G30: =G29 + IF(EXACT(H30, ""), 0, 1) -> 253000000000022 | H30: =IF(AND(EXACT(B30, ""), EXACT(D30, "")), "", CONCATENATE("PERFORM ""SchSysConfig"".""Func_TblAppObject_UserRole_SET""(varSystemLoginSession, null::bigint, null::varchar, null::timestamptz, null::timestamptz, null::varchar, varInstitutionBranchID, varBaseCurrencyID, ", (IF(EXACT(B30, ""), "NULL", CONCATENATE("'", B30, "'"))),"::varchar);")) -> PERFORM "SchSysConfig"."Func_TblAppObject_UserRole_SET"(varSystemLoginSession, null::bigint, null::varchar, null::timestamptz, null::timestamptz, null::varchar, varInstitutionBranchID, varBaseCurrencyID, '95000000000022'::varchar); | J30: =IF(EXACT($H30, ""), "", CONCATENATE( "varSQL := varSQL || (CASE WHEN (varSQL = '') THEN '' ELSE ', ' END) || (SELECT JSON_BUILD_OBJECT (", "'recordID', NULL::bigint,", "'entities', ", "JSON_BUILD_OBJECT (", "'sysLoginSession_RefID', varSystemLoginSession::bigint,", "'sysDataAnnotation', NULL::varchar,", "'sysDataSetDateTimeTZ', NULL::timestamptz,", "'sysDataValidityStartDateTimeTZ', NULL::timestamptz,", "'sysDataValidityFinishDateTimeTZ', NULL::timestamptz,", "'sysPartitionRemovableRecordKey_RefID', NULL::bigint,", "'sysBranch_RefID', varInstitutionBranchID::bigint,", "'sysBaseCurrency_RefID',varBaseCurrencyID::bigint,", "'userRoleGroup_RefID', ", IF(EXACT($D30, ""), "null", CONCATENATE("'", SUBSTITUTE($D30, "'", "\'"), "'")), "::bigint, ", "'userRole_RefID', ", IF(EXACT($B30, ""), "null", CONCATENATE("'", SUBSTITUTE($B30, "'", "\'"), "'")), "::bigint", ")))::varchar;")) -> varSQL := varSQL || (CASE WHEN (varSQL = '') THEN '' ELSE ', ' END) || (SELECT JSON_BUILD_OBJECT ('recordID', NULL::bigint,'entities', JSON_BUILD_OBJECT ('sysLoginSession_RefID', varSystemLoginSession::bigint,'sysDataAnnotation', NULL::varchar,'sysDataSetDateTimeTZ', NULL::timestamptz,'sysDataValidityStartDateTimeTZ', NULL::timestamptz,'sysDataValidityFinishDateTimeTZ', NULL::timestamptz,'sysPartitionRemovableRecordKey_RefID', NULL::bigint,'sysBranch_RefID', varInstitutionBranchID::bigint,'sysBaseCurrency_RefID',varBaseCurrencyID::bigint,'userRoleGroup_RefID', '252000000000015'::bigint, 'userRole_RefID', '95000000000022'::bigint)))::varchar;
B31: =IF(EXACT([1]DataLookUp!$B31, ""), "", [1]DataLookUp!$B31) -> 95000000000023 | C31: =IF(EXACT(B31, ""), "", [1]DataLookUp!$C31) -> Project Administrator Coordinator | D31: 252000000000015 | E31: =IF(EXACT(D31, ""), "", VLOOKUP(D31, [2]DataLookUp!$B$4:$C$32, 2, FALSE)) -> Department - Project | G31: =G30 + IF(EXACT(H31, ""), 0, 1) -> 253000000000023 | H31: =IF(AND(EXACT(B31, ""), EXACT(D31, "")), "", CONCATENATE("PERFORM ""SchSysConfig"".""Func_TblAppObject_UserRole_SET""(varSystemLoginSession, null::bigint, null::varchar, null::timestamptz, null::timestamptz, null::varchar, varInstitutionBranchID, varBaseCurrencyID, ", (IF(EXACT(B31, ""), "NULL", CONCATENATE("'", B31, "'"))),"::varchar);")) -> PERFORM "SchSysConfig"."Func_TblAppObject_UserRole_SET"(varSystemLoginSession, null::bigint, null::varchar, null::timestamptz, null::timestamptz, null::varchar, varInstitutionBranchID, varBaseCurrencyID, '95000000000023'::varchar); | J31: =IF(EXACT($H31, ""), "", CONCATENATE( "varSQL := varSQL || (CASE WHEN (varSQL = '') THEN '' ELSE ', ' END) || (SELECT JSON_BUILD_OBJECT (", "'recordID', NULL::bigint,", "'entities', ", "JSON_BUILD_OBJECT (", "'sysLoginSession_RefID', varSystemLoginSession::bigint,", "'sysDataAnnotation', NULL::varchar,", "'sysDataSetDateTimeTZ', NULL::timestamptz,", "'sysDataValidityStartDateTimeTZ', NULL::timestamptz,", "'sysDataValidityFinishDateTimeTZ', NULL::timestamptz,", "'sysPartitionRemovableRecordKey_RefID', NULL::bigint,", "'sysBranch_RefID', varInstitutionBranchID::bigint,", "'sysBaseCurrency_RefID',varBaseCurrencyID::bigint,", "'userRoleGroup_RefID', ", IF(EXACT($D31, ""), "null", CONCATENATE("'", SUBSTITUTE($D31, "'", "\'"), "'")), "::bigint, ", "'userRole_RefID', ", IF(EXACT($B31, ""), "null", CONCATENATE("'", SUBSTITUTE($B31, "'", "\'"), "'")), "::bigint", ")))::varchar;")) -> varSQL := varSQL || (CASE WHEN (varSQL = '') THEN '' ELSE ', ' END) || (SELECT JSON_BUILD_OBJECT ('recordID', NULL::bigint,'entities', JSON_BUILD_OBJECT ('sysLoginSession_RefID', varSystemLoginSession::bigint,'sysDataAnnotation', NULL::varchar,'sysDataSetDateTimeTZ', NULL::timestamptz,'sysDataValidityStartDateTimeTZ', NULL::timestamptz,'sysDataValidityFinishDateTimeTZ', NULL::timestamptz,'sysPartitionRemovableRecordKey_RefID', NULL::bigint,'sysBranch_RefID', varInstitutionBranchID::bigint,'sysBaseCurrency_RefID',varBaseCurrencyID::bigint,'userRoleGroup_RefID', '252000000000015'::bigint, 'userRole_RefID', '95000000000023'::bigint)))::varchar;
B32: =IF(EXACT([1]DataLookUp!$B32, ""), "", [1]DataLookUp!$B32) -> 95000000000024 | C32: =IF(EXACT(B32, ""), "", [1]DataLookUp!$C32) -> Project Administrator Staff | D32: 252000000000015 | E32: =IF(EXACT(D32, ""), "", VLOOKUP(D32, [2]DataLookUp!$B$4:$C$32, 2, FALSE)) -> Department - Project | G32: =G31 + IF(EXACT(H32, ""), 0, 1) -> 253000000000024 | H32: =IF(AND(EXACT(B32, ""), EXACT(D32, "")), "", CONCATENATE("PERFORM ""SchSysConfig"".""Func_TblAppObject_UserRole_SET""(varSystemLoginSession, null::bigint, null::varchar, null::timestamptz, null::timestamptz, null::varchar, varInstitutionBranchID, varBaseCurrencyID, ", (IF(EXACT(B32, ""), "NULL", CONCATENATE("'", B32, "'"))),"::varchar);")) -> PERFORM "SchSysConfig"."Func_TblAppObject_UserRole_SET"(varSystemLoginSession, null::bigint, null::varchar, null::timestamptz, null::timestamptz, null::varchar, varInstitutionBranchID, varBaseCurrencyID, '95000000000024'::varchar); | J32: =IF(EXACT($H32, ""), "", CONCATENATE( "varSQL := varSQL || (CASE WHEN (varSQL = '') THEN '' ELSE ', ' END) || (SELECT JSON_BUILD_OBJECT (", "'recordID', NULL::bigint,", "'entities', ", "JSON_BUILD_OBJECT (", "'sysLoginSession_RefID', varSystemLoginSession::bigint,", "'sysDataAnnotation', NULL::varchar,", "'sysDataSetDateTimeTZ', NULL::timestamptz,", "'sysDataValidityStartDateTimeTZ', NULL::timestamptz,", "'sysDataValidityFinishDateTimeTZ', NULL::timestamptz,", "'sysPartitionRemovableRecordKey_RefID', NULL::bigint,", "'sysBranch_RefID', varInstitutionBranchID::bigint,", "'sysBaseCurrency_RefID',varBaseCurrencyID::bigint,", "'userRoleGroup_RefID', ", IF(EXACT($D32, ""), "null", CONCATENATE("'", SUBSTITUTE($D32, "'", "\'"), "'")), "::bigint, ", "'userRole_RefID', ", IF(EXACT($B32, ""), "null", CONCATENATE("'", SUBSTITUTE($B32, "'", "\'"), "'")), "::bigint", ")))::varchar;")) -> varSQL := varSQL || (CASE WHEN (varSQL = '') THEN '' ELSE ', ' END) || (SELECT JSON_BUILD_OBJECT ('recordID', NULL::bigint,'entities', JSON_BUILD_OBJECT ('sysLoginSession_RefID', varSystemLoginSession::bigint,'sysDataAnnotation', NULL::varchar,'sysDataSetDateTimeTZ', NULL::timestamptz,'sysDataValidityStartDateTimeTZ', NULL::timestamptz,'sysDataValidityFinishDateTimeTZ', NULL::timestamptz,'sysPartitionRemovableRecordKey_RefID', NULL::bigint,'sysBranch_RefID', varInstitutionBranchID::bigint,'sysBaseCurrency_RefID',varBaseCurrencyID::bigint,'userRoleGroup_RefID', '252000000000015'::bigint, 'userRole_RefID', '95000000000024'::bigint)))::varchar;
B33: =IF(EXACT([1]DataLookUp!$B33, ""), "", [1]DataLookUp!$B33) -> 95000000000025 | C33: =IF(EXACT(B33, ""), "", [1]DataLookUp!$C33) -> Project Worker Coordinator | D33: 252000000000015 | E33: =IF(EXACT(D33, ""), "", VLOOKUP(D33, [2]DataLookUp!$B$4:$C$32, 2, FALSE)) -> Department - Project | G33: =G32 + IF(EXACT(H33, ""), 0, 1) -> 253000000000025 | H33: =IF(AND(EXACT(B33, ""), EXACT(D33, "")), "", CONCATENATE("PERFORM ""SchSysConfig"".""Func_TblAppObject_UserRole_SET""(varSystemLoginSession, null::bigint, null::varchar, null::timestamptz, null::timestamptz, null::varchar, varInstitutionBranchID, varBaseCurrencyID, ", (IF(EXACT(B33, ""), "NULL", CONCATENATE("'", B33, "'"))),"::varchar);")) -> PERFORM "SchSysConfig"."Func_TblAppObject_UserRole_SET"(varSystemLoginSession, null::bigint, null::varchar, null::timestamptz, null::timestamptz, null::varchar, varInstitutionBranchID, varBaseCurrencyID, '95000000000025'::varchar); | J33: =IF(EXACT($H33, ""), "", CONCATENATE( "varSQL := varSQL || (CASE WHEN (varSQL = '') THEN '' ELSE ', ' END) || (SELECT JSON_BUILD_OBJECT (", "'recordID', NULL::bigint,", "'entities', ", "JSON_BUILD_OBJECT (", "'sysLoginSession_RefID', varSystemLoginSession::bigint,", "'sysDataAnnotation', NULL::varchar,", "'sysDataSetDateTimeTZ', NULL::timestamptz,", "'sysDataValidityStartDateTimeTZ', NULL::timestamptz,", "'sysDataValidityFinishDateTimeTZ', NULL::timestamptz,", "'sysPartitionRemovableRecordKey_RefID', NULL::bigint,", "'sysBranch_RefID', varInstitutionBranchID::bigint,", "'sysBaseCurrency_RefID',varBaseCurrencyID::bigint,", "'userRoleGroup_RefID', ", IF(EXACT($D33, ""), "null", CONCATENATE("'", SUBSTITUTE($D33, "'", "\'"), "'")), "::bigint, ", "'userRole_RefID', ", IF(EXACT($B33, ""), "null", CONCATENATE("'", SUBSTITUTE($B33, "'", "\'"), "'")), "::bigint", ")))::varchar;")) -> varSQL := varSQL || (CASE WHEN (varSQL = '') THEN '' ELSE ', ' END) || (SELECT JSON_BUILD_OBJECT ('recordID', NULL::bigint,'entities', JSON_BUILD_OBJECT ('sysLoginSession_RefID', varSystemLoginSession::bigint,'sysDataAnnotation', NULL::varchar,'sysDataSetDateTimeTZ', NULL::timestamptz,'sysDataValidityStartDateTimeTZ', NULL::timestamptz,'sysDataValidityFinishDateTimeTZ', NULL::timestamptz,'sysPartitionRemovableRecordKey_RefID', NULL::bigint,'sysBranch_RefID', varInstitutionBranchID::bigint,'sysBaseCurrency_RefID',varBaseCurrencyID::bigint,'userRoleGroup_RefID', '252000000000015'::bigint, 'userRole_RefID', '95000000000025'::bigint)))::varchar;
B34: =IF(EXACT([1]DataLookUp!$B34, ""), "", [1]DataLookUp!$B34) -> 95000000000026 | C34: =IF(EXACT(B34, ""), "", [1]DataLookUp!$C34) -> Project Worker Staff | D34: 252000000000015 | E34: =IF(EXACT(D34, ""), "", VLOOKUP(D34, [2]DataLookUp!$B$4:$C$32, 2, FALSE)) -> Department - Project | G34: =G33 + IF(EXACT(H34, ""), 0, 1) -> 253000000000026 | H34: =IF(AND(EXACT(B34, ""), EXACT(D34, "")), "", CONCATENATE("PERFORM ""SchSysConfig"".""Func_TblAppObject_UserRole_SET""(varSystemLoginSession, null::bigint, null::varchar, null::timestamptz, null::timestamptz, null::varchar, varInstitutionBranchID, varBaseCurrencyID, ", (IF(EXACT(B34, ""), "NULL", CONCATENATE("'", B34, "'"))),"::varchar);")) -> PERFORM "SchSysConfig"."Func_TblAppObject_UserRole_SET"(varSystemLoginSession, null::bigint, null::varchar, null::timestamptz, null::timestamptz, null::varchar, varInstitutionBranchID, varBaseCurrencyID, '95000000000026'::varchar); | J34: =IF(EXACT($H34, ""), "", CONCATENATE( "varSQL := varSQL || (CASE WHEN (varSQL = '') THEN '' ELSE ', ' END) || (SELECT JSON_BUILD_OBJECT (", "'recordID', NULL::bigint,", "'entities', ", "JSON_BUILD_OBJECT (", "'sysLoginSession_RefID', varSystemLoginSession::bigint,", "'sysDataAnnotation', NULL::varchar,", "'sysDataSetDateTimeTZ', NULL::timestamptz,", "'sysDataValidityStartDateTimeTZ', NULL::timestamptz,", "'sysDataValidityFinishDateTimeTZ', NULL::timestamptz,", "'sysPartitionRemovableRecordKey_RefID', NULL::bigint,", "'sysBranch_RefID', varInstitutionBranchID::bigint,", "'sysBaseCurrency_RefID',varBaseCurrencyID::bigint,", "'userRoleGroup_RefID', ", IF(EXACT($D34, ""), "null", CONCATENATE("'", SUBSTITUTE($D34, "'", "\'"), "'")), "::bigint, ", "'userRole_RefID', ", IF(EXACT($B34, ""), "null", CONCATENATE("'", SUBSTITUTE($B34, "'", "\'"), "'")), "::bigint", ")))::varchar;")) -> varSQL := varSQL || (CASE WHEN (varSQL = '') THEN '' ELSE ', ' END) || (SELECT JSON_BUILD_OBJECT ('recordID', NULL::bigint,'entities', JSON_BUILD_OBJECT ('sysLoginSession_RefID', varSystemLoginSession::bigint,'sysDataAnnotation', NULL::varchar,'sysDataSetDateTimeTZ', NULL::timestamptz,'sysDataValidityStartDateTimeTZ', NULL::timestamptz,'sysDataValidityFinishDateTimeTZ', NULL::timestamptz,'sysPartitionRemovableRecordKey_RefID', NULL::bigint,'sysBranch_RefID', varInstitutionBranchID::bigint,'sysBaseCurrency_RefID',varBaseCurrencyID::bigint,'userRoleGroup_RefID', '252000000000015'::bigint, 'userRole_RefID', '95000000000026'::bigint)))::varchar;
B35: =IF(EXACT([1]DataLookUp!$B35, ""), "", [1]DataLookUp!$B35) | C35: =IF(EXACT(B35, ""), "", [1]DataLookUp!$C35) | E35: =IF(EXACT(D35, ""), "", VLOOKUP(D35, [2]DataLookUp!$B$4:$C$32, 2, FALSE)) | G35: =G34 + IF(EXACT(H35, ""), 0, 1) -> 253000000000026 | H35: =IF(AND(EXACT(B35, ""), EXACT(D35, "")), "", CONCATENATE("PERFORM ""SchSysConfig"".""Func_TblAppObject_UserRole_SET""(varSystemLoginSession, null::bigint, null::varchar, null::timestamptz, null::timestamptz, null::varchar, varInstitutionBranchID, varBaseCurrencyID, ", (IF(EXACT(B35, ""), "NULL", CONCATENATE("'", B35, "'"))),"::varchar);")) | J35: =IF(EXACT($H35, ""), "", CONCATENATE( "varSQL := varSQL || (CASE WHEN (varSQL = '') THEN '' ELSE ', ' END) || (SELECT JSON_BUILD_OBJECT (", "'recordID', NULL::bigint,", "'entities', ", "JSON_BUILD_OBJECT (", "'sysLoginSession_RefID', varSystemLoginSession::bigint,", "'sysDataAnnotation', NULL::varchar,", "'sysDataSetDateTimeTZ', NULL::timestamptz,", "'sysDataValidityStartDateTimeTZ', NULL::timestamptz,", "'sysDataValidityFinishDateTimeTZ', NULL::timestamptz,", "'sysPartitionRemovableRecordKey_RefID', NULL::bigint,", "'sysBranch_RefID', varInstitutionBranchID::bigint,", "'sysBaseCurrency_RefID',varBaseCurrencyID::bigint,", "'userRoleGroup_RefID', ", IF(EXACT($D35, ""), "null", CONCATENATE("'", SUBSTITUTE($D35, "'", "\'"), "'")), "::bigint, ", "'userRole_RefID', ", IF(EXACT($B35, ""), "null", CONCATENATE("'", SUBSTITUTE($B35, "'", "\'"), "'")), "::bigint", ")))::varchar;"))
B36: =IF(EXACT([1]DataLookUp!$B36, ""), "", [1]DataLookUp!$B36) -> 95000000000027 | C36: =IF(EXACT(B36, ""), "", [1]DataLookUp!$C36) -> Finance Manager | D36: 252000000000009 | E36: =IF(EXACT(D36, ""), "", VLOOKUP(D36, [2]DataLookUp!$B$4:$C$32, 2, FALSE)) -> Department - Finance & Accounting | G36: =G35 + IF(EXACT(H36, ""), 0, 1) -> 253000000000027 | H36: =IF(AND(EXACT(B36, ""), EXACT(D36, "")), "", CONCATENATE("PERFORM ""SchSysConfig"".""Func_TblAppObject_UserRole_SET""(varSystemLoginSession, null::bigint, null::varchar, null::timestamptz, null::timestamptz, null::varchar, varInstitutionBranchID, varBaseCurrencyID, ", (IF(EXACT(B36, ""), "NULL", CONCATENATE("'", B36, "'"))),"::varchar);")) -> PERFORM "SchSysConfig"."Func_TblAppObject_UserRole_SET"(varSystemLoginSession, null::bigint, null::varchar, null::timestamptz, null::timestamptz, null::varchar, varInstitutionBranchID, varBaseCurrencyID, '95000000000027'::varchar); | J36: =IF(EXACT($H36, ""), "", CONCATENATE( "varSQL := varSQL || (CASE WHEN (varSQL = '') THEN '' ELSE ', ' END) || (SELECT JSON_BUILD_OBJECT (", "'recordID', NULL::bigint,", "'entities', ", "JSON_BUILD_OBJECT (", "'sysLoginSession_RefID', varSystemLoginSession::bigint,", "'sysDataAnnotation', NULL::varchar,", "'sysDataSetDateTimeTZ', NULL::timestamptz,", "'sysDataValidityStartDateTimeTZ', NULL::timestamptz,", "'sysDataValidityFinishDateTimeTZ', NULL::timestamptz,", "'sysPartitionRemovableRecordKey_RefID', NULL::bigint,", "'sysBranch_RefID', varInstitutionBranchID::bigint,", "'sysBaseCurrency_RefID',varBaseCurrencyID::bigint,", "'userRoleGroup_RefID', ", IF(EXACT($D36, ""), "null", CONCATENATE("'", SUBSTITUTE($D36, "'", "\'"), "'")), "::bigint, ", "'userRole_RefID', ", IF(EXACT($B36, ""), "null", CONCATENATE("'", SUBSTITUTE($B36, "'", "\'"), "'")), "::bigint", ")))::varchar;")) -> varSQL := varSQL || (CASE WHEN (varSQL = '') THEN '' ELSE ', ' END) || (SELECT JSON_BUILD_OBJECT ('recordID', NULL::bigint,'entities', JSON_BUILD_OBJECT ('sysLoginSession_RefID', varSystemLoginSession::bigint,'sysDataAnnotation', NULL::varchar,'sysDataSetDateTimeTZ', NULL::timestamptz,'sysDataValidityStartDateTimeTZ', NULL::timestamptz,'sysDataValidityFinishDateTimeTZ', NULL::timestamptz,'sysPartitionRemovableRecordKey_RefID', NULL::bigint,'sysBranch_RefID', varInstitutionBranchID::bigint,'sysBaseCurrency_RefID',varBaseCurrencyID::bigint,'userRoleGroup_RefID', '252000000000009'::bigint, 'userRole_RefID', '95000000000027'::bigint)))::varchar;
B37: =IF(EXACT([1]DataLookUp!$B37, ""), "", [1]DataLookUp!$B37) -> 95000000000028 | C37: =IF(EXACT(B37, ""), "", [1]DataLookUp!$C37) -> Cashier & Treasury Coordinator | D37: 252000000000009 | E37: =IF(EXACT(D37, ""), "", VLOOKUP(D37, [2]DataLookUp!$B$4:$C$32, 2, FALSE)) -> Department - Finance & Accounting | G37: =G36 + IF(EXACT(H37, ""), 0, 1) -> 253000000000028 | H37: =IF(AND(EXACT(B37, ""), EXACT(D37, "")), "", CONCATENATE("PERFORM ""SchSysConfig"".""Func_TblAppObject_UserRole_SET""(varSystemLoginSession, null::bigint, null::varchar, null::timestamptz, null::timestamptz, null::varchar, varInstitutionBranchID, varBaseCurrencyID, ", (IF(EXACT(B37, ""), "NULL", CONCATENATE("'", B37, "'"))),"::varchar);")) -> PERFORM "SchSysConfig"."Func_TblAppObject_UserRole_SET"(varSystemLoginSession, null::bigint, null::varchar, null::timestamptz, null::timestamptz, null::varchar, varInstitutionBranchID, varBaseCurrencyID, '95000000000028'::varchar); | J37: =IF(EXACT($H37, ""), "", CONCATENATE( "varSQL := varSQL || (CASE WHEN (varSQL = '') THEN '' ELSE ', ' END) || (SELECT JSON_BUILD_OBJECT (", "'recordID', NULL::bigint,", "'entities', ", "JSON_BUILD_OBJECT (", "'sysLoginSession_RefID', varSystemLoginSession::bigint,", "'sysDataAnnotation', NULL::varchar,", "'sysDataSetDateTimeTZ', NULL::timestamptz,", "'sysDataValidityStartDateTimeTZ', NULL::timestamptz,", "'sysDataValidityFinishDateTimeTZ', NULL::timestamptz,", "'sysPartitionRemovableRecordKey_RefID', NULL::bigint,", "'sysBranch_RefID', varInstitutionBranchID::bigint,", "'sysBaseCurrency_RefID',varBaseCurrencyID::bigint,", "'userRoleGroup_RefID', ", IF(EXACT($D37, ""), "null", CONCATENATE("'", SUBSTITUTE($D37, "'", "\'"), "'")), "::bigint, ", "'userRole_RefID', ", IF(EXACT($B37, ""), "null", CONCATENATE("'", SUBSTITUTE($B37, "'", "\'"), "'")), "::bigint", ")))::varchar;")) -> varSQL := varSQL || (CASE WHEN (varSQL = '') THEN '' ELSE ', ' END) || (SELECT JSON_BUILD_OBJECT ('recordID', NULL::bigint,'entities', JSON_BUILD_OBJECT ('sysLoginSession_RefID', varSystemLoginSession::bigint,'sysDataAnnotation', NULL::varchar,'sysDataSetDateTimeTZ', NULL::timestamptz,'sysDataValidityStartDateTimeTZ', NULL::timestamptz,'sysDataValidityFinishDateTimeTZ', NULL::timestamptz,'sysPartitionRemovableRecordKey_RefID', NULL::bigint,'sysBranch_RefID', varInstitutionBranchID::bigint,'sysBaseCurrency_RefID',varBaseCurrencyID::bigint,'userRoleGroup_RefID', '252000000000009'::bigint, 'userRole_RefID', '95000000000028'::bigint)))::varchar;
B38: =IF(EXACT([1]DataLookUp!$B38, ""), "", [1]DataLookUp!$B38) -> 95000000000029 | C38: =IF(EXACT(B38, ""), "", [1]DataLookUp!$C38) -> Cashier & Treasury Staff | D38: 252000000000009 | E38: =IF(EXACT(D38, ""), "", VLOOKUP(D38, [2]DataLookUp!$B$4:$C$32, 2, FALSE)) -> Department - Finance & Accounting | G38: =G37 + IF(EXACT(H38, ""), 0, 1) -> 253000000000029 | H38: =IF(AND(EXACT(B38, ""), EXACT(D38, "")), "", CONCATENATE("PERFORM ""SchSysConfig"".""Func_TblAppObject_UserRole_SET""(varSystemLoginSession, null::bigint, null::varchar, null::timestamptz, null::timestamptz, null::varchar, varInstitutionBranchID, varBaseCurrencyID, ", (IF(EXACT(B38, ""), "NULL", CONCATENATE("'", B38, "'"))),"::varchar);")) -> PERFORM "SchSysConfig"."Func_TblAppObject_UserRole_SET"(varSystemLoginSession, null::bigint, null::varchar, null::timestamptz, null::timestamptz, null::varchar, varInstitutionBranchID, varBaseCurrencyID, '95000000000029'::varchar); | J38: =IF(EXACT($H38, ""), "", CONCATENATE( "varSQL := varSQL || (CASE WHEN (varSQL = '') THEN '' ELSE ', ' END) || (SELECT JSON_BUILD_OBJECT (", "'recordID', NULL::bigint,", "'entities', ", "JSON_BUILD_OBJECT (", "'sysLoginSession_RefID', varSystemLoginSession::bigint,", "'sysDataAnnotation', NULL::varchar,", "'sysDataSetDateTimeTZ', NULL::timestamptz,", "'sysDataValidityStartDateTimeTZ', NULL::timestamptz,", "'sysDataValidityFinishDateTimeTZ', NULL::timestamptz,", "'sysPartitionRemovableRecordKey_RefID', NULL::bigint,", "'sysBranch_RefID', varInstitutionBranchID::bigint,", "'sysBaseCurrency_RefID',varBaseCurrencyID::bigint,", "'userRoleGroup_RefID', ", IF(EXACT($D38, ""), "null", CONCATENATE("'", SUBSTITUTE($D38, "'", "\'"), "'")), "::bigint, ", "'userRole_RefID', ", IF(EXACT($B38, ""), "null", CONCATENATE("'", SUBSTITUTE($B38, "'", "\'"), "'")), "::bigint", ")))::varchar;")) -> varSQL := varSQL || (CASE WHEN (varSQL = '') THEN '' ELSE ', ' END) || (SELECT JSON_BUILD_OBJECT ('recordID', NULL::bigint,'entities', JSON_BUILD_OBJECT ('sysLoginSession_RefID', varSystemLoginSession::bigint,'sysDataAnnotation', NULL::varchar,'sysDataSetDateTimeTZ', NULL::timestamptz,'sysDataValidityStartDateTimeTZ', NULL::timestamptz,'sysDataValidityFinishDateTimeTZ', NULL::timestamptz,'sysPartitionRemovableRecordKey_RefID', NULL::bigint,'sysBranch_RefID', varInstitutionBranchID::bigint,'sysBaseCurrency_RefID',varBaseCurrencyID::bigint,'userRoleGroup_RefID', '252000000000009'::bigint, 'userRole_RefID', '95000000000029'::bigint)))::varchar;
B39: =IF(EXACT([1]DataLookUp!$B39, ""), "", [1]DataLookUp!$B39) -> 95000000000030 | C39: =IF(EXACT(B39, ""), "", [1]DataLookUp!$C39) -> Cost Controller Coordinator | D39: 252000000000009 | E39: =IF(EXACT(D39, ""), "", VLOOKUP(D39, [2]DataLookUp!$B$4:$C$32, 2, FALSE)) -> Department - Finance & Accounting | G39: =G38 + IF(EXACT(H39, ""), 0, 1) -> 253000000000030 | H39: =IF(AND(EXACT(B39, ""), EXACT(D39, "")), "", CONCATENATE("PERFORM ""SchSysConfig"".""Func_TblAppObject_UserRole_SET""(varSystemLoginSession, null::bigint, null::varchar, null::timestamptz, null::timestamptz, null::varchar, varInstitutionBranchID, varBaseCurrencyID, ", (IF(EXACT(B39, ""), "NULL", CONCATENATE("'", B39, "'"))),"::varchar);")) -> PERFORM "SchSysConfig"."Func_TblAppObject_UserRole_SET"(varSystemLoginSession, null::bigint, null::varchar, null::timestamptz, null::timestamptz, null::varchar, varInstitutionBranchID, varBaseCurrencyID, '95000000000030'::varchar); | J39: =IF(EXACT($H39, ""), "", CONCATENATE( "varSQL := varSQL || (CASE WHEN (varSQL = '') THEN '' ELSE ', ' END) || (SELECT JSON_BUILD_OBJECT (", "'recordID', NULL::bigint,", "'entities', ", "JSON_BUILD_OBJECT (", "'sysLoginSession_RefID', varSystemLoginSession::bigint,", "'sysDataAnnotation', NULL::varchar,", "'sysDataSetDateTimeTZ', NULL::timestamptz,", "'sysDataValidityStartDateTimeTZ', NULL::timestamptz,", "'sysDataValidityFinishDateTimeTZ', NULL::timestamptz,", "'sysPartitionRemovableRecordKey_RefID', NULL::bigint,", "'sysBranch_RefID', varInstitutionBranchID::bigint,", "'sysBaseCurrency_RefID',varBaseCurrencyID::bigint,", "'userRoleGroup_RefID', ", IF(EXACT($D39, ""), "null", CONCATENATE("'", SUBSTITUTE($D39, "'", "\'"), "'")), "::bigint, ", "'userRole_RefID', ", IF(EXACT($B39, ""), "null", CONCATENATE("'", SUBSTITUTE($B39, "'", "\'"), "'")), "::bigint", ")))::varchar;")) -> varSQL := varSQL || (CASE WHEN (varSQL = '') THEN '' ELSE ', ' END) || (SELECT JSON_BUILD_OBJECT ('recordID', NULL::bigint,'entities', JSON_BUILD_OBJECT ('sysLoginSession_RefID', varSystemLoginSession::bigint,'sysDataAnnotation', NULL::varchar,'sysDataSetDateTimeTZ', NULL::timestamptz,'sysDataValidityStartDateTimeTZ', NULL::timestamptz,'sysDataValidityFinishDateTimeTZ', NULL::timestamptz,'sysPartitionRemovableRecordKey_RefID', NULL::bigint,'sysBranch_RefID', varInstitutionBranchID::bigint,'sysBaseCurrency_RefID',varBaseCurrencyID::bigint,'userRoleGroup_RefID', '252000000000009'::bigint, 'userRole_RefID', '95000000000030'::bigint)))::varchar;
B40: =IF(EXACT([1]DataLookUp!$B40, ""), "", [1]DataLookUp!$B40) -> 95000000000031 | C40: =IF(EXACT(B40, ""), "", [1]DataLookUp!$C40) -> Cost Controller Staff | D40: 252000000000009 | E40: =IF(EXACT(D40, ""), "", VLOOKUP(D40, [2]DataLookUp!$B$4:$C$32, 2, FALSE)) -> Department - Finance & Accounting | G40: =G39 + IF(EXACT(H40, ""), 0, 1) -> 253000000000031 | H40: =IF(AND(EXACT(B40, ""), EXACT(D40, "")), "", CONCATENATE("PERFORM ""SchSysConfig"".""Func_TblAppObject_UserRole_SET""(varSystemLoginSession, null::bigint, null::varchar, null::timestamptz, null::timestamptz, null::varchar, varInstitutionBranchID, varBaseCurrencyID, ", (IF(EXACT(B40, ""), "NULL", CONCATENATE("'", B40, "'"))),"::varchar);")) -> PERFORM "SchSysConfig"."Func_TblAppObject_UserRole_SET"(varSystemLoginSession, null::bigint, null::varchar, null::timestamptz, null::timestamptz, null::varchar, varInstitutionBranchID, varBaseCurrencyID, '95000000000031'::varchar); | J40: =IF(EXACT($H40, ""), "", CONCATENATE( "varSQL := varSQL || (CASE WHEN (varSQL = '') THEN '' ELSE ', ' END) || (SELECT JSON_BUILD_OBJECT (", "'recordID', NULL::bigint,", "'entities', ", "JSON_BUILD_OBJECT (", "'sysLoginSession_RefID', varSystemLoginSession::bigint,", "'sysDataAnnotation', NULL::varchar,", "'sysDataSetDateTimeTZ', NULL::timestamptz,", "'sysDataValidityStartDateTimeTZ', NULL::timestamptz,", "'sysDataValidityFinishDateTimeTZ', NULL::timestamptz,", "'sysPartitionRemovableRecordKey_RefID', NULL::bigint,", "'sysBranch_RefID', varInstitutionBranchID::bigint,", "'sysBaseCurrency_RefID',varBaseCurrencyID::bigint,", "'userRoleGroup_RefID', ", IF(EXACT($D40, ""), "null", CONCATENATE("'", SUBSTITUTE($D40, "'", "\'"), "'")), "::bigint, ", "'userRole_RefID', ", IF(EXACT($B40, ""), "null", CONCATENATE("'", SUBSTITUTE($B40, "'", "\'"), "'")), "::bigint", ")))::varchar;")) -> varSQL := varSQL || (CASE WHEN (varSQL = '') THEN '' ELSE ', ' END) || (SELECT JSON_BUILD_OBJECT ('recordID', NULL::bigint,'entities', JSON_BUILD_OBJECT ('sysLoginSession_RefID', varSystemLoginSession::bigint,'sysDataAnnotation', NULL::varchar,'sysDataSetDateTimeTZ', NULL::timestamptz,'sysDataValidityStartDateTimeTZ', NULL::timestamptz,'sysDataValidityFinishDateTimeTZ', NULL::timestamptz,'sysPartitionRemovableRecordKey_RefID', NULL::bigint,'sysBranch_RefID', varInstitutionBranchID::bigint,'sysBaseCurrency_RefID',varBaseCurrencyID::bigint,'userRoleGroup_RefID', '252000000000009'::bigint, 'userRole_RefID', '95000000000031'::bigint)))::varchar;
B41: =IF(EXACT([1]DataLookUp!$B41, ""), "", [1]DataLookUp!$B41) | C41: =IF(EXACT(B41, ""), "", [1]DataLookUp!$C41) | E41: =IF(EXACT(D41, ""), "", VLOOKUP(D41, [2]DataLookUp!$B$4:$C$32, 2, FALSE)) | G41: =G40 + IF(EXACT(H41, ""), 0, 1) -> 253000000000031 | H41: =IF(AND(EXACT(B41, ""), EXACT(D41, "")), "", CONCATENATE("PERFORM ""SchSysConfig"".""Func_TblAppObject_UserRole_SET""(varSystemLoginSession, null::bigint, null::varchar, null::timestamptz, null::timestamptz, null::varchar, varInstitutionBranchID, varBaseCurrencyID, ", (IF(EXACT(B41, ""), "NULL", CONCATENATE("'", B41, "'"))),"::varchar);")) | J41: =IF(EXACT($H41, ""), "", CONCATENATE( "varSQL := varSQL || (CASE WHEN (varSQL = '') THEN '' ELSE ', ' END) || (SELECT JSON_BUILD_OBJECT (", "'recordID', NULL::bigint,", "'entities', ", "JSON_BUILD_OBJECT (", "'sysLoginSession_RefID', varSystemLoginSession::bigint,", "'sysDataAnnotation', NULL::varchar,", "'sysDataSetDateTimeTZ', NULL::timestamptz,", "'sysDataValidityStartDateTimeTZ', NULL::timestamptz,", "'sysDataValidityFinishDateTimeTZ', NULL::timestamptz,", "'sysPartitionRemovableRecordKey_RefID', NULL::bigint,", "'sysBranch_RefID', varInstitutionBranchID::bigint,", "'sysBaseCurrency_RefID',varBaseCurrencyID::bigint,", "'userRoleGroup_RefID', ", IF(EXACT($D41, ""), "null", CONCATENATE("'", SUBSTITUTE($D41, "'", "\'"), "'")), "::bigint, ", "'userRole_RefID', ", IF(EXACT($B41, ""), "null", CONCATENATE("'", SUBSTITUTE($B41, "'", "\'"), "'")), "::bigint", ")))::varchar;"))
B42: =IF(EXACT([1]DataLookUp!$B42, ""), "", [1]DataLookUp!$B42) -> 95000000000032 | C42: =IF(EXACT(B42, ""), "", [1]DataLookUp!$C42) -> Accounting & Tax Manager | D42: 252000000000009 | E42: =IF(EXACT(D42, ""), "", VLOOKUP(D42, [2]DataLookUp!$B$4:$C$32, 2, FALSE)) -> Department - Finance & Accounting | G42: =G41 + IF(EXACT(H42, ""), 0, 1) -> 253000000000032 | H42: =IF(AND(EXACT(B42, ""), EXACT(D42, "")), "", CONCATENATE("PERFORM ""SchSysConfig"".""Func_TblAppObject_UserRole_SET""(varSystemLoginSession, null::bigint, null::varchar, null::timestamptz, null::timestamptz, null::varchar, varInstitutionBranchID, varBaseCurrencyID, ", (IF(EXACT(B42, ""), "NULL", CONCATENATE("'", B42, "'"))),"::varchar);")) -> PERFORM "SchSysConfig"."Func_TblAppObject_UserRole_SET"(varSystemLoginSession, null::bigint, null::varchar, null::timestamptz, null::timestamptz, null::varchar, varInstitutionBranchID, varBaseCurrencyID, '95000000000032'::varchar); | J42: =IF(EXACT($H42, ""), "", CONCATENATE( "varSQL := varSQL || (CASE WHEN (varSQL = '') THEN '' ELSE ', ' END) || (SELECT JSON_BUILD_OBJECT (", "'recordID', NULL::bigint,", "'entities', ", "JSON_BUILD_OBJECT (", "'sysLoginSession_RefID', varSystemLoginSession::bigint,", "'sysDataAnnotation', NULL::varchar,", "'sysDataSetDateTimeTZ', NULL::timestamptz,", "'sysDataValidityStartDateTimeTZ', NULL::timestamptz,", "'sysDataValidityFinishDateTimeTZ', NULL::timestamptz,", "'sysPartitionRemovableRecordKey_RefID', NULL::bigint,", "'sysBranch_RefID', varInstitutionBranchID::bigint,", "'sysBaseCurrency_RefID',varBaseCurrencyID::bigint,", "'userRoleGroup_RefID', ", IF(EXACT($D42, ""), "null", CONCATENATE("'", SUBSTITUTE($D42, "'", "\'"), "'")), "::bigint, ", "'userRole_RefID', ", IF(EXACT($B42, ""), "null", CONCATENATE("'", SUBSTITUTE($B42, "'", "\'"), "'")), "::bigint", ")))::varchar;")) -> varSQL := varSQL || (CASE WHEN (varSQL = '') THEN '' ELSE ', ' END) || (SELECT JSON_BUILD_OBJECT ('recordID', NULL::bigint,'entities', JSON_BUILD_OBJECT ('sysLoginSession_RefID', varSystemLoginSession::bigint,'sysDataAnnotation', NULL::varchar,'sysDataSetDateTimeTZ', NULL::timestamptz,'sysDataValidityStartDateTimeTZ', NULL::timestamptz,'sysDataValidityFinishDateTimeTZ', NULL::timestamptz,'sysPartitionRemovableRecordKey_RefID', NULL::bigint,'sysBranch_RefID', varInstitutionBranchID::bigint,'sysBaseCurrency_RefID',varBaseCurrencyID::bigint,'userRoleGroup_RefID', '252000000000009'::bigint, 'userRole_RefID', '95000000000032'::bigint)))::varchar;
B43: =IF(EXACT([1]DataLookUp!$B43, ""), "", [1]DataLookUp!$B43) -> 95000000000033 | C43: =IF(EXACT(B43, ""), "", [1]DataLookUp!$C43) -> Accounting & Tax Coordinator | D43: 252000000000009 | E43: =IF(EXACT(D43, ""), "", VLOOKUP(D43, [2]DataLookUp!$B$4:$C$32, 2, FALSE)) -> Department - Finance & Accounting | G43: =G42 + IF(EXACT(H43, ""), 0, 1) -> 253000000000033 | H43: =IF(AND(EXACT(B43, ""), EXACT(D43, "")), "", CONCATENATE("PERFORM ""SchSysConfig"".""Func_TblAppObject_UserRole_SET""(varSystemLoginSession, null::bigint, null::varchar, null::timestamptz, null::timestamptz, null::varchar, varInstitutionBranchID, varBaseCurrencyID, ", (IF(EXACT(B43, ""), "NULL", CONCATENATE("'", B43, "'"))),"::varchar);")) -> PERFORM "SchSysConfig"."Func_TblAppObject_UserRole_SET"(varSystemLoginSession, null::bigint, null::varchar, null::timestamptz, null::timestamptz, null::varchar, varInstitutionBranchID, varBaseCurrencyID, '95000000000033'::varchar); | J43: =IF(EXACT($H43, ""), "", CONCATENATE( "varSQL := varSQL || (CASE WHEN (varSQL = '') THEN '' ELSE ', ' END) || (SELECT JSON_BUILD_OBJECT (", "'recordID', NULL::bigint,", "'entities', ", "JSON_BUILD_OBJECT (", "'sysLoginSession_RefID', varSystemLoginSession::bigint,", "'sysDataAnnotation', NULL::varchar,", "'sysDataSetDateTimeTZ', NULL::timestamptz,", "'sysDataValidityStartDateTimeTZ', NULL::timestamptz,", "'sysDataValidityFinishDateTimeTZ', NULL::timestamptz,", "'sysPartitionRemovableRecordKey_RefID', NULL::bigint,", "'sysBranch_RefID', varInstitutionBranchID::bigint,", "'sysBaseCurrency_RefID',varBaseCurrencyID::bigint,", "'userRoleGroup_RefID', ", IF(EXACT($D43, ""), "null", CONCATENATE("'", SUBSTITUTE($D43, "'", "\'"), "'")), "::bigint, ", "'userRole_RefID', ", IF(EXACT($B43, ""), "null", CONCATENATE("'", SUBSTITUTE($B43, "'", "\'"), "'")), "::bigint", ")))::varchar;")) -> varSQL := varSQL || (CASE WHEN (varSQL = '') THEN '' ELSE ', ' END) || (SELECT JSON_BUILD_OBJECT ('recordID', NULL::bigint,'entities', JSON_BUILD_OBJECT ('sysLoginSession_RefID', varSystemLoginSession::bigint,'sysDataAnnotation', NULL::varchar,'sysDataSetDateTimeTZ', NULL::timestamptz,'sysDataValidityStartDateTimeTZ', NULL::timestamptz,'sysDataValidityFinishDateTimeTZ', NULL::timestamptz,'sysPartitionRemovableRecordKey_RefID', NULL::bigint,'sysBranch_RefID', varInstitutionBranchID::bigint,'sysBaseCurrency_RefID',varBaseCurrencyID::bigint,'userRoleGroup_RefID', '252000000000009'::bigint, 'userRole_RefID', '95000000000033'::bigint)))::varchar;
B44: =IF(EXACT([1]DataLookUp!$B44, ""), "", [1]DataLookUp!$B44) -> 95000000000034 | C44: =IF(EXACT(B44, ""), "", [1]DataLookUp!$C44) -> Accounting & Tax Staff | D44: 252000000000009 | E44: =IF(EXACT(D44, ""), "", VLOOKUP(D44, [2]DataLookUp!$B$4:$C$32, 2, FALSE)) -> Department - Finance & Accounting | G44: =G43 + IF(EXACT(H44, ""), 0, 1) -> 253000000000034 | H44: =IF(AND(EXACT(B44, ""), EXACT(D44, "")), "", CONCATENATE("PERFORM ""SchSysConfig"".""Func_TblAppObject_UserRole_SET""(varSystemLoginSession, null::bigint, null::varchar, null::timestamptz, null::timestamptz, null::varchar, varInstitutionBranchID, varBaseCurrencyID, ", (IF(EXACT(B44, ""), "NULL", CONCATENATE("'", B44, "'"))),"::varchar);")) -> PERFORM "SchSysConfig"."Func_TblAppObject_UserRole_SET"(varSystemLoginSession, null::bigint, null::varchar, null::timestamptz, null::timestamptz, null::varchar, varInstitutionBranchID, varBaseCurrencyID, '95000000000034'::varchar); | J44: =IF(EXACT($H44, ""), "", CONCATENATE( "varSQL := varSQL || (CASE WHEN (varSQL = '') THEN '' ELSE ', ' END) || (SELECT JSON_BUILD_OBJECT (", "'recordID', NULL::bigint,", "'entities', ", "JSON_BUILD_OBJECT (", "'sysLoginSession_RefID', varSystemLoginSession::bigint,", "'sysDataAnnotation', NULL::varchar,", "'sysDataSetDateTimeTZ', NULL::timestamptz,", "'sysDataValidityStartDateTimeTZ', NULL::timestamptz,", "'sysDataValidityFinishDateTimeTZ', NULL::timestamptz,", "'sysPartitionRemovableRecordKey_RefID', NULL::bigint,", "'sysBranch_RefID', varInstitutionBranchID::bigint,", "'sysBaseCurrency_RefID',varBaseCurrencyID::bigint,", "'userRoleGroup_RefID', ", IF(EXACT($D44, ""), "null", CONCATENATE("'", SUBSTITUTE($D44, "'", "\'"), "'")), "::bigint, ", "'userRole_RefID', ", IF(EXACT($B44, ""), "null", CONCATENATE("'", SUBSTITUTE($B44, "'", "\'"), "'")), "::bigint", ")))::varchar;")) -> varSQL := varSQL || (CASE WHEN (varSQL = '') THEN '' ELSE ', ' END) || (SELECT JSON_BUILD_OBJECT ('recordID', NULL::bigint,'entities', JSON_BUILD_OBJECT ('sysLoginSession_RefID', varSystemLoginSession::bigint,'sysDataAnnotation', NULL::varchar,'sysDataSetDateTimeTZ', NULL::timestamptz,'sysDataValidityStartDateTimeTZ', NULL::timestamptz,'sysDataValidityFinishDateTimeTZ', NULL::timestamptz,'sysPartitionRemovableRecordKey_RefID', NULL::bigint,'sysBranch_RefID', varInstitutionBranchID::bigint,'sysBaseCurrency_RefID',varBaseCurrencyID::bigint,'userRoleGroup_RefID', '252000000000009'::bigint, 'userRole_RefID', '95000000000034'::bigint)))::varchar;
B45: =IF(EXACT([1]DataLookUp!$B45, ""), "", [1]DataLookUp!$B45) | C45: =IF(EXACT(B45, ""), "", [1]DataLookUp!$C45) | E45: =IF(EXACT(D45, ""), "", VLOOKUP(D45, [2]DataLookUp!$B$4:$C$32, 2, FALSE)) | G45: =G44 + IF(EXACT(H45, ""), 0, 1) -> 253000000000034 | H45: =IF(AND(EXACT(B45, ""), EXACT(D45, "")), "", CONCATENATE("PERFORM ""SchSysConfig"".""Func_TblAppObject_UserRole_SET""(varSystemLoginSession, null::bigint, null::varchar, null::timestamptz, null::timestamptz, null::varchar, varInstitutionBranchID, varBaseCurrencyID, ", (IF(EXACT(B45, ""), "NULL", CONCATENATE("'", B45, "'"))),"::varchar);")) | J45: =IF(EXACT($H45, ""), "", CONCATENATE( "varSQL := varSQL || (CASE WHEN (varSQL = '') THEN '' ELSE ', ' END) || (SELECT JSON_BUILD_OBJECT (", "'recordID', NULL::bigint,", "'entities', ", "JSON_BUILD_OBJECT (", "'sysLoginSession_RefID', varSystemLoginSession::bigint,", "'sysDataAnnotation', NULL::varchar,", "'sysDataSetDateTimeTZ', NULL::timestamptz,", "'sysDataValidityStartDateTimeTZ', NULL::timestamptz,", "'sysDataValidityFinishDateTimeTZ', NULL::timestamptz,", "'sysPartitionRemovableRecordKey_RefID', NULL::bigint,", "'sysBranch_RefID', varInstitutionBranchID::bigint,", "'sysBaseCurrency_RefID',varBaseCurrencyID::bigint,", "'userRoleGroup_RefID', ", IF(EXACT($D45, ""), "null", CONCATENATE("'", SUBSTITUTE($D45, "'", "\'"), "'")), "::bigint, ", "'userRole_RefID', ", IF(EXACT($B45, ""), "null", CONCATENATE("'", SUBSTITUTE($B45, "'", "\'"), "'")), "::bigint", ")))::varchar;"))
B46: =IF(EXACT([1]DataLookUp!$B46, ""), "", [1]DataLookUp!$B46) -> 95000000000035 | C46: =IF(EXACT(B46, ""), "", [1]DataLookUp!$C46) -> IT System Manager | D46: 252000000000007 | E46: =IF(EXACT(D46, ""), "", VLOOKUP(D46, [2]DataLookUp!$B$4:$C$32, 2, FALSE)) -> Department - Information Technology | G46: =G45 + IF(EXACT(H46, ""), 0, 1) -> 253000000000035 | H46: =IF(AND(EXACT(B46, ""), EXACT(D46, "")), "", CONCATENATE("PERFORM ""SchSysConfig"".""Func_TblAppObject_UserRole_SET""(varSystemLoginSession, null::bigint, null::varchar, null::timestamptz, null::timestamptz, null::varchar, varInstitutionBranchID, varBaseCurrencyID, ", (IF(EXACT(B46, ""), "NULL", CONCATENATE("'", B46, "'"))),"::varchar);")) -> PERFORM "SchSysConfig"."Func_TblAppObject_UserRole_SET"(varSystemLoginSession, null::bigint, null::varchar, null::timestamptz, null::timestamptz, null::varchar, varInstitutionBranchID, varBaseCurrencyID, '95000000000035'::varchar); | J46: =IF(EXACT($H46, ""), "", CONCATENATE( "varSQL := varSQL || (CASE WHEN (varSQL = '') THEN '' ELSE ', ' END) || (SELECT JSON_BUILD_OBJECT (", "'recordID', NULL::bigint,", "'entities', ", "JSON_BUILD_OBJECT (", "'sysLoginSession_RefID', varSystemLoginSession::bigint,", "'sysDataAnnotation', NULL::varchar,", "'sysDataSetDateTimeTZ', NULL::timestamptz,", "'sysDataValidityStartDateTimeTZ', NULL::timestamptz,", "'sysDataValidityFinishDateTimeTZ', NULL::timestamptz,", "'sysPartitionRemovableRecordKey_RefID', NULL::bigint,", "'sysBranch_RefID', varInstitutionBranchID::bigint,", "'sysBaseCurrency_RefID',varBaseCurrencyID::bigint,", "'userRoleGroup_RefID', ", IF(EXACT($D46, ""), "null", CONCATENATE("'", SUBSTITUTE($D46, "'", "\'"), "'")), "::bigint, ", "'userRole_RefID', ", IF(EXACT($B46, ""), "null", CONCATENATE("'", SUBSTITUTE($B46, "'", "\'"), "'")), "::bigint", ")))::varchar;")) -> varSQL := varSQL || (CASE WHEN (varSQL = '') THEN '' ELSE ', ' END) || (SELECT JSON_BUILD_OBJECT ('recordID', NULL::bigint,'entities', JSON_BUILD_OBJECT ('sysLoginSession_RefID', varSystemLoginSession::bigint,'sysDataAnnotation', NULL::varchar,'sysDataSetDateTimeTZ', NULL::timestamptz,'sysDataValidityStartDateTimeTZ', NULL::timestamptz,'sysDataValidityFinishDateTimeTZ', NULL::timestamptz,'sysPartitionRemovableRecordKey_RefID', NULL::bigint,'sysBranch_RefID', varInstitutionBranchID::bigint,'sysBaseCurrency_RefID',varBaseCurrencyID::bigint,'userRoleGroup_RefID', '252000000000007'::bigint, 'userRole_RefID', '95000000000035'::bigint)))::varchar;
B47: =IF(EXACT([1]DataLookUp!$B47, ""), "", [1]DataLookUp!$B47) -> 95000000000036 | C47: =IF(EXACT(B47, ""), "", [1]DataLookUp!$C47) -> IT System Engineer Coordinator | D47: 252000000000007 | E47: =IF(EXACT(D47, ""), "", VLOOKUP(D47, [2]DataLookUp!$B$4:$C$32, 2, FALSE)) -> Department - Information Technology | G47: =G46 + IF(EXACT(H47, ""), 0, 1) -> 253000000000036 | H47: =IF(AND(EXACT(B47, ""), EXACT(D47, "")), "", CONCATENATE("PERFORM ""SchSysConfig"".""Func_TblAppObject_UserRole_SET""(varSystemLoginSession, null::bigint, null::varchar, null::timestamptz, null::timestamptz, null::varchar, varInstitutionBranchID, varBaseCurrencyID, ", (IF(EXACT(B47, ""), "NULL", CONCATENATE("'", B47, "'"))),"::varchar);")) -> PERFORM "SchSysConfig"."Func_TblAppObject_UserRole_SET"(varSystemLoginSession, null::bigint, null::varchar, null::timestamptz, null::timestamptz, null::varchar, varInstitutionBranchID, varBaseCurrencyID, '95000000000036'::varchar); | J47: =IF(EXACT($H47, ""), "", CONCATENATE( "varSQL := varSQL || (CASE WHEN (varSQL = '') THEN '' ELSE ', ' END) || (SELECT JSON_BUILD_OBJECT (", "'recordID', NULL::bigint,", "'entities', ", "JSON_BUILD_OBJECT (", "'sysLoginSession_RefID', varSystemLoginSession::bigint,", "'sysDataAnnotation', NULL::varchar,", "'sysDataSetDateTimeTZ', NULL::timestamptz,", "'sysDataValidityStartDateTimeTZ', NULL::timestamptz,", "'sysDataValidityFinishDateTimeTZ', NULL::timestamptz,", "'sysPartitionRemovableRecordKey_RefID', NULL::bigint,", "'sysBranch_RefID', varInstitutionBranchID::bigint,", "'sysBaseCurrency_RefID',varBaseCurrencyID::bigint,", "'userRoleGroup_RefID', ", IF(EXACT($D47, ""), "null", CONCATENATE("'", SUBSTITUTE($D47, "'", "\'"), "'")), "::bigint, ", "'userRole_RefID', ", IF(EXACT($B47, ""), "null", CONCATENATE("'", SUBSTITUTE($B47, "'", "\'"), "'")), "::bigint", ")))::varchar;")) -> varSQL := varSQL || (CASE WHEN (varSQL = '') THEN '' ELSE ', ' END) || (SELECT JSON_BUILD_OBJECT ('recordID', NULL::bigint,'entities', JSON_BUILD_OBJECT ('sysLoginSession_RefID', varSystemLoginSession::bigint,'sysDataAnnotation', NULL::varchar,'sysDataSetDateTimeTZ', NULL::timestamptz,'sysDataValidityStartDateTimeTZ', NULL::timestamptz,'sysDataValidityFinishDateTimeTZ', NULL::timestamptz,'sysPartitionRemovableRecordKey_RefID', NULL::bigint,'sysBranch_RefID', varInstitutionBranchID::bigint,'sysBaseCurrency_RefID',varBaseCurrencyID::bigint,'userRoleGroup_RefID', '252000000000007'::bigint, 'userRole_RefID', '95000000000036'::bigint)))::varchar;
B48: =IF(EXACT([1]DataLookUp!$B48, ""), "", [1]DataLookUp!$B48) -> 95000000000037 | C48: =IF(EXACT(B48, ""), "", [1]DataLookUp!$C48) -> IT System Engineer Staff | D48: 252000000000007 | E48: =IF(EXACT(D48, ""), "", VLOOKUP(D48, [2]DataLookUp!$B$4:$C$32, 2, FALSE)) -> Department - Information Technology | G48: =G47 + IF(EXACT(H48, ""), 0, 1) -> 253000000000037 | H48: =IF(AND(EXACT(B48, ""), EXACT(D48, "")), "", CONCATENATE("PERFORM ""SchSysConfig"".""Func_TblAppObject_UserRole_SET""(varSystemLoginSession, null::bigint, null::varchar, null::timestamptz, null::timestamptz, null::varchar, varInstitutionBranchID, varBaseCurrencyID, ", (IF(EXACT(B48, ""), "NULL", CONCATENATE("'", B48, "'"))),"::varchar);")) -> PERFORM "SchSysConfig"."Func_TblAppObject_UserRole_SET"(varSystemLoginSession, null::bigint, null::varchar, null::timestamptz, null::timestamptz, null::varchar, varInstitutionBranchID, varBaseCurrencyID, '95000000000037'::varchar); | J48: =IF(EXACT($H48, ""), "", CONCATENATE( "varSQL := varSQL || (CASE WHEN (varSQL = '') THEN '' ELSE ', ' END) || (SELECT JSON_BUILD_OBJECT (", "'recordID', NULL::bigint,", "'entities', ", "JSON_BUILD_OBJECT (", "'sysLoginSession_RefID', varSystemLoginSession::bigint,", "'sysDataAnnotation', NULL::varchar,", "'sysDataSetDateTimeTZ', NULL::timestamptz,", "'sysDataValidityStartDateTimeTZ', NULL::timestamptz,", "'sysDataValidityFinishDateTimeTZ', NULL::timestamptz,", "'sysPartitionRemovableRecordKey_RefID', NULL::bigint,", "'sysBranch_RefID', varInstitutionBranchID::bigint,", "'sysBaseCurrency_RefID',varBaseCurrencyID::bigint,", "'userRoleGroup_RefID', ", IF(EXACT($D48, ""), "null", CONCATENATE("'", SUBSTITUTE($D48, "'", "\'"), "'")), "::bigint, ", "'userRole_RefID', ", IF(EXACT($B48, ""), "null", CONCATENATE("'", SUBSTITUTE($B48, "'", "\'"), "'")), "::bigint", ")))::varchar;")) -> varSQL := varSQL || (CASE WHEN (varSQL = '') THEN '' ELSE ', ' END) || (SELECT JSON_BUILD_OBJECT ('recordID', NULL::bigint,'entities', JSON_BUILD_OBJECT ('sysLoginSession_RefID', varSystemLoginSession::bigint,'sysDataAnnotation', NULL::varchar,'sysDataSetDateTimeTZ', NULL::timestamptz,'sysDataValidityStartDateTimeTZ', NULL::timestamptz,'sysDataValidityFinishDateTimeTZ', NULL::timestamptz,'sysPartitionRemovableRecordKey_RefID', NULL::bigint,'sysBranch_RefID', varInstitutionBranchID::bigint,'sysBaseCurrency_RefID',varBaseCurrencyID::bigint,'userRoleGroup_RefID', '252000000000007'::bigint, 'userRole_RefID', '95000000000037'::bigint)))::varchar;
B49: =IF(EXACT([1]DataLookUp!$B49, ""), "", [1]DataLookUp!$B49) -> 95000000000038 | C49: =IF(EXACT(B49, ""), "", [1]DataLookUp!$C49) -> IT Software Engineer Coordinator | D49: 252000000000007 | E49: =IF(EXACT(D49, ""), "", VLOOKUP(D49, [2]DataLookUp!$B$4:$C$32, 2, FALSE)) -> Department - Information Technology | G49: =G48 + IF(EXACT(H49, ""), 0, 1) -> 253000000000038 | H49: =IF(AND(EXACT(B49, ""), EXACT(D49, "")), "", CONCATENATE("PERFORM ""SchSysConfig"".""Func_TblAppObject_UserRole_SET""(varSystemLoginSession, null::bigint, null::varchar, null::timestamptz, null::timestamptz, null::varchar, varInstitutionBranchID, varBaseCurrencyID, ", (IF(EXACT(B49, ""), "NULL", CONCATENATE("'", B49, "'"))),"::varchar);")) -> PERFORM "SchSysConfig"."Func_TblAppObject_UserRole_SET"(varSystemLoginSession, null::bigint, null::varchar, null::timestamptz, null::timestamptz, null::varchar, varInstitutionBranchID, varBaseCurrencyID, '95000000000038'::varchar); | J49: =IF(EXACT($H49, ""), "", CONCATENATE( "varSQL := varSQL || (CASE WHEN (varSQL = '') THEN '' ELSE ', ' END) || (SELECT JSON_BUILD_OBJECT (", "'recordID', NULL::bigint,", "'entities', ", "JSON_BUILD_OBJECT (", "'sysLoginSession_RefID', varSystemLoginSession::bigint,", "'sysDataAnnotation', NULL::varchar,", "'sysDataSetDateTimeTZ', NULL::timestamptz,", "'sysDataValidityStartDateTimeTZ', NULL::timestamptz,", "'sysDataValidityFinishDateTimeTZ', NULL::timestamptz,", "'sysPartitionRemovableRecordKey_RefID', NULL::bigint,", "'sysBranch_RefID', varInstitutionBranchID::bigint,", "'sysBaseCurrency_RefID',varBaseCurrencyID::bigint,", "'userRoleGroup_RefID', ", IF(EXACT($D49, ""), "null", CONCATENATE("'", SUBSTITUTE($D49, "'", "\'"), "'")), "::bigint, ", "'userRole_RefID', ", IF(EXACT($B49, ""), "null", CONCATENATE("'", SUBSTITUTE($B49, "'", "\'"), "'")), "::bigint", ")))::varchar;")) -> varSQL := varSQL || (CASE WHEN (varSQL = '') THEN '' ELSE ', ' END) || (SELECT JSON_BUILD_OBJECT ('recordID', NULL::bigint,'entities', JSON_BUILD_OBJECT ('sysLoginSession_RefID', varSystemLoginSession::bigint,'sysDataAnnotation', NULL::varchar,'sysDataSetDateTimeTZ', NULL::timestamptz,'sysDataValidityStartDateTimeTZ', NULL::timestamptz,'sysDataValidityFinishDateTimeTZ', NULL::timestamptz,'sysPartitionRemovableRecordKey_RefID', NULL::bigint,'sysBranch_RefID', varInstitutionBranchID::bigint,'sysBaseCurrency_RefID',varBaseCurrencyID::bigint,'userRoleGroup_RefID', '252000000000007'::bigint, 'userRole_RefID', '95000000000038'::bigint)))::varchar;
B50: =IF(EXACT([1]DataLookUp!$B50, ""), "", [1]DataLookUp!$B50) -> 95000000000039 | C50: =IF(EXACT(B50, ""), "", [1]DataLookUp!$C50) -> IT Software Engineer Staff | D50: 252000000000007 | E50: =IF(EXACT(D50, ""), "", VLOOKUP(D50, [2]DataLookUp!$B$4:$C$32, 2, FALSE)) -> Department - Information Technology | G50: =G49 + IF(EXACT(H50, ""), 0, 1) -> 253000000000039 | H50: =IF(AND(EXACT(B50, ""), EXACT(D50, "")), "", CONCATENATE("PERFORM ""SchSysConfig"".""Func_TblAppObject_UserRole_SET""(varSystemLoginSession, null::bigint, null::varchar, null::timestamptz, null::timestamptz, null::varchar, varInstitutionBranchID, varBaseCurrencyID, ", (IF(EXACT(B50, ""), "NULL", CONCATENATE("'", B50, "'"))),"::varchar);")) -> PERFORM "SchSysConfig"."Func_TblAppObject_UserRole_SET"(varSystemLoginSession, null::bigint, null::varchar, null::timestamptz, null::timestamptz, null::varchar, varInstitutionBranchID, varBaseCurrencyID, '95000000000039'::varchar); | J50: =IF(EXACT($H50, ""), "", CONCATENATE( "varSQL := varSQL || (CASE WHEN (varSQL = '') THEN '' ELSE ', ' END) || (SELECT JSON_BUILD_OBJECT (", "'recordID', NULL::bigint,", "'entities', ", "JSON_BUILD_OBJECT (", "'sysLoginSession_RefID', varSystemLoginSession::bigint,", "'sysDataAnnotation', NULL::varchar,", "'sysDataSetDateTimeTZ', NULL::timestamptz,", "'sysDataValidityStartDateTimeTZ', NULL::timestamptz,", "'sysDataValidityFinishDateTimeTZ', NULL::timestamptz,", "'sysPartitionRemovableRecordKey_RefID', NULL::bigint,", "'sysBranch_RefID', varInstitutionBranchID::bigint,", "'sysBaseCurrency_RefID',varBaseCurrencyID::bigint,", "'userRoleGroup_RefID', ", IF(EXACT($D50, ""), "null", CONCATENATE("'", SUBSTITUTE($D50, "'", "\'"), "'")), "::bigint, ", "'userRole_RefID', ", IF(EXACT($B50, ""), "null", CONCATENATE("'", SUBSTITUTE($B50, "'", "\'"), "'")), "::bigint", ")))::varchar;")) -> varSQL := varSQL || (CASE WHEN (varSQL = '') THEN '' ELSE ', ' END) || (SELECT JSON_BUILD_OBJECT ('recordID', NULL::bigint,'entities', JSON_BUILD_OBJECT ('sysLoginSession_RefID', varSystemLoginSession::bigint,'sysDataAnnotation', NULL::varchar,'sysDataSetDateTimeTZ', NULL::timestamptz,'sysDataValidityStartDateTimeTZ', NULL::timestamptz,'sysDataValidityFinishDateTimeTZ', NULL::timestamptz,'sysPartitionRemovableRecordKey_RefID', NULL::bigint,'sysBranch_RefID', varInstitutionBranchID::bigint,'sysBaseCurrency_RefID',varBaseCurrencyID::bigint,'userRoleGroup_RefID', '252000000000007'::bigint, 'userRole_RefID', '95000000000039'::bigint)))::varchar;
B51: =IF(EXACT([1]DataLookUp!$B51, ""), "", [1]DataLookUp!$B51) | C51: =IF(EXACT(B51, ""), "", [1]DataLookUp!$C51) | E51: =IF(EXACT(D51, ""), "", VLOOKUP(D51, [2]DataLookUp!$B$4:$C$32, 2, FALSE)) | G51: =G50 + IF(EXACT(H51, ""), 0, 1) -> 253000000000039 | H51: =IF(AND(EXACT(B51, ""), EXACT(D51, "")), "", CONCATENATE("PERFORM ""SchSysConfig"".""Func_TblAppObject_UserRole_SET""(varSystemLoginSession, null::bigint, null::varchar, null::timestamptz, null::timestamptz, null::varchar, varInstitutionBranchID, varBaseCurrencyID, ", (IF(EXACT(B51, ""), "NULL", CONCATENATE("'", B51, "'"))),"::varchar);")) | J51: =IF(EXACT($H51, ""), "", CONCATENATE( "varSQL := varSQL || (CASE WHEN (varSQL = '') THEN '' ELSE ', ' END) || (SELECT JSON_BUILD_OBJECT (", "'recordID', NULL::bigint,", "'entities', ", "JSON_BUILD_OBJECT (", "'sysLoginSession_RefID', varSystemLoginSession::bigint,", "'sysDataAnnotation', NULL::varchar,", "'sysDataSetDateTimeTZ', NULL::timestamptz,", "'sysDataValidityStartDateTimeTZ', NULL::timestamptz,", "'sysDataValidityFinishDateTimeTZ', NULL::timestamptz,", "'sysPartitionRemovableRecordKey_RefID', NULL::bigint,", "'sysBranch_RefID', varInstitutionBranchID::bigint,", "'sysBaseCurrency_RefID',varBaseCurrencyID::bigint,", "'userRoleGroup_RefID', ", IF(EXACT($D51, ""), "null", CONCATENATE("'", SUBSTITUTE($D51, "'", "\'"), "'")), "::bigint, ", "'userRole_RefID', ", IF(EXACT($B51, ""), "null", CONCATENATE("'", SUBSTITUTE($B51, "'", "\'"), "'")), "::bigint", ")))::varchar;"))
B52: =IF(EXACT([1]DataLookUp!$B52, ""), "", [1]DataLookUp!$B52) -> 95000000000040 | C52: =IF(EXACT(B52, ""), "", [1]DataLookUp!$C52) -> Procurement Manager | D52: 252000000000016 | E52: =IF(EXACT(D52, ""), "", VLOOKUP(D52, [2]DataLookUp!$B$4:$C$32, 2, FALSE)) -> Department - Procurement | G52: =G51 + IF(EXACT(H52, ""), 0, 1) -> 253000000000040 | H52: =IF(AND(EXACT(B52, ""), EXACT(D52, "")), "", CONCATENATE("PERFORM ""SchSysConfig"".""Func_TblAppObject_UserRole_SET""(varSystemLoginSession, null::bigint, null::varchar, null::timestamptz, null::timestamptz, null::varchar, varInstitutionBranchID, varBaseCurrencyID, ", (IF(EXACT(B52, ""), "NULL", CONCATENATE("'", B52, "'"))),"::varchar);")) -> PERFORM "SchSysConfig"."Func_TblAppObject_UserRole_SET"(varSystemLoginSession, null::bigint, null::varchar, null::timestamptz, null::timestamptz, null::varchar, varInstitutionBranchID, varBaseCurrencyID, '95000000000040'::varchar); | J52: =IF(EXACT($H52, ""), "", CONCATENATE( "varSQL := varSQL || (CASE WHEN (varSQL = '') THEN '' ELSE ', ' END) || (SELECT JSON_BUILD_OBJECT (", "'recordID', NULL::bigint,", "'entities', ", "JSON_BUILD_OBJECT (", "'sysLoginSession_RefID', varSystemLoginSession::bigint,", "'sysDataAnnotation', NULL::varchar,", "'sysDataSetDateTimeTZ', NULL::timestamptz,", "'sysDataValidityStartDateTimeTZ', NULL::timestamptz,", "'sysDataValidityFinishDateTimeTZ', NULL::timestamptz,", "'sysPartitionRemovableRecordKey_RefID', NULL::bigint,", "'sysBranch_RefID', varInstitutionBranchID::bigint,", "'sysBaseCurrency_RefID',varBaseCurrencyID::bigint,", "'userRoleGroup_RefID', ", IF(EXACT($D52, ""), "null", CONCATENATE("'", SUBSTITUTE($D52, "'", "\'"), "'")), "::bigint, ", "'userRole_RefID', ", IF(EXACT($B52, ""), "null", CONCATENATE("'", SUBSTITUTE($B52, "'", "\'"), "'")), "::bigint", ")))::varchar;")) -> varSQL := varSQL || (CASE WHEN (varSQL = '') THEN '' ELSE ', ' END) || (SELECT JSON_BUILD_OBJECT ('recordID', NULL::bigint,'entities', JSON_BUILD_OBJECT ('sysLoginSession_RefID', varSystemLoginSession::bigint,'sysDataAnnotation', NULL::varchar,'sysDataSetDateTimeTZ', NULL::timestamptz,'sysDataValidityStartDateTimeTZ', NULL::timestamptz,'sysDataValidityFinishDateTimeTZ', NULL::timestamptz,'sysPartitionRemovableRecordKey_RefID', NULL::bigint,'sysBranch_RefID', varInstitutionBranchID::bigint,'sysBaseCurrency_RefID',varBaseCurrencyID::bigint,'userRoleGroup_RefID', '252000000000016'::bigint, 'userRole_RefID', '95000000000040'::bigint)))::varchar;
B53: =IF(EXACT([1]DataLookUp!$B53, ""), "", [1]DataLookUp!$B53) -> 95000000000041 | C53: =IF(EXACT(B53, ""), "", [1]DataLookUp!$C53) -> Procurement Coordinator | D53: 252000000000016 | E53: =IF(EXACT(D53, ""), "", VLOOKUP(D53, [2]DataLookUp!$B$4:$C$32, 2, FALSE)) -> Department - Procurement | G53: =G52 + IF(EXACT(H53, ""), 0, 1) -> 253000000000041 | H53: =IF(AND(EXACT(B53, ""), EXACT(D53, "")), "", CONCATENATE("PERFORM ""SchSysConfig"".""Func_TblAppObject_UserRole_SET""(varSystemLoginSession, null::bigint, null::varchar, null::timestamptz, null::timestamptz, null::varchar, varInstitutionBranchID, varBaseCurrencyID, ", (IF(EXACT(B53, ""), "NULL", CONCATENATE("'", B53, "'"))),"::varchar);")) -> PERFORM "SchSysConfig"."Func_TblAppObject_UserRole_SET"(varSystemLoginSession, null::bigint, null::varchar, null::timestamptz, null::timestamptz, null::varchar, varInstitutionBranchID, varBaseCurrencyID, '95000000000041'::varchar); | J53: =IF(EXACT($H53, ""), "", CONCATENATE( "varSQL := varSQL || (CASE WHEN (varSQL = '') THEN '' ELSE ', ' END) || (SELECT JSON_BUILD_OBJECT (", "'recordID', NULL::bigint,", "'entities', ", "JSON_BUILD_OBJECT (", "'sysLoginSession_RefID', varSystemLoginSession::bigint,", "'sysDataAnnotation', NULL::varchar,", "'sysDataSetDateTimeTZ', NULL::timestamptz,", "'sysDataValidityStartDateTimeTZ', NULL::timestamptz,", "'sysDataValidityFinishDateTimeTZ', NULL::timestamptz,", "'sysPartitionRemovableRecordKey_RefID', NULL::bigint,", "'sysBranch_RefID', varInstitutionBranchID::bigint,", "'sysBaseCurrency_RefID',varBaseCurrencyID::bigint,", "'userRoleGroup_RefID', ", IF(EXACT($D53, ""), "null", CONCATENATE("'", SUBSTITUTE($D53, "'", "\'"), "'")), "::bigint, ", "'userRole_RefID', ", IF(EXACT($B53, ""), "null", CONCATENATE("'", SUBSTITUTE($B53, "'", "\'"), "'")), "::bigint", ")))::varchar;")) -> varSQL := varSQL || (CASE WHEN (varSQL = '') THEN '' ELSE ', ' END) || (SELECT JSON_BUILD_OBJECT ('recordID', NULL::bigint,'entities', JSON_BUILD_OBJECT ('sysLoginSession_RefID', varSystemLoginSession::bigint,'sysDataAnnotation', NULL::varchar,'sysDataSetDateTimeTZ', NULL::timestamptz,'sysDataValidityStartDateTimeTZ', NULL::timestamptz,'sysDataValidityFinishDateTimeTZ', NULL::timestamptz,'sysPartitionRemovableRecordKey_RefID', NULL::bigint,'sysBranch_RefID', varInstitutionBranchID::bigint,'sysBaseCurrency_RefID',varBaseCurrencyID::bigint,'userRoleGroup_RefID', '252000000000016'::bigint, 'userRole_RefID', '95000000000041'::bigint)))::varchar;
B54: =IF(EXACT([1]DataLookUp!$B54, ""), "", [1]DataLookUp!$B54) -> 95000000000042 | C54: =IF(EXACT(B54, ""), "", [1]DataLookUp!$C54) -> Procurement Staff | D54: 252000000000016 | E54: =IF(EXACT(D54, ""), "", VLOOKUP(D54, [2]DataLookUp!$B$4:$C$32, 2, FALSE)) -> Department - Procurement | G54: =G53 + IF(EXACT(H54, ""), 0, 1) -> 253000000000042 | H54: =IF(AND(EXACT(B54, ""), EXACT(D54, "")), "", CONCATENATE("PERFORM ""SchSysConfig"".""Func_TblAppObject_UserRole_SET""(varSystemLoginSession, null::bigint, null::varchar, null::timestamptz, null::timestamptz, null::varchar, varInstitutionBranchID, varBaseCurrencyID, ", (IF(EXACT(B54, ""), "NULL", CONCATENATE("'", B54, "'"))),"::varchar);")) -> PERFORM "SchSysConfig"."Func_TblAppObject_UserRole_SET"(varSystemLoginSession, null::bigint, null::varchar, null::timestamptz, null::timestamptz, null::varchar, varInstitutionBranchID, varBaseCurrencyID, '95000000000042'::varchar); | J54: =IF(EXACT($H54, ""), "", CONCATENATE( "varSQL := varSQL || (CASE WHEN (varSQL = '') THEN '' ELSE ', ' END) || (SELECT JSON_BUILD_OBJECT (", "'recordID', NULL::bigint,", "'entities', ", "JSON_BUILD_OBJECT (", "'sysLoginSession_RefID', varSystemLoginSession::bigint,", "'sysDataAnnotation', NULL::varchar,", "'sysDataSetDateTimeTZ', NULL::timestamptz,", "'sysDataValidityStartDateTimeTZ', NULL::timestamptz,", "'sysDataValidityFinishDateTimeTZ', NULL::timestamptz,", "'sysPartitionRemovableRecordKey_RefID', NULL::bigint,", "'sysBranch_RefID', varInstitutionBranchID::bigint,", "'sysBaseCurrency_RefID',varBaseCurrencyID::bigint,", "'userRoleGroup_RefID', ", IF(EXACT($D54, ""), "null", CONCATENATE("'", SUBSTITUTE($D54, "'", "\'"), "'")), "::bigint, ", "'userRole_RefID', ", IF(EXACT($B54, ""), "null", CONCATENATE("'", SUBSTITUTE($B54, "'", "\'"), "'")), "::bigint", ")))::varchar;")) -> varSQL := varSQL || (CASE WHEN (varSQL = '') THEN '' ELSE ', ' END) || (SELECT JSON_BUILD_OBJECT ('recordID', NULL::bigint,'entities', JSON_BUILD_OBJECT ('sysLoginSession_RefID', varSystemLoginSession::bigint,'sysDataAnnotation', NULL::varchar,'sysDataSetDateTimeTZ', NULL::timestamptz,'sysDataValidityStartDateTimeTZ', NULL::timestamptz,'sysDataValidityFinishDateTimeTZ', NULL::timestamptz,'sysPartitionRemovableRecordKey_RefID', NULL::bigint,'sysBranch_RefID', varInstitutionBranchID::bigint,'sysBaseCurrency_RefID',varBaseCurrencyID::bigint,'userRoleGroup_RefID', '252000000000016'::bigint, 'userRole_RefID', '95000000000042'::bigint)))::varchar;
B55: =IF(EXACT([1]DataLookUp!$B55, ""), "", [1]DataLookUp!$B55) | C55: =IF(EXACT(B55, ""), "", [1]DataLookUp!$C55) | E55: =IF(EXACT(D55, ""), "", VLOOKUP(D55, [2]DataLookUp!$B$4:$C$32, 2, FALSE)) | G55: =G54 + IF(EXACT(H55, ""), 0, 1) -> 253000000000042 | H55: =IF(AND(EXACT(B55, ""), EXACT(D55, "")), "", CONCATENATE("PERFORM ""SchSysConfig"".""Func_TblAppObject_UserRole_SET""(varSystemLoginSession, null::bigint, null::varchar, null::timestamptz, null::timestamptz, null::varchar, varInstitutionBranchID, varBaseCurrencyID, ", (IF(EXACT(B55, ""), "NULL", CONCATENATE("'", B55, "'"))),"::varchar);")) | J55: =IF(EXACT($H55, ""), "", CONCATENATE( "varSQL := varSQL || (CASE WHEN (varSQL = '') THEN '' ELSE ', ' END) || (SELECT JSON_BUILD_OBJECT (", "'recordID', NULL::bigint,", "'entities', ", "JSON_BUILD_OBJECT (", "'sysLoginSession_RefID', varSystemLoginSession::bigint,", "'sysDataAnnotation', NULL::varchar,", "'sysDataSetDateTimeTZ', NULL::timestamptz,", "'sysDataValidityStartDateTimeTZ', NULL::timestamptz,", "'sysDataValidityFinishDateTimeTZ', NULL::timestamptz,", "'sysPartitionRemovableRecordKey_RefID', NULL::bigint,", "'sysBranch_RefID', varInstitutionBranchID::bigint,", "'sysBaseCurrency_RefID',varBaseCurrencyID::bigint,", "'userRoleGroup_RefID', ", IF(EXACT($D55, ""), "null", CONCATENATE("'", SUBSTITUTE($D55, "'", "\'"), "'")), "::bigint, ", "'userRole_RefID', ", IF(EXACT($B55, ""), "null", CONCATENATE("'", SUBSTITUTE($B55, "'", "\'"), "'")), "::bigint", ")))::varchar;"))
B56: =IF(EXACT([1]DataLookUp!$B56, ""), "", [1]DataLookUp!$B56) -> 95000000000043 | C56: =IF(EXACT(B56, ""), "", [1]DataLookUp!$C56) -> Sales Manager | D56: 252000000000008 | E56: =IF(EXACT(D56, ""), "", VLOOKUP(D56, [2]DataLookUp!$B$4:$C$32, 2, FALSE)) -> Department - Sales & Marketing | G56: =G55 + IF(EXACT(H56, ""), 0, 1) -> 253000000000043 | H56: =IF(AND(EXACT(B56, ""), EXACT(D56, "")), "", CONCATENATE("PERFORM ""SchSysConfig"".""Func_TblAppObject_UserRole_SET""(varSystemLoginSession, null::bigint, null::varchar, null::timestamptz, null::timestamptz, null::varchar, varInstitutionBranchID, varBaseCurrencyID, ", (IF(EXACT(B56, ""), "NULL", CONCATENATE("'", B56, "'"))),"::varchar);")) -> PERFORM "SchSysConfig"."Func_TblAppObject_UserRole_SET"(varSystemLoginSession, null::bigint, null::varchar, null::timestamptz, null::timestamptz, null::varchar, varInstitutionBranchID, varBaseCurrencyID, '95000000000043'::varchar); | J56: =IF(EXACT($H56, ""), "", CONCATENATE( "varSQL := varSQL || (CASE WHEN (varSQL = '') THEN '' ELSE ', ' END) || (SELECT JSON_BUILD_OBJECT (", "'recordID', NULL::bigint,", "'entities', ", "JSON_BUILD_OBJECT (", "'sysLoginSession_RefID', varSystemLoginSession::bigint,", "'sysDataAnnotation', NULL::varchar,", "'sysDataSetDateTimeTZ', NULL::timestamptz,", "'sysDataValidityStartDateTimeTZ', NULL::timestamptz,", "'sysDataValidityFinishDateTimeTZ', NULL::timestamptz,", "'sysPartitionRemovableRecordKey_RefID', NULL::bigint,", "'sysBranch_RefID', varInstitutionBranchID::bigint,", "'sysBaseCurrency_RefID',varBaseCurrencyID::bigint,", "'userRoleGroup_RefID', ", IF(EXACT($D56, ""), "null", CONCATENATE("'", SUBSTITUTE($D56, "'", "\'"), "'")), "::bigint, ", "'userRole_RefID', ", IF(EXACT($B56, ""), "null", CONCATENATE("'", SUBSTITUTE($B56, "'", "\'"), "'")), "::bigint", ")))::varchar;")) -> varSQL := varSQL || (CASE WHEN (varSQL = '') THEN '' ELSE ', ' END) || (SELECT JSON_BUILD_OBJECT ('recordID', NULL::bigint,'entities', JSON_BUILD_OBJECT ('sysLoginSession_RefID', varSystemLoginSession::bigint,'sysDataAnnotation', NULL::varchar,'sysDataSetDateTimeTZ', NULL::timestamptz,'sysDataValidityStartDateTimeTZ', NULL::timestamptz,'sysDataValidityFinishDateTimeTZ', NULL::timestamptz,'sysPartitionRemovableRecordKey_RefID', NULL::bigint,'sysBranch_RefID', varInstitutionBranchID::bigint,'sysBaseCurrency_RefID',varBaseCurrencyID::bigint,'userRoleGroup_RefID', '252000000000008'::bigint, 'userRole_RefID', '95000000000043'::bigint)))::varchar;
B57: =IF(EXACT([1]DataLookUp!$B57, ""), "", [1]DataLookUp!$B57) -> 95000000000044 | C57: =IF(EXACT(B57, ""), "", [1]DataLookUp!$C57) -> Sales Coordinator | D57: 252000000000008 | E57: =IF(EXACT(D57, ""), "", VLOOKUP(D57, [2]DataLookUp!$B$4:$C$32, 2, FALSE)) -> Department - Sales & Marketing | G57: =G56 + IF(EXACT(H57, ""), 0, 1) -> 253000000000044 | H57: =IF(AND(EXACT(B57, ""), EXACT(D57, "")), "", CONCATENATE("PERFORM ""SchSysConfig"".""Func_TblAppObject_UserRole_SET""(varSystemLoginSession, null::bigint, null::varchar, null::timestamptz, null::timestamptz, null::varchar, varInstitutionBranchID, varBaseCurrencyID, ", (IF(EXACT(B57, ""), "NULL", CONCATENATE("'", B57, "'"))),"::varchar);")) -> PERFORM "SchSysConfig"."Func_TblAppObject_UserRole_SET"(varSystemLoginSession, null::bigint, null::varchar, null::timestamptz, null::timestamptz, null::varchar, varInstitutionBranchID, varBaseCurrencyID, '95000000000044'::varchar); | J57: =IF(EXACT($H57, ""), "", CONCATENATE( "varSQL := varSQL || (CASE WHEN (varSQL = '') THEN '' ELSE ', ' END) || (SELECT JSON_BUILD_OBJECT (", "'recordID', NULL::bigint,", "'entities', ", "JSON_BUILD_OBJECT (", "'sysLoginSession_RefID', varSystemLoginSession::bigint,", "'sysDataAnnotation', NULL::varchar,", "'sysDataSetDateTimeTZ', NULL::timestamptz,", "'sysDataValidityStartDateTimeTZ', NULL::timestamptz,", "'sysDataValidityFinishDateTimeTZ', NULL::timestamptz,", "'sysPartitionRemovableRecordKey_RefID', NULL::bigint,", "'sysBranch_RefID', varInstitutionBranchID::bigint,", "'sysBaseCurrency_RefID',varBaseCurrencyID::bigint,", "'userRoleGroup_RefID', ", IF(EXACT($D57, ""), "null", CONCATENATE("'", SUBSTITUTE($D57, "'", "\'"), "'")), "::bigint, ", "'userRole_RefID', ", IF(EXACT($B57, ""), "null", CONCATENATE("'", SUBSTITUTE($B57, "'", "\'"), "'")), "::bigint", ")))::varchar;")) -> varSQL := varSQL || (CASE WHEN (varSQL = '') THEN '' ELSE ', ' END) || (SELECT JSON_BUILD_OBJECT ('recordID', NULL::bigint,'entities', JSON_BUILD_OBJECT ('sysLoginSession_RefID', varSystemLoginSession::bigint,'sysDataAnnotation', NULL::varchar,'sysDataSetDateTimeTZ', NULL::timestamptz,'sysDataValidityStartDateTimeTZ', NULL::timestamptz,'sysDataValidityFinishDateTimeTZ', NULL::timestamptz,'sysPartitionRemovableRecordKey_RefID', NULL::bigint,'sysBranch_RefID', varInstitutionBranchID::bigint,'sysBaseCurrency_RefID',varBaseCurrencyID::bigint,'userRoleGroup_RefID', '252000000000008'::bigint, 'userRole_RefID', '95000000000044'::bigint)))::varchar;
B58: =IF(EXACT([1]DataLookUp!$B58, ""), "", [1]DataLookUp!$B58) -> 95000000000045 | C58: =IF(EXACT(B58, ""), "", [1]DataLookUp!$C58) -> Bid And Sales Administrator Staff | D58: 252000000000008 | E58: =IF(EXACT(D58, ""), "", VLOOKUP(D58, [2]DataLookUp!$B$4:$C$32, 2, FALSE)) -> Department - Sales & Marketing | G58: =G57 + IF(EXACT(H58, ""), 0, 1) -> 253000000000045 | H58: =IF(AND(EXACT(B58, ""), EXACT(D58, "")), "", CONCATENATE("PERFORM ""SchSysConfig"".""Func_TblAppObject_UserRole_SET""(varSystemLoginSession, null::bigint, null::varchar, null::timestamptz, null::timestamptz, null::varchar, varInstitutionBranchID, varBaseCurrencyID, ", (IF(EXACT(B58, ""), "NULL", CONCATENATE("'", B58, "'"))),"::varchar);")) -> PERFORM "SchSysConfig"."Func_TblAppObject_UserRole_SET"(varSystemLoginSession, null::bigint, null::varchar, null::timestamptz, null::timestamptz, null::varchar, varInstitutionBranchID, varBaseCurrencyID, '95000000000045'::varchar); | J58: =IF(EXACT($H58, ""), "", CONCATENATE( "varSQL := varSQL || (CASE WHEN (varSQL = '') THEN '' ELSE ', ' END) || (SELECT JSON_BUILD_OBJECT (", "'recordID', NULL::bigint,", "'entities', ", "JSON_BUILD_OBJECT (", "'sysLoginSession_RefID', varSystemLoginSession::bigint,", "'sysDataAnnotation', NULL::varchar,", "'sysDataSetDateTimeTZ', NULL::timestamptz,", "'sysDataValidityStartDateTimeTZ', NULL::timestamptz,", "'sysDataValidityFinishDateTimeTZ', NULL::timestamptz,", "'sysPartitionRemovableRecordKey_RefID', NULL::bigint,", "'sysBranch_RefID', varInstitutionBranchID::bigint,", "'sysBaseCurrency_RefID',varBaseCurrencyID::bigint,", "'userRoleGroup_RefID', ", IF(EXACT($D58, ""), "null", CONCATENATE("'", SUBSTITUTE($D58, "'", "\'"), "'")), "::bigint, ", "'userRole_RefID', ", IF(EXACT($B58, ""), "null", CONCATENATE("'", SUBSTITUTE($B58, "'", "\'"), "'")), "::bigint", ")))::varchar;")) -> varSQL := varSQL || (CASE WHEN (varSQL = '') THEN '' ELSE ', ' END) || (SELECT JSON_BUILD_OBJECT ('recordID', NULL::bigint,'entities', JSON_BUILD_OBJECT ('sysLoginSession_RefID', varSystemLoginSession::bigint,'sysDataAnnotation', NULL::varchar,'sysDataSetDateTimeTZ', NULL::timestamptz,'sysDataValidityStartDateTimeTZ', NULL::timestamptz,'sysDataValidityFinishDateTimeTZ', NULL::timestamptz,'sysPartitionRemovableRecordKey_RefID', NULL::bigint,'sysBranch_RefID', varInstitutionBranchID::bigint,'sysBaseCurrency_RefID',varBaseCurrencyID::bigint,'userRoleGroup_RefID', '252000000000008'::bigint, 'userRole_RefID', '95000000000045'::bigint)))::varchar;
B59: =IF(EXACT([1]DataLookUp!$B59, ""), "", [1]DataLookUp!$B59) -> 95000000000046 | C59: =IF(EXACT(B59, ""), "", [1]DataLookUp!$C59) -> Sales Estimator Coordinator | D59: 252000000000008 | E59: =IF(EXACT(D59, ""), "", VLOOKUP(D59, [2]DataLookUp!$B$4:$C$32, 2, FALSE)) -> Department - Sales & Marketing | G59: =G58 + IF(EXACT(H59, ""), 0, 1) -> 253000000000046 | H59: =IF(AND(EXACT(B59, ""), EXACT(D59, "")), "", CONCATENATE("PERFORM ""SchSysConfig"".""Func_TblAppObject_UserRole_SET""(varSystemLoginSession, null::bigint, null::varchar, null::timestamptz, null::timestamptz, null::varchar, varInstitutionBranchID, varBaseCurrencyID, ", (IF(EXACT(B59, ""), "NULL", CONCATENATE("'", B59, "'"))),"::varchar);")) -> PERFORM "SchSysConfig"."Func_TblAppObject_UserRole_SET"(varSystemLoginSession, null::bigint, null::varchar, null::timestamptz, null::timestamptz, null::varchar, varInstitutionBranchID, varBaseCurrencyID, '95000000000046'::varchar); | J59: =IF(EXACT($H59, ""), "", CONCATENATE( "varSQL := varSQL || (CASE WHEN (varSQL = '') THEN '' ELSE ', ' END) || (SELECT JSON_BUILD_OBJECT (", "'recordID', NULL::bigint,", "'entities', ", "JSON_BUILD_OBJECT (", "'sysLoginSession_RefID', varSystemLoginSession::bigint,", "'sysDataAnnotation', NULL::varchar,", "'sysDataSetDateTimeTZ', NULL::timestamptz,", "'sysDataValidityStartDateTimeTZ', NULL::timestamptz,", "'sysDataValidityFinishDateTimeTZ', NULL::timestamptz,", "'sysPartitionRemovableRecordKey_RefID', NULL::bigint,", "'sysBranch_RefID', varInstitutionBranchID::bigint,", "'sysBaseCurrency_RefID',varBaseCurrencyID::bigint,", "'userRoleGroup_RefID', ", IF(EXACT($D59, ""), "null", CONCATENATE("'", SUBSTITUTE($D59, "'", "\'"), "'")), "::bigint, ", "'userRole_RefID', ", IF(EXACT($B59, ""), "null", CONCATENATE("'", SUBSTITUTE($B59, "'", "\'"), "'")), "::bigint", ")))::varchar;")) -> varSQL := varSQL || (CASE WHEN (varSQL = '') THEN '' ELSE ', ' END) || (SELECT JSON_BUILD_OBJECT ('recordID', NULL::bigint,'entities', JSON_BUILD_OBJECT ('sysLoginSession_RefID', varSystemLoginSession::bigint,'sysDataAnnotation', NULL::varchar,'sysDataSetDateTimeTZ', NULL::timestamptz,'sysDataValidityStartDateTimeTZ', NULL::timestamptz,'sysDataValidityFinishDateTimeTZ', NULL::timestamptz,'sysPartitionRemovableRecordKey_RefID', NULL::bigint,'sysBranch_RefID', varInstitutionBranchID::bigint,'sysBaseCurrency_RefID',varBaseCurrencyID::bigint,'userRoleGroup_RefID', '252000000000008'::bigint, 'userRole_RefID', '95000000000046'::bigint)))::varchar;
B60: =IF(EXACT([1]DataLookUp!$B60, ""), "", [1]DataLookUp!$B60) -> 95000000000047 | C60: =IF(EXACT(B60, ""), "", [1]DataLookUp!$C60) -> Sales Estimator Staff | D60: 252000000000008 | E60: =IF(EXACT(D60, ""), "", VLOOKUP(D60, [2]DataLookUp!$B$4:$C$32, 2, FALSE)) -> Department - Sales & Marketing | G60: =G59 + IF(EXACT(H60, ""), 0, 1) -> 253000000000047 | H60: =IF(AND(EXACT(B60, ""), EXACT(D60, "")), "", CONCATENATE("PERFORM ""SchSysConfig"".""Func_TblAppObject_UserRole_SET""(varSystemLoginSession, null::bigint, null::varchar, null::timestamptz, null::timestamptz, null::varchar, varInstitutionBranchID, varBaseCurrencyID, ", (IF(EXACT(B60, ""), "NULL", CONCATENATE("'", B60, "'"))),"::varchar);")) -> PERFORM "SchSysConfig"."Func_TblAppObject_UserRole_SET"(varSystemLoginSession, null::bigint, null::varchar, null::timestamptz, null::timestamptz, null::varchar, varInstitutionBranchID, varBaseCurrencyID, '95000000000047'::varchar); | J60: =IF(EXACT($H60, ""), "", CONCATENATE( "varSQL := varSQL || (CASE WHEN (varSQL = '') THEN '' ELSE ', ' END) || (SELECT JSON_BUILD_OBJECT (", "'recordID', NULL::bigint,", "'entities', ", "JSON_BUILD_OBJECT (", "'sysLoginSession_RefID', varSystemLoginSession::bigint,", "'sysDataAnnotation', NULL::varchar,", "'sysDataSetDateTimeTZ', NULL::timestamptz,", "'sysDataValidityStartDateTimeTZ', NULL::timestamptz,", "'sysDataValidityFinishDateTimeTZ', NULL::timestamptz,", "'sysPartitionRemovableRecordKey_RefID', NULL::bigint,", "'sysBranch_RefID', varInstitutionBranchID::bigint,", "'sysBaseCurrency_RefID',varBaseCurrencyID::bigint,", "'userRoleGroup_RefID', ", IF(EXACT($D60, ""), "null", CONCATENATE("'", SUBSTITUTE($D60, "'", "\'"), "'")), "::bigint, ", "'userRole_RefID', ", IF(EXACT($B60, ""), "null", CONCATENATE("'", SUBSTITUTE($B60, "'", "\'"), "'")), "::bigint", ")))::varchar;")) -> varSQL := varSQL || (CASE WHEN (varSQL = '') THEN '' ELSE ', ' END) || (SELECT JSON_BUILD_OBJECT ('recordID', NULL::bigint,'entities', JSON_BUILD_OBJECT ('sysLoginSession_RefID', varSystemLoginSession::bigint,'sysDataAnnotation', NULL::varchar,'sysDataSetDateTimeTZ', NULL::timestamptz,'sysDataValidityStartDateTimeTZ', NULL::timestamptz,'sysDataValidityFinishDateTimeTZ', NULL::timestamptz,'sysPartitionRemovableRecordKey_RefID', NULL::bigint,'sysBranch_RefID', varInstitutionBranchID::bigint,'sysBaseCurrency_RefID',varBaseCurrencyID::bigint,'userRoleGroup_RefID', '252000000000008'::bigint, 'userRole_RefID', '95000000000047'::bigint)))::varchar;
B61: =IF(EXACT([1]DataLookUp!$B61, ""), "", [1]DataLookUp!$B61) | C61: =IF(EXACT(B61, ""), "", [1]DataLookUp!$C61) | E61: =IF(EXACT(D61, ""), "", VLOOKUP(D61, [2]DataLookUp!$B$4:$C$32, 2, FALSE)) | G61: =G60 + IF(EXACT(H61, ""), 0, 1) -> 253000000000047 | H61: =IF(AND(EXACT(B61, ""), EXACT(D61, "")), "", CONCATENATE("PERFORM ""SchSysConfig"".""Func_TblAppObject_UserRole_SET""(varSystemLoginSession, null::bigint, null::varchar, null::timestamptz, null::timestamptz, null::varchar, varInstitutionBranchID, varBaseCurrencyID, ", (IF(EXACT(B61, ""), "NULL", CONCATENATE("'", B61, "'"))),"::varchar);")) | J61: =IF(EXACT($H61, ""), "", CONCATENATE( "varSQL := varSQL || (CASE WHEN (varSQL = '') THEN '' ELSE ', ' END) || (SELECT JSON_BUILD_OBJECT (", "'recordID', NULL::bigint,", "'entities', ", "JSON_BUILD_OBJECT (", "'sysLoginSession_RefID', varSystemLoginSession::bigint,", "'sysDataAnnotation', NULL::varchar,", "'sysDataSetDateTimeTZ', NULL::timestamptz,", "'sysDataValidityStartDateTimeTZ', NULL::timestamptz,", "'sysDataValidityFinishDateTimeTZ', NULL::timestamptz,", "'sysPartitionRemovableRecordKey_RefID', NULL::bigint,", "'sysBranch_RefID', varInstitutionBranchID::bigint,", "'sysBaseCurrency_RefID',varBaseCurrencyID::bigint,", "'userRoleGroup_RefID', ", IF(EXACT($D61, ""), "null", CONCATENATE("'", SUBSTITUTE($D61, "'", "\'"), "'")), "::bigint, ", "'userRole_RefID', ", IF(EXACT($B61, ""), "null", CONCATENATE("'", SUBSTITUTE($B61, "'", "\'"), "'")), "::bigint", ")))::varchar;"))
B62: =IF(EXACT([1]DataLookUp!$B62, ""), "", [1]DataLookUp!$B62) -> 95000000000048 | C62: =IF(EXACT(B62, ""), "", [1]DataLookUp!$C62) -> Health Safety Environment Manager | D62: 252000000000011 | E62: =IF(EXACT(D62, ""), "", VLOOKUP(D62, [2]DataLookUp!$B$4:$C$32, 2, FALSE)) -> Department - Health Safety Environment | G62: =G61 + IF(EXACT(H62, ""), 0, 1) -> 253000000000048 | H62: =IF(AND(EXACT(B62, ""), EXACT(D62, "")), "", CONCATENATE("PERFORM ""SchSysConfig"".""Func_TblAppObject_UserRole_SET""(varSystemLoginSession, null::bigint, null::varchar, null::timestamptz, null::timestamptz, null::varchar, varInstitutionBranchID, varBaseCurrencyID, ", (IF(EXACT(B62, ""), "NULL", CONCATENATE("'", B62, "'"))),"::varchar);")) -> PERFORM "SchSysConfig"."Func_TblAppObject_UserRole_SET"(varSystemLoginSession, null::bigint, null::varchar, null::timestamptz, null::timestamptz, null::varchar, varInstitutionBranchID, varBaseCurrencyID, '95000000000048'::varchar); | J62: =IF(EXACT($H62, ""), "", CONCATENATE( "varSQL := varSQL || (CASE WHEN (varSQL = '') THEN '' ELSE ', ' END) || (SELECT JSON_BUILD_OBJECT (", "'recordID', NULL::bigint,", "'entities', ", "JSON_BUILD_OBJECT (", "'sysLoginSession_RefID', varSystemLoginSession::bigint,", "'sysDataAnnotation', NULL::varchar,", "'sysDataSetDateTimeTZ', NULL::timestamptz,", "'sysDataValidityStartDateTimeTZ', NULL::timestamptz,", "'sysDataValidityFinishDateTimeTZ', NULL::timestamptz,", "'sysPartitionRemovableRecordKey_RefID', NULL::bigint,", "'sysBranch_RefID', varInstitutionBranchID::bigint,", "'sysBaseCurrency_RefID',varBaseCurrencyID::bigint,", "'userRoleGroup_RefID', ", IF(EXACT($D62, ""), "null", CONCATENATE("'", SUBSTITUTE($D62, "'", "\'"), "'")), "::bigint, ", "'userRole_RefID', ", IF(EXACT($B62, ""), "null", CONCATENATE("'", SUBSTITUTE($B62, "'", "\'"), "'")), "::bigint", ")))::varchar;")) -> varSQL := varSQL || (CASE WHEN (varSQL = '') THEN '' ELSE ', ' END) || (SELECT JSON_BUILD_OBJECT ('recordID', NULL::bigint,'entities', JSON_BUILD_OBJECT ('sysLoginSession_RefID', varSystemLoginSession::bigint,'sysDataAnnotation', NULL::varchar,'sysDataSetDateTimeTZ', NULL::timestamptz,'sysDataValidityStartDateTimeTZ', NULL::timestamptz,'sysDataValidityFinishDateTimeTZ', NULL::timestamptz,'sysPartitionRemovableRecordKey_RefID', NULL::bigint,'sysBranch_RefID', varInstitutionBranchID::bigint,'sysBaseCurrency_RefID',varBaseCurrencyID::bigint,'userRoleGroup_RefID', '252000000000011'::bigint, 'userRole_RefID', '95000000000048'::bigint)))::varchar;
B63: =IF(EXACT([1]DataLookUp!$B63, ""), "", [1]DataLookUp!$B63) -> 95000000000049 | C63: =IF(EXACT(B63, ""), "", [1]DataLookUp!$C63) -> Health Safety Environment Coordinator | D63: 252000000000011 | E63: =IF(EXACT(D63, ""), "", VLOOKUP(D63, [2]DataLookUp!$B$4:$C$32, 2, FALSE)) -> Department - Health Safety Environment | G63: =G62 + IF(EXACT(H63, ""), 0, 1) -> 253000000000049 | H63: =IF(AND(EXACT(B63, ""), EXACT(D63, "")), "", CONCATENATE("PERFORM ""SchSysConfig"".""Func_TblAppObject_UserRole_SET""(varSystemLoginSession, null::bigint, null::varchar, null::timestamptz, null::timestamptz, null::varchar, varInstitutionBranchID, varBaseCurrencyID, ", (IF(EXACT(B63, ""), "NULL", CONCATENATE("'", B63, "'"))),"::varchar);")) -> PERFORM "SchSysConfig"."Func_TblAppObject_UserRole_SET"(varSystemLoginSession, null::bigint, null::varchar, null::timestamptz, null::timestamptz, null::varchar, varInstitutionBranchID, varBaseCurrencyID, '95000000000049'::varchar); | J63: =IF(EXACT($H63, ""), "", CONCATENATE( "varSQL := varSQL || (CASE WHEN (varSQL = '') THEN '' ELSE ', ' END) || (SELECT JSON_BUILD_OBJECT (", "'recordID', NULL::bigint,", "'entities', ", "JSON_BUILD_OBJECT (", "'sysLoginSession_RefID', varSystemLoginSession::bigint,", "'sysDataAnnotation', NULL::varchar,", "'sysDataSetDateTimeTZ', NULL::timestamptz,", "'sysDataValidityStartDateTimeTZ', NULL::timestamptz,", "'sysDataValidityFinishDateTimeTZ', NULL::timestamptz,", "'sysPartitionRemovableRecordKey_RefID', NULL::bigint,", "'sysBranch_RefID', varInstitutionBranchID::bigint,", "'sysBaseCurrency_RefID',varBaseCurrencyID::bigint,", "'userRoleGroup_RefID', ", IF(EXACT($D63, ""), "null", CONCATENATE("'", SUBSTITUTE($D63, "'", "\'"), "'")), "::bigint, ", "'userRole_RefID', ", IF(EXACT($B63, ""), "null", CONCATENATE("'", SUBSTITUTE($B63, "'", "\'"), "'")), "::bigint", ")))::varchar;")) -> varSQL := varSQL || (CASE WHEN (varSQL = '') THEN '' ELSE ', ' END) || (SELECT JSON_BUILD_OBJECT ('recordID', NULL::bigint,'entities', JSON_BUILD_OBJECT ('sysLoginSession_RefID', varSystemLoginSession::bigint,'sysDataAnnotation', NULL::varchar,'sysDataSetDateTimeTZ', NULL::timestamptz,'sysDataValidityStartDateTimeTZ', NULL::timestamptz,'sysDataValidityFinishDateTimeTZ', NULL::timestamptz,'sysPartitionRemovableRecordKey_RefID', NULL::bigint,'sysBranch_RefID', varInstitutionBranchID::bigint,'sysBaseCurrency_RefID',varBaseCurrencyID::bigint,'userRoleGroup_RefID', '252000000000011'::bigint, 'userRole_RefID', '95000000000049'::bigint)))::varchar;
B64: =IF(EXACT([1]DataLookUp!$B64, ""), "", [1]DataLookUp!$B64) -> 95000000000050 | C64: =IF(EXACT(B64, ""), "", [1]DataLookUp!$C64) -> Health Safety Environment Staff | D64: 252000000000011 | E64: =IF(EXACT(D64, ""), "", VLOOKUP(D64, [2]DataLookUp!$B$4:$C$32, 2, FALSE)) -> Department - Health Safety Environment | G64: =G63 + IF(EXACT(H64, ""), 0, 1) -> 253000000000050 | H64: =IF(AND(EXACT(B64, ""), EXACT(D64, "")), "", CONCATENATE("PERFORM ""SchSysConfig"".""Func_TblAppObject_UserRole_SET""(varSystemLoginSession, null::bigint, null::varchar, null::timestamptz, null::timestamptz, null::varchar, varInstitutionBranchID, varBaseCurrencyID, ", (IF(EXACT(B64, ""), "NULL", CONCATENATE("'", B64, "'"))),"::varchar);")) -> PERFORM "SchSysConfig"."Func_TblAppObject_UserRole_SET"(varSystemLoginSession, null::bigint, null::varchar, null::timestamptz, null::timestamptz, null::varchar, varInstitutionBranchID, varBaseCurrencyID, '95000000000050'::varchar); | J64: =IF(EXACT($H64, ""), "", CONCATENATE( "varSQL := varSQL || (CASE WHEN (varSQL = '') THEN '' ELSE ', ' END) || (SELECT JSON_BUILD_OBJECT (", "'recordID', NULL::bigint,", "'entities', ", "JSON_BUILD_OBJECT (", "'sysLoginSession_RefID', varSystemLoginSession::bigint,", "'sysDataAnnotation', NULL::varchar,", "'sysDataSetDateTimeTZ', NULL::timestamptz,", "'sysDataValidityStartDateTimeTZ', NULL::timestamptz,", "'sysDataValidityFinishDateTimeTZ', NULL::timestamptz,", "'sysPartitionRemovableRecordKey_RefID', NULL::bigint,", "'sysBranch_RefID', varInstitutionBranchID::bigint,", "'sysBaseCurrency_RefID',varBaseCurrencyID::bigint,", "'userRoleGroup_RefID', ", IF(EXACT($D64, ""), "null", CONCATENATE("'", SUBSTITUTE($D64, "'", "\'"), "'")), "::bigint, ", "'userRole_RefID', ", IF(EXACT($B64, ""), "null", CONCATENATE("'", SUBSTITUTE($B64, "'", "\'"), "'")), "::bigint", ")))::varchar;")) -> varSQL := varSQL || (CASE WHEN (varSQL = '') THEN '' ELSE ', ' END) || (SELECT JSON_BUILD_OBJECT ('recordID', NULL::bigint,'entities', JSON_BUILD_OBJECT ('sysLoginSession_RefID', varSystemLoginSession::bigint,'sysDataAnnotation', NULL::varchar,'sysDataSetDateTimeTZ', NULL::timestamptz,'sysDataValidityStartDateTimeTZ', NULL::timestamptz,'sysDataValidityFinishDateTimeTZ', NULL::timestamptz,'sysPartitionRemovableRecordKey_RefID', NULL::bigint,'sysBranch_RefID', varInstitutionBranchID::bigint,'sysBaseCurrency_RefID',varBaseCurrencyID::bigint,'userRoleGroup_RefID', '252000000000011'::bigint, 'userRole_RefID', '95000000000050'::bigint)))::varchar;
B65: =IF(EXACT([1]DataLookUp!$B65, ""), "", [1]DataLookUp!$B65) | C65: =IF(EXACT(B65, ""), "", [1]DataLookUp!$C65) | E65: =IF(EXACT(D65, ""), "", VLOOKUP(D65, [2]DataLookUp!$B$4:$C$32, 2, FALSE)) | G65: =G64 + IF(EXACT(H65, ""), 0, 1) -> 253000000000050 | H65: =IF(AND(EXACT(B65, ""), EXACT(D65, "")), "", CONCATENATE("PERFORM ""SchSysConfig"".""Func_TblAppObject_UserRole_SET""(varSystemLoginSession, null::bigint, null::varchar, null::timestamptz, null::timestamptz, null::varchar, varInstitutionBranchID, varBaseCurrencyID, ", (IF(EXACT(B65, ""), "NULL", CONCATENATE("'", B65, "'"))),"::varchar);")) | J65: =IF(EXACT($H65, ""), "", CONCATENATE( "varSQL := varSQL || (CASE WHEN (varSQL = '') THEN '' ELSE ', ' END) || (SELECT JSON_BUILD_OBJECT (", "'recordID', NULL::bigint,", "'entities', ", "JSON_BUILD_OBJECT (", "'sysLoginSession_RefID', varSystemLoginSession::bigint,", "'sysDataAnnotation', NULL::varchar,", "'sysDataSetDateTimeTZ', NULL::timestamptz,", "'sysDataValidityStartDateTimeTZ', NULL::timestamptz,", "'sysDataValidityFinishDateTimeTZ', NULL::timestamptz,", "'sysPartitionRemovableRecordKey_RefID', NULL::bigint,", "'sysBranch_RefID', varInstitutionBranchID::bigint,", "'sysBaseCurrency_RefID',varBaseCurrencyID::bigint,", "'userRoleGroup_RefID', ", IF(EXACT($D65, ""), "null", CONCATENATE("'", SUBSTITUTE($D65, "'", "\'"), "'")), "::bigint, ", "'userRole_RefID', ", IF(EXACT($B65, ""), "null", CONCATENATE("'", SUBSTITUTE($B65, "'", "\'"), "'")), "::bigint", ")))::varchar;"))
B66: =IF(EXACT([1]DataLookUp!$B66, ""), "", [1]DataLookUp!$B66) -> 95000000000051 | C66: =IF(EXACT(B66, ""), "", [1]DataLookUp!$C66) -> Human Resource Development Manager | D66: 252000000000010 | E66: =IF(EXACT(D66, ""), "", VLOOKUP(D66, [2]DataLookUp!$B$4:$C$32, 2, FALSE)) -> Department - Human Resource Development | G66: =G65 + IF(EXACT(H66, ""), 0, 1) -> 253000000000051 | H66: =IF(AND(EXACT(B66, ""), EXACT(D66, "")), "", CONCATENATE("PERFORM ""SchSysConfig"".""Func_TblAppObject_UserRole_SET""(varSystemLoginSession, null::bigint, null::varchar, null::timestamptz, null::timestamptz, null::varchar, varInstitutionBranchID, varBaseCurrencyID, ", (IF(EXACT(B66, ""), "NULL", CONCATENATE("'", B66, "'"))),"::varchar);")) -> PERFORM "SchSysConfig"."Func_TblAppObject_UserRole_SET"(varSystemLoginSession, null::bigint, null::varchar, null::timestamptz, null::timestamptz, null::varchar, varInstitutionBranchID, varBaseCurrencyID, '95000000000051'::varchar); | J66: =IF(EXACT($H66, ""), "", CONCATENATE( "varSQL := varSQL || (CASE WHEN (varSQL = '') THEN '' ELSE ', ' END) || (SELECT JSON_BUILD_OBJECT (", "'recordID', NULL::bigint,", "'entities', ", "JSON_BUILD_OBJECT (", "'sysLoginSession_RefID', varSystemLoginSession::bigint,", "'sysDataAnnotation', NULL::varchar,", "'sysDataSetDateTimeTZ', NULL::timestamptz,", "'sysDataValidityStartDateTimeTZ', NULL::timestamptz,", "'sysDataValidityFinishDateTimeTZ', NULL::timestamptz,", "'sysPartitionRemovableRecordKey_RefID', NULL::bigint,", "'sysBranch_RefID', varInstitutionBranchID::bigint,", "'sysBaseCurrency_RefID',varBaseCurrencyID::bigint,", "'userRoleGroup_RefID', ", IF(EXACT($D66, ""), "null", CONCATENATE("'", SUBSTITUTE($D66, "'", "\'"), "'")), "::bigint, ", "'userRole_RefID', ", IF(EXACT($B66, ""), "null", CONCATENATE("'", SUBSTITUTE($B66, "'", "\'"), "'")), "::bigint", ")))::varchar;")) -> varSQL := varSQL || (CASE WHEN (varSQL = '') THEN '' ELSE ', ' END) || (SELECT JSON_BUILD_OBJECT ('recordID', NULL::bigint,'entities', JSON_BUILD_OBJECT ('sysLoginSession_RefID', varSystemLoginSession::bigint,'sysDataAnnotation', NULL::varchar,'sysDataSetDateTimeTZ', NULL::timestamptz,'sysDataValidityStartDateTimeTZ', NULL::timestamptz,'sysDataValidityFinishDateTimeTZ', NULL::timestamptz,'sysPartitionRemovableRecordKey_RefID', NULL::bigint,'sysBranch_RefID', varInstitutionBranchID::bigint,'sysBaseCurrency_RefID',varBaseCurrencyID::bigint,'userRoleGroup_RefID', '252000000000010'::bigint, 'userRole_RefID', '95000000000051'::bigint)))::varchar;
B67: =IF(EXACT([1]DataLookUp!$B67, ""), "", [1]DataLookUp!$B67) -> 95000000000052 | C67: =IF(EXACT(B67, ""), "", [1]DataLookUp!$C67) -> Human Resource Development Coordinator | D67: 252000000000010 | E67: =IF(EXACT(D67, ""), "", VLOOKUP(D67, [2]DataLookUp!$B$4:$C$32, 2, FALSE)) -> Department - Human Resource Development | G67: =G66 + IF(EXACT(H67, ""), 0, 1) -> 253000000000052 | H67: =IF(AND(EXACT(B67, ""), EXACT(D67, "")), "", CONCATENATE("PERFORM ""SchSysConfig"".""Func_TblAppObject_UserRole_SET""(varSystemLoginSession, null::bigint, null::varchar, null::timestamptz, null::timestamptz, null::varchar, varInstitutionBranchID, varBaseCurrencyID, ", (IF(EXACT(B67, ""), "NULL", CONCATENATE("'", B67, "'"))),"::varchar);")) -> PERFORM "SchSysConfig"."Func_TblAppObject_UserRole_SET"(varSystemLoginSession, null::bigint, null::varchar, null::timestamptz, null::timestamptz, null::varchar, varInstitutionBranchID, varBaseCurrencyID, '95000000000052'::varchar); | J67: =IF(EXACT($H67, ""), "", CONCATENATE( "varSQL := varSQL || (CASE WHEN (varSQL = '') THEN '' ELSE ', ' END) || (SELECT JSON_BUILD_OBJECT (", "'recordID', NULL::bigint,", "'entities', ", "JSON_BUILD_OBJECT (", "'sysLoginSession_RefID', varSystemLoginSession::bigint,", "'sysDataAnnotation', NULL::varchar,", "'sysDataSetDateTimeTZ', NULL::timestamptz,", "'sysDataValidityStartDateTimeTZ', NULL::timestamptz,", "'sysDataValidityFinishDateTimeTZ', NULL::timestamptz,", "'sysPartitionRemovableRecordKey_RefID', NULL::bigint,", "'sysBranch_RefID', varInstitutionBranchID::bigint,", "'sysBaseCurrency_RefID',varBaseCurrencyID::bigint,", "'userRoleGroup_RefID', ", IF(EXACT($D67, ""), "null", CONCATENATE("'", SUBSTITUTE($D67, "'", "\'"), "'")), "::bigint, ", "'userRole_RefID', ", IF(EXACT($B67, ""), "null", CONCATENATE("'", SUBSTITUTE($B67, "'", "\'"), "'")), "::bigint", ")))::varchar;")) -> varSQL := varSQL || (CASE WHEN (varSQL = '') THEN '' ELSE ', ' END) || (SELECT JSON_BUILD_OBJECT ('recordID', NULL::bigint,'entities', JSON_BUILD_OBJECT ('sysLoginSession_RefID', varSystemLoginSession::bigint,'sysDataAnnotation', NULL::varchar,'sysDataSetDateTimeTZ', NULL::timestamptz,'sysDataValidityStartDateTimeTZ', NULL::timestamptz,'sysDataValidityFinishDateTimeTZ', NULL::timestamptz,'sysPartitionRemovableRecordKey_RefID', NULL::bigint,'sysBranch_RefID', varInstitutionBranchID::bigint,'sysBaseCurrency_RefID',varBaseCurrencyID::bigint,'userRoleGroup_RefID', '252000000000010'::bigint, 'userRole_RefID', '95000000000052'::bigint)))::varchar;
B68: =IF(EXACT([1]DataLookUp!$B68, ""), "", [1]DataLookUp!$B68) -> 95000000000053 | C68: =IF(EXACT(B68, ""), "", [1]DataLookUp!$C68) -> Human Resource Development Staff | D68: 252000000000010 | E68: =IF(EXACT(D68, ""), "", VLOOKUP(D68, [2]DataLookUp!$B$4:$C$32, 2, FALSE)) -> Department - Human Resource Development | G68: =G67 + IF(EXACT(H68, ""), 0, 1) -> 253000000000053 | H68: =IF(AND(EXACT(B68, ""), EXACT(D68, "")), "", CONCATENATE("PERFORM ""SchSysConfig"".""Func_TblAppObject_UserRole_SET""(varSystemLoginSession, null::bigint, null::varchar, null::timestamptz, null::timestamptz, null::varchar, varInstitutionBranchID, varBaseCurrencyID, ", (IF(EXACT(B68, ""), "NULL", CONCATENATE("'", B68, "'"))),"::varchar);")) -> PERFORM "SchSysConfig"."Func_TblAppObject_UserRole_SET"(varSystemLoginSession, null::bigint, null::varchar, null::timestamptz, null::timestamptz, null::varchar, varInstitutionBranchID, varBaseCurrencyID, '95000000000053'::varchar); | J68: =IF(EXACT($H68, ""), "", CONCATENATE( "varSQL := varSQL || (CASE WHEN (varSQL = '') THEN '' ELSE ', ' END) || (SELECT JSON_BUILD_OBJECT (", "'recordID', NULL::bigint,", "'entities', ", "JSON_BUILD_OBJECT (", "'sysLoginSession_RefID', varSystemLoginSession::bigint,", "'sysDataAnnotation', NULL::varchar,", "'sysDataSetDateTimeTZ', NULL::timestamptz,", "'sysDataValidityStartDateTimeTZ', NULL::timestamptz,", "'sysDataValidityFinishDateTimeTZ', NULL::timestamptz,", "'sysPartitionRemovableRecordKey_RefID', NULL::bigint,", "'sysBranch_RefID', varInstitutionBranchID::bigint,", "'sysBaseCurrency_RefID',varBaseCurrencyID::bigint,", "'userRoleGroup_RefID', ", IF(EXACT($D68, ""), "null", CONCATENATE("'", SUBSTITUTE($D68, "'", "\'"), "'")), "::bigint, ", "'userRole_RefID', ", IF(EXACT($B68, ""), "null", CONCATENATE("'", SUBSTITUTE($B68, "'", "\'"), "'")), "::bigint", ")))::varchar;")) -> varSQL := varSQL || (CASE WHEN (varSQL = '') THEN '' ELSE ', ' END) || (SELECT JSON_BUILD_OBJECT ('recordID', NULL::bigint,'entities', JSON_BUILD_OBJECT ('sysLoginSession_RefID', varSystemLoginSession::bigint,'sysDataAnnotation', NULL::varchar,'sysDataSetDateTimeTZ', NULL::timestamptz,'sysDataValidityStartDateTimeTZ', NULL::timestamptz,'sysDataValidityFinishDateTimeTZ', NULL::timestamptz,'sysPartitionRemovableRecordKey_RefID', NULL::bigint,'sysBranch_RefID', varInstitutionBranchID::bigint,'sysBaseCurrency_RefID',varBaseCurrencyID::bigint,'userRoleGroup_RefID', '252000000000010'::bigint, 'userRole_RefID', '95000000000053'::bigint)))::varchar;
B69: =IF(EXACT([1]DataLookUp!$B69, ""), "", [1]DataLookUp!$B69) | C69: =IF(EXACT(B69, ""), "", [1]DataLookUp!$C69) | E69: =IF(EXACT(D69, ""), "", VLOOKUP(D69, [2]DataLookUp!$B$4:$C$32, 2, FALSE)) | G69: =G68 + IF(EXACT(H69, ""), 0, 1) -> 253000000000053 | H69: =IF(AND(EXACT(B69, ""), EXACT(D69, "")), "", CONCATENATE("PERFORM ""SchSysConfig"".""Func_TblAppObject_UserRole_SET""(varSystemLoginSession, null::bigint, null::varchar, null::timestamptz, null::timestamptz, null::varchar, varInstitutionBranchID, varBaseCurrencyID, ", (IF(EXACT(B69, ""), "NULL", CONCATENATE("'", B69, "'"))),"::varchar);")) | J69: =IF(EXACT($H69, ""), "", CONCATENATE( "varSQL := varSQL || (CASE WHEN (varSQL = '') THEN '' ELSE ', ' END) || (SELECT JSON_BUILD_OBJECT (", "'recordID', NULL::bigint,", "'entities', ", "JSON_BUILD_OBJECT (", "'sysLoginSession_RefID', varSystemLoginSession::bigint,", "'sysDataAnnotation', NULL::varchar,", "'sysDataSetDateTimeTZ', NULL::timestamptz,", "'sysDataValidityStartDateTimeTZ', NULL::timestamptz,", "'sysDataValidityFinishDateTimeTZ', NULL::timestamptz,", "'sysPartitionRemovableRecordKey_RefID', NULL::bigint,", "'sysBranch_RefID', varInstitutionBranchID::bigint,", "'sysBaseCurrency_RefID',varBaseCurrencyID::bigint,", "'userRoleGroup_RefID', ", IF(EXACT($D69, ""), "null", CONCATENATE("'", SUBSTITUTE($D69, "'", "\'"), "'")), "::bigint, ", "'userRole_RefID', ", IF(EXACT($B69, ""), "null", CONCATENATE("'", SUBSTITUTE($B69, "'", "\'"), "'")), "::bigint", ")))::varchar;"))
B70: =IF(EXACT([1]DataLookUp!$B70, ""), "", [1]DataLookUp!$B70) -> 95000000000054 | C70: =IF(EXACT(B70, ""), "", [1]DataLookUp!$C70) -> General Affairs Manager | D70: 252000000000010 | E70: =IF(EXACT(D70, ""), "", VLOOKUP(D70, [2]DataLookUp!$B$4:$C$32, 2, FALSE)) -> Department - Human Resource Development | G70: =G69 + IF(EXACT(H70, ""), 0, 1) -> 253000000000054 | H70: =IF(AND(EXACT(B70, ""), EXACT(D70, "")), "", CONCATENATE("PERFORM ""SchSysConfig"".""Func_TblAppObject_UserRole_SET""(varSystemLoginSession, null::bigint, null::varchar, null::timestamptz, null::timestamptz, null::varchar, varInstitutionBranchID, varBaseCurrencyID, ", (IF(EXACT(B70, ""), "NULL", CONCATENATE("'", B70, "'"))),"::varchar);")) -> PERFORM "SchSysConfig"."Func_TblAppObject_UserRole_SET"(varSystemLoginSession, null::bigint, null::varchar, null::timestamptz, null::timestamptz, null::varchar, varInstitutionBranchID, varBaseCurrencyID, '95000000000054'::varchar); | J70: =IF(EXACT($H70, ""), "", CONCATENATE( "varSQL := varSQL || (CASE WHEN (varSQL = '') THEN '' ELSE ', ' END) || (SELECT JSON_BUILD_OBJECT (", "'recordID', NULL::bigint,", "'entities', ", "JSON_BUILD_OBJECT (", "'sysLoginSession_RefID', varSystemLoginSession::bigint,", "'sysDataAnnotation', NULL::varchar,", "'sysDataSetDateTimeTZ', NULL::timestamptz,", "'sysDataValidityStartDateTimeTZ', NULL::timestamptz,", "'sysDataValidityFinishDateTimeTZ', NULL::timestamptz,", "'sysPartitionRemovableRecordKey_RefID', NULL::bigint,", "'sysBranch_RefID', varInstitutionBranchID::bigint,", "'sysBaseCurrency_RefID',varBaseCurrencyID::bigint,", "'userRoleGroup_RefID', ", IF(EXACT($D70, ""), "null", CONCATENATE("'", SUBSTITUTE($D70, "'", "\'"), "'")), "::bigint, ", "'userRole_RefID', ", IF(EXACT($B70, ""), "null", CONCATENATE("'", SUBSTITUTE($B70, "'", "\'"), "'")), "::bigint", ")))::varchar;")) -> varSQL := varSQL || (CASE WHEN (varSQL = '') THEN '' ELSE ', ' END) || (SELECT JSON_BUILD_OBJECT ('recordID', NULL::bigint,'entities', JSON_BUILD_OBJECT ('sysLoginSession_RefID', varSystemLoginSession::bigint,'sysDataAnnotation', NULL::varchar,'sysDataSetDateTimeTZ', NULL::timestamptz,'sysDataValidityStartDateTimeTZ', NULL::timestamptz,'sysDataValidityFinishDateTimeTZ', NULL::timestamptz,'sysPartitionRemovableRecordKey_RefID', NULL::bigint,'sysBranch_RefID', varInstitutionBranchID::bigint,'sysBaseCurrency_RefID',varBaseCurrencyID::bigint,'userRoleGroup_RefID', '252000000000010'::bigint, 'userRole_RefID', '95000000000054'::bigint)))::varchar;
B71: =IF(EXACT([1]DataLookUp!$B71, ""), "", [1]DataLookUp!$B71) -> 95000000000055 | C71: =IF(EXACT(B71, ""), "", [1]DataLookUp!$C71) -> General Affairs Coordinator | D71: 252000000000010 | E71: =IF(EXACT(D71, ""), "", VLOOKUP(D71, [2]DataLookUp!$B$4:$C$32, 2, FALSE)) -> Department - Human Resource Development | G71: =G70 + IF(EXACT(H71, ""), 0, 1) -> 253000000000055 | H71: =IF(AND(EXACT(B71, ""), EXACT(D71, "")), "", CONCATENATE("PERFORM ""SchSysConfig"".""Func_TblAppObject_UserRole_SET""(varSystemLoginSession, null::bigint, null::varchar, null::timestamptz, null::timestamptz, null::varchar, varInstitutionBranchID, varBaseCurrencyID, ", (IF(EXACT(B71, ""), "NULL", CONCATENATE("'", B71, "'"))),"::varchar);")) -> PERFORM "SchSysConfig"."Func_TblAppObject_UserRole_SET"(varSystemLoginSession, null::bigint, null::varchar, null::timestamptz, null::timestamptz, null::varchar, varInstitutionBranchID, varBaseCurrencyID, '95000000000055'::varchar); | J71: =IF(EXACT($H71, ""), "", CONCATENATE( "varSQL := varSQL || (CASE WHEN (varSQL = '') THEN '' ELSE ', ' END) || (SELECT JSON_BUILD_OBJECT (", "'recordID', NULL::bigint,", "'entities', ", "JSON_BUILD_OBJECT (", "'sysLoginSession_RefID', varSystemLoginSession::bigint,", "'sysDataAnnotation', NULL::varchar,", "'sysDataSetDateTimeTZ', NULL::timestamptz,", "'sysDataValidityStartDateTimeTZ', NULL::timestamptz,", "'sysDataValidityFinishDateTimeTZ', NULL::timestamptz,", "'sysPartitionRemovableRecordKey_RefID', NULL::bigint,", "'sysBranch_RefID', varInstitutionBranchID::bigint,", "'sysBaseCurrency_RefID',varBaseCurrencyID::bigint,", "'userRoleGroup_RefID', ", IF(EXACT($D71, ""), "null", CONCATENATE("'", SUBSTITUTE($D71, "'", "\'"), "'")), "::bigint, ", "'userRole_RefID', ", IF(EXACT($B71, ""), "null", CONCATENATE("'", SUBSTITUTE($B71, "'", "\'"), "'")), "::bigint", ")))::varchar;")) -> varSQL := varSQL || (CASE WHEN (varSQL = '') THEN '' ELSE ', ' END) || (SELECT JSON_BUILD_OBJECT ('recordID', NULL::bigint,'entities', JSON_BUILD_OBJECT ('sysLoginSession_RefID', varSystemLoginSession::bigint,'sysDataAnnotation', NULL::varchar,'sysDataSetDateTimeTZ', NULL::timestamptz,'sysDataValidityStartDateTimeTZ', NULL::timestamptz,'sysDataValidityFinishDateTimeTZ', NULL::timestamptz,'sysPartitionRemovableRecordKey_RefID', NULL::bigint,'sysBranch_RefID', varInstitutionBranchID::bigint,'sysBaseCurrency_RefID',varBaseCurrencyID::bigint,'userRoleGroup_RefID', '252000000000010'::bigint, 'userRole_RefID', '95000000000055'::bigint)))::varchar;
B72: =IF(EXACT([1]DataLookUp!$B72, ""), "", [1]DataLookUp!$B72) -> 95000000000056 | C72: =IF(EXACT(B72, ""), "", [1]DataLookUp!$C72) -> General Affairs Staff | D72: 252000000000010 | E72: =IF(EXACT(D72, ""), "", VLOOKUP(D72, [2]DataLookUp!$B$4:$C$32, 2, FALSE)) -> Department - Human Resource Development | G72: =G71 + IF(EXACT(H72, ""), 0, 1) -> 253000000000056 | H72: =IF(AND(EXACT(B72, ""), EXACT(D72, "")), "", CONCATENATE("PERFORM ""SchSysConfig"".""Func_TblAppObject_UserRole_SET""(varSystemLoginSession, null::bigint, null::varchar, null::timestamptz, null::timestamptz, null::varchar, varInstitutionBranchID, varBaseCurrencyID, ", (IF(EXACT(B72, ""), "NULL", CONCATENATE("'", B72, "'"))),"::varchar);")) -> PERFORM "SchSysConfig"."Func_TblAppObject_UserRole_SET"(varSystemLoginSession, null::bigint, null::varchar, null::timestamptz, null::timestamptz, null::varchar, varInstitutionBranchID, varBaseCurrencyID, '95000000000056'::varchar); | J72: =IF(EXACT($H72, ""), "", CONCATENATE( "varSQL := varSQL || (CASE WHEN (varSQL = '') THEN '' ELSE ', ' END) || (SELECT JSON_BUILD_OBJECT (", "'recordID', NULL::bigint,", "'entities', ", "JSON_BUILD_OBJECT (", "'sysLoginSession_RefID', varSystemLoginSession::bigint,", "'sysDataAnnotation', NULL::varchar,", "'sysDataSetDateTimeTZ', NULL::timestamptz,", "'sysDataValidityStartDateTimeTZ', NULL::timestamptz,", "'sysDataValidityFinishDateTimeTZ', NULL::timestamptz,", "'sysPartitionRemovableRecordKey_RefID', NULL::bigint,", "'sysBranch_RefID', varInstitutionBranchID::bigint,", "'sysBaseCurrency_RefID',varBaseCurrencyID::bigint,", "'userRoleGroup_RefID', ", IF(EXACT($D72, ""), "null", CONCATENATE("'", SUBSTITUTE($D72, "'", "\'"), "'")), "::bigint, ", "'userRole_RefID', ", IF(EXACT($B72, ""), "null", CONCATENATE("'", SUBSTITUTE($B72, "'", "\'"), "'")), "::bigint", ")))::varchar;")) -> varSQL := varSQL || (CASE WHEN (varSQL = '') THEN '' ELSE ', ' END) || (SELECT JSON_BUILD_OBJECT ('recordID', NULL::bigint,'entities', JSON_BUILD_OBJECT ('sysLoginSession_RefID', varSystemLoginSession::bigint,'sysDataAnnotation', NULL::varchar,'sysDataSetDateTimeTZ', NULL::timestamptz,'sysDataValidityStartDateTimeTZ', NULL::timestamptz,'sysDataValidityFinishDateTimeTZ', NULL::timestamptz,'sysPartitionRemovableRecordKey_RefID', NULL::bigint,'sysBranch_RefID', varInstitutionBranchID::bigint,'sysBaseCurrency_RefID',varBaseCurrencyID::bigint,'userRoleGroup_RefID', '252000000000010'::bigint, 'userRole_RefID', '95000000000056'::bigint)))::varchar;
B73: =IF(EXACT([1]DataLookUp!$B73, ""), "", [1]DataLookUp!$B73) | C73: =IF(EXACT(B73, ""), "", [1]DataLookUp!$C73) | E73: =IF(EXACT(D73, ""), "", VLOOKUP(D73, [2]DataLookUp!$B$4:$C$32, 2, FALSE)) | G73: =G72 + IF(EXACT(H73, ""), 0, 1) -> 253000000000056 | H73: =IF(AND(EXACT(B73, ""), EXACT(D73, "")), "", CONCATENATE("PERFORM ""SchSysConfig"".""Func_TblAppObject_UserRole_SET""(varSystemLoginSession, null::bigint, null::varchar, null::timestamptz, null::timestamptz, null::varchar, varInstitutionBranchID, varBaseCurrencyID, ", (IF(EXACT(B73, ""), "NULL", CONCATENATE("'", B73, "'"))),"::varchar);")) | J73: =IF(EXACT($H73, ""), "", CONCATENATE( "varSQL := varSQL || (CASE WHEN (varSQL = '') THEN '' ELSE ', ' END) || (SELECT JSON_BUILD_OBJECT (", "'recordID', NULL::bigint,", "'entities', ", "JSON_BUILD_OBJECT (", "'sysLoginSession_RefID', varSystemLoginSession::bigint,", "'sysDataAnnotation', NULL::varchar,", "'sysDataSetDateTimeTZ', NULL::timestamptz,", "'sysDataValidityStartDateTimeTZ', NULL::timestamptz,", "'sysDataValidityFinishDateTimeTZ', NULL::timestamptz,", "'sysPartitionRemovableRecordKey_RefID', NULL::bigint,", "'sysBranch_RefID', varInstitutionBranchID::bigint,", "'sysBaseCurrency_RefID',varBaseCurrencyID::bigint,", "'userRoleGroup_RefID', ", IF(EXACT($D73, ""), "null", CONCATENATE("'", SUBSTITUTE($D73, "'", "\'"), "'")), "::bigint, ", "'userRole_RefID', ", IF(EXACT($B73, ""), "null", CONCATENATE("'", SUBSTITUTE($B73, "'", "\'"), "'")), "::bigint", ")))::varchar;"))
B74: =IF(EXACT([1]DataLookUp!$B74, ""), "", [1]DataLookUp!$B74) -> 95000000000057 | C74: =IF(EXACT(B74, ""), "", [1]DataLookUp!$C74) -> Legal Manager | D74: 252000000000013 | E74: =IF(EXACT(D74, ""), "", VLOOKUP(D74, [2]DataLookUp!$B$4:$C$32, 2, FALSE)) -> Department - Legal | G74: =G73 + IF(EXACT(H74, ""), 0, 1) -> 253000000000057 | H74: =IF(AND(EXACT(B74, ""), EXACT(D74, "")), "", CONCATENATE("PERFORM ""SchSysConfig"".""Func_TblAppObject_UserRole_SET""(varSystemLoginSession, null::bigint, null::varchar, null::timestamptz, null::timestamptz, null::varchar, varInstitutionBranchID, varBaseCurrencyID, ", (IF(EXACT(B74, ""), "NULL", CONCATENATE("'", B74, "'"))),"::varchar);")) -> PERFORM "SchSysConfig"."Func_TblAppObject_UserRole_SET"(varSystemLoginSession, null::bigint, null::varchar, null::timestamptz, null::timestamptz, null::varchar, varInstitutionBranchID, varBaseCurrencyID, '95000000000057'::varchar); | J74: =IF(EXACT($H74, ""), "", CONCATENATE( "varSQL := varSQL || (CASE WHEN (varSQL = '') THEN '' ELSE ', ' END) || (SELECT JSON_BUILD_OBJECT (", "'recordID', NULL::bigint,", "'entities', ", "JSON_BUILD_OBJECT (", "'sysLoginSession_RefID', varSystemLoginSession::bigint,", "'sysDataAnnotation', NULL::varchar,", "'sysDataSetDateTimeTZ', NULL::timestamptz,", "'sysDataValidityStartDateTimeTZ', NULL::timestamptz,", "'sysDataValidityFinishDateTimeTZ', NULL::timestamptz,", "'sysPartitionRemovableRecordKey_RefID', NULL::bigint,", "'sysBranch_RefID', varInstitutionBranchID::bigint,", "'sysBaseCurrency_RefID',varBaseCurrencyID::bigint,", "'userRoleGroup_RefID', ", IF(EXACT($D74, ""), "null", CONCATENATE("'", SUBSTITUTE($D74, "'", "\'"), "'")), "::bigint, ", "'userRole_RefID', ", IF(EXACT($B74, ""), "null", CONCATENATE("'", SUBSTITUTE($B74, "'", "\'"), "'")), "::bigint", ")))::varchar;")) -> varSQL := varSQL || (CASE WHEN (varSQL = '') THEN '' ELSE ', ' END) || (SELECT JSON_BUILD_OBJECT ('recordID', NULL::bigint,'entities', JSON_BUILD_OBJECT ('sysLoginSession_RefID', varSystemLoginSession::bigint,'sysDataAnnotation', NULL::varchar,'sysDataSetDateTimeTZ', NULL::timestamptz,'sysDataValidityStartDateTimeTZ', NULL::timestamptz,'sysDataValidityFinishDateTimeTZ', NULL::timestamptz,'sysPartitionRemovableRecordKey_RefID', NULL::bigint,'sysBranch_RefID', varInstitutionBranchID::bigint,'sysBaseCurrency_RefID',varBaseCurrencyID::bigint,'userRoleGroup_RefID', '252000000000013'::bigint, 'userRole_RefID', '95000000000057'::bigint)))::varchar;
B75: =IF(EXACT([1]DataLookUp!$B75, ""), "", [1]DataLookUp!$B75) -> 95000000000058 | C75: =IF(EXACT(B75, ""), "", [1]DataLookUp!$C75) -> Legal Coordinator | D75: 252000000000013 | E75: =IF(EXACT(D75, ""), "", VLOOKUP(D75, [2]DataLookUp!$B$4:$C$32, 2, FALSE)) -> Department - Legal | G75: =G74 + IF(EXACT(H75, ""), 0, 1) -> 253000000000058 | H75: =IF(AND(EXACT(B75, ""), EXACT(D75, "")), "", CONCATENATE("PERFORM ""SchSysConfig"".""Func_TblAppObject_UserRole_SET""(varSystemLoginSession, null::bigint, null::varchar, null::timestamptz, null::timestamptz, null::varchar, varInstitutionBranchID, varBaseCurrencyID, ", (IF(EXACT(B75, ""), "NULL", CONCATENATE("'", B75, "'"))),"::varchar);")) -> PERFORM "SchSysConfig"."Func_TblAppObject_UserRole_SET"(varSystemLoginSession, null::bigint, null::varchar, null::timestamptz, null::timestamptz, null::varchar, varInstitutionBranchID, varBaseCurrencyID, '95000000000058'::varchar); | J75: =IF(EXACT($H75, ""), "", CONCATENATE( "varSQL := varSQL || (CASE WHEN (varSQL = '') THEN '' ELSE ', ' END) || (SELECT JSON_BUILD_OBJECT (", "'recordID', NULL::bigint,", "'entities', ", "JSON_BUILD_OBJECT (", "'sysLoginSession_RefID', varSystemLoginSession::bigint,", "'sysDataAnnotation', NULL::varchar,", "'sysDataSetDateTimeTZ', NULL::timestamptz,", "'sysDataValidityStartDateTimeTZ', NULL::timestamptz,", "'sysDataValidityFinishDateTimeTZ', NULL::timestamptz,", "'sysPartitionRemovableRecordKey_RefID', NULL::bigint,", "'sysBranch_RefID', varInstitutionBranchID::bigint,", "'sysBaseCurrency_RefID',varBaseCurrencyID::bigint,", "'userRoleGroup_RefID', ", IF(EXACT($D75, ""), "null", CONCATENATE("'", SUBSTITUTE($D75, "'", "\'"), "'")), "::bigint, ", "'userRole_RefID', ", IF(EXACT($B75, ""), "null", CONCATENATE("'", SUBSTITUTE($B75, "'", "\'"), "'")), "::bigint", ")))::varchar;")) -> varSQL := varSQL || (CASE WHEN (varSQL = '') THEN '' ELSE ', ' END) || (SELECT JSON_BUILD_OBJECT ('recordID', NULL::bigint,'entities', JSON_BUILD_OBJECT ('sysLoginSession_RefID', varSystemLoginSession::bigint,'sysDataAnnotation', NULL::varchar,'sysDataSetDateTimeTZ', NULL::timestamptz,'sysDataValidityStartDateTimeTZ', NULL::timestamptz,'sysDataValidityFinishDateTimeTZ', NULL::timestamptz,'sysPartitionRemovableRecordKey_RefID', NULL::bigint,'sysBranch_RefID', varInstitutionBranchID::bigint,'sysBaseCurrency_RefID',varBaseCurrencyID::bigint,'userRoleGroup_RefID', '252000000000013'::bigint, 'userRole_RefID', '95000000000058'::bigint)))::varchar;
B76: =IF(EXACT([1]DataLookUp!$B76, ""), "", [1]DataLookUp!$B76) -> 95000000000059 | C76: =IF(EXACT(B76, ""), "", [1]DataLookUp!$C76) -> Legal Staff | D76: 252000000000013 | E76: =IF(EXACT(D76, ""), "", VLOOKUP(D76, [2]DataLookUp!$B$4:$C$32, 2, FALSE)) -> Department - Legal | G76: =G75 + IF(EXACT(H76, ""), 0, 1) -> 253000000000059 | H76: =IF(AND(EXACT(B76, ""), EXACT(D76, "")), "", CONCATENATE("PERFORM ""SchSysConfig"".""Func_TblAppObject_UserRole_SET""(varSystemLoginSession, null::bigint, null::varchar, null::timestamptz, null::timestamptz, null::varchar, varInstitutionBranchID, varBaseCurrencyID, ", (IF(EXACT(B76, ""), "NULL", CONCATENATE("'", B76, "'"))),"::varchar);")) -> PERFORM "SchSysConfig"."Func_TblAppObject_UserRole_SET"(varSystemLoginSession, null::bigint, null::varchar, null::timestamptz, null::timestamptz, null::varchar, varInstitutionBranchID, varBaseCurrencyID, '95000000000059'::varchar); | J76: =IF(EXACT($H76, ""), "", CONCATENATE( "varSQL := varSQL || (CASE WHEN (varSQL = '') THEN '' ELSE ', ' END) || (SELECT JSON_BUILD_OBJECT (", "'recordID', NULL::bigint,", "'entities', ", "JSON_BUILD_OBJECT (", "'sysLoginSession_RefID', varSystemLoginSession::bigint,", "'sysDataAnnotation', NULL::varchar,", "'sysDataSetDateTimeTZ', NULL::timestamptz,", "'sysDataValidityStartDateTimeTZ', NULL::timestamptz,", "'sysDataValidityFinishDateTimeTZ', NULL::timestamptz,", "'sysPartitionRemovableRecordKey_RefID', NULL::bigint,", "'sysBranch_RefID', varInstitutionBranchID::bigint,", "'sysBaseCurrency_RefID',varBaseCurrencyID::bigint,", "'userRoleGroup_RefID', ", IF(EXACT($D76, ""), "null", CONCATENATE("'", SUBSTITUTE($D76, "'", "\'"), "'")), "::bigint, ", "'userRole_RefID', ", IF(EXACT($B76, ""), "null", CONCATENATE("'", SUBSTITUTE($B76, "'", "\'"), "'")), "::bigint", ")))::varchar;")) -> varSQL := varSQL || (CASE WHEN (varSQL = '') THEN '' ELSE ', ' END) || (SELECT JSON_BUILD_OBJECT ('recordID', NULL::bigint,'entities', JSON_BUILD_OBJECT ('sysLoginSession_RefID', varSystemLoginSession::bigint,'sysDataAnnotation', NULL::varchar,'sysDataSetDateTimeTZ', NULL::timestamptz,'sysDataValidityStartDateTimeTZ', NULL::timestamptz,'sysDataValidityFinishDateTimeTZ', NULL::timestamptz,'sysPartitionRemovableRecordKey_RefID', NULL::bigint,'sysBranch_RefID', varInstitutionBranchID::bigint,'sysBaseCurrency_RefID',varBaseCurrencyID::bigint,'userRoleGroup_RefID', '252000000000013'::bigint, 'userRole_RefID', '95000000000059'::bigint)))::varchar;
B77: =IF(EXACT([1]DataLookUp!$B77, ""), "", [1]DataLookUp!$B77) | C77: =IF(EXACT(B77, ""), "", [1]DataLookUp!$C77) | E77: =IF(EXACT(D77, ""), "", VLOOKUP(D77, [2]DataLookUp!$B$4:$C$32, 2, FALSE)) | G77: =G76 + IF(EXACT(H77, ""), 0, 1) -> 253000000000059 | H77: =IF(AND(EXACT(B77, ""), EXACT(D77, "")), "", CONCATENATE("PERFORM ""SchSysConfig"".""Func_TblAppObject_UserRole_SET""(varSystemLoginSession, null::bigint, null::varchar, null::timestamptz, null::timestamptz, null::varchar, varInstitutionBranchID, varBaseCurrencyID, ", (IF(EXACT(B77, ""), "NULL", CONCATENATE("'", B77, "'"))),"::varchar);")) | J77: =IF(EXACT($H77, ""), "", CONCATENATE( "varSQL := varSQL || (CASE WHEN (varSQL = '') THEN '' ELSE ', ' END) || (SELECT JSON_BUILD_OBJECT (", "'recordID', NULL::bigint,", "'entities', ", "JSON_BUILD_OBJECT (", "'sysLoginSession_RefID', varSystemLoginSession::bigint,", "'sysDataAnnotation', NULL::varchar,", "'sysDataSetDateTimeTZ', NULL::timestamptz,", "'sysDataValidityStartDateTimeTZ', NULL::timestamptz,", "'sysDataValidityFinishDateTimeTZ', NULL::timestamptz,", "'sysPartitionRemovableRecordKey_RefID', NULL::bigint,", "'sysBranch_RefID', varInstitutionBranchID::bigint,", "'sysBaseCurrency_RefID',varBaseCurrencyID::bigint,", "'userRoleGroup_RefID', ", IF(EXACT($D77, ""), "null", CONCATENATE("'", SUBSTITUTE($D77, "'", "\'"), "'")), "::bigint, ", "'userRole_RefID', ", IF(EXACT($B77, ""), "null", CONCATENATE("'", SUBSTITUTE($B77, "'", "\'"), "'")), "::bigint", ")))::varchar;"))
B78: =IF(EXACT([1]DataLookUp!$B78, ""), "", [1]DataLookUp!$B78) -> 95000000000060 | C78: =IF(EXACT(B78, ""), "", [1]DataLookUp!$C78) -> Tools And Asset Manager | D78: 252000000000014 | E78: =IF(EXACT(D78, ""), "", VLOOKUP(D78, [2]DataLookUp!$B$4:$C$32, 2, FALSE)) -> Department - Tools & Asset Management | G78: =G77 + IF(EXACT(H78, ""), 0, 1) -> 253000000000060 | H78: =IF(AND(EXACT(B78, ""), EXACT(D78, "")), "", CONCATENATE("PERFORM ""SchSysConfig"".""Func_TblAppObject_UserRole_SET""(varSystemLoginSession, null::bigint, null::varchar, null::timestamptz, null::timestamptz, null::varchar, varInstitutionBranchID, varBaseCurrencyID, ", (IF(EXACT(B78, ""), "NULL", CONCATENATE("'", B78, "'"))),"::varchar);")) -> PERFORM "SchSysConfig"."Func_TblAppObject_UserRole_SET"(varSystemLoginSession, null::bigint, null::varchar, null::timestamptz, null::timestamptz, null::varchar, varInstitutionBranchID, varBaseCurrencyID, '95000000000060'::varchar); | J78: =IF(EXACT($H78, ""), "", CONCATENATE( "varSQL := varSQL || (CASE WHEN (varSQL = '') THEN '' ELSE ', ' END) || (SELECT JSON_BUILD_OBJECT (", "'recordID', NULL::bigint,", "'entities', ", "JSON_BUILD_OBJECT (", "'sysLoginSession_RefID', varSystemLoginSession::bigint,", "'sysDataAnnotation', NULL::varchar,", "'sysDataSetDateTimeTZ', NULL::timestamptz,", "'sysDataValidityStartDateTimeTZ', NULL::timestamptz,", "'sysDataValidityFinishDateTimeTZ', NULL::timestamptz,", "'sysPartitionRemovableRecordKey_RefID', NULL::bigint,", "'sysBranch_RefID', varInstitutionBranchID::bigint,", "'sysBaseCurrency_RefID',varBaseCurrencyID::bigint,", "'userRoleGroup_RefID', ", IF(EXACT($D78, ""), "null", CONCATENATE("'", SUBSTITUTE($D78, "'", "\'"), "'")), "::bigint, ", "'userRole_RefID', ", IF(EXACT($B78, ""), "null", CONCATENATE("'", SUBSTITUTE($B78, "'", "\'"), "'")), "::bigint", ")))::varchar;")) -> varSQL := varSQL || (CASE WHEN (varSQL = '') THEN '' ELSE ', ' END) || (SELECT JSON_BUILD_OBJECT ('recordID', NULL::bigint,'entities', JSON_BUILD_OBJECT ('sysLoginSession_RefID', varSystemLoginSession::bigint,'sysDataAnnotation', NULL::varchar,'sysDataSetDateTimeTZ', NULL::timestamptz,'sysDataValidityStartDateTimeTZ', NULL::timestamptz,'sysDataValidityFinishDateTimeTZ', NULL::timestamptz,'sysPartitionRemovableRecordKey_RefID', NULL::bigint,'sysBranch_RefID', varInstitutionBranchID::bigint,'sysBaseCurrency_RefID',varBaseCurrencyID::bigint,'userRoleGroup_RefID', '252000000000014'::bigint, 'userRole_RefID', '95000000000060'::bigint)))::varchar;
B79: =IF(EXACT([1]DataLookUp!$B79, ""), "", [1]DataLookUp!$B79) -> 95000000000061 | C79: =IF(EXACT(B79, ""), "", [1]DataLookUp!$C79) -> Tools And Asset Coordinator | D79: 252000000000014 | E79: =IF(EXACT(D79, ""), "", VLOOKUP(D79, [2]DataLookUp!$B$4:$C$32, 2, FALSE)) -> Department - Tools & Asset Management | G79: =G78 + IF(EXACT(H79, ""), 0, 1) -> 253000000000061 | H79: =IF(AND(EXACT(B79, ""), EXACT(D79, "")), "", CONCATENATE("PERFORM ""SchSysConfig"".""Func_TblAppObject_UserRole_SET""(varSystemLoginSession, null::bigint, null::varchar, null::timestamptz, null::timestamptz, null::varchar, varInstitutionBranchID, varBaseCurrencyID, ", (IF(EXACT(B79, ""), "NULL", CONCATENATE("'", B79, "'"))),"::varchar);")) -> PERFORM "SchSysConfig"."Func_TblAppObject_UserRole_SET"(varSystemLoginSession, null::bigint, null::varchar, null::timestamptz, null::timestamptz, null::varchar, varInstitutionBranchID, varBaseCurrencyID, '95000000000061'::varchar); | J79: =IF(EXACT($H79, ""), "", CONCATENATE( "varSQL := varSQL || (CASE WHEN (varSQL = '') THEN '' ELSE ', ' END) || (SELECT JSON_BUILD_OBJECT (", "'recordID', NULL::bigint,", "'entities', ", "JSON_BUILD_OBJECT (", "'sysLoginSession_RefID', varSystemLoginSession::bigint,", "'sysDataAnnotation', NULL::varchar,", "'sysDataSetDateTimeTZ', NULL::timestamptz,", "'sysDataValidityStartDateTimeTZ', NULL::timestamptz,", "'sysDataValidityFinishDateTimeTZ', NULL::timestamptz,", "'sysPartitionRemovableRecordKey_RefID', NULL::bigint,", "'sysBranch_RefID', varInstitutionBranchID::bigint,", "'sysBaseCurrency_RefID',varBaseCurrencyID::bigint,", "'userRoleGroup_RefID', ", IF(EXACT($D79, ""), "null", CONCATENATE("'", SUBSTITUTE($D79, "'", "\'"), "'")), "::bigint, ", "'userRole_RefID', ", IF(EXACT($B79, ""), "null", CONCATENATE("'", SUBSTITUTE($B79, "'", "\'"), "'")), "::bigint", ")))::varchar;")) -> varSQL := varSQL || (CASE WHEN (varSQL = '') THEN '' ELSE ', ' END) || (SELECT JSON_BUILD_OBJECT ('recordID', NULL::bigint,'entities', JSON_BUILD_OBJECT ('sysLoginSession_RefID', varSystemLoginSession::bigint,'sysDataAnnotation', NULL::varchar,'sysDataSetDateTimeTZ', NULL::timestamptz,'sysDataValidityStartDateTimeTZ', NULL::timestamptz,'sysDataValidityFinishDateTimeTZ', NULL::timestamptz,'sysPartitionRemovableRecordKey_RefID', NULL::bigint,'sysBranch_RefID', varInstitutionBranchID::bigint,'sysBaseCurrency_RefID',varBaseCurrencyID::bigint,'userRoleGroup_RefID', '252000000000014'::bigint, 'userRole_RefID', '95000000000061'::bigint)))::varchar;
B80: =IF(EXACT([1]DataLookUp!$B80, ""), "", [1]DataLookUp!$B80) -> 95000000000062 | C80: =IF(EXACT(B80, ""), "", [1]DataLookUp!$C80) -> Tools And Asset Staff | D80: 252000000000014 | E80: =IF(EXACT(D80, ""), "", VLOOKUP(D80, [2]DataLookUp!$B$4:$C$32, 2, FALSE)) -> Department - Tools & Asset Management | G80: =G79 + IF(EXACT(H80, ""), 0, 1) -> 253000000000062 | H80: =IF(AND(EXACT(B80, ""), EXACT(D80, "")), "", CONCATENATE("PERFORM ""SchSysConfig"".""Func_TblAppObject_UserRole_SET""(varSystemLoginSession, null::bigint, null::varchar, null::timestamptz, null::timestamptz, null::varchar, varInstitutionBranchID, varBaseCurrencyID, ", (IF(EXACT(B80, ""), "NULL", CONCATENATE("'", B80, "'"))),"::varchar);")) -> PERFORM "SchSysConfig"."Func_TblAppObject_UserRole_SET"(varSystemLoginSession, null::bigint, null::varchar, null::timestamptz, null::timestamptz, null::varchar, varInstitutionBranchID, varBaseCurrencyID, '95000000000062'::varchar); | J80: =IF(EXACT($H80, ""), "", CONCATENATE( "varSQL := varSQL || (CASE WHEN (varSQL = '') THEN '' ELSE ', ' END) || (SELECT JSON_BUILD_OBJECT (", "'recordID', NULL::bigint,", "'entities', ", "JSON_BUILD_OBJECT (", "'sysLoginSession_RefID', varSystemLoginSession::bigint,", "'sysDataAnnotation', NULL::varchar,", "'sysDataSetDateTimeTZ', NULL::timestamptz,", "'sysDataValidityStartDateTimeTZ', NULL::timestamptz,", "'sysDataValidityFinishDateTimeTZ', NULL::timestamptz,", "'sysPartitionRemovableRecordKey_RefID', NULL::bigint,", "'sysBranch_RefID', varInstitutionBranchID::bigint,", "'sysBaseCurrency_RefID',varBaseCurrencyID::bigint,", "'userRoleGroup_RefID', ", IF(EXACT($D80, ""), "null", CONCATENATE("'", SUBSTITUTE($D80, "'", "\'"), "'")), "::bigint, ", "'userRole_RefID', ", IF(EXACT($B80, ""), "null", CONCATENATE("'", SUBSTITUTE($B80, "'", "\'"), "'")), "::bigint", ")))::varchar;")) -> varSQL := varSQL || (CASE WHEN (varSQL = '') THEN '' ELSE ', ' END) || (SELECT JSON_BUILD_OBJECT ('recordID', NULL::bigint,'entities', JSON_BUILD_OBJECT ('sysLoginSession_RefID', varSystemLoginSession::bigint,'sysDataAnnotation', NULL::varchar,'sysDataSetDateTimeTZ', NULL::timestamptz,'sysDataValidityStartDateTimeTZ', NULL::timestamptz,'sysDataValidityFinishDateTimeTZ', NULL::timestamptz,'sysPartitionRemovableRecordKey_RefID', NULL::bigint,'sysBranch_RefID', varInstitutionBranchID::bigint,'sysBaseCurrency_RefID',varBaseCurrencyID::bigint,'userRoleGroup_RefID', '252000000000014'::bigint, 'userRole_RefID', '95000000000062'::bigint)))::varchar;
B81: =IF(EXACT([1]DataLookUp!$B81, ""), "", [1]DataLookUp!$B81) | C81: =IF(EXACT(B81, ""), "", [1]DataLookUp!$C81) | E81: =IF(EXACT(D81, ""), "", VLOOKUP(D81, [2]DataLookUp!$B$4:$C$32, 2, FALSE)) | G81: =G80 + IF(EXACT(H81, ""), 0, 1) -> 253000000000062 | H81: =IF(AND(EXACT(B81, ""), EXACT(D81, "")), "", CONCATENATE("PERFORM ""SchSysConfig"".""Func_TblAppObject_UserRole_SET""(varSystemLoginSession, null::bigint, null::varchar, null::timestamptz, null::timestamptz, null::varchar, varInstitutionBranchID, varBaseCurrencyID, ", (IF(EXACT(B81, ""), "NULL", CONCATENATE("'", B81, "'"))),"::varchar);")) | J81: =IF(EXACT($H81, ""), "", CONCATENATE( "varSQL := varSQL || (CASE WHEN (varSQL = '') THEN '' ELSE ', ' END) || (SELECT JSON_BUILD_OBJECT (", "'recordID', NULL::bigint,", "'entities', ", "JSON_BUILD_OBJECT (", "'sysLoginSession_RefID', varSystemLoginSession::bigint,", "'sysDataAnnotation', NULL::varchar,", "'sysDataSetDateTimeTZ', NULL::timestamptz,", "'sysDataValidityStartDateTimeTZ', NULL::timestamptz,", "'sysDataValidityFinishDateTimeTZ', NULL::timestamptz,", "'sysPartitionRemovableRecordKey_RefID', NULL::bigint,", "'sysBranch_RefID', varInstitutionBranchID::bigint,", "'sysBaseCurrency_RefID',varBaseCurrencyID::bigint,", "'userRoleGroup_RefID', ", IF(EXACT($D81, ""), "null", CONCATENATE("'", SUBSTITUTE($D81, "'", "\'"), "'")), "::bigint, ", "'userRole_RefID', ", IF(EXACT($B81, ""), "null", CONCATENATE("'", SUBSTITUTE($B81, "'", "\'"), "'")), "::bigint", ")))::varchar;"))
B82: =IF(EXACT([1]DataLookUp!$B82, ""), "", [1]DataLookUp!$B82) -> 95000000000063 | C82: =IF(EXACT(B82, ""), "", [1]DataLookUp!$C82) -> Engineering Manager | D82: 252000000000017 | E82: =IF(EXACT(D82, ""), "", VLOOKUP(D82, [2]DataLookUp!$B$4:$C$32, 2, FALSE)) -> Department - Civil And Mechanical Engineering | G82: =G81 + IF(EXACT(H82, ""), 0, 1) -> 253000000000063 | H82: =IF(AND(EXACT(B82, ""), EXACT(D82, "")), "", CONCATENATE("PERFORM ""SchSysConfig"".""Func_TblAppObject_UserRole_SET""(varSystemLoginSession, null::bigint, null::varchar, null::timestamptz, null::timestamptz, null::varchar, varInstitutionBranchID, varBaseCurrencyID, ", (IF(EXACT(B82, ""), "NULL", CONCATENATE("'", B82, "'"))),"::varchar);")) -> PERFORM "SchSysConfig"."Func_TblAppObject_UserRole_SET"(varSystemLoginSession, null::bigint, null::varchar, null::timestamptz, null::timestamptz, null::varchar, varInstitutionBranchID, varBaseCurrencyID, '95000000000063'::varchar); | J82: =IF(EXACT($H82, ""), "", CONCATENATE( "varSQL := varSQL || (CASE WHEN (varSQL = '') THEN '' ELSE ', ' END) || (SELECT JSON_BUILD_OBJECT (", "'recordID', NULL::bigint,", "'entities', ", "JSON_BUILD_OBJECT (", "'sysLoginSession_RefID', varSystemLoginSession::bigint,", "'sysDataAnnotation', NULL::varchar,", "'sysDataSetDateTimeTZ', NULL::timestamptz,", "'sysDataValidityStartDateTimeTZ', NULL::timestamptz,", "'sysDataValidityFinishDateTimeTZ', NULL::timestamptz,", "'sysPartitionRemovableRecordKey_RefID', NULL::bigint,", "'sysBranch_RefID', varInstitutionBranchID::bigint,", "'sysBaseCurrency_RefID',varBaseCurrencyID::bigint,", "'userRoleGroup_RefID', ", IF(EXACT($D82, ""), "null", CONCATENATE("'", SUBSTITUTE($D82, "'", "\'"), "'")), "::bigint, ", "'userRole_RefID', ", IF(EXACT($B82, ""), "null", CONCATENATE("'", SUBSTITUTE($B82, "'", "\'"), "'")), "::bigint", ")))::varchar;")) -> varSQL := varSQL || (CASE WHEN (varSQL = '') THEN '' ELSE ', ' END) || (SELECT JSON_BUILD_OBJECT ('recordID', NULL::bigint,'entities', JSON_BUILD_OBJECT ('sysLoginSession_RefID', varSystemLoginSession::bigint,'sysDataAnnotation', NULL::varchar,'sysDataSetDateTimeTZ', NULL::timestamptz,'sysDataValidityStartDateTimeTZ', NULL::timestamptz,'sysDataValidityFinishDateTimeTZ', NULL::timestamptz,'sysPartitionRemovableRecordKey_RefID', NULL::bigint,'sysBranch_RefID', varInstitutionBranchID::bigint,'sysBaseCurrency_RefID',varBaseCurrencyID::bigint,'userRoleGroup_RefID', '252000000000017'::bigint, 'userRole_RefID', '95000000000063'::bigint)))::varchar;
B83: =IF(EXACT([1]DataLookUp!$B83, ""), "", [1]DataLookUp!$B83) -> 95000000000064 | C83: =IF(EXACT(B83, ""), "", [1]DataLookUp!$C83) -> Engineering Coordinator | D83: 252000000000017 | E83: =IF(EXACT(D83, ""), "", VLOOKUP(D83, [2]DataLookUp!$B$4:$C$32, 2, FALSE)) -> Department - Civil And Mechanical Engineering | G83: =G82 + IF(EXACT(H83, ""), 0, 1) -> 253000000000064 | H83: =IF(AND(EXACT(B83, ""), EXACT(D83, "")), "", CONCATENATE("PERFORM ""SchSysConfig"".""Func_TblAppObject_UserRole_SET""(varSystemLoginSession, null::bigint, null::varchar, null::timestamptz, null::timestamptz, null::varchar, varInstitutionBranchID, varBaseCurrencyID, ", (IF(EXACT(B83, ""), "NULL", CONCATENATE("'", B83, "'"))),"::varchar);")) -> PERFORM "SchSysConfig"."Func_TblAppObject_UserRole_SET"(varSystemLoginSession, null::bigint, null::varchar, null::timestamptz, null::timestamptz, null::varchar, varInstitutionBranchID, varBaseCurrencyID, '95000000000064'::varchar); | J83: =IF(EXACT($H83, ""), "", CONCATENATE( "varSQL := varSQL || (CASE WHEN (varSQL = '') THEN '' ELSE ', ' END) || (SELECT JSON_BUILD_OBJECT (", "'recordID', NULL::bigint,", "'entities', ", "JSON_BUILD_OBJECT (", "'sysLoginSession_RefID', varSystemLoginSession::bigint,", "'sysDataAnnotation', NULL::varchar,", "'sysDataSetDateTimeTZ', NULL::timestamptz,", "'sysDataValidityStartDateTimeTZ', NULL::timestamptz,", "'sysDataValidityFinishDateTimeTZ', NULL::timestamptz,", "'sysPartitionRemovableRecordKey_RefID', NULL::bigint,", "'sysBranch_RefID', varInstitutionBranchID::bigint,", "'sysBaseCurrency_RefID',varBaseCurrencyID::bigint,", "'userRoleGroup_RefID', ", IF(EXACT($D83, ""), "null", CONCATENATE("'", SUBSTITUTE($D83, "'", "\'"), "'")), "::bigint, ", "'userRole_RefID', ", IF(EXACT($B83, ""), "null", CONCATENATE("'", SUBSTITUTE($B83, "'", "\'"), "'")), "::bigint", ")))::varchar;")) -> varSQL := varSQL || (CASE WHEN (varSQL = '') THEN '' ELSE ', ' END) || (SELECT JSON_BUILD_OBJECT ('recordID', NULL::bigint,'entities', JSON_BUILD_OBJECT ('sysLoginSession_RefID', varSystemLoginSession::bigint,'sysDataAnnotation', NULL::varchar,'sysDataSetDateTimeTZ', NULL::timestamptz,'sysDataValidityStartDateTimeTZ', NULL::timestamptz,'sysDataValidityFinishDateTimeTZ', NULL::timestamptz,'sysPartitionRemovableRecordKey_RefID', NULL::bigint,'sysBranch_RefID', varInstitutionBranchID::bigint,'sysBaseCurrency_RefID',varBaseCurrencyID::bigint,'userRoleGroup_RefID', '252000000000017'::bigint, 'userRole_RefID', '95000000000064'::bigint)))::varchar;
B84: =IF(EXACT([1]DataLookUp!$B84, ""), "", [1]DataLookUp!$B84) -> 95000000000065 | C84: =IF(EXACT(B84, ""), "", [1]DataLookUp!$C84) -> Engineering Staff | D84: 252000000000017 | E84: =IF(EXACT(D84, ""), "", VLOOKUP(D84, [2]DataLookUp!$B$4:$C$32, 2, FALSE)) -> Department - Civil And Mechanical Engineering | G84: =G83 + IF(EXACT(H84, ""), 0, 1) -> 253000000000065 | H84: =IF(AND(EXACT(B84, ""), EXACT(D84, "")), "", CONCATENATE("PERFORM ""SchSysConfig"".""Func_TblAppObject_UserRole_SET""(varSystemLoginSession, null::bigint, null::varchar, null::timestamptz, null::timestamptz, null::varchar, varInstitutionBranchID, varBaseCurrencyID, ", (IF(EXACT(B84, ""), "NULL", CONCATENATE("'", B84, "'"))),"::varchar);")) -> PERFORM "SchSysConfig"."Func_TblAppObject_UserRole_SET"(varSystemLoginSession, null::bigint, null::varchar, null::timestamptz, null::timestamptz, null::varchar, varInstitutionBranchID, varBaseCurrencyID, '95000000000065'::varchar); | J84: =IF(EXACT($H84, ""), "", CONCATENATE( "varSQL := varSQL || (CASE WHEN (varSQL = '') THEN '' ELSE ', ' END) || (SELECT JSON_BUILD_OBJECT (", "'recordID', NULL::bigint,", "'entities', ", "JSON_BUILD_OBJECT (", "'sysLoginSession_RefID', varSystemLoginSession::bigint,", "'sysDataAnnotation', NULL::varchar,", "'sysDataSetDateTimeTZ', NULL::timestamptz,", "'sysDataValidityStartDateTimeTZ', NULL::timestamptz,", "'sysDataValidityFinishDateTimeTZ', NULL::timestamptz,", "'sysPartitionRemovableRecordKey_RefID', NULL::bigint,", "'sysBranch_RefID', varInstitutionBranchID::bigint,", "'sysBaseCurrency_RefID',varBaseCurrencyID::bigint,", "'userRoleGroup_RefID', ", IF(EXACT($D84, ""), "null", CONCATENATE("'", SUBSTITUTE($D84, "'", "\'"), "'")), "::bigint, ", "'userRole_RefID', ", IF(EXACT($B84, ""), "null", CONCATENATE("'", SUBSTITUTE($B84, "'", "\'"), "'")), "::bigint", ")))::varchar;")) -> varSQL := varSQL || (CASE WHEN (varSQL = '') THEN '' ELSE ', ' END) || (SELECT JSON_BUILD_OBJECT ('recordID', NULL::bigint,'entities', JSON_BUILD_OBJECT ('sysLoginSession_RefID', varSystemLoginSession::bigint,'sysDataAnnotation', NULL::varchar,'sysDataSetDateTimeTZ', NULL::timestamptz,'sysDataValidityStartDateTimeTZ', NULL::timestamptz,'sysDataValidityFinishDateTimeTZ', NULL::timestamptz,'sysPartitionRemovableRecordKey_RefID', NULL::bigint,'sysBranch_RefID', varInstitutionBranchID::bigint,'sysBaseCurrency_RefID',varBaseCurrencyID::bigint,'userRoleGroup_RefID', '252000000000017'::bigint, 'userRole_RefID', '95000000000065'::bigint)))::varchar;

Sheet DataLookUp
B2: Sys_PID | C2: =MAIN!B2 -> User Role RefID
B4: =IF(AND(EXACT(MAIN!$B4, ""), EXACT(MAIN!$E4, "")), "", MAIN!$G4) -> 253000000000001 | C4: =IF(EXACT(B4, ""), "", IF(EXACT(MAIN!B4, ""), IF(EXACT(MAIN!D4, ""), "", CONCATENATE("Department - ", MAIN!E4)), MAIN!B4)) -> 95000000000001
B5: =IF(AND(EXACT(MAIN!$B5, ""), EXACT(MAIN!$E5, "")), "", MAIN!$G5) -> 253000000000002 | C5: =IF(EXACT(B5, ""), "", IF(EXACT(MAIN!B5, ""), IF(EXACT(MAIN!D5, ""), "", CONCATENATE("Department - ", MAIN!E5)), MAIN!B5)) -> 95000000000002
B6: =IF(AND(EXACT(MAIN!$B6, ""), EXACT(MAIN!$E6, "")), "", MAIN!$G6) | C6: =IF(EXACT(B6, ""), "", IF(EXACT(MAIN!B6, ""), IF(EXACT(MAIN!D6, ""), "", CONCATENATE("Department - ", MAIN!E6)), MAIN!B6))
B7: =IF(AND(EXACT(MAIN!$B7, ""), EXACT(MAIN!$E7, "")), "", MAIN!$G7) -> 253000000000003 | C7: =IF(EXACT(B7, ""), "", IF(EXACT(MAIN!B7, ""), IF(EXACT(MAIN!D7, ""), "", CONCATENATE("Department - ", MAIN!E7)), MAIN!B7)) -> 95000000000003
B8: =IF(AND(EXACT(MAIN!$B8, ""), EXACT(MAIN!$E8, "")), "", MAIN!$G8) | C8: =IF(EXACT(B8, ""), "", IF(EXACT(MAIN!B8, ""), IF(EXACT(MAIN!D8, ""), "", CONCATENATE("Department - ", MAIN!E8)), MAIN!B8))
B9: =IF(AND(EXACT(MAIN!$B9, ""), EXACT(MAIN!$E9, "")), "", MAIN!$G9) -> 253000000000004 | C9: =IF(EXACT(B9, ""), "", IF(EXACT(MAIN!B9, ""), IF(EXACT(MAIN!D9, ""), "", CONCATENATE("Department - ", MAIN!E9)), MAIN!B9)) -> 95000000000004
B10: =IF(AND(EXACT(MAIN!$B10, ""), EXACT(MAIN!$E10, "")), "", MAIN!$G10) -> 253000000000005 | C10: =IF(EXACT(B10, ""), "", IF(EXACT(MAIN!B10, ""), IF(EXACT(MAIN!D10, ""), "", CONCATENATE("Department - ", MAIN!E10)), MAIN!B10)) -> 95000000000005
B11: =IF(AND(EXACT(MAIN!$B11, ""), EXACT(MAIN!$E11, "")), "", MAIN!$G11) -> 253000000000006 | C11: =IF(EXACT(B11, ""), "", IF(EXACT(MAIN!B11, ""), IF(EXACT(MAIN!D11, ""), "", CONCATENATE("Department - ", MAIN!E11)), MAIN!B11)) -> 95000000000006
B12: =IF(AND(EXACT(MAIN!$B12, ""), EXACT(MAIN!$E12, "")), "", MAIN!$G12) -> 253000000000007 | C12: =IF(EXACT(B12, ""), "", IF(EXACT(MAIN!B12, ""), IF(EXACT(MAIN!D12, ""), "", CONCATENATE("Department - ", MAIN!E12)), MAIN!B12)) -> 95000000000007
B13: =IF(AND(EXACT(MAIN!$B13, ""), EXACT(MAIN!$E13, "")), "", MAIN!$G13) | C13: =IF(EXACT(B13, ""), "", IF(EXACT(MAIN!B13, ""), IF(EXACT(MAIN!D13, ""), "", CONCATENATE("Department - ", MAIN!E13)), MAIN!B13))
B14: =IF(AND(EXACT(MAIN!$B14, ""), EXACT(MAIN!$E14, "")), "", MAIN!$G14) -> 253000000000008 | C14: =IF(EXACT(B14, ""), "", IF(EXACT(MAIN!B14, ""), IF(EXACT(MAIN!D14, ""), "", CONCATENATE("Department - ", MAIN!E14)), MAIN!B14)) -> 95000000000008
B15: =IF(AND(EXACT(MAIN!$B15, ""), EXACT(MAIN!$E15, "")), "", MAIN!$G15) -> 253000000000009 | C15: =IF(EXACT(B15, ""), "", IF(EXACT(MAIN!B15, ""), IF(EXACT(MAIN!D15, ""), "", CONCATENATE("Department - ", MAIN!E15)), MAIN!B15)) -> 95000000000009
... B32: =IF(AND(EXACT(MAIN!$B32, ""), EXACT(MAIN!$E32, "")), "", MAIN!$G32) -> 253000000000024 | C32: =IF(EXACT(B32, ""), "", IF(EXACT(MAIN!B32, ""), IF(EXACT(MAIN!D32, ""), "", CONCATENATE("Department - ", MAIN!E32)), MAIN!B32)) -> 95000000000024
